Workbook

Sheet Variables
A1: Variable | B1: Description | C1: Time Frame | D1: Time Unit | E1: Links
A2: S&P 500 Index | B2: A stock market index that may influence investment decisions and consumer confidence, impacting gasoline demand. | C2: 2016 - 2026 | D2: Daily except weekends | E2: S&P 500® | S&P Dow Jones Indices (spglobal.com)
A3: Weekly Jobless Claims | B3: A measure of unemployment trends, which can affect consumer spending on gasoline. | C3: 1967 - 2026 | D3: Weekly | E3: Initial Claims (ICSA) | FRED | St. Louis Fed (stlouisfed.org)
A4: TSA Passenger Throughput | B4: Indicates air travel activity and its impact on airport gasoline sales. | C4: 2019 - 2026 | D4: Daily | E4: Travel Passenger Throughputs
A5: US Spot Market Prices of Crude Oil | B5: The cost of crude oil in the United States, influencing gasoline production costs and prices. | C5: 1986 - 2026 | D5: Weekly | E5: Weekly Cushing, OK WTI Spot Price FOB (Dollars per Barrel) (eia.gov)
A6: Europe Spot Market Prices of Crude Oil | B6: Crude oil prices in Europe, affecting international oil markets and gasoline pricing. | C6: 1987 - 2026 | D6: Weekly | E6: Weekly Europe Brent Spot Price FOB (Dollars per Barrel) (eia.gov)
A7: Regular (87 Octane) Gasoline Prices | B7: The cost of regular gasoline, a key factor in consumer gasoline purchasing decisions. | C7: 1990 - 2026 | D7: Weekly | E7: Weekly U.S. Regular All Formulations Retail Gasoline Prices (Dollars per Gallon) (eia.gov)
A8: USA GDP | B8: The overall economic output of the United States, influencing gasoline consumption patterns. | C8: 1947 - 2026 | D8: Quarterly | E8: Gross Domestic Product (GDP) | FRED | St. Louis Fed (stlouisfed.org)
A9: Public Transport Ridership | B9: Trends in the use of public transportation, which can affect gasoline demand. | C9: 1990 - 2026 | D9: Quarterly | E9: Ridership Data Archives - APTA
A10: Rig Count | B10: The number of active drilling rigs, providing insight into future oil and gasoline supply. | C10: 1973 - 2026 | D10: Monthly | E10: U.S. Crude Oil and Natural Gas Drilling Activity
A11: Automobile Sales | B11: Sales of vehicles, impacting gasoline consumption through vehicle ownership. | C11: 1976 - 2026 | D11: Monthly | E11: Total Vehicle Sales (TOTALSA) | FRED | St. Louis Fed (stlouisfed.org)
A12: Highway Traffic Data | B12: Data on road traffic and congestion levels, influencing gasoline usage patterns. | C12: 2002 - 2026 | D12: Monthly | E12: Office of Highway Policy Information - Policy | Federal Highway Administration (dot.gov)
... A29: US Population-Weighted CDD | B29: Weekly sum of cooling degree days weighted across U.S. population to capture real summer heatwaves. | C29: 1991 - 2026 | D29: Weekly (Ending Friday) | E29: https://open-meteo.com/

Sheet Hypotheses
A1: Predictor | B1: Hypothesis | C1: Magnitude | D1: Direction
A2: US Spot Market Prices of Crude Oil | B2: Higher crude prices often deter gasoline consumption due to price elasticity. | C2: High | D2: Negative | F2: Karina's personal hypotheses: you can challenge or disagree.
A3: Regular (87 Octane) Gasoline Prices | B3: Higher gasoline prices generally deter consumption. | C3: High | D3: Negative
A4: EV Sales | B4: Increased EV sales may decrease gasoline demand as more people use electric vehicles. | C4: High | D4: Negative
A5: EV Regulations | B5: Higher EV regulations decrease gasoline demand as fleet companies are forced to transition away from gasoline vehicles. | C5: High | D5: Negative
A6: Highway Traffic Data | B6: Increased highway traffic indicates greater vehicle usage, leading to higher gasoline demand. | C6: High | D6: Positive
A7: S&P 500 Index | B7: Higher stock market performance may indicate a booming economy, leading to increased gasoline demand. | C7: Medium | D7: Positive
A8: Weekly Jobless Claims | B8: Higher jobless claims indicate economic downturns, which may result in decreased gasoline demand. | C8: Medium | D8: Negative
A9: Europe Spot Market Prices of Crude Oil | B9: If European crude prices rise and the US follows, it could deter gasoline demand. | C9: Medium | D9: Negative
A10: USA GDP | B10: Higher GDP indicates a robust economy, potentially driving up gasoline demand. | C10: Medium | D10: Positive
A11: Public Transport Ridership | B11: Increased public transport ridership may lead to decreased gasoline demand. | C11: Medium | D11: Negative
A12: Automobile Sales | B12: Higher sales, especially of gasoline-based vehicles, indicate potential increased gasoline demand. | C12: Medium | D12: Positive
A13: Personal Consumption Expenditures | B13: Higher consumer spending can suggest increased economic activity and gasoline demand. | C13: Medium | D13: Positive
A14: Refinery Utilization | B14: Higher refinery utilization can lead to increased gasoline supply, potentially affecting demand balance. | C14: Medium | D14: Positive
... A16: Inflation Expectations | B16: Higher inflation expectations could deter spending, potentially reducing gasoline demand. | C16: Medium | D16: Negative
A17: Employee Earnings | B17: Higher earnings boost disposable income, possibly increasing gasoline demand due to increased travel. | C17: Medium | D17: Positive | O17: -
A18: TSA Passenger Throughput | B18: An increase in passenger throughput may indicate higher air travel, potentially reducing gasoline demand. | C18: Low | D18: Negative
A19: Rig Count | B19: A higher rig count suggests increased domestic production, potentially influencing gasoline demand. | C19: Low | D19: Positive
A20: Consumer Credit Data | B20: Higher consumer credit indicates more spending, including on vehicles and travel, potentially driving gasoline demand. | C20: Low | D20: Positive
A21: Household Debt and Credit | B21: Higher household debt may deter spending, including on travel, potentially reducing gasoline demand. | C21: Low | D21: Negative
A22: Labor Costs | B22: Rising labor costs could affect gasoline production costs, potentially affecting gasoline demand. | C22: Low | D22: Negative
A23: Smoking Consumption | B23: Decrease in smoking might indicate health-conscious decisions, including eco-friendly transportation choices. | C23: Low | D23: Negative
A24: Housing Market Expectations | B24: A booming housing market might lead to increased travel, potentially driving up gasoline demand. | C24: Low | D24: Positive
A25: Major Driving Holiday Week | B25: Weeks containing Memorial Day, July 4, Labor Day, Thanksgiving, Christmas, or New Year's Day see a surge in road trips and family travel, which should raise gasoline demand relative to an ordinary week. But Thanksgiving and Christmas weeks also carry days when many people don't commute or run errands at all, so the net effect could go either way depending on which force dominates. | C25: High | D25: Conditional
A26: Work From Home Share | B26: A higher share of work-from-home days should lower gasoline demand, since commuting is a large and regular share of vehicle miles driven and this trip disappears entirely on remote days. This is a structural shift rather than a short-term fluctuation, and expected to matter most in explaining why demand hasn't returned to pre-2020 levels rather than in explaining week-to-week noise. | C26: High | D26: Negative
A27: US Population-Weighted HDD | B27: Severe winter cold and winter storms reduce vehicle miles traveled and suppress gasoline demand. | C27: Medium | D27: Negative
A28: US Population-Weighted CDD | B28: Warmer summer temperatures increase vacation driving trips and air conditioning load. | C28: Medium | D28: Positive

Sheet Simple Linear Regression
A1: SUMMARY OUTPUT
A3: Regression Statistics
A4: Multiple R | B4: 0.59469786
A5: R Square | B5: 0.35366554
A6: Adjusted R Square | B6: 0.35329976
A7: Standard Error | B7: 589.22746
A8: Observations | B8: 1769
A10: ANOVA
B11: df | C11: SS | D11: MS | E11: F | F11: Significance F
A12: Regression | B12: 1 | C12: 3.3568964e+08 | D12: 3.3568964e+08 | E12: 966.87869 | F12: 1.1029353e-169
A13: Residual | B13: 1767 | C13: 6.1348295e+08 | D13: 347188.99
A14: Total | B14: 1768 | C14: 9.4917259e+08
B16: Coefficients | C16: Standard Error | D16: t Stat | E16: P-value | F16: Lower 95% | G16: Upper 95% | H16: Lower 95.0% | I16: Upper 95.0%
A17: Intercept | B17: 7885.3363 | C17: 28.030652 | D17: 281.31119 | E17: 0 | F17: 7830.3596 | G17: 7940.3131 | H17: 7830.3596 | I17: 7940.3131
A18: X Variable 1 | B18: 0.85303708 | C18: 0.027433544 | D18: 31.094673 | E18: 1.1029353e-169 | F18: 0.79923147 | G18: 0.9068427 | H18: 0.79923147 | I18: 0.9068427

Sheet Target
A1: Week # | B1: Date | C1: Demand | D1: sp500_weekly_avg | E1: initial_jobless_claims | F1: tsa_passengers_weekly_avg | G1: wti_spot_usd_per_bbl | H1: brent_spot_usd_per_bbl | I1: regular_gas_usd_per_gal | J1: gdp_saar_bil_usd | K1: transit_unlinked_trips_thous | L1: rotary_rig_count | M1: vehicle_sales_saar_mil | N1: vehicle_miles_mil | O1: pce_saar_bil_usd | P1: consumer_credit_mil_usd | Q1: ev_sales_vehicles | R1: regulated_afv_acquisitions | S1: household_debt_tril_usd | T1: eci_total_comp_index | U1: smoking_adults_pct | V1: refinery_utilization_pct | W1: fed_broad_dollar_index | X1: home_price_expectation_pct | Y1: inflation_expectation_1y_pct | Z1: mean_annual_earnings_thous_usd | AA1: us_population_thous | AB1: wfh_share_paid_days_pct | AC1: major_holiday_week | AD1: hdd_pop_weighted | AE1: cdd_pop_weighted | AG1: Model C | AH1: Simple Linear Regression Model | AI1: forward selection | AJ1: backward selection | AK1: Restricted Model C | AL1: gas*VMT interaction | AM1: M1 Weather + Holiday | AN1: ARIMAX with cdd and hdd | AP1: ARIMAX(1,1,1) + covariates: fit / forecast | AQ1: ARIMAX Xβ (regression part) | AR1: ARIMAX u (level error) | AS1: ARIMAX ε (1-step residual) | AT1: ARIMAX horizon h | AU1: ARIMAX ψ weight | AV1: ARIMAX Σψ² | AW1: ARIMAX 95% lower | AX1: ARIMAX 95% upper
A2: 1 | B2: 33277 | C2: 6621 | E2: 483000 | G2: 21.304 | H2: 20.626 | I2: 1.139 | L2: 1136 | V2: 84.2 | AC2: 0 | AD2: 18.5 | AE2: 0 | AG2: =6753.47943187+0.36116788*I2+0.01252571*N2-22.85359542*V2+0.00407811*AA2-0.00067349*E2 -> 4504.3224 | AH2: =A2*'Simple Linear Regression'!$B$18+'Simple Linear Regression'!$B$17 -> 7886.1894 | AI2: =7491.3971+0.0137554*N2-0.00058829*E2-34.3283*V2+0.30565*L2+54.6031*M2 -> 4664.0286 | AJ2: =7491.3971-0.00058829*E2+0.30565*L2+54.6031*M2+0.0137554*N2-34.3283*V2 -> 4664.0286 | AL2: =2192.59+2373.87*I2+0.0316653*N2-15.7623*V2+0.00202406*AA2-0.000740146*E2-0.00963493*(I2*N2) -> 3211.7518 | AM2: =5205.907083+122.0638992*I2+13.609808*(N2/1000)-1.245906883*AD2+0.7746840854*AE2-134.2474226*AC2-1547.125689*IF(AND(B2>=DATE(2020,3,20),B2<=DATE(2020,6,26)),1,0) -> 5321.8886 | AN2: =IF(ISNUMBER(C3),C3,AN3)-0.8328750492*(AD4-AD3)+3.274150872*(AE4-AE3)+0.7954612886*((IF(ISNUMBER(C3),C3,AN3)-IF(ISNUMBER(C2),C2,AN2))-(-0.8328750492*(AD3-AD2)+3.274150872*(AE3-AE2)))-1.394571582*AO3+0.4181414112*AO2 -> 6381.8139
A3: 2 | B3: 33284 | C3: 6433 | E3: 480000 | G3: 22.116 | H3: 20.436 | I3: 1.106 | L3: 1136 | V3: 84.2 | AC3: 0 | AD3: 145.9 | AE3: 0.7 | AG3: =6753.47943187+0.36116788*I3+0.01252571*N3-22.85359542*V3+0.00407811*AA3-0.00067349*E3 -> 4506.3309 | AH3: =A3*'Simple Linear Regression'!$B$18+'Simple Linear Regression'!$B$17 -> 7887.0424 | AI3: =7491.3971+0.0137554*N3-0.00058829*E3-34.3283*V3+0.30565*L3+54.6031*M3 -> 4665.7934 | AJ3: =7491.3971-0.00058829*E3+0.30565*L3+54.6031*M3+0.0137554*N3-34.3283*V3 -> 4665.7934 | AL3: =2192.59+2373.87*I3+0.0316653*N3-15.7623*V3+0.00202406*AA3-0.000740146*E3-0.00963493*(I3*N3) -> 3135.6345 | AM3: =5205.907083+122.0638992*I3+13.609808*(N3/1000)-1.245906883*AD3+0.7746840854*AE3-134.2474226*AC3-1547.125689*IF(AND(B3>=DATE(2020,3,20),B3<=DATE(2020,6,26)),1,0) -> 5159.6742 | AN3: =IF(ISNUMBER(C4),C4,AN4)-0.8328750492*(AD5-AD4)+3.274150872*(AE5-AE4)+0.7954612886*((IF(ISNUMBER(C4),C4,AN4)-IF(ISNUMBER(C3),C3,AN3))-(-0.8328750492*(AD4-AD3)+3.274150872*(AE4-AE3)))-1.394571582*AO4+0.4181414112*AO3 -> 6669.6002
A4: 3 | B4: 33291 | C4: 6582 | E4: 474000 | G4: 19.38 | H4: 18.126 | I4: 1.078 | L4: 1136 | M4: 11.829 | V4: 84.2 | AC4: 0 | AD4: 130.1 | AE4: 1.5 | AG4: =6753.47943187+0.36116788*I4+0.01252571*N4-22.85359542*V4+0.00407811*AA4-0.00067349*E4 -> 4510.3618 | AH4: =A4*'Simple Linear Regression'!$B$18+'Simple Linear Regression'!$B$17 -> 7887.8955 | AI4: =7491.3971+0.0137554*N4-0.00058829*E4-34.3283*V4+0.30565*L4+54.6031*M4 -> 5315.2232 | AJ4: =7491.3971-0.00058829*E4+0.30565*L4+54.6031*M4+0.0137554*N4-34.3283*V4 -> 5315.2232 | AL4: =2192.59+2373.87*I4+0.0316653*N4-15.7623*V4+0.00202406*AA4-0.000740146*E4-0.00963493*(I4*N4) -> 3073.607 | AM4: =5205.907083+122.0638992*I4+13.609808*(N4/1000)-1.245906883*AD4+0.7746840854*AE4-134.2474226*AC4-1547.125689*IF(AND(B4>=DATE(2020,3,20),B4<=DATE(2020,6,26)),1,0) -> 5176.5615 | AN4: =IF(ISNUMBER(C5),C5,AN5)-0.8328750492*(AD6-AD5)+3.274150872*(AE6-AE5)+0.7954612886*((IF(ISNUMBER(C5),C5,AN5)-IF(ISNUMBER(C4),C4,AN4))-(-0.8328750492*(AD5-AD4)+3.274150872*(AE5-AE4)))-1.394571582*AO5+0.4181414112*AO4 -> 7784.4795
A5: 4 | B5: 33298 | C5: 7224 | E5: 499000 | G5: 18.73 | H5: 18.662 | I5: 1.054 | L5: 1136 | M5: 11.829 | V5: 84.2 | AC5: 0 | AD5: 149.8 | AE5: 0.9 | AG5: =6753.47943187+0.36116788*I5+0.01252571*N5-22.85359542*V5+0.00407811*AA5-0.00067349*E5 -> 4493.5159 | AH5: =A5*'Simple Linear Regression'!$B$18+'Simple Linear Regression'!$B$17 -> 7888.7485 | AI5: =7491.3971+0.0137554*N5-0.00058829*E5-34.3283*V5+0.30565*L5+54.6031*M5 -> 5300.516 | AJ5: =7491.3971-0.00058829*E5+0.30565*L5+54.6031*M5+0.0137554*N5-34.3283*V5 -> 5300.516 | AL5: =2192.59+2373.87*I5+0.0316653*N5-15.7623*V5+0.00202406*AA5-0.000740146*E5-0.00963493*(I5*N5) -> 2998.1305 | AM5: =5205.907083+122.0638992*I5+13.609808*(N5/1000)-1.245906883*AD5+0.7746840854*AE5-134.2474226*AC5-1547.125689*IF(AND(B5>=DATE(2020,3,20),B5<=DATE(2020,6,26)),1,0) -> 5148.6228 | AN5: =IF(ISNUMBER(C6),C6,AN6)-0.8328750492*(AD7-AD6)+3.274150872*(AE7-AE6)+0.7954612886*((IF(ISNUMBER(C6),C6,AN6)-IF(ISNUMBER(C5),C5,AN5))-(-0.8328750492*(AD6-AD5)+3.274150872*(AE6-AE5)))-1.394571582*AO6+0.4181414112*AO5 -> 6535.0658
A6: 5 | B6: 33305 | C6: 6875 | E6: 488000 | G6: 19.856 | H6: 19.77 | I6: 1.025 | L6: 1068 | M6: 11.829 | O6: 3841 | V6: 82.8 | AC6: 0 | AD6: 111.1 | AE6: 1.8 | AG6: =6753.47943187+0.36116788*I6+0.01252571*N6-22.85359542*V6+0.00407811*AA6-0.00067349*E6 -> 4532.9088 | AH6: =A6*'Simple Linear Regression'!$B$18+'Simple Linear Regression'!$B$17 -> 7889.6015 | AI6: =7491.3971+0.0137554*N6-0.00058829*E6-34.3283*V6+0.30565*L6+54.6031*M6 -> 5334.2626 | AJ6: =7491.3971-0.00058829*E6+0.30565*L6+54.6031*M6+0.0137554*N6-34.3283*V6 -> 5334.2626 | AL6: =2192.59+2373.87*I6+0.0316653*N6-15.7623*V6+0.00202406*AA6-0.000740146*E6-0.00963493*(I6*N6) -> 2959.4971 | AM6: =5205.907083+122.0638992*I6+13.609808*(N6/1000)-1.245906883*AD6+0.7746840854*AE6-134.2474226*AC6-1547.125689*IF(AND(B6>=DATE(2020,3,20),B6<=DATE(2020,6,26)),1,0) -> 5193.9968 | AN6: =IF(ISNUMBER(C7),C7,AN7)-0.8328750492*(AD8-AD7)+3.274150872*(AE8-AE7)+0.7954612886*((IF(ISNUMBER(C7),C7,AN7)-IF(ISNUMBER(C6),C6,AN6))-(-0.8328750492*(AD7-AD6)+3.274150872*(AE7-AE6)))-1.394571582*AO7+0.4181414112*AO6 -> 7075.9948
A7: 6 | B7: 33312 | C7: 6947 | E7: 499000 | G7: 19.894 | H7: 19.278 | I7: 1.045 | L7: 1068 | M7: 11.829 | O7: 3841 | V7: 82.8 | AC7: 0 | AD7: 148 | AE7: 0.7 | AG7: =6753.47943187+0.36116788*I7+0.01252571*N7-22.85359542*V7+0.00407811*AA7-0.00067349*E7 -> 4525.5076 | AH7: =A7*'Simple Linear Regression'!$B$18+'Simple Linear Regression'!$B$17 -> 7890.4546 | AI7: =7491.3971+0.0137554*N7-0.00058829*E7-34.3283*V7+0.30565*L7+54.6031*M7 -> 5327.7914 | AJ7: =7491.3971-0.00058829*E7+0.30565*L7+54.6031*M7+0.0137554*N7-34.3283*V7 -> 5327.7914 | AL7: =2192.59+2373.87*I7+0.0316653*N7-15.7623*V7+0.00202406*AA7-0.000740146*E7-0.00963493*(I7*N7) -> 2998.8329 | AM7: =5205.907083+122.0638992*I7+13.609808*(N7/1000)-1.245906883*AD7+0.7746840854*AE7-134.2474226*AC7-1547.125689*IF(AND(B7>=DATE(2020,3,20),B7<=DATE(2020,6,26)),1,0) -> 5149.6119 | AN7: =IF(ISNUMBER(C8),C8,AN8)-0.8328750492*(AD9-AD8)+3.274150872*(AE9-AE8)+0.7954612886*((IF(ISNUMBER(C8),C8,AN8)-IF(ISNUMBER(C7),C7,AN7))-(-0.8328750492*(AD8-AD7)+3.274150872*(AE8-AE7)))-1.394571582*AO8+0.4181414112*AO7 -> 7629.7578
A8: 7 | B8: 33319 | C8: 7328 | E8: 498000 | G8: 20.304 | H8: 18.796 | I8: 1.043 | L8: 1068 | M8: 12.409 | N8: 157889 | O8: 3841 | V8: 82.8 | AC8: 0 | AD8: 104.9 | AE8: 3.3 | AG8: =6753.47943187+0.36116788*I8+0.01252571*N8-22.85359542*V8+0.00407811*AA8-0.00067349*E8 -> 6503.8522 | AH8: =A8*'Simple Linear Regression'!$B$18+'Simple Linear Regression'!$B$17 -> 7891.3076 | AI8: =7491.3971+0.0137554*N8-0.00058829*E8-34.3283*V8+0.30565*L8+54.6031*M8 -> 7531.8759 | AJ8: =7491.3971-0.00058829*E8+0.30565*L8+54.6031*M8+0.0137554*N8-34.3283*V8 -> 7531.8759 | AL8: =2192.59+2373.87*I8+0.0316653*N8-15.7623*V8+0.00202406*AA8-0.000740146*E8-0.00963493*(I8*N8) -> 6407.7646 | AM8: =5205.907083+122.0638992*I8+13.609808*(N8/1000)-1.245906883*AD8+0.7746840854*AE8-134.2474226*AC8-1547.125689*IF(AND(B8>=DATE(2020,3,20),B8<=DATE(2020,6,26)),1,0) -> 7353.9195 | AN8: =IF(ISNUMBER(C9),C9,AN9)-0.8328750492*(AD10-AD9)+3.274150872*(AE10-AE9)+0.7954612886*((IF(ISNUMBER(C9),C9,AN9)-IF(ISNUMBER(C8),C8,AN8))-(-0.8328750492*(AD9-AD8)+3.274150872*(AE9-AE8)))-1.394571582*AO9+0.4181414112*AO8 -> 6286.4885 | AP8: =C8 -> 7328 | AQ8: ='ARIMAX(1,1,1) Model'!$C$6*I8+'ARIMAX(1,1,1) Model'!$C$7*N8/1000+'ARIMAX(1,1,1) Model'!$C$8*AD8+'ARIMAX(1,1,1) Model'!$C$9*AE8+'ARIMAX(1,1,1) Model'!$C$10*AC8+'ARIMAX(1,1,1) Model'!$C$11*IF(AND(B8>='ARIMAX(1,1,1) Model'!$C$25,B8<='ARIMAX(1,1,1) Model'!$C$26),1,0)+'ARIMAX(1,1,1) Model'!$C$12*E8/1000+'ARIMAX(1,1,1) Model'!$C$13*V8+'ARIMAX(1,1,1) Model'!$C$14*A8+'ARIMAX(1,1,1) Model'!$C$15*SIN(2*PI()*A8/'ARIMAX(1,1,1) Model'!$C$24)+'ARIMAX(1,1,1) Model'!$C$16*COS(2*PI()*A8/'ARIMAX(1,1,1) Model'!$C$24)+'ARIMAX(1,1,1) Model'!$C$17*SIN(4*PI()*A8/'ARIMAX(1,1,1) Model'!$C$24)+'ARIMAX(1,1,1) Model'!$C$18*COS(4*PI()*A8/'ARIMAX(1,1,1) Model'!$C$24) -> 840.57554 | AR8: =IF(ISNUMBER(C8),C8,AP8)-AQ8 -> 6487.4245 | AS8: =IF(ISNUMBER(C8),C8-AP8,0) -> 0
A9: 8 | B9: 33326 | C9: 6777 | E9: 509000 | G9: 19.5825 | H9: 18.275 | I9: 1.047 | L9: 1068 | M9: 12.409 | N9: 157889 | O9: 3841 | V9: 82.8 | AC9: 0 | AD9: 79 | AE9: 7.1 | AG9: =6753.47943187+0.36116788*I9+0.01252571*N9-22.85359542*V9+0.00407811*AA9-0.00067349*E9 -> 6496.4453 | AH9: =A9*'Simple Linear Regression'!$B$18+'Simple Linear Regression'!$B$17 -> 7892.1606 | AI9: =7491.3971+0.0137554*N9-0.00058829*E9-34.3283*V9+0.30565*L9+54.6031*M9 -> 7525.4047 | AJ9: =7491.3971-0.00058829*E9+0.30565*L9+54.6031*M9+0.0137554*N9-34.3283*V9 -> 7525.4047 | AL9: =2192.59+2373.87*I9+0.0316653*N9-15.7623*V9+0.00202406*AA9-0.000740146*E9-0.00963493*(I9*N9) -> 6403.0335 | AM9: =5205.907083+122.0638992*I9+13.609808*(N9/1000)-1.245906883*AD9+0.7746840854*AE9-134.2474226*AC9-1547.125689*IF(AND(B9>=DATE(2020,3,20),B9<=DATE(2020,6,26)),1,0) -> 7389.6206 | AN9: =IF(ISNUMBER(C10),C10,AN10)-0.8328750492*(AD11-AD10)+3.274150872*(AE11-AE10)+0.7954612886*((IF(ISNUMBER(C10),C10,AN10)-IF(ISNUMBER(C9),C9,AN9))-(-0.8328750492*(AD10-AD9)+3.274150872*(AE10-AE9)))-1.394571582*AO10+0.4181414112*AO9 -> 8183.7323 | AP9: =AQ9+AR8 -> 7371.8143 | AQ9: ='ARIMAX(1,1,1) Model'!$C$6*I9+'ARIMAX(1,1,1) Model'!$C$7*N9/1000+'ARIMAX(1,1,1) Model'!$C$8*AD9+'ARIMAX(1,1,1) Model'!$C$9*AE9+'ARIMAX(1,1,1) Model'!$C$10*AC9+'ARIMAX(1,1,1) Model'!$C$11*IF(AND(B9>='ARIMAX(1,1,1) Model'!$C$25,B9<='ARIMAX(1,1,1) Model'!$C$26),1,0)+'ARIMAX(1,1,1) Model'!$C$12*E9/1000+'ARIMAX(1,1,1) Model'!$C$13*V9+'ARIMAX(1,1,1) Model'!$C$14*A9+'ARIMAX(1,1,1) Model'!$C$15*SIN(2*PI()*A9/'ARIMAX(1,1,1) Model'!$C$24)+'ARIMAX(1,1,1) Model'!$C$16*COS(2*PI()*A9/'ARIMAX(1,1,1) Model'!$C$24)+'ARIMAX(1,1,1) Model'!$C$17*SIN(4*PI()*A9/'ARIMAX(1,1,1) Model'!$C$24)+'ARIMAX(1,1,1) Model'!$C$18*COS(4*PI()*A9/'ARIMAX(1,1,1) Model'!$C$24) -> 884.38984 | AR9: =IF(ISNUMBER(C9),C9,AP9)-AQ9 -> 5892.6102 | AS9: =IF(ISNUMBER(C9),C9-AP9,0) -> -594.8143
A10: 9 | B10: 33333 | C10: 7503 | E10: 499000 | G10: 19.63 | H10: 17.946 | I10: 1.052 | L10: 984 | M10: 12.409 | N10: 157889 | O10: 3866.7 | V10: 82.8 | AC10: 0 | AD10: 92.3 | AE10: 2.8 | AG10: =6753.47943187+0.36116788*I10+0.01252571*N10-22.85359542*V10+0.00407811*AA10-0.00067349*E10 -> 6503.182 | AH10: =A10*'Simple Linear Regression'!$B$18+'Simple Linear Regression'!$B$17 -> 7893.0137 | AI10: =7491.3971+0.0137554*N10-0.00058829*E10-34.3283*V10+0.30565*L10+54.6031*M10 -> 7505.613 | AJ10: =7491.3971-0.00058829*E10+0.30565*L10+54.6031*M10+0.0137554*N10-34.3283*V10 -> 7505.613 | AL10: =2192.59+2373.87*I10+0.0316653*N10-15.7623*V10+0.00202406*AA10-0.000740146*E10-0.00963493*(I10*N10) -> 6414.6981 | AM10: =5205.907083+122.0638992*I10+13.609808*(N10/1000)-1.245906883*AD10+0.7746840854*AE10-134.2474226*AC10-1547.125689*IF(AND(B10>=DATE(2020,3,20),B10<=DATE(2020,6,26)),1,0) -> 7370.3292 | AN10: =IF(ISNUMBER(C11),C11,AN11)-0.8328750492*(AD12-AD11)+3.274150872*(AE12-AE11)+0.7954612886*((IF(ISNUMBER(C11),C11,AN11)-IF(ISNUMBER(C10),C10,AN10))-(-0.8328750492*(AD11-AD10)+3.274150872*(AE11-AE10)))-1.394571582*AO11+0.4181414112*AO10 -> 6363.5229 | AP10: =AQ10+AR9+'ARIMAX(1,1,1) Model'!$C$19*(AR9-AR8)+'ARIMAX(1,1,1) Model'!$C$20*AS9 -> 7315.4054 | AQ10: ='ARIMAX(1,1,1) Model'!$C$6*I10+'ARIMAX(1,1,1) Model'!$C$7*N10/1000+'ARIMAX(1,1,1) Model'!$C$8*AD10+'ARIMAX(1,1,1) Model'!$C$9*AE10+'ARIMAX(1,1,1) Model'!$C$10*AC10+'ARIMAX(1,1,1) Model'!$C$11*IF(AND(B10>='ARIMAX(1,1,1) Model'!$C$25,B10<='ARIMAX(1,1,1) Model'!$C$26),1,0)+'ARIMAX(1,1,1) Model'!$C$12*E10/1000+'ARIMAX(1,1,1) Model'!$C$13*V10+'ARIMAX(1,1,1) Model'!$C$14*A10+'ARIMAX(1,1,1) Model'!$C$15*SIN(2*PI()*A10/'ARIMAX(1,1,1) Model'!$C$24)+'ARIMAX(1,1,1) Model'!$C$16*COS(2*PI()*A10/'ARIMAX(1,1,1) Model'!$C$24)+'ARIMAX(1,1,1) Model'!$C$17*SIN(4*PI()*A10/'ARIMAX(1,1,1) Model'!$C$24)+'ARIMAX(1,1,1) Model'!$C$18*COS(4*PI()*A10/'ARIMAX(1,1,1) Model'!$C$24) -> 945.42591 | AR10: =IF(ISNUMBER(C10),C10,AP10)-AQ10 -> 6557.5741 | AS10: =IF(ISNUMBER(C10),C10-AP10,0) -> 187.59462
A11: 10 | B11: 33340 | C11: 6916 | E11: 452000 | G11: 20.892 | H11: 19.172 | I11: 1.066 | L11: 984 | M11: 12.409 | N11: 157889 | O11: 3866.7 | V11: 82.5 | AC11: 0 | AD11: 37.2 | AE11: 14.2 | AG11: =6753.47943187+0.36116788*I11+0.01252571*N11-22.85359542*V11+0.00407811*AA11-0.00067349*E11 -> 6541.6972 | AH11: =A11*'Simple Linear Regression'!$B$18+'Simple Linear Regression'!$B$17 -> 7893.8667 | AI11: =7491.3971+0.0137554*N11-0.00058829*E11-34.3283*V11+0.30565*L11+54.6031*M11 -> 7543.5611 | AJ11: =7491.3971-0.00058829*E11+0.30565*L11+54.6031*M11+0.0137554*N11-34.3283*V11 -> 7543.5611 | AL11: =2192.59+2373.87*I11+0.0316653*N11-15.7623*V11+0.00202406*AA11-0.000740146*E11-0.00963493*(I11*N11) -> 6466.1503 | AM11: =5205.907083+122.0638992*I11+13.609808*(N11/1000)-1.245906883*AD11+0.7746840854*AE11-134.2474226*AC11-1547.125689*IF(AND(B11>=DATE(2020,3,20),B11<=DATE(2020,6,26)),1,0) -> 7449.519 | AN11: =IF(ISNUMBER(C12),C12,AN12)-0.8328750492*(AD13-AD12)+3.274150872*(AE13-AE12)+0.7954612886*((IF(ISNUMBER(C12),C12,AN12)-IF(ISNUMBER(C11),C11,AN11))-(-0.8328750492*(AD12-AD11)+3.274150872*(AE12-AE11)))-1.394571582*AO12+0.4181414112*AO11 -> 7145.1994 | AP11: =AQ11+AR10+'ARIMAX(1,1,1) Model'!$C$19*(AR10-AR9)+'ARIMAX(1,1,1) Model'!$C$20*AS10 -> 7481.8839 | AQ11: ='ARIMAX(1,1,1) Model'!$C$6*I11+'ARIMAX(1,1,1) Model'!$C$7*N11/1000+'ARIMAX(1,1,1) Model'!$C$8*AD11+'ARIMAX(1,1,1) Model'!$C$9*AE11+'ARIMAX(1,1,1) Model'!$C$10*AC11+'ARIMAX(1,1,1) Model'!$C$11*IF(AND(B11>='ARIMAX(1,1,1) Model'!$C$25,B11<='ARIMAX(1,1,1) Model'!$C$26),1,0)+'ARIMAX(1,1,1) Model'!$C$12*E11/1000+'ARIMAX(1,1,1) Model'!$C$13*V11+'ARIMAX(1,1,1) Model'!$C$14*A11+'ARIMAX(1,1,1) Model'!$C$15*SIN(2*PI()*A11/'ARIMAX(1,1,1) Model'!$C$24)+'ARIMAX(1,1,1) Model'!$C$16*COS(2*PI()*A11/'ARIMAX(1,1,1) Model'!$C$24)+'ARIMAX(1,1,1) Model'!$C$17*SIN(4*PI()*A11/'ARIMAX(1,1,1) Model'!$C$24)+'ARIMAX(1,1,1) Model'!$C$18*COS(4*PI()*A11/'ARIMAX(1,1,1) Model'!$C$24) -> 1028.3056 | AR11: =IF(ISNUMBER(C11),C11,AP11)-AQ11 -> 5887.6944 | AS11: =IF(ISNUMBER(C11),C11-AP11,0) -> -565.88388
A12: 11 | B12: 33347 | C12: 7045 | E12: 477000 | G12: 21.484 | H12: 19.712 | I12: 1.069 | L12: 984 | M12: 12.848 | N12: 153351 | O12: 3866.7 | V12: 82.5 | AC12: 0 | AD12: 62 | AE12: 14.6 | AG12: =6753.47943187+0.36116788*I12+0.01252571*N12-22.85359542*V12+0.00407811*AA12-0.00067349*E12 -> 6468.0193 | AH12: =A12*'Simple Linear Regression'!$B$18+'Simple Linear Regression'!$B$17 -> 7894.7198 | AI12: =7491.3971+0.0137554*N12-0.00058829*E12-34.3283*V12+0.30565*L12+54.6031*M12 -> 7490.4026 | AJ12: =7491.3971-0.00058829*E12+0.30565*L12+54.6031*M12+0.0137554*N12-34.3283*V12 -> 7490.4026 | AL12: =2192.59+2373.87*I12+0.0316653*N12-15.7623*V12+0.00202406*AA12-0.000740146*E12-0.00963493*(I12*N12) -> 6353.2476 | AM12: =5205.907083+122.0638992*I12+13.609808*(N12/1000)-1.245906883*AD12+0.7746840854*AE12-134.2474226*AC12-1547.125689*IF(AND(B12>=DATE(2020,3,20),B12<=DATE(2020,6,26)),1,0) -> 7357.5352 | AN12: =IF(ISNUMBER(C13),C13,AN13)-0.8328750492*(AD14-AD13)+3.274150872*(AE14-AE13)+0.7954612886*((IF(ISNUMBER(C13),C13,AN13)-IF(ISNUMBER(C12),C12,AN12))-(-0.8328750492*(AD13-AD12)+3.274150872*(AE13-AE12)))-1.394571582*AO13+0.4181414112*AO12 -> 6965.9197 | AP12: =AQ12+AR11+'ARIMAX(1,1,1) Model'!$C$19*(AR11-AR10)+'ARIMAX(1,1,1) Model'!$C$20*AS11 -> 7412.2866 | AQ12: ='ARIMAX(1,1,1) Model'!$C$6*I12+'ARIMAX(1,1,1) Model'!$C$7*N12/1000+'ARIMAX(1,1,1) Model'!$C$8*AD12+'ARIMAX(1,1,1) Model'!$C$9*AE12+'ARIMAX(1,1,1) Model'!$C$10*AC12+'ARIMAX(1,1,1) Model'!$C$11*IF(AND(B12>='ARIMAX(1,1,1) Model'!$C$25,B12<='ARIMAX(1,1,1) Model'!$C$26),1,0)+'ARIMAX(1,1,1) Model'!$C$12*E12/1000+'ARIMAX(1,1,1) Model'!$C$13*V12+'ARIMAX(1,1,1) Model'!$C$14*A12+'ARIMAX(1,1,1) Model'!$C$15*SIN(2*PI()*A12/'ARIMAX(1,1,1) Model'!$C$24)+'ARIMAX(1,1,1) Model'!$C$16*COS(2*PI()*A12/'ARIMAX(1,1,1) Model'!$C$24)+'ARIMAX(1,1,1) Model'!$C$17*SIN(4*PI()*A12/'ARIMAX(1,1,1) Model'!$C$24)+'ARIMAX(1,1,1) Model'!$C$18*COS(4*PI()*A12/'ARIMAX(1,1,1) Model'!$C$24) -> 1080.584 | AR12: =IF(ISNUMBER(C12),C12,AP12)-AQ12 -> 5964.416 | AS12: =IF(ISNUMBER(C12),C12-AP12,0) -> -367.28664
A13: 12 | B13: 33354 | C13: 6956 | E13: 478000 | G13: 21.188 | H13: 19.632 | I13: 1.09 | L13: 984 | M13: 12.848 | N13: 153351 | O13: 3866.7 | V13: 82.5 | AC13: 0 | AD13: 64.9 | AE13: 9.9 | AG13: =6753.47943187+0.36116788*I13+0.01252571*N13-22.85359542*V13+0.00407811*AA13-0.00067349*E13 -> 6467.3534 | AH13: =A13*'Simple Linear Regression'!$B$18+'Simple Linear Regression'!$B$17 -> 7895.5728 | AI13: =7491.3971+0.0137554*N13-0.00058829*E13-34.3283*V13+0.30565*L13+54.6031*M13 -> 7489.8143 | AJ13: =7491.3971-0.00058829*E13+0.30565*L13+54.6031*M13+0.0137554*N13-34.3283*V13 -> 7489.8143 | AL13: =2192.59+2373.87*I13+0.0316653*N13-15.7623*V13+0.00202406*AA13-0.000740146*E13-0.00963493*(I13*N13) -> 6371.3307 | AM13: =5205.907083+122.0638992*I13+13.609808*(N13/1000)-1.245906883*AD13+0.7746840854*AE13-134.2474226*AC13-1547.125689*IF(AND(B13>=DATE(2020,3,20),B13<=DATE(2020,6,26)),1,0) -> 7352.8444 | AN13: =IF(ISNUMBER(C14),C14,AN14)-0.8328750492*(AD15-AD14)+3.274150872*(AE15-AE14)+0.7954612886*((IF(ISNUMBER(C14),C14,AN14)-IF(ISNUMBER(C13),C13,AN13))-(-0.8328750492*(AD14-AD13)+3.274150872*(AE14-AE13)))-1.394571582*AO14+0.4181414112*AO13 -> 6934.3358 | AP13: =AQ13+AR12+'ARIMAX(1,1,1) Model'!$C$19*(AR12-AR11)+'ARIMAX(1,1,1) Model'!$C$20*AS12 -> 7418.0548 | AQ13: ='ARIMAX(1,1,1) Model'!$C$6*I13+'ARIMAX(1,1,1) Model'!$C$7*N13/1000+'ARIMAX(1,1,1) Model'!$C$8*AD13+'ARIMAX(1,1,1) Model'!$C$9*AE13+'ARIMAX(1,1,1) Model'!$C$10*AC13+'ARIMAX(1,1,1) Model'!$C$11*IF(AND(B13>='ARIMAX(1,1,1) Model'!$C$25,B13<='ARIMAX(1,1,1) Model'!$C$26),1,0)+'ARIMAX(1,1,1) Model'!$C$12*E13/1000+'ARIMAX(1,1,1) Model'!$C$13*V13+'ARIMAX(1,1,1) Model'!$C$14*A13+'ARIMAX(1,1,1) Model'!$C$15*SIN(2*PI()*A13/'ARIMAX(1,1,1) Model'!$C$24)+'ARIMAX(1,1,1) Model'!$C$16*COS(2*PI()*A13/'ARIMAX(1,1,1) Model'!$C$24)+'ARIMAX(1,1,1) Model'!$C$17*SIN(4*PI()*A13/'ARIMAX(1,1,1) Model'!$C$24)+'ARIMAX(1,1,1) Model'!$C$18*COS(4*PI()*A13/'ARIMAX(1,1,1) Model'!$C$24) -> 1115.5673 | AR13: =IF(ISNUMBER(C13),C13,AP13)-AQ13 -> 5840.4327 | AS13: =IF(ISNUMBER(C13),C13-AP13,0) -> -462.05481
A14: 13 | B14: 33361 | C14: 6976 | E14: 462000 | G14: 21.234 | H14: 19.72 | I14: 1.104 | L14: 984 | M14: 12.848 | N14: 153351 | O14: 3866.7 | V14: 82.5 | AC14: 0 | AD14: 30.2 | AE14: 21.4 | AG14: =6753.47943187+0.36116788*I14+0.01252571*N14-22.85359542*V14+0.00407811*AA14-0.00067349*E14 -> 6478.1343 | AH14: =A14*'Simple Linear Regression'!$B$18+'Simple Linear Regression'!$B$17 -> 7896.4258 | AI14: =7491.3971+0.0137554*N14-0.00058829*E14-34.3283*V14+0.30565*L14+54.6031*M14 -> 7499.2269 | AJ14: =7491.3971-0.00058829*E14+0.30565*L14+54.6031*M14+0.0137554*N14-34.3283*V14 -> 7499.2269 | AL14: =2192.59+2373.87*I14+0.0316653*N14-15.7623*V14+0.00202406*AA14-0.000740146*E14-0.00963493*(I14*N14) -> 6395.7218 | AM14: =5205.907083+122.0638992*I14+13.609808*(N14/1000)-1.245906883*AD14+0.7746840854*AE14-134.2474226*AC14-1547.125689*IF(AND(B14>=DATE(2020,3,20),B14<=DATE(2020,6,26)),1,0) -> 7406.6951 | AN14: =IF(ISNUMBER(C15),C15,AN15)-0.8328750492*(AD16-AD15)+3.274150872*(AE16-AE15)+0.7954612886*((IF(ISNUMBER(C15),C15,AN15)-IF(ISNUMBER(C14),C14,AN14))-(-0.8328750492*(AD15-AD14)+3.274150872*(AE15-AE14)))-1.394571582*AO15+0.4181414112*AO14 -> 7450.0587 | AP14: =AQ14+AR13+'ARIMAX(1,1,1) Model'!$C$19*(AR13-AR12)+'ARIMAX(1,1,1) Model'!$C$20*AS13 -> 7426.8074 | AQ14: ='ARIMAX(1,1,1) Model'!$C$6*I14+'ARIMAX(1,1,1) Model'!$C$7*N14/1000+'ARIMAX(1,1,1) Model'!$C$8*AD14+'ARIMAX(1,1,1) Model'!$C$9*AE14+'ARIMAX(1,1,1) Model'!$C$10*AC14+'ARIMAX(1,1,1) Model'!$C$11*IF(AND(B14>='ARIMAX(1,1,1) Model'!$C$25,B14<='ARIMAX(1,1,1) Model'!$C$26),1,0)+'ARIMAX(1,1,1) Model'!$C$12*E14/1000+'ARIMAX(1,1,1) Model'!$C$13*V14+'ARIMAX(1,1,1) Model'!$C$14*A14+'ARIMAX(1,1,1) Model'!$C$15*SIN(2*PI()*A14/'ARIMAX(1,1,1) Model'!$C$24)+'ARIMAX(1,1,1) Model'!$C$16*COS(2*PI()*A14/'ARIMAX(1,1,1) Model'!$C$24)+'ARIMAX(1,1,1) Model'!$C$17*SIN(4*PI()*A14/'ARIMAX(1,1,1) Model'!$C$24)+'ARIMAX(1,1,1) Model'!$C$18*COS(4*PI()*A14/'ARIMAX(1,1,1) Model'!$C$24) -> 1182.5791 | AR14: =IF(ISNUMBER(C14),C14,AP14)-AQ14 -> 5793.4209 | AS14: =IF(ISNUMBER(C14),C14-AP14,0) -> -450.80736
A15: 14 | B15: 33368 | C15: 7185 | E15: 451000 | G15: 21.69 | H15: 19.812 | I15: 1.113 | J15: 6035.178 | L15: 929 | M15: 12.848 | N15: 153351 | O15: 3913 | V15: 84.4 | AC15: 0 | AD15: 27.9 | AE15: 19.4 | AG15: =6753.47943187+0.36116788*I15+0.01252571*N15-22.85359542*V15+0.00407811*AA15-0.00067349*E15 -> 6442.1241 | AH15: =A15*'Simple Linear Regression'!$B$18+'Simple Linear Regression'!$B$17 -> 7897.2789 | AI15: =7491.3971+0.0137554*N15-0.00058829*E15-34.3283*V15+0.30565*L15+54.6031*M15 -> 7423.6636 | AJ15: =7491.3971-0.00058829*E15+0.30565*L15+54.6031*M15+0.0137554*N15-34.3283*V15 -> 7423.6636 | AL15: =2192.59+2373.87*I15+0.0316653*N15-15.7623*V15+0.00202406*AA15-0.000740146*E15-0.00963493*(I15*N15) -> 6381.9822 | AM15: =5205.907083+122.0638992*I15+13.609808*(N15/1000)-1.245906883*AD15+0.7746840854*AE15-134.2474226*AC15-1547.125689*IF(AND(B15>=DATE(2020,3,20),B15<=DATE(2020,6,26)),1,0) -> 7409.1099 | AN15: =IF(ISNUMBER(C16),C16,AN16)-0.8328750492*(AD17-AD16)+3.274150872*(AE17-AE16)+0.7954612886*((IF(ISNUMBER(C16),C16,AN16)-IF(ISNUMBER(C15),C15,AN15))-(-0.8328750492*(AD16-AD15)+3.274150872*(AE16-AE15)))-1.394571582*AO16+0.4181414112*AO15 -> 6551.7146 | AP15: =AQ15+AR14+'ARIMAX(1,1,1) Model'!$C$19*(AR14-AR13)+'ARIMAX(1,1,1) Model'!$C$20*AS14 -> 7445.1868 | AQ15: ='ARIMAX(1,1,1) Model'!$C$6*I15+'ARIMAX(1,1,1) Model'!$C$7*N15/1000+'ARIMAX(1,1,1) Model'!$C$8*AD15+'ARIMAX(1,1,1) Model'!$C$9*AE15+'ARIMAX(1,1,1) Model'!$C$10*AC15+'ARIMAX(1,1,1) Model'!$C$11*IF(AND(B15>='ARIMAX(1,1,1) Model'!$C$25,B15<='ARIMAX(1,1,1) Model'!$C$26),1,0)+'ARIMAX(1,1,1) Model'!$C$12*E15/1000+'ARIMAX(1,1,1) Model'!$C$13*V15+'ARIMAX(1,1,1) Model'!$C$14*A15+'ARIMAX(1,1,1) Model'!$C$15*SIN(2*PI()*A15/'ARIMAX(1,1,1) Model'!$C$24)+'ARIMAX(1,1,1) Model'!$C$16*COS(2*PI()*A15/'ARIMAX(1,1,1) Model'!$C$24)+'ARIMAX(1,1,1) Model'!$C$17*SIN(4*PI()*A15/'ARIMAX(1,1,1) Model'!$C$24)+'ARIMAX(1,1,1) Model'!$C$18*COS(4*PI()*A15/'ARIMAX(1,1,1) Model'!$C$24) -> 1250.5868 | AR15: =IF(ISNUMBER(C15),C15,AP15)-AQ15 -> 5934.4132 | AS15: =IF(ISNUMBER(C15),C15-AP15,0) -> -260.1868
A16: 15 | B16: 33375 | C16: 6899 | E16: 446000 | G16: 20.952 | H16: 18.9 | I16: 1.121 | J16: 6035.178 | L16: 929 | M16: 12.038 | N16: 179076 | O16: 3913 | V16: 84.4 | AC16: 0 | AD16: 4.5 | AE16: 42.5 | AG16: =6753.47943187+0.36116788*I16+0.01252571*N16-22.85359542*V16+0.00407811*AA16-0.00067349*E16 -> 6767.7184 | AH16: =A16*'Simple Linear Regression'!$B$18+'Simple Linear Regression'!$B$17 -> 7898.1319 | AI16: =7491.3971+0.0137554*N16-0.00058829*E16-34.3283*V16+0.30565*L16+54.6031*M16 -> 7736.2342 | AJ16: =7491.3971-0.00058829*E16+0.30565*L16+54.6031*M16+0.0137554*N16-34.3283*V16 -> 7736.2342 | AL16: =2192.59+2373.87*I16+0.0316653*N16-15.7623*V16+0.00202406*AA16-0.000740146*E16-0.00963493*(I16*N16) -> 6929.594 | AM16: =5205.907083+122.0638992*I16+13.609808*(N16/1000)-1.245906883*AD16+0.7746840854*AE16-134.2474226*AC16-1547.125689*IF(AND(B16>=DATE(2020,3,20),B16<=DATE(2020,6,26)),1,0) -> 7807.2482 | AN16: =IF(ISNUMBER(C17),C17,AN17)-0.8328750492*(AD18-AD17)+3.274150872*(AE18-AE17)+0.7954612886*((IF(ISNUMBER(C17),C17,AN17)-IF(ISNUMBER(C16),C16,AN16))-(-0.8328750492*(AD17-AD16)+3.274150872*(AE17-AE16)))-1.394571582*AO17+0.4181414112*AO16 -> 7957.9868 | AP16: =AQ16+AR15+'ARIMAX(1,1,1) Model'!$C$19*(AR15-AR14)+'ARIMAX(1,1,1) Model'!$C$20*AS15 -> 7541.1047 | AQ16: ='ARIMAX(1,1,1) Model'!$C$6*I16+'ARIMAX(1,1,1) Model'!$C$7*N16/1000+'ARIMAX(1,1,1) Model'!$C$8*AD16+'ARIMAX(1,1,1) Model'!$C$9*AE16+'ARIMAX(1,1,1) Model'!$C$10*AC16+'ARIMAX(1,1,1) Model'!$C$11*IF(AND(B16>='ARIMAX(1,1,1) Model'!$C$25,B16<='ARIMAX(1,1,1) Model'!$C$26),1,0)+'ARIMAX(1,1,1) Model'!$C$12*E16/1000+'ARIMAX(1,1,1) Model'!$C$13*V16+'ARIMAX(1,1,1) Model'!$C$14*A16+'ARIMAX(1,1,1) Model'!$C$15*SIN(2*PI()*A16/'ARIMAX(1,1,1) Model'!$C$24)+'ARIMAX(1,1,1) Model'!$C$16*COS(2*PI()*A16/'ARIMAX(1,1,1) Model'!$C$24)+'ARIMAX(1,1,1) Model'!$C$17*SIN(4*PI()*A16/'ARIMAX(1,1,1) Model'!$C$24)+'ARIMAX(1,1,1) Model'!$C$18*COS(4*PI()*A16/'ARIMAX(1,1,1) Model'!$C$24) -> 1358.7504 | AR16: =IF(ISNUMBER(C16),C16,AP16)-AQ16 -> 5540.2496 | AS16: =IF(ISNUMBER(C16),C16-AP16,0) -> -642.10473
A17: 16 | B17: 33382 | C17: 7396 | E17: 448000 | G17: 21.036 | H17: 18.824 | I17: 1.129 | J17: 6035.178 | L17: 929 | M17: 12.038 | N17: 179076 | O17: 3913 | V17: 84.4 | AC17: 0 | AD17: 15.8 | AE17: 31.9 | AG17: =6753.47943187+0.36116788*I17+0.01252571*N17-22.85359542*V17+0.00407811*AA17-0.00067349*E17 -> 6766.3743 | AH17: =A17*'Simple Linear Regression'!$B$18+'Simple Linear Regression'!$B$17 -> 7898.9849 | AI17: =7491.3971+0.0137554*N17-0.00058829*E17-34.3283*V17+0.30565*L17+54.6031*M17 -> 7735.0576 | AJ17: =7491.3971-0.00058829*E17+0.30565*L17+54.6031*M17+0.0137554*N17-34.3283*V17 -> 7735.0576 | AL17: =2192.59+2373.87*I17+0.0316653*N17-15.7623*V17+0.00202406*AA17-0.000740146*E17-0.00963493*(I17*N17) -> 6933.3016 | AM17: =5205.907083+122.0638992*I17+13.609808*(N17/1000)-1.245906883*AD17+0.7746840854*AE17-134.2474226*AC17-1547.125689*IF(AND(B17>=DATE(2020,3,20),B17<=DATE(2020,6,26)),1,0) -> 7785.9343 | AN17: =IF(ISNUMBER(C18),C18,AN18)-0.8328750492*(AD19-AD18)+3.274150872*(AE19-AE18)+0.7954612886*((IF(ISNUMBER(C18),C18,AN18)-IF(ISNUMBER(C17),C17,AN17))-(-0.8328750492*(AD18-AD17)+3.274150872*(AE18-AE17)))-1.394571582*AO18+0.4181414112*AO17 -> 7022.6392 | AP17: =AQ17+AR16+'ARIMAX(1,1,1) Model'!$C$19*(AR16-AR15)+'ARIMAX(1,1,1) Model'!$C$20*AS16 -> 7432.5921 | AQ17: ='ARIMAX(1,1,1) Model'!$C$6*I17+'ARIMAX(1,1,1) Model'!$C$7*N17/1000+'ARIMAX(1,1,1) Model'!$C$8*AD17+'ARIMAX(1,1,1) Model'!$C$9*AE17+'ARIMAX(1,1,1) Model'!$C$10*AC17+'ARIMAX(1,1,1) Model'!$C$11*IF(AND(B17>='ARIMAX(1,1,1) Model'!$C$25,B17<='ARIMAX(1,1,1) Model'!$C$26),1,0)+'ARIMAX(1,1,1) Model'!$C$12*E17/1000+'ARIMAX(1,1,1) Model'!$C$13*V17+'ARIMAX(1,1,1) Model'!$C$14*A17+'ARIMAX(1,1,1) Model'!$C$15*SIN(2*PI()*A17/'ARIMAX(1,1,1) Model'!$C$24)+'ARIMAX(1,1,1) Model'!$C$16*COS(2*PI()*A17/'ARIMAX(1,1,1) Model'!$C$24)+'ARIMAX(1,1,1) Model'!$C$17*SIN(4*PI()*A17/'ARIMAX(1,1,1) Model'!$C$24)+'ARIMAX(1,1,1) Model'!$C$18*COS(4*PI()*A17/'ARIMAX(1,1,1) Model'!$C$24) -> 1352.8381 | AR17: =IF(ISNUMBER(C17),C17,AP17)-AQ17 -> 6043.1619 | AS17: =IF(ISNUMBER(C17),C17-AP17,0) -> -36.592074
A18: 17 | B18: 33389 | C18: 7287 | E18: 443000 | G18: 21.21 | H18: 18.87 | I18: 1.14 | J18: 6035.178 | L18: 929 | M18: 12.038 | N18: 179076 | O18: 3913 | V18: 84.4 | AC18: 1 | AD18: 3.7 | AE18: 69 | AG18: =6753.47943187+0.36116788*I18+0.01252571*N18-22.85359542*V18+0.00407811*AA18-0.00067349*E18 -> 6769.7457 | AH18: =A18*'Simple Linear Regression'!$B$18+'Simple Linear Regression'!$B$17 -> 7899.838 | AI18: =7491.3971+0.0137554*N18-0.00058829*E18-34.3283*V18+0.30565*L18+54.6031*M18 -> 7737.9991 | AJ18: =7491.3971-0.00058829*E18+0.30565*L18+54.6031*M18+0.0137554*N18-34.3283*V18 -> 7737.9991 | AL18: =2192.59+2373.87*I18+0.0316653*N18-15.7623*V18+0.00202406*AA18-0.000740146*E18-0.00963493*(I18*N18) -> 6944.1357 | AM18: =5205.907083+122.0638992*I18+13.609808*(N18/1000)-1.245906883*AD18+0.7746840854*AE18-134.2474226*AC18-1547.125689*IF(AND(B18>=DATE(2020,3,20),B18<=DATE(2020,6,26)),1,0) -> 7696.8458 | AN18: =IF(ISNUMBER(C19),C19,AN19)-0.8328750492*(AD20-AD19)+3.274150872*(AE20-AE19)+0.7954612886*((IF(ISNUMBER(C19),C19,AN19)-IF(ISNUMBER(C18),C18,AN18))-(-0.8328750492*(AD19-AD18)+3.274150872*(AE19-AE18)))-1.394571582*AO19+0.4181414112*AO18 -> 7259.4579 | AP18: =AQ18+AR17+'ARIMAX(1,1,1) Model'!$C$19*(AR17-AR16)+'ARIMAX(1,1,1) Model'!$C$20*AS17 -> 7485.4494 | AQ18: ='ARIMAX(1,1,1) Model'!$C$6*I18+'ARIMAX(1,1,1) Model'!$C$7*N18/1000+'ARIMAX(1,1,1) Model'!$C$8*AD18+'ARIMAX(1,1,1) Model'!$C$9*AE18+'ARIMAX(1,1,1) Model'!$C$10*AC18+'ARIMAX(1,1,1) Model'!$C$11*IF(AND(B18>='ARIMAX(1,1,1) Model'!$C$25,B18<='ARIMAX(1,1,1) Model'!$C$26),1,0)+'ARIMAX(1,1,1) Model'!$C$12*E18/1000+'ARIMAX(1,1,1) Model'!$C$13*V18+'ARIMAX(1,1,1) Model'!$C$14*A18+'ARIMAX(1,1,1) Model'!$C$15*SIN(2*PI()*A18/'ARIMAX(1,1,1) Model'!$C$24)+'ARIMAX(1,1,1) Model'!$C$16*COS(2*PI()*A18/'ARIMAX(1,1,1) Model'!$C$24)+'ARIMAX(1,1,1) Model'!$C$17*SIN(4*PI()*A18/'ARIMAX(1,1,1) Model'!$C$24)+'ARIMAX(1,1,1) Model'!$C$18*COS(4*PI()*A18/'ARIMAX(1,1,1) Model'!$C$24) -> 1360.3016 | AR18: =IF(ISNUMBER(C18),C18,AP18)-AQ18 -> 5926.6984 | AS18: =IF(ISNUMBER(C18),C18-AP18,0) -> -198.44936
A19: 18 | B19: 33396 | C19: 7220 | E19: 432000 | G19: 20.634 | H19: 18.554 | I19: 1.138 | J19: 6035.178 | L19: 865 | M19: 12.038 | N19: 179076 | O19: 3907.1 | V19: 83.2 | AC19: 0 | AD19: 3.7 | AE19: 46.7 | AG19: =6753.47943187+0.36116788*I19+0.01252571*N19-22.85359542*V19+0.00407811*AA19-0.00067349*E19 -> 6804.5777 | AH19: =A19*'Simple Linear Regression'!$B$18+'Simple Linear Regression'!$B$17 -> 7900.691 | AI19: =7491.3971+0.0137554*N19-0.00058829*E19-34.3283*V19+0.30565*L19+54.6031*M19 -> 7766.1026 | AJ19: =7491.3971-0.00058829*E19+0.30565*L19+54.6031*M19+0.0137554*N19-34.3283*V19 -> 7766.1026 | AL19: =2192.59+2373.87*I19+0.0316653*N19-15.7623*V19+0.00202406*AA19-0.000740146*E19-0.00963493*(I19*N19) -> 6969.8951 | AM19: =5205.907083+122.0638992*I19+13.609808*(N19/1000)-1.245906883*AD19+0.7746840854*AE19-134.2474226*AC19-1547.125689*IF(AND(B19>=DATE(2020,3,20),B19<=DATE(2020,6,26)),1,0) -> 7813.5737 | AN19: =IF(ISNUMBER(C20),C20,AN20)-0.8328750492*(AD21-AD20)+3.274150872*(AE21-AE20)+0.7954612886*((IF(ISNUMBER(C20),C20,AN20)-IF(ISNUMBER(C19),C19,AN19))-(-0.8328750492*(AD20-AD19)+3.274150872*(AE20-AE19)))-1.394571582*AO20+0.4181414112*AO19 -> 8008.8257 | AP19: =AQ19+AR18+'ARIMAX(1,1,1) Model'!$C$19*(AR18-AR17)+'ARIMAX(1,1,1) Model'!$C$20*AS18 -> 7489.183 | AQ19: ='ARIMAX(1,1,1) Model'!$C$6*I19+'ARIMAX(1,1,1) Model'!$C$7*N19/1000+'ARIMAX(1,1,1) Model'!$C$8*AD19+'ARIMAX(1,1,1) Model'!$C$9*AE19+'ARIMAX(1,1,1) Model'!$C$10*AC19+'ARIMAX(1,1,1) Model'!$C$11*IF(AND(B19>='ARIMAX(1,1,1) Model'!$C$25,B19<='ARIMAX(1,1,1) Model'!$C$26),1,0)+'ARIMAX(1,1,1) Model'!$C$12*E19/1000+'ARIMAX(1,1,1) Model'!$C$13*V19+'ARIMAX(1,1,1) Model'!$C$14*A19+'ARIMAX(1,1,1) Model'!$C$15*SIN(2*PI()*A19/'ARIMAX(1,1,1) Model'!$C$24)+'ARIMAX(1,1,1) Model'!$C$16*COS(2*PI()*A19/'ARIMAX(1,1,1) Model'!$C$24)+'ARIMAX(1,1,1) Model'!$C$17*SIN(4*PI()*A19/'ARIMAX(1,1,1) Model'!$C$24)+'ARIMAX(1,1,1) Model'!$C$18*COS(4*PI()*A19/'ARIMAX(1,1,1) Model'!$C$24) -> 1395.2226 | AR19: =IF(ISNUMBER(C19),C19,AP19)-AQ19 -> 5824.7774 | AS19: =IF(ISNUMBER(C19),C19-AP19,0) -> -269.18305
A20: 19 | B20: 33403 | C20: 7651 | E20: 441000 | G20: 19.836 | H20: 17.856 | I20: 1.135 | J20: 6035.178 | L20: 865 | M20: 12.038 | N20: 179076 | O20: 3907.1 | V20: 83.2 | AC20: 0 | AD20: 0.2 | AE20: 56.4 | AG20: =6753.47943187+0.36116788*I20+0.01252571*N20-22.85359542*V20+0.00407811*AA20-0.00067349*E20 -> 6798.5152 | AH20: =A20*'Simple Linear Regression'!$B$18+'Simple Linear Regression'!$B$17 -> 7901.5441 | AI20: =7491.3971+0.0137554*N20-0.00058829*E20-34.3283*V20+0.30565*L20+54.6031*M20 -> 7760.808 | AJ20: =7491.3971-0.00058829*E20+0.30565*L20+54.6031*M20+0.0137554*N20-34.3283*V20 -> 7760.808 | AL20: =2192.59+2373.87*I20+0.0316653*N20-15.7623*V20+0.00202406*AA20-0.000740146*E20-0.00963493*(I20*N20) -> 6961.2883 | AM20: =5205.907083+122.0638992*I20+13.609808*(N20/1000)-1.245906883*AD20+0.7746840854*AE20-134.2474226*AC20-1547.125689*IF(AND(B20>=DATE(2020,3,20),B20<=DATE(2020,6,26)),1,0) -> 7825.0826 | AN20: =IF(ISNUMBER(C21),C21,AN21)-0.8328750492*(AD22-AD21)+3.274150872*(AE22-AE21)+0.7954612886*((IF(ISNUMBER(C21),C21,AN21)-IF(ISNUMBER(C20),C20,AN20))-(-0.8328750492*(AD21-AD20)+3.274150872*(AE21-AE20)))-1.394571582*AO21+0.4181414112*AO20 -> 7700.2571 | AP20: =AQ20+AR19+'ARIMAX(1,1,1) Model'!$C$19*(AR19-AR18)+'ARIMAX(1,1,1) Model'!$C$20*AS19 -> 7468.2031 | AQ20: ='ARIMAX(1,1,1) Model'!$C$6*I20+'ARIMAX(1,1,1) Model'!$C$7*N20/1000+'ARIMAX(1,1,1) Model'!$C$8*AD20+'ARIMAX(1,1,1) Model'!$C$9*AE20+'ARIMAX(1,1,1) Model'!$C$10*AC20+'ARIMAX(1,1,1) Model'!$C$11*IF(AND(B20>='ARIMAX(1,1,1) Model'!$C$25,B20<='ARIMAX(1,1,1) Model'!$C$26),1,0)+'ARIMAX(1,1,1) Model'!$C$12*E20/1000+'ARIMAX(1,1,1) Model'!$C$13*V20+'ARIMAX(1,1,1) Model'!$C$14*A20+'ARIMAX(1,1,1) Model'!$C$15*SIN(2*PI()*A20/'ARIMAX(1,1,1) Model'!$C$24)+'ARIMAX(1,1,1) Model'!$C$16*COS(2*PI()*A20/'ARIMAX(1,1,1) Model'!$C$24)+'ARIMAX(1,1,1) Model'!$C$17*SIN(4*PI()*A20/'ARIMAX(1,1,1) Model'!$C$24)+'ARIMAX(1,1,1) Model'!$C$18*COS(4*PI()*A20/'ARIMAX(1,1,1) Model'!$C$24) -> 1411.079 | AR20: =IF(ISNUMBER(C20),C20,AP20)-AQ20 -> 6239.921 | AS20: =IF(ISNUMBER(C20),C20-AP20,0) -> 182.79688
A21: 20 | B21: 33410 | C21: 7720 | E21: 429000 | G21: 20.078 | H21: 18.062 | I21: 1.126 | J21: 6035.178 | L21: 865 | M21: 12.487 | N21: 179538 | O21: 3907.1 | P21: 824860 | V21: 83.2 | AC21: 0 | AD21: 0.2 | AE21: 69.4 | AG21: =6753.47943187+0.36116788*I21+0.01252571*N21-22.85359542*V21+0.00407811*AA21-0.00067349*E21 -> 6812.3807 | AH21: =A21*'Simple Linear Regression'!$B$18+'Simple Linear Regression'!$B$17 -> 7902.3971 | AI21: =7491.3971+0.0137554*N21-0.00058829*E21-34.3283*V21+0.30565*L21+54.6031*M21 -> 7798.7393 | AJ21: =7491.3971-0.00058829*E21+0.30565*L21+54.6031*M21+0.0137554*N21-34.3283*V21 -> 7798.7393 | AL21: =2192.59+2373.87*I21+0.0316653*N21-15.7623*V21+0.00202406*AA21-0.000740146*E21-0.00963493*(I21*N21) -> 6973.9509 | AM21: =5205.907083+122.0638992*I21+13.609808*(N21/1000)-1.245906883*AD21+0.7746840854*AE21-134.2474226*AC21-1547.125689*IF(AND(B21>=DATE(2020,3,20),B21<=DATE(2020,6,26)),1,0) -> 7840.3426 | AN21: =IF(ISNUMBER(C22),C22,AN22)-0.8328750492*(AD23-AD22)+3.274150872*(AE23-AE22)+0.7954612886*((IF(ISNUMBER(C22),C22,AN22)-IF(ISNUMBER(C21),C21,AN21))-(-0.8328750492*(AD22-AD21)+3.274150872*(AE22-AE21)))-1.394571582*AO22+0.4181414112*AO21 -> 7538.7652 | AP21: =AQ21+AR20+'ARIMAX(1,1,1) Model'!$C$19*(AR20-AR19)+'ARIMAX(1,1,1) Model'!$C$20*AS20 -> 7563.6902 | AQ21: ='ARIMAX(1,1,1) Model'!$C$6*I21+'ARIMAX(1,1,1) Model'!$C$7*N21/1000+'ARIMAX(1,1,1) Model'!$C$8*AD21+'ARIMAX(1,1,1) Model'!$C$9*AE21+'ARIMAX(1,1,1) Model'!$C$10*AC21+'ARIMAX(1,1,1) Model'!$C$11*IF(AND(B21>='ARIMAX(1,1,1) Model'!$C$25,B21<='ARIMAX(1,1,1) Model'!$C$26),1,0)+'ARIMAX(1,1,1) Model'!$C$12*E21/1000+'ARIMAX(1,1,1) Model'!$C$13*V21+'ARIMAX(1,1,1) Model'!$C$14*A21+'ARIMAX(1,1,1) Model'!$C$15*SIN(2*PI()*A21/'ARIMAX(1,1,1) Model'!$C$24)+'ARIMAX(1,1,1) Model'!$C$16*COS(2*PI()*A21/'ARIMAX(1,1,1) Model'!$C$24)+'ARIMAX(1,1,1) Model'!$C$17*SIN(4*PI()*A21/'ARIMAX(1,1,1) Model'!$C$24)+'ARIMAX(1,1,1) Model'!$C$18*COS(4*PI()*A21/'ARIMAX(1,1,1) Model'!$C$24) -> 1447.812 | AR21: =IF(ISNUMBER(C21),C21,AP21)-AQ21 -> 6272.188 | AS21: =IF(ISNUMBER(C21),C21-AP21,0) -> 156.30983
A22: 21 | B22: 33417 | C22: 7543 | E22: 423000 | G22: 20.208 | H22: 18.198 | I22: 1.114 | J22: 6035.178 | L22: 865 | M22: 12.487 | N22: 179538 | O22: 3907.1 | P22: 824860 | V22: 83.2 | AC22: 0 | AD22: 0.8 | AE22: 57.1 | AG22: =6753.47943187+0.36116788*I22+0.01252571*N22-22.85359542*V22+0.00407811*AA22-0.00067349*E22 -> 6816.4173 | AH22: =A22*'Simple Linear Regression'!$B$18+'Simple Linear Regression'!$B$17 -> 7903.2501 | AI22: =7491.3971+0.0137554*N22-0.00058829*E22-34.3283*V22+0.30565*L22+54.6031*M22 -> 7802.269 | AJ22: =7491.3971-0.00058829*E22+0.30565*L22+54.6031*M22+0.0137554*N22-34.3283*V22 -> 7802.269 | AL22: =2192.59+2373.87*I22+0.0316653*N22-15.7623*V22+0.00202406*AA22-0.000740146*E22-0.00963493*(I22*N22) -> 6970.6633 | AM22: =5205.907083+122.0638992*I22+13.609808*(N22/1000)-1.245906883*AD22+0.7746840854*AE22-134.2474226*AC22-1547.125689*IF(AND(B22>=DATE(2020,3,20),B22<=DATE(2020,6,26)),1,0) -> 7828.6017 | AN22: =IF(ISNUMBER(C23),C23,AN23)-0.8328750492*(AD24-AD23)+3.274150872*(AE24-AE23)+0.7954612886*((IF(ISNUMBER(C23),C23,AN23)-IF(ISNUMBER(C22),C22,AN22))-(-0.8328750492*(AD23-AD22)+3.274150872*(AE23-AE22)))-1.394571582*AO23+0.4181414112*AO22 -> 8192.664 | AP22: =AQ22+AR21+'ARIMAX(1,1,1) Model'!$C$19*(AR21-AR20)+'ARIMAX(1,1,1) Model'!$C$20*AS21 -> 7533.0678 | AQ22: ='ARIMAX(1,1,1) Model'!$C$6*I22+'ARIMAX(1,1,1) Model'!$C$7*N22/1000+'ARIMAX(1,1,1) Model'!$C$8*AD22+'ARIMAX(1,1,1) Model'!$C$9*AE22+'ARIMAX(1,1,1) Model'!$C$10*AC22+'ARIMAX(1,1,1) Model'!$C$11*IF(AND(B22>='ARIMAX(1,1,1) Model'!$C$25,B22<='ARIMAX(1,1,1) Model'!$C$26),1,0)+'ARIMAX(1,1,1) Model'!$C$12*E22/1000+'ARIMAX(1,1,1) Model'!$C$13*V22+'ARIMAX(1,1,1) Model'!$C$14*A22+'ARIMAX(1,1,1) Model'!$C$15*SIN(2*PI()*A22/'ARIMAX(1,1,1) Model'!$C$24)+'ARIMAX(1,1,1) Model'!$C$16*COS(2*PI()*A22/'ARIMAX(1,1,1) Model'!$C$24)+'ARIMAX(1,1,1) Model'!$C$17*SIN(4*PI()*A22/'ARIMAX(1,1,1) Model'!$C$24)+'ARIMAX(1,1,1) Model'!$C$18*COS(4*PI()*A22/'ARIMAX(1,1,1) Model'!$C$24) -> 1398.4246 | AR22: =IF(ISNUMBER(C22),C22,AP22)-AQ22 -> 6144.5754 | AS22: =IF(ISNUMBER(C22),C22-AP22,0) -> 9.9322033
A23: 22 | B23: 33424 | C23: 7961 | E23: 418000 | G23: 20.798 | H23: 18.552 | I23: 1.104 | J23: 6035.178 | L23: 865 | M23: 12.487 | N23: 179538 | O23: 3907.1 | P23: 824860 | V23: 84.6 | AC23: 1 | AD23: 0 | AE23: 88.7 | AG23: =6753.47943187+0.36116788*I23+0.01252571*N23-22.85359542*V23+0.00407811*AA23-0.00067349*E23 -> 6787.7861 | AH23: =A23*'Simple Linear Regression'!$B$18+'Simple Linear Regression'!$B$17 -> 7904.1032 | AI23: =7491.3971+0.0137554*N23-0.00058829*E23-34.3283*V23+0.30565*L23+54.6031*M23 -> 7757.1509 | AJ23: =7491.3971-0.00058829*E23+0.30565*L23+54.6031*M23+0.0137554*N23-34.3283*V23 -> 7757.1509 | AL23: =2192.59+2373.87*I23+0.0316653*N23-15.7623*V23+0.00202406*AA23-0.000740146*E23-0.00963493*(I23*N23) -> 6945.8565 | AM23: =5205.907083+122.0638992*I23+13.609808*(N23/1000)-1.245906883*AD23+0.7746840854*AE23-134.2474226*AC23-1547.125689*IF(AND(B23>=DATE(2020,3,20),B23<=DATE(2020,6,26)),1,0) -> 7718.6104 | AN23: =IF(ISNUMBER(C24),C24,AN24)-0.8328750492*(AD25-AD24)+3.274150872*(AE25-AE24)+0.7954612886*((IF(ISNUMBER(C24),C24,AN24)-IF(ISNUMBER(C23),C23,AN23))-(-0.8328750492*(AD24-AD23)+3.274150872*(AE24-AE23)))-1.394571582*AO24+0.4181414112*AO23 -> 6838.9666 | AP23: =AQ23+AR22+'ARIMAX(1,1,1) Model'!$C$19*(AR22-AR21)+'ARIMAX(1,1,1) Model'!$C$20*AS22 -> 7509.6822 | AQ23: ='ARIMAX(1,1,1) Model'!$C$6*I23+'ARIMAX(1,1,1) Model'!$C$7*N23/1000+'ARIMAX(1,1,1) Model'!$C$8*AD23+'ARIMAX(1,1,1) Model'!$C$9*AE23+'ARIMAX(1,1,1) Model'!$C$10*AC23+'ARIMAX(1,1,1) Model'!$C$11*IF(AND(B23>='ARIMAX(1,1,1) Model'!$C$25,B23<='ARIMAX(1,1,1) Model'!$C$26),1,0)+'ARIMAX(1,1,1) Model'!$C$12*E23/1000+'ARIMAX(1,1,1) Model'!$C$13*V23+'ARIMAX(1,1,1) Model'!$C$14*A23+'ARIMAX(1,1,1) Model'!$C$15*SIN(2*PI()*A23/'ARIMAX(1,1,1) Model'!$C$24)+'ARIMAX(1,1,1) Model'!$C$16*COS(2*PI()*A23/'ARIMAX(1,1,1) Model'!$C$24)+'ARIMAX(1,1,1) Model'!$C$17*SIN(4*PI()*A23/'ARIMAX(1,1,1) Model'!$C$24)+'ARIMAX(1,1,1) Model'!$C$18*COS(4*PI()*A23/'ARIMAX(1,1,1) Model'!$C$24) -> 1386.4929 | AR23: =IF(ISNUMBER(C23),C23,AP23)-AQ23 -> 6574.5071 | AS23: =IF(ISNUMBER(C23),C23-AP23,0) -> 451.31777
A24: 23 | B24: 33431 | C24: 7327 | E24: 422000 | G24: 21.426 | H24: 19.244 | I24: 1.098 | J24: 6035.178 | L24: 819 | M24: 12.487 | N24: 179538 | O24: 3933.2 | P24: 824860 | V24: 84.6 | AC24: 0 | AD24: 0 | AE24: 83.2 | AG24: =6753.47943187+0.36116788*I24+0.01252571*N24-22.85359542*V24+0.00407811*AA24-0.00067349*E24 -> 6785.09 | AH24: =A24*'Simple Linear Regression'!$B$18+'Simple Linear Regression'!$B$17 -> 7904.9562 | AI24: =7491.3971+0.0137554*N24-0.00058829*E24-34.3283*V24+0.30565*L24+54.6031*M24 -> 7740.7378 | AJ24: =7491.3971-0.00058829*E24+0.30565*L24+54.6031*M24+0.0137554*N24-34.3283*V24 -> 7740.7378 | AL24: =2192.59+2373.87*I24+0.0316653*N24-15.7623*V24+0.00202406*AA24-0.000740146*E24-0.00963493*(I24*N24) -> 6939.0317 | AM24: =5205.907083+122.0638992*I24+13.609808*(N24/1000)-1.245906883*AD24+0.7746840854*AE24-134.2474226*AC24-1547.125689*IF(AND(B24>=DATE(2020,3,20),B24<=DATE(2020,6,26)),1,0) -> 7847.8647 | AN24: =IF(ISNUMBER(C25),C25,AN25)-0.8328750492*(AD26-AD25)+3.274150872*(AE26-AE25)+0.7954612886*((IF(ISNUMBER(C25),C25,AN25)-IF(ISNUMBER(C24),C24,AN24))-(-0.8328750492*(AD25-AD24)+3.274150872*(AE25-AE24)))-1.394571582*AO25+0.4181414112*AO24 -> 7442.861 | AP24: =AQ24+AR23+'ARIMAX(1,1,1) Model'!$C$19*(AR23-AR22)+'ARIMAX(1,1,1) Model'!$C$20*AS23 -> 7660.0718 | AQ24: ='ARIMAX(1,1,1) Model'!$C$6*I24+'ARIMAX(1,1,1) Model'!$C$7*N24/1000+'ARIMAX(1,1,1) Model'!$C$8*AD24+'ARIMAX(1,1,1) Model'!$C$9*AE24+'ARIMAX(1,1,1) Model'!$C$10*AC24+'ARIMAX(1,1,1) Model'!$C$11*IF(AND(B24>='ARIMAX(1,1,1) Model'!$C$25,B24<='ARIMAX(1,1,1) Model'!$C$26),1,0)+'ARIMAX(1,1,1) Model'!$C$12*E24/1000+'ARIMAX(1,1,1) Model'!$C$13*V24+'ARIMAX(1,1,1) Model'!$C$14*A24+'ARIMAX(1,1,1) Model'!$C$15*SIN(2*PI()*A24/'ARIMAX(1,1,1) Model'!$C$24)+'ARIMAX(1,1,1) Model'!$C$16*COS(2*PI()*A24/'ARIMAX(1,1,1) Model'!$C$24)+'ARIMAX(1,1,1) Model'!$C$17*SIN(4*PI()*A24/'ARIMAX(1,1,1) Model'!$C$24)+'ARIMAX(1,1,1) Model'!$C$18*COS(4*PI()*A24/'ARIMAX(1,1,1) Model'!$C$24) -> 1449.8565 | AR24: =IF(ISNUMBER(C24),C24,AP24)-AQ24 -> 5877.1435 | AS24: =IF(ISNUMBER(C24),C24-AP24,0) -> -333.07178
A25: 24 | B25: 33438 | C25: 7380 | E25: 420000 | G25: 21.906 | H25: 20.024 | I25: 1.094 | J25: 6035.178 | L25: 819 | M25: 12.719 | N25: 191929 | O25: 3933.2 | P25: 824860 | V25: 84.6 | AC25: 0 | AD25: 0 | AE25: 83.8 | AG25: =6753.47943187+0.36116788*I25+0.01252571*N25-22.85359542*V25+0.00407811*AA25-0.00067349*E25 -> 6941.6416 | AH25: =A25*'Simple Linear Regression'!$B$18+'Simple Linear Regression'!$B$17 -> 7905.8092 | AI25: =7491.3971+0.0137554*N25-0.00058829*E25-34.3283*V25+0.30565*L25+54.6031*M25 -> 7925.0255 | AJ25: =7491.3971-0.00058829*E25+0.30565*L25+54.6031*M25+0.0137554*N25-34.3283*V25 -> 7925.0255 | AL25: =2192.59+2373.87*I25+0.0316653*N25-15.7623*V25+0.00202406*AA25-0.000740146*E25-0.00963493*(I25*N25) -> 7199.6919 | AM25: =5205.907083+122.0638992*I25+13.609808*(N25/1000)-1.245906883*AD25+0.7746840854*AE25-134.2474226*AC25-1547.125689*IF(AND(B25>=DATE(2020,3,20),B25<=DATE(2020,6,26)),1,0) -> 8016.4804 | AN25: =IF(ISNUMBER(C26),C26,AN26)-0.8328750492*(AD27-AD26)+3.274150872*(AE27-AE26)+0.7954612886*((IF(ISNUMBER(C26),C26,AN26)-IF(ISNUMBER(C25),C25,AN25))-(-0.8328750492*(AD26-AD25)+3.274150872*(AE26-AE25)))-1.394571582*AO26+0.4181414112*AO25 -> 7547.1264 | AP25: =AQ25+AR24+'ARIMAX(1,1,1) Model'!$C$19*(AR24-AR23)+'ARIMAX(1,1,1) Model'!$C$20*AS24 -> 7542.7428 | AQ25: ='ARIMAX(1,1,1) Model'!$C$6*I25+'ARIMAX(1,1,1) Model'!$C$7*N25/1000+'ARIMAX(1,1,1) Model'!$C$8*AD25+'ARIMAX(1,1,1) Model'!$C$9*AE25+'ARIMAX(1,1,1) Model'!$C$10*AC25+'ARIMAX(1,1,1) Model'!$C$11*IF(AND(B25>='ARIMAX(1,1,1) Model'!$C$25,B25<='ARIMAX(1,1,1) Model'!$C$26),1,0)+'ARIMAX(1,1,1) Model'!$C$12*E25/1000+'ARIMAX(1,1,1) Model'!$C$13*V25+'ARIMAX(1,1,1) Model'!$C$14*A25+'ARIMAX(1,1,1) Model'!$C$15*SIN(2*PI()*A25/'ARIMAX(1,1,1) Model'!$C$24)+'ARIMAX(1,1,1) Model'!$C$16*COS(2*PI()*A25/'ARIMAX(1,1,1) Model'!$C$24)+'ARIMAX(1,1,1) Model'!$C$17*SIN(4*PI()*A25/'ARIMAX(1,1,1) Model'!$C$24)+'ARIMAX(1,1,1) Model'!$C$18*COS(4*PI()*A25/'ARIMAX(1,1,1) Model'!$C$24) -> 1433.8218 | AR25: =IF(ISNUMBER(C25),C25,AP25)-AQ25 -> 5946.1782 | AS25: =IF(ISNUMBER(C25),C25-AP25,0) -> -162.74277
A26: 25 | B26: 33445 | C26: 7501 | E26: 408000 | G26: 21.398 | H26: 19.664 | I26: 1.091 | J26: 6035.178 | L26: 819 | M26: 12.719 | N26: 191929 | O26: 3933.2 | P26: 824860 | V26: 84.6 | AC26: 0 | AD26: 0 | AE26: 90.6 | AG26: =6753.47943187+0.36116788*I26+0.01252571*N26-22.85359542*V26+0.00407811*AA26-0.00067349*E26 -> 6949.7224 | AH26: =A26*'Simple Linear Regression'!$B$18+'Simple Linear Regression'!$B$17 -> 7906.6623 | AI26: =7491.3971+0.0137554*N26-0.00058829*E26-34.3283*V26+0.30565*L26+54.6031*M26 -> 7932.0849 | AJ26: =7491.3971-0.00058829*E26+0.30565*L26+54.6031*M26+0.0137554*N26-34.3283*V26 -> 7932.0849 | AL26: =2192.59+2373.87*I26+0.0316653*N26-15.7623*V26+0.00202406*AA26-0.000740146*E26-0.00963493*(I26*N26) -> 7206.9997 | AM26: =5205.907083+122.0638992*I26+13.609808*(N26/1000)-1.245906883*AD26+0.7746840854*AE26-134.2474226*AC26-1547.125689*IF(AND(B26>=DATE(2020,3,20),B26<=DATE(2020,6,26)),1,0) -> 8021.382 | AN26: =IF(ISNUMBER(C27),C27,AN27)-0.8328750492*(AD28-AD27)+3.274150872*(AE28-AE27)+0.7954612886*((IF(ISNUMBER(C27),C27,AN27)-IF(ISNUMBER(C26),C26,AN26))-(-0.8328750492*(AD27-AD26)+3.274150872*(AE27-AE26)))-1.394571582*AO27+0.4181414112*AO26 -> 7694.1946 | AP26: =AQ26+AR25+'ARIMAX(1,1,1) Model'!$C$19*(AR25-AR24)+'ARIMAX(1,1,1) Model'!$C$20*AS25 -> 7532.0817 | AQ26: ='ARIMAX(1,1,1) Model'!$C$6*I26+'ARIMAX(1,1,1) Model'!$C$7*N26/1000+'ARIMAX(1,1,1) Model'!$C$8*AD26+'ARIMAX(1,1,1) Model'!$C$9*AE26+'ARIMAX(1,1,1) Model'!$C$10*AC26+'ARIMAX(1,1,1) Model'!$C$11*IF(AND(B26>='ARIMAX(1,1,1) Model'!$C$25,B26<='ARIMAX(1,1,1) Model'!$C$26),1,0)+'ARIMAX(1,1,1) Model'!$C$12*E26/1000+'ARIMAX(1,1,1) Model'!$C$13*V26+'ARIMAX(1,1,1) Model'!$C$14*A26+'ARIMAX(1,1,1) Model'!$C$15*SIN(2*PI()*A26/'ARIMAX(1,1,1) Model'!$C$24)+'ARIMAX(1,1,1) Model'!$C$16*COS(2*PI()*A26/'ARIMAX(1,1,1) Model'!$C$24)+'ARIMAX(1,1,1) Model'!$C$17*SIN(4*PI()*A26/'ARIMAX(1,1,1) Model'!$C$24)+'ARIMAX(1,1,1) Model'!$C$18*COS(4*PI()*A26/'ARIMAX(1,1,1) Model'!$C$24) -> 1432.6884 | AR26: =IF(ISNUMBER(C26),C26,AP26)-AQ26 -> 6068.3116 | AS26: =IF(ISNUMBER(C26),C26-AP26,0) -> -31.081718
A27: 26 | B27: 33452 | C27: 7605 | E27: 423000 | G27: 21.462 | H27: 19.568 | I27: 1.091 | J27: 6035.178 | L27: 819 | M27: 12.719 | N27: 191929 | O27: 3933.2 | P27: 824860 | V27: 84.6 | AC27: 0 | AD27: 0 | AE27: 80.7 | AG27: =6753.47943187+0.36116788*I27+0.01252571*N27-22.85359542*V27+0.00407811*AA27-0.00067349*E27 -> 6939.62 | AH27: =A27*'Simple Linear Regression'!$B$18+'Simple Linear Regression'!$B$17 -> 7907.5153 | AI27: =7491.3971+0.0137554*N27-0.00058829*E27-34.3283*V27+0.30565*L27+54.6031*M27 -> 7923.2606 | AJ27: =7491.3971-0.00058829*E27+0.30565*L27+54.6031*M27+0.0137554*N27-34.3283*V27 -> 7923.2606 | AL27: =2192.59+2373.87*I27+0.0316653*N27-15.7623*V27+0.00202406*AA27-0.000740146*E27-0.00963493*(I27*N27) -> 7195.8975 | AM27: =5205.907083+122.0638992*I27+13.609808*(N27/1000)-1.245906883*AD27+0.7746840854*AE27-134.2474226*AC27-1547.125689*IF(AND(B27>=DATE(2020,3,20),B27<=DATE(2020,6,26)),1,0) -> 8013.7126 | AN27: =IF(ISNUMBER(C28),C28,AN28)-0.8328750492*(AD29-AD28)+3.274150872*(AE29-AE28)+0.7954612886*((IF(ISNUMBER(C28),C28,AN28)-IF(ISNUMBER(C27),C27,AN27))-(-0.8328750492*(AD28-AD27)+3.274150872*(AE28-AE27)))-1.394571582*AO28+0.4181414112*AO27 -> 7583.9713 | AP27: =AQ27+AR26+'ARIMAX(1,1,1) Model'!$C$19*(AR26-AR25)+'ARIMAX(1,1,1) Model'!$C$20*AS26 -> 7471.0462 | AQ27: ='ARIMAX(1,1,1) Model'!$C$6*I27+'ARIMAX(1,1,1) Model'!$C$7*N27/1000+'ARIMAX(1,1,1) Model'!$C$8*AD27+'ARIMAX(1,1,1) Model'!$C$9*AE27+'ARIMAX(1,1,1) Model'!$C$10*AC27+'ARIMAX(1,1,1) Model'!$C$11*IF(AND(B27>='ARIMAX(1,1,1) Model'!$C$25,B27<='ARIMAX(1,1,1) Model'!$C$26),1,0)+'ARIMAX(1,1,1) Model'!$C$12*E27/1000+'ARIMAX(1,1,1) Model'!$C$13*V27+'ARIMAX(1,1,1) Model'!$C$14*A27+'ARIMAX(1,1,1) Model'!$C$15*SIN(2*PI()*A27/'ARIMAX(1,1,1) Model'!$C$24)+'ARIMAX(1,1,1) Model'!$C$16*COS(2*PI()*A27/'ARIMAX(1,1,1) Model'!$C$24)+'ARIMAX(1,1,1) Model'!$C$17*SIN(4*PI()*A27/'ARIMAX(1,1,1) Model'!$C$24)+'ARIMAX(1,1,1) Model'!$C$18*COS(4*PI()*A27/'ARIMAX(1,1,1) Model'!$C$24) -> 1362.8466 | AR27: =IF(ISNUMBER(C27),C27,AP27)-AQ27 -> 6242.1534 | AS27: =IF(ISNUMBER(C27),C27-AP27,0) -> 133.95378
A28: 27 | B28: 33459 | C28: 7584 | E28: 438000 | G28: 21.502 | H28: 19.516 | I28: 1.099 | J28: 6126.862 | L28: 867 | M28: 12.719 | N28: 191929 | O28: 3940.5 | P28: 824860 | V28: 87.5 | AC28: 0 | AD28: 0 | AE28: 74.8 | AG28: =6753.47943187+0.36116788*I28+0.01252571*N28-22.85359542*V28+0.00407811*AA28-0.00067349*E28 -> 6863.2451 | AH28: =A28*'Simple Linear Regression'!$B$18+'Simple Linear Regression'!$B$17 -> 7908.3683 | AI28: =7491.3971+0.0137554*N28-0.00058829*E28-34.3283*V28+0.30565*L28+54.6031*M28 -> 7829.5554 | AJ28: =7491.3971-0.00058829*E28+0.30565*L28+54.6031*M28+0.0137554*N28-34.3283*V28 -> 7829.5554 | AL28: =2192.59+2373.87*I28+0.0316653*N28-15.7623*V28+0.00202406*AA28-0.000740146*E28-0.00963493*(I28*N28) -> 7143.2818 | AM28: =5205.907083+122.0638992*I28+13.609808*(N28/1000)-1.245906883*AD28+0.7746840854*AE28-134.2474226*AC28-1547.125689*IF(AND(B28>=DATE(2020,3,20),B28<=DATE(2020,6,26)),1,0) -> 8010.1185 | AN28: =IF(ISNUMBER(C29),C29,AN29)-0.8328750492*(AD30-AD29)+3.274150872*(AE30-AE29)+0.7954612886*((IF(ISNUMBER(C29),C29,AN29)-IF(ISNUMBER(C28),C28,AN28))-(-0.8328750492*(AD29-AD28)+3.274150872*(AE29-AE28)))-1.394571582*AO29+0.4181414112*AO28 -> 7248.4953 | AP28: =AQ28+AR27+'ARIMAX(1,1,1) Model'!$C$19*(AR27-AR26)+'ARIMAX(1,1,1) Model'!$C$20*AS27 -> 7490.4253 | AQ28: ='ARIMAX(1,1,1) Model'!$C$6*I28+'ARIMAX(1,1,1) Model'!$C$7*N28/1000+'ARIMAX(1,1,1) Model'!$C$8*AD28+'ARIMAX(1,1,1) Model'!$C$9*AE28+'ARIMAX(1,1,1) Model'!$C$10*AC28+'ARIMAX(1,1,1) Model'!$C$11*IF(AND(B28>='ARIMAX(1,1,1) Model'!$C$25,B28<='ARIMAX(1,1,1) Model'!$C$26),1,0)+'ARIMAX(1,1,1) Model'!$C$12*E28/1000+'ARIMAX(1,1,1) Model'!$C$13*V28+'ARIMAX(1,1,1) Model'!$C$14*A28+'ARIMAX(1,1,1) Model'!$C$15*SIN(2*PI()*A28/'ARIMAX(1,1,1) Model'!$C$24)+'ARIMAX(1,1,1) Model'!$C$16*COS(2*PI()*A28/'ARIMAX(1,1,1) Model'!$C$24)+'ARIMAX(1,1,1) Model'!$C$17*SIN(4*PI()*A28/'ARIMAX(1,1,1) Model'!$C$24)+'ARIMAX(1,1,1) Model'!$C$18*COS(4*PI()*A28/'ARIMAX(1,1,1) Model'!$C$24) -> 1351.8864 | AR28: =IF(ISNUMBER(C28),C28,AP28)-AQ28 -> 6232.1136 | AS28: =IF(ISNUMBER(C28),C28-AP28,0) -> 93.57473
A29: 28 | B29: 33466 | C29: 7401 | E29: 437000 | G29: 21.442 | H29: 19.392 | I29: 1.112 | J29: 6126.862 | L29: 867 | M29: 12.972 | N29: 193467 | O29: 3940.5 | P29: 824860 | V29: 87.5 | AC29: 0 | AD29: 0 | AE29: 75.2 | AG29: =6753.47943187+0.36116788*I29+0.01252571*N29-22.85359542*V29+0.00407811*AA29-0.00067349*E29 -> 6883.1879 | AH29: =A29*'Simple Linear Regression'!$B$18+'Simple Linear Regression'!$B$17 -> 7909.2214 | AI29: =7491.3971+0.0137554*N29-0.00058829*E29-34.3283*V29+0.30565*L29+54.6031*M29 -> 7865.1141 | AJ29: =7491.3971-0.00058829*E29+0.30565*L29+54.6031*M29+0.0137554*N29-34.3283*V29 -> 7865.1141 | AL29: =2192.59+2373.87*I29+0.0316653*N29-15.7623*V29+0.00202406*AA29-0.000740146*E29-0.00963493*(I29*N29) -> 7183.0654 | AM29: =5205.907083+122.0638992*I29+13.609808*(N29/1000)-1.245906883*AD29+0.7746840854*AE29-134.2474226*AC29-1547.125689*IF(AND(B29>=DATE(2020,3,20),B29<=DATE(2020,6,26)),1,0) -> 8032.9471 | AN29: =IF(ISNUMBER(C30),C30,AN30)-0.8328750492*(AD31-AD30)+3.274150872*(AE31-AE30)+0.7954612886*((IF(ISNUMBER(C30),C30,AN30)-IF(ISNUMBER(C29),C29,AN29))-(-0.8328750492*(AD30-AD29)+3.274150872*(AE30-AE29)))-1.394571582*AO30+0.4181414112*AO29 -> 7623.193 | AP29: =AQ29+AR28+'ARIMAX(1,1,1) Model'!$C$19*(AR28-AR27)+'ARIMAX(1,1,1) Model'!$C$20*AS28 -> 7474.9934 | AQ29: ='ARIMAX(1,1,1) Model'!$C$6*I29+'ARIMAX(1,1,1) Model'!$C$7*N29/1000+'ARIMAX(1,1,1) Model'!$C$8*AD29+'ARIMAX(1,1,1) Model'!$C$9*AE29+'ARIMAX(1,1,1) Model'!$C$10*AC29+'ARIMAX(1,1,1) Model'!$C$11*IF(AND(B29>='ARIMAX(1,1,1) Model'!$C$25,B29<='ARIMAX(1,1,1) Model'!$C$26),1,0)+'ARIMAX(1,1,1) Model'!$C$12*E29/1000+'ARIMAX(1,1,1) Model'!$C$13*V29+'ARIMAX(1,1,1) Model'!$C$14*A29+'ARIMAX(1,1,1) Model'!$C$15*SIN(2*PI()*A29/'ARIMAX(1,1,1) Model'!$C$24)+'ARIMAX(1,1,1) Model'!$C$16*COS(2*PI()*A29/'ARIMAX(1,1,1) Model'!$C$24)+'ARIMAX(1,1,1) Model'!$C$17*SIN(4*PI()*A29/'ARIMAX(1,1,1) Model'!$C$24)+'ARIMAX(1,1,1) Model'!$C$18*COS(4*PI()*A29/'ARIMAX(1,1,1) Model'!$C$24) -> 1328.0841 | AR29: =IF(ISNUMBER(C29),C29,AP29)-AQ29 -> 6072.9159 | AS29: =IF(ISNUMBER(C29),C29-AP29,0) -> -73.993413
A30: 29 | B30: 33473 | C30: 7505 | E30: 433000 | G30: 21.99 | H30: 20.092 | I30: 1.124 | J30: 6126.862 | L30: 867 | M30: 12.972 | N30: 193467 | O30: 3940.5 | P30: 824860 | V30: 87.5 | AC30: 0 | AD30: 0 | AE30: 73.4 | AG30: =6753.47943187+0.36116788*I30+0.01252571*N30-22.85359542*V30+0.00407811*AA30-0.00067349*E30 -> 6885.8862 | AH30: =A30*'Simple Linear Regression'!$B$18+'Simple Linear Regression'!$B$17 -> 7910.0744 | AI30: =7491.3971+0.0137554*N30-0.00058829*E30-34.3283*V30+0.30565*L30+54.6031*M30 -> 7867.4672 | AJ30: =7491.3971-0.00058829*E30+0.30565*L30+54.6031*M30+0.0137554*N30-34.3283*V30 -> 7867.4672 | AL30: =2192.59+2373.87*I30+0.0316653*N30-15.7623*V30+0.00202406*AA30-0.000740146*E30-0.00963493*(I30*N30) -> 7192.1439 | AM30: =5205.907083+122.0638992*I30+13.609808*(N30/1000)-1.245906883*AD30+0.7746840854*AE30-134.2474226*AC30-1547.125689*IF(AND(B30>=DATE(2020,3,20),B30<=DATE(2020,6,26)),1,0) -> 8033.0174 | AN30: =IF(ISNUMBER(C31),C31,AN31)-0.8328750492*(AD32-AD31)+3.274150872*(AE32-AE31)+0.7954612886*((IF(ISNUMBER(C31),C31,AN31)-IF(ISNUMBER(C30),C30,AN30))-(-0.8328750492*(AD31-AD30)+3.274150872*(AE31-AE30)))-1.394571582*AO31+0.4181414112*AO30 -> 7276.6204 | AP30: =AQ30+AR29+'ARIMAX(1,1,1) Model'!$C$19*(AR29-AR28)+'ARIMAX(1,1,1) Model'!$C$20*AS29 -> 7426.6352 | AQ30: ='ARIMAX(1,1,1) Model'!$C$6*I30+'ARIMAX(1,1,1) Model'!$C$7*N30/1000+'ARIMAX(1,1,1) Model'!$C$8*AD30+'ARIMAX(1,1,1) Model'!$C$9*AE30+'ARIMAX(1,1,1) Model'!$C$10*AC30+'ARIMAX(1,1,1) Model'!$C$11*IF(AND(B30>='ARIMAX(1,1,1) Model'!$C$25,B30<='ARIMAX(1,1,1) Model'!$C$26),1,0)+'ARIMAX(1,1,1) Model'!$C$12*E30/1000+'ARIMAX(1,1,1) Model'!$C$13*V30+'ARIMAX(1,1,1) Model'!$C$14*A30+'ARIMAX(1,1,1) Model'!$C$15*SIN(2*PI()*A30/'ARIMAX(1,1,1) Model'!$C$24)+'ARIMAX(1,1,1) Model'!$C$16*COS(2*PI()*A30/'ARIMAX(1,1,1) Model'!$C$24)+'ARIMAX(1,1,1) Model'!$C$17*SIN(4*PI()*A30/'ARIMAX(1,1,1) Model'!$C$24)+'ARIMAX(1,1,1) Model'!$C$18*COS(4*PI()*A30/'ARIMAX(1,1,1) Model'!$C$24) -> 1302.6458 | AR30: =IF(ISNUMBER(C30),C30,AP30)-AQ30 -> 6202.3542 | AS30: =IF(ISNUMBER(C30),C30-AP30,0) -> 78.364794
A31: 30 | B31: 33480 | C31: 7427 | E31: 425000 | G31: 21.982 | H31: 20.174 | I31: 1.124 | J31: 6126.862 | L31: 867 | M31: 12.972 | N31: 193467 | O31: 3940.5 | P31: 824860 | V31: 87.5 | AC31: 0 | AD31: 0 | AE31: 82.8 | AG31: =6753.47943187+0.36116788*I31+0.01252571*N31-22.85359542*V31+0.00407811*AA31-0.00067349*E31 -> 6891.2741 | AH31: =A31*'Simple Linear Regression'!$B$18+'Simple Linear Regression'!$B$17 -> 7910.9275 | AI31: =7491.3971+0.0137554*N31-0.00058829*E31-34.3283*V31+0.30565*L31+54.6031*M31 -> 7872.1735 | AJ31: =7491.3971-0.00058829*E31+0.30565*L31+54.6031*M31+0.0137554*N31-34.3283*V31 -> 7872.1735 | AL31: =2192.59+2373.87*I31+0.0316653*N31-15.7623*V31+0.00202406*AA31-0.000740146*E31-0.00963493*(I31*N31) -> 7198.0651 | AM31: =5205.907083+122.0638992*I31+13.609808*(N31/1000)-1.245906883*AD31+0.7746840854*AE31-134.2474226*AC31-1547.125689*IF(AND(B31>=DATE(2020,3,20),B31<=DATE(2020,6,26)),1,0) -> 8040.2995 | AN31: =IF(ISNUMBER(C32),C32,AN32)-0.8328750492*(AD33-AD32)+3.274150872*(AE33-AE32)+0.7954612886*((IF(ISNUMBER(C32),C32,AN32)-IF(ISNUMBER(C31),C31,AN31))-(-0.8328750492*(AD32-AD31)+3.274150872*(AE32-AE31)))-1.394571582*AO32+0.4181414112*AO31 -> 6690.4592 | AP31: =AQ31+AR30+'ARIMAX(1,1,1) Model'!$C$19*(AR30-AR29)+'ARIMAX(1,1,1) Model'!$C$20*AS30 -> 7465.0874 | AQ31: ='ARIMAX(1,1,1) Model'!$C$6*I31+'ARIMAX(1,1,1) Model'!$C$7*N31/1000+'ARIMAX(1,1,1) Model'!$C$8*AD31+'ARIMAX(1,1,1) Model'!$C$9*AE31+'ARIMAX(1,1,1) Model'!$C$10*AC31+'ARIMAX(1,1,1) Model'!$C$11*IF(AND(B31>='ARIMAX(1,1,1) Model'!$C$25,B31<='ARIMAX(1,1,1) Model'!$C$26),1,0)+'ARIMAX(1,1,1) Model'!$C$12*E31/1000+'ARIMAX(1,1,1) Model'!$C$13*V31+'ARIMAX(1,1,1) Model'!$C$14*A31+'ARIMAX(1,1,1) Model'!$C$15*SIN(2*PI()*A31/'ARIMAX(1,1,1) Model'!$C$24)+'ARIMAX(1,1,1) Model'!$C$16*COS(2*PI()*A31/'ARIMAX(1,1,1) Model'!$C$24)+'ARIMAX(1,1,1) Model'!$C$17*SIN(4*PI()*A31/'ARIMAX(1,1,1) Model'!$C$24)+'ARIMAX(1,1,1) Model'!$C$18*COS(4*PI()*A31/'ARIMAX(1,1,1) Model'!$C$24) -> 1320.6437 | AR31: =IF(ISNUMBER(C31),C31,AP31)-AQ31 -> 6106.3563 | AS31: =IF(ISNUMBER(C31),C31-AP31,0) -> -38.087378
A32: 31 | B32: 33487 | C32: 6993 | E32: 425000 | G32: 21.8375 | H32: 20.336 | I32: 1.127 | J32: 6126.862 | L32: 844 | M32: 12.972 | N32: 193467 | O32: 3966 | P32: 824860 | V32: 89.8 | AC32: 1 | AD32: 0.4 | AE32: 63.4 | AG32: =6753.47943187+0.36116788*I32+0.01252571*N32-22.85359542*V32+0.00407811*AA32-0.00067349*E32 -> 6838.7119 | AH32: =A32*'Simple Linear Regression'!$B$18+'Simple Linear Regression'!$B$17 -> 7911.7805 | AI32: =7491.3971+0.0137554*N32-0.00058829*E32-34.3283*V32+0.30565*L32+54.6031*M32 -> 7786.1885 | AJ32: =7491.3971-0.00058829*E32+0.30565*L32+54.6031*M32+0.0137554*N32-34.3283*V32 -> 7786.1885 | AL32: =2192.59+2373.87*I32+0.0316653*N32-15.7623*V32+0.00202406*AA32-0.000740146*E32-0.00963493*(I32*N32) -> 7163.3413 | AM32: =5205.907083+122.0638992*I32+13.609808*(N32/1000)-1.245906883*AD32+0.7746840854*AE32-134.2474226*AC32-1547.125689*IF(AND(B32>=DATE(2020,3,20),B32<=DATE(2020,6,26)),1,0) -> 7890.891 | AN32: =IF(ISNUMBER(C33),C33,AN33)-0.8328750492*(AD34-AD33)+3.274150872*(AE34-AE33)+0.7954612886*((IF(ISNUMBER(C33),C33,AN33)-IF(ISNUMBER(C32),C32,AN32))-(-0.8328750492*(AD33-AD32)+3.274150872*(AE33-AE32)))-1.394571582*AO33+0.4181414112*AO32 -> 7737.847 | AP32: =AQ32+AR31+'ARIMAX(1,1,1) Model'!$C$19*(AR31-AR30)+'ARIMAX(1,1,1) Model'!$C$20*AS31 -> 7308.4749 | AQ32: ='ARIMAX(1,1,1) Model'!$C$6*I32+'ARIMAX(1,1,1) Model'!$C$7*N32/1000+'ARIMAX(1,1,1) Model'!$C$8*AD32+'ARIMAX(1,1,1) Model'!$C$9*AE32+'ARIMAX(1,1,1) Model'!$C$10*AC32+'ARIMAX(1,1,1) Model'!$C$11*IF(AND(B32>='ARIMAX(1,1,1) Model'!$C$25,B32<='ARIMAX(1,1,1) Model'!$C$26),1,0)+'ARIMAX(1,1,1) Model'!$C$12*E32/1000+'ARIMAX(1,1,1) Model'!$C$13*V32+'ARIMAX(1,1,1) Model'!$C$14*A32+'ARIMAX(1,1,1) Model'!$C$15*SIN(2*PI()*A32/'ARIMAX(1,1,1) Model'!$C$24)+'ARIMAX(1,1,1) Model'!$C$16*COS(2*PI()*A32/'ARIMAX(1,1,1) Model'!$C$24)+'ARIMAX(1,1,1) Model'!$C$17*SIN(4*PI()*A32/'ARIMAX(1,1,1) Model'!$C$24)+'ARIMAX(1,1,1) Model'!$C$18*COS(4*PI()*A32/'ARIMAX(1,1,1) Model'!$C$24) -> 1177.1996 | AR32: =IF(ISNUMBER(C32),C32,AP32)-AQ32 -> 5815.8004 | AS32: =IF(ISNUMBER(C32),C32-AP32,0) -> -315.4749
... A47: 46 | B47: 33592 | C47: 7447 | E47: 475000 | G47: 19.204 | H47: 18.306 | I47: 1.075 | J47: 6205.937 | L47: 795 | M47: 12.576 | N47: 188445 | O47: 3976 | P47: 818093 | V47: 88.3 | AC47: 0 | AD47: 161.3 | AE47: 0.6 | AG47: =6753.47943187+0.36116788*I47+0.01252571*N47-22.85359542*V47+0.00407811*AA47-0.00067349*E47 -> 6776.3949 | AH47: =A47*'Simple Linear Regression'!$B$18+'Simple Linear Regression'!$B$17 -> 7924.5761 | AI47: =7491.3971+0.0137554*N47-0.00058829*E47-34.3283*V47+0.30565*L47+54.6031*M47 -> 7702.5871 | AJ47: =7491.3971-0.00058829*E47+0.30565*L47+54.6031*M47+0.0137554*N47-34.3283*V47 -> 7702.5871 | AL47: =2192.59+2373.87*I47+0.0316653*N47-15.7623*V47+0.00202406*AA47-0.000740146*E47-0.00963493*(I47*N47) -> 7016.4588 | AM47: =5205.907083+122.0638992*I47+13.609808*(N47/1000)-1.245906883*AD47+0.7746840854*AE47-134.2474226*AC47-1547.125689*IF(AND(B47>=DATE(2020,3,20),B47<=DATE(2020,6,26)),1,0) -> 7701.3261 | AN47: =IF(ISNUMBER(C48),C48,AN48)-0.8328750492*(AD49-AD48)+3.274150872*(AE49-AE48)+0.7954612886*((IF(ISNUMBER(C48),C48,AN48)-IF(ISNUMBER(C47),C47,AN47))-(-0.8328750492*(AD48-AD47)+3.274150872*(AE48-AE47)))-1.394571582*AO48+0.4181414112*AO47 -> 6953.021 | AP47: =AQ47+AR46+'ARIMAX(1,1,1) Model'!$C$19*(AR46-AR45)+'ARIMAX(1,1,1) Model'!$C$20*AS46 -> 7055.1412 | AQ47: ='ARIMAX(1,1,1) Model'!$C$6*I47+'ARIMAX(1,1,1) Model'!$C$7*N47/1000+'ARIMAX(1,1,1) Model'!$C$8*AD47+'ARIMAX(1,1,1) Model'!$C$9*AE47+'ARIMAX(1,1,1) Model'!$C$10*AC47+'ARIMAX(1,1,1) Model'!$C$11*IF(AND(B47>='ARIMAX(1,1,1) Model'!$C$25,B47<='ARIMAX(1,1,1) Model'!$C$26),1,0)+'ARIMAX(1,1,1) Model'!$C$12*E47/1000+'ARIMAX(1,1,1) Model'!$C$13*V47+'ARIMAX(1,1,1) Model'!$C$14*A47+'ARIMAX(1,1,1) Model'!$C$15*SIN(2*PI()*A47/'ARIMAX(1,1,1) Model'!$C$24)+'ARIMAX(1,1,1) Model'!$C$16*COS(2*PI()*A47/'ARIMAX(1,1,1) Model'!$C$24)+'ARIMAX(1,1,1) Model'!$C$17*SIN(4*PI()*A47/'ARIMAX(1,1,1) Model'!$C$24)+'ARIMAX(1,1,1) Model'!$C$18*COS(4*PI()*A47/'ARIMAX(1,1,1) Model'!$C$24) -> 950.51702 | AR47: =IF(ISNUMBER(C47),C47,AP47)-AQ47 -> 6496.483 | AS47: =IF(ISNUMBER(C47),C47-AP47,0) -> 391.85881
A48: 47 | B48: 33599 | C48: 7186 | E48: 436000 | G48: 18.6775 | H48: 17.7275 | I48: 1.063 | J48: 6205.937 | L48: 795 | M48: 12.576 | N48: 188445 | O48: 3976 | P48: 818093 | U48: 28 | V48: 88.3 | AC48: 1 | AD48: 145.4 | AE48: 1.4 | AG48: =6753.47943187+0.36116788*I48+0.01252571*N48-22.85359542*V48+0.00407811*AA48-0.00067349*E48 -> 6802.6567 | AH48: =A48*'Simple Linear Regression'!$B$18+'Simple Linear Regression'!$B$17 -> 7925.4291 | AI48: =7491.3971+0.0137554*N48-0.00058829*E48-34.3283*V48+0.30565*L48+54.6031*M48 -> 7725.5305 | AJ48: =7491.3971-0.00058829*E48+0.30565*L48+54.6031*M48+0.0137554*N48-34.3283*V48 -> 7725.5305 | AL48: =2192.59+2373.87*I48+0.0316653*N48-15.7623*V48+0.00202406*AA48-0.000740146*E48-0.00963493*(I48*N48) -> 7038.6259 | AM48: =5205.907083+122.0638992*I48+13.609808*(N48/1000)-1.245906883*AD48+0.7746840854*AE48-134.2474226*AC48-1547.125689*IF(AND(B48>=DATE(2020,3,20),B48<=DATE(2020,6,26)),1,0) -> 7586.0436 | AN48: =IF(ISNUMBER(C49),C49,AN49)-0.8328750492*(AD50-AD49)+3.274150872*(AE50-AE49)+0.7954612886*((IF(ISNUMBER(C49),C49,AN49)-IF(ISNUMBER(C48),C48,AN48))-(-0.8328750492*(AD49-AD48)+3.274150872*(AE49-AE48)))-1.394571582*AO49+0.4181414112*AO48 -> 6231.4014 | AP48: =AQ48+AR47+'ARIMAX(1,1,1) Model'!$C$19*(AR47-AR46)+'ARIMAX(1,1,1) Model'!$C$20*AS47 -> 6985.4826 | AQ48: ='ARIMAX(1,1,1) Model'!$C$6*I48+'ARIMAX(1,1,1) Model'!$C$7*N48/1000+'ARIMAX(1,1,1) Model'!$C$8*AD48+'ARIMAX(1,1,1) Model'!$C$9*AE48+'ARIMAX(1,1,1) Model'!$C$10*AC48+'ARIMAX(1,1,1) Model'!$C$11*IF(AND(B48>='ARIMAX(1,1,1) Model'!$C$25,B48<='ARIMAX(1,1,1) Model'!$C$26),1,0)+'ARIMAX(1,1,1) Model'!$C$12*E48/1000+'ARIMAX(1,1,1) Model'!$C$13*V48+'ARIMAX(1,1,1) Model'!$C$14*A48+'ARIMAX(1,1,1) Model'!$C$15*SIN(2*PI()*A48/'ARIMAX(1,1,1) Model'!$C$24)+'ARIMAX(1,1,1) Model'!$C$16*COS(2*PI()*A48/'ARIMAX(1,1,1) Model'!$C$24)+'ARIMAX(1,1,1) Model'!$C$17*SIN(4*PI()*A48/'ARIMAX(1,1,1) Model'!$C$24)+'ARIMAX(1,1,1) Model'!$C$18*COS(4*PI()*A48/'ARIMAX(1,1,1) Model'!$C$24) -> 832.24452 | AR48: =IF(ISNUMBER(C48),C48,AP48)-AQ48 -> 6353.7555 | AS48: =IF(ISNUMBER(C48),C48-AP48,0) -> 200.5174
A49: 48 | B49: 33606 | C49: 6642 | E49: 441000 | G49: 19.1075 | H49: 18.175 | I49: 1.053 | J49: 6205.937 | L49: 795 | M49: 12.576 | N49: 188445 | O49: 3976 | P49: 818093 | U49: 28 | V49: 88.3 | AC49: 1 | AD49: 155.2 | AE49: 0 | AG49: =6753.47943187+0.36116788*I49+0.01252571*N49-22.85359542*V49+0.00407811*AA49-0.00067349*E49 -> 6799.2856 | AH49: =A49*'Simple Linear Regression'!$B$18+'Simple Linear Regression'!$B$17 -> 7926.2821 | AI49: =7491.3971+0.0137554*N49-0.00058829*E49-34.3283*V49+0.30565*L49+54.6031*M49 -> 7722.589 | AJ49: =7491.3971-0.00058829*E49+0.30565*L49+54.6031*M49+0.0137554*N49-34.3283*V49 -> 7722.589 | AL49: =2192.59+2373.87*I49+0.0316653*N49-15.7623*V49+0.00202406*AA49-0.000740146*E49-0.00963493*(I49*N49) -> 7029.343 | AM49: =5205.907083+122.0638992*I49+13.609808*(N49/1000)-1.245906883*AD49+0.7746840854*AE49-134.2474226*AC49-1547.125689*IF(AND(B49>=DATE(2020,3,20),B49<=DATE(2020,6,26)),1,0) -> 7571.5285 | AN49: =IF(ISNUMBER(C50),C50,AN50)-0.8328750492*(AD51-AD50)+3.274150872*(AE51-AE50)+0.7954612886*((IF(ISNUMBER(C50),C50,AN50)-IF(ISNUMBER(C49),C49,AN49))-(-0.8328750492*(AD50-AD49)+3.274150872*(AE50-AE49)))-1.394571582*AO50+0.4181414112*AO49 -> 6857.2843 | AP49: =AQ49+AR48+'ARIMAX(1,1,1) Model'!$C$19*(AR48-AR47)+'ARIMAX(1,1,1) Model'!$C$20*AS48 -> 6963.8213 | AQ49: ='ARIMAX(1,1,1) Model'!$C$6*I49+'ARIMAX(1,1,1) Model'!$C$7*N49/1000+'ARIMAX(1,1,1) Model'!$C$8*AD49+'ARIMAX(1,1,1) Model'!$C$9*AE49+'ARIMAX(1,1,1) Model'!$C$10*AC49+'ARIMAX(1,1,1) Model'!$C$11*IF(AND(B49>='ARIMAX(1,1,1) Model'!$C$25,B49<='ARIMAX(1,1,1) Model'!$C$26),1,0)+'ARIMAX(1,1,1) Model'!$C$12*E49/1000+'ARIMAX(1,1,1) Model'!$C$13*V49+'ARIMAX(1,1,1) Model'!$C$14*A49+'ARIMAX(1,1,1) Model'!$C$15*SIN(2*PI()*A49/'ARIMAX(1,1,1) Model'!$C$24)+'ARIMAX(1,1,1) Model'!$C$16*COS(2*PI()*A49/'ARIMAX(1,1,1) Model'!$C$24)+'ARIMAX(1,1,1) Model'!$C$17*SIN(4*PI()*A49/'ARIMAX(1,1,1) Model'!$C$24)+'ARIMAX(1,1,1) Model'!$C$18*COS(4*PI()*A49/'ARIMAX(1,1,1) Model'!$C$24) -> 804.4687 | AR49: =IF(ISNUMBER(C49),C49,AP49)-AQ49 -> 5837.5313 | AS49: =IF(ISNUMBER(C49),C49-AP49,0) -> -321.82133
A50: 49 | B50: 33613 | C50: 6788 | E50: 432000 | G50: 18.412 | H50: 17.772 | I50: 1.042 | J50: 6205.937 | L50: 808 | M50: 12.576 | N50: 188445 | O50: 4003.6 | P50: 818093 | U50: 28 | V50: 83.4 | AC50: 0 | AD50: 140.8 | AE50: 0 | AG50: =6753.47943187+0.36116788*I50+0.01252571*N50-22.85359542*V50+0.00407811*AA50-0.00067349*E50 -> 6917.3257 | AH50: =A50*'Simple Linear Regression'!$B$18+'Simple Linear Regression'!$B$17 -> 7927.1352 | AI50: =7491.3971+0.0137554*N50-0.00058829*E50-34.3283*V50+0.30565*L50+54.6031*M50 -> 7900.0657 | AJ50: =7491.3971-0.00058829*E50+0.30565*L50+54.6031*M50+0.0137554*N50-34.3283*V50 -> 7900.0657 | AL50: =2192.59+2373.87*I50+0.0316653*N50-15.7623*V50+0.00202406*AA50-0.000740146*E50-0.00963493*(I50*N50) -> 7107.0992 | AM50: =5205.907083+122.0638992*I50+13.609808*(N50/1000)-1.245906883*AD50+0.7746840854*AE50-134.2474226*AC50-1547.125689*IF(AND(B50>=DATE(2020,3,20),B50<=DATE(2020,6,26)),1,0) -> 7722.3742 | AN50: =IF(ISNUMBER(C51),C51,AN51)-0.8328750492*(AD52-AD51)+3.274150872*(AE52-AE51)+0.7954612886*((IF(ISNUMBER(C51),C51,AN51)-IF(ISNUMBER(C50),C50,AN50))-(-0.8328750492*(AD51-AD50)+3.274150872*(AE51-AE50)))-1.394571582*AO51+0.4181414112*AO50 -> 6803.9562 | AP50: =AQ50+AR49+'ARIMAX(1,1,1) Model'!$C$19*(AR49-AR48)+'ARIMAX(1,1,1) Model'!$C$20*AS49 -> 6887.2394 | AQ50: ='ARIMAX(1,1,1) Model'!$C$6*I50+'ARIMAX(1,1,1) Model'!$C$7*N50/1000+'ARIMAX(1,1,1) Model'!$C$8*AD50+'ARIMAX(1,1,1) Model'!$C$9*AE50+'ARIMAX(1,1,1) Model'!$C$10*AC50+'ARIMAX(1,1,1) Model'!$C$11*IF(AND(B50>='ARIMAX(1,1,1) Model'!$C$25,B50<='ARIMAX(1,1,1) Model'!$C$26),1,0)+'ARIMAX(1,1,1) Model'!$C$12*E50/1000+'ARIMAX(1,1,1) Model'!$C$13*V50+'ARIMAX(1,1,1) Model'!$C$14*A50+'ARIMAX(1,1,1) Model'!$C$15*SIN(2*PI()*A50/'ARIMAX(1,1,1) Model'!$C$24)+'ARIMAX(1,1,1) Model'!$C$16*COS(2*PI()*A50/'ARIMAX(1,1,1) Model'!$C$24)+'ARIMAX(1,1,1) Model'!$C$17*SIN(4*PI()*A50/'ARIMAX(1,1,1) Model'!$C$24)+'ARIMAX(1,1,1) Model'!$C$18*COS(4*PI()*A50/'ARIMAX(1,1,1) Model'!$C$24) -> 810.39021 | AR50: =IF(ISNUMBER(C50),C50,AP50)-AQ50 -> 5977.6098 | AS50: =IF(ISNUMBER(C50),C50-AP50,0) -> -99.239381
A51: 50 | B51: 33620 | C51: 6783 | E51: 440000 | G51: 18.81 | H51: 18.37 | I51: 1.026 | J51: 6205.937 | L51: 808 | M51: 12.658 | N51: 169693 | O51: 4003.6 | P51: 818093 | U51: 28 | V51: 83.4 | AC51: 0 | AD51: 185.6 | AE51: 0 | AG51: =6753.47943187+0.36116788*I51+0.01252571*N51-22.85359542*V51+0.00407811*AA51-0.00067349*E51 -> 6677.0498 | AH51: =A51*'Simple Linear Regression'!$B$18+'Simple Linear Regression'!$B$17 -> 7927.9882 | AI51: =7491.3971+0.0137554*N51-0.00058829*E51-34.3283*V51+0.30565*L51+54.6031*M51 -> 7641.8956 | AJ51: =7491.3971-0.00058829*E51+0.30565*L51+54.6031*M51+0.0137554*N51-34.3283*V51 -> 7641.8956 | AL51: =2192.59+2373.87*I51+0.0316653*N51-15.7623*V51+0.00202406*AA51-0.000740146*E51-0.00963493*(I51*N51) -> 6683.8307 | AM51: =5205.907083+122.0638992*I51+13.609808*(N51/1000)-1.245906883*AD51+0.7746840854*AE51-134.2474226*AC51-1547.125689*IF(AND(B51>=DATE(2020,3,20),B51<=DATE(2020,6,26)),1,0) -> 7409.3935 | AN51: =IF(ISNUMBER(C52),C52,AN52)-0.8328750492*(AD53-AD52)+3.274150872*(AE53-AE52)+0.7954612886*((IF(ISNUMBER(C52),C52,AN52)-IF(ISNUMBER(C51),C51,AN51))-(-0.8328750492*(AD52-AD51)+3.274150872*(AE52-AE51)))-1.394571582*AO52+0.4181414112*AO51 -> 7272.1407 | AP51: =AQ51+AR50+'ARIMAX(1,1,1) Model'!$C$19*(AR50-AR49)+'ARIMAX(1,1,1) Model'!$C$20*AS50 -> 6882.866 | AQ51: ='ARIMAX(1,1,1) Model'!$C$6*I51+'ARIMAX(1,1,1) Model'!$C$7*N51/1000+'ARIMAX(1,1,1) Model'!$C$8*AD51+'ARIMAX(1,1,1) Model'!$C$9*AE51+'ARIMAX(1,1,1) Model'!$C$10*AC51+'ARIMAX(1,1,1) Model'!$C$11*IF(AND(B51>='ARIMAX(1,1,1) Model'!$C$25,B51<='ARIMAX(1,1,1) Model'!$C$26),1,0)+'ARIMAX(1,1,1) Model'!$C$12*E51/1000+'ARIMAX(1,1,1) Model'!$C$13*V51+'ARIMAX(1,1,1) Model'!$C$14*A51+'ARIMAX(1,1,1) Model'!$C$15*SIN(2*PI()*A51/'ARIMAX(1,1,1) Model'!$C$24)+'ARIMAX(1,1,1) Model'!$C$16*COS(2*PI()*A51/'ARIMAX(1,1,1) Model'!$C$24)+'ARIMAX(1,1,1) Model'!$C$17*SIN(4*PI()*A51/'ARIMAX(1,1,1) Model'!$C$24)+'ARIMAX(1,1,1) Model'!$C$18*COS(4*PI()*A51/'ARIMAX(1,1,1) Model'!$C$24) -> 802.27038 | AR51: =IF(ISNUMBER(C51),C51,AP51)-AQ51 -> 5980.7296 | AS51: =IF(ISNUMBER(C51),C51-AP51,0) -> -99.865985
A52: 51 | B52: 33627 | C52: 7037 | E52: 443000 | G52: 18.656 | H52: 18.112 | I52: 1.014 | J52: 6205.937 | L52: 808 | M52: 12.658 | N52: 169693 | O52: 4003.6 | P52: 818093 | U52: 28 | V52: 83.4 | AC52: 0 | AD52: 191.3 | AE52: 0 | AG52: =6753.47943187+0.36116788*I52+0.01252571*N52-22.85359542*V52+0.00407811*AA52-0.00067349*E52 -> 6675.025 | AH52: =A52*'Simple Linear Regression'!$B$18+'Simple Linear Regression'!$B$17 -> 7928.8412 | AI52: =7491.3971+0.0137554*N52-0.00058829*E52-34.3283*V52+0.30565*L52+54.6031*M52 -> 7640.1307 | AJ52: =7491.3971-0.00058829*E52+0.30565*L52+54.6031*M52+0.0137554*N52-34.3283*V52 -> 7640.1307 | AL52: =2192.59+2373.87*I52+0.0316653*N52-15.7623*V52+0.00202406*AA52-0.000740146*E52-0.00963493*(I52*N52) -> 6672.7435 | AM52: =5205.907083+122.0638992*I52+13.609808*(N52/1000)-1.245906883*AD52+0.7746840854*AE52-134.2474226*AC52-1547.125689*IF(AND(B52>=DATE(2020,3,20),B52<=DATE(2020,6,26)),1,0) -> 7400.827 | AN52: =IF(ISNUMBER(C53),C53,AN53)-0.8328750492*(AD54-AD53)+3.274150872*(AE54-AE53)+0.7954612886*((IF(ISNUMBER(C53),C53,AN53)-IF(ISNUMBER(C52),C52,AN52))-(-0.8328750492*(AD53-AD52)+3.274150872*(AE53-AE52)))-1.394571582*AO53+0.4181414112*AO52 -> 7148.5888 | AP52: =AQ52+AR51+'ARIMAX(1,1,1) Model'!$C$19*(AR51-AR50)+'ARIMAX(1,1,1) Model'!$C$20*AS51 -> 6864.5104 | AQ52: ='ARIMAX(1,1,1) Model'!$C$6*I52+'ARIMAX(1,1,1) Model'!$C$7*N52/1000+'ARIMAX(1,1,1) Model'!$C$8*AD52+'ARIMAX(1,1,1) Model'!$C$9*AE52+'ARIMAX(1,1,1) Model'!$C$10*AC52+'ARIMAX(1,1,1) Model'!$C$11*IF(AND(B52>='ARIMAX(1,1,1) Model'!$C$25,B52<='ARIMAX(1,1,1) Model'!$C$26),1,0)+'ARIMAX(1,1,1) Model'!$C$12*E52/1000+'ARIMAX(1,1,1) Model'!$C$13*V52+'ARIMAX(1,1,1) Model'!$C$14*A52+'ARIMAX(1,1,1) Model'!$C$15*SIN(2*PI()*A52/'ARIMAX(1,1,1) Model'!$C$24)+'ARIMAX(1,1,1) Model'!$C$16*COS(2*PI()*A52/'ARIMAX(1,1,1) Model'!$C$24)+'ARIMAX(1,1,1) Model'!$C$17*SIN(4*PI()*A52/'ARIMAX(1,1,1) Model'!$C$24)+'ARIMAX(1,1,1) Model'!$C$18*COS(4*PI()*A52/'ARIMAX(1,1,1) Model'!$C$24) -> 793.58879 | AR52: =IF(ISNUMBER(C52),C52,AP52)-AQ52 -> 6243.4112 | AS52: =IF(ISNUMBER(C52),C52-AP52,0) -> 172.48959
A53: 52 | B53: 33634 | C53: 7112 | E53: 441000 | G53: 19.048 | H53: 18.276 | I53: 1.006 | J53: 6205.937 | L53: 808 | M53: 12.658 | N53: 169693 | O53: 4003.6 | P53: 818093 | U53: 28 | V53: 83.4 | AC53: 0 | AD53: 156.1 | AE53: 0 | AG53: =6753.47943187+0.36116788*I53+0.01252571*N53-22.85359542*V53+0.00407811*AA53-0.00067349*E53 -> 6676.3691 | AH53: =A53*'Simple Linear Regression'!$B$18+'Simple Linear Regression'!$B$17 -> 7929.6943 | AI53: =7491.3971+0.0137554*N53-0.00058829*E53-34.3283*V53+0.30565*L53+54.6031*M53 -> 7641.3073 | AJ53: =7491.3971-0.00058829*E53+0.30565*L53+54.6031*M53+0.0137554*N53-34.3283*V53 -> 7641.3073 | AL53: =2192.59+2373.87*I53+0.0316653*N53-15.7623*V53+0.00202406*AA53-0.000740146*E53-0.00963493*(I53*N53) -> 6668.3127 | AM53: =5205.907083+122.0638992*I53+13.609808*(N53/1000)-1.245906883*AD53+0.7746840854*AE53-134.2474226*AC53-1547.125689*IF(AND(B53>=DATE(2020,3,20),B53<=DATE(2020,6,26)),1,0) -> 7443.7065 | AN53: =IF(ISNUMBER(C54),C54,AN54)-0.8328750492*(AD55-AD54)+3.274150872*(AE55-AE54)+0.7954612886*((IF(ISNUMBER(C54),C54,AN54)-IF(ISNUMBER(C53),C53,AN53))-(-0.8328750492*(AD54-AD53)+3.274150872*(AE54-AE53)))-1.394571582*AO54+0.4181414112*AO53 -> 6970.4595 | AP53: =AQ53+AR52+'ARIMAX(1,1,1) Model'!$C$19*(AR52-AR51)+'ARIMAX(1,1,1) Model'!$C$20*AS52 -> 6882.7663 | AQ53: ='ARIMAX(1,1,1) Model'!$C$6*I53+'ARIMAX(1,1,1) Model'!$C$7*N53/1000+'ARIMAX(1,1,1) Model'!$C$8*AD53+'ARIMAX(1,1,1) Model'!$C$9*AE53+'ARIMAX(1,1,1) Model'!$C$10*AC53+'ARIMAX(1,1,1) Model'!$C$11*IF(AND(B53>='ARIMAX(1,1,1) Model'!$C$25,B53<='ARIMAX(1,1,1) Model'!$C$26),1,0)+'ARIMAX(1,1,1) Model'!$C$12*E53/1000+'ARIMAX(1,1,1) Model'!$C$13*V53+'ARIMAX(1,1,1) Model'!$C$14*A53+'ARIMAX(1,1,1) Model'!$C$15*SIN(2*PI()*A53/'ARIMAX(1,1,1) Model'!$C$24)+'ARIMAX(1,1,1) Model'!$C$16*COS(2*PI()*A53/'ARIMAX(1,1,1) Model'!$C$24)+'ARIMAX(1,1,1) Model'!$C$17*SIN(4*PI()*A53/'ARIMAX(1,1,1) Model'!$C$24)+'ARIMAX(1,1,1) Model'!$C$18*COS(4*PI()*A53/'ARIMAX(1,1,1) Model'!$C$24) -> 768.99038 | AR53: =IF(ISNUMBER(C53),C53,AP53)-AQ53 -> 6343.0096 | AS53: =IF(ISNUMBER(C53),C53-AP53,0) -> 229.23367
A54: 53 | B54: 33641 | C54: 7039 | E54: 440000 | G54: 19.424 | H54: 18.468 | I54: 0.995 | J54: 6264.54 | L54: 796 | M54: 12.658 | N54: 169693 | O54: 4020.5 | P54: 818093 | U54: 28 | V54: 83.7 | AC54: 0 | AD54: 155.8 | AE54: 0 | AG54: =6753.47943187+0.36116788*I54+0.01252571*N54-22.85359542*V54+0.00407811*AA54-0.00067349*E54 -> 6670.1826 | AH54: =A54*'Simple Linear Regression'!$B$18+'Simple Linear Regression'!$B$17 -> 7930.5473 | AI54: =7491.3971+0.0137554*N54-0.00058829*E54-34.3283*V54+0.30565*L54+54.6031*M54 -> 7627.9293 | AJ54: =7491.3971-0.00058829*E54+0.30565*L54+54.6031*M54+0.0137554*N54-34.3283*V54 -> 7627.9293 | AL54: =2192.59+2373.87*I54+0.0316653*N54-15.7623*V54+0.00202406*AA54-0.000740146*E54-0.00963493*(I54*N54) -> 6656.1964 | AM54: =5205.907083+122.0638992*I54+13.609808*(N54/1000)-1.245906883*AD54+0.7746840854*AE54-134.2474226*AC54-1547.125689*IF(AND(B54>=DATE(2020,3,20),B54<=DATE(2020,6,26)),1,0) -> 7442.7375 | AN54: =IF(ISNUMBER(C55),C55,AN55)-0.8328750492*(AD56-AD55)+3.274150872*(AE56-AE55)+0.7954612886*((IF(ISNUMBER(C55),C55,AN55)-IF(ISNUMBER(C54),C54,AN54))-(-0.8328750492*(AD55-AD54)+3.274150872*(AE55-AE54)))-1.394571582*AO55+0.4181414112*AO54 -> 6254.0907 | AP54: =AQ54+AR53+'ARIMAX(1,1,1) Model'!$C$19*(AR53-AR52)+'ARIMAX(1,1,1) Model'!$C$20*AS53 -> 6926.8932 | AQ54: ='ARIMAX(1,1,1) Model'!$C$6*I54+'ARIMAX(1,1,1) Model'!$C$7*N54/1000+'ARIMAX(1,1,1) Model'!$C$8*AD54+'ARIMAX(1,1,1) Model'!$C$9*AE54+'ARIMAX(1,1,1) Model'!$C$10*AC54+'ARIMAX(1,1,1) Model'!$C$11*IF(AND(B54>='ARIMAX(1,1,1) Model'!$C$25,B54<='ARIMAX(1,1,1) Model'!$C$26),1,0)+'ARIMAX(1,1,1) Model'!$C$12*E54/1000+'ARIMAX(1,1,1) Model'!$C$13*V54+'ARIMAX(1,1,1) Model'!$C$14*A54+'ARIMAX(1,1,1) Model'!$C$15*SIN(2*PI()*A54/'ARIMAX(1,1,1) Model'!$C$24)+'ARIMAX(1,1,1) Model'!$C$16*COS(2*PI()*A54/'ARIMAX(1,1,1) Model'!$C$24)+'ARIMAX(1,1,1) Model'!$C$17*SIN(4*PI()*A54/'ARIMAX(1,1,1) Model'!$C$24)+'ARIMAX(1,1,1) Model'!$C$18*COS(4*PI()*A54/'ARIMAX(1,1,1) Model'!$C$24) -> 780.49904 | AR54: =IF(ISNUMBER(C54),C54,AP54)-AQ54 -> 6258.501 | AS54: =IF(ISNUMBER(C54),C54-AP54,0) -> 112.10678
A55: 54 | B55: 33648 | C55: 6576 | E55: 445000 | G55: 19.492 | H55: 18.584 | I55: 1.004 | J55: 6264.54 | L55: 796 | M55: 12.658 | N55: 169693 | O55: 4020.5 | P55: 818093 | U55: 28 | V55: 83.7 | AC55: 0 | AD55: 170.1 | AE55: 0.5 | AG55: =6753.47943187+0.36116788*I55+0.01252571*N55-22.85359542*V55+0.00407811*AA55-0.00067349*E55 -> 6666.8184 | AH55: =A55*'Simple Linear Regression'!$B$18+'Simple Linear Regression'!$B$17 -> 7931.4003 | AI55: =7491.3971+0.0137554*N55-0.00058829*E55-34.3283*V55+0.30565*L55+54.6031*M55 -> 7624.9879 | AJ55: =7491.3971-0.00058829*E55+0.30565*L55+54.6031*M55+0.0137554*N55-34.3283*V55 -> 7624.9879 | AL55: =2192.59+2373.87*I55+0.0316653*N55-15.7623*V55+0.00202406*AA55-0.000740146*E55-0.00963493*(I55*N55) -> 6659.1457 | AM55: =5205.907083+122.0638992*I55+13.609808*(N55/1000)-1.245906883*AD55+0.7746840854*AE55-134.2474226*AC55-1547.125689*IF(AND(B55>=DATE(2020,3,20),B55<=DATE(2020,6,26)),1,0) -> 7426.407 | AN55: =IF(ISNUMBER(C56),C56,AN56)-0.8328750492*(AD57-AD56)+3.274150872*(AE57-AE56)+0.7954612886*((IF(ISNUMBER(C56),C56,AN56)-IF(ISNUMBER(C55),C55,AN55))-(-0.8328750492*(AD56-AD55)+3.274150872*(AE56-AE55)))-1.394571582*AO56+0.4181414112*AO55 -> 7318.002 | AP55: =AQ55+AR54+'ARIMAX(1,1,1) Model'!$C$19*(AR54-AR53)+'ARIMAX(1,1,1) Model'!$C$20*AS54 -> 6947.9951 | AQ55: ='ARIMAX(1,1,1) Model'!$C$6*I55+'ARIMAX(1,1,1) Model'!$C$7*N55/1000+'ARIMAX(1,1,1) Model'!$C$8*AD55+'ARIMAX(1,1,1) Model'!$C$9*AE55+'ARIMAX(1,1,1) Model'!$C$10*AC55+'ARIMAX(1,1,1) Model'!$C$11*IF(AND(B55>='ARIMAX(1,1,1) Model'!$C$25,B55<='ARIMAX(1,1,1) Model'!$C$26),1,0)+'ARIMAX(1,1,1) Model'!$C$12*E55/1000+'ARIMAX(1,1,1) Model'!$C$13*V55+'ARIMAX(1,1,1) Model'!$C$14*A55+'ARIMAX(1,1,1) Model'!$C$15*SIN(2*PI()*A55/'ARIMAX(1,1,1) Model'!$C$24)+'ARIMAX(1,1,1) Model'!$C$16*COS(2*PI()*A55/'ARIMAX(1,1,1) Model'!$C$24)+'ARIMAX(1,1,1) Model'!$C$17*SIN(4*PI()*A55/'ARIMAX(1,1,1) Model'!$C$24)+'ARIMAX(1,1,1) Model'!$C$18*COS(4*PI()*A55/'ARIMAX(1,1,1) Model'!$C$24) -> 798.64184 | AR55: =IF(ISNUMBER(C55),C55,AP55)-AQ55 -> 5777.3582 | AS55: =IF(ISNUMBER(C55),C55-AP55,0) -> -371.99507
A56: 55 | B56: 33655 | C56: 7002 | E56: 446000 | G56: 18.62 | H56: 17.74 | I56: 1.011 | J56: 6264.54 | L56: 796 | M56: 12.591 | N56: 172782 | O56: 4020.5 | P56: 818093 | U56: 28 | V56: 83.7 | AC56: 0 | AD56: 125 | AE56: 0.7 | AG56: =6753.47943187+0.36116788*I56+0.01252571*N56-22.85359542*V56+0.00407811*AA56-0.00067349*E56 -> 6704.8393 | AH56: =A56*'Simple Linear Regression'!$B$18+'Simple Linear Regression'!$B$17 -> 7932.2534 | AI56: =7491.3971+0.0137554*N56-0.00058829*E56-34.3283*V56+0.30565*L56+54.6031*M56 -> 7663.2316 | AJ56: =7491.3971-0.00058829*E56+0.30565*L56+54.6031*M56+0.0137554*N56-34.3283*V56 -> 7663.2316 | AL56: =2192.59+2373.87*I56+0.0316653*N56-15.7623*V56+0.00202406*AA56-0.000740146*E56-0.00963493*(I56*N56) -> 6731.3022 | AM56: =5205.907083+122.0638992*I56+13.609808*(N56/1000)-1.245906883*AD56+0.7746840854*AE56-134.2474226*AC56-1547.125689*IF(AND(B56>=DATE(2020,3,20),B56<=DATE(2020,6,26)),1,0) -> 7525.6474 | AN56: =IF(ISNUMBER(C57),C57,AN57)-0.8328750492*(AD58-AD57)+3.274150872*(AE58-AE57)+0.7954612886*((IF(ISNUMBER(C57),C57,AN57)-IF(ISNUMBER(C56),C56,AN56))-(-0.8328750492*(AD57-AD56)+3.274150872*(AE57-AE56)))-1.394571582*AO57+0.4181414112*AO56 -> 6591.7822 | AP56: =AQ56+AR55+'ARIMAX(1,1,1) Model'!$C$19*(AR55-AR54)+'ARIMAX(1,1,1) Model'!$C$20*AS55 -> 6858.0434 | AQ56: ='ARIMAX(1,1,1) Model'!$C$6*I56+'ARIMAX(1,1,1) Model'!$C$7*N56/1000+'ARIMAX(1,1,1) Model'!$C$8*AD56+'ARIMAX(1,1,1) Model'!$C$9*AE56+'ARIMAX(1,1,1) Model'!$C$10*AC56+'ARIMAX(1,1,1) Model'!$C$11*IF(AND(B56>='ARIMAX(1,1,1) Model'!$C$25,B56<='ARIMAX(1,1,1) Model'!$C$26),1,0)+'ARIMAX(1,1,1) Model'!$C$12*E56/1000+'ARIMAX(1,1,1) Model'!$C$13*V56+'ARIMAX(1,1,1) Model'!$C$14*A56+'ARIMAX(1,1,1) Model'!$C$15*SIN(2*PI()*A56/'ARIMAX(1,1,1) Model'!$C$24)+'ARIMAX(1,1,1) Model'!$C$16*COS(2*PI()*A56/'ARIMAX(1,1,1) Model'!$C$24)+'ARIMAX(1,1,1) Model'!$C$17*SIN(4*PI()*A56/'ARIMAX(1,1,1) Model'!$C$24)+'ARIMAX(1,1,1) Model'!$C$18*COS(4*PI()*A56/'ARIMAX(1,1,1) Model'!$C$24) -> 792.78523 | AR56: =IF(ISNUMBER(C56),C56,AP56)-AQ56 -> 6209.2148 | AS56: =IF(ISNUMBER(C56),C56-AP56,0) -> 143.95664
A57: 56 | B57: 33662 | C57: 6770 | E57: 436000 | G57: 18.514 | H57: 17.422 | I57: 1.014 | J57: 6264.54 | L57: 796 | M57: 12.591 | N57: 172782 | O57: 4020.5 | P57: 818093 | U57: 28 | V57: 83.7 | AC57: 0 | AD57: 113.2 | AE57: 0 | AG57: =6753.47943187+0.36116788*I57+0.01252571*N57-22.85359542*V57+0.00407811*AA57-0.00067349*E57 -> 6711.5753 | AH57: =A57*'Simple Linear Regression'!$B$18+'Simple Linear Regression'!$B$17 -> 7933.1064 | AI57: =7491.3971+0.0137554*N57-0.00058829*E57-34.3283*V57+0.30565*L57+54.6031*M57 -> 7669.1145 | AJ57: =7491.3971-0.00058829*E57+0.30565*L57+54.6031*M57+0.0137554*N57-34.3283*V57 -> 7669.1145 | AL57: =2192.59+2373.87*I57+0.0316653*N57-15.7623*V57+0.00202406*AA57-0.000740146*E57-0.00963493*(I57*N57) -> 6740.831 | AM57: =5205.907083+122.0638992*I57+13.609808*(N57/1000)-1.245906883*AD57+0.7746840854*AE57-134.2474226*AC57-1547.125689*IF(AND(B57>=DATE(2020,3,20),B57<=DATE(2020,6,26)),1,0) -> 7540.1731 | AN57: =IF(ISNUMBER(C58),C58,AN58)-0.8328750492*(AD59-AD58)+3.274150872*(AE59-AE58)+0.7954612886*((IF(ISNUMBER(C58),C58,AN58)-IF(ISNUMBER(C57),C57,AN57))-(-0.8328750492*(AD58-AD57)+3.274150872*(AE58-AE57)))-1.394571582*AO58+0.4181414112*AO57 -> 7162.3898 | AP57: =AQ57+AR56+'ARIMAX(1,1,1) Model'!$C$19*(AR56-AR55)+'ARIMAX(1,1,1) Model'!$C$20*AS56 -> 6942.7045 | AQ57: ='ARIMAX(1,1,1) Model'!$C$6*I57+'ARIMAX(1,1,1) Model'!$C$7*N57/1000+'ARIMAX(1,1,1) Model'!$C$8*AD57+'ARIMAX(1,1,1) Model'!$C$9*AE57+'ARIMAX(1,1,1) Model'!$C$10*AC57+'ARIMAX(1,1,1) Model'!$C$11*IF(AND(B57>='ARIMAX(1,1,1) Model'!$C$25,B57<='ARIMAX(1,1,1) Model'!$C$26),1,0)+'ARIMAX(1,1,1) Model'!$C$12*E57/1000+'ARIMAX(1,1,1) Model'!$C$13*V57+'ARIMAX(1,1,1) Model'!$C$14*A57+'ARIMAX(1,1,1) Model'!$C$15*SIN(2*PI()*A57/'ARIMAX(1,1,1) Model'!$C$24)+'ARIMAX(1,1,1) Model'!$C$16*COS(2*PI()*A57/'ARIMAX(1,1,1) Model'!$C$24)+'ARIMAX(1,1,1) Model'!$C$17*SIN(4*PI()*A57/'ARIMAX(1,1,1) Model'!$C$24)+'ARIMAX(1,1,1) Model'!$C$18*COS(4*PI()*A57/'ARIMAX(1,1,1) Model'!$C$24) -> 820.943 | AR57: =IF(ISNUMBER(C57),C57,AP57)-AQ57 -> 5949.057 | AS57: =IF(ISNUMBER(C57),C57-AP57,0) -> -172.70446
A58: 57 | B58: 33669 | C58: 7002 | E58: 444000 | G58: 18.552 | H58: 17.282 | I58: 1.012 | J58: 6264.54 | L58: 796 | M58: 12.591 | N58: 172782 | O58: 4020.5 | P58: 818093 | U58: 28 | V58: 86.6 | AA58: 253530 | AC58: 0 | AD58: 104.3 | AE58: 1.5 | AG58: =6753.47943187+0.36116788*I58+0.01252571*N58-22.85359542*V58+0.00407811*AA58-0.00067349*E58 -> 7673.8345 | AH58: =A58*'Simple Linear Regression'!$B$18+'Simple Linear Regression'!$B$17 -> 7933.9595 | AI58: =7491.3971+0.0137554*N58-0.00058829*E58-34.3283*V58+0.30565*L58+54.6031*M58 -> 7564.8561 | AJ58: =7491.3971-0.00058829*E58+0.30565*L58+54.6031*M58+0.0137554*N58-34.3283*V58 -> 7564.8561 | AL58: =2192.59+2373.87*I58+0.0316653*N58-15.7623*V58+0.00202406*AA58-0.000740146*E58-0.00963493*(I58*N58) -> 7200.9408 | AM58: =5205.907083+122.0638992*I58+13.609808*(N58/1000)-1.245906883*AD58+0.7746840854*AE58-134.2474226*AC58-1547.125689*IF(AND(B58>=DATE(2020,3,20),B58<=DATE(2020,6,26)),1,0) -> 7552.1795 | AN58: =IF(ISNUMBER(C59),C59,AN59)-0.8328750492*(AD60-AD59)+3.274150872*(AE60-AE59)+0.7954612886*((IF(ISNUMBER(C59),C59,AN59)-IF(ISNUMBER(C58),C58,AN58))-(-0.8328750492*(AD59-AD58)+3.274150872*(AE59-AE58)))-1.394571582*AO59+0.4181414112*AO58 -> 6647.705 | AP58: =AQ58+AR57+'ARIMAX(1,1,1) Model'!$C$19*(AR57-AR56)+'ARIMAX(1,1,1) Model'!$C$20*AS57 -> 6980.0546 | AQ58: ='ARIMAX(1,1,1) Model'!$C$6*I58+'ARIMAX(1,1,1) Model'!$C$7*N58/1000+'ARIMAX(1,1,1) Model'!$C$8*AD58+'ARIMAX(1,1,1) Model'!$C$9*AE58+'ARIMAX(1,1,1) Model'!$C$10*AC58+'ARIMAX(1,1,1) Model'!$C$11*IF(AND(B58>='ARIMAX(1,1,1) Model'!$C$25,B58<='ARIMAX(1,1,1) Model'!$C$26),1,0)+'ARIMAX(1,1,1) Model'!$C$12*E58/1000+'ARIMAX(1,1,1) Model'!$C$13*V58+'ARIMAX(1,1,1) Model'!$C$14*A58+'ARIMAX(1,1,1) Model'!$C$15*SIN(2*PI()*A58/'ARIMAX(1,1,1) Model'!$C$24)+'ARIMAX(1,1,1) Model'!$C$16*COS(2*PI()*A58/'ARIMAX(1,1,1) Model'!$C$24)+'ARIMAX(1,1,1) Model'!$C$17*SIN(4*PI()*A58/'ARIMAX(1,1,1) Model'!$C$24)+'ARIMAX(1,1,1) Model'!$C$18*COS(4*PI()*A58/'ARIMAX(1,1,1) Model'!$C$24) -> 900.92279 | AR58: =IF(ISNUMBER(C58),C58,AP58)-AQ58 -> 6101.0772 | AS58: =IF(ISNUMBER(C58),C58-AP58,0) -> 21.945395
A59: 58 | B59: 33676 | C59: 6806 | E59: 421000 | G59: 18.758 | H59: 17.396 | I59: 1.013 | J59: 6264.54 | L59: 710 | M59: 12.591 | N59: 172782 | O59: 4084.7 | P59: 818093 | U59: 28 | V59: 86.6 | AA59: 253530 | AC59: 0 | AD59: 123.5 | AE59: 2 | AG59: =6753.47943187+0.36116788*I59+0.01252571*N59-22.85359542*V59+0.00407811*AA59-0.00067349*E59 -> 7689.3251 | AH59: =A59*'Simple Linear Regression'!$B$18+'Simple Linear Regression'!$B$17 -> 7934.8125 | AI59: =7491.3971+0.0137554*N59-0.00058829*E59-34.3283*V59+0.30565*L59+54.6031*M59 -> 7552.1009 | AJ59: =7491.3971-0.00058829*E59+0.30565*L59+54.6031*M59+0.0137554*N59-34.3283*V59 -> 7552.1009 | AL59: =2192.59+2373.87*I59+0.0316653*N59-15.7623*V59+0.00202406*AA59-0.000740146*E59-0.00963493*(I59*N59) -> 7218.6733 | AM59: =5205.907083+122.0638992*I59+13.609808*(N59/1000)-1.245906883*AD59+0.7746840854*AE59-134.2474226*AC59-1547.125689*IF(AND(B59>=DATE(2020,3,20),B59<=DATE(2020,6,26)),1,0) -> 7528.7675 | AN59: =IF(ISNUMBER(C60),C60,AN60)-0.8328750492*(AD61-AD60)+3.274150872*(AE61-AE60)+0.7954612886*((IF(ISNUMBER(C60),C60,AN60)-IF(ISNUMBER(C59),C59,AN59))-(-0.8328750492*(AD60-AD59)+3.274150872*(AE60-AE59)))-1.394571582*AO60+0.4181414112*AO59 -> 7562.903 | AP59: =AQ59+AR58+'ARIMAX(1,1,1) Model'!$C$19*(AR58-AR57)+'ARIMAX(1,1,1) Model'!$C$20*AS58 -> 7074.1228 | AQ59: ='ARIMAX(1,1,1) Model'!$C$6*I59+'ARIMAX(1,1,1) Model'!$C$7*N59/1000+'ARIMAX(1,1,1) Model'!$C$8*AD59+'ARIMAX(1,1,1) Model'!$C$9*AE59+'ARIMAX(1,1,1) Model'!$C$10*AC59+'ARIMAX(1,1,1) Model'!$C$11*IF(AND(B59>='ARIMAX(1,1,1) Model'!$C$25,B59<='ARIMAX(1,1,1) Model'!$C$26),1,0)+'ARIMAX(1,1,1) Model'!$C$12*E59/1000+'ARIMAX(1,1,1) Model'!$C$13*V59+'ARIMAX(1,1,1) Model'!$C$14*A59+'ARIMAX(1,1,1) Model'!$C$15*SIN(2*PI()*A59/'ARIMAX(1,1,1) Model'!$C$24)+'ARIMAX(1,1,1) Model'!$C$16*COS(2*PI()*A59/'ARIMAX(1,1,1) Model'!$C$24)+'ARIMAX(1,1,1) Model'!$C$17*SIN(4*PI()*A59/'ARIMAX(1,1,1) Model'!$C$24)+'ARIMAX(1,1,1) Model'!$C$18*COS(4*PI()*A59/'ARIMAX(1,1,1) Model'!$C$24) -> 977.9715 | AR59: =IF(ISNUMBER(C59),C59,AP59)-AQ59 -> 5828.0285 | AS59: =IF(ISNUMBER(C59),C59-AP59,0) -> -268.1228
A60: 59 | B60: 33683 | C60: 7221 | E60: 437000 | G60: 19.104 | H60: 17.732 | I60: 1.01 | J60: 6264.54 | L60: 710 | M60: 12.927 | N60: 167652 | O60: 4084.7 | P60: 815581 | U60: 28 | V60: 86.6 | AA60: 253530 | AC60: 0 | AD60: 138.5 | AE60: 1.6 | AG60: =6753.47943187+0.36116788*I60+0.01252571*N60-22.85359542*V60+0.00407811*AA60-0.00067349*E60 -> 7614.2913 | AH60: =A60*'Simple Linear Regression'!$B$18+'Simple Linear Regression'!$B$17 -> 7935.6655 | AI60: =7491.3971+0.0137554*N60-0.00058829*E60-34.3283*V60+0.30565*L60+54.6031*M60 -> 7490.4697 | AJ60: =7491.3971-0.00058829*E60+0.30565*L60+54.6031*M60+0.0137554*N60-34.3283*V60 -> 7490.4697 | AL60: =2192.59+2373.87*I60+0.0316653*N60-15.7623*V60+0.00202406*AA60-0.000740146*E60-0.00963493*(I60*N60) -> 7092.1821 | AM60: =5205.907083+122.0638992*I60+13.609808*(N60/1000)-1.245906883*AD60+0.7746840854*AE60-134.2474226*AC60-1547.125689*IF(AND(B60>=DATE(2020,3,20),B60<=DATE(2020,6,26)),1,0) -> 7439.5845 | AN60: =IF(ISNUMBER(C61),C61,AN61)-0.8328750492*(AD62-AD61)+3.274150872*(AE62-AE61)+0.7954612886*((IF(ISNUMBER(C61),C61,AN61)-IF(ISNUMBER(C60),C60,AN60))-(-0.8328750492*(AD61-AD60)+3.274150872*(AE61-AE60)))-1.394571582*AO61+0.4181414112*AO60 -> 7518.1941 | AP60: =AQ60+AR59+'ARIMAX(1,1,1) Model'!$C$19*(AR59-AR58)+'ARIMAX(1,1,1) Model'!$C$20*AS59 -> 7067.5675 | AQ60: ='ARIMAX(1,1,1) Model'!$C$6*I60+'ARIMAX(1,1,1) Model'!$C$7*N60/1000+'ARIMAX(1,1,1) Model'!$C$8*AD60+'ARIMAX(1,1,1) Model'!$C$9*AE60+'ARIMAX(1,1,1) Model'!$C$10*AC60+'ARIMAX(1,1,1) Model'!$C$11*IF(AND(B60>='ARIMAX(1,1,1) Model'!$C$25,B60<='ARIMAX(1,1,1) Model'!$C$26),1,0)+'ARIMAX(1,1,1) Model'!$C$12*E60/1000+'ARIMAX(1,1,1) Model'!$C$13*V60+'ARIMAX(1,1,1) Model'!$C$14*A60+'ARIMAX(1,1,1) Model'!$C$15*SIN(2*PI()*A60/'ARIMAX(1,1,1) Model'!$C$24)+'ARIMAX(1,1,1) Model'!$C$16*COS(2*PI()*A60/'ARIMAX(1,1,1) Model'!$C$24)+'ARIMAX(1,1,1) Model'!$C$17*SIN(4*PI()*A60/'ARIMAX(1,1,1) Model'!$C$24)+'ARIMAX(1,1,1) Model'!$C$18*COS(4*PI()*A60/'ARIMAX(1,1,1) Model'!$C$24) -> 1024.837 | AR60: =IF(ISNUMBER(C60),C60,AP60)-AQ60 -> 6196.163 | AS60: =IF(ISNUMBER(C60),C60-AP60,0) -> 153.43249
A61: 60 | B61: 33690 | C61: 7379 | E61: 440000 | G61: 19.094 | H61: 17.752 | I61: 1.015 | J61: 6264.54 | L61: 710 | M61: 12.927 | N61: 167652 | O61: 4084.7 | P61: 815581 | U61: 28 | V61: 86.6 | AA61: 253530 | AC61: 0 | AD61: 133.6 | AE61: 0.6 | AG61: =6753.47943187+0.36116788*I61+0.01252571*N61-22.85359542*V61+0.00407811*AA61-0.00067349*E61 -> 7612.2726 | AH61: =A61*'Simple Linear Regression'!$B$18+'Simple Linear Regression'!$B$17 -> 7936.5186 | AI61: =7491.3971+0.0137554*N61-0.00058829*E61-34.3283*V61+0.30565*L61+54.6031*M61 -> 7488.7048 | AJ61: =7491.3971-0.00058829*E61+0.30565*L61+54.6031*M61+0.0137554*N61-34.3283*V61 -> 7488.7048 | AL61: =2192.59+2373.87*I61+0.0316653*N61-15.7623*V61+0.00202406*AA61-0.000740146*E61-0.00963493*(I61*N61) -> 7093.7544 | AM61: =5205.907083+122.0638992*I61+13.609808*(N61/1000)-1.245906883*AD61+0.7746840854*AE61-134.2474226*AC61-1547.125689*IF(AND(B61>=DATE(2020,3,20),B61<=DATE(2020,6,26)),1,0) -> 7445.5251 | AN61: =IF(ISNUMBER(C62),C62,AN62)-0.8328750492*(AD63-AD62)+3.274150872*(AE63-AE62)+0.7954612886*((IF(ISNUMBER(C62),C62,AN62)-IF(ISNUMBER(C61),C61,AN61))-(-0.8328750492*(AD62-AD61)+3.274150872*(AE62-AE61)))-1.394571582*AO62+0.4181414112*AO61 -> 6766.5702 | AP61: =AQ61+AR60+'ARIMAX(1,1,1) Model'!$C$19*(AR60-AR59)+'ARIMAX(1,1,1) Model'!$C$20*AS60 -> 7166.5833 | AQ61: ='ARIMAX(1,1,1) Model'!$C$6*I61+'ARIMAX(1,1,1) Model'!$C$7*N61/1000+'ARIMAX(1,1,1) Model'!$C$8*AD61+'ARIMAX(1,1,1) Model'!$C$9*AE61+'ARIMAX(1,1,1) Model'!$C$10*AC61+'ARIMAX(1,1,1) Model'!$C$11*IF(AND(B61>='ARIMAX(1,1,1) Model'!$C$25,B61<='ARIMAX(1,1,1) Model'!$C$26),1,0)+'ARIMAX(1,1,1) Model'!$C$12*E61/1000+'ARIMAX(1,1,1) Model'!$C$13*V61+'ARIMAX(1,1,1) Model'!$C$14*A61+'ARIMAX(1,1,1) Model'!$C$15*SIN(2*PI()*A61/'ARIMAX(1,1,1) Model'!$C$24)+'ARIMAX(1,1,1) Model'!$C$16*COS(2*PI()*A61/'ARIMAX(1,1,1) Model'!$C$24)+'ARIMAX(1,1,1) Model'!$C$17*SIN(4*PI()*A61/'ARIMAX(1,1,1) Model'!$C$24)+'ARIMAX(1,1,1) Model'!$C$18*COS(4*PI()*A61/'ARIMAX(1,1,1) Model'!$C$24) -> 1072.6175 | AR61: =IF(ISNUMBER(C61),C61,AP61)-AQ61 -> 6306.3825 | AS61: =IF(ISNUMBER(C61),C61-AP61,0) -> 212.41675
A62: 61 | B62: 33697 | C62: 7027 | E62: 420000 | G62: 19.726 | H62: 18.522 | I62: 1.013 | J62: 6264.54 | L62: 710 | M62: 12.927 | N62: 167652 | O62: 4084.7 | P62: 815581 | U62: 28 | V62: 86.6 | AA62: 253530 | AC62: 0 | AD62: 117 | AE62: 0.7 | AG62: =6753.47943187+0.36116788*I62+0.01252571*N62-22.85359542*V62+0.00407811*AA62-0.00067349*E62 -> 7625.7417 | AH62: =A62*'Simple Linear Regression'!$B$18+'Simple Linear Regression'!$B$17 -> 7937.3716 | AI62: =7491.3971+0.0137554*N62-0.00058829*E62-34.3283*V62+0.30565*L62+54.6031*M62 -> 7500.4706 | AJ62: =7491.3971-0.00058829*E62+0.30565*L62+54.6031*M62+0.0137554*N62-34.3283*V62 -> 7500.4706 | AL62: =2192.59+2373.87*I62+0.0316653*N62-15.7623*V62+0.00202406*AA62-0.000740146*E62-0.00963493*(I62*N62) -> 7107.0402 | AM62: =5205.907083+122.0638992*I62+13.609808*(N62/1000)-1.245906883*AD62+0.7746840854*AE62-134.2474226*AC62-1547.125689*IF(AND(B62>=DATE(2020,3,20),B62<=DATE(2020,6,26)),1,0) -> 7466.0405 | AN62: =IF(ISNUMBER(C63),C63,AN63)-0.8328750492*(AD64-AD63)+3.274150872*(AE64-AE63)+0.7954612886*((IF(ISNUMBER(C63),C63,AN63)-IF(ISNUMBER(C62),C62,AN62))-(-0.8328750492*(AD63-AD62)+3.274150872*(AE63-AE62)))-1.394571582*AO63+0.4181414112*AO62 -> 8330.0554 | AP62: =AQ62+AR61+'ARIMAX(1,1,1) Model'!$C$19*(AR61-AR60)+'ARIMAX(1,1,1) Model'!$C$20*AS61 -> 7261.9708 | AQ62: ='ARIMAX(1,1,1) Model'!$C$6*I62+'ARIMAX(1,1,1) Model'!$C$7*N62/1000+'ARIMAX(1,1,1) Model'!$C$8*AD62+'ARIMAX(1,1,1) Model'!$C$9*AE62+'ARIMAX(1,1,1) Model'!$C$10*AC62+'ARIMAX(1,1,1) Model'!$C$11*IF(AND(B62>='ARIMAX(1,1,1) Model'!$C$25,B62<='ARIMAX(1,1,1) Model'!$C$26),1,0)+'ARIMAX(1,1,1) Model'!$C$12*E62/1000+'ARIMAX(1,1,1) Model'!$C$13*V62+'ARIMAX(1,1,1) Model'!$C$14*A62+'ARIMAX(1,1,1) Model'!$C$15*SIN(2*PI()*A62/'ARIMAX(1,1,1) Model'!$C$24)+'ARIMAX(1,1,1) Model'!$C$16*COS(2*PI()*A62/'ARIMAX(1,1,1) Model'!$C$24)+'ARIMAX(1,1,1) Model'!$C$17*SIN(4*PI()*A62/'ARIMAX(1,1,1) Model'!$C$24)+'ARIMAX(1,1,1) Model'!$C$18*COS(4*PI()*A62/'ARIMAX(1,1,1) Model'!$C$24) -> 1136.0312 | AR62: =IF(ISNUMBER(C62),C62,AP62)-AQ62 -> 5890.9688 | AS62: =IF(ISNUMBER(C62),C62-AP62,0) -> -234.97076
A63: 62 | B63: 33704 | C63: 7744 | E63: 412000 | G63: 20.43 | H63: 19.008 | I63: 1.026 | J63: 6264.54 | L63: 669 | M63: 12.927 | N63: 167652 | O63: 4099.5 | P63: 815581 | U63: 28 | V63: 83.4 | AA63: 253530 | AC63: 0 | AD63: 84.7 | AE63: 1.9 | AG63: =6753.47943187+0.36116788*I63+0.01252571*N63-22.85359542*V63+0.00407811*AA63-0.00067349*E63 -> 7704.2658 | AH63: =A63*'Simple Linear Regression'!$B$18+'Simple Linear Regression'!$B$17 -> 7938.2246 | AI63: =7491.3971+0.0137554*N63-0.00058829*E63-34.3283*V63+0.30565*L63+54.6031*M63 -> 7602.4958 | AJ63: =7491.3971-0.00058829*E63+0.30565*L63+54.6031*M63+0.0137554*N63-34.3283*V63 -> 7602.4958 | AL63: =2192.59+2373.87*I63+0.0316653*N63-15.7623*V63+0.00202406*AA63-0.000740146*E63-0.00963493*(I63*N63) -> 7173.262 | AM63: =5205.907083+122.0638992*I63+13.609808*(N63/1000)-1.245906883*AD63+0.7746840854*AE63-134.2474226*AC63-1547.125689*IF(AND(B63>=DATE(2020,3,20),B63<=DATE(2020,6,26)),1,0) -> 7508.7998 | AN63: =IF(ISNUMBER(C64),C64,AN64)-0.8328750492*(AD65-AD64)+3.274150872*(AE65-AE64)+0.7954612886*((IF(ISNUMBER(C64),C64,AN64)-IF(ISNUMBER(C63),C63,AN63))-(-0.8328750492*(AD64-AD63)+3.274150872*(AE64-AE63)))-1.394571582*AO64+0.4181414112*AO63 -> 5451.3217 | AP63: =AQ63+AR62+'ARIMAX(1,1,1) Model'!$C$19*(AR62-AR61)+'ARIMAX(1,1,1) Model'!$C$20*AS62 -> 7191.645 | AQ63: ='ARIMAX(1,1,1) Model'!$C$6*I63+'ARIMAX(1,1,1) Model'!$C$7*N63/1000+'ARIMAX(1,1,1) Model'!$C$8*AD63+'ARIMAX(1,1,1) Model'!$C$9*AE63+'ARIMAX(1,1,1) Model'!$C$10*AC63+'ARIMAX(1,1,1) Model'!$C$11*IF(AND(B63>='ARIMAX(1,1,1) Model'!$C$25,B63<='ARIMAX(1,1,1) Model'!$C$26),1,0)+'ARIMAX(1,1,1) Model'!$C$12*E63/1000+'ARIMAX(1,1,1) Model'!$C$13*V63+'ARIMAX(1,1,1) Model'!$C$14*A63+'ARIMAX(1,1,1) Model'!$C$15*SIN(2*PI()*A63/'ARIMAX(1,1,1) Model'!$C$24)+'ARIMAX(1,1,1) Model'!$C$16*COS(2*PI()*A63/'ARIMAX(1,1,1) Model'!$C$24)+'ARIMAX(1,1,1) Model'!$C$17*SIN(4*PI()*A63/'ARIMAX(1,1,1) Model'!$C$24)+'ARIMAX(1,1,1) Model'!$C$18*COS(4*PI()*A63/'ARIMAX(1,1,1) Model'!$C$24) -> 1129.6988 | AR63: =IF(ISNUMBER(C63),C63,AP63)-AQ63 -> 6614.3012 | AS63: =IF(ISNUMBER(C63),C63-AP63,0) -> 552.35505
A64: 63 | B64: 33711 | C64: 6464 | E64: 413000 | G64: 20.0575 | H64: 18.8575 | I64: 1.051 | J64: 6264.54 | L64: 669 | M64: 12.824 | N64: 160204 | O64: 4099.5 | P64: 815581 | U64: 28 | V64: 83.4 | AA64: 253530 | AC64: 0 | AD64: 70.2 | AE64: 10.5 | AG64: =6753.47943187+0.36116788*I64+0.01252571*N64-22.85359542*V64+0.00407811*AA64-0.00067349*E64 -> 7610.3099 | AH64: =A64*'Simple Linear Regression'!$B$18+'Simple Linear Regression'!$B$17 -> 7939.0777 | AI64: =7491.3971+0.0137554*N64-0.00058829*E64-34.3283*V64+0.30565*L64+54.6031*M64 -> 7493.8332 | AJ64: =7491.3971-0.00058829*E64+0.30565*L64+54.6031*M64+0.0137554*N64-34.3283*V64 -> 7493.8332 | AL64: =2192.59+2373.87*I64+0.0316653*N64-15.7623*V64+0.00202406*AA64-0.000740146*E64-0.00963493*(I64*N64) -> 7031.0633 | AM64: =5205.907083+122.0638992*I64+13.609808*(N64/1000)-1.245906883*AD64+0.7746840854*AE64-134.2474226*AC64-1547.125689*IF(AND(B64>=DATE(2020,3,20),B64<=DATE(2020,6,26)),1,0) -> 7435.2134 | AN64: =IF(ISNUMBER(C65),C65,AN65)-0.8328750492*(AD66-AD65)+3.274150872*(AE66-AE65)+0.7954612886*((IF(ISNUMBER(C65),C65,AN65)-IF(ISNUMBER(C64),C64,AN64))-(-0.8328750492*(AD65-AD64)+3.274150872*(AE65-AE64)))-1.394571582*AO65+0.4181414112*AO64 -> 8055.3189 | AP64: =AQ64+AR63+'ARIMAX(1,1,1) Model'!$C$19*(AR63-AR62)+'ARIMAX(1,1,1) Model'!$C$20*AS63 -> 7378.844 | AQ64: ='ARIMAX(1,1,1) Model'!$C$6*I64+'ARIMAX(1,1,1) Model'!$C$7*N64/1000+'ARIMAX(1,1,1) Model'!$C$8*AD64+'ARIMAX(1,1,1) Model'!$C$9*AE64+'ARIMAX(1,1,1) Model'!$C$10*AC64+'ARIMAX(1,1,1) Model'!$C$11*IF(AND(B64>='ARIMAX(1,1,1) Model'!$C$25,B64<='ARIMAX(1,1,1) Model'!$C$26),1,0)+'ARIMAX(1,1,1) Model'!$C$12*E64/1000+'ARIMAX(1,1,1) Model'!$C$13*V64+'ARIMAX(1,1,1) Model'!$C$14*A64+'ARIMAX(1,1,1) Model'!$C$15*SIN(2*PI()*A64/'ARIMAX(1,1,1) Model'!$C$24)+'ARIMAX(1,1,1) Model'!$C$16*COS(2*PI()*A64/'ARIMAX(1,1,1) Model'!$C$24)+'ARIMAX(1,1,1) Model'!$C$17*SIN(4*PI()*A64/'ARIMAX(1,1,1) Model'!$C$24)+'ARIMAX(1,1,1) Model'!$C$18*COS(4*PI()*A64/'ARIMAX(1,1,1) Model'!$C$24) -> 1191.1607 | AR64: =IF(ISNUMBER(C64),C64,AP64)-AQ64 -> 5272.8393 | AS64: =IF(ISNUMBER(C64),C64-AP64,0) -> -914.84404
A65: 64 | B65: 33718 | C65: 7376 | E65: 424000 | G65: 20.062 | H65: 18.856 | I65: 1.058 | J65: 6264.54 | L65: 669 | M65: 12.824 | N65: 160204 | O65: 4099.5 | P65: 815581 | U65: 28 | V65: 83.4 | AA65: 253530 | AC65: 0 | AD65: 39.7 | AE65: 14.2 | AG65: =6753.47943187+0.36116788*I65+0.01252571*N65-22.85359542*V65+0.00407811*AA65-0.00067349*E65 -> 7602.904 | AH65: =A65*'Simple Linear Regression'!$B$18+'Simple Linear Regression'!$B$17 -> 7939.9307 | AI65: =7491.3971+0.0137554*N65-0.00058829*E65-34.3283*V65+0.30565*L65+54.6031*M65 -> 7487.362 | AJ65: =7491.3971-0.00058829*E65+0.30565*L65+54.6031*M65+0.0137554*N65-34.3283*V65 -> 7487.362 | AL65: =2192.59+2373.87*I65+0.0316653*N65-15.7623*V65+0.00202406*AA65-0.000740146*E65-0.00963493*(I65*N65) -> 7028.7339 | AM65: =5205.907083+122.0638992*I65+13.609808*(N65/1000)-1.245906883*AD65+0.7746840854*AE65-134.2474226*AC65-1547.125689*IF(AND(B65>=DATE(2020,3,20),B65<=DATE(2020,6,26)),1,0) -> 7476.9344 | AN65: =IF(ISNUMBER(C66),C66,AN66)-0.8328750492*(AD67-AD66)+3.274150872*(AE67-AE66)+0.7954612886*((IF(ISNUMBER(C66),C66,AN66)-IF(ISNUMBER(C65),C65,AN65))-(-0.8328750492*(AD66-AD65)+3.274150872*(AE66-AE65)))-1.394571582*AO66+0.4181414112*AO65 -> 8331.3108 | AP65: =AQ65+AR64+'ARIMAX(1,1,1) Model'!$C$19*(AR64-AR63)+'ARIMAX(1,1,1) Model'!$C$20*AS64 -> 7192.3875 | AQ65: ='ARIMAX(1,1,1) Model'!$C$6*I65+'ARIMAX(1,1,1) Model'!$C$7*N65/1000+'ARIMAX(1,1,1) Model'!$C$8*AD65+'ARIMAX(1,1,1) Model'!$C$9*AE65+'ARIMAX(1,1,1) Model'!$C$10*AC65+'ARIMAX(1,1,1) Model'!$C$11*IF(AND(B65>='ARIMAX(1,1,1) Model'!$C$25,B65<='ARIMAX(1,1,1) Model'!$C$26),1,0)+'ARIMAX(1,1,1) Model'!$C$12*E65/1000+'ARIMAX(1,1,1) Model'!$C$13*V65+'ARIMAX(1,1,1) Model'!$C$14*A65+'ARIMAX(1,1,1) Model'!$C$15*SIN(2*PI()*A65/'ARIMAX(1,1,1) Model'!$C$24)+'ARIMAX(1,1,1) Model'!$C$16*COS(2*PI()*A65/'ARIMAX(1,1,1) Model'!$C$24)+'ARIMAX(1,1,1) Model'!$C$17*SIN(4*PI()*A65/'ARIMAX(1,1,1) Model'!$C$24)+'ARIMAX(1,1,1) Model'!$C$18*COS(4*PI()*A65/'ARIMAX(1,1,1) Model'!$C$24) -> 1226.9472 | AR65: =IF(ISNUMBER(C65),C65,AP65)-AQ65 -> 6149.0528 | AS65: =IF(ISNUMBER(C65),C65-AP65,0) -> 183.61254
A66: 65 | B66: 33725 | C66: 7899 | E66: 424000 | G66: 20.626 | H66: 19.368 | I66: 1.072 | J66: 6264.54 | L66: 669 | M66: 12.824 | N66: 160204 | O66: 4099.5 | P66: 815581 | U66: 28 | V66: 83.4 | AA66: 253530 | AC66: 0 | AD66: 63.2 | AE66: 15.2 | AG66: =6753.47943187+0.36116788*I66+0.01252571*N66-22.85359542*V66+0.00407811*AA66-0.00067349*E66 -> 7602.9091 | AH66: =A66*'Simple Linear Regression'!$B$18+'Simple Linear Regression'!$B$17 -> 7940.7838 | AI66: =7491.3971+0.0137554*N66-0.00058829*E66-34.3283*V66+0.30565*L66+54.6031*M66 -> 7487.362 | AJ66: =7491.3971-0.00058829*E66+0.30565*L66+54.6031*M66+0.0137554*N66-34.3283*V66 -> 7487.362 | AL66: =2192.59+2373.87*I66+0.0316653*N66-15.7623*V66+0.00202406*AA66-0.000740146*E66-0.00963493*(I66*N66) -> 7040.3583 | AM66: =5205.907083+122.0638992*I66+13.609808*(N66/1000)-1.245906883*AD66+0.7746840854*AE66-134.2474226*AC66-1547.125689*IF(AND(B66>=DATE(2020,3,20),B66<=DATE(2020,6,26)),1,0) -> 7450.1391 | AN66: =IF(ISNUMBER(C67),C67,AN67)-0.8328750492*(AD68-AD67)+3.274150872*(AE68-AE67)+0.7954612886*((IF(ISNUMBER(C67),C67,AN67)-IF(ISNUMBER(C66),C66,AN66))-(-0.8328750492*(AD67-AD66)+3.274150872*(AE67-AE66)))-1.394571582*AO67+0.4181414112*AO66 -> 6902.7214 | AP66: =AQ66+AR65+'ARIMAX(1,1,1) Model'!$C$19*(AR65-AR64)+'ARIMAX(1,1,1) Model'!$C$20*AS65 -> 7359.1598 | AQ66: ='ARIMAX(1,1,1) Model'!$C$6*I66+'ARIMAX(1,1,1) Model'!$C$7*N66/1000+'ARIMAX(1,1,1) Model'!$C$8*AD66+'ARIMAX(1,1,1) Model'!$C$9*AE66+'ARIMAX(1,1,1) Model'!$C$10*AC66+'ARIMAX(1,1,1) Model'!$C$11*IF(AND(B66>='ARIMAX(1,1,1) Model'!$C$25,B66<='ARIMAX(1,1,1) Model'!$C$26),1,0)+'ARIMAX(1,1,1) Model'!$C$12*E66/1000+'ARIMAX(1,1,1) Model'!$C$13*V66+'ARIMAX(1,1,1) Model'!$C$14*A66+'ARIMAX(1,1,1) Model'!$C$15*SIN(2*PI()*A66/'ARIMAX(1,1,1) Model'!$C$24)+'ARIMAX(1,1,1) Model'!$C$16*COS(2*PI()*A66/'ARIMAX(1,1,1) Model'!$C$24)+'ARIMAX(1,1,1) Model'!$C$17*SIN(4*PI()*A66/'ARIMAX(1,1,1) Model'!$C$24)+'ARIMAX(1,1,1) Model'!$C$18*COS(4*PI()*A66/'ARIMAX(1,1,1) Model'!$C$24) -> 1289.915 | AR66: =IF(ISNUMBER(C66),C66,AP66)-AQ66 -> 6609.085 | AS66: =IF(ISNUMBER(C66),C66-AP66,0) -> 539.84025
A67: 66 | B67: 33732 | C67: 7318 | E67: 431000 | G67: 20.856 | H67: 19.764 | I67: 1.089 | J67: 6363.102 | L67: 648 | M67: 12.824 | N67: 160204 | O67: 4117 | P67: 815581 | U67: 28 | V67: 81.3 | AA67: 253530 | AC67: 0 | AD67: 48.6 | AE67: 12.5 | AG67: =6753.47943187+0.36116788*I67+0.01252571*N67-22.85359542*V67+0.00407811*AA67-0.00067349*E67 -> 7646.1933 | AH67: =A67*'Simple Linear Regression'!$B$18+'Simple Linear Regression'!$B$17 -> 7941.6368 | AI67: =7491.3971+0.0137554*N67-0.00058829*E67-34.3283*V67+0.30565*L67+54.6031*M67 -> 7548.9148 | AJ67: =7491.3971-0.00058829*E67+0.30565*L67+54.6031*M67+0.0137554*N67-34.3283*V67 -> 7548.9148 | AL67: =2192.59+2373.87*I67+0.0316653*N67-15.7623*V67+0.00202406*AA67-0.000740146*E67-0.00963493*(I67*N67) -> 7082.3935 | AM67: =5205.907083+122.0638992*I67+13.609808*(N67/1000)-1.245906883*AD67+0.7746840854*AE67-134.2474226*AC67-1547.125689*IF(AND(B67>=DATE(2020,3,20),B67<=DATE(2020,6,26)),1,0) -> 7468.3128 | AN67: =IF(ISNUMBER(C68),C68,AN68)-0.8328750492*(AD69-AD68)+3.274150872*(AE69-AE68)+0.7954612886*((IF(ISNUMBER(C68),C68,AN68)-IF(ISNUMBER(C67),C67,AN67))-(-0.8328750492*(AD68-AD67)+3.274150872*(AE68-AE67)))-1.394571582*AO68+0.4181414112*AO67 -> 7056.427 | AP67: =AQ67+AR66+'ARIMAX(1,1,1) Model'!$C$19*(AR66-AR65)+'ARIMAX(1,1,1) Model'!$C$20*AS66 -> 7438.9121 | AQ67: ='ARIMAX(1,1,1) Model'!$C$6*I67+'ARIMAX(1,1,1) Model'!$C$7*N67/1000+'ARIMAX(1,1,1) Model'!$C$8*AD67+'ARIMAX(1,1,1) Model'!$C$9*AE67+'ARIMAX(1,1,1) Model'!$C$10*AC67+'ARIMAX(1,1,1) Model'!$C$11*IF(AND(B67>='ARIMAX(1,1,1) Model'!$C$25,B67<='ARIMAX(1,1,1) Model'!$C$26),1,0)+'ARIMAX(1,1,1) Model'!$C$12*E67/1000+'ARIMAX(1,1,1) Model'!$C$13*V67+'ARIMAX(1,1,1) Model'!$C$14*A67+'ARIMAX(1,1,1) Model'!$C$15*SIN(2*PI()*A67/'ARIMAX(1,1,1) Model'!$C$24)+'ARIMAX(1,1,1) Model'!$C$16*COS(2*PI()*A67/'ARIMAX(1,1,1) Model'!$C$24)+'ARIMAX(1,1,1) Model'!$C$17*SIN(4*PI()*A67/'ARIMAX(1,1,1) Model'!$C$24)+'ARIMAX(1,1,1) Model'!$C$18*COS(4*PI()*A67/'ARIMAX(1,1,1) Model'!$C$24) -> 1270.8607 | AR67: =IF(ISNUMBER(C67),C67,AP67)-AQ67 -> 6047.1393 | AS67: =IF(ISNUMBER(C67),C67-AP67,0) -> -120.91214
A68: 67 | B68: 33739 | C68: 7174 | E68: 417000 | G68: 20.802 | H68: 19.786 | I68: 1.102 | J68: 6363.102 | L68: 648 | M68: 12.824 | N68: 160204 | O68: 4117 | P68: 815581 | U68: 28 | V68: 81.3 | AA68: 253530 | AC68: 0 | AD68: 19.8 | AE68: 20.3 | AG68: =6753.47943187+0.36116788*I68+0.01252571*N68-22.85359542*V68+0.00407811*AA68-0.00067349*E68 -> 7655.6269 | AH68: =A68*'Simple Linear Regression'!$B$18+'Simple Linear Regression'!$B$17 -> 7942.4898 | AI68: =7491.3971+0.0137554*N68-0.00058829*E68-34.3283*V68+0.30565*L68+54.6031*M68 -> 7557.1508 | AJ68: =7491.3971-0.00058829*E68+0.30565*L68+54.6031*M68+0.0137554*N68-34.3283*V68 -> 7557.1508 | AL68: =2192.59+2373.87*I68+0.0316653*N68-15.7623*V68+0.00202406*AA68-0.000740146*E68-0.00963493*(I68*N68) -> 7103.5497 | AM68: =5205.907083+122.0638992*I68+13.609808*(N68/1000)-1.245906883*AD68+0.7746840854*AE68-134.2474226*AC68-1547.125689*IF(AND(B68>=DATE(2020,3,20),B68<=DATE(2020,6,26)),1,0) -> 7511.8243 | AN68: =IF(ISNUMBER(C69),C69,AN69)-0.8328750492*(AD70-AD69)+3.274150872*(AE70-AE69)+0.7954612886*((IF(ISNUMBER(C69),C69,AN69)-IF(ISNUMBER(C68),C68,AN68))-(-0.8328750492*(AD69-AD68)+3.274150872*(AE69-AE68)))-1.394571582*AO69+0.4181414112*AO68 -> 6945.2125 | AP68: =AQ68+AR67+'ARIMAX(1,1,1) Model'!$C$19*(AR67-AR66)+'ARIMAX(1,1,1) Model'!$C$20*AS67 -> 7416.2992 | AQ68: ='ARIMAX(1,1,1) Model'!$C$6*I68+'ARIMAX(1,1,1) Model'!$C$7*N68/1000+'ARIMAX(1,1,1) Model'!$C$8*AD68+'ARIMAX(1,1,1) Model'!$C$9*AE68+'ARIMAX(1,1,1) Model'!$C$10*AC68+'ARIMAX(1,1,1) Model'!$C$11*IF(AND(B68>='ARIMAX(1,1,1) Model'!$C$25,B68<='ARIMAX(1,1,1) Model'!$C$26),1,0)+'ARIMAX(1,1,1) Model'!$C$12*E68/1000+'ARIMAX(1,1,1) Model'!$C$13*V68+'ARIMAX(1,1,1) Model'!$C$14*A68+'ARIMAX(1,1,1) Model'!$C$15*SIN(2*PI()*A68/'ARIMAX(1,1,1) Model'!$C$24)+'ARIMAX(1,1,1) Model'!$C$16*COS(2*PI()*A68/'ARIMAX(1,1,1) Model'!$C$24)+'ARIMAX(1,1,1) Model'!$C$17*SIN(4*PI()*A68/'ARIMAX(1,1,1) Model'!$C$24)+'ARIMAX(1,1,1) Model'!$C$18*COS(4*PI()*A68/'ARIMAX(1,1,1) Model'!$C$24) -> 1315.1364 | AR68: =IF(ISNUMBER(C68),C68,AP68)-AQ68 -> 5858.8636 | AS68: =IF(ISNUMBER(C68),C68-AP68,0) -> -242.29918
A69: 68 | B69: 33746 | C69: 7086 | E69: 414000 | G69: 20.488 | H69: 19.492 | I69: 1.118 | J69: 6363.102 | L69: 648 | M69: 12.55 | N69: 183778 | O69: 4117 | P69: 815581 | U69: 28 | V69: 81.3 | AA69: 253530 | AC69: 0 | AD69: 12.3 | AE69: 29.5 | AG69: =6753.47943187+0.36116788*I69+0.01252571*N69-22.85359542*V69+0.00407811*AA69-0.00067349*E69 -> 7952.9342 | AH69: =A69*'Simple Linear Regression'!$B$18+'Simple Linear Regression'!$B$17 -> 7943.3429 | AI69: =7491.3971+0.0137554*N69-0.00058829*E69-34.3283*V69+0.30565*L69+54.6031*M69 -> 7868.2243 | AJ69: =7491.3971-0.00058829*E69+0.30565*L69+54.6031*M69+0.0137554*N69-34.3283*V69 -> 7868.2243 | AL69: =2192.59+2373.87*I69+0.0316653*N69-15.7623*V69+0.00202406*AA69-0.000740146*E69-0.00963493*(I69*N69) -> 7611.5973 | AM69: =5205.907083+122.0638992*I69+13.609808*(N69/1000)-1.245906883*AD69+0.7746840854*AE69-134.2474226*AC69-1547.125689*IF(AND(B69>=DATE(2020,3,20),B69<=DATE(2020,6,26)),1,0) -> 7851.0863 | AN69: =IF(ISNUMBER(C70),C70,AN70)-0.8328750492*(AD71-AD70)+3.274150872*(AE71-AE70)+0.7954612886*((IF(ISNUMBER(C70),C70,AN70)-IF(ISNUMBER(C69),C69,AN69))-(-0.8328750492*(AD70-AD69)+3.274150872*(AE70-AE69)))-1.394571582*AO70+0.4181414112*AO69 -> 8377.8735 | AP69: =AQ69+AR68+'ARIMAX(1,1,1) Model'!$C$19*(AR68-AR67)+'ARIMAX(1,1,1) Model'!$C$20*AS68 -> 7437.8681 | AQ69: ='ARIMAX(1,1,1) Model'!$C$6*I69+'ARIMAX(1,1,1) Model'!$C$7*N69/1000+'ARIMAX(1,1,1) Model'!$C$8*AD69+'ARIMAX(1,1,1) Model'!$C$9*AE69+'ARIMAX(1,1,1) Model'!$C$10*AC69+'ARIMAX(1,1,1) Model'!$C$11*IF(AND(B69>='ARIMAX(1,1,1) Model'!$C$25,B69<='ARIMAX(1,1,1) Model'!$C$26),1,0)+'ARIMAX(1,1,1) Model'!$C$12*E69/1000+'ARIMAX(1,1,1) Model'!$C$13*V69+'ARIMAX(1,1,1) Model'!$C$14*A69+'ARIMAX(1,1,1) Model'!$C$15*SIN(2*PI()*A69/'ARIMAX(1,1,1) Model'!$C$24)+'ARIMAX(1,1,1) Model'!$C$16*COS(2*PI()*A69/'ARIMAX(1,1,1) Model'!$C$24)+'ARIMAX(1,1,1) Model'!$C$17*SIN(4*PI()*A69/'ARIMAX(1,1,1) Model'!$C$24)+'ARIMAX(1,1,1) Model'!$C$18*COS(4*PI()*A69/'ARIMAX(1,1,1) Model'!$C$24) -> 1379.2778 | AR69: =IF(ISNUMBER(C69),C69,AP69)-AQ69 -> 5706.7222 | AS69: =IF(ISNUMBER(C69),C69-AP69,0) -> -351.86808
... A213: 212 | B213: 34754 | C213: 7670 | E213: 343000 | G213: 18.7475 | H213: 17.178 | I213: 1.067 | J213: 7455.288 | L213: 816 | M213: 14.801 | N213: 193087 | O213: 4841.6 | P213: 980405 | U213: 27 | V213: 92.7 | AA213: 260282 | AC213: 0 | AD213: 128.6 | AE213: 0.2 | AG213: =6753.47943187+0.36116788*I213+0.01252571*N213-22.85359542*V213+0.00407811*AA213-0.00067349*E213 -> 7884.3398 | AH213: =A213*'Simple Linear Regression'!$B$18+'Simple Linear Regression'!$B$17 -> 8066.1802 | AI213: =7491.3971+0.0137554*N213-0.00058829*E213-34.3283*V213+0.30565*L213+54.6031*M213 -> 7820.96 | AJ213: =7491.3971-0.00058829*E213+0.30565*L213+54.6031*M213+0.0137554*N213-34.3283*V213 -> 7820.96 | AL213: =2192.59+2373.87*I213+0.0316653*N213-15.7623*V213+0.00202406*AA213-0.000740146*E213-0.00963493*(I213*N213) -> 7666.433 | AM213: =5205.907083+122.0638992*I213+13.609808*(N213/1000)-1.245906883*AD213+0.7746840854*AE213-134.2474226*AC213-1547.125689*IF(AND(B213>=DATE(2020,3,20),B213<=DATE(2020,6,26)),1,0) -> 7803.9576 | AN213: =IF(ISNUMBER(C214),C214,AN214)-0.8328750492*(AD215-AD214)+3.274150872*(AE215-AE214)+0.7954612886*((IF(ISNUMBER(C214),C214,AN214)-IF(ISNUMBER(C213),C213,AN213))-(-0.8328750492*(AD214-AD213)+3.274150872*(AE214-AE213)))-1.394571582*AO214+0.4181414112*AO213 -> 6835.378 | AP213: =AQ213+AR212+'ARIMAX(1,1,1) Model'!$C$19*(AR212-AR211)+'ARIMAX(1,1,1) Model'!$C$20*AS212 -> 7416.3382 | AQ213: ='ARIMAX(1,1,1) Model'!$C$6*I213+'ARIMAX(1,1,1) Model'!$C$7*N213/1000+'ARIMAX(1,1,1) Model'!$C$8*AD213+'ARIMAX(1,1,1) Model'!$C$9*AE213+'ARIMAX(1,1,1) Model'!$C$10*AC213+'ARIMAX(1,1,1) Model'!$C$11*IF(AND(B213>='ARIMAX(1,1,1) Model'!$C$25,B213<='ARIMAX(1,1,1) Model'!$C$26),1,0)+'ARIMAX(1,1,1) Model'!$C$12*E213/1000+'ARIMAX(1,1,1) Model'!$C$13*V213+'ARIMAX(1,1,1) Model'!$C$14*A213+'ARIMAX(1,1,1) Model'!$C$15*SIN(2*PI()*A213/'ARIMAX(1,1,1) Model'!$C$24)+'ARIMAX(1,1,1) Model'!$C$16*COS(2*PI()*A213/'ARIMAX(1,1,1) Model'!$C$24)+'ARIMAX(1,1,1) Model'!$C$17*SIN(4*PI()*A213/'ARIMAX(1,1,1) Model'!$C$24)+'ARIMAX(1,1,1) Model'!$C$18*COS(4*PI()*A213/'ARIMAX(1,1,1) Model'!$C$24) -> 1202.5166 | AR213: =IF(ISNUMBER(C213),C213,AP213)-AQ213 -> 6467.4834 | AS213: =IF(ISNUMBER(C213),C213-AP213,0) -> 253.66184
A214: 213 | B214: 34761 | C214: 7194 | E214: 336000 | G214: 18.5 | H214: 16.932 | I214: 1.073 | J214: 7455.288 | L214: 816 | M214: 14.801 | N214: 193087 | O214: 4841.6 | P214: 980405 | R214: 2483 | U214: 27 | V214: 92.7 | AA214: 263455 | AC214: 0 | AD214: 149.6 | AE214: 0.7 | AG214: =6753.47943187+0.36116788*I214+0.01252571*N214-22.85359542*V214+0.00407811*AA214-0.00067349*E214 -> 7901.9963 | AH214: =A214*'Simple Linear Regression'!$B$18+'Simple Linear Regression'!$B$17 -> 8067.0332 | AI214: =7491.3971+0.0137554*N214-0.00058829*E214-34.3283*V214+0.30565*L214+54.6031*M214 -> 7825.0781 | AJ214: =7491.3971-0.00058829*E214+0.30565*L214+54.6031*M214+0.0137554*N214-34.3283*V214 -> 7825.0781 | AL214: =2192.59+2373.87*I214+0.0316653*N214-15.7623*V214+0.00202406*AA214-0.000740146*E214-0.00963493*(I214*N214) -> 7681.1173 | AM214: =5205.907083+122.0638992*I214+13.609808*(N214/1000)-1.245906883*AD214+0.7746840854*AE214-134.2474226*AC214-1547.125689*IF(AND(B214>=DATE(2020,3,20),B214<=DATE(2020,6,26)),1,0) -> 7778.9133 | AN214: =IF(ISNUMBER(C215),C215,AN215)-0.8328750492*(AD216-AD215)+3.274150872*(AE216-AE215)+0.7954612886*((IF(ISNUMBER(C215),C215,AN215)-IF(ISNUMBER(C214),C214,AN214))-(-0.8328750492*(AD215-AD214)+3.274150872*(AE215-AE214)))-1.394571582*AO215+0.4181414112*AO214 -> 7863.0418 | AP214: =AQ214+AR213+'ARIMAX(1,1,1) Model'!$C$19*(AR213-AR212)+'ARIMAX(1,1,1) Model'!$C$20*AS213 -> 7522.7732 | AQ214: ='ARIMAX(1,1,1) Model'!$C$6*I214+'ARIMAX(1,1,1) Model'!$C$7*N214/1000+'ARIMAX(1,1,1) Model'!$C$8*AD214+'ARIMAX(1,1,1) Model'!$C$9*AE214+'ARIMAX(1,1,1) Model'!$C$10*AC214+'ARIMAX(1,1,1) Model'!$C$11*IF(AND(B214>='ARIMAX(1,1,1) Model'!$C$25,B214<='ARIMAX(1,1,1) Model'!$C$26),1,0)+'ARIMAX(1,1,1) Model'!$C$12*E214/1000+'ARIMAX(1,1,1) Model'!$C$13*V214+'ARIMAX(1,1,1) Model'!$C$14*A214+'ARIMAX(1,1,1) Model'!$C$15*SIN(2*PI()*A214/'ARIMAX(1,1,1) Model'!$C$24)+'ARIMAX(1,1,1) Model'!$C$16*COS(2*PI()*A214/'ARIMAX(1,1,1) Model'!$C$24)+'ARIMAX(1,1,1) Model'!$C$17*SIN(4*PI()*A214/'ARIMAX(1,1,1) Model'!$C$24)+'ARIMAX(1,1,1) Model'!$C$18*COS(4*PI()*A214/'ARIMAX(1,1,1) Model'!$C$24) -> 1256.7068 | AR214: =IF(ISNUMBER(C214),C214,AP214)-AQ214 -> 5937.2932 | AS214: =IF(ISNUMBER(C214),C214-AP214,0) -> -328.77325
A215: 214 | B215: 34768 | C215: 7548 | E215: 339000 | G215: 18.27 | H215: 16.696 | I215: 1.076 | J215: 7455.288 | L215: 748 | M215: 14.801 | N215: 193087 | O215: 4851.2 | P215: 980405 | R215: 2483 | U215: 27 | V215: 92.6 | AA215: 263455 | AC215: 0 | AD215: 141.1 | AE215: 0.8 | AG215: =6753.47943187+0.36116788*I215+0.01252571*N215-22.85359542*V215+0.00407811*AA215-0.00067349*E215 -> 7902.2622 | AH215: =A215*'Simple Linear Regression'!$B$18+'Simple Linear Regression'!$B$17 -> 8067.8863 | AI215: =7491.3971+0.0137554*N215-0.00058829*E215-34.3283*V215+0.30565*L215+54.6031*M215 -> 7805.9618 | AJ215: =7491.3971-0.00058829*E215+0.30565*L215+54.6031*M215+0.0137554*N215-34.3283*V215 -> 7805.9618 | AL215: =2192.59+2373.87*I215+0.0316653*N215-15.7623*V215+0.00202406*AA215-0.000740146*E215-0.00963493*(I215*N215) -> 7682.0136 | AM215: =5205.907083+122.0638992*I215+13.609808*(N215/1000)-1.245906883*AD215+0.7746840854*AE215-134.2474226*AC215-1547.125689*IF(AND(B215>=DATE(2020,3,20),B215<=DATE(2020,6,26)),1,0) -> 7789.9471 | AN215: =IF(ISNUMBER(C216),C216,AN216)-0.8328750492*(AD217-AD216)+3.274150872*(AE217-AE216)+0.7954612886*((IF(ISNUMBER(C216),C216,AN216)-IF(ISNUMBER(C215),C215,AN215))-(-0.8328750492*(AD216-AD215)+3.274150872*(AE216-AE215)))-1.394571582*AO216+0.4181414112*AO215 -> 8053.6614 | AP215: =AQ215+AR214+'ARIMAX(1,1,1) Model'!$C$19*(AR214-AR213)+'ARIMAX(1,1,1) Model'!$C$20*AS214 -> 7472.1891 | AQ215: ='ARIMAX(1,1,1) Model'!$C$6*I215+'ARIMAX(1,1,1) Model'!$C$7*N215/1000+'ARIMAX(1,1,1) Model'!$C$8*AD215+'ARIMAX(1,1,1) Model'!$C$9*AE215+'ARIMAX(1,1,1) Model'!$C$10*AC215+'ARIMAX(1,1,1) Model'!$C$11*IF(AND(B215>='ARIMAX(1,1,1) Model'!$C$25,B215<='ARIMAX(1,1,1) Model'!$C$26),1,0)+'ARIMAX(1,1,1) Model'!$C$12*E215/1000+'ARIMAX(1,1,1) Model'!$C$13*V215+'ARIMAX(1,1,1) Model'!$C$14*A215+'ARIMAX(1,1,1) Model'!$C$15*SIN(2*PI()*A215/'ARIMAX(1,1,1) Model'!$C$24)+'ARIMAX(1,1,1) Model'!$C$16*COS(2*PI()*A215/'ARIMAX(1,1,1) Model'!$C$24)+'ARIMAX(1,1,1) Model'!$C$17*SIN(4*PI()*A215/'ARIMAX(1,1,1) Model'!$C$24)+'ARIMAX(1,1,1) Model'!$C$18*COS(4*PI()*A215/'ARIMAX(1,1,1) Model'!$C$24) -> 1290.6828 | AR215: =IF(ISNUMBER(C215),C215,AP215)-AQ215 -> 6257.3172 | AS215: =IF(ISNUMBER(C215),C215-AP215,0) -> 75.810934
A216: 215 | B216: 34775 | C216: 7834 | E216: 347000 | G216: 18.132 | H216: 16.412 | I216: 1.069 | J216: 7455.288 | L216: 748 | M216: 14.861 | N216: 193087 | O216: 4851.2 | P216: 1021168 | R216: 2483 | U216: 27 | V216: 92.6 | AA216: 263455 | AC216: 0 | AD216: 91.9 | AE216: 0.3 | AG216: =6753.47943187+0.36116788*I216+0.01252571*N216-22.85359542*V216+0.00407811*AA216-0.00067349*E216 -> 7896.8718 | AH216: =A216*'Simple Linear Regression'!$B$18+'Simple Linear Regression'!$B$17 -> 8068.7393 | AI216: =7491.3971+0.0137554*N216-0.00058829*E216-34.3283*V216+0.30565*L216+54.6031*M216 -> 7804.5317 | AJ216: =7491.3971-0.00058829*E216+0.30565*L216+54.6031*M216+0.0137554*N216-34.3283*V216 -> 7804.5317 | AL216: =2192.59+2373.87*I216+0.0316653*N216-15.7623*V216+0.00202406*AA216-0.000740146*E216-0.00963493*(I216*N216) -> 7672.498 | AM216: =5205.907083+122.0638992*I216+13.609808*(N216/1000)-1.245906883*AD216+0.7746840854*AE216-134.2474226*AC216-1547.125689*IF(AND(B216>=DATE(2020,3,20),B216<=DATE(2020,6,26)),1,0) -> 7850.004 | AN216: =IF(ISNUMBER(C217),C217,AN217)-0.8328750492*(AD218-AD217)+3.274150872*(AE218-AE217)+0.7954612886*((IF(ISNUMBER(C217),C217,AN217)-IF(ISNUMBER(C216),C216,AN216))-(-0.8328750492*(AD217-AD216)+3.274150872*(AE217-AE216)))-1.394571582*AO217+0.4181414112*AO216 -> 7729.4998 | AP216: =AQ216+AR215+'ARIMAX(1,1,1) Model'!$C$19*(AR215-AR214)+'ARIMAX(1,1,1) Model'!$C$20*AS215 -> 7523.9366 | AQ216: ='ARIMAX(1,1,1) Model'!$C$6*I216+'ARIMAX(1,1,1) Model'!$C$7*N216/1000+'ARIMAX(1,1,1) Model'!$C$8*AD216+'ARIMAX(1,1,1) Model'!$C$9*AE216+'ARIMAX(1,1,1) Model'!$C$10*AC216+'ARIMAX(1,1,1) Model'!$C$11*IF(AND(B216>='ARIMAX(1,1,1) Model'!$C$25,B216<='ARIMAX(1,1,1) Model'!$C$26),1,0)+'ARIMAX(1,1,1) Model'!$C$12*E216/1000+'ARIMAX(1,1,1) Model'!$C$13*V216+'ARIMAX(1,1,1) Model'!$C$14*A216+'ARIMAX(1,1,1) Model'!$C$15*SIN(2*PI()*A216/'ARIMAX(1,1,1) Model'!$C$24)+'ARIMAX(1,1,1) Model'!$C$16*COS(2*PI()*A216/'ARIMAX(1,1,1) Model'!$C$24)+'ARIMAX(1,1,1) Model'!$C$17*SIN(4*PI()*A216/'ARIMAX(1,1,1) Model'!$C$24)+'ARIMAX(1,1,1) Model'!$C$18*COS(4*PI()*A216/'ARIMAX(1,1,1) Model'!$C$24) -> 1303.6431 | AR216: =IF(ISNUMBER(C216),C216,AP216)-AQ216 -> 6530.3569 | AS216: =IF(ISNUMBER(C216),C216-AP216,0) -> 310.06337
A217: 216 | B217: 34782 | C217: 7797 | E217: 343000 | G217: 18.692 | H217: 17.168 | I217: 1.068 | J217: 7455.288 | L217: 748 | M217: 14.861 | N217: 193838 | O217: 4851.2 | P217: 1021168 | R217: 2483 | U217: 27 | V217: 92.6 | AA217: 263455 | AC217: 0 | AD217: 88.9 | AE217: 6.7 | AG217: =6753.47943187+0.36116788*I217+0.01252571*N217-22.85359542*V217+0.00407811*AA217-0.00067349*E217 -> 7908.9722 | AH217: =A217*'Simple Linear Regression'!$B$18+'Simple Linear Regression'!$B$17 -> 8069.5924 | AI217: =7491.3971+0.0137554*N217-0.00058829*E217-34.3283*V217+0.30565*L217+54.6031*M217 -> 7817.2151 | AJ217: =7491.3971-0.00058829*E217+0.30565*L217+54.6031*M217+0.0137554*N217-34.3283*V217 -> 7817.2151 | AL217: =2192.59+2373.87*I217+0.0316653*N217-15.7623*V217+0.00202406*AA217-0.000740146*E217-0.00963493*(I217*N217) -> 7690.9978 | AM217: =5205.907083+122.0638992*I217+13.609808*(N217/1000)-1.245906883*AD217+0.7746840854*AE217-134.2474226*AC217-1547.125689*IF(AND(B217>=DATE(2020,3,20),B217<=DATE(2020,6,26)),1,0) -> 7868.7986 | AN217: =IF(ISNUMBER(C218),C218,AN218)-0.8328750492*(AD219-AD218)+3.274150872*(AE219-AE218)+0.7954612886*((IF(ISNUMBER(C218),C218,AN218)-IF(ISNUMBER(C217),C217,AN217))-(-0.8328750492*(AD218-AD217)+3.274150872*(AE218-AE217)))-1.394571582*AO218+0.4181414112*AO217 -> 8519.424 | AP217: =AQ217+AR216+'ARIMAX(1,1,1) Model'!$C$19*(AR216-AR215)+'ARIMAX(1,1,1) Model'!$C$20*AS216 -> 7657.7553 | AQ217: ='ARIMAX(1,1,1) Model'!$C$6*I217+'ARIMAX(1,1,1) Model'!$C$7*N217/1000+'ARIMAX(1,1,1) Model'!$C$8*AD217+'ARIMAX(1,1,1) Model'!$C$9*AE217+'ARIMAX(1,1,1) Model'!$C$10*AC217+'ARIMAX(1,1,1) Model'!$C$11*IF(AND(B217>='ARIMAX(1,1,1) Model'!$C$25,B217<='ARIMAX(1,1,1) Model'!$C$26),1,0)+'ARIMAX(1,1,1) Model'!$C$12*E217/1000+'ARIMAX(1,1,1) Model'!$C$13*V217+'ARIMAX(1,1,1) Model'!$C$14*A217+'ARIMAX(1,1,1) Model'!$C$15*SIN(2*PI()*A217/'ARIMAX(1,1,1) Model'!$C$24)+'ARIMAX(1,1,1) Model'!$C$16*COS(2*PI()*A217/'ARIMAX(1,1,1) Model'!$C$24)+'ARIMAX(1,1,1) Model'!$C$17*SIN(4*PI()*A217/'ARIMAX(1,1,1) Model'!$C$24)+'ARIMAX(1,1,1) Model'!$C$18*COS(4*PI()*A217/'ARIMAX(1,1,1) Model'!$C$24) -> 1379.8514 | AR217: =IF(ISNUMBER(C217),C217,AP217)-AQ217 -> 6417.1486 | AS217: =IF(ISNUMBER(C217),C217-AP217,0) -> 139.24466
A218: 217 | B218: 34789 | C218: 8195 | E218: 332000 | G218: 19.118 | H218: 17.938 | I218: 1.075 | J218: 7455.288 | L218: 748 | M218: 14.861 | N218: 193838 | O218: 4851.2 | P218: 1021168 | R218: 2483 | U218: 27 | V218: 92.6 | AA218: 263455 | AC218: 0 | AD218: 101.2 | AE218: 3.9 | AG218: =6753.47943187+0.36116788*I218+0.01252571*N218-22.85359542*V218+0.00407811*AA218-0.00067349*E218 -> 7916.3831 | AH218: =A218*'Simple Linear Regression'!$B$18+'Simple Linear Regression'!$B$17 -> 8070.4454 | AI218: =7491.3971+0.0137554*N218-0.00058829*E218-34.3283*V218+0.30565*L218+54.6031*M218 -> 7823.6863 | AJ218: =7491.3971-0.00058829*E218+0.30565*L218+54.6031*M218+0.0137554*N218-34.3283*V218 -> 7823.6863 | AL218: =2192.59+2373.87*I218+0.0316653*N218-15.7623*V218+0.00202406*AA218-0.000740146*E218-0.00963493*(I218*N218) -> 7702.6832 | AM218: =5205.907083+122.0638992*I218+13.609808*(N218/1000)-1.245906883*AD218+0.7746840854*AE218-134.2474226*AC218-1547.125689*IF(AND(B218>=DATE(2020,3,20),B218<=DATE(2020,6,26)),1,0) -> 7852.1592 | AN218: =IF(ISNUMBER(C219),C219,AN219)-0.8328750492*(AD220-AD219)+3.274150872*(AE220-AE219)+0.7954612886*((IF(ISNUMBER(C219),C219,AN219)-IF(ISNUMBER(C218),C218,AN218))-(-0.8328750492*(AD219-AD218)+3.274150872*(AE219-AE218)))-1.394571582*AO219+0.4181414112*AO218 -> 7143.7551 | AP218: =AQ218+AR217+'ARIMAX(1,1,1) Model'!$C$19*(AR217-AR216)+'ARIMAX(1,1,1) Model'!$C$20*AS217 -> 7724.6971 | AQ218: ='ARIMAX(1,1,1) Model'!$C$6*I218+'ARIMAX(1,1,1) Model'!$C$7*N218/1000+'ARIMAX(1,1,1) Model'!$C$8*AD218+'ARIMAX(1,1,1) Model'!$C$9*AE218+'ARIMAX(1,1,1) Model'!$C$10*AC218+'ARIMAX(1,1,1) Model'!$C$11*IF(AND(B218>='ARIMAX(1,1,1) Model'!$C$25,B218<='ARIMAX(1,1,1) Model'!$C$26),1,0)+'ARIMAX(1,1,1) Model'!$C$12*E218/1000+'ARIMAX(1,1,1) Model'!$C$13*V218+'ARIMAX(1,1,1) Model'!$C$14*A218+'ARIMAX(1,1,1) Model'!$C$15*SIN(2*PI()*A218/'ARIMAX(1,1,1) Model'!$C$24)+'ARIMAX(1,1,1) Model'!$C$16*COS(2*PI()*A218/'ARIMAX(1,1,1) Model'!$C$24)+'ARIMAX(1,1,1) Model'!$C$17*SIN(4*PI()*A218/'ARIMAX(1,1,1) Model'!$C$24)+'ARIMAX(1,1,1) Model'!$C$18*COS(4*PI()*A218/'ARIMAX(1,1,1) Model'!$C$24) -> 1443.9217 | AR218: =IF(ISNUMBER(C218),C218,AP218)-AQ218 -> 6751.0783 | AS218: =IF(ISNUMBER(C218),C218-AP218,0) -> 470.30287
A219: 218 | B219: 34796 | C219: 7588 | E219: 335000 | G219: 19.428 | H219: 18.242 | I219: 1.087 | J219: 7455.288 | L219: 713 | M219: 14.861 | N219: 193838 | O219: 4850.8 | P219: 1021168 | R219: 2483 | U219: 27 | V219: 89.6 | AA219: 263455 | AC219: 0 | AD219: 95.4 | AE219: 0.1 | AG219: =6753.47943187+0.36116788*I219+0.01252571*N219-22.85359542*V219+0.00407811*AA219-0.00067349*E219 -> 7982.9278 | AH219: =A219*'Simple Linear Regression'!$B$18+'Simple Linear Regression'!$B$17 -> 8071.2984 | AI219: =7491.3971+0.0137554*N219-0.00058829*E219-34.3283*V219+0.30565*L219+54.6031*M219 -> 7914.2086 | AJ219: =7491.3971-0.00058829*E219+0.30565*L219+54.6031*M219+0.0137554*N219-34.3283*V219 -> 7914.2086 | AL219: =2192.59+2373.87*I219+0.0316653*N219-15.7623*V219+0.00202406*AA219-0.000740146*E219-0.00963493*(I219*N219) -> 7753.8247 | AM219: =5205.907083+122.0638992*I219+13.609808*(N219/1000)-1.245906883*AD219+0.7746840854*AE219-134.2474226*AC219-1547.125689*IF(AND(B219>=DATE(2020,3,20),B219<=DATE(2020,6,26)),1,0) -> 7857.9065 | AN219: =IF(ISNUMBER(C220),C220,AN220)-0.8328750492*(AD221-AD220)+3.274150872*(AE221-AE220)+0.7954612886*((IF(ISNUMBER(C220),C220,AN220)-IF(ISNUMBER(C219),C219,AN219))-(-0.8328750492*(AD220-AD219)+3.274150872*(AE220-AE219)))-1.394571582*AO220+0.4181414112*AO219 -> 7522.8567 | AP219: =AQ219+AR218+'ARIMAX(1,1,1) Model'!$C$19*(AR218-AR217)+'ARIMAX(1,1,1) Model'!$C$20*AS218 -> 7795.9161 | AQ219: ='ARIMAX(1,1,1) Model'!$C$6*I219+'ARIMAX(1,1,1) Model'!$C$7*N219/1000+'ARIMAX(1,1,1) Model'!$C$8*AD219+'ARIMAX(1,1,1) Model'!$C$9*AE219+'ARIMAX(1,1,1) Model'!$C$10*AC219+'ARIMAX(1,1,1) Model'!$C$11*IF(AND(B219>='ARIMAX(1,1,1) Model'!$C$25,B219<='ARIMAX(1,1,1) Model'!$C$26),1,0)+'ARIMAX(1,1,1) Model'!$C$12*E219/1000+'ARIMAX(1,1,1) Model'!$C$13*V219+'ARIMAX(1,1,1) Model'!$C$14*A219+'ARIMAX(1,1,1) Model'!$C$15*SIN(2*PI()*A219/'ARIMAX(1,1,1) Model'!$C$24)+'ARIMAX(1,1,1) Model'!$C$16*COS(2*PI()*A219/'ARIMAX(1,1,1) Model'!$C$24)+'ARIMAX(1,1,1) Model'!$C$17*SIN(4*PI()*A219/'ARIMAX(1,1,1) Model'!$C$24)+'ARIMAX(1,1,1) Model'!$C$18*COS(4*PI()*A219/'ARIMAX(1,1,1) Model'!$C$24) -> 1435.581 | AR219: =IF(ISNUMBER(C219),C219,AP219)-AQ219 -> 6152.419 | AS219: =IF(ISNUMBER(C219),C219-AP219,0) -> -207.91613
A220: 219 | B220: 34803 | C220: 7543 | E220: 347000 | G220: 19.5275 | H220: 18.3725 | I220: 1.103 | J220: 7455.288 | L220: 713 | M220: 14.861 | N220: 193838 | O220: 4850.8 | P220: 1021168 | R220: 2483 | U220: 27 | V220: 89.6 | AA220: 263455 | AC220: 0 | AD220: 74.8 | AE220: 4.8 | AG220: =6753.47943187+0.36116788*I220+0.01252571*N220-22.85359542*V220+0.00407811*AA220-0.00067349*E220 -> 7974.8517 | AH220: =A220*'Simple Linear Regression'!$B$18+'Simple Linear Regression'!$B$17 -> 8072.1515 | AI220: =7491.3971+0.0137554*N220-0.00058829*E220-34.3283*V220+0.30565*L220+54.6031*M220 -> 7907.1491 | AJ220: =7491.3971-0.00058829*E220+0.30565*L220+54.6031*M220+0.0137554*N220-34.3283*V220 -> 7907.1491 | AL220: =2192.59+2373.87*I220+0.0316653*N220-15.7623*V220+0.00202406*AA220-0.000740146*E220-0.00963493*(I220*N220) -> 7753.0431 | AM220: =5205.907083+122.0638992*I220+13.609808*(N220/1000)-1.245906883*AD220+0.7746840854*AE220-134.2474226*AC220-1547.125689*IF(AND(B220>=DATE(2020,3,20),B220<=DATE(2020,6,26)),1,0) -> 7889.1662 | AN220: =IF(ISNUMBER(C221),C221,AN221)-0.8328750492*(AD222-AD221)+3.274150872*(AE222-AE221)+0.7954612886*((IF(ISNUMBER(C221),C221,AN221)-IF(ISNUMBER(C220),C220,AN220))-(-0.8328750492*(AD221-AD220)+3.274150872*(AE221-AE220)))-1.394571582*AO221+0.4181414112*AO220 -> 8589.291 | AP220: =AQ220+AR219+'ARIMAX(1,1,1) Model'!$C$19*(AR219-AR218)+'ARIMAX(1,1,1) Model'!$C$20*AS219 -> 7764.3179 | AQ220: ='ARIMAX(1,1,1) Model'!$C$6*I220+'ARIMAX(1,1,1) Model'!$C$7*N220/1000+'ARIMAX(1,1,1) Model'!$C$8*AD220+'ARIMAX(1,1,1) Model'!$C$9*AE220+'ARIMAX(1,1,1) Model'!$C$10*AC220+'ARIMAX(1,1,1) Model'!$C$11*IF(AND(B220>='ARIMAX(1,1,1) Model'!$C$25,B220<='ARIMAX(1,1,1) Model'!$C$26),1,0)+'ARIMAX(1,1,1) Model'!$C$12*E220/1000+'ARIMAX(1,1,1) Model'!$C$13*V220+'ARIMAX(1,1,1) Model'!$C$14*A220+'ARIMAX(1,1,1) Model'!$C$15*SIN(2*PI()*A220/'ARIMAX(1,1,1) Model'!$C$24)+'ARIMAX(1,1,1) Model'!$C$16*COS(2*PI()*A220/'ARIMAX(1,1,1) Model'!$C$24)+'ARIMAX(1,1,1) Model'!$C$17*SIN(4*PI()*A220/'ARIMAX(1,1,1) Model'!$C$24)+'ARIMAX(1,1,1) Model'!$C$18*COS(4*PI()*A220/'ARIMAX(1,1,1) Model'!$C$24) -> 1483.1452 | AR220: =IF(ISNUMBER(C220),C220,AP220)-AQ220 -> 6059.8548 | AS220: =IF(ISNUMBER(C220),C220-AP220,0) -> -221.31789
A221: 220 | B221: 34810 | C221: 8156 | E221: 355000 | G221: 20.264 | H221: 18.9025 | I221: 1.117 | J221: 7455.288 | L221: 713 | M221: 15.256 | N221: 171053 | O221: 4850.8 | P221: 1021168 | R221: 2483 | U221: 27 | V221: 89.6 | AA221: 263455 | AC221: 0 | AD221: 66.2 | AE221: 15.3 | AG221: =6753.47943187+0.36116788*I221+0.01252571*N221-22.85359542*V221+0.00407811*AA221-0.00067349*E221 -> 7684.0705 | AH221: =A221*'Simple Linear Regression'!$B$18+'Simple Linear Regression'!$B$17 -> 8073.0045 | AI221: =7491.3971+0.0137554*N221-0.00058829*E221-34.3283*V221+0.30565*L221+54.6031*M221 -> 7610.5942 | AJ221: =7491.3971-0.00058829*E221+0.30565*L221+54.6031*M221+0.0137554*N221-34.3283*V221 -> 7610.5942 | AL221: =2192.59+2373.87*I221+0.0316653*N221-15.7623*V221+0.00202406*AA221-0.000740146*E221-0.00963493*(I221*N221) -> 7277.9327 | AM221: =5205.907083+122.0638992*I221+13.609808*(N221/1000)-1.245906883*AD221+0.7746840854*AE221-134.2474226*AC221-1547.125689*IF(AND(B221>=DATE(2020,3,20),B221<=DATE(2020,6,26)),1,0) -> 7599.6246 | AN221: =IF(ISNUMBER(C222),C222,AN222)-0.8328750492*(AD223-AD222)+3.274150872*(AE223-AE222)+0.7954612886*((IF(ISNUMBER(C222),C222,AN222)-IF(ISNUMBER(C221),C221,AN221))-(-0.8328750492*(AD222-AD221)+3.274150872*(AE222-AE221)))-1.394571582*AO222+0.4181414112*AO221 -> 7432.9323 | AP221: =AQ221+AR220+'ARIMAX(1,1,1) Model'!$C$19*(AR220-AR219)+'ARIMAX(1,1,1) Model'!$C$20*AS220 -> 7787.6242 | AQ221: ='ARIMAX(1,1,1) Model'!$C$6*I221+'ARIMAX(1,1,1) Model'!$C$7*N221/1000+'ARIMAX(1,1,1) Model'!$C$8*AD221+'ARIMAX(1,1,1) Model'!$C$9*AE221+'ARIMAX(1,1,1) Model'!$C$10*AC221+'ARIMAX(1,1,1) Model'!$C$11*IF(AND(B221>='ARIMAX(1,1,1) Model'!$C$25,B221<='ARIMAX(1,1,1) Model'!$C$26),1,0)+'ARIMAX(1,1,1) Model'!$C$12*E221/1000+'ARIMAX(1,1,1) Model'!$C$13*V221+'ARIMAX(1,1,1) Model'!$C$14*A221+'ARIMAX(1,1,1) Model'!$C$15*SIN(2*PI()*A221/'ARIMAX(1,1,1) Model'!$C$24)+'ARIMAX(1,1,1) Model'!$C$16*COS(2*PI()*A221/'ARIMAX(1,1,1) Model'!$C$24)+'ARIMAX(1,1,1) Model'!$C$17*SIN(4*PI()*A221/'ARIMAX(1,1,1) Model'!$C$24)+'ARIMAX(1,1,1) Model'!$C$18*COS(4*PI()*A221/'ARIMAX(1,1,1) Model'!$C$24) -> 1537.5928 | AR221: =IF(ISNUMBER(C221),C221,AP221)-AQ221 -> 6618.4072 | AS221: =IF(ISNUMBER(C221),C221-AP221,0) -> 368.37583
A222: 221 | B222: 34817 | C222: 7731 | E222: 349000 | G222: 20.292 | H222: 19.072 | I222: 1.138 | J222: 7455.288 | L222: 713 | M222: 15.256 | N222: 171053 | O222: 4850.8 | P222: 1021168 | R222: 2483 | U222: 27 | V222: 89.6 | AA222: 263455 | AC222: 0 | AD222: 54.8 | AE222: 5.9 | AG222: =6753.47943187+0.36116788*I222+0.01252571*N222-22.85359542*V222+0.00407811*AA222-0.00067349*E222 -> 7688.119 | AH222: =A222*'Simple Linear Regression'!$B$18+'Simple Linear Regression'!$B$17 -> 8073.8575 | AI222: =7491.3971+0.0137554*N222-0.00058829*E222-34.3283*V222+0.30565*L222+54.6031*M222 -> 7614.124 | AJ222: =7491.3971-0.00058829*E222+0.30565*L222+54.6031*M222+0.0137554*N222-34.3283*V222 -> 7614.124 | AL222: =2192.59+2373.87*I222+0.0316653*N222-15.7623*V222+0.00202406*AA222-0.000740146*E222-0.00963493*(I222*N222) -> 7297.6151 | AM222: =5205.907083+122.0638992*I222+13.609808*(N222/1000)-1.245906883*AD222+0.7746840854*AE222-134.2474226*AC222-1547.125689*IF(AND(B222>=DATE(2020,3,20),B222<=DATE(2020,6,26)),1,0) -> 7609.1092 | AN222: =IF(ISNUMBER(C223),C223,AN223)-0.8328750492*(AD224-AD223)+3.274150872*(AE224-AE223)+0.7954612886*((IF(ISNUMBER(C223),C223,AN223)-IF(ISNUMBER(C222),C222,AN222))-(-0.8328750492*(AD223-AD222)+3.274150872*(AE223-AE222)))-1.394571582*AO223+0.4181414112*AO222 -> 7415.0556 | AP222: =AQ222+AR221+'ARIMAX(1,1,1) Model'!$C$19*(AR221-AR220)+'ARIMAX(1,1,1) Model'!$C$20*AS221 -> 7893.8803 | AQ222: ='ARIMAX(1,1,1) Model'!$C$6*I222+'ARIMAX(1,1,1) Model'!$C$7*N222/1000+'ARIMAX(1,1,1) Model'!$C$8*AD222+'ARIMAX(1,1,1) Model'!$C$9*AE222+'ARIMAX(1,1,1) Model'!$C$10*AC222+'ARIMAX(1,1,1) Model'!$C$11*IF(AND(B222>='ARIMAX(1,1,1) Model'!$C$25,B222<='ARIMAX(1,1,1) Model'!$C$26),1,0)+'ARIMAX(1,1,1) Model'!$C$12*E222/1000+'ARIMAX(1,1,1) Model'!$C$13*V222+'ARIMAX(1,1,1) Model'!$C$14*A222+'ARIMAX(1,1,1) Model'!$C$15*SIN(2*PI()*A222/'ARIMAX(1,1,1) Model'!$C$24)+'ARIMAX(1,1,1) Model'!$C$16*COS(2*PI()*A222/'ARIMAX(1,1,1) Model'!$C$24)+'ARIMAX(1,1,1) Model'!$C$17*SIN(4*PI()*A222/'ARIMAX(1,1,1) Model'!$C$24)+'ARIMAX(1,1,1) Model'!$C$18*COS(4*PI()*A222/'ARIMAX(1,1,1) Model'!$C$24) -> 1552.5655 | AR222: =IF(ISNUMBER(C222),C222,AP222)-AQ222 -> 6178.4345 | AS222: =IF(ISNUMBER(C222),C222-AP222,0) -> -162.88028
A223: 222 | B223: 34824 | C223: 7539 | E223: 365000 | G223: 20.244 | H223: 18.814 | I223: 1.148 | J223: 7455.288 | L223: 713 | M223: 15.256 | N223: 171053 | O223: 4850.8 | P223: 1021168 | R223: 2483 | U223: 27 | V223: 87.9 | AA223: 263455 | AC223: 0 | AD223: 55.4 | AE223: 13.1 | AG223: =6753.47943187+0.36116788*I223+0.01252571*N223-22.85359542*V223+0.00407811*AA223-0.00067349*E223 -> 7716.1979 | AH223: =A223*'Simple Linear Regression'!$B$18+'Simple Linear Regression'!$B$17 -> 8074.7106 | AI223: =7491.3971+0.0137554*N223-0.00058829*E223-34.3283*V223+0.30565*L223+54.6031*M223 -> 7663.0695 | AJ223: =7491.3971-0.00058829*E223+0.30565*L223+54.6031*M223+0.0137554*N223-34.3283*V223 -> 7663.0695 | AL223: =2192.59+2373.87*I223+0.0316653*N223-15.7623*V223+0.00202406*AA223-0.000740146*E223-0.00963493*(I223*N223) -> 7319.8265 | AM223: =5205.907083+122.0638992*I223+13.609808*(N223/1000)-1.245906883*AD223+0.7746840854*AE223-134.2474226*AC223-1547.125689*IF(AND(B223>=DATE(2020,3,20),B223<=DATE(2020,6,26)),1,0) -> 7615.16 | AN223: =IF(ISNUMBER(C224),C224,AN224)-0.8328750492*(AD225-AD224)+3.274150872*(AE225-AE224)+0.7954612886*((IF(ISNUMBER(C224),C224,AN224)-IF(ISNUMBER(C223),C223,AN223))-(-0.8328750492*(AD224-AD223)+3.274150872*(AE224-AE223)))-1.394571582*AO224+0.4181414112*AO223 -> 8463.6074 | AP223: =AQ223+AR222+'ARIMAX(1,1,1) Model'!$C$19*(AR222-AR221)+'ARIMAX(1,1,1) Model'!$C$20*AS222 -> 7860.8867 | AQ223: ='ARIMAX(1,1,1) Model'!$C$6*I223+'ARIMAX(1,1,1) Model'!$C$7*N223/1000+'ARIMAX(1,1,1) Model'!$C$8*AD223+'ARIMAX(1,1,1) Model'!$C$9*AE223+'ARIMAX(1,1,1) Model'!$C$10*AC223+'ARIMAX(1,1,1) Model'!$C$11*IF(AND(B223>='ARIMAX(1,1,1) Model'!$C$25,B223<='ARIMAX(1,1,1) Model'!$C$26),1,0)+'ARIMAX(1,1,1) Model'!$C$12*E223/1000+'ARIMAX(1,1,1) Model'!$C$13*V223+'ARIMAX(1,1,1) Model'!$C$14*A223+'ARIMAX(1,1,1) Model'!$C$15*SIN(2*PI()*A223/'ARIMAX(1,1,1) Model'!$C$24)+'ARIMAX(1,1,1) Model'!$C$16*COS(2*PI()*A223/'ARIMAX(1,1,1) Model'!$C$24)+'ARIMAX(1,1,1) Model'!$C$17*SIN(4*PI()*A223/'ARIMAX(1,1,1) Model'!$C$24)+'ARIMAX(1,1,1) Model'!$C$18*COS(4*PI()*A223/'ARIMAX(1,1,1) Model'!$C$24) -> 1578.7576 | AR223: =IF(ISNUMBER(C223),C223,AP223)-AQ223 -> 5960.2424 | AS223: =IF(ISNUMBER(C223),C223-AP223,0) -> -321.88668
A224: 223 | B224: 34831 | C224: 8052 | E224: 364000 | G224: 19.74 | H224: 18.262 | I224: 1.169 | J224: 7522.289 | L224: 665 | M224: 15.256 | N224: 171053 | O224: 4885.4 | P224: 1021168 | R224: 2483 | U224: 27 | V224: 87.9 | AA224: 263455 | AC224: 0 | AD224: 38.9 | AE224: 23.3 | AG224: =6753.47943187+0.36116788*I224+0.01252571*N224-22.85359542*V224+0.00407811*AA224-0.00067349*E224 -> 7716.879 | AH224: =A224*'Simple Linear Regression'!$B$18+'Simple Linear Regression'!$B$17 -> 8075.5636 | AI224: =7491.3971+0.0137554*N224-0.00058829*E224-34.3283*V224+0.30565*L224+54.6031*M224 -> 7648.9865 | AJ224: =7491.3971-0.00058829*E224+0.30565*L224+54.6031*M224+0.0137554*N224-34.3283*V224 -> 7648.9865 | AL224: =2192.59+2373.87*I224+0.0316653*N224-15.7623*V224+0.00202406*AA224-0.000740146*E224-0.00963493*(I224*N224) -> 7335.8082 | AM224: =5205.907083+122.0638992*I224+13.609808*(N224/1000)-1.245906883*AD224+0.7746840854*AE224-134.2474226*AC224-1547.125689*IF(AND(B224>=DATE(2020,3,20),B224<=DATE(2020,6,26)),1,0) -> 7646.1826 | AN224: =IF(ISNUMBER(C225),C225,AN225)-0.8328750492*(AD226-AD225)+3.274150872*(AE226-AE225)+0.7954612886*((IF(ISNUMBER(C225),C225,AN225)-IF(ISNUMBER(C224),C224,AN224))-(-0.8328750492*(AD225-AD224)+3.274150872*(AE225-AE224)))-1.394571582*AO225+0.4181414112*AO224 -> 8237.1261 | AP224: =AQ224+AR223+'ARIMAX(1,1,1) Model'!$C$19*(AR223-AR222)+'ARIMAX(1,1,1) Model'!$C$20*AS223 -> 7860.456 | AQ224: ='ARIMAX(1,1,1) Model'!$C$6*I224+'ARIMAX(1,1,1) Model'!$C$7*N224/1000+'ARIMAX(1,1,1) Model'!$C$8*AD224+'ARIMAX(1,1,1) Model'!$C$9*AE224+'ARIMAX(1,1,1) Model'!$C$10*AC224+'ARIMAX(1,1,1) Model'!$C$11*IF(AND(B224>='ARIMAX(1,1,1) Model'!$C$25,B224<='ARIMAX(1,1,1) Model'!$C$26),1,0)+'ARIMAX(1,1,1) Model'!$C$12*E224/1000+'ARIMAX(1,1,1) Model'!$C$13*V224+'ARIMAX(1,1,1) Model'!$C$14*A224+'ARIMAX(1,1,1) Model'!$C$15*SIN(2*PI()*A224/'ARIMAX(1,1,1) Model'!$C$24)+'ARIMAX(1,1,1) Model'!$C$16*COS(2*PI()*A224/'ARIMAX(1,1,1) Model'!$C$24)+'ARIMAX(1,1,1) Model'!$C$17*SIN(4*PI()*A224/'ARIMAX(1,1,1) Model'!$C$24)+'ARIMAX(1,1,1) Model'!$C$18*COS(4*PI()*A224/'ARIMAX(1,1,1) Model'!$C$24) -> 1631.7694 | AR224: =IF(ISNUMBER(C224),C224,AP224)-AQ224 -> 6420.2306 | AS224: =IF(ISNUMBER(C224),C224-AP224,0) -> 191.54396
A225: 224 | B225: 34838 | C225: 8183 | E225: 366000 | G225: 19.982 | H225: 18.424 | I225: 1.179 | J225: 7522.289 | L225: 665 | M225: 14.378 | N225: 201227 | O225: 4885.4 | P225: 1021168 | R225: 2483 | U225: 27 | V225: 87.9 | AA225: 263455 | AC225: 0 | AD225: 25.8 | AE225: 32.5 | AG225: =6753.47943187+0.36116788*I225+0.01252571*N225-22.85359542*V225+0.00407811*AA225-0.00067349*E225 -> 8093.4864 | AH225: =A225*'Simple Linear Regression'!$B$18+'Simple Linear Regression'!$B$17 -> 8076.4167 | AI225: =7491.3971+0.0137554*N225-0.00058829*E225-34.3283*V225+0.30565*L225+54.6031*M225 -> 8014.9239 | AJ225: =7491.3971-0.00058829*E225+0.30565*L225+54.6031*M225+0.0137554*N225-34.3283*V225 -> 8014.9239 | AL225: =2192.59+2373.87*I225+0.0316653*N225-15.7623*V225+0.00202406*AA225-0.000740146*E225-0.00963493*(I225*N225) -> 7954.2905 | AM225: =5205.907083+122.0638992*I225+13.609808*(N225/1000)-1.245906883*AD225+0.7746840854*AE225-134.2474226*AC225-1547.125689*IF(AND(B225>=DATE(2020,3,20),B225<=DATE(2020,6,26)),1,0) -> 8081.5141 | AN225: =IF(ISNUMBER(C226),C226,AN226)-0.8328750492*(AD227-AD226)+3.274150872*(AE227-AE226)+0.7954612886*((IF(ISNUMBER(C226),C226,AN226)-IF(ISNUMBER(C225),C225,AN225))-(-0.8328750492*(AD226-AD225)+3.274150872*(AE226-AE225)))-1.394571582*AO226+0.4181414112*AO225 -> 7556.2448 | AP225: =AQ225+AR224+'ARIMAX(1,1,1) Model'!$C$19*(AR224-AR223)+'ARIMAX(1,1,1) Model'!$C$20*AS224 -> 7993.171 | AQ225: ='ARIMAX(1,1,1) Model'!$C$6*I225+'ARIMAX(1,1,1) Model'!$C$7*N225/1000+'ARIMAX(1,1,1) Model'!$C$8*AD225+'ARIMAX(1,1,1) Model'!$C$9*AE225+'ARIMAX(1,1,1) Model'!$C$10*AC225+'ARIMAX(1,1,1) Model'!$C$11*IF(AND(B225>='ARIMAX(1,1,1) Model'!$C$25,B225<='ARIMAX(1,1,1) Model'!$C$26),1,0)+'ARIMAX(1,1,1) Model'!$C$12*E225/1000+'ARIMAX(1,1,1) Model'!$C$13*V225+'ARIMAX(1,1,1) Model'!$C$14*A225+'ARIMAX(1,1,1) Model'!$C$15*SIN(2*PI()*A225/'ARIMAX(1,1,1) Model'!$C$24)+'ARIMAX(1,1,1) Model'!$C$16*COS(2*PI()*A225/'ARIMAX(1,1,1) Model'!$C$24)+'ARIMAX(1,1,1) Model'!$C$17*SIN(4*PI()*A225/'ARIMAX(1,1,1) Model'!$C$24)+'ARIMAX(1,1,1) Model'!$C$18*COS(4*PI()*A225/'ARIMAX(1,1,1) Model'!$C$24) -> 1700.4826 | AR225: =IF(ISNUMBER(C225),C225,AP225)-AQ225 -> 6482.5174 | AS225: =IF(ISNUMBER(C225),C225-AP225,0) -> 189.82897
... A484: 483 | B484: 36651 | C484: 8679 | E484: 291000 | G484: 26.75 | H484: 24.9625 | I484: 1.42 | J484: 9900.169 | L484: 763 | M484: 18.343 | N484: 199261 | O484: 6625.3 | P484: 1553622 | R484: 6119 | U484: 23 | V484: 86.4 | AA484: 279328 | AC484: 0 | AD484: 27.8 | AE484: 22.2 | AG484: =6753.47943187+0.36116788*I484+0.01252571*N484-22.85359542*V484+0.00407811*AA484-0.00067349*E484 -> 8218.4719 | AH484: =A484*'Simple Linear Regression'!$B$18+'Simple Linear Regression'!$B$17 -> 8297.3533 | AI484: =7491.3971+0.0137554*N484-0.00058829*E484-34.3283*V484+0.30565*L484+54.6031*M484 -> 8329.95 | AJ484: =7491.3971-0.00058829*E484+0.30565*L484+54.6031*M484+0.0137554*N484-34.3283*V484 -> 8329.95 | AL484: =2192.59+2373.87*I484+0.0316653*N484-15.7623*V484+0.00202406*AA484-0.000740146*E484-0.00963493*(I484*N484) -> 8135.0668 | AM484: =5205.907083+122.0638992*I484+13.609808*(N484/1000)-1.245906883*AD484+0.7746840854*AE484-134.2474226*AC484-1547.125689*IF(AND(B484>=DATE(2020,3,20),B484<=DATE(2020,6,26)),1,0) -> 8073.7035 | AN484: =IF(ISNUMBER(C485),C485,AN485)-0.8328750492*(AD486-AD485)+3.274150872*(AE486-AE485)+0.7954612886*((IF(ISNUMBER(C485),C485,AN485)-IF(ISNUMBER(C484),C484,AN484))-(-0.8328750492*(AD485-AD484)+3.274150872*(AE485-AE484)))-1.394571582*AO485+0.4181414112*AO484 -> 7763.8817 | AP484: =AQ484+AR483+'ARIMAX(1,1,1) Model'!$C$19*(AR483-AR482)+'ARIMAX(1,1,1) Model'!$C$20*AS483 -> 8542.997 | AQ484: ='ARIMAX(1,1,1) Model'!$C$6*I484+'ARIMAX(1,1,1) Model'!$C$7*N484/1000+'ARIMAX(1,1,1) Model'!$C$8*AD484+'ARIMAX(1,1,1) Model'!$C$9*AE484+'ARIMAX(1,1,1) Model'!$C$10*AC484+'ARIMAX(1,1,1) Model'!$C$11*IF(AND(B484>='ARIMAX(1,1,1) Model'!$C$25,B484<='ARIMAX(1,1,1) Model'!$C$26),1,0)+'ARIMAX(1,1,1) Model'!$C$12*E484/1000+'ARIMAX(1,1,1) Model'!$C$13*V484+'ARIMAX(1,1,1) Model'!$C$14*A484+'ARIMAX(1,1,1) Model'!$C$15*SIN(2*PI()*A484/'ARIMAX(1,1,1) Model'!$C$24)+'ARIMAX(1,1,1) Model'!$C$16*COS(2*PI()*A484/'ARIMAX(1,1,1) Model'!$C$24)+'ARIMAX(1,1,1) Model'!$C$17*SIN(4*PI()*A484/'ARIMAX(1,1,1) Model'!$C$24)+'ARIMAX(1,1,1) Model'!$C$18*COS(4*PI()*A484/'ARIMAX(1,1,1) Model'!$C$24) -> 1873.5616 | AR484: =IF(ISNUMBER(C484),C484,AP484)-AQ484 -> 6805.4384 | AS484: =IF(ISNUMBER(C484),C484-AP484,0) -> 136.00298
A485: 484 | B485: 36658 | C485: 8242 | E485: 293000 | G485: 28.7 | H485: 26.902 | I485: 1.455 | J485: 10002.179 | K485: 724934 | L485: 773 | M485: 18.343 | N485: 199261 | O485: 6686.5 | P485: 1553622 | R485: 6119 | U485: 23 | V485: 86.4 | AA485: 279328 | AC485: 0 | AD485: 6.7 | AE485: 44.2 | AG485: =6753.47943187+0.36116788*I485+0.01252571*N485-22.85359542*V485+0.00407811*AA485-0.00067349*E485 -> 8217.1375 | AH485: =A485*'Simple Linear Regression'!$B$18+'Simple Linear Regression'!$B$17 -> 8298.2063 | AI485: =7491.3971+0.0137554*N485-0.00058829*E485-34.3283*V485+0.30565*L485+54.6031*M485 -> 8331.8299 | AJ485: =7491.3971-0.00058829*E485+0.30565*L485+54.6031*M485+0.0137554*N485-34.3283*V485 -> 8331.8299 | AL485: =2192.59+2373.87*I485+0.0316653*N485-15.7623*V485+0.00202406*AA485-0.000740146*E485-0.00963493*(I485*N485) -> 8149.4766 | AM485: =5205.907083+122.0638992*I485+13.609808*(N485/1000)-1.245906883*AD485+0.7746840854*AE485-134.2474226*AC485-1547.125689*IF(AND(B485>=DATE(2020,3,20),B485<=DATE(2020,6,26)),1,0) -> 8121.3075 | AN485: =IF(ISNUMBER(C486),C486,AN486)-0.8328750492*(AD487-AD486)+3.274150872*(AE487-AE486)+0.7954612886*((IF(ISNUMBER(C486),C486,AN486)-IF(ISNUMBER(C485),C485,AN485))-(-0.8328750492*(AD486-AD485)+3.274150872*(AE486-AE485)))-1.394571582*AO486+0.4181414112*AO485 -> 8636.8496 | AP485: =AQ485+AR484+'ARIMAX(1,1,1) Model'!$C$19*(AR484-AR483)+'ARIMAX(1,1,1) Model'!$C$20*AS484 -> 8667.6931 | AQ485: ='ARIMAX(1,1,1) Model'!$C$6*I485+'ARIMAX(1,1,1) Model'!$C$7*N485/1000+'ARIMAX(1,1,1) Model'!$C$8*AD485+'ARIMAX(1,1,1) Model'!$C$9*AE485+'ARIMAX(1,1,1) Model'!$C$10*AC485+'ARIMAX(1,1,1) Model'!$C$11*IF(AND(B485>='ARIMAX(1,1,1) Model'!$C$25,B485<='ARIMAX(1,1,1) Model'!$C$26),1,0)+'ARIMAX(1,1,1) Model'!$C$12*E485/1000+'ARIMAX(1,1,1) Model'!$C$13*V485+'ARIMAX(1,1,1) Model'!$C$14*A485+'ARIMAX(1,1,1) Model'!$C$15*SIN(2*PI()*A485/'ARIMAX(1,1,1) Model'!$C$24)+'ARIMAX(1,1,1) Model'!$C$16*COS(2*PI()*A485/'ARIMAX(1,1,1) Model'!$C$24)+'ARIMAX(1,1,1) Model'!$C$17*SIN(4*PI()*A485/'ARIMAX(1,1,1) Model'!$C$24)+'ARIMAX(1,1,1) Model'!$C$18*COS(4*PI()*A485/'ARIMAX(1,1,1) Model'!$C$24) -> 1952.8141 | AR485: =IF(ISNUMBER(C485),C485,AP485)-AQ485 -> 6289.1859 | AS485: =IF(ISNUMBER(C485),C485-AP485,0) -> -425.69308
A486: 485 | B486: 36665 | C486: 8408 | E486: 276000 | G486: 29.878 | H486: 28.67 | I486: 1.492 | J486: 10002.179 | K486: 724934 | L486: 773 | M486: 17.939 | N486: 232490 | O486: 6686.5 | P486: 1553622 | R486: 6119 | U486: 23 | V486: 86.4 | AA486: 279328 | AC486: 0 | AD486: 21.2 | AE486: 29.8 | AG486: =6753.47943187+0.36116788*I486+0.01252571*N486-22.85359542*V486+0.00407811*AA486-0.00067349*E486 -> 8644.817 | AH486: =A486*'Simple Linear Regression'!$B$18+'Simple Linear Regression'!$B$17 -> 8299.0593 | AI486: =7491.3971+0.0137554*N486-0.00058829*E486-34.3283*V486+0.30565*L486+54.6031*M486 -> 8776.8493 | AJ486: =7491.3971-0.00058829*E486+0.30565*L486+54.6031*M486+0.0137554*N486-34.3283*V486 -> 8776.8493 | AL486: =2192.59+2373.87*I486+0.0316653*N486-15.7623*V486+0.00202406*AA486-0.000740146*E486-0.00963493*(I486*N486) -> 8753.3861 | AM486: =5205.907083+122.0638992*I486+13.609808*(N486/1000)-1.245906883*AD486+0.7746840854*AE486-134.2474226*AC486-1547.125689*IF(AND(B486>=DATE(2020,3,20),B486<=DATE(2020,6,26)),1,0) -> 8548.843 | AN486: =IF(ISNUMBER(C487),C487,AN487)-0.8328750492*(AD488-AD487)+3.274150872*(AE488-AE487)+0.7954612886*((IF(ISNUMBER(C487),C487,AN487)-IF(ISNUMBER(C486),C486,AN486))-(-0.8328750492*(AD487-AD486)+3.274150872*(AE487-AE486)))-1.394571582*AO487+0.4181414112*AO486 -> 9593.6936 | AP486: =AQ486+AR485+'ARIMAX(1,1,1) Model'!$C$19*(AR485-AR484)+'ARIMAX(1,1,1) Model'!$C$20*AS485 -> 8598.9481 | AQ486: ='ARIMAX(1,1,1) Model'!$C$6*I486+'ARIMAX(1,1,1) Model'!$C$7*N486/1000+'ARIMAX(1,1,1) Model'!$C$8*AD486+'ARIMAX(1,1,1) Model'!$C$9*AE486+'ARIMAX(1,1,1) Model'!$C$10*AC486+'ARIMAX(1,1,1) Model'!$C$11*IF(AND(B486>='ARIMAX(1,1,1) Model'!$C$25,B486<='ARIMAX(1,1,1) Model'!$C$26),1,0)+'ARIMAX(1,1,1) Model'!$C$12*E486/1000+'ARIMAX(1,1,1) Model'!$C$13*V486+'ARIMAX(1,1,1) Model'!$C$14*A486+'ARIMAX(1,1,1) Model'!$C$15*SIN(2*PI()*A486/'ARIMAX(1,1,1) Model'!$C$24)+'ARIMAX(1,1,1) Model'!$C$16*COS(2*PI()*A486/'ARIMAX(1,1,1) Model'!$C$24)+'ARIMAX(1,1,1) Model'!$C$17*SIN(4*PI()*A486/'ARIMAX(1,1,1) Model'!$C$24)+'ARIMAX(1,1,1) Model'!$C$18*COS(4*PI()*A486/'ARIMAX(1,1,1) Model'!$C$24) -> 1976.9538 | AR486: =IF(ISNUMBER(C486),C486,AP486)-AQ486 -> 6431.0462 | AS486: =IF(ISNUMBER(C486),C486-AP486,0) -> -190.9481
A487: 486 | B487: 36672 | C487: 9075 | E487: 280000 | G487: 29.462 | H487: 29.05 | I487: 1.527 | J487: 10002.179 | K487: 724934 | L487: 773 | M487: 17.939 | N487: 232490 | O487: 6686.5 | P487: 1553622 | R487: 6119 | U487: 23 | V487: 86.4 | AA487: 279328 | AC487: 0 | AD487: 15 | AE487: 43.4 | AG487: =6753.47943187+0.36116788*I487+0.01252571*N487-22.85359542*V487+0.00407811*AA487-0.00067349*E487 -> 8642.1357 | AH487: =A487*'Simple Linear Regression'!$B$18+'Simple Linear Regression'!$B$17 -> 8299.9124 | AI487: =7491.3971+0.0137554*N487-0.00058829*E487-34.3283*V487+0.30565*L487+54.6031*M487 -> 8774.4962 | AJ487: =7491.3971-0.00058829*E487+0.30565*L487+54.6031*M487+0.0137554*N487-34.3283*V487 -> 8774.4962 | AL487: =2192.59+2373.87*I487+0.0316653*N487-15.7623*V487+0.00202406*AA487-0.000740146*E487-0.00963493*(I487*N487) -> 8755.1101 | AM487: =5205.907083+122.0638992*I487+13.609808*(N487/1000)-1.245906883*AD487+0.7746840854*AE487-134.2474226*AC487-1547.125689*IF(AND(B487>=DATE(2020,3,20),B487<=DATE(2020,6,26)),1,0) -> 8571.3756 | AN487: =IF(ISNUMBER(C488),C488,AN488)-0.8328750492*(AD489-AD488)+3.274150872*(AE489-AE488)+0.7954612886*((IF(ISNUMBER(C488),C488,AN488)-IF(ISNUMBER(C487),C487,AN487))-(-0.8328750492*(AD488-AD487)+3.274150872*(AE488-AE487)))-1.394571582*AO488+0.4181414112*AO487 -> 8646.7581 | AP487: =AQ487+AR486+'ARIMAX(1,1,1) Model'!$C$19*(AR486-AR485)+'ARIMAX(1,1,1) Model'!$C$20*AS486 -> 8637.8484 | AQ487: ='ARIMAX(1,1,1) Model'!$C$6*I487+'ARIMAX(1,1,1) Model'!$C$7*N487/1000+'ARIMAX(1,1,1) Model'!$C$8*AD487+'ARIMAX(1,1,1) Model'!$C$9*AE487+'ARIMAX(1,1,1) Model'!$C$10*AC487+'ARIMAX(1,1,1) Model'!$C$11*IF(AND(B487>='ARIMAX(1,1,1) Model'!$C$25,B487<='ARIMAX(1,1,1) Model'!$C$26),1,0)+'ARIMAX(1,1,1) Model'!$C$12*E487/1000+'ARIMAX(1,1,1) Model'!$C$13*V487+'ARIMAX(1,1,1) Model'!$C$14*A487+'ARIMAX(1,1,1) Model'!$C$15*SIN(2*PI()*A487/'ARIMAX(1,1,1) Model'!$C$24)+'ARIMAX(1,1,1) Model'!$C$16*COS(2*PI()*A487/'ARIMAX(1,1,1) Model'!$C$24)+'ARIMAX(1,1,1) Model'!$C$17*SIN(4*PI()*A487/'ARIMAX(1,1,1) Model'!$C$24)+'ARIMAX(1,1,1) Model'!$C$18*COS(4*PI()*A487/'ARIMAX(1,1,1) Model'!$C$24) -> 2021.0971 | AR487: =IF(ISNUMBER(C487),C487,AP487)-AQ487 -> 7053.9029 | AS487: =IF(ISNUMBER(C487),C487-AP487,0) -> 437.15159
A488: 487 | B488: 36679 | C488: 8863 | E488: 280000 | G488: 29.98 | H488: 29.6425 | I488: 1.54 | J488: 10002.179 | K488: 724934 | L488: 773 | M488: 17.939 | N488: 232490 | O488: 6686.5 | P488: 1553622 | R488: 6119 | U488: 23 | V488: 86.4 | AA488: 279328 | AC488: 1 | AD488: 10.5 | AE488: 50.7 | AG488: =6753.47943187+0.36116788*I488+0.01252571*N488-22.85359542*V488+0.00407811*AA488-0.00067349*E488 -> 8642.1404 | AH488: =A488*'Simple Linear Regression'!$B$18+'Simple Linear Regression'!$B$17 -> 8300.7654 | AI488: =7491.3971+0.0137554*N488-0.00058829*E488-34.3283*V488+0.30565*L488+54.6031*M488 -> 8774.4962 | AJ488: =7491.3971-0.00058829*E488+0.30565*L488+54.6031*M488+0.0137554*N488-34.3283*V488 -> 8774.4962 | AL488: =2192.59+2373.87*I488+0.0316653*N488-15.7623*V488+0.00202406*AA488-0.000740146*E488-0.00963493*(I488*N488) -> 8756.8501 | AM488: =5205.907083+122.0638992*I488+13.609808*(N488/1000)-1.245906883*AD488+0.7746840854*AE488-134.2474226*AC488-1547.125689*IF(AND(B488>=DATE(2020,3,20),B488<=DATE(2020,6,26)),1,0) -> 8449.9768 | AN488: =IF(ISNUMBER(C489),C489,AN489)-0.8328750492*(AD490-AD489)+3.274150872*(AE490-AE489)+0.7954612886*((IF(ISNUMBER(C489),C489,AN489)-IF(ISNUMBER(C488),C488,AN488))-(-0.8328750492*(AD489-AD488)+3.274150872*(AE489-AE488)))-1.394571582*AO489+0.4181414112*AO488 -> 8163.318 | AP488: =AQ488+AR487+'ARIMAX(1,1,1) Model'!$C$19*(AR487-AR486)+'ARIMAX(1,1,1) Model'!$C$20*AS487 -> 8657.3249 | AQ488: ='ARIMAX(1,1,1) Model'!$C$6*I488+'ARIMAX(1,1,1) Model'!$C$7*N488/1000+'ARIMAX(1,1,1) Model'!$C$8*AD488+'ARIMAX(1,1,1) Model'!$C$9*AE488+'ARIMAX(1,1,1) Model'!$C$10*AC488+'ARIMAX(1,1,1) Model'!$C$11*IF(AND(B488>='ARIMAX(1,1,1) Model'!$C$25,B488<='ARIMAX(1,1,1) Model'!$C$26),1,0)+'ARIMAX(1,1,1) Model'!$C$12*E488/1000+'ARIMAX(1,1,1) Model'!$C$13*V488+'ARIMAX(1,1,1) Model'!$C$14*A488+'ARIMAX(1,1,1) Model'!$C$15*SIN(2*PI()*A488/'ARIMAX(1,1,1) Model'!$C$24)+'ARIMAX(1,1,1) Model'!$C$16*COS(2*PI()*A488/'ARIMAX(1,1,1) Model'!$C$24)+'ARIMAX(1,1,1) Model'!$C$17*SIN(4*PI()*A488/'ARIMAX(1,1,1) Model'!$C$24)+'ARIMAX(1,1,1) Model'!$C$18*COS(4*PI()*A488/'ARIMAX(1,1,1) Model'!$C$24) -> 1936.1467 | AR488: =IF(ISNUMBER(C488),C488,AP488)-AQ488 -> 6926.8533 | AS488: =IF(ISNUMBER(C488),C488-AP488,0) -> 205.6751
A489: 488 | B489: 36686 | C489: 8403 | E489: 290000 | G489: 29.788 | H489: 28.67 | I489: 1.563 | J489: 10002.179 | K489: 756536 | L489: 805 | M489: 17.939 | N489: 232490 | O489: 6679.1 | P489: 1553622 | R489: 6119 | U489: 23 | V489: 89.7 | AA489: 279328 | AC489: 0 | AD489: 9.8 | AE489: 42.7 | AG489: =6753.47943187+0.36116788*I489+0.01252571*N489-22.85359542*V489+0.00407811*AA489-0.00067349*E489 -> 8559.997 | AH489: =A489*'Simple Linear Regression'!$B$18+'Simple Linear Regression'!$B$17 -> 8301.6184 | AI489: =7491.3971+0.0137554*N489-0.00058829*E489-34.3283*V489+0.30565*L489+54.6031*M489 -> 8665.1107 | AJ489: =7491.3971-0.00058829*E489+0.30565*L489+54.6031*M489+0.0137554*N489-34.3283*V489 -> 8665.1107 | AL489: =2192.59+2373.87*I489+0.0316653*N489-15.7623*V489+0.00202406*AA489-0.000740146*E489-0.00963493*(I489*N489) -> 8700.5115 | AM489: =5205.907083+122.0638992*I489+13.609808*(N489/1000)-1.245906883*AD489+0.7746840854*AE489-134.2474226*AC489-1547.125689*IF(AND(B489>=DATE(2020,3,20),B489<=DATE(2020,6,26)),1,0) -> 8581.7063 | AN489: =IF(ISNUMBER(C490),C490,AN490)-0.8328750492*(AD491-AD490)+3.274150872*(AE491-AE490)+0.7954612886*((IF(ISNUMBER(C490),C490,AN490)-IF(ISNUMBER(C489),C489,AN489))-(-0.8328750492*(AD490-AD489)+3.274150872*(AE490-AE489)))-1.394571582*AO490+0.4181414112*AO489 -> 9183.2827 | AP489: =AQ489+AR488+'ARIMAX(1,1,1) Model'!$C$19*(AR488-AR487)+'ARIMAX(1,1,1) Model'!$C$20*AS488 -> 8790.8462 | AQ489: ='ARIMAX(1,1,1) Model'!$C$6*I489+'ARIMAX(1,1,1) Model'!$C$7*N489/1000+'ARIMAX(1,1,1) Model'!$C$8*AD489+'ARIMAX(1,1,1) Model'!$C$9*AE489+'ARIMAX(1,1,1) Model'!$C$10*AC489+'ARIMAX(1,1,1) Model'!$C$11*IF(AND(B489>='ARIMAX(1,1,1) Model'!$C$25,B489<='ARIMAX(1,1,1) Model'!$C$26),1,0)+'ARIMAX(1,1,1) Model'!$C$12*E489/1000+'ARIMAX(1,1,1) Model'!$C$13*V489+'ARIMAX(1,1,1) Model'!$C$14*A489+'ARIMAX(1,1,1) Model'!$C$15*SIN(2*PI()*A489/'ARIMAX(1,1,1) Model'!$C$24)+'ARIMAX(1,1,1) Model'!$C$16*COS(2*PI()*A489/'ARIMAX(1,1,1) Model'!$C$24)+'ARIMAX(1,1,1) Model'!$C$17*SIN(4*PI()*A489/'ARIMAX(1,1,1) Model'!$C$24)+'ARIMAX(1,1,1) Model'!$C$18*COS(4*PI()*A489/'ARIMAX(1,1,1) Model'!$C$24) -> 2061.509 | AR489: =IF(ISNUMBER(C489),C489,AP489)-AQ489 -> 6341.491 | AS489: =IF(ISNUMBER(C489),C489-AP489,0) -> -387.84618
A490: 489 | B490: 36693 | C490: 8895 | E490: 284000 | G490: 32.452 | H490: 29.814 | I490: 1.631 | J490: 10002.179 | K490: 756536 | L490: 805 | M490: 17.943 | N490: 227698 | O490: 6679.1 | P490: 1584412 | R490: 6119 | U490: 23 | V490: 89.7 | AA490: 279328 | AC490: 0 | AD490: 2.6 | AE490: 73.2 | AG490: =6753.47943187+0.36116788*I490+0.01252571*N490-22.85359542*V490+0.00407811*AA490-0.00067349*E490 -> 8504.0393 | AH490: =A490*'Simple Linear Regression'!$B$18+'Simple Linear Regression'!$B$17 -> 8302.4715 | AI490: =7491.3971+0.0137554*N490-0.00058829*E490-34.3283*V490+0.30565*L490+54.6031*M490 -> 8602.943 | AJ490: =7491.3971-0.00058829*E490+0.30565*L490+54.6031*M490+0.0137554*N490-34.3283*V490 -> 8602.943 | AL490: =2192.59+2373.87*I490+0.0316653*N490-15.7623*V490+0.00202406*AA490-0.000740146*E490-0.00963493*(I490*N490) -> 8637.618 | AM490: =5205.907083+122.0638992*I490+13.609808*(N490/1000)-1.245906883*AD490+0.7746840854*AE490-134.2474226*AC490-1547.125689*IF(AND(B490>=DATE(2020,3,20),B490<=DATE(2020,6,26)),1,0) -> 8557.3869 | AN490: =IF(ISNUMBER(C491),C491,AN491)-0.8328750492*(AD492-AD491)+3.274150872*(AE492-AE491)+0.7954612886*((IF(ISNUMBER(C491),C491,AN491)-IF(ISNUMBER(C490),C490,AN490))-(-0.8328750492*(AD491-AD490)+3.274150872*(AE491-AE490)))-1.394571582*AO491+0.4181414112*AO490 -> 8192.3552 | AP490: =AQ490+AR489+'ARIMAX(1,1,1) Model'!$C$19*(AR489-AR488)+'ARIMAX(1,1,1) Model'!$C$20*AS489 -> 8757.9424 | AQ490: ='ARIMAX(1,1,1) Model'!$C$6*I490+'ARIMAX(1,1,1) Model'!$C$7*N490/1000+'ARIMAX(1,1,1) Model'!$C$8*AD490+'ARIMAX(1,1,1) Model'!$C$9*AE490+'ARIMAX(1,1,1) Model'!$C$10*AC490+'ARIMAX(1,1,1) Model'!$C$11*IF(AND(B490>='ARIMAX(1,1,1) Model'!$C$25,B490<='ARIMAX(1,1,1) Model'!$C$26),1,0)+'ARIMAX(1,1,1) Model'!$C$12*E490/1000+'ARIMAX(1,1,1) Model'!$C$13*V490+'ARIMAX(1,1,1) Model'!$C$14*A490+'ARIMAX(1,1,1) Model'!$C$15*SIN(2*PI()*A490/'ARIMAX(1,1,1) Model'!$C$24)+'ARIMAX(1,1,1) Model'!$C$16*COS(2*PI()*A490/'ARIMAX(1,1,1) Model'!$C$24)+'ARIMAX(1,1,1) Model'!$C$17*SIN(4*PI()*A490/'ARIMAX(1,1,1) Model'!$C$24)+'ARIMAX(1,1,1) Model'!$C$18*COS(4*PI()*A490/'ARIMAX(1,1,1) Model'!$C$24) -> 2124.4488 | AR490: =IF(ISNUMBER(C490),C490,AP490)-AQ490 -> 6770.5512 | AS490: =IF(ISNUMBER(C490),C490-AP490,0) -> 137.05762
A491: 490 | B491: 36700 | C491: 8475 | E491: 294000 | G491: 33.552 | H491: 29.778 | I491: 1.681 | J491: 10002.179 | K491: 756536 | L491: 805 | M491: 17.943 | N491: 227698 | O491: 6679.1 | P491: 1584412 | R491: 6119 | U491: 23 | V491: 89.7 | AA491: 279328 | AC491: 0 | AD491: 0.5 | AE491: 66.9 | AG491: =6753.47943187+0.36116788*I491+0.01252571*N491-22.85359542*V491+0.00407811*AA491-0.00067349*E491 -> 8497.3224 | AH491: =A491*'Simple Linear Regression'!$B$18+'Simple Linear Regression'!$B$17 -> 8303.3245 | AI491: =7491.3971+0.0137554*N491-0.00058829*E491-34.3283*V491+0.30565*L491+54.6031*M491 -> 8597.0601 | AJ491: =7491.3971-0.00058829*E491+0.30565*L491+54.6031*M491+0.0137554*N491-34.3283*V491 -> 8597.0601 | AL491: =2192.59+2373.87*I491+0.0316653*N491-15.7623*V491+0.00202406*AA491-0.000740146*E491-0.00963493*(I491*N491) -> 8639.2173 | AM491: =5205.907083+122.0638992*I491+13.609808*(N491/1000)-1.245906883*AD491+0.7746840854*AE491-134.2474226*AC491-1547.125689*IF(AND(B491>=DATE(2020,3,20),B491<=DATE(2020,6,26)),1,0) -> 8561.226 | AN491: =IF(ISNUMBER(C492),C492,AN492)-0.8328750492*(AD493-AD492)+3.274150872*(AE493-AE492)+0.7954612886*((IF(ISNUMBER(C492),C492,AN492)-IF(ISNUMBER(C491),C491,AN491))-(-0.8328750492*(AD492-AD491)+3.274150872*(AE492-AE491)))-1.394571582*AO492+0.4181414112*AO491 -> 8707.6712 | AP491: =AQ491+AR490+'ARIMAX(1,1,1) Model'!$C$19*(AR490-AR489)+'ARIMAX(1,1,1) Model'!$C$20*AS490 -> 8758.6434 | AQ491: ='ARIMAX(1,1,1) Model'!$C$6*I491+'ARIMAX(1,1,1) Model'!$C$7*N491/1000+'ARIMAX(1,1,1) Model'!$C$8*AD491+'ARIMAX(1,1,1) Model'!$C$9*AE491+'ARIMAX(1,1,1) Model'!$C$10*AC491+'ARIMAX(1,1,1) Model'!$C$11*IF(AND(B491>='ARIMAX(1,1,1) Model'!$C$25,B491<='ARIMAX(1,1,1) Model'!$C$26),1,0)+'ARIMAX(1,1,1) Model'!$C$12*E491/1000+'ARIMAX(1,1,1) Model'!$C$13*V491+'ARIMAX(1,1,1) Model'!$C$14*A491+'ARIMAX(1,1,1) Model'!$C$15*SIN(2*PI()*A491/'ARIMAX(1,1,1) Model'!$C$24)+'ARIMAX(1,1,1) Model'!$C$16*COS(2*PI()*A491/'ARIMAX(1,1,1) Model'!$C$24)+'ARIMAX(1,1,1) Model'!$C$17*SIN(4*PI()*A491/'ARIMAX(1,1,1) Model'!$C$24)+'ARIMAX(1,1,1) Model'!$C$18*COS(4*PI()*A491/'ARIMAX(1,1,1) Model'!$C$24) -> 2069.6085 | AR491: =IF(ISNUMBER(C491),C491,AP491)-AQ491 -> 6405.3915 | AS491: =IF(ISNUMBER(C491),C491-AP491,0) -> -283.64336
A492: 491 | B492: 36707 | C492: 8620 | E492: 296000 | G492: 32.12 | H492: 31.03 | I492: 1.658 | J492: 10002.179 | K492: 756536 | L492: 805 | M492: 17.943 | N492: 227698 | O492: 6679.1 | P492: 1584412 | R492: 6119 | U492: 23 | V492: 89.7 | AA492: 279328 | AC492: 0 | AD492: 0 | AE492: 77.9 | AG492: =6753.47943187+0.36116788*I492+0.01252571*N492-22.85359542*V492+0.00407811*AA492-0.00067349*E492 -> 8495.9671 | AH492: =A492*'Simple Linear Regression'!$B$18+'Simple Linear Regression'!$B$17 -> 8304.1776 | AI492: =7491.3971+0.0137554*N492-0.00058829*E492-34.3283*V492+0.30565*L492+54.6031*M492 -> 8595.8835 | AJ492: =7491.3971-0.00058829*E492+0.30565*L492+54.6031*M492+0.0137554*N492-34.3283*V492 -> 8595.8835 | AL492: =2192.59+2373.87*I492+0.0316653*N492-15.7623*V492+0.00202406*AA492-0.000740146*E492-0.00963493*(I492*N492) -> 8633.5966 | AM492: =5205.907083+122.0638992*I492+13.609808*(N492/1000)-1.245906883*AD492+0.7746840854*AE492-134.2474226*AC492-1547.125689*IF(AND(B492>=DATE(2020,3,20),B492<=DATE(2020,6,26)),1,0) -> 8567.563 | AN492: =IF(ISNUMBER(C493),C493,AN493)-0.8328750492*(AD494-AD493)+3.274150872*(AE494-AE493)+0.7954612886*((IF(ISNUMBER(C493),C493,AN493)-IF(ISNUMBER(C492),C492,AN492))-(-0.8328750492*(AD493-AD492)+3.274150872*(AE493-AE492)))-1.394571582*AO493+0.4181414112*AO492 -> 8471.3404 | AP492: =AQ492+AR491+'ARIMAX(1,1,1) Model'!$C$19*(AR491-AR490)+'ARIMAX(1,1,1) Model'!$C$20*AS491 -> 8709.3333 | AQ492: ='ARIMAX(1,1,1) Model'!$C$6*I492+'ARIMAX(1,1,1) Model'!$C$7*N492/1000+'ARIMAX(1,1,1) Model'!$C$8*AD492+'ARIMAX(1,1,1) Model'!$C$9*AE492+'ARIMAX(1,1,1) Model'!$C$10*AC492+'ARIMAX(1,1,1) Model'!$C$11*IF(AND(B492>='ARIMAX(1,1,1) Model'!$C$25,B492<='ARIMAX(1,1,1) Model'!$C$26),1,0)+'ARIMAX(1,1,1) Model'!$C$12*E492/1000+'ARIMAX(1,1,1) Model'!$C$13*V492+'ARIMAX(1,1,1) Model'!$C$14*A492+'ARIMAX(1,1,1) Model'!$C$15*SIN(2*PI()*A492/'ARIMAX(1,1,1) Model'!$C$24)+'ARIMAX(1,1,1) Model'!$C$16*COS(2*PI()*A492/'ARIMAX(1,1,1) Model'!$C$24)+'ARIMAX(1,1,1) Model'!$C$17*SIN(4*PI()*A492/'ARIMAX(1,1,1) Model'!$C$24)+'ARIMAX(1,1,1) Model'!$C$18*COS(4*PI()*A492/'ARIMAX(1,1,1) Model'!$C$24) -> 2084.2537 | AR492: =IF(ISNUMBER(C492),C492,AP492)-AQ492 -> 6535.7463 | AS492: =IF(ISNUMBER(C492),C492-AP492,0) -> -89.333286
A493: 492 | B493: 36714 | C493: 8519 | E493: 281000 | G493: 30.403333 | H493: 30.904 | I493: 1.625 | J493: 10002.179 | K493: 756536 | L493: 844 | M493: 17.943 | N493: 227698 | O493: 6709.7 | P493: 1584412 | R493: 6119 | U493: 23 | V493: 92.6 | AA493: 279328 | AC493: 1 | AD493: 0 | AE493: 78.3 | AG493: =6753.47943187+0.36116788*I493+0.01252571*N493-22.85359542*V493+0.00407811*AA493-0.00067349*E493 -> 8439.7821 | AH493: =A493*'Simple Linear Regression'!$B$18+'Simple Linear Regression'!$B$17 -> 8305.0306 | AI493: =7491.3971+0.0137554*N493-0.00058829*E493-34.3283*V493+0.30565*L493+54.6031*M493 -> 8517.0761 | AJ493: =7491.3971-0.00058829*E493+0.30565*L493+54.6031*M493+0.0137554*N493-34.3283*V493 -> 8517.0761 | AL493: =2192.59+2373.87*I493+0.0316653*N493-15.7623*V493+0.00202406*AA493-0.000740146*E493-0.00963493*(I493*N493) -> 8593.0476 | AM493: =5205.907083+122.0638992*I493+13.609808*(N493/1000)-1.245906883*AD493+0.7746840854*AE493-134.2474226*AC493-1547.125689*IF(AND(B493>=DATE(2020,3,20),B493<=DATE(2020,6,26)),1,0) -> 8429.5973 | AN493: =IF(ISNUMBER(C494),C494,AN494)-0.8328750492*(AD495-AD494)+3.274150872*(AE495-AE494)+0.7954612886*((IF(ISNUMBER(C494),C494,AN494)-IF(ISNUMBER(C493),C493,AN493))-(-0.8328750492*(AD494-AD493)+3.274150872*(AE494-AE493)))-1.394571582*AO494+0.4181414112*AO493 -> 9079.3005 | AP493: =AQ493+AR492+'ARIMAX(1,1,1) Model'!$C$19*(AR492-AR491)+'ARIMAX(1,1,1) Model'!$C$20*AS492 -> 8642.5822 | AQ493: ='ARIMAX(1,1,1) Model'!$C$6*I493+'ARIMAX(1,1,1) Model'!$C$7*N493/1000+'ARIMAX(1,1,1) Model'!$C$8*AD493+'ARIMAX(1,1,1) Model'!$C$9*AE493+'ARIMAX(1,1,1) Model'!$C$10*AC493+'ARIMAX(1,1,1) Model'!$C$11*IF(AND(B493>='ARIMAX(1,1,1) Model'!$C$25,B493<='ARIMAX(1,1,1) Model'!$C$26),1,0)+'ARIMAX(1,1,1) Model'!$C$12*E493/1000+'ARIMAX(1,1,1) Model'!$C$13*V493+'ARIMAX(1,1,1) Model'!$C$14*A493+'ARIMAX(1,1,1) Model'!$C$15*SIN(2*PI()*A493/'ARIMAX(1,1,1) Model'!$C$24)+'ARIMAX(1,1,1) Model'!$C$16*COS(2*PI()*A493/'ARIMAX(1,1,1) Model'!$C$24)+'ARIMAX(1,1,1) Model'!$C$17*SIN(4*PI()*A493/'ARIMAX(1,1,1) Model'!$C$24)+'ARIMAX(1,1,1) Model'!$C$18*COS(4*PI()*A493/'ARIMAX(1,1,1) Model'!$C$24) -> 2013.7148 | AR493: =IF(ISNUMBER(C493),C493,AP493)-AQ493 -> 6505.2852 | AS493: =IF(ISNUMBER(C493),C493-AP493,0) -> -123.58221
A494: 493 | B494: 36721 | C494: 8844 | E494: 293000 | G494: 30.436 | H494: 30.53 | I494: 1.593 | J494: 10002.179 | K494: 843730 | L494: 844 | M494: 17.943 | N494: 227698 | O494: 6709.7 | P494: 1584412 | R494: 6119 | U494: 23 | V494: 92.6 | AA494: 279328 | AC494: 0 | AD494: 0 | AE494: 88.6 | AG494: =6753.47943187+0.36116788*I494+0.01252571*N494-22.85359542*V494+0.00407811*AA494-0.00067349*E494 -> 8431.6887 | AH494: =A494*'Simple Linear Regression'!$B$18+'Simple Linear Regression'!$B$17 -> 8305.8836 | AI494: =7491.3971+0.0137554*N494-0.00058829*E494-34.3283*V494+0.30565*L494+54.6031*M494 -> 8510.0166 | AJ494: =7491.3971-0.00058829*E494+0.30565*L494+54.6031*M494+0.0137554*N494-34.3283*V494 -> 8510.0166 | AL494: =2192.59+2373.87*I494+0.0316653*N494-15.7623*V494+0.00202406*AA494-0.000740146*E494-0.00963493*(I494*N494) -> 8578.4054 | AM494: =5205.907083+122.0638992*I494+13.609808*(N494/1000)-1.245906883*AD494+0.7746840854*AE494-134.2474226*AC494-1547.125689*IF(AND(B494>=DATE(2020,3,20),B494<=DATE(2020,6,26)),1,0) -> 8567.9179 | AN494: =IF(ISNUMBER(C495),C495,AN495)-0.8328750492*(AD496-AD495)+3.274150872*(AE496-AE495)+0.7954612886*((IF(ISNUMBER(C495),C495,AN495)-IF(ISNUMBER(C494),C494,AN494))-(-0.8328750492*(AD495-AD494)+3.274150872*(AE495-AE494)))-1.394571582*AO495+0.4181414112*AO494 -> 7929.7263 | AP494: =AQ494+AR493+'ARIMAX(1,1,1) Model'!$C$19*(AR493-AR492)+'ARIMAX(1,1,1) Model'!$C$20*AS493 -> 8737.5576 | AQ494: ='ARIMAX(1,1,1) Model'!$C$6*I494+'ARIMAX(1,1,1) Model'!$C$7*N494/1000+'ARIMAX(1,1,1) Model'!$C$8*AD494+'ARIMAX(1,1,1) Model'!$C$9*AE494+'ARIMAX(1,1,1) Model'!$C$10*AC494+'ARIMAX(1,1,1) Model'!$C$11*IF(AND(B494>='ARIMAX(1,1,1) Model'!$C$25,B494<='ARIMAX(1,1,1) Model'!$C$26),1,0)+'ARIMAX(1,1,1) Model'!$C$12*E494/1000+'ARIMAX(1,1,1) Model'!$C$13*V494+'ARIMAX(1,1,1) Model'!$C$14*A494+'ARIMAX(1,1,1) Model'!$C$15*SIN(2*PI()*A494/'ARIMAX(1,1,1) Model'!$C$24)+'ARIMAX(1,1,1) Model'!$C$16*COS(2*PI()*A494/'ARIMAX(1,1,1) Model'!$C$24)+'ARIMAX(1,1,1) Model'!$C$17*SIN(4*PI()*A494/'ARIMAX(1,1,1) Model'!$C$24)+'ARIMAX(1,1,1) Model'!$C$18*COS(4*PI()*A494/'ARIMAX(1,1,1) Model'!$C$24) -> 2124.0089 | AR494: =IF(ISNUMBER(C494),C494,AP494)-AQ494 -> 6719.9911 | AS494: =IF(ISNUMBER(C494),C494-AP494,0) -> 106.44244
A495: 494 | B495: 36728 | C495: 8361 | E495: 303000 | G495: 30.65 | H495: 27.952 | I495: 1.546 | J495: 10002.179 | K495: 843730 | L495: 844 | M495: 17.596 | N495: 242501 | O495: 6709.7 | P495: 1584412 | R495: 6119 | U495: 23 | V495: 92.6 | AA495: 279328 | AC495: 0 | AD495: 0 | AE495: 89.7 | AG495: =6753.47943187+0.36116788*I495+0.01252571*N495-22.85359542*V495+0.00407811*AA495-0.00067349*E495 -> 8610.3549 | AH495: =A495*'Simple Linear Regression'!$B$18+'Simple Linear Regression'!$B$17 -> 8306.7367 | AI495: =7491.3971+0.0137554*N495-0.00058829*E495-34.3283*V495+0.30565*L495+54.6031*M495 -> 8688.8077 | AJ495: =7491.3971-0.00058829*E495+0.30565*L495+54.6031*M495+0.0137554*N495-34.3283*V495 -> 8688.8077 | AL495: =2192.59+2373.87*I495+0.0316653*N495-15.7623*V495+0.00202406*AA495-0.000740146*E495-0.00963493*(I495*N495) -> 8810.785 | AM495: =5205.907083+122.0638992*I495+13.609808*(N495/1000)-1.245906883*AD495+0.7746840854*AE495-134.2474226*AC495-1547.125689*IF(AND(B495>=DATE(2020,3,20),B495<=DATE(2020,6,26)),1,0) -> 8764.4991 | AN495: =IF(ISNUMBER(C496),C496,AN496)-0.8328750492*(AD497-AD496)+3.274150872*(AE497-AE496)+0.7954612886*((IF(ISNUMBER(C496),C496,AN496)-IF(ISNUMBER(C495),C495,AN495))-(-0.8328750492*(AD496-AD495)+3.274150872*(AE496-AE495)))-1.394571582*AO496+0.4181414112*AO495 -> 8858.5973 | AP495: =AQ495+AR494+'ARIMAX(1,1,1) Model'!$C$19*(AR494-AR493)+'ARIMAX(1,1,1) Model'!$C$20*AS494 -> 8757.7755 | AQ495: ='ARIMAX(1,1,1) Model'!$C$6*I495+'ARIMAX(1,1,1) Model'!$C$7*N495/1000+'ARIMAX(1,1,1) Model'!$C$8*AD495+'ARIMAX(1,1,1) Model'!$C$9*AE495+'ARIMAX(1,1,1) Model'!$C$10*AC495+'ARIMAX(1,1,1) Model'!$C$11*IF(AND(B495>='ARIMAX(1,1,1) Model'!$C$25,B495<='ARIMAX(1,1,1) Model'!$C$26),1,0)+'ARIMAX(1,1,1) Model'!$C$12*E495/1000+'ARIMAX(1,1,1) Model'!$C$13*V495+'ARIMAX(1,1,1) Model'!$C$14*A495+'ARIMAX(1,1,1) Model'!$C$15*SIN(2*PI()*A495/'ARIMAX(1,1,1) Model'!$C$24)+'ARIMAX(1,1,1) Model'!$C$16*COS(2*PI()*A495/'ARIMAX(1,1,1) Model'!$C$24)+'ARIMAX(1,1,1) Model'!$C$17*SIN(4*PI()*A495/'ARIMAX(1,1,1) Model'!$C$24)+'ARIMAX(1,1,1) Model'!$C$18*COS(4*PI()*A495/'ARIMAX(1,1,1) Model'!$C$24) -> 2112.6509 | AR495: =IF(ISNUMBER(C495),C495,AP495)-AQ495 -> 6248.3491 | AS495: =IF(ISNUMBER(C495),C495-AP495,0) -> -396.77551
A496: 495 | B496: 36735 | C496: 8614 | E496: 300000 | G496: 28.02 | H496: 26.02 | I496: 1.52 | J496: 10002.179 | K496: 843730 | L496: 844 | M496: 17.596 | N496: 242501 | O496: 6709.7 | P496: 1584412 | R496: 6119 | U496: 23 | V496: 92.6 | AA496: 279328 | AC496: 0 | AD496: 0 | AE496: 76.2 | AG496: =6753.47943187+0.36116788*I496+0.01252571*N496-22.85359542*V496+0.00407811*AA496-0.00067349*E496 -> 8612.366 | AH496: =A496*'Simple Linear Regression'!$B$18+'Simple Linear Regression'!$B$17 -> 8307.5897 | AI496: =7491.3971+0.0137554*N496-0.00058829*E496-34.3283*V496+0.30565*L496+54.6031*M496 -> 8690.5725 | AJ496: =7491.3971-0.00058829*E496+0.30565*L496+54.6031*M496+0.0137554*N496-34.3283*V496 -> 8690.5725 | AL496: =2192.59+2373.87*I496+0.0316653*N496-15.7623*V496+0.00202406*AA496-0.000740146*E496-0.00963493*(I496*N496) -> 8812.0333 | AM496: =5205.907083+122.0638992*I496+13.609808*(N496/1000)-1.245906883*AD496+0.7746840854*AE496-134.2474226*AC496-1547.125689*IF(AND(B496>=DATE(2020,3,20),B496<=DATE(2020,6,26)),1,0) -> 8750.8672 | AN496: =IF(ISNUMBER(C497),C497,AN497)-0.8328750492*(AD498-AD497)+3.274150872*(AE498-AE497)+0.7954612886*((IF(ISNUMBER(C497),C497,AN497)-IF(ISNUMBER(C496),C496,AN496))-(-0.8328750492*(AD497-AD496)+3.274150872*(AE497-AE496)))-1.394571582*AO497+0.4181414112*AO496 -> 8932.3315 | AP496: =AQ496+AR495+'ARIMAX(1,1,1) Model'!$C$19*(AR495-AR494)+'ARIMAX(1,1,1) Model'!$C$20*AS495 -> 8609.2491 | AQ496: ='ARIMAX(1,1,1) Model'!$C$6*I496+'ARIMAX(1,1,1) Model'!$C$7*N496/1000+'ARIMAX(1,1,1) Model'!$C$8*AD496+'ARIMAX(1,1,1) Model'!$C$9*AE496+'ARIMAX(1,1,1) Model'!$C$10*AC496+'ARIMAX(1,1,1) Model'!$C$11*IF(AND(B496>='ARIMAX(1,1,1) Model'!$C$25,B496<='ARIMAX(1,1,1) Model'!$C$26),1,0)+'ARIMAX(1,1,1) Model'!$C$12*E496/1000+'ARIMAX(1,1,1) Model'!$C$13*V496+'ARIMAX(1,1,1) Model'!$C$14*A496+'ARIMAX(1,1,1) Model'!$C$15*SIN(2*PI()*A496/'ARIMAX(1,1,1) Model'!$C$24)+'ARIMAX(1,1,1) Model'!$C$16*COS(2*PI()*A496/'ARIMAX(1,1,1) Model'!$C$24)+'ARIMAX(1,1,1) Model'!$C$17*SIN(4*PI()*A496/'ARIMAX(1,1,1) Model'!$C$24)+'ARIMAX(1,1,1) Model'!$C$18*COS(4*PI()*A496/'ARIMAX(1,1,1) Model'!$C$24) -> 2049.7689 | AR496: =IF(ISNUMBER(C496),C496,AP496)-AQ496 -> 6564.2311 | AS496: =IF(ISNUMBER(C496),C496-AP496,0) -> 4.7509397
... A536: 535 | B536: 37015 | C536: 8665 | E536: 406000 | G536: 28.362 | H536: 27.278 | I536: 1.626 | J536: 10435.744 | K536: 755040 | L536: 1136 | M536: 17.248 | N536: 200876 | O536: 7001.8 | P536: 1741267 | R536: 8007 | U536: 25 | V536: 90.2 | AA536: 282398 | AC536: 0 | AD536: 18.3 | AE536: 17.4 | AG536: =6753.47943187+0.36116788*I536+0.01252571*N536-22.85359542*V536+0.00407811*AA536-0.00067349*E536 -> 8087.0001 | AH536: =A536*'Simple Linear Regression'!$B$18+'Simple Linear Regression'!$B$17 -> 8341.7112 | AI536: =7491.3971+0.0137554*N536-0.00058829*E536-34.3283*V536+0.30565*L536+54.6031*M536 -> 8208.2811 | AJ536: =7491.3971-0.00058829*E536+0.30565*L536+54.6031*M536+0.0137554*N536-34.3283*V536 -> 8208.2811 | AL536: =2192.59+2373.87*I536+0.0316653*N536-15.7623*V536+0.00202406*AA536-0.000740146*E536-0.00963493*(I536*N536) -> 8115.6302 | AM536: =5205.907083+122.0638992*I536+13.609808*(N536/1000)-1.245906883*AD536+0.7746840854*AE536-134.2474226*AC536-1547.125689*IF(AND(B536>=DATE(2020,3,20),B536<=DATE(2020,6,26)),1,0) -> 8128.9462 | AN536: =IF(ISNUMBER(C537),C537,AN537)-0.8328750492*(AD538-AD537)+3.274150872*(AE538-AE537)+0.7954612886*((IF(ISNUMBER(C537),C537,AN537)-IF(ISNUMBER(C536),C536,AN536))-(-0.8328750492*(AD537-AD536)+3.274150872*(AE537-AE536)))-1.394571582*AO537+0.4181414112*AO536 -> 7938.7869 | AP536: =AQ536+AR535+'ARIMAX(1,1,1) Model'!$C$19*(AR535-AR534)+'ARIMAX(1,1,1) Model'!$C$20*AS535 -> 8539.9019 | AQ536: ='ARIMAX(1,1,1) Model'!$C$6*I536+'ARIMAX(1,1,1) Model'!$C$7*N536/1000+'ARIMAX(1,1,1) Model'!$C$8*AD536+'ARIMAX(1,1,1) Model'!$C$9*AE536+'ARIMAX(1,1,1) Model'!$C$10*AC536+'ARIMAX(1,1,1) Model'!$C$11*IF(AND(B536>='ARIMAX(1,1,1) Model'!$C$25,B536<='ARIMAX(1,1,1) Model'!$C$26),1,0)+'ARIMAX(1,1,1) Model'!$C$12*E536/1000+'ARIMAX(1,1,1) Model'!$C$13*V536+'ARIMAX(1,1,1) Model'!$C$14*A536+'ARIMAX(1,1,1) Model'!$C$15*SIN(2*PI()*A536/'ARIMAX(1,1,1) Model'!$C$24)+'ARIMAX(1,1,1) Model'!$C$16*COS(2*PI()*A536/'ARIMAX(1,1,1) Model'!$C$24)+'ARIMAX(1,1,1) Model'!$C$17*SIN(4*PI()*A536/'ARIMAX(1,1,1) Model'!$C$24)+'ARIMAX(1,1,1) Model'!$C$18*COS(4*PI()*A536/'ARIMAX(1,1,1) Model'!$C$24) -> 1838.2478 | AR536: =IF(ISNUMBER(C536),C536,AP536)-AQ536 -> 6826.7522 | AS536: =IF(ISNUMBER(C536),C536-AP536,0) -> 125.09814
A537: 536 | B537: 37022 | C537: 8275 | E537: 381000 | G537: 28.124 | H537: 27.772 | I537: 1.703 | J537: 10470.231 | K537: 755040 | L537: 1163 | M537: 17.248 | N537: 200876 | O537: 6996.7 | P537: 1741267 | R537: 8007 | T537: 84.7 | U537: 25 | V537: 90.5 | AA537: 282398 | AC537: 0 | AD537: 15.2 | AE537: 26.6 | AG537: =6753.47943187+0.36116788*I537+0.01252571*N537-22.85359542*V537+0.00407811*AA537-0.00067349*E537 -> 8097.0091 | AH537: =A537*'Simple Linear Regression'!$B$18+'Simple Linear Regression'!$B$17 -> 8342.5642 | AI537: =7491.3971+0.0137554*N537-0.00058829*E537-34.3283*V537+0.30565*L537+54.6031*M537 -> 8220.9424 | AJ537: =7491.3971-0.00058829*E537+0.30565*L537+54.6031*M537+0.0137554*N537-34.3283*V537 -> 8220.9424 | AL537: =2192.59+2373.87*I537+0.0316653*N537-15.7623*V537+0.00202406*AA537-0.000740146*E537-0.00963493*(I537*N537) -> 8163.1653 | AM537: =5205.907083+122.0638992*I537+13.609808*(N537/1000)-1.245906883*AD537+0.7746840854*AE537-134.2474226*AC537-1547.125689*IF(AND(B537>=DATE(2020,3,20),B537<=DATE(2020,6,26)),1,0) -> 8149.3345 | AN537: =IF(ISNUMBER(C538),C538,AN538)-0.8328750492*(AD539-AD538)+3.274150872*(AE539-AE538)+0.7954612886*((IF(ISNUMBER(C538),C538,AN538)-IF(ISNUMBER(C537),C537,AN537))-(-0.8328750492*(AD538-AD537)+3.274150872*(AE538-AE537)))-1.394571582*AO538+0.4181414112*AO537 -> 9427.7213 | AP537: =AQ537+AR536+'ARIMAX(1,1,1) Model'!$C$19*(AR536-AR535)+'ARIMAX(1,1,1) Model'!$C$20*AS536 -> 8640.9399 | AQ537: ='ARIMAX(1,1,1) Model'!$C$6*I537+'ARIMAX(1,1,1) Model'!$C$7*N537/1000+'ARIMAX(1,1,1) Model'!$C$8*AD537+'ARIMAX(1,1,1) Model'!$C$9*AE537+'ARIMAX(1,1,1) Model'!$C$10*AC537+'ARIMAX(1,1,1) Model'!$C$11*IF(AND(B537>='ARIMAX(1,1,1) Model'!$C$25,B537<='ARIMAX(1,1,1) Model'!$C$26),1,0)+'ARIMAX(1,1,1) Model'!$C$12*E537/1000+'ARIMAX(1,1,1) Model'!$C$13*V537+'ARIMAX(1,1,1) Model'!$C$14*A537+'ARIMAX(1,1,1) Model'!$C$15*SIN(2*PI()*A537/'ARIMAX(1,1,1) Model'!$C$24)+'ARIMAX(1,1,1) Model'!$C$16*COS(2*PI()*A537/'ARIMAX(1,1,1) Model'!$C$24)+'ARIMAX(1,1,1) Model'!$C$17*SIN(4*PI()*A537/'ARIMAX(1,1,1) Model'!$C$24)+'ARIMAX(1,1,1) Model'!$C$18*COS(4*PI()*A537/'ARIMAX(1,1,1) Model'!$C$24) -> 1906.1255 | AR537: =IF(ISNUMBER(C537),C537,AP537)-AQ537 -> 6368.8745 | AS537: =IF(ISNUMBER(C537),C537-AP537,0) -> -365.93987
A538: 537 | B538: 37029 | C538: 8917 | E538: 390000 | G538: 29.084 | H538: 28.342 | I538: 1.713 | J538: 10470.231 | K538: 800293 | L538: 1163 | M538: 16.872 | N538: 232587 | O538: 6996.7 | P538: 1741267 | R538: 8007 | T538: 84.7 | U538: 25 | V538: 90.5 | AA538: 282398 | AC538: 0 | AD538: 18.7 | AE538: 27.5 | AG538: =6753.47943187+0.36116788*I538+0.01252571*N538-22.85359542*V538+0.00407811*AA538-0.00067349*E538 -> 8488.154 | AH538: =A538*'Simple Linear Regression'!$B$18+'Simple Linear Regression'!$B$17 -> 8343.4173 | AI538: =7491.3971+0.0137554*N538-0.00058829*E538-34.3283*V538+0.30565*L538+54.6031*M538 -> 8631.3145 | AJ538: =7491.3971-0.00058829*E538+0.30565*L538+54.6031*M538+0.0137554*N538-34.3283*V538 -> 8631.3145 | AL538: =2192.59+2373.87*I538+0.0316653*N538-15.7623*V538+0.00202406*AA538-0.000740146*E538-0.00963493*(I538*N538) -> 8641.6483 | AM538: =5205.907083+122.0638992*I538+13.609808*(N538/1000)-1.245906883*AD538+0.7746840854*AE538-134.2474226*AC538-1547.125689*IF(AND(B538>=DATE(2020,3,20),B538<=DATE(2020,6,26)),1,0) -> 8578.4723 | AN538: =IF(ISNUMBER(C539),C539,AN539)-0.8328750492*(AD540-AD539)+3.274150872*(AE540-AE539)+0.7954612886*((IF(ISNUMBER(C539),C539,AN539)-IF(ISNUMBER(C538),C538,AN538))-(-0.8328750492*(AD539-AD538)+3.274150872*(AE539-AE538)))-1.394571582*AO539+0.4181414112*AO538 -> 7757.7069 | AP538: =AQ538+AR537+'ARIMAX(1,1,1) Model'!$C$19*(AR537-AR536)+'ARIMAX(1,1,1) Model'!$C$20*AS537 -> 8611.1385 | AQ538: ='ARIMAX(1,1,1) Model'!$C$6*I538+'ARIMAX(1,1,1) Model'!$C$7*N538/1000+'ARIMAX(1,1,1) Model'!$C$8*AD538+'ARIMAX(1,1,1) Model'!$C$9*AE538+'ARIMAX(1,1,1) Model'!$C$10*AC538+'ARIMAX(1,1,1) Model'!$C$11*IF(AND(B538>='ARIMAX(1,1,1) Model'!$C$25,B538<='ARIMAX(1,1,1) Model'!$C$26),1,0)+'ARIMAX(1,1,1) Model'!$C$12*E538/1000+'ARIMAX(1,1,1) Model'!$C$13*V538+'ARIMAX(1,1,1) Model'!$C$14*A538+'ARIMAX(1,1,1) Model'!$C$15*SIN(2*PI()*A538/'ARIMAX(1,1,1) Model'!$C$24)+'ARIMAX(1,1,1) Model'!$C$16*COS(2*PI()*A538/'ARIMAX(1,1,1) Model'!$C$24)+'ARIMAX(1,1,1) Model'!$C$17*SIN(4*PI()*A538/'ARIMAX(1,1,1) Model'!$C$24)+'ARIMAX(1,1,1) Model'!$C$18*COS(4*PI()*A538/'ARIMAX(1,1,1) Model'!$C$24) -> 1957.5451 | AR538: =IF(ISNUMBER(C538),C538,AP538)-AQ538 -> 6959.4549 | AS538: =IF(ISNUMBER(C538),C538-AP538,0) -> 305.86153
A539: 538 | B539: 37036 | C539: 8270 | E539: 402000 | G539: 28.922 | H539: 29.314 | I539: 1.687 | J539: 10470.231 | K539: 800293 | L539: 1163 | M539: 16.872 | N539: 232587 | O539: 6996.7 | P539: 1741267 | R539: 8007 | T539: 84.7 | U539: 25 | V539: 90.5 | AA539: 282398 | AC539: 0 | AD539: 20.2 | AE539: 27.9 | AG539: =6753.47943187+0.36116788*I539+0.01252571*N539-22.85359542*V539+0.00407811*AA539-0.00067349*E539 -> 8480.0628 | AH539: =A539*'Simple Linear Regression'!$B$18+'Simple Linear Regression'!$B$17 -> 8344.2703 | AI539: =7491.3971+0.0137554*N539-0.00058829*E539-34.3283*V539+0.30565*L539+54.6031*M539 -> 8624.255 | AJ539: =7491.3971-0.00058829*E539+0.30565*L539+54.6031*M539+0.0137554*N539-34.3283*V539 -> 8624.255 | AL539: =2192.59+2373.87*I539+0.0316653*N539-15.7623*V539+0.00202406*AA539-0.000740146*E539-0.00963493*(I539*N539) -> 8629.3109 | AM539: =5205.907083+122.0638992*I539+13.609808*(N539/1000)-1.245906883*AD539+0.7746840854*AE539-134.2474226*AC539-1547.125689*IF(AND(B539>=DATE(2020,3,20),B539<=DATE(2020,6,26)),1,0) -> 8573.7397 | AN539: =IF(ISNUMBER(C540),C540,AN540)-0.8328750492*(AD541-AD540)+3.274150872*(AE541-AE540)+0.7954612886*((IF(ISNUMBER(C540),C540,AN540)-IF(ISNUMBER(C539),C539,AN539))-(-0.8328750492*(AD540-AD539)+3.274150872*(AE540-AE539)))-1.394571582*AO540+0.4181414112*AO539 -> 9253.559 | AP539: =AQ539+AR538+'ARIMAX(1,1,1) Model'!$C$19*(AR538-AR537)+'ARIMAX(1,1,1) Model'!$C$20*AS538 -> 8718.8638 | AQ539: ='ARIMAX(1,1,1) Model'!$C$6*I539+'ARIMAX(1,1,1) Model'!$C$7*N539/1000+'ARIMAX(1,1,1) Model'!$C$8*AD539+'ARIMAX(1,1,1) Model'!$C$9*AE539+'ARIMAX(1,1,1) Model'!$C$10*AC539+'ARIMAX(1,1,1) Model'!$C$11*IF(AND(B539>='ARIMAX(1,1,1) Model'!$C$25,B539<='ARIMAX(1,1,1) Model'!$C$26),1,0)+'ARIMAX(1,1,1) Model'!$C$12*E539/1000+'ARIMAX(1,1,1) Model'!$C$13*V539+'ARIMAX(1,1,1) Model'!$C$14*A539+'ARIMAX(1,1,1) Model'!$C$15*SIN(2*PI()*A539/'ARIMAX(1,1,1) Model'!$C$24)+'ARIMAX(1,1,1) Model'!$C$16*COS(2*PI()*A539/'ARIMAX(1,1,1) Model'!$C$24)+'ARIMAX(1,1,1) Model'!$C$17*SIN(4*PI()*A539/'ARIMAX(1,1,1) Model'!$C$24)+'ARIMAX(1,1,1) Model'!$C$18*COS(4*PI()*A539/'ARIMAX(1,1,1) Model'!$C$24) -> 1977.1095 | AR539: =IF(ISNUMBER(C539),C539,AP539)-AQ539 -> 6292.8905 | AS539: =IF(ISNUMBER(C539),C539-AP539,0) -> -448.86379
A540: 539 | B540: 37043 | C540: 8809 | E540: 405000 | G540: 28.435 | H540: 28.86 | I540: 1.704 | J540: 10470.231 | K540: 800293 | L540: 1163 | M540: 16.872 | N540: 232587 | O540: 6996.7 | P540: 1741267 | R540: 8007 | T540: 84.7 | U540: 25 | V540: 90.5 | AA540: 282398 | AC540: 1 | AD540: 22.8 | AE540: 29.3 | AG540: =6753.47943187+0.36116788*I540+0.01252571*N540-22.85359542*V540+0.00407811*AA540-0.00067349*E540 -> 8478.0484 | AH540: =A540*'Simple Linear Regression'!$B$18+'Simple Linear Regression'!$B$17 -> 8345.1233 | AI540: =7491.3971+0.0137554*N540-0.00058829*E540-34.3283*V540+0.30565*L540+54.6031*M540 -> 8622.4902 | AJ540: =7491.3971-0.00058829*E540+0.30565*L540+54.6031*M540+0.0137554*N540-34.3283*V540 -> 8622.4902 | AL540: =2192.59+2373.87*I540+0.0316653*N540-15.7623*V540+0.00202406*AA540-0.000740146*E540-0.00963493*(I540*N540) -> 8629.3499 | AM540: =5205.907083+122.0638992*I540+13.609808*(N540/1000)-1.245906883*AD540+0.7746840854*AE540-134.2474226*AC540-1547.125689*IF(AND(B540>=DATE(2020,3,20),B540<=DATE(2020,6,26)),1,0) -> 8439.4125 | AN540: =IF(ISNUMBER(C541),C541,AN541)-0.8328750492*(AD542-AD541)+3.274150872*(AE542-AE541)+0.7954612886*((IF(ISNUMBER(C541),C541,AN541)-IF(ISNUMBER(C540),C540,AN540))-(-0.8328750492*(AD541-AD540)+3.274150872*(AE541-AE540)))-1.394571582*AO541+0.4181414112*AO540 -> 8218.8243 | AP540: =AQ540+AR539+'ARIMAX(1,1,1) Model'!$C$19*(AR539-AR538)+'ARIMAX(1,1,1) Model'!$C$20*AS539 -> 8509.5296 | AQ540: ='ARIMAX(1,1,1) Model'!$C$6*I540+'ARIMAX(1,1,1) Model'!$C$7*N540/1000+'ARIMAX(1,1,1) Model'!$C$8*AD540+'ARIMAX(1,1,1) Model'!$C$9*AE540+'ARIMAX(1,1,1) Model'!$C$10*AC540+'ARIMAX(1,1,1) Model'!$C$11*IF(AND(B540>='ARIMAX(1,1,1) Model'!$C$25,B540<='ARIMAX(1,1,1) Model'!$C$26),1,0)+'ARIMAX(1,1,1) Model'!$C$12*E540/1000+'ARIMAX(1,1,1) Model'!$C$13*V540+'ARIMAX(1,1,1) Model'!$C$14*A540+'ARIMAX(1,1,1) Model'!$C$15*SIN(2*PI()*A540/'ARIMAX(1,1,1) Model'!$C$24)+'ARIMAX(1,1,1) Model'!$C$16*COS(2*PI()*A540/'ARIMAX(1,1,1) Model'!$C$24)+'ARIMAX(1,1,1) Model'!$C$17*SIN(4*PI()*A540/'ARIMAX(1,1,1) Model'!$C$24)+'ARIMAX(1,1,1) Model'!$C$18*COS(4*PI()*A540/'ARIMAX(1,1,1) Model'!$C$24) -> 1877.6353 | AR540: =IF(ISNUMBER(C540),C540,AP540)-AQ540 -> 6931.3647 | AS540: =IF(ISNUMBER(C540),C540-AP540,0) -> 299.47039
A541: 540 | B541: 37050 | C541: 8428 | E541: 406000 | G541: 27.976 | H541: 28.872 | I541: 1.679 | J541: 10470.231 | K541: 800293 | L541: 1206 | M541: 16.872 | N541: 232587 | O541: 7004.2 | P541: 1741267 | R541: 8007 | T541: 84.7 | U541: 25 | V541: 89.4 | AA541: 282398 | AC541: 0 | AD541: 13.7 | AE541: 32.4 | AG541: =6753.47943187+0.36116788*I541+0.01252571*N541-22.85359542*V541+0.00407811*AA541-0.00067349*E541 -> 8502.5049 | AH541: =A541*'Simple Linear Regression'!$B$18+'Simple Linear Regression'!$B$17 -> 8345.9764 | AI541: =7491.3971+0.0137554*N541-0.00058829*E541-34.3283*V541+0.30565*L541+54.6031*M541 -> 8672.806 | AJ541: =7491.3971-0.00058829*E541+0.30565*L541+54.6031*M541+0.0137554*N541-34.3283*V541 -> 8672.806 | AL541: =2192.59+2373.87*I541+0.0316653*N541-15.7623*V541+0.00202406*AA541-0.000740146*E541-0.00963493*(I541*N541) -> 8642.6255 | AM541: =5205.907083+122.0638992*I541+13.609808*(N541/1000)-1.245906883*AD541+0.7746840854*AE541-134.2474226*AC541-1547.125689*IF(AND(B541>=DATE(2020,3,20),B541<=DATE(2020,6,26)),1,0) -> 8584.3476 | AN541: =IF(ISNUMBER(C542),C542,AN542)-0.8328750492*(AD543-AD542)+3.274150872*(AE543-AE542)+0.7954612886*((IF(ISNUMBER(C542),C542,AN542)-IF(ISNUMBER(C541),C541,AN541))-(-0.8328750492*(AD542-AD541)+3.274150872*(AE542-AE541)))-1.394571582*AO542+0.4181414112*AO541 -> 8300.6103 | AP541: =AQ541+AR540+'ARIMAX(1,1,1) Model'!$C$19*(AR540-AR539)+'ARIMAX(1,1,1) Model'!$C$20*AS540 -> 8703.6165 | AQ541: ='ARIMAX(1,1,1) Model'!$C$6*I541+'ARIMAX(1,1,1) Model'!$C$7*N541/1000+'ARIMAX(1,1,1) Model'!$C$8*AD541+'ARIMAX(1,1,1) Model'!$C$9*AE541+'ARIMAX(1,1,1) Model'!$C$10*AC541+'ARIMAX(1,1,1) Model'!$C$11*IF(AND(B541>='ARIMAX(1,1,1) Model'!$C$25,B541<='ARIMAX(1,1,1) Model'!$C$26),1,0)+'ARIMAX(1,1,1) Model'!$C$12*E541/1000+'ARIMAX(1,1,1) Model'!$C$13*V541+'ARIMAX(1,1,1) Model'!$C$14*A541+'ARIMAX(1,1,1) Model'!$C$15*SIN(2*PI()*A541/'ARIMAX(1,1,1) Model'!$C$24)+'ARIMAX(1,1,1) Model'!$C$16*COS(2*PI()*A541/'ARIMAX(1,1,1) Model'!$C$24)+'ARIMAX(1,1,1) Model'!$C$17*SIN(4*PI()*A541/'ARIMAX(1,1,1) Model'!$C$24)+'ARIMAX(1,1,1) Model'!$C$18*COS(4*PI()*A541/'ARIMAX(1,1,1) Model'!$C$24) -> 1979.5288 | AR541: =IF(ISNUMBER(C541),C541,AP541)-AQ541 -> 6448.4712 | AS541: =IF(ISNUMBER(C541),C541-AP541,0) -> -275.61654
A542: 541 | B542: 37057 | C542: 8393 | E542: 411000 | G542: 28.904 | H542: 28.872 | I542: 1.647 | J542: 10470.231 | K542: 761213 | L542: 1206 | M542: 16.872 | N542: 232513 | O542: 7004.2 | P542: 1784759 | R542: 8007 | T542: 84.7 | U542: 25 | V542: 89.4 | AA542: 282398 | AC542: 0 | AD542: 0 | AE542: 61.9 | AG542: =6753.47943187+0.36116788*I542+0.01252571*N542-22.85359542*V542+0.00407811*AA542-0.00067349*E542 -> 8498.199 | AH542: =A542*'Simple Linear Regression'!$B$18+'Simple Linear Regression'!$B$17 -> 8346.8294 | AI542: =7491.3971+0.0137554*N542-0.00058829*E542-34.3283*V542+0.30565*L542+54.6031*M542 -> 8668.8466 | AJ542: =7491.3971-0.00058829*E542+0.30565*L542+54.6031*M542+0.0137554*N542-34.3283*V542 -> 8668.8466 | AL542: =2192.59+2373.87*I542+0.0316653*N542-15.7623*V542+0.00202406*AA542-0.000740146*E542-0.00963493*(I542*N542) -> 8633.5027 | AM542: =5205.907083+122.0638992*I542+13.609808*(N542/1000)-1.245906883*AD542+0.7746840854*AE542-134.2474226*AC542-1547.125689*IF(AND(B542>=DATE(2020,3,20),B542<=DATE(2020,6,26)),1,0) -> 8619.3566 | AN542: =IF(ISNUMBER(C543),C543,AN543)-0.8328750492*(AD544-AD543)+3.274150872*(AE544-AE543)+0.7954612886*((IF(ISNUMBER(C543),C543,AN543)-IF(ISNUMBER(C542),C542,AN542))-(-0.8328750492*(AD543-AD542)+3.274150872*(AE543-AE542)))-1.394571582*AO543+0.4181414112*AO542 -> 9321.1494 | AP542: =AQ542+AR541+'ARIMAX(1,1,1) Model'!$C$19*(AR541-AR540)+'ARIMAX(1,1,1) Model'!$C$20*AS541 -> 8705.3696 | AQ542: ='ARIMAX(1,1,1) Model'!$C$6*I542+'ARIMAX(1,1,1) Model'!$C$7*N542/1000+'ARIMAX(1,1,1) Model'!$C$8*AD542+'ARIMAX(1,1,1) Model'!$C$9*AE542+'ARIMAX(1,1,1) Model'!$C$10*AC542+'ARIMAX(1,1,1) Model'!$C$11*IF(AND(B542>='ARIMAX(1,1,1) Model'!$C$25,B542<='ARIMAX(1,1,1) Model'!$C$26),1,0)+'ARIMAX(1,1,1) Model'!$C$12*E542/1000+'ARIMAX(1,1,1) Model'!$C$13*V542+'ARIMAX(1,1,1) Model'!$C$14*A542+'ARIMAX(1,1,1) Model'!$C$15*SIN(2*PI()*A542/'ARIMAX(1,1,1) Model'!$C$24)+'ARIMAX(1,1,1) Model'!$C$16*COS(2*PI()*A542/'ARIMAX(1,1,1) Model'!$C$24)+'ARIMAX(1,1,1) Model'!$C$17*SIN(4*PI()*A542/'ARIMAX(1,1,1) Model'!$C$24)+'ARIMAX(1,1,1) Model'!$C$18*COS(4*PI()*A542/'ARIMAX(1,1,1) Model'!$C$24) -> 2055.9179 | AR542: =IF(ISNUMBER(C542),C542,AP542)-AQ542 -> 6337.0821 | AS542: =IF(ISNUMBER(C542),C542-AP542,0) -> -312.36961
A543: 542 | B543: 37064 | C543: 8921 | E543: 394000 | G543: 27.086 | H543: 26.818 | I543: 1.601 | J543: 10470.231 | K543: 761213 | L543: 1206 | M543: 16.876 | N543: 232513 | O543: 7004.2 | P543: 1784759 | R543: 8007 | T543: 84.7 | U543: 25 | V543: 89.4 | AA543: 282398 | AC543: 0 | AD543: 0.3 | AE543: 68.5 | AG543: =6753.47943187+0.36116788*I543+0.01252571*N543-22.85359542*V543+0.00407811*AA543-0.00067349*E543 -> 8509.6317 | AH543: =A543*'Simple Linear Regression'!$B$18+'Simple Linear Regression'!$B$17 -> 8347.6824 | AI543: =7491.3971+0.0137554*N543-0.00058829*E543-34.3283*V543+0.30565*L543+54.6031*M543 -> 8679.066 | AJ543: =7491.3971-0.00058829*E543+0.30565*L543+54.6031*M543+0.0137554*N543-34.3283*V543 -> 8679.066 | AL543: =2192.59+2373.87*I543+0.0316653*N543-15.7623*V543+0.00202406*AA543-0.000740146*E543-0.00963493*(I543*N543) -> 8639.9385 | AM543: =5205.907083+122.0638992*I543+13.609808*(N543/1000)-1.245906883*AD543+0.7746840854*AE543-134.2474226*AC543-1547.125689*IF(AND(B543>=DATE(2020,3,20),B543<=DATE(2020,6,26)),1,0) -> 8618.4808 | AN543: =IF(ISNUMBER(C544),C544,AN544)-0.8328750492*(AD545-AD544)+3.274150872*(AE545-AE544)+0.7954612886*((IF(ISNUMBER(C544),C544,AN544)-IF(ISNUMBER(C543),C543,AN543))-(-0.8328750492*(AD544-AD543)+3.274150872*(AE544-AE543)))-1.394571582*AO544+0.4181414112*AO543 -> 9148.2519 | AP543: =AQ543+AR542+'ARIMAX(1,1,1) Model'!$C$19*(AR542-AR541)+'ARIMAX(1,1,1) Model'!$C$20*AS542 -> 8691.0462 | AQ543: ='ARIMAX(1,1,1) Model'!$C$6*I543+'ARIMAX(1,1,1) Model'!$C$7*N543/1000+'ARIMAX(1,1,1) Model'!$C$8*AD543+'ARIMAX(1,1,1) Model'!$C$9*AE543+'ARIMAX(1,1,1) Model'!$C$10*AC543+'ARIMAX(1,1,1) Model'!$C$11*IF(AND(B543>='ARIMAX(1,1,1) Model'!$C$25,B543<='ARIMAX(1,1,1) Model'!$C$26),1,0)+'ARIMAX(1,1,1) Model'!$C$12*E543/1000+'ARIMAX(1,1,1) Model'!$C$13*V543+'ARIMAX(1,1,1) Model'!$C$14*A543+'ARIMAX(1,1,1) Model'!$C$15*SIN(2*PI()*A543/'ARIMAX(1,1,1) Model'!$C$24)+'ARIMAX(1,1,1) Model'!$C$16*COS(2*PI()*A543/'ARIMAX(1,1,1) Model'!$C$24)+'ARIMAX(1,1,1) Model'!$C$17*SIN(4*PI()*A543/'ARIMAX(1,1,1) Model'!$C$24)+'ARIMAX(1,1,1) Model'!$C$18*COS(4*PI()*A543/'ARIMAX(1,1,1) Model'!$C$24) -> 2083.6693 | AR543: =IF(ISNUMBER(C543),C543,AP543)-AQ543 -> 6837.3307 | AS543: =IF(ISNUMBER(C543),C543-AP543,0) -> 229.95385
A544: 543 | B544: 37071 | C544: 9036 | E544: 381000 | G544: 26.374 | H544: 26.632 | I544: 1.538 | J544: 10470.231 | K544: 761213 | L544: 1206 | M544: 16.876 | N544: 232513 | O544: 7004.2 | P544: 1784759 | R544: 8007 | T544: 84.7 | U544: 25 | V544: 89.4 | AA544: 282398 | AC544: 0 | AD544: 0.2 | AE544: 67.6 | AG544: =6753.47943187+0.36116788*I544+0.01252571*N544-22.85359542*V544+0.00407811*AA544-0.00067349*E544 -> 8518.3643 | AH544: =A544*'Simple Linear Regression'!$B$18+'Simple Linear Regression'!$B$17 -> 8348.5355 | AI544: =7491.3971+0.0137554*N544-0.00058829*E544-34.3283*V544+0.30565*L544+54.6031*M544 -> 8686.7137 | AJ544: =7491.3971-0.00058829*E544+0.30565*L544+54.6031*M544+0.0137554*N544-34.3283*V544 -> 8686.7137 | AL544: =2192.59+2373.87*I544+0.0316653*N544-15.7623*V544+0.00202406*AA544-0.000740146*E544-0.00963493*(I544*N544) -> 8641.1421 | AM544: =5205.907083+122.0638992*I544+13.609808*(N544/1000)-1.245906883*AD544+0.7746840854*AE544-134.2474226*AC544-1547.125689*IF(AND(B544>=DATE(2020,3,20),B544<=DATE(2020,6,26)),1,0) -> 8610.2181 | AN544: =IF(ISNUMBER(C545),C545,AN545)-0.8328750492*(AD546-AD545)+3.274150872*(AE546-AE545)+0.7954612886*((IF(ISNUMBER(C545),C545,AN545)-IF(ISNUMBER(C544),C544,AN544))-(-0.8328750492*(AD545-AD544)+3.274150872*(AE545-AE544)))-1.394571582*AO545+0.4181414112*AO544 -> 8297.6167 | AP544: =AQ544+AR543+'ARIMAX(1,1,1) Model'!$C$19*(AR543-AR542)+'ARIMAX(1,1,1) Model'!$C$20*AS543 -> 8762.629 | AQ544: ='ARIMAX(1,1,1) Model'!$C$6*I544+'ARIMAX(1,1,1) Model'!$C$7*N544/1000+'ARIMAX(1,1,1) Model'!$C$8*AD544+'ARIMAX(1,1,1) Model'!$C$9*AE544+'ARIMAX(1,1,1) Model'!$C$10*AC544+'ARIMAX(1,1,1) Model'!$C$11*IF(AND(B544>='ARIMAX(1,1,1) Model'!$C$25,B544<='ARIMAX(1,1,1) Model'!$C$26),1,0)+'ARIMAX(1,1,1) Model'!$C$12*E544/1000+'ARIMAX(1,1,1) Model'!$C$13*V544+'ARIMAX(1,1,1) Model'!$C$14*A544+'ARIMAX(1,1,1) Model'!$C$15*SIN(2*PI()*A544/'ARIMAX(1,1,1) Model'!$C$24)+'ARIMAX(1,1,1) Model'!$C$16*COS(2*PI()*A544/'ARIMAX(1,1,1) Model'!$C$24)+'ARIMAX(1,1,1) Model'!$C$17*SIN(4*PI()*A544/'ARIMAX(1,1,1) Model'!$C$24)+'ARIMAX(1,1,1) Model'!$C$18*COS(4*PI()*A544/'ARIMAX(1,1,1) Model'!$C$24) -> 2083.4859 | AR544: =IF(ISNUMBER(C544),C544,AP544)-AQ544 -> 6952.5141 | AS544: =IF(ISNUMBER(C544),C544-AP544,0) -> 273.37102
A545: 544 | B545: 37078 | C545: 8622 | E545: 394000 | G545: 26.8675 | H545: 25.9 | I545: 1.474 | J545: 10470.231 | K545: 761213 | L545: 1234 | M545: 16.876 | N545: 232513 | O545: 7052.8 | P545: 1784759 | R545: 8007 | T545: 84.7 | U545: 25 | V545: 94.9 | AA545: 282398 | AC545: 1 | AD545: 0.4 | AE545: 73.3 | AG545: =6753.47943187+0.36116788*I545+0.01252571*N545-22.85359542*V545+0.00407811*AA545-0.00067349*E545 -> 8383.891 | AH545: =A545*'Simple Linear Regression'!$B$18+'Simple Linear Regression'!$B$17 -> 8349.3885 | AI545: =7491.3971+0.0137554*N545-0.00058829*E545-34.3283*V545+0.30565*L545+54.6031*M545 -> 8498.8185 | AJ545: =7491.3971-0.00058829*E545+0.30565*L545+54.6031*M545+0.0137554*N545-34.3283*V545 -> 8498.8185 | AL545: =2192.59+2373.87*I545+0.0316653*N545-15.7623*V545+0.00202406*AA545-0.000740146*E545-0.00963493*(I545*N545) -> 8536.2757 | AM545: =5205.907083+122.0638992*I545+13.609808*(N545/1000)-1.245906883*AD545+0.7746840854*AE545-134.2474226*AC545-1547.125689*IF(AND(B545>=DATE(2020,3,20),B545<=DATE(2020,6,26)),1,0) -> 8472.3251 | AN545: =IF(ISNUMBER(C546),C546,AN546)-0.8328750492*(AD547-AD546)+3.274150872*(AE547-AE546)+0.7954612886*((IF(ISNUMBER(C546),C546,AN546)-IF(ISNUMBER(C545),C545,AN545))-(-0.8328750492*(AD546-AD545)+3.274150872*(AE546-AE545)))-1.394571582*AO546+0.4181414112*AO545 -> 9451.0381 | AP545: =AQ545+AR544+'ARIMAX(1,1,1) Model'!$C$19*(AR544-AR543)+'ARIMAX(1,1,1) Model'!$C$20*AS544 -> 8776.5017 | AQ545: ='ARIMAX(1,1,1) Model'!$C$6*I545+'ARIMAX(1,1,1) Model'!$C$7*N545/1000+'ARIMAX(1,1,1) Model'!$C$8*AD545+'ARIMAX(1,1,1) Model'!$C$9*AE545+'ARIMAX(1,1,1) Model'!$C$10*AC545+'ARIMAX(1,1,1) Model'!$C$11*IF(AND(B545>='ARIMAX(1,1,1) Model'!$C$25,B545<='ARIMAX(1,1,1) Model'!$C$26),1,0)+'ARIMAX(1,1,1) Model'!$C$12*E545/1000+'ARIMAX(1,1,1) Model'!$C$13*V545+'ARIMAX(1,1,1) Model'!$C$14*A545+'ARIMAX(1,1,1) Model'!$C$15*SIN(2*PI()*A545/'ARIMAX(1,1,1) Model'!$C$24)+'ARIMAX(1,1,1) Model'!$C$16*COS(2*PI()*A545/'ARIMAX(1,1,1) Model'!$C$24)+'ARIMAX(1,1,1) Model'!$C$17*SIN(4*PI()*A545/'ARIMAX(1,1,1) Model'!$C$24)+'ARIMAX(1,1,1) Model'!$C$18*COS(4*PI()*A545/'ARIMAX(1,1,1) Model'!$C$24) -> 2058.8103 | AR545: =IF(ISNUMBER(C545),C545,AP545)-AQ545 -> 6563.1897 | AS545: =IF(ISNUMBER(C545),C545-AP545,0) -> -154.50174
A546: 545 | B546: 37085 | C546: 9095 | E546: 401000 | G546: 27.068 | H546: 24.472 | I546: 1.437 | J546: 10470.231 | K546: 846702 | L546: 1234 | M546: 16.876 | N546: 232513 | O546: 7052.8 | P546: 1784759 | R546: 8007 | T546: 84.7 | U546: 25 | V546: 94.9 | AA546: 282398 | AC546: 0 | AD546: 0 | AE546: 79.2 | AG546: =6753.47943187+0.36116788*I546+0.01252571*N546-22.85359542*V546+0.00407811*AA546-0.00067349*E546 -> 8379.1633 | AH546: =A546*'Simple Linear Regression'!$B$18+'Simple Linear Regression'!$B$17 -> 8350.2416 | AI546: =7491.3971+0.0137554*N546-0.00058829*E546-34.3283*V546+0.30565*L546+54.6031*M546 -> 8494.7005 | AJ546: =7491.3971-0.00058829*E546+0.30565*L546+54.6031*M546+0.0137554*N546-34.3283*V546 -> 8494.7005 | AL546: =2192.59+2373.87*I546+0.0316653*N546-15.7623*V546+0.00202406*AA546-0.000740146*E546-0.00963493*(I546*N546) -> 8526.1506 | AM546: =5205.907083+122.0638992*I546+13.609808*(N546/1000)-1.245906883*AD546+0.7746840854*AE546-134.2474226*AC546-1547.125689*IF(AND(B546>=DATE(2020,3,20),B546<=DATE(2020,6,26)),1,0) -> 8607.1252 | AN546: =IF(ISNUMBER(C547),C547,AN547)-0.8328750492*(AD548-AD547)+3.274150872*(AE548-AE547)+0.7954612886*((IF(ISNUMBER(C547),C547,AN547)-IF(ISNUMBER(C546),C546,AN546))-(-0.8328750492*(AD547-AD546)+3.274150872*(AE547-AE546)))-1.394571582*AO547+0.4181414112*AO546 -> 9270.2718 | AP546: =AQ546+AR545+'ARIMAX(1,1,1) Model'!$C$19*(AR545-AR544)+'ARIMAX(1,1,1) Model'!$C$20*AS545 -> 8824.9487 | AQ546: ='ARIMAX(1,1,1) Model'!$C$6*I546+'ARIMAX(1,1,1) Model'!$C$7*N546/1000+'ARIMAX(1,1,1) Model'!$C$8*AD546+'ARIMAX(1,1,1) Model'!$C$9*AE546+'ARIMAX(1,1,1) Model'!$C$10*AC546+'ARIMAX(1,1,1) Model'!$C$11*IF(AND(B546>='ARIMAX(1,1,1) Model'!$C$25,B546<='ARIMAX(1,1,1) Model'!$C$26),1,0)+'ARIMAX(1,1,1) Model'!$C$12*E546/1000+'ARIMAX(1,1,1) Model'!$C$13*V546+'ARIMAX(1,1,1) Model'!$C$14*A546+'ARIMAX(1,1,1) Model'!$C$15*SIN(2*PI()*A546/'ARIMAX(1,1,1) Model'!$C$24)+'ARIMAX(1,1,1) Model'!$C$16*COS(2*PI()*A546/'ARIMAX(1,1,1) Model'!$C$24)+'ARIMAX(1,1,1) Model'!$C$17*SIN(4*PI()*A546/'ARIMAX(1,1,1) Model'!$C$24)+'ARIMAX(1,1,1) Model'!$C$18*COS(4*PI()*A546/'ARIMAX(1,1,1) Model'!$C$24) -> 2160.666 | AR546: =IF(ISNUMBER(C546),C546,AP546)-AQ546 -> 6934.334 | AS546: =IF(ISNUMBER(C546),C546-AP546,0) -> 270.05128
