Workbook

Sheet Variables
A1: Variable | B1: Description | C1: Time Frame | D1: Time Unit | E1: Links
A2: S&P 500 Index | B2: A stock market index that may influence investment decisions and consumer confidence, impacting gasoline demand. | C2: 2016 - 2026 | D2: Daily except weekends | E2: S&P 500® | S&P Dow Jones Indices (spglobal.com)
A3: Weekly Jobless Claims | B3: A measure of unemployment trends, which can affect consumer spending on gasoline. | C3: 1967 - 2026 | D3: Weekly | E3: Initial Claims (ICSA) | FRED | St. Louis Fed (stlouisfed.org)
A4: TSA Passenger Throughput | B4: Indicates air travel activity and its impact on airport gasoline sales. | C4: 2019 - 2026 | D4: Daily | E4: Travel Passenger Throughputs
A5: US Spot Market Prices of Crude Oil | B5: The cost of crude oil in the United States, influencing gasoline production costs and prices. | C5: 1986 - 2026 | D5: Weekly | E5: Weekly Cushing, OK WTI Spot Price FOB (Dollars per Barrel) (eia.gov)
A6: Europe Spot Market Prices of Crude Oil | B6: Crude oil prices in Europe, affecting international oil markets and gasoline pricing. | C6: 1987 - 2026 | D6: Weekly | E6: Weekly Europe Brent Spot Price FOB (Dollars per Barrel) (eia.gov)
A7: Regular (87 Octane) Gasoline Prices | B7: The cost of regular gasoline, a key factor in consumer gasoline purchasing decisions. | C7: 1990 - 2026 | D7: Weekly | E7: Weekly U.S. Regular All Formulations Retail Gasoline Prices (Dollars per Gallon) (eia.gov)
A8: USA GDP | B8: The overall economic output of the United States, influencing gasoline consumption patterns. | C8: 1947 - 2026 | D8: Quarterly | E8: Gross Domestic Product (GDP) | FRED | St. Louis Fed (stlouisfed.org)
A9: Public Transport Ridership | B9: Trends in the use of public transportation, which can affect gasoline demand. | C9: 1990 - 2026 | D9: Quarterly | E9: Ridership Data Archives - APTA
A10: Rig Count | B10: The number of active drilling rigs, providing insight into future oil and gasoline supply. | C10: 1973 - 2026 | D10: Monthly | E10: U.S. Crude Oil and Natural Gas Drilling Activity
A11: Automobile Sales | B11: Sales of vehicles, impacting gasoline consumption through vehicle ownership. | C11: 1976 - 2026 | D11: Monthly | E11: Total Vehicle Sales (TOTALSA) | FRED | St. Louis Fed (stlouisfed.org)
A12: Highway Traffic Data | B12: Data on road traffic and congestion levels, influencing gasoline usage patterns. | C12: 2002 - 2026 | D12: Monthly | E12: Office of Highway Policy Information - Policy | Federal Highway Administration (dot.gov)
... A30: Daylight Hours | B30: Hours of daylight at the U.S. population center for each week, a deterministic seasonal term added because the demand series is not seasonally adjusted and no other variable captures the regular spring-summer rise in driving. | C30: 1991 - 2026 | D30: Weekly (Ending Friday) | E30: NOAA solar declination approximation (computed in-sheet)

Sheet Hypotheses
A1: Predictor | B1: Hypothesis | C1: Magnitude | D1: Direction
A2: US Spot Market Prices of Crude Oil | B2: Higher crude prices often deter gasoline consumption due to price elasticity. | C2: High | D2: Negative | F2: Karina's personal hypotheses: you can challenge or disagree.
A3: Regular (87 Octane) Gasoline Prices | B3: Higher gasoline prices generally deter consumption. | C3: High | D3: Negative
A4: EV Sales | B4: Increased EV sales may decrease gasoline demand as more people use electric vehicles. | C4: High | D4: Negative
A5: EV Regulations | B5: Higher EV regulations decrease gasoline demand as fleet companies are forced to transition away from gasoline vehicles. | C5: High | D5: Negative
A6: Highway Traffic Data | B6: Increased highway traffic indicates greater vehicle usage, leading to higher gasoline demand. | C6: High | D6: Positive
A7: S&P 500 Index | B7: Higher stock market performance may indicate a booming economy, leading to increased gasoline demand. | C7: Medium | D7: Positive
A8: Weekly Jobless Claims | B8: Higher jobless claims indicate economic downturns, which may result in decreased gasoline demand. | C8: Medium | D8: Negative
A9: Europe Spot Market Prices of Crude Oil | B9: If European crude prices rise and the US follows, it could deter gasoline demand. | C9: Medium | D9: Negative
A10: USA GDP | B10: Higher GDP indicates a robust economy, potentially driving up gasoline demand. | C10: Medium | D10: Positive
A11: Public Transport Ridership | B11: Increased public transport ridership may lead to decreased gasoline demand. | C11: Medium | D11: Negative
A12: Automobile Sales | B12: Higher sales, especially of gasoline-based vehicles, indicate potential increased gasoline demand. | C12: Medium | D12: Positive
A13: Personal Consumption Expenditures | B13: Higher consumer spending can suggest increased economic activity and gasoline demand. | C13: Medium | D13: Positive
A14: Refinery Utilization | B14: Higher refinery utilization can lead to increased gasoline supply, potentially affecting demand balance. | C14: Medium | D14: Positive
... A16: Inflation Expectations | B16: Higher inflation expectations could deter spending, potentially reducing gasoline demand. | C16: Medium | D16: Negative
A17: Employee Earnings | B17: Higher earnings boost disposable income, possibly increasing gasoline demand due to increased travel. | C17: Medium | D17: Positive | O17: -
A18: TSA Passenger Throughput | B18: An increase in passenger throughput may indicate higher air travel, potentially reducing gasoline demand. | C18: Low | D18: Negative
A19: Rig Count | B19: A higher rig count suggests increased domestic production, potentially influencing gasoline demand. | C19: Low | D19: Positive
A20: Consumer Credit Data | B20: Higher consumer credit indicates more spending, including on vehicles and travel, potentially driving gasoline demand. | C20: Low | D20: Positive
A21: Household Debt and Credit | B21: Higher household debt may deter spending, including on travel, potentially reducing gasoline demand. | C21: Low | D21: Negative
A22: Labor Costs | B22: Rising labor costs could affect gasoline production costs, potentially affecting gasoline demand. | C22: Low | D22: Negative
A23: Smoking Consumption | B23: Decrease in smoking might indicate health-conscious decisions, including eco-friendly transportation choices. | C23: Low | D23: Negative
A24: Housing Market Expectations | B24: A booming housing market might lead to increased travel, potentially driving up gasoline demand. | C24: Low | D24: Positive
A25: Major Driving Holiday Week | B25: Weeks containing Memorial Day, July 4, Labor Day, Thanksgiving, Christmas, or New Year's Day see a surge in road trips and family travel, which should raise gasoline demand relative to an ordinary week. But Thanksgiving and Christmas weeks also carry days when many people don't commute or run errands at all, so the net effect could go either way depending on which force dominates. | C25: High | D25: Conditional
A26: Work From Home Share | B26: A higher share of work-from-home days should lower gasoline demand, since commuting is a large and regular share of vehicle miles driven and this trip disappears entirely on remote days. This is a structural shift rather than a short-term fluctuation, and expected to matter most in explaining why demand hasn't returned to pre-2020 levels rather than in explaining week-to-week noise. | C26: High | D26: Negative
A27: US Population-Weighted HDD | B27: Severe winter cold and winter storms reduce vehicle miles traveled and suppress gasoline demand. | C27: Medium | D27: Negative
A28: US Population-Weighted CDD | B28: Warmer summer temperatures increase vacation driving trips and air conditioning load. | C28: Medium | D28: Positive
A29: Daylight Hours | B29: Longer days support more evening and discretionary driving and coincide with the summer travel season, so demand should rise with daylight. Part of this overlaps with temperature (HDD/CDD), but daylight tracks the calendar cycle itself rather than weather surprises. | C29: Medium | D29: Positive

Sheet Simple Linear Regression
A1: SUMMARY OUTPUT
A3: Regression Statistics
A4: Multiple R | B4: 0.59469786
A5: R Square | B5: 0.35366554
A6: Adjusted R Square | B6: 0.35329976
A7: Standard Error | B7: 589.22746
A8: Observations | B8: 1769
A10: ANOVA
B11: df | C11: SS | D11: MS | E11: F | F11: Significance F
A12: Regression | B12: 1 | C12: 3.3568964e+08 | D12: 3.3568964e+08 | E12: 966.87869 | F12: 1.1029353e-169
A13: Residual | B13: 1767 | C13: 6.1348295e+08 | D13: 347188.99
A14: Total | B14: 1768 | C14: 9.4917259e+08
B16: Coefficients | C16: Standard Error | D16: t Stat | E16: P-value | F16: Lower 95% | G16: Upper 95% | H16: Lower 95.0% | I16: Upper 95.0%
A17: Intercept | B17: 7885.3363 | C17: 28.030652 | D17: 281.31119 | E17: 0 | F17: 7830.3596 | G17: 7940.3131 | H17: 7830.3596 | I17: 7940.3131
A18: X Variable 1 | B18: 0.85303708 | C18: 0.027433544 | D18: 31.094673 | E18: 1.1029353e-169 | F18: 0.79923147 | G18: 0.9068427 | H18: 0.79923147 | I18: 0.9068427

Sheet Target
A1: Week # | B1: Date | C1: Demand | D1: sp500_weekly_avg | E1: initial_jobless_claims | F1: tsa_passengers_weekly_avg | G1: wti_spot_usd_per_bbl | H1: brent_spot_usd_per_bbl | I1: regular_gas_usd_per_gal | J1: gdp_saar_bil_usd | K1: transit_unlinked_trips_thous | L1: rotary_rig_count | M1: vehicle_sales_saar_mil | N1: vehicle_miles_mil | O1: pce_saar_bil_usd | P1: consumer_credit_mil_usd | Q1: ev_sales_vehicles | R1: regulated_afv_acquisitions | S1: household_debt_tril_usd | T1: eci_total_comp_index | U1: smoking_adults_pct | V1: refinery_utilization_pct | W1: fed_broad_dollar_index | X1: home_price_expectation_pct | Y1: inflation_expectation_1y_pct | Z1: mean_annual_earnings_thous_usd | AA1: us_population_thous | AB1: wfh_share_paid_days_pct | AC1: major_holiday_week | AD1: hdd_pop_weighted | AE1: cdd_pop_weighted | AF1: daylight_hours | AG1: Model C | AH1: Simple Linear Regression Model | AI1: forward selection | AJ1: backward selection | AK1: Restricted Model C | AL1: gas*VMT interaction | AM1: M1 Weather + Holiday | AN1: major holiday week and daylgiht hours interaction | AO1: gas*VMT interaction 2 | AP1: gas*vmt interaction traine on 08-24 | AQ1: INT1 term: Gas×VMT (I×N) | AR1: INT2 term: Gas×Jobless (I×E) | AS1: INT3 term: Holiday×Daylight (AC×AF) | AT1: Pred Demand – Base | AU1: Pred Demand – Int1: Gas x VMT | AV1: Pred Demand – Int2: Gas x Jobless | AW1: Pred Demand – Int3: Holiday x Daylight | AX1: Pred Demand – Final: Gas x VMT (refit 1991-2024) | AY1: Gas * Jobless | AZ1: Holiday*Daylight | BA1: Gas*VMT
A2: 1 | B2: 33277 | C2: 6621 | E2: 483000 | G2: 21.304 | H2: 20.626 | I2: 1.139 | L2: 1136 | V2: 84.2 | AC2: 0 | AD2: 18.5 | AE2: 0 | AF2: 10.2996 | AG2: =6753.47943187+0.36116788*I2+0.01252571*N2-22.85359542*V2+0.00407811*AA2-0.00067349*E2 -> 4504.3224 | AH2: =A2*'Simple Linear Regression'!$B$18+'Simple Linear Regression'!$B$17 -> 7886.1894 | AI2: =7491.3971+0.0137554*N2-0.00058829*E2-34.3283*V2+0.30565*L2+54.6031*M2 -> 4664.0286 | AJ2: =7491.3971-0.00058829*E2+0.30565*L2+54.6031*M2+0.0137554*N2-34.3283*V2 -> 4664.0286 | AL2: =2192.59+2373.87*I2+0.0316653*N2-15.7623*V2+0.00202406*AA2-0.000740146*E2-0.00963493*(I2*N2) -> 3211.7518 | AM2: =5205.907083+122.0638992*I2+13.609808*(N2/1000)-1.245906883*AD2+0.7746840854*AE2-134.2474226*AC2-1547.125689*IF(AND(B2>=DATE(2020,3,20),B2<=DATE(2020,6,26)),1,0) -> 5321.8886 | AN2: =7707.2178-144.397321*AC2+139.5614087*AF2-0.0008594506251*E2-265.7105668*I2-0.02506176117*J2+0.004708026652*N2 -> 8426.8855 | AO2: =IF(N2="","",2190.39 + 2739.06*I2 + 0.034693*N2 - 16.722*V2 - 0.000802*E2 - 1.3691*AD2 + 1.8691*AE2 - 121.7*AC2 + 209.88*IF(AND(B2>=DATE(2020,3,20),B2<=DATE(2020,6,26)),1,0) - 0.011049*(I2*N2)) | AP2: =IF(B2<DATE(2008,1,1),"",3929.06 + 1212.53*I2 - 0.0003097*N2 + 59.426*V2 - 0.0006734*E2 - 1.036*AD2 + 1.2076*AE2 + 94.923*AF2 - 131.43*AC2 - 759.61*IF(AND(B2>=DATE(2020,3,20),B2<=DATE(2020,6,26)),1,0) - 17.324*(I2*V2)) | AQ2: =IF(N2="","",I2*N2) | AR2: =I2*E2 -> 550137 | AS2: =AC2*AF2 -> 0 | AT2: =IF(N2="","",2413.3773+89.103503*I2+0.018847679*N2-5.0917058*V2-0.00064564578*E2+1.4315076*AD2-3.1976817*AE2-66.972905*AC2-217.08397*IF(AND(B2>=DATE(2020,3,20),B2<=DATE(2020,6,26)),1,0)+190.76803*AF2) | AU2: =IF(N2="","",-480.76297+2186.3009*I2+0.033368804*N2-5.3903106*V2-0.00073731439*E2+0.93396876*AD2-1.6242981*AE2-61.304389*AC2-95.472727*IF(AND(B2>=DATE(2020,3,20),B2<=DATE(2020,6,26)),1,0)+156.04851*AF2-0.0087322858*AQ2) | AV2: =IF(N2="","",2518.0489-204.66184*I2+0.019354281*N2-2.3328708*V2-0.0022533804*E2+1.5259709*AD2-3.5842757*AE2-65.580099*AC2-62.828483*IF(AND(B2>=DATE(2020,3,20),B2<=DATE(2020,6,26)),1,0)+200.94286*AF2+0.00080379976*AR2) | AW2: =IF(N2="","",2361.7153+89.223162*I2+0.018847054*N2-5.0210815*V2-0.0006437347*E2+1.4213619*AD2-3.2156123*AE2+167.41121*AC2-224.35191*IF(AND(B2>=DATE(2020,3,20),B2<=DATE(2020,6,26)),1,0)+194.56435*AF2-19.897843*AS2) | AX2: =IF(N2="","",-654.03928+2464.5589*I2+0.035956453*N2-8.0754527*V2-0.00069441316*E2+0.69511606*AD2-1.1669613*AE2-90.724569*AC2-211.24919*IF(AND(B2>=DATE(2020,3,20),B2<=DATE(2020,6,26)),1,0)+147.22132*AF2-0.010108087*AQ2) | AY2: MAPE = 8.3505 | AZ2: MAPE = 9.6655 | BA2: MAPE =4.6201
A3: 2 | B3: 33284 | C3: 6433 | E3: 480000 | G3: 22.116 | H3: 20.436 | I3: 1.106 | L3: 1136 | V3: 84.2 | AC3: 0 | AD3: 145.9 | AE3: 0.7 | AF3: 10.5413 | AG3: =6753.47943187+0.36116788*I3+0.01252571*N3-22.85359542*V3+0.00407811*AA3-0.00067349*E3 -> 4506.3309 | AH3: =A3*'Simple Linear Regression'!$B$18+'Simple Linear Regression'!$B$17 -> 7887.0424 | AI3: =7491.3971+0.0137554*N3-0.00058829*E3-34.3283*V3+0.30565*L3+54.6031*M3 -> 4665.7934 | AJ3: =7491.3971-0.00058829*E3+0.30565*L3+54.6031*M3+0.0137554*N3-34.3283*V3 -> 4665.7934 | AL3: =2192.59+2373.87*I3+0.0316653*N3-15.7623*V3+0.00202406*AA3-0.000740146*E3-0.00963493*(I3*N3) -> 3135.6345 | AM3: =5205.907083+122.0638992*I3+13.609808*(N3/1000)-1.245906883*AD3+0.7746840854*AE3-134.2474226*AC3-1547.125689*IF(AND(B3>=DATE(2020,3,20),B3<=DATE(2020,6,26)),1,0) -> 5159.6742 | AN3: =7707.2178-144.397321*AC3+139.5614087*AF3-0.0008594506251*E3-265.7105668*I3-0.02506176117*J3+0.004708026652*N3 -> 8471.9643 | AO3: =IF(N3="","",2190.39 + 2739.06*I3 + 0.034693*N3 - 16.722*V3 - 0.000802*E3 - 1.3691*AD3 + 1.8691*AE3 - 121.7*AC3 + 209.88*IF(AND(B3>=DATE(2020,3,20),B3<=DATE(2020,6,26)),1,0) - 0.011049*(I3*N3)) | AP3: =IF(B3<DATE(2008,1,1),"",3929.06 + 1212.53*I3 - 0.0003097*N3 + 59.426*V3 - 0.0006734*E3 - 1.036*AD3 + 1.2076*AE3 + 94.923*AF3 - 131.43*AC3 - 759.61*IF(AND(B3>=DATE(2020,3,20),B3<=DATE(2020,6,26)),1,0) - 17.324*(I3*V3)) | AQ3: =IF(N3="","",I3*N3) | AR3: =I3*E3 -> 530880 | AS3: =AC3*AF3 -> 0 | AT3: =IF(N3="","",2413.3773+89.103503*I3+0.018847679*N3-5.0917058*V3-0.00064564578*E3+1.4315076*AD3-3.1976817*AE3-66.972905*AC3-217.08397*IF(AND(B3>=DATE(2020,3,20),B3<=DATE(2020,6,26)),1,0)+190.76803*AF3) | AU3: =IF(N3="","",-480.76297+2186.3009*I3+0.033368804*N3-5.3903106*V3-0.00073731439*E3+0.93396876*AD3-1.6242981*AE3-61.304389*AC3-95.472727*IF(AND(B3>=DATE(2020,3,20),B3<=DATE(2020,6,26)),1,0)+156.04851*AF3-0.0087322858*AQ3) | AV3: =IF(N3="","",2518.0489-204.66184*I3+0.019354281*N3-2.3328708*V3-0.0022533804*E3+1.5259709*AD3-3.5842757*AE3-65.580099*AC3-62.828483*IF(AND(B3>=DATE(2020,3,20),B3<=DATE(2020,6,26)),1,0)+200.94286*AF3+0.00080379976*AR3) | AW3: =IF(N3="","",2361.7153+89.223162*I3+0.018847054*N3-5.0210815*V3-0.0006437347*E3+1.4213619*AD3-3.2156123*AE3+167.41121*AC3-224.35191*IF(AND(B3>=DATE(2020,3,20),B3<=DATE(2020,6,26)),1,0)+194.56435*AF3-19.897843*AS3) | AX3: =IF(N3="","",-654.03928+2464.5589*I3+0.035956453*N3-8.0754527*V3-0.00069441316*E3+0.69511606*AD3-1.1669613*AE3-90.724569*AC3-211.24919*IF(AND(B3>=DATE(2020,3,20),B3<=DATE(2020,6,26)),1,0)+147.22132*AF3-0.010108087*AQ3) | AY3: RMSLE = 0.0871 | AZ3: RMSLE = 0.0977 | BA3: RMSLE = 0.0536
A4: 3 | B4: 33291 | C4: 6582 | E4: 474000 | G4: 19.38 | H4: 18.126 | I4: 1.078 | L4: 1136 | M4: 11.829 | V4: 84.2 | AC4: 0 | AD4: 130.1 | AE4: 1.5 | AF4: 10.7989 | AG4: =6753.47943187+0.36116788*I4+0.01252571*N4-22.85359542*V4+0.00407811*AA4-0.00067349*E4 -> 4510.3618 | AH4: =A4*'Simple Linear Regression'!$B$18+'Simple Linear Regression'!$B$17 -> 7887.8955 | AI4: =7491.3971+0.0137554*N4-0.00058829*E4-34.3283*V4+0.30565*L4+54.6031*M4 -> 5315.2232 | AJ4: =7491.3971-0.00058829*E4+0.30565*L4+54.6031*M4+0.0137554*N4-34.3283*V4 -> 5315.2232 | AL4: =2192.59+2373.87*I4+0.0316653*N4-15.7623*V4+0.00202406*AA4-0.000740146*E4-0.00963493*(I4*N4) -> 3073.607 | AM4: =5205.907083+122.0638992*I4+13.609808*(N4/1000)-1.245906883*AD4+0.7746840854*AE4-134.2474226*AC4-1547.125689*IF(AND(B4>=DATE(2020,3,20),B4<=DATE(2020,6,26)),1,0) -> 5176.5615 | AN4: =7707.2178-144.397321*AC4+139.5614087*AF4-0.0008594506251*E4-265.7105668*I4-0.02506176117*J4+0.004708026652*N4 -> 8520.5119 | AO4: =IF(N4="","",2190.39 + 2739.06*I4 + 0.034693*N4 - 16.722*V4 - 0.000802*E4 - 1.3691*AD4 + 1.8691*AE4 - 121.7*AC4 + 209.88*IF(AND(B4>=DATE(2020,3,20),B4<=DATE(2020,6,26)),1,0) - 0.011049*(I4*N4)) | AP4: =IF(B4<DATE(2008,1,1),"",3929.06 + 1212.53*I4 - 0.0003097*N4 + 59.426*V4 - 0.0006734*E4 - 1.036*AD4 + 1.2076*AE4 + 94.923*AF4 - 131.43*AC4 - 759.61*IF(AND(B4>=DATE(2020,3,20),B4<=DATE(2020,6,26)),1,0) - 17.324*(I4*V4)) | AQ4: =IF(N4="","",I4*N4) | AR4: =I4*E4 -> 510972 | AS4: =AC4*AF4 -> 0 | AT4: =IF(N4="","",2413.3773+89.103503*I4+0.018847679*N4-5.0917058*V4-0.00064564578*E4+1.4315076*AD4-3.1976817*AE4-66.972905*AC4-217.08397*IF(AND(B4>=DATE(2020,3,20),B4<=DATE(2020,6,26)),1,0)+190.76803*AF4) | AU4: =IF(N4="","",-480.76297+2186.3009*I4+0.033368804*N4-5.3903106*V4-0.00073731439*E4+0.93396876*AD4-1.6242981*AE4-61.304389*AC4-95.472727*IF(AND(B4>=DATE(2020,3,20),B4<=DATE(2020,6,26)),1,0)+156.04851*AF4-0.0087322858*AQ4) | AV4: =IF(N4="","",2518.0489-204.66184*I4+0.019354281*N4-2.3328708*V4-0.0022533804*E4+1.5259709*AD4-3.5842757*AE4-65.580099*AC4-62.828483*IF(AND(B4>=DATE(2020,3,20),B4<=DATE(2020,6,26)),1,0)+200.94286*AF4+0.00080379976*AR4) | AW4: =IF(N4="","",2361.7153+89.223162*I4+0.018847054*N4-5.0210815*V4-0.0006437347*E4+1.4213619*AD4-3.2156123*AE4+167.41121*AC4-224.35191*IF(AND(B4>=DATE(2020,3,20),B4<=DATE(2020,6,26)),1,0)+194.56435*AF4-19.897843*AS4) | AX4: =IF(N4="","",-654.03928+2464.5589*I4+0.035956453*N4-8.0754527*V4-0.00069441316*E4+0.69511606*AD4-1.1669613*AE4-90.724569*AC4-211.24919*IF(AND(B4>=DATE(2020,3,20),B4<=DATE(2020,6,26)),1,0)+147.22132*AF4-0.010108087*AQ4) | AY4: RSE = 789.5686 | AZ4: RSE = 910.3424 | BA4: RSE = 910.3424
A5: 4 | B5: 33298 | C5: 7224 | E5: 499000 | G5: 18.73 | H5: 18.662 | I5: 1.054 | L5: 1136 | M5: 11.829 | V5: 84.2 | AC5: 0 | AD5: 149.8 | AE5: 0.9 | AF5: 11.0684 | AG5: =6753.47943187+0.36116788*I5+0.01252571*N5-22.85359542*V5+0.00407811*AA5-0.00067349*E5 -> 4493.5159 | AH5: =A5*'Simple Linear Regression'!$B$18+'Simple Linear Regression'!$B$17 -> 7888.7485 | AI5: =7491.3971+0.0137554*N5-0.00058829*E5-34.3283*V5+0.30565*L5+54.6031*M5 -> 5300.516 | AJ5: =7491.3971-0.00058829*E5+0.30565*L5+54.6031*M5+0.0137554*N5-34.3283*V5 -> 5300.516 | AL5: =2192.59+2373.87*I5+0.0316653*N5-15.7623*V5+0.00202406*AA5-0.000740146*E5-0.00963493*(I5*N5) -> 2998.1305 | AM5: =5205.907083+122.0638992*I5+13.609808*(N5/1000)-1.245906883*AD5+0.7746840854*AE5-134.2474226*AC5-1547.125689*IF(AND(B5>=DATE(2020,3,20),B5<=DATE(2020,6,26)),1,0) -> 5148.6228 | AN5: =7707.2178-144.397321*AC5+139.5614087*AF5-0.0008594506251*E5-265.7105668*I5-0.02506176117*J5+0.004708026652*N5 -> 8543.0145 | AO5: =IF(N5="","",2190.39 + 2739.06*I5 + 0.034693*N5 - 16.722*V5 - 0.000802*E5 - 1.3691*AD5 + 1.8691*AE5 - 121.7*AC5 + 209.88*IF(AND(B5>=DATE(2020,3,20),B5<=DATE(2020,6,26)),1,0) - 0.011049*(I5*N5)) | AP5: =IF(B5<DATE(2008,1,1),"",3929.06 + 1212.53*I5 - 0.0003097*N5 + 59.426*V5 - 0.0006734*E5 - 1.036*AD5 + 1.2076*AE5 + 94.923*AF5 - 131.43*AC5 - 759.61*IF(AND(B5>=DATE(2020,3,20),B5<=DATE(2020,6,26)),1,0) - 17.324*(I5*V5)) | AQ5: =IF(N5="","",I5*N5) | AR5: =I5*E5 -> 525946 | AS5: =AC5*AF5 -> 0 | AT5: =IF(N5="","",2413.3773+89.103503*I5+0.018847679*N5-5.0917058*V5-0.00064564578*E5+1.4315076*AD5-3.1976817*AE5-66.972905*AC5-217.08397*IF(AND(B5>=DATE(2020,3,20),B5<=DATE(2020,6,26)),1,0)+190.76803*AF5) | AU5: =IF(N5="","",-480.76297+2186.3009*I5+0.033368804*N5-5.3903106*V5-0.00073731439*E5+0.93396876*AD5-1.6242981*AE5-61.304389*AC5-95.472727*IF(AND(B5>=DATE(2020,3,20),B5<=DATE(2020,6,26)),1,0)+156.04851*AF5-0.0087322858*AQ5) | AV5: =IF(N5="","",2518.0489-204.66184*I5+0.019354281*N5-2.3328708*V5-0.0022533804*E5+1.5259709*AD5-3.5842757*AE5-65.580099*AC5-62.828483*IF(AND(B5>=DATE(2020,3,20),B5<=DATE(2020,6,26)),1,0)+200.94286*AF5+0.00080379976*AR5) | AW5: =IF(N5="","",2361.7153+89.223162*I5+0.018847054*N5-5.0210815*V5-0.0006437347*E5+1.4213619*AD5-3.2156123*AE5+167.41121*AC5-224.35191*IF(AND(B5>=DATE(2020,3,20),B5<=DATE(2020,6,26)),1,0)+194.56435*AF5-19.897843*AS5) | AX5: =IF(N5="","",-654.03928+2464.5589*I5+0.035956453*N5-8.0754527*V5-0.00069441316*E5+0.69511606*AD5-1.1669613*AE5-90.724569*AC5-211.24919*IF(AND(B5>=DATE(2020,3,20),B5<=DATE(2020,6,26)),1,0)+147.22132*AF5-0.010108087*AQ5)
A6: 5 | B6: 33305 | C6: 6875 | E6: 488000 | G6: 19.856 | H6: 19.77 | I6: 1.025 | L6: 1068 | M6: 11.829 | O6: 3841 | V6: 82.8 | AC6: 0 | AD6: 111.1 | AE6: 1.8 | AF6: 11.3467 | AG6: =6753.47943187+0.36116788*I6+0.01252571*N6-22.85359542*V6+0.00407811*AA6-0.00067349*E6 -> 4532.9088 | AH6: =A6*'Simple Linear Regression'!$B$18+'Simple Linear Regression'!$B$17 -> 7889.6015 | AI6: =7491.3971+0.0137554*N6-0.00058829*E6-34.3283*V6+0.30565*L6+54.6031*M6 -> 5334.2626 | AJ6: =7491.3971-0.00058829*E6+0.30565*L6+54.6031*M6+0.0137554*N6-34.3283*V6 -> 5334.2626 | AL6: =2192.59+2373.87*I6+0.0316653*N6-15.7623*V6+0.00202406*AA6-0.000740146*E6-0.00963493*(I6*N6) -> 2959.4971 | AM6: =5205.907083+122.0638992*I6+13.609808*(N6/1000)-1.245906883*AD6+0.7746840854*AE6-134.2474226*AC6-1547.125689*IF(AND(B6>=DATE(2020,3,20),B6<=DATE(2020,6,26)),1,0) -> 5193.9968 | AN6: =7707.2178-144.397321*AC6+139.5614087*AF6-0.0008594506251*E6-265.7105668*I6-0.02506176117*J6+0.004708026652*N6 -> 8599.014 | AO6: =IF(N6="","",2190.39 + 2739.06*I6 + 0.034693*N6 - 16.722*V6 - 0.000802*E6 - 1.3691*AD6 + 1.8691*AE6 - 121.7*AC6 + 209.88*IF(AND(B6>=DATE(2020,3,20),B6<=DATE(2020,6,26)),1,0) - 0.011049*(I6*N6)) | AP6: =IF(B6<DATE(2008,1,1),"",3929.06 + 1212.53*I6 - 0.0003097*N6 + 59.426*V6 - 0.0006734*E6 - 1.036*AD6 + 1.2076*AE6 + 94.923*AF6 - 131.43*AC6 - 759.61*IF(AND(B6>=DATE(2020,3,20),B6<=DATE(2020,6,26)),1,0) - 17.324*(I6*V6)) | AQ6: =IF(N6="","",I6*N6) | AR6: =I6*E6 -> 500200 | AS6: =AC6*AF6 -> 0 | AT6: =IF(N6="","",2413.3773+89.103503*I6+0.018847679*N6-5.0917058*V6-0.00064564578*E6+1.4315076*AD6-3.1976817*AE6-66.972905*AC6-217.08397*IF(AND(B6>=DATE(2020,3,20),B6<=DATE(2020,6,26)),1,0)+190.76803*AF6) | AU6: =IF(N6="","",-480.76297+2186.3009*I6+0.033368804*N6-5.3903106*V6-0.00073731439*E6+0.93396876*AD6-1.6242981*AE6-61.304389*AC6-95.472727*IF(AND(B6>=DATE(2020,3,20),B6<=DATE(2020,6,26)),1,0)+156.04851*AF6-0.0087322858*AQ6) | AV6: =IF(N6="","",2518.0489-204.66184*I6+0.019354281*N6-2.3328708*V6-0.0022533804*E6+1.5259709*AD6-3.5842757*AE6-65.580099*AC6-62.828483*IF(AND(B6>=DATE(2020,3,20),B6<=DATE(2020,6,26)),1,0)+200.94286*AF6+0.00080379976*AR6) | AW6: =IF(N6="","",2361.7153+89.223162*I6+0.018847054*N6-5.0210815*V6-0.0006437347*E6+1.4213619*AD6-3.2156123*AE6+167.41121*AC6-224.35191*IF(AND(B6>=DATE(2020,3,20),B6<=DATE(2020,6,26)),1,0)+194.56435*AF6-19.897843*AS6) | AX6: =IF(N6="","",-654.03928+2464.5589*I6+0.035956453*N6-8.0754527*V6-0.00069441316*E6+0.69511606*AD6-1.1669613*AE6-90.724569*AC6-211.24919*IF(AND(B6>=DATE(2020,3,20),B6<=DATE(2020,6,26)),1,0)+147.22132*AF6-0.010108087*AQ6)
A7: 6 | B7: 33312 | C7: 6947 | E7: 499000 | G7: 19.894 | H7: 19.278 | I7: 1.045 | L7: 1068 | M7: 11.829 | O7: 3841 | V7: 82.8 | AC7: 0 | AD7: 148 | AE7: 0.7 | AF7: 11.6306 | AG7: =6753.47943187+0.36116788*I7+0.01252571*N7-22.85359542*V7+0.00407811*AA7-0.00067349*E7 -> 4525.5076 | AH7: =A7*'Simple Linear Regression'!$B$18+'Simple Linear Regression'!$B$17 -> 7890.4546 | AI7: =7491.3971+0.0137554*N7-0.00058829*E7-34.3283*V7+0.30565*L7+54.6031*M7 -> 5327.7914 | AJ7: =7491.3971-0.00058829*E7+0.30565*L7+54.6031*M7+0.0137554*N7-34.3283*V7 -> 5327.7914 | AL7: =2192.59+2373.87*I7+0.0316653*N7-15.7623*V7+0.00202406*AA7-0.000740146*E7-0.00963493*(I7*N7) -> 2998.8329 | AM7: =5205.907083+122.0638992*I7+13.609808*(N7/1000)-1.245906883*AD7+0.7746840854*AE7-134.2474226*AC7-1547.125689*IF(AND(B7>=DATE(2020,3,20),B7<=DATE(2020,6,26)),1,0) -> 5149.6119 | AN7: =7707.2178-144.397321*AC7+139.5614087*AF7-0.0008594506251*E7-265.7105668*I7-0.02506176117*J7+0.004708026652*N7 -> 8623.8673 | AO7: =IF(N7="","",2190.39 + 2739.06*I7 + 0.034693*N7 - 16.722*V7 - 0.000802*E7 - 1.3691*AD7 + 1.8691*AE7 - 121.7*AC7 + 209.88*IF(AND(B7>=DATE(2020,3,20),B7<=DATE(2020,6,26)),1,0) - 0.011049*(I7*N7)) | AP7: =IF(B7<DATE(2008,1,1),"",3929.06 + 1212.53*I7 - 0.0003097*N7 + 59.426*V7 - 0.0006734*E7 - 1.036*AD7 + 1.2076*AE7 + 94.923*AF7 - 131.43*AC7 - 759.61*IF(AND(B7>=DATE(2020,3,20),B7<=DATE(2020,6,26)),1,0) - 17.324*(I7*V7)) | AQ7: =IF(N7="","",I7*N7) | AR7: =I7*E7 -> 521455 | AS7: =AC7*AF7 -> 0 | AT7: =IF(N7="","",2413.3773+89.103503*I7+0.018847679*N7-5.0917058*V7-0.00064564578*E7+1.4315076*AD7-3.1976817*AE7-66.972905*AC7-217.08397*IF(AND(B7>=DATE(2020,3,20),B7<=DATE(2020,6,26)),1,0)+190.76803*AF7) | AU7: =IF(N7="","",-480.76297+2186.3009*I7+0.033368804*N7-5.3903106*V7-0.00073731439*E7+0.93396876*AD7-1.6242981*AE7-61.304389*AC7-95.472727*IF(AND(B7>=DATE(2020,3,20),B7<=DATE(2020,6,26)),1,0)+156.04851*AF7-0.0087322858*AQ7) | AV7: =IF(N7="","",2518.0489-204.66184*I7+0.019354281*N7-2.3328708*V7-0.0022533804*E7+1.5259709*AD7-3.5842757*AE7-65.580099*AC7-62.828483*IF(AND(B7>=DATE(2020,3,20),B7<=DATE(2020,6,26)),1,0)+200.94286*AF7+0.00080379976*AR7) | AW7: =IF(N7="","",2361.7153+89.223162*I7+0.018847054*N7-5.0210815*V7-0.0006437347*E7+1.4213619*AD7-3.2156123*AE7+167.41121*AC7-224.35191*IF(AND(B7>=DATE(2020,3,20),B7<=DATE(2020,6,26)),1,0)+194.56435*AF7-19.897843*AS7) | AX7: =IF(N7="","",-654.03928+2464.5589*I7+0.035956453*N7-8.0754527*V7-0.00069441316*E7+0.69511606*AD7-1.1669613*AE7-90.724569*AC7-211.24919*IF(AND(B7>=DATE(2020,3,20),B7<=DATE(2020,6,26)),1,0)+147.22132*AF7-0.010108087*AQ7)
A8: 7 | B8: 33319 | C8: 7328 | E8: 498000 | G8: 20.304 | H8: 18.796 | I8: 1.043 | L8: 1068 | M8: 12.409 | N8: 157889 | O8: 3841 | V8: 82.8 | AC8: 0 | AD8: 104.9 | AE8: 3.3 | AF8: 11.9177 | AG8: =6753.47943187+0.36116788*I8+0.01252571*N8-22.85359542*V8+0.00407811*AA8-0.00067349*E8 -> 6503.8522 | AH8: =A8*'Simple Linear Regression'!$B$18+'Simple Linear Regression'!$B$17 -> 7891.3076 | AI8: =7491.3971+0.0137554*N8-0.00058829*E8-34.3283*V8+0.30565*L8+54.6031*M8 -> 7531.8759 | AJ8: =7491.3971-0.00058829*E8+0.30565*L8+54.6031*M8+0.0137554*N8-34.3283*V8 -> 7531.8759 | AL8: =2192.59+2373.87*I8+0.0316653*N8-15.7623*V8+0.00202406*AA8-0.000740146*E8-0.00963493*(I8*N8) -> 6407.7646 | AM8: =5205.907083+122.0638992*I8+13.609808*(N8/1000)-1.245906883*AD8+0.7746840854*AE8-134.2474226*AC8-1547.125689*IF(AND(B8>=DATE(2020,3,20),B8<=DATE(2020,6,26)),1,0) -> 7353.9195 | AN8: =7707.2178-144.397321*AC8+139.5614087*AF8-0.0008594506251*E8-265.7105668*I8-0.02506176117*J8+0.004708026652*N8 -> 9408.6719 | AO8: =IF(N8="","",2190.39 + 2739.06*I8 + 0.034693*N8 - 16.722*V8 - 0.000802*E8 - 1.3691*AD8 + 1.8691*AE8 - 121.7*AC8 + 209.88*IF(AND(B8>=DATE(2020,3,20),B8<=DATE(2020,6,26)),1,0) - 0.011049*(I8*N8)) -> 6783.9148 | AP8: =IF(B8<DATE(2008,1,1),"",3929.06 + 1212.53*I8 - 0.0003097*N8 + 59.426*V8 - 0.0006734*E8 - 1.036*AD8 + 1.2076*AE8 + 94.923*AF8 - 131.43*AC8 - 759.61*IF(AND(B8>=DATE(2020,3,20),B8<=DATE(2020,6,26)),1,0) - 17.324*(I8*V8)) | AQ8: =IF(N8="","",I8*Target!N8) -> 164678.23 | AR8: =I8*E8 -> 519414 | AS8: =AC8*AF8 -> 0 | AT8: =IF(N8="","",2413.3773+89.103503*I8+0.018847679*N8-5.0917058*V8-0.00064564578*E8+1.4315076*AD8-3.1976817*AE8-66.972905*AC8-217.08397*IF(AND(B8>=DATE(2020,3,20),B8<=DATE(2020,6,26)),1,0)+190.76803*AF8) -> 7152.1576 | AU8: =IF(N8="","",-480.76297+2186.3009*I8+0.033368804*N8-5.3903106*V8-0.00073731439*E8+0.93396876*AD8-1.6242981*AE8-61.304389*AC8-95.472727*IF(AND(B8>=DATE(2020,3,20),B8<=DATE(2020,6,26)),1,0)+156.04851*AF8-0.0087322858*AQ8) -> 6768.9508 | AV8: =IF(N8="","",2518.0489-204.66184*I8+0.019354281*N8-2.3328708*V8-0.0022533804*E8+1.5259709*AD8-3.5842757*AE8-65.580099*AC8-62.828483*IF(AND(B8>=DATE(2020,3,20),B8<=DATE(2020,6,26)),1,0)+200.94286*AF8+0.00080379976*AR8) -> 7005.5973 | AW8: =IF(N8="","",2361.7153+89.223162*I8+0.018847054*N8-5.0210815*V8-0.0006437347*E8+1.4213619*AD8-3.2156123*AE8+167.41121*AC8-224.35191*IF(AND(B8>=DATE(2020,3,20),B8<=DATE(2020,6,26)),1,0)+194.56435*AF8-19.897843*AS8) -> 7151.441 | AX8: =IF(N8="","",-654.03928+2464.5589*I8+0.035956453*N8-8.0754527*V8-0.00069441316*E8+0.69511606*AD8-1.1669613*AE8-90.724569*AC8-211.24919*IF(AND(B8>=DATE(2020,3,20),B8<=DATE(2020,6,26)),1,0)+147.22132*AF8-0.010108087*AQ8) -> 6738.1832
A9: 8 | B9: 33326 | C9: 6777 | E9: 509000 | G9: 19.5825 | H9: 18.275 | I9: 1.047 | L9: 1068 | M9: 12.409 | N9: 157889 | O9: 3841 | V9: 82.8 | AC9: 0 | AD9: 79 | AE9: 7.1 | AF9: 12.2055 | AG9: =6753.47943187+0.36116788*I9+0.01252571*N9-22.85359542*V9+0.00407811*AA9-0.00067349*E9 -> 6496.4453 | AH9: =A9*'Simple Linear Regression'!$B$18+'Simple Linear Regression'!$B$17 -> 7892.1606 | AI9: =7491.3971+0.0137554*N9-0.00058829*E9-34.3283*V9+0.30565*L9+54.6031*M9 -> 7525.4047 | AJ9: =7491.3971-0.00058829*E9+0.30565*L9+54.6031*M9+0.0137554*N9-34.3283*V9 -> 7525.4047 | AL9: =2192.59+2373.87*I9+0.0316653*N9-15.7623*V9+0.00202406*AA9-0.000740146*E9-0.00963493*(I9*N9) -> 6403.0335 | AM9: =5205.907083+122.0638992*I9+13.609808*(N9/1000)-1.245906883*AD9+0.7746840854*AE9-134.2474226*AC9-1547.125689*IF(AND(B9>=DATE(2020,3,20),B9<=DATE(2020,6,26)),1,0) -> 7389.6206 | AN9: =7707.2178-144.397321*AC9+139.5614087*AF9-0.0008594506251*E9-265.7105668*I9-0.02506176117*J9+0.004708026652*N9 -> 9438.3209 | AO9: =IF(N9="","",2190.39 + 2739.06*I9 + 0.034693*N9 - 16.722*V9 - 0.000802*E9 - 1.3691*AD9 + 1.8691*AE9 - 121.7*AC9 + 209.88*IF(AND(B9>=DATE(2020,3,20),B9<=DATE(2020,6,26)),1,0) - 0.011049*(I9*N9)) -> 6821.6332 | AP9: =IF(B9<DATE(2008,1,1),"",3929.06 + 1212.53*I9 - 0.0003097*N9 + 59.426*V9 - 0.0006734*E9 - 1.036*AD9 + 1.2076*AE9 + 94.923*AF9 - 131.43*AC9 - 759.61*IF(AND(B9>=DATE(2020,3,20),B9<=DATE(2020,6,26)),1,0) - 17.324*(I9*V9)) | AQ9: =IF(N9="","",I9*N9) -> 165309.78 | AR9: =I9*E9 -> 532923 | AS9: =AC9*AF9 -> 0 | AT9: =IF(N9="","",2413.3773+89.103503*I9+0.018847679*N9-5.0917058*V9-0.00064564578*E9+1.4315076*AD9-3.1976817*AE9-66.972905*AC9-217.08397*IF(AND(B9>=DATE(2020,3,20),B9<=DATE(2020,6,26)),1,0)+190.76803*AF9) -> 7151.0877 | AU9: =IF(N9="","",-480.76297+2186.3009*I9+0.033368804*N9-5.3903106*V9-0.00073731439*E9+0.93396876*AD9-1.6242981*AE9-61.304389*AC9-95.472727*IF(AND(B9>=DATE(2020,3,20),B9<=DATE(2020,6,26)),1,0)+156.04851*AF9-0.0087322858*AQ9) -> 6778.6193 | AV9: =IF(N9="","",2518.0489-204.66184*I9+0.019354281*N9-2.3328708*V9-0.0022533804*E9+1.5259709*AD9-3.5842757*AE9-65.580099*AC9-62.828483*IF(AND(B9>=DATE(2020,3,20),B9<=DATE(2020,6,26)),1,0)+200.94286*AF9+0.00080379976*AR9) -> 6995.5385 | AW9: =IF(N9="","",2361.7153+89.223162*I9+0.018847054*N9-5.0210815*V9-0.0006437347*E9+1.4213619*AD9-3.2156123*AE9+167.41121*AC9-224.35191*IF(AND(B9>=DATE(2020,3,20),B9<=DATE(2020,6,26)),1,0)+194.56435*AF9-19.897843*AS9) -> 7151.6799 | AX9: =IF(N9="","",-654.03928+2464.5589*I9+0.035956453*N9-8.0754527*V9-0.00069441316*E9+0.69511606*AD9-1.1669613*AE9-90.724569*AC9-211.24919*IF(AND(B9>=DATE(2020,3,20),B9<=DATE(2020,6,26)),1,0)+147.22132*AF9-0.010108087*AQ9) -> 6753.9514
A10: 9 | B10: 33333 | C10: 7503 | E10: 499000 | G10: 19.63 | H10: 17.946 | I10: 1.052 | L10: 984 | M10: 12.409 | N10: 157889 | O10: 3866.7 | V10: 82.8 | AC10: 0 | AD10: 92.3 | AE10: 2.8 | AF10: 12.4916 | AG10: =6753.47943187+0.36116788*I10+0.01252571*N10-22.85359542*V10+0.00407811*AA10-0.00067349*E10 -> 6503.182 | AH10: =A10*'Simple Linear Regression'!$B$18+'Simple Linear Regression'!$B$17 -> 7893.0137 | AI10: =7491.3971+0.0137554*N10-0.00058829*E10-34.3283*V10+0.30565*L10+54.6031*M10 -> 7505.613 | AJ10: =7491.3971-0.00058829*E10+0.30565*L10+54.6031*M10+0.0137554*N10-34.3283*V10 -> 7505.613 | AL10: =2192.59+2373.87*I10+0.0316653*N10-15.7623*V10+0.00202406*AA10-0.000740146*E10-0.00963493*(I10*N10) -> 6414.6981 | AM10: =5205.907083+122.0638992*I10+13.609808*(N10/1000)-1.245906883*AD10+0.7746840854*AE10-134.2474226*AC10-1547.125689*IF(AND(B10>=DATE(2020,3,20),B10<=DATE(2020,6,26)),1,0) -> 7370.3292 | AN10: =7707.2178-144.397321*AC10+139.5614087*AF10-0.0008594506251*E10-265.7105668*I10-0.02506176117*J10+0.004708026652*N10 -> 9485.5153 | AO10: =IF(N10="","",2190.39 + 2739.06*I10 + 0.034693*N10 - 16.722*V10 - 0.000802*E10 - 1.3691*AD10 + 1.8691*AE10 - 121.7*AC10 + 209.88*IF(AND(B10>=DATE(2020,3,20),B10<=DATE(2020,6,26)),1,0) - 0.011049*(I10*N10)) -> 6808.3798 | AP10: =IF(B10<DATE(2008,1,1),"",3929.06 + 1212.53*I10 - 0.0003097*N10 + 59.426*V10 - 0.0006734*E10 - 1.036*AD10 + 1.2076*AE10 + 94.923*AF10 - 131.43*AC10 - 759.61*IF(AND(B10>=DATE(2020,3,20),B10<=DATE(2020,6,26)),1,0) - 17.324*(I10*V10)) | AQ10: =IF(N10="","",I10*N10) -> 166099.23 | AR10: =I10*E10 -> 524948 | AS10: =AC10*AF10 -> 0 | AT10: =IF(N10="","",2413.3773+89.103503*I10+0.018847679*N10-5.0917058*V10-0.00064564578*E10+1.4315076*AD10-3.1976817*AE10-66.972905*AC10-217.08397*IF(AND(B10>=DATE(2020,3,20),B10<=DATE(2020,6,26)),1,0)+190.76803*AF10) -> 7245.3575 | AU10: =IF(N10="","",-480.76297+2186.3009*I10+0.033368804*N10-5.3903106*V10-0.00073731439*E10+0.93396876*AD10-1.6242981*AE10-61.304389*AC10-95.472727*IF(AND(B10>=DATE(2020,3,20),B10<=DATE(2020,6,26)),1,0)+156.04851*AF10-0.0087322858*AQ10) -> 6854.082 | AV10: =IF(N10="","",2518.0489-204.66184*I10+0.019354281*N10-2.3328708*V10-0.0022533804*E10+1.5259709*AD10-3.5842757*AE10-65.580099*AC10-62.828483*IF(AND(B10>=DATE(2020,3,20),B10<=DATE(2020,6,26)),1,0)+200.94286*AF10+0.00080379976*AR10) -> 7103.8362 | AW10: =IF(N10="","",2361.7153+89.223162*I10+0.018847054*N10-5.0210815*V10-0.0006437347*E10+1.4213619*AD10-3.2156123*AE10+167.41121*AC10-224.35191*IF(AND(B10>=DATE(2020,3,20),B10<=DATE(2020,6,26)),1,0)+194.56435*AF10-19.897843*AS10) -> 7246.9594 | AX10: =IF(N10="","",-654.03928+2464.5589*I10+0.035956453*N10-8.0754527*V10-0.00069441316*E10+0.69511606*AD10-1.1669613*AE10-90.724569*AC10-211.24919*IF(AND(B10>=DATE(2020,3,20),B10<=DATE(2020,6,26)),1,0)+147.22132*AF10-0.010108087*AQ10) -> 6821.6216
A11: 10 | B11: 33340 | C11: 6916 | E11: 452000 | G11: 20.892 | H11: 19.172 | I11: 1.066 | L11: 984 | M11: 12.409 | N11: 157889 | O11: 3866.7 | V11: 82.5 | AC11: 0 | AD11: 37.2 | AE11: 14.2 | AF11: 12.7734 | AG11: =6753.47943187+0.36116788*I11+0.01252571*N11-22.85359542*V11+0.00407811*AA11-0.00067349*E11 -> 6541.6972 | AH11: =A11*'Simple Linear Regression'!$B$18+'Simple Linear Regression'!$B$17 -> 7893.8667 | AI11: =7491.3971+0.0137554*N11-0.00058829*E11-34.3283*V11+0.30565*L11+54.6031*M11 -> 7543.5611 | AJ11: =7491.3971-0.00058829*E11+0.30565*L11+54.6031*M11+0.0137554*N11-34.3283*V11 -> 7543.5611 | AL11: =2192.59+2373.87*I11+0.0316653*N11-15.7623*V11+0.00202406*AA11-0.000740146*E11-0.00963493*(I11*N11) -> 6466.1503 | AM11: =5205.907083+122.0638992*I11+13.609808*(N11/1000)-1.245906883*AD11+0.7746840854*AE11-134.2474226*AC11-1547.125689*IF(AND(B11>=DATE(2020,3,20),B11<=DATE(2020,6,26)),1,0) -> 7449.519 | AN11: =7707.2178-144.397321*AC11+139.5614087*AF11-0.0008594506251*E11-265.7105668*I11-0.02506176117*J11+0.004708026652*N11 -> 9561.518 | AO11: =IF(N11="","",2190.39 + 2739.06*I11 + 0.034693*N11 - 16.722*V11 - 0.000802*E11 - 1.3691*AD11 + 1.8691*AE11 - 121.7*AC11 + 209.88*IF(AND(B11>=DATE(2020,3,20),B11<=DATE(2020,6,26)),1,0) - 0.011049*(I11*N11)) -> 6961.7591 | AP11: =IF(B11<DATE(2008,1,1),"",3929.06 + 1212.53*I11 - 0.0003097*N11 + 59.426*V11 - 0.0006734*E11 - 1.036*AD11 + 1.2076*AE11 + 94.923*AF11 - 131.43*AC11 - 759.61*IF(AND(B11>=DATE(2020,3,20),B11<=DATE(2020,6,26)),1,0) - 17.324*(I11*V11)) | AQ11: =IF(N11="","",I11*N11) -> 168309.67 | AR11: =I11*E11 -> 481832 | AS11: =AC11*AF11 -> 0 | AT11: =IF(N11="","",2413.3773+89.103503*I11+0.018847679*N11-5.0917058*V11-0.00064564578*E11+1.4315076*AD11-3.1976817*AE11-66.972905*AC11-217.08397*IF(AND(B11>=DATE(2020,3,20),B11<=DATE(2020,6,26)),1,0)+190.76803*AF11) -> 7216.9066 | AU11: =IF(N11="","",-480.76297+2186.3009*I11+0.033368804*N11-5.3903106*V11-0.00073731439*E11+0.93396876*AD11-1.6242981*AE11-61.304389*AC11-95.472727*IF(AND(B11>=DATE(2020,3,20),B11<=DATE(2020,6,26)),1,0)+156.04851*AF11-0.0087322858*AQ11) -> 6875.6546 | AV11: =IF(N11="","",2518.0489-204.66184*I11+0.019354281*N11-2.3328708*V11-0.0022533804*E11+1.5259709*AD11-3.5842757*AE11-65.580099*AC11-62.828483*IF(AND(B11>=DATE(2020,3,20),B11<=DATE(2020,6,26)),1,0)+200.94286*AF11+0.00080379976*AR11) -> 7104.607 | AW11: =IF(N11="","",2361.7153+89.223162*I11+0.018847054*N11-5.0210815*V11-0.0006437347*E11+1.4213619*AD11-3.2156123*AE11+167.41121*AC11-224.35191*IF(AND(B11>=DATE(2020,3,20),B11<=DATE(2020,6,26)),1,0)+194.56435*AF11-19.897843*AS11) -> 7219.8236 | AX11: =IF(N11="","",-654.03928+2464.5589*I11+0.035956453*N11-8.0754527*V11-0.00069441316*E11+0.69511606*AD11-1.1669613*AE11-90.724569*AC11-211.24919*IF(AND(B11>=DATE(2020,3,20),B11<=DATE(2020,6,26)),1,0)+147.22132*AF11-0.010108087*AQ11) -> 6858.7248
A12: 11 | B12: 33347 | C12: 7045 | E12: 477000 | G12: 21.484 | H12: 19.712 | I12: 1.069 | L12: 984 | M12: 12.848 | N12: 153351 | O12: 3866.7 | V12: 82.5 | AC12: 0 | AD12: 62 | AE12: 14.6 | AF12: 13.0483 | AG12: =6753.47943187+0.36116788*I12+0.01252571*N12-22.85359542*V12+0.00407811*AA12-0.00067349*E12 -> 6468.0193 | AH12: =A12*'Simple Linear Regression'!$B$18+'Simple Linear Regression'!$B$17 -> 7894.7198 | AI12: =7491.3971+0.0137554*N12-0.00058829*E12-34.3283*V12+0.30565*L12+54.6031*M12 -> 7490.4026 | AJ12: =7491.3971-0.00058829*E12+0.30565*L12+54.6031*M12+0.0137554*N12-34.3283*V12 -> 7490.4026 | AL12: =2192.59+2373.87*I12+0.0316653*N12-15.7623*V12+0.00202406*AA12-0.000740146*E12-0.00963493*(I12*N12) -> 6353.2476 | AM12: =5205.907083+122.0638992*I12+13.609808*(N12/1000)-1.245906883*AD12+0.7746840854*AE12-134.2474226*AC12-1547.125689*IF(AND(B12>=DATE(2020,3,20),B12<=DATE(2020,6,26)),1,0) -> 7357.5352 | AN12: =7707.2178-144.397321*AC12+139.5614087*AF12-0.0008594506251*E12-265.7105668*I12-0.02506176117*J12+0.004708026652*N12 -> 9556.235 | AO12: =IF(N12="","",2190.39 + 2739.06*I12 + 0.034693*N12 - 16.722*V12 - 0.000802*E12 - 1.3691*AD12 + 1.8691*AE12 - 121.7*AC12 + 209.88*IF(AND(B12>=DATE(2020,3,20),B12<=DATE(2020,6,26)),1,0) - 0.011049*(I12*N12)) -> 6807.65 | AP12: =IF(B12<DATE(2008,1,1),"",3929.06 + 1212.53*I12 - 0.0003097*N12 + 59.426*V12 - 0.0006734*E12 - 1.036*AD12 + 1.2076*AE12 + 94.923*AF12 - 131.43*AC12 - 759.61*IF(AND(B12>=DATE(2020,3,20),B12<=DATE(2020,6,26)),1,0) - 17.324*(I12*V12)) | AQ12: =IF(N12="","",I12*N12) -> 163932.22 | AR12: =I12*E12 -> 509913 | AS12: =AC12*AF12 -> 0 | AT12: =IF(N12="","",2413.3773+89.103503*I12+0.018847679*N12-5.0917058*V12-0.00064564578*E12+1.4315076*AD12-3.1976817*AE12-66.972905*AC12-217.08397*IF(AND(B12>=DATE(2020,3,20),B12<=DATE(2020,6,26)),1,0)+190.76803*AF12) -> 7202.1664 | AU12: =IF(N12="","",-480.76297+2186.3009*I12+0.033368804*N12-5.3903106*V12-0.00073731439*E12+0.93396876*AD12-1.6242981*AE12-61.304389*AC12-95.472727*IF(AND(B12>=DATE(2020,3,20),B12<=DATE(2020,6,26)),1,0)+156.04851*AF12-0.0087322858*AQ12) -> 6815.9887 | AV12: =IF(N12="","",2518.0489-204.66184*I12+0.019354281*N12-2.3328708*V12-0.0022533804*E12+1.5259709*AD12-3.5842757*AE12-65.580099*AC12-62.828483*IF(AND(B12>=DATE(2020,3,20),B12<=DATE(2020,6,26)),1,0)+200.94286*AF12+0.00080379976*AR12) -> 7074.0499 | AW12: =IF(N12="","",2361.7153+89.223162*I12+0.018847054*N12-5.0210815*V12-0.0006437347*E12+1.4213619*AD12-3.2156123*AE12+167.41121*AC12-224.35191*IF(AND(B12>=DATE(2020,3,20),B12<=DATE(2020,6,26)),1,0)+194.56435*AF12-19.897843*AS12) -> 7205.9193 | AX12: =IF(N12="","",-654.03928+2464.5589*I12+0.035956453*N12-8.0754527*V12-0.00069441316*E12+0.69511606*AD12-1.1669613*AE12-90.724569*AC12-211.24919*IF(AND(B12>=DATE(2020,3,20),B12<=DATE(2020,6,26)),1,0)+147.22132*AF12-0.010108087*AQ12) -> 6787.0787
A13: 12 | B13: 33354 | C13: 6956 | E13: 478000 | G13: 21.188 | H13: 19.632 | I13: 1.09 | L13: 984 | M13: 12.848 | N13: 153351 | O13: 3866.7 | V13: 82.5 | AC13: 0 | AD13: 64.9 | AE13: 9.9 | AF13: 13.3132 | AG13: =6753.47943187+0.36116788*I13+0.01252571*N13-22.85359542*V13+0.00407811*AA13-0.00067349*E13 -> 6467.3534 | AH13: =A13*'Simple Linear Regression'!$B$18+'Simple Linear Regression'!$B$17 -> 7895.5728 | AI13: =7491.3971+0.0137554*N13-0.00058829*E13-34.3283*V13+0.30565*L13+54.6031*M13 -> 7489.8143 | AJ13: =7491.3971-0.00058829*E13+0.30565*L13+54.6031*M13+0.0137554*N13-34.3283*V13 -> 7489.8143 | AL13: =2192.59+2373.87*I13+0.0316653*N13-15.7623*V13+0.00202406*AA13-0.000740146*E13-0.00963493*(I13*N13) -> 6371.3307 | AM13: =5205.907083+122.0638992*I13+13.609808*(N13/1000)-1.245906883*AD13+0.7746840854*AE13-134.2474226*AC13-1547.125689*IF(AND(B13>=DATE(2020,3,20),B13<=DATE(2020,6,26)),1,0) -> 7352.8444 | AN13: =7707.2178-144.397321*AC13+139.5614087*AF13-0.0008594506251*E13-265.7105668*I13-0.02506176117*J13+0.004708026652*N13 -> 9586.7654 | AO13: =IF(N13="","",2190.39 + 2739.06*I13 + 0.034693*N13 - 16.722*V13 - 0.000802*E13 - 1.3691*AD13 + 1.8691*AE13 - 121.7*AC13 + 209.88*IF(AND(B13>=DATE(2020,3,20),B13<=DATE(2020,6,26)),1,0) - 0.011049*(I13*N13)) -> 6816.0312 | AP13: =IF(B13<DATE(2008,1,1),"",3929.06 + 1212.53*I13 - 0.0003097*N13 + 59.426*V13 - 0.0006734*E13 - 1.036*AD13 + 1.2076*AE13 + 94.923*AF13 - 131.43*AC13 - 759.61*IF(AND(B13>=DATE(2020,3,20),B13<=DATE(2020,6,26)),1,0) - 17.324*(I13*V13)) | AQ13: =IF(N13="","",I13*N13) -> 167152.59 | AR13: =I13*E13 -> 521020 | AS13: =AC13*AF13 -> 0 | AT13: =IF(N13="","",2413.3773+89.103503*I13+0.018847679*N13-5.0917058*V13-0.00064564578*E13+1.4315076*AD13-3.1976817*AE13-66.972905*AC13-217.08397*IF(AND(B13>=DATE(2020,3,20),B13<=DATE(2020,6,26)),1,0)+190.76803*AF13) -> 7273.1069 | AU13: =IF(N13="","",-480.76297+2186.3009*I13+0.033368804*N13-5.3903106*V13-0.00073731439*E13+0.93396876*AD13-1.6242981*AE13-61.304389*AC13-95.472727*IF(AND(B13>=DATE(2020,3,20),B13<=DATE(2020,6,26)),1,0)+156.04851*AF13-0.0087322858*AQ13) -> 6884.7224 | AV13: =IF(N13="","",2518.0489-204.66184*I13+0.019354281*N13-2.3328708*V13-0.0022533804*E13+1.5259709*AD13-3.5842757*AE13-65.580099*AC13-62.828483*IF(AND(B13>=DATE(2020,3,20),B13<=DATE(2020,6,26)),1,0)+200.94286*AF13+0.00080379976*AR13) -> 7150.9276 | AW13: =IF(N13="","",2361.7153+89.223162*I13+0.018847054*N13-5.0210815*V13-0.0006437347*E13+1.4213619*AD13-3.2156123*AE13+167.41121*AC13-224.35191*IF(AND(B13>=DATE(2020,3,20),B13<=DATE(2020,6,26)),1,0)+194.56435*AF13-19.897843*AS13) -> 7277.9246 | AX13: =IF(N13="","",-654.03928+2464.5589*I13+0.035956453*N13-8.0754527*V13-0.00069441316*E13+0.69511606*AD13-1.1669613*AE13-90.724569*AC13-211.24919*IF(AND(B13>=DATE(2020,3,20),B13<=DATE(2020,6,26)),1,0)+147.22132*AF13-0.010108087*AQ13) -> 6852.0877
A14: 13 | B14: 33361 | C14: 6976 | E14: 462000 | G14: 21.234 | H14: 19.72 | I14: 1.104 | L14: 984 | M14: 12.848 | N14: 153351 | O14: 3866.7 | V14: 82.5 | AC14: 0 | AD14: 30.2 | AE14: 21.4 | AF14: 13.5644 | AG14: =6753.47943187+0.36116788*I14+0.01252571*N14-22.85359542*V14+0.00407811*AA14-0.00067349*E14 -> 6478.1343 | AH14: =A14*'Simple Linear Regression'!$B$18+'Simple Linear Regression'!$B$17 -> 7896.4258 | AI14: =7491.3971+0.0137554*N14-0.00058829*E14-34.3283*V14+0.30565*L14+54.6031*M14 -> 7499.2269 | AJ14: =7491.3971-0.00058829*E14+0.30565*L14+54.6031*M14+0.0137554*N14-34.3283*V14 -> 7499.2269 | AL14: =2192.59+2373.87*I14+0.0316653*N14-15.7623*V14+0.00202406*AA14-0.000740146*E14-0.00963493*(I14*N14) -> 6395.7218 | AM14: =5205.907083+122.0638992*I14+13.609808*(N14/1000)-1.245906883*AD14+0.7746840854*AE14-134.2474226*AC14-1547.125689*IF(AND(B14>=DATE(2020,3,20),B14<=DATE(2020,6,26)),1,0) -> 7406.6951 | AN14: =7707.2178-144.397321*AC14+139.5614087*AF14-0.0008594506251*E14-265.7105668*I14-0.02506176117*J14+0.004708026652*N14 -> 9631.8545 | AO14: =IF(N14="","",2190.39 + 2739.06*I14 + 0.034693*N14 - 16.722*V14 - 0.000802*E14 - 1.3691*AD14 + 1.8691*AE14 - 121.7*AC14 + 209.88*IF(AND(B14>=DATE(2020,3,20),B14<=DATE(2020,6,26)),1,0) - 0.011049*(I14*N14)) -> 6912.4912 | AP14: =IF(B14<DATE(2008,1,1),"",3929.06 + 1212.53*I14 - 0.0003097*N14 + 59.426*V14 - 0.0006734*E14 - 1.036*AD14 + 1.2076*AE14 + 94.923*AF14 - 131.43*AC14 - 759.61*IF(AND(B14>=DATE(2020,3,20),B14<=DATE(2020,6,26)),1,0) - 17.324*(I14*V14)) | AQ14: =IF(N14="","",I14*N14) -> 169299.5 | AR14: =I14*E14 -> 510048 | AS14: =AC14*AF14 -> 0 | AT14: =IF(N14="","",2413.3773+89.103503*I14+0.018847679*N14-5.0917058*V14-0.00064564578*E14+1.4315076*AD14-3.1976817*AE14-66.972905*AC14-217.08397*IF(AND(B14>=DATE(2020,3,20),B14<=DATE(2020,6,26)),1,0)+190.76803*AF14) -> 7246.1589 | AU14: =IF(N14="","",-480.76297+2186.3009*I14+0.033368804*N14-5.3903106*V14-0.00073731439*E14+0.93396876*AD14-1.6242981*AE14-61.304389*AC14-95.472727*IF(AND(B14>=DATE(2020,3,20),B14<=DATE(2020,6,26)),1,0)+156.04851*AF14-0.0087322858*AQ14) -> 6896.4914 | AV14: =IF(N14="","",2518.0489-204.66184*I14+0.019354281*N14-2.3328708*V14-0.0022533804*E14+1.5259709*AD14-3.5842757*AE14-65.580099*AC14-62.828483*IF(AND(B14>=DATE(2020,3,20),B14<=DATE(2020,6,26)),1,0)+200.94286*AF14+0.00080379976*AR14) -> 7131.6036 | AW14: =IF(N14="","",2361.7153+89.223162*I14+0.018847054*N14-5.0210815*V14-0.0006437347*E14+1.4213619*AD14-3.2156123*AE14+167.41121*AC14-224.35191*IF(AND(B14>=DATE(2020,3,20),B14<=DATE(2020,6,26)),1,0)+194.56435*AF14-19.897843*AS14) -> 7252.0473 | AX14: =IF(N14="","",-654.03928+2464.5589*I14+0.035956453*N14-8.0754527*V14-0.00069441316*E14+0.69511606*AD14-1.1669613*AE14-90.724569*AC14-211.24919*IF(AND(B14>=DATE(2020,3,20),B14<=DATE(2020,6,26)),1,0)+147.22132*AF14-0.010108087*AQ14) -> 6875.4423
A15: 14 | B15: 33368 | C15: 7185 | E15: 451000 | G15: 21.69 | H15: 19.812 | I15: 1.113 | J15: 6035.178 | L15: 929 | M15: 12.848 | N15: 153351 | O15: 3913 | V15: 84.4 | AC15: 0 | AD15: 27.9 | AE15: 19.4 | AF15: 13.7981 | AG15: =6753.47943187+0.36116788*I15+0.01252571*N15-22.85359542*V15+0.00407811*AA15-0.00067349*E15 -> 6442.1241 | AH15: =A15*'Simple Linear Regression'!$B$18+'Simple Linear Regression'!$B$17 -> 7897.2789 | AI15: =7491.3971+0.0137554*N15-0.00058829*E15-34.3283*V15+0.30565*L15+54.6031*M15 -> 7423.6636 | AJ15: =7491.3971-0.00058829*E15+0.30565*L15+54.6031*M15+0.0137554*N15-34.3283*V15 -> 7423.6636 | AL15: =2192.59+2373.87*I15+0.0316653*N15-15.7623*V15+0.00202406*AA15-0.000740146*E15-0.00963493*(I15*N15) -> 6381.9822 | AM15: =5205.907083+122.0638992*I15+13.609808*(N15/1000)-1.245906883*AD15+0.7746840854*AE15-134.2474226*AC15-1547.125689*IF(AND(B15>=DATE(2020,3,20),B15<=DATE(2020,6,26)),1,0) -> 7409.1099 | AN15: =7707.2178-144.397321*AC15+139.5614087*AF15-0.0008594506251*E15-265.7105668*I15-0.02506176117*J15+0.004708026652*N15 -> 9520.2804 | AO15: =IF(N15="","",2190.39 + 2739.06*I15 + 0.034693*N15 - 16.722*V15 - 0.000802*E15 - 1.3691*AD15 + 1.8691*AE15 - 121.7*AC15 + 209.88*IF(AND(B15>=DATE(2020,3,20),B15<=DATE(2020,6,26)),1,0) - 0.011049*(I15*N15)) -> 6898.3543 | AP15: =IF(B15<DATE(2008,1,1),"",3929.06 + 1212.53*I15 - 0.0003097*N15 + 59.426*V15 - 0.0006734*E15 - 1.036*AD15 + 1.2076*AE15 + 94.923*AF15 - 131.43*AC15 - 759.61*IF(AND(B15>=DATE(2020,3,20),B15<=DATE(2020,6,26)),1,0) - 17.324*(I15*V15)) | AQ15: =IF(N15="","",I15*N15) -> 170679.66 | AR15: =I15*E15 -> 501963 | AS15: =AC15*AF15 -> 0 | AT15: =IF(N15="","",2413.3773+89.103503*I15+0.018847679*N15-5.0917058*V15-0.00064564578*E15+1.4315076*AD15-3.1976817*AE15-66.972905*AC15-217.08397*IF(AND(B15>=DATE(2020,3,20),B15<=DATE(2020,6,26)),1,0)+190.76803*AF15) -> 7292.0741 | AU15: =IF(N15="","",-480.76297+2186.3009*I15+0.033368804*N15-5.3903106*V15-0.00073731439*E15+0.93396876*AD15-1.6242981*AE15-61.304389*AC15-95.472727*IF(AND(B15>=DATE(2020,3,20),B15<=DATE(2020,6,26)),1,0)+156.04851*AF15-0.0087322858*AQ15) -> 6939.5541 | AV15: =IF(N15="","",2518.0489-204.66184*I15+0.019354281*N15-2.3328708*V15-0.0022533804*E15+1.5259709*AD15-3.5842757*AE15-65.580099*AC15-62.828483*IF(AND(B15>=DATE(2020,3,20),B15<=DATE(2020,6,26)),1,0)+200.94286*AF15+0.00080379976*AR15) -> 7194.2368 | AW15: =IF(N15="","",2361.7153+89.223162*I15+0.018847054*N15-5.0210815*V15-0.0006437347*E15+1.4213619*AD15-3.2156123*AE15+167.41121*AC15-224.35191*IF(AND(B15>=DATE(2020,3,20),B15<=DATE(2020,6,26)),1,0)+194.56435*AF15-19.897843*AS15) -> 7299.0231 | AX15: =IF(N15="","",-654.03928+2464.5589*I15+0.035956453*N15-8.0754527*V15-0.00069441316*E15+0.69511606*AD15-1.1669613*AE15-90.724569*AC15-211.24919*IF(AND(B15>=DATE(2020,3,20),B15<=DATE(2020,6,26)),1,0)+147.22132*AF15-0.010108087*AQ15) -> 6911.1086
A16: 15 | B16: 33375 | C16: 6899 | E16: 446000 | G16: 20.952 | H16: 18.9 | I16: 1.121 | J16: 6035.178 | L16: 929 | M16: 12.038 | N16: 179076 | O16: 3913 | V16: 84.4 | AC16: 0 | AD16: 4.5 | AE16: 42.5 | AF16: 14.0096 | AG16: =6753.47943187+0.36116788*I16+0.01252571*N16-22.85359542*V16+0.00407811*AA16-0.00067349*E16 -> 6767.7184 | AH16: =A16*'Simple Linear Regression'!$B$18+'Simple Linear Regression'!$B$17 -> 7898.1319 | AI16: =7491.3971+0.0137554*N16-0.00058829*E16-34.3283*V16+0.30565*L16+54.6031*M16 -> 7736.2342 | AJ16: =7491.3971-0.00058829*E16+0.30565*L16+54.6031*M16+0.0137554*N16-34.3283*V16 -> 7736.2342 | AL16: =2192.59+2373.87*I16+0.0316653*N16-15.7623*V16+0.00202406*AA16-0.000740146*E16-0.00963493*(I16*N16) -> 6929.594 | AM16: =5205.907083+122.0638992*I16+13.609808*(N16/1000)-1.245906883*AD16+0.7746840854*AE16-134.2474226*AC16-1547.125689*IF(AND(B16>=DATE(2020,3,20),B16<=DATE(2020,6,26)),1,0) -> 7807.2482 | AN16: =7707.2178-144.397321*AC16+139.5614087*AF16-0.0008594506251*E16-265.7105668*I16-0.02506176117*J16+0.004708026652*N16 -> 9673.0832 | AO16: =IF(N16="","",2190.39 + 2739.06*I16 + 0.034693*N16 - 16.722*V16 - 0.000802*E16 - 1.3691*AD16 + 1.8691*AE16 - 121.7*AC16 + 209.88*IF(AND(B16>=DATE(2020,3,20),B16<=DATE(2020,6,26)),1,0) - 0.011049*(I16*N16)) -> 7559.7843 | AP16: =IF(B16<DATE(2008,1,1),"",3929.06 + 1212.53*I16 - 0.0003097*N16 + 59.426*V16 - 0.0006734*E16 - 1.036*AD16 + 1.2076*AE16 + 94.923*AF16 - 131.43*AC16 - 759.61*IF(AND(B16>=DATE(2020,3,20),B16<=DATE(2020,6,26)),1,0) - 17.324*(I16*V16)) | AQ16: =IF(N16="","",I16*N16) -> 200744.2 | AR16: =I16*E16 -> 499966 | AS16: =AC16*AF16 -> 0 | AT16: =IF(N16="","",2413.3773+89.103503*I16+0.018847679*N16-5.0917058*V16-0.00064564578*E16+1.4315076*AD16-3.1976817*AE16-66.972905*AC16-217.08397*IF(AND(B16>=DATE(2020,3,20),B16<=DATE(2020,6,26)),1,0)+190.76803*AF16) -> 7713.8554 | AU16: =IF(N16="","",-480.76297+2186.3009*I16+0.033368804*N16-5.3903106*V16-0.00073731439*E16+0.93396876*AD16-1.6242981*AE16-61.304389*AC16-95.472727*IF(AND(B16>=DATE(2020,3,20),B16<=DATE(2020,6,26)),1,0)+156.04851*AF16-0.0087322858*AQ16) -> 7530.2396 | AV16: =IF(N16="","",2518.0489-204.66184*I16+0.019354281*N16-2.3328708*V16-0.0022533804*E16+1.5259709*AD16-3.5842757*AE16-65.580099*AC16-62.828483*IF(AND(B16>=DATE(2020,3,20),B16<=DATE(2020,6,26)),1,0)+200.94286*AF16+0.00080379976*AR16) -> 7624.145 | AW16: =IF(N16="","",2361.7153+89.223162*I16+0.018847054*N16-5.0210815*V16-0.0006437347*E16+1.4213619*AD16-3.2156123*AE16+167.41121*AC16-224.35191*IF(AND(B16>=DATE(2020,3,20),B16<=DATE(2020,6,26)),1,0)+194.56435*AF16-19.897843*AS16) -> 7721.4059 | AX16: =IF(N16="","",-654.03928+2464.5589*I16+0.035956453*N16-8.0754527*V16-0.00069441316*E16+0.69511606*AD16-1.1669613*AE16-90.724569*AC16-211.24919*IF(AND(B16>=DATE(2020,3,20),B16<=DATE(2020,6,26)),1,0)+147.22132*AF16-0.010108087*AQ16) -> 7543.2967
A17: 16 | B17: 33382 | C17: 7396 | E17: 448000 | G17: 21.036 | H17: 18.824 | I17: 1.129 | J17: 6035.178 | L17: 929 | M17: 12.038 | N17: 179076 | O17: 3913 | V17: 84.4 | AC17: 0 | AD17: 15.8 | AE17: 31.9 | AF17: 14.1945 | AG17: =6753.47943187+0.36116788*I17+0.01252571*N17-22.85359542*V17+0.00407811*AA17-0.00067349*E17 -> 6766.3743 | AH17: =A17*'Simple Linear Regression'!$B$18+'Simple Linear Regression'!$B$17 -> 7898.9849 | AI17: =7491.3971+0.0137554*N17-0.00058829*E17-34.3283*V17+0.30565*L17+54.6031*M17 -> 7735.0576 | AJ17: =7491.3971-0.00058829*E17+0.30565*L17+54.6031*M17+0.0137554*N17-34.3283*V17 -> 7735.0576 | AL17: =2192.59+2373.87*I17+0.0316653*N17-15.7623*V17+0.00202406*AA17-0.000740146*E17-0.00963493*(I17*N17) -> 6933.3016 | AM17: =5205.907083+122.0638992*I17+13.609808*(N17/1000)-1.245906883*AD17+0.7746840854*AE17-134.2474226*AC17-1547.125689*IF(AND(B17>=DATE(2020,3,20),B17<=DATE(2020,6,26)),1,0) -> 7785.9343 | AN17: =7707.2178-144.397321*AC17+139.5614087*AF17-0.0008594506251*E17-265.7105668*I17-0.02506176117*J17+0.004708026652*N17 -> 9695.0435 | AO17: =IF(N17="","",2190.39 + 2739.06*I17 + 0.034693*N17 - 16.722*V17 - 0.000802*E17 - 1.3691*AD17 + 1.8691*AE17 - 121.7*AC17 + 209.88*IF(AND(B17>=DATE(2020,3,20),B17<=DATE(2020,6,26)),1,0) - 0.011049*(I17*N17)) -> 7528.9806 | AP17: =IF(B17<DATE(2008,1,1),"",3929.06 + 1212.53*I17 - 0.0003097*N17 + 59.426*V17 - 0.0006734*E17 - 1.036*AD17 + 1.2076*AE17 + 94.923*AF17 - 131.43*AC17 - 759.61*IF(AND(B17>=DATE(2020,3,20),B17<=DATE(2020,6,26)),1,0) - 17.324*(I17*V17)) | AQ17: =IF(N17="","",I17*N17) -> 202176.8 | AR17: =I17*E17 -> 505792 | AS17: =AC17*AF17 -> 0 | AT17: =IF(N17="","",2413.3773+89.103503*I17+0.018847679*N17-5.0917058*V17-0.00064564578*E17+1.4315076*AD17-3.1976817*AE17-66.972905*AC17-217.08397*IF(AND(B17>=DATE(2020,3,20),B17<=DATE(2020,6,26)),1,0)+190.76803*AF17) -> 7798.6214 | AU17: =IF(N17="","",-480.76297+2186.3009*I17+0.033368804*N17-5.3903106*V17-0.00073731439*E17+0.93396876*AD17-1.6242981*AE17-61.304389*AC17-95.472727*IF(AND(B17>=DATE(2020,3,20),B17<=DATE(2020,6,26)),1,0)+156.04851*AF17-0.0087322858*AQ17) -> 7590.3702 | AV17: =IF(N17="","",2518.0489-204.66184*I17+0.019354281*N17-2.3328708*V17-0.0022533804*E17+1.5259709*AD17-3.5842757*AE17-65.580099*AC17-62.828483*IF(AND(B17>=DATE(2020,3,20),B17<=DATE(2020,6,26)),1,0)+200.94286*AF17+0.00080379976*AR17) -> 7715.0751 | AW17: =IF(N17="","",2361.7153+89.223162*I17+0.018847054*N17-5.0210815*V17-0.0006437347*E17+1.4213619*AD17-3.2156123*AE17+167.41121*AC17-224.35191*IF(AND(B17>=DATE(2020,3,20),B17<=DATE(2020,6,26)),1,0)+194.56435*AF17-19.897843*AS17) -> 7806.954 | AX17: =IF(N17="","",-654.03928+2464.5589*I17+0.035956453*N17-8.0754527*V17-0.00069441316*E17+0.69511606*AD17-1.1669613*AE17-90.724569*AC17-211.24919*IF(AND(B17>=DATE(2020,3,20),B17<=DATE(2020,6,26)),1,0)+147.22132*AF17-0.010108087*AQ17) -> 7594.5893
A18: 17 | B18: 33389 | C18: 7287 | E18: 443000 | G18: 21.21 | H18: 18.87 | I18: 1.14 | J18: 6035.178 | L18: 929 | M18: 12.038 | N18: 179076 | O18: 3913 | V18: 84.4 | AC18: 1 | AD18: 3.7 | AE18: 69 | AF18: 14.3479 | AG18: =6753.47943187+0.36116788*I18+0.01252571*N18-22.85359542*V18+0.00407811*AA18-0.00067349*E18 -> 6769.7457 | AH18: =A18*'Simple Linear Regression'!$B$18+'Simple Linear Regression'!$B$17 -> 7899.838 | AI18: =7491.3971+0.0137554*N18-0.00058829*E18-34.3283*V18+0.30565*L18+54.6031*M18 -> 7737.9991 | AJ18: =7491.3971-0.00058829*E18+0.30565*L18+54.6031*M18+0.0137554*N18-34.3283*V18 -> 7737.9991 | AL18: =2192.59+2373.87*I18+0.0316653*N18-15.7623*V18+0.00202406*AA18-0.000740146*E18-0.00963493*(I18*N18) -> 6944.1357 | AM18: =5205.907083+122.0638992*I18+13.609808*(N18/1000)-1.245906883*AD18+0.7746840854*AE18-134.2474226*AC18-1547.125689*IF(AND(B18>=DATE(2020,3,20),B18<=DATE(2020,6,26)),1,0) -> 7696.8458 | AN18: =7707.2178-144.397321*AC18+139.5614087*AF18-0.0008594506251*E18-265.7105668*I18-0.02506176117*J18+0.004708026652*N18 -> 9573.4293 | AO18: =IF(N18="","",2190.39 + 2739.06*I18 + 0.034693*N18 - 16.722*V18 - 0.000802*E18 - 1.3691*AD18 + 1.8691*AE18 - 121.7*AC18 + 209.88*IF(AND(B18>=DATE(2020,3,20),B18<=DATE(2020,6,26)),1,0) - 0.011049*(I18*N18)) -> 7505.5653 | AP18: =IF(B18<DATE(2008,1,1),"",3929.06 + 1212.53*I18 - 0.0003097*N18 + 59.426*V18 - 0.0006734*E18 - 1.036*AD18 + 1.2076*AE18 + 94.923*AF18 - 131.43*AC18 - 759.61*IF(AND(B18>=DATE(2020,3,20),B18<=DATE(2020,6,26)),1,0) - 17.324*(I18*V18)) | AQ18: =IF(N18="","",I18*N18) -> 204146.64 | AR18: =I18*E18 -> 505020 | AS18: =AC18*AF18 -> 14.3479 | AT18: =IF(N18="","",2413.3773+89.103503*I18+0.018847679*N18-5.0917058*V18-0.00064564578*E18+1.4315076*AD18-3.1976817*AE18-66.972905*AC18-217.08397*IF(AND(B18>=DATE(2020,3,20),B18<=DATE(2020,6,26)),1,0)+190.76803*AF18) -> 7629.1655 | AU18: =IF(N18="","",-480.76297+2186.3009*I18+0.033368804*N18-5.3903106*V18-0.00073731439*E18+0.93396876*AD18-1.6242981*AE18-61.304389*AC18-95.472727*IF(AND(B18>=DATE(2020,3,20),B18<=DATE(2020,6,26)),1,0)+156.04851*AF18-0.0087322858*AQ18) -> 7491.9758 | AV18: =IF(N18="","",2518.0489-204.66184*I18+0.019354281*N18-2.3328708*V18-0.0022533804*E18+1.5259709*AD18-3.5842757*AE18-65.580099*AC18-62.828483*IF(AND(B18>=DATE(2020,3,20),B18<=DATE(2020,6,26)),1,0)+200.94286*AF18+0.00080379976*AR18) -> 7537.2738 | AW18: =IF(N18="","",2361.7153+89.223162*I18+0.018847054*N18-5.0210815*V18-0.0006437347*E18+1.4213619*AD18-3.2156123*AE18+167.41121*AC18-224.35191*IF(AND(B18>=DATE(2020,3,20),B18<=DATE(2020,6,26)),1,0)+194.56435*AF18-19.897843*AS18) -> 7586.4216 | AX18: =IF(N18="","",-654.03928+2464.5589*I18+0.035956453*N18-8.0754527*V18-0.00069441316*E18+0.69511606*AD18-1.1669613*AE18-90.724569*AC18-211.24919*IF(AND(B18>=DATE(2020,3,20),B18<=DATE(2020,6,26)),1,0)+147.22132*AF18-0.010108087*AQ18) -> 7485.4142
A19: 18 | B19: 33396 | C19: 7220 | E19: 432000 | G19: 20.634 | H19: 18.554 | I19: 1.138 | J19: 6035.178 | L19: 865 | M19: 12.038 | N19: 179076 | O19: 3907.1 | V19: 83.2 | AC19: 0 | AD19: 3.7 | AE19: 46.7 | AF19: 14.4654 | AG19: =6753.47943187+0.36116788*I19+0.01252571*N19-22.85359542*V19+0.00407811*AA19-0.00067349*E19 -> 6804.5777 | AH19: =A19*'Simple Linear Regression'!$B$18+'Simple Linear Regression'!$B$17 -> 7900.691 | AI19: =7491.3971+0.0137554*N19-0.00058829*E19-34.3283*V19+0.30565*L19+54.6031*M19 -> 7766.1026 | AJ19: =7491.3971-0.00058829*E19+0.30565*L19+54.6031*M19+0.0137554*N19-34.3283*V19 -> 7766.1026 | AL19: =2192.59+2373.87*I19+0.0316653*N19-15.7623*V19+0.00202406*AA19-0.000740146*E19-0.00963493*(I19*N19) -> 6969.8951 | AM19: =5205.907083+122.0638992*I19+13.609808*(N19/1000)-1.245906883*AD19+0.7746840854*AE19-134.2474226*AC19-1547.125689*IF(AND(B19>=DATE(2020,3,20),B19<=DATE(2020,6,26)),1,0) -> 7813.5737 | AN19: =7707.2178-144.397321*AC19+139.5614087*AF19-0.0008594506251*E19-265.7105668*I19-0.02506176117*J19+0.004708026652*N19 -> 9744.2105 | AO19: =IF(N19="","",2190.39 + 2739.06*I19 + 0.034693*N19 - 16.722*V19 - 0.000802*E19 - 1.3691*AD19 + 1.8691*AE19 - 121.7*AC19 + 209.88*IF(AND(B19>=DATE(2020,3,20),B19<=DATE(2020,6,26)),1,0) - 0.011049*(I19*N19)) -> 7612.9518 | AP19: =IF(B19<DATE(2008,1,1),"",3929.06 + 1212.53*I19 - 0.0003097*N19 + 59.426*V19 - 0.0006734*E19 - 1.036*AD19 + 1.2076*AE19 + 94.923*AF19 - 131.43*AC19 - 759.61*IF(AND(B19>=DATE(2020,3,20),B19<=DATE(2020,6,26)),1,0) - 17.324*(I19*V19)) | AQ19: =IF(N19="","",I19*N19) -> 203788.49 | AR19: =I19*E19 -> 491616 | AS19: =AC19*AF19 -> 0 | AT19: =IF(N19="","",2413.3773+89.103503*I19+0.018847679*N19-5.0917058*V19-0.00064564578*E19+1.4315076*AD19-3.1976817*AE19-66.972905*AC19-217.08397*IF(AND(B19>=DATE(2020,3,20),B19<=DATE(2020,6,26)),1,0)+190.76803*AF19) -> 7802.8959 | AU19: =IF(N19="","",-480.76297+2186.3009*I19+0.033368804*N19-5.3903106*V19-0.00073731439*E19+0.93396876*AD19-1.6242981*AE19-61.304389*AC19-95.472727*IF(AND(B19>=DATE(2020,3,20),B19<=DATE(2020,6,26)),1,0)+156.04851*AF19-0.0087322858*AQ19) -> 7621.1715 | AV19: =IF(N19="","",2518.0489-204.66184*I19+0.019354281*N19-2.3328708*V19-0.0022533804*E19+1.5259709*AD19-3.5842757*AE19-65.580099*AC19-62.828483*IF(AND(B19>=DATE(2020,3,20),B19<=DATE(2020,6,26)),1,0)+200.94286*AF19+0.00080379976*AR19) -> 7723.6159 | AW19: =IF(N19="","",2361.7153+89.223162*I19+0.018847054*N19-5.0210815*V19-0.0006437347*E19+1.4213619*AD19-3.2156123*AE19+167.41121*AC19-224.35191*IF(AND(B19>=DATE(2020,3,20),B19<=DATE(2020,6,26)),1,0)+194.56435*AF19-19.897843*AS19) -> 7812 | AX19: =IF(N19="","",-654.03928+2464.5589*I19+0.035956453*N19-8.0754527*V19-0.00069441316*E19+0.69511606*AD19-1.1669613*AE19-90.724569*AC19-211.24919*IF(AND(B19>=DATE(2020,3,20),B19<=DATE(2020,6,26)),1,0)+147.22132*AF19-0.010108087*AQ19) -> 7635.4807
A20: 19 | B20: 33403 | C20: 7651 | E20: 441000 | G20: 19.836 | H20: 17.856 | I20: 1.135 | J20: 6035.178 | L20: 865 | M20: 12.038 | N20: 179076 | O20: 3907.1 | V20: 83.2 | AC20: 0 | AD20: 0.2 | AE20: 56.4 | AF20: 14.5433 | AG20: =6753.47943187+0.36116788*I20+0.01252571*N20-22.85359542*V20+0.00407811*AA20-0.00067349*E20 -> 6798.5152 | AH20: =A20*'Simple Linear Regression'!$B$18+'Simple Linear Regression'!$B$17 -> 7901.5441 | AI20: =7491.3971+0.0137554*N20-0.00058829*E20-34.3283*V20+0.30565*L20+54.6031*M20 -> 7760.808 | AJ20: =7491.3971-0.00058829*E20+0.30565*L20+54.6031*M20+0.0137554*N20-34.3283*V20 -> 7760.808 | AL20: =2192.59+2373.87*I20+0.0316653*N20-15.7623*V20+0.00202406*AA20-0.000740146*E20-0.00963493*(I20*N20) -> 6961.2883 | AM20: =5205.907083+122.0638992*I20+13.609808*(N20/1000)-1.245906883*AD20+0.7746840854*AE20-134.2474226*AC20-1547.125689*IF(AND(B20>=DATE(2020,3,20),B20<=DATE(2020,6,26)),1,0) -> 7825.0826 | AN20: =7707.2178-144.397321*AC20+139.5614087*AF20-0.0008594506251*E20-265.7105668*I20-0.02506176117*J20+0.004708026652*N20 -> 9748.1444 | AO20: =IF(N20="","",2190.39 + 2739.06*I20 + 0.034693*N20 - 16.722*V20 - 0.000802*E20 - 1.3691*AD20 + 1.8691*AE20 - 121.7*AC20 + 209.88*IF(AND(B20>=DATE(2020,3,20),B20<=DATE(2020,6,26)),1,0) - 0.011049*(I20*N20)) -> 7626.3746 | AP20: =IF(B20<DATE(2008,1,1),"",3929.06 + 1212.53*I20 - 0.0003097*N20 + 59.426*V20 - 0.0006734*E20 - 1.036*AD20 + 1.2076*AE20 + 94.923*AF20 - 131.43*AC20 - 759.61*IF(AND(B20>=DATE(2020,3,20),B20<=DATE(2020,6,26)),1,0) - 17.324*(I20*V20)) | AQ20: =IF(N20="","",I20*N20) -> 203251.26 | AR20: =I20*E20 -> 500535 | AS20: =AC20*AF20 -> 0 | AT20: =IF(N20="","",2413.3773+89.103503*I20+0.018847679*N20-5.0917058*V20-0.00064564578*E20+1.4315076*AD20-3.1976817*AE20-66.972905*AC20-217.08397*IF(AND(B20>=DATE(2020,3,20),B20<=DATE(2020,6,26)),1,0)+190.76803*AF20) -> 7775.6508 | AU20: =IF(N20="","",-480.76297+2186.3009*I20+0.033368804*N20-5.3903106*V20-0.00073731439*E20+0.93396876*AD20-1.6242981*AE20-61.304389*AC20-95.472727*IF(AND(B20>=DATE(2020,3,20),B20<=DATE(2020,6,26)),1,0)+156.04851*AF20-0.0087322858*AQ20) -> 7605.7996 | AV20: =IF(N20="","",2518.0489-204.66184*I20+0.019354281*N20-2.3328708*V20-0.0022533804*E20+1.5259709*AD20-3.5842757*AE20-65.580099*AC20-62.828483*IF(AND(B20>=DATE(2020,3,20),B20<=DATE(2020,6,26)),1,0)+200.94286*AF20+0.00080379976*AR20) -> 7686.6636 | AW20: =IF(N20="","",2361.7153+89.223162*I20+0.018847054*N20-5.0210815*V20-0.0006437347*E20+1.4213619*AD20-3.2156123*AE20+167.41121*AC20-224.35191*IF(AND(B20>=DATE(2020,3,20),B20<=DATE(2020,6,26)),1,0)+194.56435*AF20-19.897843*AS20) -> 7784.9291 | AX20: =IF(N20="","",-654.03928+2464.5589*I20+0.035956453*N20-8.0754527*V20-0.00069441316*E20+0.69511606*AD20-1.1669613*AE20-90.724569*AC20-211.24919*IF(AND(B20>=DATE(2020,3,20),B20<=DATE(2020,6,26)),1,0)+147.22132*AF20-0.010108087*AQ20) -> 7624.9838
A21: 20 | B21: 33410 | C21: 7720 | E21: 429000 | G21: 20.078 | H21: 18.062 | I21: 1.126 | J21: 6035.178 | L21: 865 | M21: 12.487 | N21: 179538 | O21: 3907.1 | P21: 824860 | V21: 83.2 | AC21: 0 | AD21: 0.2 | AE21: 69.4 | AF21: 14.579 | AG21: =6753.47943187+0.36116788*I21+0.01252571*N21-22.85359542*V21+0.00407811*AA21-0.00067349*E21 -> 6812.3807 | AH21: =A21*'Simple Linear Regression'!$B$18+'Simple Linear Regression'!$B$17 -> 7902.3971 | AI21: =7491.3971+0.0137554*N21-0.00058829*E21-34.3283*V21+0.30565*L21+54.6031*M21 -> 7798.7393 | AJ21: =7491.3971-0.00058829*E21+0.30565*L21+54.6031*M21+0.0137554*N21-34.3283*V21 -> 7798.7393 | AL21: =2192.59+2373.87*I21+0.0316653*N21-15.7623*V21+0.00202406*AA21-0.000740146*E21-0.00963493*(I21*N21) -> 6973.9509 | AM21: =5205.907083+122.0638992*I21+13.609808*(N21/1000)-1.245906883*AD21+0.7746840854*AE21-134.2474226*AC21-1547.125689*IF(AND(B21>=DATE(2020,3,20),B21<=DATE(2020,6,26)),1,0) -> 7840.3426 | AN21: =7707.2178-144.397321*AC21+139.5614087*AF21-0.0008594506251*E21-265.7105668*I21-0.02506176117*J21+0.004708026652*N21 -> 9768.0067 | AO21: =IF(N21="","",2190.39 + 2739.06*I21 + 0.034693*N21 - 16.722*V21 - 0.000802*E21 - 1.3691*AD21 + 1.8691*AE21 - 121.7*AC21 + 209.88*IF(AND(B21>=DATE(2020,3,20),B21<=DATE(2020,6,26)),1,0) - 0.011049*(I21*N21)) -> 7663.7332 | AP21: =IF(B21<DATE(2008,1,1),"",3929.06 + 1212.53*I21 - 0.0003097*N21 + 59.426*V21 - 0.0006734*E21 - 1.036*AD21 + 1.2076*AE21 + 94.923*AF21 - 131.43*AC21 - 759.61*IF(AND(B21>=DATE(2020,3,20),B21<=DATE(2020,6,26)),1,0) - 17.324*(I21*V21)) | AQ21: =IF(N21="","",I21*N21) -> 202159.79 | AR21: =I21*E21 -> 483054 | AS21: =AC21*AF21 -> 0 | AT21: =IF(N21="","",2413.3773+89.103503*I21+0.018847679*N21-5.0917058*V21-0.00064564578*E21+1.4315076*AD21-3.1976817*AE21-66.972905*AC21-217.08397*IF(AND(B21>=DATE(2020,3,20),B21<=DATE(2020,6,26)),1,0)+190.76803*AF21) -> 7756.5448 | AU21: =IF(N21="","",-480.76297+2186.3009*I21+0.033368804*N21-5.3903106*V21-0.00073731439*E21+0.93396876*AD21-1.6242981*AE21-61.304389*AC21-95.472727*IF(AND(B21>=DATE(2020,3,20),B21<=DATE(2020,6,26)),1,0)+156.04851*AF21-0.0087322858*AQ21) -> 7604.3731 | AV21: =IF(N21="","",2518.0489-204.66184*I21+0.019354281*N21-2.3328708*V21-0.0022533804*E21+1.5259709*AD21-3.5842757*AE21-65.580099*AC21-62.828483*IF(AND(B21>=DATE(2020,3,20),B21<=DATE(2020,6,26)),1,0)+200.94286*AF21+0.00080379976*AR21) -> 7671.0146 | AW21: =IF(N21="","",2361.7153+89.223162*I21+0.018847054*N21-5.0210815*V21-0.0006437347*E21+1.4213619*AD21-3.2156123*AE21+167.41121*AC21-224.35191*IF(AND(B21>=DATE(2020,3,20),B21<=DATE(2020,6,26)),1,0)+194.56435*AF21-19.897843*AS21) -> 7765.7012 | AX21: =IF(N21="","",-654.03928+2464.5589*I21+0.035956453*N21-8.0754527*V21-0.00069441316*E21+0.69511606*AD21-1.1669613*AE21-90.724569*AC21-211.24919*IF(AND(B21>=DATE(2020,3,20),B21<=DATE(2020,6,26)),1,0)+147.22132*AF21-0.010108087*AQ21) -> 7628.8656
A22: 21 | B22: 33417 | C22: 7543 | E22: 423000 | G22: 20.208 | H22: 18.198 | I22: 1.114 | J22: 6035.178 | L22: 865 | M22: 12.487 | N22: 179538 | O22: 3907.1 | P22: 824860 | V22: 83.2 | AC22: 0 | AD22: 0.8 | AE22: 57.1 | AF22: 14.5712 | AG22: =6753.47943187+0.36116788*I22+0.01252571*N22-22.85359542*V22+0.00407811*AA22-0.00067349*E22 -> 6816.4173 | AH22: =A22*'Simple Linear Regression'!$B$18+'Simple Linear Regression'!$B$17 -> 7903.2501 | AI22: =7491.3971+0.0137554*N22-0.00058829*E22-34.3283*V22+0.30565*L22+54.6031*M22 -> 7802.269 | AJ22: =7491.3971-0.00058829*E22+0.30565*L22+54.6031*M22+0.0137554*N22-34.3283*V22 -> 7802.269 | AL22: =2192.59+2373.87*I22+0.0316653*N22-15.7623*V22+0.00202406*AA22-0.000740146*E22-0.00963493*(I22*N22) -> 6970.6633 | AM22: =5205.907083+122.0638992*I22+13.609808*(N22/1000)-1.245906883*AD22+0.7746840854*AE22-134.2474226*AC22-1547.125689*IF(AND(B22>=DATE(2020,3,20),B22<=DATE(2020,6,26)),1,0) -> 7828.6017 | AN22: =7707.2178-144.397321*AC22+139.5614087*AF22-0.0008594506251*E22-265.7105668*I22-0.02506176117*J22+0.004708026652*N22 -> 9775.2633 | AO22: =IF(N22="","",2190.39 + 2739.06*I22 + 0.034693*N22 - 16.722*V22 - 0.000802*E22 - 1.3691*AD22 + 1.8691*AE22 - 121.7*AC22 + 209.88*IF(AND(B22>=DATE(2020,3,20),B22<=DATE(2020,6,26)),1,0) - 0.011049*(I22*N22)) -> 7635.6697 | AP22: =IF(B22<DATE(2008,1,1),"",3929.06 + 1212.53*I22 - 0.0003097*N22 + 59.426*V22 - 0.0006734*E22 - 1.036*AD22 + 1.2076*AE22 + 94.923*AF22 - 131.43*AC22 - 759.61*IF(AND(B22>=DATE(2020,3,20),B22<=DATE(2020,6,26)),1,0) - 17.324*(I22*V22)) | AQ22: =IF(N22="","",I22*N22) -> 200005.33 | AR22: =I22*E22 -> 471222 | AS22: =AC22*AF22 -> 0 | AT22: =IF(N22="","",2413.3773+89.103503*I22+0.018847679*N22-5.0917058*V22-0.00064564578*E22+1.4315076*AD22-3.1976817*AE22-66.972905*AC22-217.08397*IF(AND(B22>=DATE(2020,3,20),B22<=DATE(2020,6,26)),1,0)+190.76803*AF22) -> 7798.0518 | AU22: =IF(N22="","",-480.76297+2186.3009*I22+0.033368804*N22-5.3903106*V22-0.00073731439*E22+0.93396876*AD22-1.6242981*AE22-61.304389*AC22-95.472727*IF(AND(B22>=DATE(2020,3,20),B22<=DATE(2020,6,26)),1,0)+156.04851*AF22-0.0087322858*AQ22) -> 7620.6968 | AV22: =IF(N22="","",2518.0489-204.66184*I22+0.019354281*N22-2.3328708*V22-0.0022533804*E22+1.5259709*AD22-3.5842757*AE22-65.580099*AC22-62.828483*IF(AND(B22>=DATE(2020,3,20),B22<=DATE(2020,6,26)),1,0)+200.94286*AF22+0.00080379976*AR22) -> 7720.9151 | AW22: =IF(N22="","",2361.7153+89.223162*I22+0.018847054*N22-5.0210815*V22-0.0006437347*E22+1.4213619*AD22-3.2156123*AE22+167.41121*AC22-224.35191*IF(AND(B22>=DATE(2020,3,20),B22<=DATE(2020,6,26)),1,0)+194.56435*AF22-19.897843*AS22) -> 7807.3802 | AX22: =IF(N22="","",-654.03928+2464.5589*I22+0.035956453*N22-8.0754527*V22-0.00069441316*E22+0.69511606*AD22-1.1669613*AE22-90.724569*AC22-211.24919*IF(AND(B22>=DATE(2020,3,20),B22<=DATE(2020,6,26)),1,0)+147.22132*AF22-0.010108087*AQ22) -> 7638.8572
A23: 22 | B23: 33424 | C23: 7961 | E23: 418000 | G23: 20.798 | H23: 18.552 | I23: 1.104 | J23: 6035.178 | L23: 865 | M23: 12.487 | N23: 179538 | O23: 3907.1 | P23: 824860 | V23: 84.6 | AC23: 1 | AD23: 0 | AE23: 88.7 | AF23: 14.5202 | AG23: =6753.47943187+0.36116788*I23+0.01252571*N23-22.85359542*V23+0.00407811*AA23-0.00067349*E23 -> 6787.7861 | AH23: =A23*'Simple Linear Regression'!$B$18+'Simple Linear Regression'!$B$17 -> 7904.1032 | AI23: =7491.3971+0.0137554*N23-0.00058829*E23-34.3283*V23+0.30565*L23+54.6031*M23 -> 7757.1509 | AJ23: =7491.3971-0.00058829*E23+0.30565*L23+54.6031*M23+0.0137554*N23-34.3283*V23 -> 7757.1509 | AL23: =2192.59+2373.87*I23+0.0316653*N23-15.7623*V23+0.00202406*AA23-0.000740146*E23-0.00963493*(I23*N23) -> 6945.8565 | AM23: =5205.907083+122.0638992*I23+13.609808*(N23/1000)-1.245906883*AD23+0.7746840854*AE23-134.2474226*AC23-1547.125689*IF(AND(B23>=DATE(2020,3,20),B23<=DATE(2020,6,26)),1,0) -> 7718.6104 | AN23: =7707.2178-144.397321*AC23+139.5614087*AF23-0.0008594506251*E23-265.7105668*I23-0.02506176117*J23+0.004708026652*N23 -> 9630.7027 | AO23: =IF(N23="","",2190.39 + 2739.06*I23 + 0.034693*N23 - 16.722*V23 - 0.000802*E23 - 1.3691*AD23 + 1.8691*AE23 - 121.7*AC23 + 209.88*IF(AND(B23>=DATE(2020,3,20),B23<=DATE(2020,6,26)),1,0) - 0.011049*(I23*N23)) -> 7547.1743 | AP23: =IF(B23<DATE(2008,1,1),"",3929.06 + 1212.53*I23 - 0.0003097*N23 + 59.426*V23 - 0.0006734*E23 - 1.036*AD23 + 1.2076*AE23 + 94.923*AF23 - 131.43*AC23 - 759.61*IF(AND(B23>=DATE(2020,3,20),B23<=DATE(2020,6,26)),1,0) - 17.324*(I23*V23)) | AQ23: =IF(N23="","",I23*N23) -> 198209.95 | AR23: =I23*E23 -> 461472 | AS23: =AC23*AF23 -> 14.5202 | AT23: =IF(N23="","",2413.3773+89.103503*I23+0.018847679*N23-5.0917058*V23-0.00064564578*E23+1.4315076*AD23-3.1976817*AE23-66.972905*AC23-217.08397*IF(AND(B23>=DATE(2020,3,20),B23<=DATE(2020,6,26)),1,0)+190.76803*AF23) -> 7614.3666 | AU23: =IF(N23="","",-480.76297+2186.3009*I23+0.033368804*N23-5.3903106*V23-0.00073731439*E23+0.93396876*AD23-1.6242981*AE23-61.304389*AC23-95.472727*IF(AND(B23>=DATE(2020,3,20),B23<=DATE(2020,6,26)),1,0)+156.04851*AF23-0.0087322858*AQ23) -> 7489.3139 | AV23: =IF(N23="","",2518.0489-204.66184*I23+0.019354281*N23-2.3328708*V23-0.0022533804*E23+1.5259709*AD23-3.5842757*AE23-65.580099*AC23-62.828483*IF(AND(B23>=DATE(2020,3,20),B23<=DATE(2020,6,26)),1,0)+200.94286*AF23+0.00080379976*AR23) -> 7532.8135 | AW23: =IF(N23="","",2361.7153+89.223162*I23+0.018847054*N23-5.0210815*V23-0.0006437347*E23+1.4213619*AD23-3.2156123*AE23+167.41121*AC23-224.35191*IF(AND(B23>=DATE(2020,3,20),B23<=DATE(2020,6,26)),1,0)+194.56435*AF23-19.897843*AS23) -> 7568.4945 | AX23: =IF(N23="","",-654.03928+2464.5589*I23+0.035956453*N23-8.0754527*V23-0.00069441316*E23+0.69511606*AD23-1.1669613*AE23-90.724569*AC23-211.24919*IF(AND(B23>=DATE(2020,3,20),B23<=DATE(2020,6,26)),1,0)+147.22132*AF23-0.010108087*AQ23) -> 7488.8609
A24: 23 | B24: 33431 | C24: 7327 | E24: 422000 | G24: 21.426 | H24: 19.244 | I24: 1.098 | J24: 6035.178 | L24: 819 | M24: 12.487 | N24: 179538 | O24: 3933.2 | P24: 824860 | V24: 84.6 | AC24: 0 | AD24: 0 | AE24: 83.2 | AF24: 14.4278 | AG24: =6753.47943187+0.36116788*I24+0.01252571*N24-22.85359542*V24+0.00407811*AA24-0.00067349*E24 -> 6785.09 | AH24: =A24*'Simple Linear Regression'!$B$18+'Simple Linear Regression'!$B$17 -> 7904.9562 | AI24: =7491.3971+0.0137554*N24-0.00058829*E24-34.3283*V24+0.30565*L24+54.6031*M24 -> 7740.7378 | AJ24: =7491.3971-0.00058829*E24+0.30565*L24+54.6031*M24+0.0137554*N24-34.3283*V24 -> 7740.7378 | AL24: =2192.59+2373.87*I24+0.0316653*N24-15.7623*V24+0.00202406*AA24-0.000740146*E24-0.00963493*(I24*N24) -> 6939.0317 | AM24: =5205.907083+122.0638992*I24+13.609808*(N24/1000)-1.245906883*AD24+0.7746840854*AE24-134.2474226*AC24-1547.125689*IF(AND(B24>=DATE(2020,3,20),B24<=DATE(2020,6,26)),1,0) -> 7847.8647 | AN24: =7707.2178-144.397321*AC24+139.5614087*AF24-0.0008594506251*E24-265.7105668*I24-0.02506176117*J24+0.004708026652*N24 -> 9760.361 | AO24: =IF(N24="","",2190.39 + 2739.06*I24 + 0.034693*N24 - 16.722*V24 - 0.000802*E24 - 1.3691*AD24 + 1.8691*AE24 - 121.7*AC24 + 209.88*IF(AND(B24>=DATE(2020,3,20),B24<=DATE(2020,6,26)),1,0) - 0.011049*(I24*N24)) -> 7650.8542 | AP24: =IF(B24<DATE(2008,1,1),"",3929.06 + 1212.53*I24 - 0.0003097*N24 + 59.426*V24 - 0.0006734*E24 - 1.036*AD24 + 1.2076*AE24 + 94.923*AF24 - 131.43*AC24 - 759.61*IF(AND(B24>=DATE(2020,3,20),B24<=DATE(2020,6,26)),1,0) - 17.324*(I24*V24)) | AQ24: =IF(N24="","",I24*N24) -> 197132.72 | AR24: =I24*E24 -> 463356 | AS24: =AC24*AF24 -> 0 | AT24: =IF(N24="","",2413.3773+89.103503*I24+0.018847679*N24-5.0917058*V24-0.00064564578*E24+1.4315076*AD24-3.1976817*AE24-66.972905*AC24-217.08397*IF(AND(B24>=DATE(2020,3,20),B24<=DATE(2020,6,26)),1,0)+190.76803*AF24) -> 7678.1826 | AU24: =IF(N24="","",-480.76297+2186.3009*I24+0.033368804*N24-5.3903106*V24-0.00073731439*E24+0.93396876*AD24-1.6242981*AE24-61.304389*AC24-95.472727*IF(AND(B24>=DATE(2020,3,20),B24<=DATE(2020,6,26)),1,0)+156.04851*AF24-0.0087322858*AQ24) -> 7538.4726 | AV24: =IF(N24="","",2518.0489-204.66184*I24+0.019354281*N24-2.3328708*V24-0.0022533804*E24+1.5259709*AD24-3.5842757*AE24-65.580099*AC24-62.828483*IF(AND(B24>=DATE(2020,3,20),B24<=DATE(2020,6,26)),1,0)+200.94286*AF24+0.00080379976*AR24) -> 7593.2688 | AW24: =IF(N24="","",2361.7153+89.223162*I24+0.018847054*N24-5.0210815*V24-0.0006437347*E24+1.4213619*AD24-3.2156123*AE24+167.41121*AC24-224.35191*IF(AND(B24>=DATE(2020,3,20),B24<=DATE(2020,6,26)),1,0)+194.56435*AF24-19.897843*AS24) -> 7686.6018 | AX24: =IF(N24="","",-654.03928+2464.5589*I24+0.035956453*N24-8.0754527*V24-0.00069441316*E24+0.69511606*AD24-1.1669613*AE24-90.724569*AC24-211.24919*IF(AND(B24>=DATE(2020,3,20),B24<=DATE(2020,6,26)),1,0)+147.22132*AF24-0.010108087*AQ24) -> 7565.7243
A25: 24 | B25: 33438 | C25: 7380 | E25: 420000 | G25: 21.906 | H25: 20.024 | I25: 1.094 | J25: 6035.178 | L25: 819 | M25: 12.719 | N25: 191929 | O25: 3933.2 | P25: 824860 | V25: 84.6 | AC25: 0 | AD25: 0 | AE25: 83.8 | AF25: 14.297 | AG25: =6753.47943187+0.36116788*I25+0.01252571*N25-22.85359542*V25+0.00407811*AA25-0.00067349*E25 -> 6941.6416 | AH25: =A25*'Simple Linear Regression'!$B$18+'Simple Linear Regression'!$B$17 -> 7905.8092 | AI25: =7491.3971+0.0137554*N25-0.00058829*E25-34.3283*V25+0.30565*L25+54.6031*M25 -> 7925.0255 | AJ25: =7491.3971-0.00058829*E25+0.30565*L25+54.6031*M25+0.0137554*N25-34.3283*V25 -> 7925.0255 | AL25: =2192.59+2373.87*I25+0.0316653*N25-15.7623*V25+0.00202406*AA25-0.000740146*E25-0.00963493*(I25*N25) -> 7199.6919 | AM25: =5205.907083+122.0638992*I25+13.609808*(N25/1000)-1.245906883*AD25+0.7746840854*AE25-134.2474226*AC25-1547.125689*IF(AND(B25>=DATE(2020,3,20),B25<=DATE(2020,6,26)),1,0) -> 8016.4804 | AN25: =7707.2178-144.397321*AC25+139.5614087*AF25-0.0008594506251*E25-265.7105668*I25-0.02506176117*J25+0.004708026652*N25 -> 9803.2253 | AO25: =IF(N25="","",2190.39 + 2739.06*I25 + 0.034693*N25 - 16.722*V25 - 0.000802*E25 - 1.3691*AD25 + 1.8691*AE25 - 121.7*AC25 + 209.88*IF(AND(B25>=DATE(2020,3,20),B25<=DATE(2020,6,26)),1,0) - 0.011049*(I25*N25)) -> 7930.6617 | AP25: =IF(B25<DATE(2008,1,1),"",3929.06 + 1212.53*I25 - 0.0003097*N25 + 59.426*V25 - 0.0006734*E25 - 1.036*AD25 + 1.2076*AE25 + 94.923*AF25 - 131.43*AC25 - 759.61*IF(AND(B25>=DATE(2020,3,20),B25<=DATE(2020,6,26)),1,0) - 17.324*(I25*V25)) | AQ25: =IF(N25="","",I25*N25) -> 209970.33 | AR25: =I25*E25 -> 459480 | AS25: =AC25*AF25 -> 0 | AT25: =IF(N25="","",2413.3773+89.103503*I25+0.018847679*N25-5.0917058*V25-0.00064564578*E25+1.4315076*AD25-3.1976817*AE25-66.972905*AC25-217.08397*IF(AND(B25>=DATE(2020,3,20),B25<=DATE(2020,6,26)),1,0)+190.76803*AF25) -> 7885.788 | AU25: =IF(N25="","",-480.76297+2186.3009*I25+0.033368804*N25-5.3903106*V25-0.00073731439*E25+0.93396876*AD25-1.6242981*AE25-61.304389*AC25-95.472727*IF(AND(B25>=DATE(2020,3,20),B25<=DATE(2020,6,26)),1,0)+156.04851*AF25-0.0087322858*AQ25) -> 7811.1875 | AV25: =IF(N25="","",2518.0489-204.66184*I25+0.019354281*N25-2.3328708*V25-0.0022533804*E25+1.5259709*AD25-3.5842757*AE25-65.580099*AC25-62.828483*IF(AND(B25>=DATE(2020,3,20),B25<=DATE(2020,6,26)),1,0)+200.94286*AF25+0.00080379976*AR25) -> 7806.8637 | AW25: =IF(N25="","",2361.7153+89.223162*I25+0.018847054*N25-5.0210815*V25-0.0006437347*E25+1.4213619*AD25-3.2156123*AE25+167.41121*AC25-224.35191*IF(AND(B25>=DATE(2020,3,20),B25<=DATE(2020,6,26)),1,0)+194.56435*AF25-19.897843*AS25) -> 7893.6878 | AX25: =IF(N25="","",-654.03928+2464.5589*I25+0.035956453*N25-8.0754527*V25-0.00069441316*E25+0.69511606*AD25-1.1669613*AE25-90.724569*AC25-211.24919*IF(AND(B25>=DATE(2020,3,20),B25<=DATE(2020,6,26)),1,0)+147.22132*AF25-0.010108087*AQ25) -> 7853.0709
A26: 25 | B26: 33445 | C26: 7501 | E26: 408000 | G26: 21.398 | H26: 19.664 | I26: 1.091 | J26: 6035.178 | L26: 819 | M26: 12.719 | N26: 191929 | O26: 3933.2 | P26: 824860 | V26: 84.6 | AC26: 0 | AD26: 0 | AE26: 90.6 | AF26: 14.1318 | AG26: =6753.47943187+0.36116788*I26+0.01252571*N26-22.85359542*V26+0.00407811*AA26-0.00067349*E26 -> 6949.7224 | AH26: =A26*'Simple Linear Regression'!$B$18+'Simple Linear Regression'!$B$17 -> 7906.6623 | AI26: =7491.3971+0.0137554*N26-0.00058829*E26-34.3283*V26+0.30565*L26+54.6031*M26 -> 7932.0849 | AJ26: =7491.3971-0.00058829*E26+0.30565*L26+54.6031*M26+0.0137554*N26-34.3283*V26 -> 7932.0849 | AL26: =2192.59+2373.87*I26+0.0316653*N26-15.7623*V26+0.00202406*AA26-0.000740146*E26-0.00963493*(I26*N26) -> 7206.9997 | AM26: =5205.907083+122.0638992*I26+13.609808*(N26/1000)-1.245906883*AD26+0.7746840854*AE26-134.2474226*AC26-1547.125689*IF(AND(B26>=DATE(2020,3,20),B26<=DATE(2020,6,26)),1,0) -> 8021.382 | AN26: =7707.2178-144.397321*AC26+139.5614087*AF26-0.0008594506251*E26-265.7105668*I26-0.02506176117*J26+0.004708026652*N26 -> 9791.2803 | AO26: =IF(N26="","",2190.39 + 2739.06*I26 + 0.034693*N26 - 16.722*V26 - 0.000802*E26 - 1.3691*AD26 + 1.8691*AE26 - 121.7*AC26 + 209.88*IF(AND(B26>=DATE(2020,3,20),B26<=DATE(2020,6,26)),1,0) - 0.011049*(I26*N26)) -> 7951.1403 | AP26: =IF(B26<DATE(2008,1,1),"",3929.06 + 1212.53*I26 - 0.0003097*N26 + 59.426*V26 - 0.0006734*E26 - 1.036*AD26 + 1.2076*AE26 + 94.923*AF26 - 131.43*AC26 - 759.61*IF(AND(B26>=DATE(2020,3,20),B26<=DATE(2020,6,26)),1,0) - 17.324*(I26*V26)) | AQ26: =IF(N26="","",I26*N26) -> 209394.54 | AR26: =I26*E26 -> 445128 | AS26: =AC26*AF26 -> 0 | AT26: =IF(N26="","",2413.3773+89.103503*I26+0.018847679*N26-5.0917058*V26-0.00064564578*E26+1.4315076*AD26-3.1976817*AE26-66.972905*AC26-217.08397*IF(AND(B26>=DATE(2020,3,20),B26<=DATE(2020,6,26)),1,0)+190.76803*AF26) -> 7840.0093 | AU26: =IF(N26="","",-480.76297+2186.3009*I26+0.033368804*N26-5.3903106*V26-0.00073731439*E26+0.93396876*AD26-1.6242981*AE26-61.304389*AC26-95.472727*IF(AND(B26>=DATE(2020,3,20),B26<=DATE(2020,6,26)),1,0)+156.04851*AF26-0.0087322858*AQ26) -> 7781.6799 | AV26: =IF(N26="","",2518.0489-204.66184*I26+0.019354281*N26-2.3328708*V26-0.0022533804*E26+1.5259709*AD26-3.5842757*AE26-65.580099*AC26-62.828483*IF(AND(B26>=DATE(2020,3,20),B26<=DATE(2020,6,26)),1,0)+200.94286*AF26+0.00080379976*AR26) -> 7765.4133 | AW26: =IF(N26="","",2361.7153+89.223162*I26+0.018847054*N26-5.0210815*V26-0.0006437347*E26+1.4213619*AD26-3.2156123*AE26+167.41121*AC26-224.35191*IF(AND(B26>=DATE(2020,3,20),B26<=DATE(2020,6,26)),1,0)+194.56435*AF26-19.897843*AS26) -> 7847.1368 | AX26: =IF(N26="","",-654.03928+2464.5589*I26+0.035956453*N26-8.0754527*V26-0.00069441316*E26+0.69511606*AD26-1.1669613*AE26-90.724569*AC26-211.24919*IF(AND(B26>=DATE(2020,3,20),B26<=DATE(2020,6,26)),1,0)+147.22132*AF26-0.010108087*AQ26) -> 7827.574
A27: 26 | B27: 33452 | C27: 7605 | E27: 423000 | G27: 21.462 | H27: 19.568 | I27: 1.091 | J27: 6035.178 | L27: 819 | M27: 12.719 | N27: 191929 | O27: 3933.2 | P27: 824860 | V27: 84.6 | AC27: 0 | AD27: 0 | AE27: 80.7 | AF27: 13.9369 | AG27: =6753.47943187+0.36116788*I27+0.01252571*N27-22.85359542*V27+0.00407811*AA27-0.00067349*E27 -> 6939.62 | AH27: =A27*'Simple Linear Regression'!$B$18+'Simple Linear Regression'!$B$17 -> 7907.5153 | AI27: =7491.3971+0.0137554*N27-0.00058829*E27-34.3283*V27+0.30565*L27+54.6031*M27 -> 7923.2606 | AJ27: =7491.3971-0.00058829*E27+0.30565*L27+54.6031*M27+0.0137554*N27-34.3283*V27 -> 7923.2606 | AL27: =2192.59+2373.87*I27+0.0316653*N27-15.7623*V27+0.00202406*AA27-0.000740146*E27-0.00963493*(I27*N27) -> 7195.8975 | AM27: =5205.907083+122.0638992*I27+13.609808*(N27/1000)-1.245906883*AD27+0.7746840854*AE27-134.2474226*AC27-1547.125689*IF(AND(B27>=DATE(2020,3,20),B27<=DATE(2020,6,26)),1,0) -> 8013.7126 | AN27: =7707.2178-144.397321*AC27+139.5614087*AF27-0.0008594506251*E27-265.7105668*I27-0.02506176117*J27+0.004708026652*N27 -> 9751.188 | AO27: =IF(N27="","",2190.39 + 2739.06*I27 + 0.034693*N27 - 16.722*V27 - 0.000802*E27 - 1.3691*AD27 + 1.8691*AE27 - 121.7*AC27 + 209.88*IF(AND(B27>=DATE(2020,3,20),B27<=DATE(2020,6,26)),1,0) - 0.011049*(I27*N27)) -> 7920.6062 | AP27: =IF(B27<DATE(2008,1,1),"",3929.06 + 1212.53*I27 - 0.0003097*N27 + 59.426*V27 - 0.0006734*E27 - 1.036*AD27 + 1.2076*AE27 + 94.923*AF27 - 131.43*AC27 - 759.61*IF(AND(B27>=DATE(2020,3,20),B27<=DATE(2020,6,26)),1,0) - 17.324*(I27*V27)) | AQ27: =IF(N27="","",I27*N27) -> 209394.54 | AR27: =I27*E27 -> 461493 | AS27: =AC27*AF27 -> 0 | AT27: =IF(N27="","",2413.3773+89.103503*I27+0.018847679*N27-5.0917058*V27-0.00064564578*E27+1.4315076*AD27-3.1976817*AE27-66.972905*AC27-217.08397*IF(AND(B27>=DATE(2020,3,20),B27<=DATE(2020,6,26)),1,0)+190.76803*AF27) -> 7824.801 | AU27: =IF(N27="","",-480.76297+2186.3009*I27+0.033368804*N27-5.3903106*V27-0.00073731439*E27+0.93396876*AD27-1.6242981*AE27-61.304389*AC27-95.472727*IF(AND(B27>=DATE(2020,3,20),B27<=DATE(2020,6,26)),1,0)+156.04851*AF27-0.0087322858*AQ27) -> 7756.2869 | AV27: =IF(N27="","",2518.0489-204.66184*I27+0.019354281*N27-2.3328708*V27-0.0022533804*E27+1.5259709*AD27-3.5842757*AE27-65.580099*AC27-62.828483*IF(AND(B27>=DATE(2020,3,20),B27<=DATE(2020,6,26)),1,0)+200.94286*AF27+0.00080379976*AR27) -> 7741.0873 | AW27: =IF(N27="","",2361.7153+89.223162*I27+0.018847054*N27-5.0210815*V27-0.0006437347*E27+1.4213619*AD27-3.2156123*AE27+167.41121*AC27-224.35191*IF(AND(B27>=DATE(2020,3,20),B27<=DATE(2020,6,26)),1,0)+194.56435*AF27-19.897843*AS27) -> 7831.3947 | AX27: =IF(N27="","",-654.03928+2464.5589*I27+0.035956453*N27-8.0754527*V27-0.00069441316*E27+0.69511606*AD27-1.1669613*AE27-90.724569*AC27-211.24919*IF(AND(B27>=DATE(2020,3,20),B27<=DATE(2020,6,26)),1,0)+147.22132*AF27-0.010108087*AQ27) -> 7800.0173
A28: 27 | B28: 33459 | C28: 7584 | E28: 438000 | G28: 21.502 | H28: 19.516 | I28: 1.099 | J28: 6126.862 | L28: 867 | M28: 12.719 | N28: 191929 | O28: 3940.5 | P28: 824860 | V28: 87.5 | AC28: 0 | AD28: 0 | AE28: 74.8 | AF28: 13.7169 | AG28: =6753.47943187+0.36116788*I28+0.01252571*N28-22.85359542*V28+0.00407811*AA28-0.00067349*E28 -> 6863.2451 | AH28: =A28*'Simple Linear Regression'!$B$18+'Simple Linear Regression'!$B$17 -> 7908.3683 | AI28: =7491.3971+0.0137554*N28-0.00058829*E28-34.3283*V28+0.30565*L28+54.6031*M28 -> 7829.5554 | AJ28: =7491.3971-0.00058829*E28+0.30565*L28+54.6031*M28+0.0137554*N28-34.3283*V28 -> 7829.5554 | AL28: =2192.59+2373.87*I28+0.0316653*N28-15.7623*V28+0.00202406*AA28-0.000740146*E28-0.00963493*(I28*N28) -> 7143.2818 | AM28: =5205.907083+122.0638992*I28+13.609808*(N28/1000)-1.245906883*AD28+0.7746840854*AE28-134.2474226*AC28-1547.125689*IF(AND(B28>=DATE(2020,3,20),B28<=DATE(2020,6,26)),1,0) -> 8010.1185 | AN28: =7707.2178-144.397321*AC28+139.5614087*AF28-0.0008594506251*E28-265.7105668*I28-0.02506176117*J28+0.004708026652*N28 -> 9703.1693 | AO28: =IF(N28="","",2190.39 + 2739.06*I28 + 0.034693*N28 - 16.722*V28 - 0.000802*E28 - 1.3691*AD28 + 1.8691*AE28 - 121.7*AC28 + 209.88*IF(AND(B28>=DATE(2020,3,20),B28<=DATE(2020,6,26)),1,0) - 0.011049*(I28*N28)) -> 7854.0022 | AP28: =IF(B28<DATE(2008,1,1),"",3929.06 + 1212.53*I28 - 0.0003097*N28 + 59.426*V28 - 0.0006734*E28 - 1.036*AD28 + 1.2076*AE28 + 94.923*AF28 - 131.43*AC28 - 759.61*IF(AND(B28>=DATE(2020,3,20),B28<=DATE(2020,6,26)),1,0) - 17.324*(I28*V28)) | AQ28: =IF(N28="","",I28*N28) -> 210929.97 | AR28: =I28*E28 -> 481362 | AS28: =AC28*AF28 -> 0 | AT28: =IF(N28="","",2413.3773+89.103503*I28+0.018847679*N28-5.0917058*V28-0.00064564578*E28+1.4315076*AD28-3.1976817*AE28-66.972905*AC28-217.08397*IF(AND(B28>=DATE(2020,3,20),B28<=DATE(2020,6,26)),1,0)+190.76803*AF28) -> 7777.9605 | AU28: =IF(N28="","",-480.76297+2186.3009*I28+0.033368804*N28-5.3903106*V28-0.00073731439*E28+0.93396876*AD28-1.6242981*AE28-61.304389*AC28-95.472727*IF(AND(B28>=DATE(2020,3,20),B28<=DATE(2020,6,26)),1,0)+156.04851*AF28-0.0087322858*AQ28) -> 7708.9305 | AV28: =IF(N28="","",2518.0489-204.66184*I28+0.019354281*N28-2.3328708*V28-0.0022533804*E28+1.5259709*AD28-3.5842757*AE28-65.580099*AC28-62.828483*IF(AND(B28>=DATE(2020,3,20),B28<=DATE(2020,6,26)),1,0)+200.94286*AF28+0.00080379976*AR28) -> 7691.7945 | AW28: =IF(N28="","",2361.7153+89.223162*I28+0.018847054*N28-5.0210815*V28-0.0006437347*E28+1.4213619*AD28-3.2156123*AE28+167.41121*AC28-224.35191*IF(AND(B28>=DATE(2020,3,20),B28<=DATE(2020,6,26)),1,0)+194.56435*AF28-19.897843*AS28) -> 7784.0593 | AX28: =IF(N28="","",-654.03928+2464.5589*I28+0.035956453*N28-8.0754527*V28-0.00069441316*E28+0.69511606*AD28-1.1669613*AE28-90.724569*AC28-211.24919*IF(AND(B28>=DATE(2020,3,20),B28<=DATE(2020,6,26)),1,0)+147.22132*AF28-0.010108087*AQ28) -> 7744.8749
A29: 28 | B29: 33466 | C29: 7401 | E29: 437000 | G29: 21.442 | H29: 19.392 | I29: 1.112 | J29: 6126.862 | L29: 867 | M29: 12.972 | N29: 193467 | O29: 3940.5 | P29: 824860 | V29: 87.5 | AC29: 0 | AD29: 0 | AE29: 75.2 | AF29: 13.4765 | AG29: =6753.47943187+0.36116788*I29+0.01252571*N29-22.85359542*V29+0.00407811*AA29-0.00067349*E29 -> 6883.1879 | AH29: =A29*'Simple Linear Regression'!$B$18+'Simple Linear Regression'!$B$17 -> 7909.2214 | AI29: =7491.3971+0.0137554*N29-0.00058829*E29-34.3283*V29+0.30565*L29+54.6031*M29 -> 7865.1141 | AJ29: =7491.3971-0.00058829*E29+0.30565*L29+54.6031*M29+0.0137554*N29-34.3283*V29 -> 7865.1141 | AL29: =2192.59+2373.87*I29+0.0316653*N29-15.7623*V29+0.00202406*AA29-0.000740146*E29-0.00963493*(I29*N29) -> 7183.0654 | AM29: =5205.907083+122.0638992*I29+13.609808*(N29/1000)-1.245906883*AD29+0.7746840854*AE29-134.2474226*AC29-1547.125689*IF(AND(B29>=DATE(2020,3,20),B29<=DATE(2020,6,26)),1,0) -> 8032.9471 | AN29: =7707.2178-144.397321*AC29+139.5614087*AF29-0.0008594506251*E29-265.7105668*I29-0.02506176117*J29+0.004708026652*N29 -> 9674.2649 | AO29: =IF(N29="","",2190.39 + 2739.06*I29 + 0.034693*N29 - 16.722*V29 - 0.000802*E29 - 1.3691*AD29 + 1.8691*AE29 - 121.7*AC29 + 209.88*IF(AND(B29>=DATE(2020,3,20),B29<=DATE(2020,6,26)),1,0) - 0.011049*(I29*N29)) -> 7898.0527 | AP29: =IF(B29<DATE(2008,1,1),"",3929.06 + 1212.53*I29 - 0.0003097*N29 + 59.426*V29 - 0.0006734*E29 - 1.036*AD29 + 1.2076*AE29 + 94.923*AF29 - 131.43*AC29 - 759.61*IF(AND(B29>=DATE(2020,3,20),B29<=DATE(2020,6,26)),1,0) - 17.324*(I29*V29)) | AQ29: =IF(N29="","",I29*N29) -> 215135.3 | AR29: =I29*E29 -> 485944 | AS29: =AC29*AF29 -> 0 | AT29: =IF(N29="","",2413.3773+89.103503*I29+0.018847679*N29-5.0917058*V29-0.00064564578*E29+1.4315076*AD29-3.1976817*AE29-66.972905*AC29-217.08397*IF(AND(B29>=DATE(2020,3,20),B29<=DATE(2020,6,26)),1,0)+190.76803*AF29) -> 7761.6125 | AU29: =IF(N29="","",-480.76297+2186.3009*I29+0.033368804*N29-5.3903106*V29-0.00073731439*E29+0.93396876*AD29-1.6242981*AE29-61.304389*AC29-95.472727*IF(AND(B29>=DATE(2020,3,20),B29<=DATE(2020,6,26)),1,0)+156.04851*AF29-0.0087322858*AQ29) -> 7714.525 | AV29: =IF(N29="","",2518.0489-204.66184*I29+0.019354281*N29-2.3328708*V29-0.0022533804*E29+1.5259709*AD29-3.5842757*AE29-65.580099*AC29-62.828483*IF(AND(B29>=DATE(2020,3,20),B29<=DATE(2020,6,26)),1,0)+200.94286*AF29+0.00080379976*AR29) -> 7675.0968 | AW29: =IF(N29="","",2361.7153+89.223162*I29+0.018847054*N29-5.0210815*V29-0.0006437347*E29+1.4213619*AD29-3.2156123*AE29+167.41121*AC29-224.35191*IF(AND(B29>=DATE(2020,3,20),B29<=DATE(2020,6,26)),1,0)+194.56435*AF29-19.897843*AS29) -> 7766.7902 | AX29: =IF(N29="","",-654.03928+2464.5589*I29+0.035956453*N29-8.0754527*V29-0.00069441316*E29+0.69511606*AD29-1.1669613*AE29-90.724569*AC29-211.24919*IF(AND(B29>=DATE(2020,3,20),B29<=DATE(2020,6,26)),1,0)+147.22132*AF29-0.010108087*AQ29) -> 7754.5429
A30: 29 | B30: 33473 | C30: 7505 | E30: 433000 | G30: 21.99 | H30: 20.092 | I30: 1.124 | J30: 6126.862 | L30: 867 | M30: 12.972 | N30: 193467 | O30: 3940.5 | P30: 824860 | V30: 87.5 | AC30: 0 | AD30: 0 | AE30: 73.4 | AF30: 13.22 | AG30: =6753.47943187+0.36116788*I30+0.01252571*N30-22.85359542*V30+0.00407811*AA30-0.00067349*E30 -> 6885.8862 | AH30: =A30*'Simple Linear Regression'!$B$18+'Simple Linear Regression'!$B$17 -> 7910.0744 | AI30: =7491.3971+0.0137554*N30-0.00058829*E30-34.3283*V30+0.30565*L30+54.6031*M30 -> 7867.4672 | AJ30: =7491.3971-0.00058829*E30+0.30565*L30+54.6031*M30+0.0137554*N30-34.3283*V30 -> 7867.4672 | AL30: =2192.59+2373.87*I30+0.0316653*N30-15.7623*V30+0.00202406*AA30-0.000740146*E30-0.00963493*(I30*N30) -> 7192.1439 | AM30: =5205.907083+122.0638992*I30+13.609808*(N30/1000)-1.245906883*AD30+0.7746840854*AE30-134.2474226*AC30-1547.125689*IF(AND(B30>=DATE(2020,3,20),B30<=DATE(2020,6,26)),1,0) -> 8033.0174 | AN30: =7707.2178-144.397321*AC30+139.5614087*AF30-0.0008594506251*E30-265.7105668*I30-0.02506176117*J30+0.004708026652*N30 -> 9638.7167 | AO30: =IF(N30="","",2190.39 + 2739.06*I30 + 0.034693*N30 - 16.722*V30 - 0.000802*E30 - 1.3691*AD30 + 1.8691*AE30 - 121.7*AC30 + 209.88*IF(AND(B30>=DATE(2020,3,20),B30<=DATE(2020,6,26)),1,0) - 0.011049*(I30*N30)) -> 7905.1136 | AP30: =IF(B30<DATE(2008,1,1),"",3929.06 + 1212.53*I30 - 0.0003097*N30 + 59.426*V30 - 0.0006734*E30 - 1.036*AD30 + 1.2076*AE30 + 94.923*AF30 - 131.43*AC30 - 759.61*IF(AND(B30>=DATE(2020,3,20),B30<=DATE(2020,6,26)),1,0) - 17.324*(I30*V30)) | AQ30: =IF(N30="","",I30*N30) -> 217456.91 | AR30: =I30*E30 -> 486692 | AS30: =AC30*AF30 -> 0 | AT30: =IF(N30="","",2413.3773+89.103503*I30+0.018847679*N30-5.0917058*V30-0.00064564578*E30+1.4315076*AD30-3.1976817*AE30-66.972905*AC30-217.08397*IF(AND(B30>=DATE(2020,3,20),B30<=DATE(2020,6,26)),1,0)+190.76803*AF30) -> 7722.0882 | AU30: =IF(N30="","",-480.76297+2186.3009*I30+0.033368804*N30-5.3903106*V30-0.00073731439*E30+0.93396876*AD30-1.6242981*AE30-61.304389*AC30-95.472727*IF(AND(B30>=DATE(2020,3,20),B30<=DATE(2020,6,26)),1,0)+156.04851*AF30-0.0087322858*AQ30) -> 7686.3343 | AV30: =IF(N30="","",2518.0489-204.66184*I30+0.019354281*N30-2.3328708*V30-0.0022533804*E30+1.5259709*AD30-3.5842757*AE30-65.580099*AC30-62.828483*IF(AND(B30>=DATE(2020,3,20),B30<=DATE(2020,6,26)),1,0)+200.94286*AF30+0.00080379976*AR30) -> 7637.1655 | AW30: =IF(N30="","",2361.7153+89.223162*I30+0.018847054*N30-5.0210815*V30-0.0006437347*E30+1.4213619*AD30-3.2156123*AE30+167.41121*AC30-224.35191*IF(AND(B30>=DATE(2020,3,20),B30<=DATE(2020,6,26)),1,0)+194.56435*AF30-19.897843*AS30) -> 7726.3181 | AX30: =IF(N30="","",-654.03928+2464.5589*I30+0.035956453*N30-8.0754527*V30-0.00069441316*E30+0.69511606*AD30-1.1669613*AE30-90.724569*AC30-211.24919*IF(AND(B30>=DATE(2020,3,20),B30<=DATE(2020,6,26)),1,0)+147.22132*AF30-0.010108087*AQ30) -> 7727.7666
A31: 30 | B31: 33480 | C31: 7427 | E31: 425000 | G31: 21.982 | H31: 20.174 | I31: 1.124 | J31: 6126.862 | L31: 867 | M31: 12.972 | N31: 193467 | O31: 3940.5 | P31: 824860 | V31: 87.5 | AC31: 0 | AD31: 0 | AE31: 82.8 | AF31: 12.9512 | AG31: =6753.47943187+0.36116788*I31+0.01252571*N31-22.85359542*V31+0.00407811*AA31-0.00067349*E31 -> 6891.2741 | AH31: =A31*'Simple Linear Regression'!$B$18+'Simple Linear Regression'!$B$17 -> 7910.9275 | AI31: =7491.3971+0.0137554*N31-0.00058829*E31-34.3283*V31+0.30565*L31+54.6031*M31 -> 7872.1735 | AJ31: =7491.3971-0.00058829*E31+0.30565*L31+54.6031*M31+0.0137554*N31-34.3283*V31 -> 7872.1735 | AL31: =2192.59+2373.87*I31+0.0316653*N31-15.7623*V31+0.00202406*AA31-0.000740146*E31-0.00963493*(I31*N31) -> 7198.0651 | AM31: =5205.907083+122.0638992*I31+13.609808*(N31/1000)-1.245906883*AD31+0.7746840854*AE31-134.2474226*AC31-1547.125689*IF(AND(B31>=DATE(2020,3,20),B31<=DATE(2020,6,26)),1,0) -> 8040.2995 | AN31: =7707.2178-144.397321*AC31+139.5614087*AF31-0.0008594506251*E31-265.7105668*I31-0.02506176117*J31+0.004708026652*N31 -> 9608.0782 | AO31: =IF(N31="","",2190.39 + 2739.06*I31 + 0.034693*N31 - 16.722*V31 - 0.000802*E31 - 1.3691*AD31 + 1.8691*AE31 - 121.7*AC31 + 209.88*IF(AND(B31>=DATE(2020,3,20),B31<=DATE(2020,6,26)),1,0) - 0.011049*(I31*N31)) -> 7929.0992 | AP31: =IF(B31<DATE(2008,1,1),"",3929.06 + 1212.53*I31 - 0.0003097*N31 + 59.426*V31 - 0.0006734*E31 - 1.036*AD31 + 1.2076*AE31 + 94.923*AF31 - 131.43*AC31 - 759.61*IF(AND(B31>=DATE(2020,3,20),B31<=DATE(2020,6,26)),1,0) - 17.324*(I31*V31)) | AQ31: =IF(N31="","",I31*N31) -> 217456.91 | AR31: =I31*E31 -> 477700 | AS31: =AC31*AF31 -> 0 | AT31: =IF(N31="","",2413.3773+89.103503*I31+0.018847679*N31-5.0917058*V31-0.00064564578*E31+1.4315076*AD31-3.1976817*AE31-66.972905*AC31-217.08397*IF(AND(B31>=DATE(2020,3,20),B31<=DATE(2020,6,26)),1,0)+190.76803*AF31) -> 7645.9167 | AU31: =IF(N31="","",-480.76297+2186.3009*I31+0.033368804*N31-5.3903106*V31-0.00073731439*E31+0.93396876*AD31-1.6242981*AE31-61.304389*AC31-95.472727*IF(AND(B31>=DATE(2020,3,20),B31<=DATE(2020,6,26)),1,0)+156.04851*AF31-0.0087322858*AQ31) -> 7635.0186 | AV31: =IF(N31="","",2518.0489-204.66184*I31+0.019354281*N31-2.3328708*V31-0.0022533804*E31+1.5259709*AD31-3.5842757*AE31-65.580099*AC31-62.828483*IF(AND(B31>=DATE(2020,3,20),B31<=DATE(2020,6,26)),1,0)+200.94286*AF31+0.00080379976*AR31) -> 7560.2591 | AW31: =IF(N31="","",2361.7153+89.223162*I31+0.018847054*N31-5.0210815*V31-0.0006437347*E31+1.4213619*AD31-3.2156123*AE31+167.41121*AC31-224.35191*IF(AND(B31>=DATE(2020,3,20),B31<=DATE(2020,6,26)),1,0)+194.56435*AF31-19.897843*AS31) -> 7648.9424 | AX31: =IF(N31="","",-654.03928+2464.5589*I31+0.035956453*N31-8.0754527*V31-0.00069441316*E31+0.69511606*AD31-1.1669613*AE31-90.724569*AC31-211.24919*IF(AND(B31>=DATE(2020,3,20),B31<=DATE(2020,6,26)),1,0)+147.22132*AF31-0.010108087*AQ31) -> 7682.7793
A32: 31 | B32: 33487 | C32: 6993 | E32: 425000 | G32: 21.8375 | H32: 20.336 | I32: 1.127 | J32: 6126.862 | L32: 844 | M32: 12.972 | N32: 193467 | O32: 3966 | P32: 824860 | V32: 89.8 | AC32: 1 | AD32: 0.4 | AE32: 63.4 | AF32: 12.6734 | AG32: =6753.47943187+0.36116788*I32+0.01252571*N32-22.85359542*V32+0.00407811*AA32-0.00067349*E32 -> 6838.7119 | AH32: =A32*'Simple Linear Regression'!$B$18+'Simple Linear Regression'!$B$17 -> 7911.7805 | AI32: =7491.3971+0.0137554*N32-0.00058829*E32-34.3283*V32+0.30565*L32+54.6031*M32 -> 7786.1885 | AJ32: =7491.3971-0.00058829*E32+0.30565*L32+54.6031*M32+0.0137554*N32-34.3283*V32 -> 7786.1885 | AL32: =2192.59+2373.87*I32+0.0316653*N32-15.7623*V32+0.00202406*AA32-0.000740146*E32-0.00963493*(I32*N32) -> 7163.3413 | AM32: =5205.907083+122.0638992*I32+13.609808*(N32/1000)-1.245906883*AD32+0.7746840854*AE32-134.2474226*AC32-1547.125689*IF(AND(B32>=DATE(2020,3,20),B32<=DATE(2020,6,26)),1,0) -> 7890.891 | AN32: =7707.2178-144.397321*AC32+139.5614087*AF32-0.0008594506251*E32-265.7105668*I32-0.02506176117*J32+0.004708026652*N32 -> 9424.1136 | AO32: =IF(N32="","",2190.39 + 2739.06*I32 + 0.034693*N32 - 16.722*V32 - 0.000802*E32 - 1.3691*AD32 + 1.8691*AE32 - 121.7*AC32 + 209.88*IF(AND(B32>=DATE(2020,3,20),B32<=DATE(2020,6,26)),1,0) - 0.011049*(I32*N32)) -> 7733.9347 | AP32: =IF(B32<DATE(2008,1,1),"",3929.06 + 1212.53*I32 - 0.0003097*N32 + 59.426*V32 - 0.0006734*E32 - 1.036*AD32 + 1.2076*AE32 + 94.923*AF32 - 131.43*AC32 - 759.61*IF(AND(B32>=DATE(2020,3,20),B32<=DATE(2020,6,26)),1,0) - 17.324*(I32*V32)) | AQ32: =IF(N32="","",I32*N32) -> 218037.31 | AR32: =I32*E32 -> 478975 | AS32: =AC32*AF32 -> 12.6734 | AT32: =IF(N32="","",2413.3773+89.103503*I32+0.018847679*N32-5.0917058*V32-0.00064564578*E32+1.4315076*AD32-3.1976817*AE32-66.972905*AC32-217.08397*IF(AND(B32>=DATE(2020,3,20),B32<=DATE(2020,6,26)),1,0)+190.76803*AF32) -> 7577.1125 | AU32: =IF(N32="","",-480.76297+2186.3009*I32+0.033368804*N32-5.3903106*V32-0.00073731439*E32+0.93396876*AD32-1.6242981*AE32-61.304389*AC32-95.472727*IF(AND(B32>=DATE(2020,3,20),B32<=DATE(2020,6,26)),1,0)+156.04851*AF32-0.0087322858*AQ32) -> 7551.3418 | AV32: =IF(N32="","",2518.0489-204.66184*I32+0.019354281*N32-2.3328708*V32-0.0022533804*E32+1.5259709*AD32-3.5842757*AE32-65.580099*AC32-62.828483*IF(AND(B32>=DATE(2020,3,20),B32<=DATE(2020,6,26)),1,0)+200.94286*AF32+0.00080379976*AR32) -> 7504.0477 | AW32: =IF(N32="","",2361.7153+89.223162*I32+0.018847054*N32-5.0210815*V32-0.0006437347*E32+1.4213619*AD32-3.2156123*AE32+167.41121*AC32-224.35191*IF(AND(B32>=DATE(2020,3,20),B32<=DATE(2020,6,26)),1,0)+194.56435*AF32-19.897843*AS32) -> 7561.8009 | AX32: =IF(N32="","",-654.03928+2464.5589*I32+0.035956453*N32-8.0754527*V32-0.00069441316*E32+0.69511606*AD32-1.1669613*AE32-90.724569*AC32-211.24919*IF(AND(B32>=DATE(2020,3,20),B32<=DATE(2020,6,26)),1,0)+147.22132*AF32-0.010108087*AQ32) -> 7557.0272
... A47: 46 | B47: 33592 | C47: 7447 | E47: 475000 | G47: 19.204 | H47: 18.306 | I47: 1.075 | J47: 6205.937 | L47: 795 | M47: 12.576 | N47: 188445 | O47: 3976 | P47: 818093 | V47: 88.3 | AC47: 0 | AD47: 161.3 | AE47: 0.6 | AF47: 9.4222 | AG47: =6753.47943187+0.36116788*I47+0.01252571*N47-22.85359542*V47+0.00407811*AA47-0.00067349*E47 -> 6776.3949 | AH47: =A47*'Simple Linear Regression'!$B$18+'Simple Linear Regression'!$B$17 -> 7924.5761 | AI47: =7491.3971+0.0137554*N47-0.00058829*E47-34.3283*V47+0.30565*L47+54.6031*M47 -> 7702.5871 | AJ47: =7491.3971-0.00058829*E47+0.30565*L47+54.6031*M47+0.0137554*N47-34.3283*V47 -> 7702.5871 | AL47: =2192.59+2373.87*I47+0.0316653*N47-15.7623*V47+0.00202406*AA47-0.000740146*E47-0.00963493*(I47*N47) -> 7016.4588 | AM47: =5205.907083+122.0638992*I47+13.609808*(N47/1000)-1.245906883*AD47+0.7746840854*AE47-134.2474226*AC47-1547.125689*IF(AND(B47>=DATE(2020,3,20),B47<=DATE(2020,6,26)),1,0) -> 7701.3261 | AN47: =7707.2178-144.397321*AC47+139.5614087*AF47-0.0008594506251*E47-265.7105668*I47-0.02506176117*J47+0.004708026652*N47 -> 9059.9878 | AO47: =IF(N47="","",2190.39 + 2739.06*I47 + 0.034693*N47 - 16.722*V47 - 0.000802*E47 - 1.3691*AD47 + 1.8691*AE47 - 121.7*AC47 + 209.88*IF(AND(B47>=DATE(2020,3,20),B47<=DATE(2020,6,26)),1,0) - 0.011049*(I47*N47)) -> 7357.0964 | AP47: =IF(B47<DATE(2008,1,1),"",3929.06 + 1212.53*I47 - 0.0003097*N47 + 59.426*V47 - 0.0006734*E47 - 1.036*AD47 + 1.2076*AE47 + 94.923*AF47 - 131.43*AC47 - 759.61*IF(AND(B47>=DATE(2020,3,20),B47<=DATE(2020,6,26)),1,0) - 17.324*(I47*V47)) | AQ47: =IF(N47="","",I47*N47) -> 202578.38 | AR47: =I47*E47 -> 510625 | AS47: =AC47*AF47 -> 0 | AT47: =IF(N47="","",2413.3773+89.103503*I47+0.018847679*N47-5.0917058*V47-0.00064564578*E47+1.4315076*AD47-3.1976817*AE47-66.972905*AC47-217.08397*IF(AND(B47>=DATE(2020,3,20),B47<=DATE(2020,6,26)),1,0)+190.76803*AF47) -> 7331.0732 | AU47: =IF(N47="","",-480.76297+2186.3009*I47+0.033368804*N47-5.3903106*V47-0.00073731439*E47+0.93396876*AD47-1.6242981*AE47-61.304389*AC47-95.472727*IF(AND(B47>=DATE(2020,3,20),B47<=DATE(2020,6,26)),1,0)+156.04851*AF47-0.0087322858*AQ47) -> 7182.5286 | AV47: =IF(N47="","",2518.0489-204.66184*I47+0.019354281*N47-2.3328708*V47-0.0022533804*E47+1.5259709*AD47-3.5842757*AE47-65.580099*AC47-62.828483*IF(AND(B47>=DATE(2020,3,20),B47<=DATE(2020,6,26)),1,0)+200.94286*AF47+0.00080379976*AR47) -> 7216.6593 | AW47: =IF(N47="","",2361.7153+89.223162*I47+0.018847054*N47-5.0210815*V47-0.0006437347*E47+1.4213619*AD47-3.2156123*AE47+167.41121*AC47-224.35191*IF(AND(B47>=DATE(2020,3,20),B47<=DATE(2020,6,26)),1,0)+194.56435*AF47-19.897843*AS47) -> 7320.6883 | AX47: =IF(N47="","",-654.03928+2464.5589*I47+0.035956453*N47-8.0754527*V47-0.00069441316*E47+0.69511606*AD47-1.1669613*AE47-90.724569*AC47-211.24919*IF(AND(B47>=DATE(2020,3,20),B47<=DATE(2020,6,26)),1,0)+147.22132*AF47-0.010108087*AQ47) -> 7179.1575
A48: 47 | B48: 33599 | C48: 7186 | E48: 436000 | G48: 18.6775 | H48: 17.7275 | I48: 1.063 | J48: 6205.937 | L48: 795 | M48: 12.576 | N48: 188445 | O48: 3976 | P48: 818093 | U48: 28 | V48: 88.3 | AC48: 1 | AD48: 145.4 | AE48: 1.4 | AF48: 9.4268 | AG48: =6753.47943187+0.36116788*I48+0.01252571*N48-22.85359542*V48+0.00407811*AA48-0.00067349*E48 -> 6802.6567 | AH48: =A48*'Simple Linear Regression'!$B$18+'Simple Linear Regression'!$B$17 -> 7925.4291 | AI48: =7491.3971+0.0137554*N48-0.00058829*E48-34.3283*V48+0.30565*L48+54.6031*M48 -> 7725.5305 | AJ48: =7491.3971-0.00058829*E48+0.30565*L48+54.6031*M48+0.0137554*N48-34.3283*V48 -> 7725.5305 | AL48: =2192.59+2373.87*I48+0.0316653*N48-15.7623*V48+0.00202406*AA48-0.000740146*E48-0.00963493*(I48*N48) -> 7038.6259 | AM48: =5205.907083+122.0638992*I48+13.609808*(N48/1000)-1.245906883*AD48+0.7746840854*AE48-134.2474226*AC48-1547.125689*IF(AND(B48>=DATE(2020,3,20),B48<=DATE(2020,6,26)),1,0) -> 7586.0436 | AN48: =7707.2178-144.397321*AC48+139.5614087*AF48-0.0008594506251*E48-265.7105668*I48-0.02506176117*J48+0.004708026652*N48 -> 8952.9395 | AO48: =IF(N48="","",2190.39 + 2739.06*I48 + 0.034693*N48 - 16.722*V48 - 0.000802*E48 - 1.3691*AD48 + 1.8691*AE48 - 121.7*AC48 + 209.88*IF(AND(B48>=DATE(2020,3,20),B48<=DATE(2020,6,26)),1,0) - 0.011049*(I48*N48)) -> 7282.0552 | AP48: =IF(B48<DATE(2008,1,1),"",3929.06 + 1212.53*I48 - 0.0003097*N48 + 59.426*V48 - 0.0006734*E48 - 1.036*AD48 + 1.2076*AE48 + 94.923*AF48 - 131.43*AC48 - 759.61*IF(AND(B48>=DATE(2020,3,20),B48<=DATE(2020,6,26)),1,0) - 17.324*(I48*V48)) | AQ48: =IF(N48="","",I48*N48) -> 200317.04 | AR48: =I48*E48 -> 463468 | AS48: =AC48*AF48 -> 9.4268 | AT48: =IF(N48="","",2413.3773+89.103503*I48+0.018847679*N48-5.0917058*V48-0.00064564578*E48+1.4315076*AD48-3.1976817*AE48-66.972905*AC48-217.08397*IF(AND(B48>=DATE(2020,3,20),B48<=DATE(2020,6,26)),1,0)+190.76803*AF48) -> 7263.7696 | AU48: =IF(N48="","",-480.76297+2186.3009*I48+0.033368804*N48-5.3903106*V48-0.00073731439*E48+0.93396876*AD48-1.6242981*AE48-61.304389*AC48-95.472727*IF(AND(B48>=DATE(2020,3,20),B48<=DATE(2020,6,26)),1,0)+156.04851*AF48-0.0087322858*AQ48) -> 7128.0588 | AV48: =IF(N48="","",2518.0489-204.66184*I48+0.019354281*N48-2.3328708*V48-0.0022533804*E48+1.5259709*AD48-3.5842757*AE48-65.580099*AC48-62.828483*IF(AND(B48>=DATE(2020,3,20),B48<=DATE(2020,6,26)),1,0)+200.94286*AF48+0.00080379976*AR48) -> 7177.3062 | AW48: =IF(N48="","",2361.7153+89.223162*I48+0.018847054*N48-5.0210815*V48-0.0006437347*E48+1.4213619*AD48-3.2156123*AE48+167.41121*AC48-224.35191*IF(AND(B48>=DATE(2020,3,20),B48<=DATE(2020,6,26)),1,0)+194.56435*AF48-19.897843*AS48) -> 7300.2844 | AX48: =IF(N48="","",-654.03928+2464.5589*I48+0.035956453*N48-8.0754527*V48-0.00069441316*E48+0.69511606*AD48-1.1669613*AE48-90.724569*AC48-211.24919*IF(AND(B48>=DATE(2020,3,20),B48<=DATE(2020,6,26)),1,0)+147.22132*AF48-0.010108087*AQ48) -> 7097.4895
A49: 48 | B49: 33606 | C49: 6642 | E49: 441000 | G49: 19.1075 | H49: 18.175 | I49: 1.053 | J49: 6205.937 | L49: 795 | M49: 12.576 | N49: 188445 | O49: 3976 | P49: 818093 | U49: 28 | V49: 88.3 | AC49: 1 | AD49: 155.2 | AE49: 0 | AF49: 9.4748 | AG49: =6753.47943187+0.36116788*I49+0.01252571*N49-22.85359542*V49+0.00407811*AA49-0.00067349*E49 -> 6799.2856 | AH49: =A49*'Simple Linear Regression'!$B$18+'Simple Linear Regression'!$B$17 -> 7926.2821 | AI49: =7491.3971+0.0137554*N49-0.00058829*E49-34.3283*V49+0.30565*L49+54.6031*M49 -> 7722.589 | AJ49: =7491.3971-0.00058829*E49+0.30565*L49+54.6031*M49+0.0137554*N49-34.3283*V49 -> 7722.589 | AL49: =2192.59+2373.87*I49+0.0316653*N49-15.7623*V49+0.00202406*AA49-0.000740146*E49-0.00963493*(I49*N49) -> 7029.343 | AM49: =5205.907083+122.0638992*I49+13.609808*(N49/1000)-1.245906883*AD49+0.7746840854*AE49-134.2474226*AC49-1547.125689*IF(AND(B49>=DATE(2020,3,20),B49<=DATE(2020,6,26)),1,0) -> 7571.5285 | AN49: =7707.2178-144.397321*AC49+139.5614087*AF49-0.0008594506251*E49-265.7105668*I49-0.02506176117*J49+0.004708026652*N49 -> 8957.9983 | AO49: =IF(N49="","",2190.39 + 2739.06*I49 + 0.034693*N49 - 16.722*V49 - 0.000802*E49 - 1.3691*AD49 + 1.8691*AE49 - 121.7*AC49 + 209.88*IF(AND(B49>=DATE(2020,3,20),B49<=DATE(2020,6,26)),1,0) - 0.011049*(I49*N49)) -> 7255.442 | AP49: =IF(B49<DATE(2008,1,1),"",3929.06 + 1212.53*I49 - 0.0003097*N49 + 59.426*V49 - 0.0006734*E49 - 1.036*AD49 + 1.2076*AE49 + 94.923*AF49 - 131.43*AC49 - 759.61*IF(AND(B49>=DATE(2020,3,20),B49<=DATE(2020,6,26)),1,0) - 17.324*(I49*V49)) | AQ49: =IF(N49="","",I49*N49) -> 198432.58 | AR49: =I49*E49 -> 464373 | AS49: =AC49*AF49 -> 9.4748 | AT49: =IF(N49="","",2413.3773+89.103503*I49+0.018847679*N49-5.0917058*V49-0.00064564578*E49+1.4315076*AD49-3.1976817*AE49-66.972905*AC49-217.08397*IF(AND(B49>=DATE(2020,3,20),B49<=DATE(2020,6,26)),1,0)+190.76803*AF49) -> 7287.3128 | AU49: =IF(N49="","",-480.76297+2186.3009*I49+0.033368804*N49-5.3903106*V49-0.00073731439*E49+0.93396876*AD49-1.6242981*AE49-61.304389*AC49-95.472727*IF(AND(B49>=DATE(2020,3,20),B49<=DATE(2020,6,26)),1,0)+156.04851*AF49-0.0087322858*AQ49) -> 7137.882 | AV49: =IF(N49="","",2518.0489-204.66184*I49+0.019354281*N49-2.3328708*V49-0.0022533804*E49+1.5259709*AD49-3.5842757*AE49-65.580099*AC49-62.828483*IF(AND(B49>=DATE(2020,3,20),B49<=DATE(2020,6,26)),1,0)+200.94286*AF49+0.00080379976*AR49) -> 7198.4311 | AW49: =IF(N49="","",2361.7153+89.223162*I49+0.018847054*N49-5.0210815*V49-0.0006437347*E49+1.4213619*AD49-3.2156123*AE49+167.41121*AC49-224.35191*IF(AND(B49>=DATE(2020,3,20),B49<=DATE(2020,6,26)),1,0)+194.56435*AF49-19.897843*AS49) -> 7322.9887 | AX49: =IF(N49="","",-654.03928+2464.5589*I49+0.035956453*N49-8.0754527*V49-0.00069441316*E49+0.69511606*AD49-1.1669613*AE49-90.724569*AC49-211.24919*IF(AND(B49>=DATE(2020,3,20),B49<=DATE(2020,6,26)),1,0)+147.22132*AF49-0.010108087*AQ49) -> 7103.9325
A50: 49 | B50: 33613 | C50: 6788 | E50: 432000 | G50: 18.412 | H50: 17.772 | I50: 1.042 | J50: 6205.937 | L50: 808 | M50: 12.576 | N50: 188445 | O50: 4003.6 | P50: 818093 | U50: 28 | V50: 83.4 | AC50: 0 | AD50: 140.8 | AE50: 0 | AF50: 9.5643 | AG50: =6753.47943187+0.36116788*I50+0.01252571*N50-22.85359542*V50+0.00407811*AA50-0.00067349*E50 -> 6917.3257 | AH50: =A50*'Simple Linear Regression'!$B$18+'Simple Linear Regression'!$B$17 -> 7927.1352 | AI50: =7491.3971+0.0137554*N50-0.00058829*E50-34.3283*V50+0.30565*L50+54.6031*M50 -> 7900.0657 | AJ50: =7491.3971-0.00058829*E50+0.30565*L50+54.6031*M50+0.0137554*N50-34.3283*V50 -> 7900.0657 | AL50: =2192.59+2373.87*I50+0.0316653*N50-15.7623*V50+0.00202406*AA50-0.000740146*E50-0.00963493*(I50*N50) -> 7107.0992 | AM50: =5205.907083+122.0638992*I50+13.609808*(N50/1000)-1.245906883*AD50+0.7746840854*AE50-134.2474226*AC50-1547.125689*IF(AND(B50>=DATE(2020,3,20),B50<=DATE(2020,6,26)),1,0) -> 7722.3742 | AN50: =7707.2178-144.397321*AC50+139.5614087*AF50-0.0008594506251*E50-265.7105668*I50-0.02506176117*J50+0.004708026652*N50 -> 9125.5443 | AO50: =IF(N50="","",2190.39 + 2739.06*I50 + 0.034693*N50 - 16.722*V50 - 0.000802*E50 - 1.3691*AD50 + 1.8691*AE50 - 121.7*AC50 + 209.88*IF(AND(B50>=DATE(2020,3,20),B50<=DATE(2020,6,26)),1,0) - 0.011049*(I50*N50)) -> 7478.7866 | AP50: =IF(B50<DATE(2008,1,1),"",3929.06 + 1212.53*I50 - 0.0003097*N50 + 59.426*V50 - 0.0006734*E50 - 1.036*AD50 + 1.2076*AE50 + 94.923*AF50 - 131.43*AC50 - 759.61*IF(AND(B50>=DATE(2020,3,20),B50<=DATE(2020,6,26)),1,0) - 17.324*(I50*V50)) | AQ50: =IF(N50="","",I50*N50) -> 196359.69 | AR50: =I50*E50 -> 450144 | AS50: =AC50*AF50 -> 0 | AT50: =IF(N50="","",2413.3773+89.103503*I50+0.018847679*N50-5.0917058*V50-0.00064564578*E50+1.4315076*AD50-3.1976817*AE50-66.972905*AC50-217.08397*IF(AND(B50>=DATE(2020,3,20),B50<=DATE(2020,6,26)),1,0)+190.76803*AF50) -> 7380.5257 | AU50: =IF(N50="","",-480.76297+2186.3009*I50+0.033368804*N50-5.3903106*V50-0.00073731439*E50+0.93396876*AD50-1.6242981*AE50-61.304389*AC50-95.472727*IF(AND(B50>=DATE(2020,3,20),B50<=DATE(2020,6,26)),1,0)+156.04851*AF50-0.0087322858*AQ50) -> 7226.8037 | AV50: =IF(N50="","",2518.0489-204.66184*I50+0.019354281*N50-2.3328708*V50-0.0022533804*E50+1.5259709*AD50-3.5842757*AE50-65.580099*AC50-62.828483*IF(AND(B50>=DATE(2020,3,20),B50<=DATE(2020,6,26)),1,0)+200.94286*AF50+0.00080379976*AR50) -> 7282.5471 | AW50: =IF(N50="","",2361.7153+89.223162*I50+0.018847054*N50-5.0210815*V50-0.0006437347*E50+1.4213619*AD50-3.2156123*AE50+167.41121*AC50-224.35191*IF(AND(B50>=DATE(2020,3,20),B50<=DATE(2020,6,26)),1,0)+194.56435*AF50-19.897843*AS50) -> 7370.4669 | AX50: =IF(N50="","",-654.03928+2464.5589*I50+0.035956453*N50-8.0754527*V50-0.00069441316*E50+0.69511606*AD50-1.1669613*AE50-90.724569*AC50-211.24919*IF(AND(B50>=DATE(2020,3,20),B50<=DATE(2020,6,26)),1,0)+147.22132*AF50-0.010108087*AQ50) -> 7237.486
A51: 50 | B51: 33620 | C51: 6783 | E51: 440000 | G51: 18.81 | H51: 18.37 | I51: 1.026 | J51: 6205.937 | L51: 808 | M51: 12.658 | N51: 169693 | O51: 4003.6 | P51: 818093 | U51: 28 | V51: 83.4 | AC51: 0 | AD51: 185.6 | AE51: 0 | AF51: 9.6925 | AG51: =6753.47943187+0.36116788*I51+0.01252571*N51-22.85359542*V51+0.00407811*AA51-0.00067349*E51 -> 6677.0498 | AH51: =A51*'Simple Linear Regression'!$B$18+'Simple Linear Regression'!$B$17 -> 7927.9882 | AI51: =7491.3971+0.0137554*N51-0.00058829*E51-34.3283*V51+0.30565*L51+54.6031*M51 -> 7641.8956 | AJ51: =7491.3971-0.00058829*E51+0.30565*L51+54.6031*M51+0.0137554*N51-34.3283*V51 -> 7641.8956 | AL51: =2192.59+2373.87*I51+0.0316653*N51-15.7623*V51+0.00202406*AA51-0.000740146*E51-0.00963493*(I51*N51) -> 6683.8307 | AM51: =5205.907083+122.0638992*I51+13.609808*(N51/1000)-1.245906883*AD51+0.7746840854*AE51-134.2474226*AC51-1547.125689*IF(AND(B51>=DATE(2020,3,20),B51<=DATE(2020,6,26)),1,0) -> 7409.3935 | AN51: =7707.2178-144.397321*AC51+139.5614087*AF51-0.0008594506251*E51-265.7105668*I51-0.02506176117*J51+0.004708026652*N51 -> 9052.5269 | AO51: =IF(N51="","",2190.39 + 2739.06*I51 + 0.034693*N51 - 16.722*V51 - 0.000802*E51 - 1.3691*AD51 + 1.8691*AE51 - 121.7*AC51 + 209.88*IF(AND(B51>=DATE(2020,3,20),B51<=DATE(2020,6,26)),1,0) - 0.011049*(I51*N51)) -> 6962.5387 | AP51: =IF(B51<DATE(2008,1,1),"",3929.06 + 1212.53*I51 - 0.0003097*N51 + 59.426*V51 - 0.0006734*E51 - 1.036*AD51 + 1.2076*AE51 + 94.923*AF51 - 131.43*AC51 - 759.61*IF(AND(B51>=DATE(2020,3,20),B51<=DATE(2020,6,26)),1,0) - 17.324*(I51*V51)) | AQ51: =IF(N51="","",I51*N51) -> 174105.02 | AR51: =I51*E51 -> 451440 | AS51: =AC51*AF51 -> 0 | AT51: =IF(N51="","",2413.3773+89.103503*I51+0.018847679*N51-5.0917058*V51-0.00064564578*E51+1.4315076*AD51-3.1976817*AE51-66.972905*AC51-217.08397*IF(AND(B51>=DATE(2020,3,20),B51<=DATE(2020,6,26)),1,0)+190.76803*AF51) -> 7109.0912 | AU51: =IF(N51="","",-480.76297+2186.3009*I51+0.033368804*N51-5.3903106*V51-0.00073731439*E51+0.93396876*AD51-1.6242981*AE51-61.304389*AC51-95.472727*IF(AND(B51>=DATE(2020,3,20),B51<=DATE(2020,6,26)),1,0)+156.04851*AF51-0.0087322858*AQ51) -> 6816.374 | AV51: =IF(N51="","",2518.0489-204.66184*I51+0.019354281*N51-2.3328708*V51-0.0022533804*E51+1.5259709*AD51-3.5842757*AE51-65.580099*AC51-62.828483*IF(AND(B51>=DATE(2020,3,20),B51<=DATE(2020,6,26)),1,0)+200.94286*AF51+0.00080379976*AR51) -> 7000.0293 | AW51: =IF(N51="","",2361.7153+89.223162*I51+0.018847054*N51-5.0210815*V51-0.0006437347*E51+1.4213619*AD51-3.2156123*AE51+167.41121*AC51-224.35191*IF(AND(B51>=DATE(2020,3,20),B51<=DATE(2020,6,26)),1,0)+194.56435*AF51-19.897843*AS51) -> 7099.0897 | AX51: =IF(N51="","",-654.03928+2464.5589*I51+0.035956453*N51-8.0754527*V51-0.00069441316*E51+0.69511606*AD51-1.1669613*AE51-90.724569*AC51-211.24919*IF(AND(B51>=DATE(2020,3,20),B51<=DATE(2020,6,26)),1,0)+147.22132*AF51-0.010108087*AQ51) -> 6793.2095
A52: 51 | B52: 33627 | C52: 7037 | E52: 443000 | G52: 18.656 | H52: 18.112 | I52: 1.014 | J52: 6205.937 | L52: 808 | M52: 12.658 | N52: 169693 | O52: 4003.6 | P52: 818093 | U52: 28 | V52: 83.4 | AC52: 0 | AD52: 191.3 | AE52: 0 | AF52: 9.8553 | AG52: =6753.47943187+0.36116788*I52+0.01252571*N52-22.85359542*V52+0.00407811*AA52-0.00067349*E52 -> 6675.025 | AH52: =A52*'Simple Linear Regression'!$B$18+'Simple Linear Regression'!$B$17 -> 7928.8412 | AI52: =7491.3971+0.0137554*N52-0.00058829*E52-34.3283*V52+0.30565*L52+54.6031*M52 -> 7640.1307 | AJ52: =7491.3971-0.00058829*E52+0.30565*L52+54.6031*M52+0.0137554*N52-34.3283*V52 -> 7640.1307 | AL52: =2192.59+2373.87*I52+0.0316653*N52-15.7623*V52+0.00202406*AA52-0.000740146*E52-0.00963493*(I52*N52) -> 6672.7435 | AM52: =5205.907083+122.0638992*I52+13.609808*(N52/1000)-1.245906883*AD52+0.7746840854*AE52-134.2474226*AC52-1547.125689*IF(AND(B52>=DATE(2020,3,20),B52<=DATE(2020,6,26)),1,0) -> 7400.827 | AN52: =7707.2178-144.397321*AC52+139.5614087*AF52-0.0008594506251*E52-265.7105668*I52-0.02506176117*J52+0.004708026652*N52 -> 9075.8577 | AO52: =IF(N52="","",2190.39 + 2739.06*I52 + 0.034693*N52 - 16.722*V52 - 0.000802*E52 - 1.3691*AD52 + 1.8691*AE52 - 121.7*AC52 + 209.88*IF(AND(B52>=DATE(2020,3,20),B52<=DATE(2020,6,26)),1,0) - 0.011049*(I52*N52)) -> 6941.9594 | AP52: =IF(B52<DATE(2008,1,1),"",3929.06 + 1212.53*I52 - 0.0003097*N52 + 59.426*V52 - 0.0006734*E52 - 1.036*AD52 + 1.2076*AE52 + 94.923*AF52 - 131.43*AC52 - 759.61*IF(AND(B52>=DATE(2020,3,20),B52<=DATE(2020,6,26)),1,0) - 17.324*(I52*V52)) | AQ52: =IF(N52="","",I52*N52) -> 172068.7 | AR52: =I52*E52 -> 449202 | AS52: =AC52*AF52 -> 0 | AT52: =IF(N52="","",2413.3773+89.103503*I52+0.018847679*N52-5.0917058*V52-0.00064564578*E52+1.4315076*AD52-3.1976817*AE52-66.972905*AC52-217.08397*IF(AND(B52>=DATE(2020,3,20),B52<=DATE(2020,6,26)),1,0)+190.76803*AF52) -> 7145.3017 | AU52: =IF(N52="","",-480.76297+2186.3009*I52+0.033368804*N52-5.3903106*V52-0.00073731439*E52+0.93396876*AD52-1.6242981*AE52-61.304389*AC52-95.472727*IF(AND(B52>=DATE(2020,3,20),B52<=DATE(2020,6,26)),1,0)+156.04851*AF52-0.0087322858*AQ52) -> 6836.4364 | AV52: =IF(N52="","",2518.0489-204.66184*I52+0.019354281*N52-2.3328708*V52-0.0022533804*E52+1.5259709*AD52-3.5842757*AE52-65.580099*AC52-62.828483*IF(AND(B52>=DATE(2020,3,20),B52<=DATE(2020,6,26)),1,0)+200.94286*AF52+0.00080379976*AR52) -> 7035.3377 | AW52: =IF(N52="","",2361.7153+89.223162*I52+0.018847054*N52-5.0210815*V52-0.0006437347*E52+1.4213619*AD52-3.2156123*AE52+167.41121*AC52-224.35191*IF(AND(B52>=DATE(2020,3,20),B52<=DATE(2020,6,26)),1,0)+194.56435*AF52-19.897843*AS52) -> 7135.8646 | AX52: =IF(N52="","",-654.03928+2464.5589*I52+0.035956453*N52-8.0754527*V52-0.00069441316*E52+0.69511606*AD52-1.1669613*AE52-90.724569*AC52-211.24919*IF(AND(B52>=DATE(2020,3,20),B52<=DATE(2020,6,26)),1,0)+147.22132*AF52-0.010108087*AQ52) -> 6810.0646
A53: 52 | B53: 33634 | C53: 7112 | E53: 441000 | G53: 19.048 | H53: 18.276 | I53: 1.006 | J53: 6205.937 | L53: 808 | M53: 12.658 | N53: 169693 | O53: 4003.6 | P53: 818093 | U53: 28 | V53: 83.4 | AC53: 0 | AD53: 156.1 | AE53: 0 | AF53: 10.0483 | AG53: =6753.47943187+0.36116788*I53+0.01252571*N53-22.85359542*V53+0.00407811*AA53-0.00067349*E53 -> 6676.3691 | AH53: =A53*'Simple Linear Regression'!$B$18+'Simple Linear Regression'!$B$17 -> 7929.6943 | AI53: =7491.3971+0.0137554*N53-0.00058829*E53-34.3283*V53+0.30565*L53+54.6031*M53 -> 7641.3073 | AJ53: =7491.3971-0.00058829*E53+0.30565*L53+54.6031*M53+0.0137554*N53-34.3283*V53 -> 7641.3073 | AL53: =2192.59+2373.87*I53+0.0316653*N53-15.7623*V53+0.00202406*AA53-0.000740146*E53-0.00963493*(I53*N53) -> 6668.3127 | AM53: =5205.907083+122.0638992*I53+13.609808*(N53/1000)-1.245906883*AD53+0.7746840854*AE53-134.2474226*AC53-1547.125689*IF(AND(B53>=DATE(2020,3,20),B53<=DATE(2020,6,26)),1,0) -> 7443.7065 | AN53: =7707.2178-144.397321*AC53+139.5614087*AF53-0.0008594506251*E53-265.7105668*I53-0.02506176117*J53+0.004708026652*N53 -> 9106.6376 | AO53: =IF(N53="","",2190.39 + 2739.06*I53 + 0.034693*N53 - 16.722*V53 - 0.000802*E53 - 1.3691*AD53 + 1.8691*AE53 - 121.7*AC53 + 209.88*IF(AND(B53>=DATE(2020,3,20),B53<=DATE(2020,6,26)),1,0) - 0.011049*(I53*N53)) -> 6984.8427 | AP53: =IF(B53<DATE(2008,1,1),"",3929.06 + 1212.53*I53 - 0.0003097*N53 + 59.426*V53 - 0.0006734*E53 - 1.036*AD53 + 1.2076*AE53 + 94.923*AF53 - 131.43*AC53 - 759.61*IF(AND(B53>=DATE(2020,3,20),B53<=DATE(2020,6,26)),1,0) - 17.324*(I53*V53)) | AQ53: =IF(N53="","",I53*N53) -> 170711.16 | AR53: =I53*E53 -> 443646 | AS53: =AC53*AF53 -> 0 | AT53: =IF(N53="","",2413.3773+89.103503*I53+0.018847679*N53-5.0917058*V53-0.00064564578*E53+1.4315076*AD53-3.1976817*AE53-66.972905*AC53-217.08397*IF(AND(B53>=DATE(2020,3,20),B53<=DATE(2020,6,26)),1,0)+190.76803*AF53) -> 7132.3093 | AU53: =IF(N53="","",-480.76297+2186.3009*I53+0.033368804*N53-5.3903106*V53-0.00073731439*E53+0.93396876*AD53-1.6242981*AE53-61.304389*AC53-95.472727*IF(AND(B53>=DATE(2020,3,20),B53<=DATE(2020,6,26)),1,0)+156.04851*AF53-0.0087322858*AQ53) -> 6829.5168 | AV53: =IF(N53="","",2518.0489-204.66184*I53+0.019354281*N53-2.3328708*V53-0.0022533804*E53+1.5259709*AD53-3.5842757*AE53-65.580099*AC53-62.828483*IF(AND(B53>=DATE(2020,3,20),B53<=DATE(2020,6,26)),1,0)+200.94286*AF53+0.00080379976*AR53) -> 7022.0837 | AW53: =IF(N53="","",2361.7153+89.223162*I53+0.018847054*N53-5.0210815*V53-0.0006437347*E53+1.4213619*AD53-3.2156123*AE53+167.41121*AC53-224.35191*IF(AND(B53>=DATE(2020,3,20),B53<=DATE(2020,6,26)),1,0)+194.56435*AF53-19.897843*AS53) -> 7123.9573 | AX53: =IF(N53="","",-654.03928+2464.5589*I53+0.035956453*N53-8.0754527*V53-0.00069441316*E53+0.69511606*AD53-1.1669613*AE53-90.724569*AC53-211.24919*IF(AND(B53>=DATE(2020,3,20),B53<=DATE(2020,6,26)),1,0)+147.22132*AF53-0.010108087*AQ53) -> 6809.4048
A54: 53 | B54: 33641 | C54: 7039 | E54: 440000 | G54: 19.424 | H54: 18.468 | I54: 0.995 | J54: 6264.54 | L54: 796 | M54: 12.658 | N54: 169693 | O54: 4020.5 | P54: 818093 | U54: 28 | V54: 83.7 | AC54: 0 | AD54: 155.8 | AE54: 0 | AF54: 10.2666 | AG54: =6753.47943187+0.36116788*I54+0.01252571*N54-22.85359542*V54+0.00407811*AA54-0.00067349*E54 -> 6670.1826 | AH54: =A54*'Simple Linear Regression'!$B$18+'Simple Linear Regression'!$B$17 -> 7930.5473 | AI54: =7491.3971+0.0137554*N54-0.00058829*E54-34.3283*V54+0.30565*L54+54.6031*M54 -> 7627.9293 | AJ54: =7491.3971-0.00058829*E54+0.30565*L54+54.6031*M54+0.0137554*N54-34.3283*V54 -> 7627.9293 | AL54: =2192.59+2373.87*I54+0.0316653*N54-15.7623*V54+0.00202406*AA54-0.000740146*E54-0.00963493*(I54*N54) -> 6656.1964 | AM54: =5205.907083+122.0638992*I54+13.609808*(N54/1000)-1.245906883*AD54+0.7746840854*AE54-134.2474226*AC54-1547.125689*IF(AND(B54>=DATE(2020,3,20),B54<=DATE(2020,6,26)),1,0) -> 7442.7375 | AN54: =7707.2178-144.397321*AC54+139.5614087*AF54-0.0008594506251*E54-265.7105668*I54-0.02506176117*J54+0.004708026652*N54 -> 9139.4174 | AO54: =IF(N54="","",2190.39 + 2739.06*I54 + 0.034693*N54 - 16.722*V54 - 0.000802*E54 - 1.3691*AD54 + 1.8691*AE54 - 121.7*AC54 + 209.88*IF(AND(B54>=DATE(2020,3,20),B54<=DATE(2020,6,26)),1,0) - 0.011049*(I54*N54)) -> 6971.5335 | AP54: =IF(B54<DATE(2008,1,1),"",3929.06 + 1212.53*I54 - 0.0003097*N54 + 59.426*V54 - 0.0006734*E54 - 1.036*AD54 + 1.2076*AE54 + 94.923*AF54 - 131.43*AC54 - 759.61*IF(AND(B54>=DATE(2020,3,20),B54<=DATE(2020,6,26)),1,0) - 17.324*(I54*V54)) | AQ54: =IF(N54="","",I54*N54) -> 168844.54 | AR54: =I54*E54 -> 437800 | AS54: =AC54*AF54 -> 0 | AT54: =IF(N54="","",2413.3773+89.103503*I54+0.018847679*N54-5.0917058*V54-0.00064564578*E54+1.4315076*AD54-3.1976817*AE54-66.972905*AC54-217.08397*IF(AND(B54>=DATE(2020,3,20),B54<=DATE(2020,6,26)),1,0)+190.76803*AF54) -> 7171.6625 | AU54: =IF(N54="","",-480.76297+2186.3009*I54+0.033368804*N54-5.3903106*V54-0.00073731439*E54+0.93396876*AD54-1.6242981*AE54-61.304389*AC54-95.472727*IF(AND(B54>=DATE(2020,3,20),B54<=DATE(2020,6,26)),1,0)+156.04851*AF54-0.0087322858*AQ54) -> 6854.6728 | AV54: =IF(N54="","",2518.0489-204.66184*I54+0.019354281*N54-2.3328708*V54-0.0022533804*E54+1.5259709*AD54-3.5842757*AE54-65.580099*AC54-62.828483*IF(AND(B54>=DATE(2020,3,20),B54<=DATE(2020,6,26)),1,0)+200.94286*AF54+0.00080379976*AR54) -> 7064.5975 | AW54: =IF(N54="","",2361.7153+89.223162*I54+0.018847054*N54-5.0210815*V54-0.0006437347*E54+1.4213619*AD54-3.2156123*AE54+167.41121*AC54-224.35191*IF(AND(B54>=DATE(2020,3,20),B54<=DATE(2020,6,26)),1,0)+194.56435*AF54-19.897843*AS54) -> 7164.1602 | AX54: =IF(N54="","",-654.03928+2464.5589*I54+0.035956453*N54-8.0754527*V54-0.00069441316*E54+0.69511606*AD54-1.1669613*AE54-90.724569*AC54-211.24919*IF(AND(B54>=DATE(2020,3,20),B54<=DATE(2020,6,26)),1,0)+147.22132*AF54-0.010108087*AQ54) -> 6831.3643
A55: 54 | B55: 33648 | C55: 6576 | E55: 445000 | G55: 19.492 | H55: 18.584 | I55: 1.004 | J55: 6264.54 | L55: 796 | M55: 12.658 | N55: 169693 | O55: 4020.5 | P55: 818093 | U55: 28 | V55: 83.7 | AC55: 0 | AD55: 170.1 | AE55: 0.5 | AF55: 10.5057 | AG55: =6753.47943187+0.36116788*I55+0.01252571*N55-22.85359542*V55+0.00407811*AA55-0.00067349*E55 -> 6666.8184 | AH55: =A55*'Simple Linear Regression'!$B$18+'Simple Linear Regression'!$B$17 -> 7931.4003 | AI55: =7491.3971+0.0137554*N55-0.00058829*E55-34.3283*V55+0.30565*L55+54.6031*M55 -> 7624.9879 | AJ55: =7491.3971-0.00058829*E55+0.30565*L55+54.6031*M55+0.0137554*N55-34.3283*V55 -> 7624.9879 | AL55: =2192.59+2373.87*I55+0.0316653*N55-15.7623*V55+0.00202406*AA55-0.000740146*E55-0.00963493*(I55*N55) -> 6659.1457 | AM55: =5205.907083+122.0638992*I55+13.609808*(N55/1000)-1.245906883*AD55+0.7746840854*AE55-134.2474226*AC55-1547.125689*IF(AND(B55>=DATE(2020,3,20),B55<=DATE(2020,6,26)),1,0) -> 7426.407 | AN55: =7707.2178-144.397321*AC55+139.5614087*AF55-0.0008594506251*E55-265.7105668*I55-0.02506176117*J55+0.004708026652*N55 -> 9166.0979 | AO55: =IF(N55="","",2190.39 + 2739.06*I55 + 0.034693*N55 - 16.722*V55 - 0.000802*E55 - 1.3691*AD55 + 1.8691*AE55 - 121.7*AC55 + 209.88*IF(AND(B55>=DATE(2020,3,20),B55<=DATE(2020,6,26)),1,0) - 0.011049*(I55*N55)) -> 6956.657 | AP55: =IF(B55<DATE(2008,1,1),"",3929.06 + 1212.53*I55 - 0.0003097*N55 + 59.426*V55 - 0.0006734*E55 - 1.036*AD55 + 1.2076*AE55 + 94.923*AF55 - 131.43*AC55 - 759.61*IF(AND(B55>=DATE(2020,3,20),B55<=DATE(2020,6,26)),1,0) - 17.324*(I55*V55)) | AQ55: =IF(N55="","",I55*N55) -> 170371.77 | AR55: =I55*E55 -> 446780 | AS55: =AC55*AF55 -> 0 | AT55: =IF(N55="","",2413.3773+89.103503*I55+0.018847679*N55-5.0917058*V55-0.00064564578*E55+1.4315076*AD55-3.1976817*AE55-66.972905*AC55-217.08397*IF(AND(B55>=DATE(2020,3,20),B55<=DATE(2020,6,26)),1,0)+190.76803*AF55) -> 7233.7206 | AU55: =IF(N55="","",-480.76297+2186.3009*I55+0.033368804*N55-5.3903106*V55-0.00073731439*E55+0.93396876*AD55-1.6242981*AE55-61.304389*AC55-95.472727*IF(AND(B55>=DATE(2020,3,20),B55<=DATE(2020,6,26)),1,0)+156.04851*AF55-0.0087322858*AQ55) -> 6907.1815 | AV55: =IF(N55="","",2518.0489-204.66184*I55+0.019354281*N55-2.3328708*V55-0.0022533804*E55+1.5259709*AD55-3.5842757*AE55-65.580099*AC55-62.828483*IF(AND(B55>=DATE(2020,3,20),B55<=DATE(2020,6,26)),1,0)+200.94286*AF55+0.00080379976*AR55) -> 7126.7814 | AW55: =IF(N55="","",2361.7153+89.223162*I55+0.018847054*N55-5.0210815*V55-0.0006437347*E55+1.4213619*AD55-3.2156123*AE55+167.41121*AC55-224.35191*IF(AND(B55>=DATE(2020,3,20),B55<=DATE(2020,6,26)),1,0)+194.56435*AF55-19.897843*AS55) -> 7226.9826 | AX55: =IF(N55="","",-654.03928+2464.5589*I55+0.035956453*N55-8.0754527*V55-0.00069441316*E55+0.69511606*AD55-1.1669613*AE55-90.724569*AC55-211.24919*IF(AND(B55>=DATE(2020,3,20),B55<=DATE(2020,6,26)),1,0)+147.22132*AF55-0.010108087*AQ55) -> 6879.1931
A56: 55 | B56: 33655 | C56: 7002 | E56: 446000 | G56: 18.62 | H56: 17.74 | I56: 1.011 | J56: 6264.54 | L56: 796 | M56: 12.591 | N56: 172782 | O56: 4020.5 | P56: 818093 | U56: 28 | V56: 83.7 | AC56: 0 | AD56: 125 | AE56: 0.7 | AF56: 10.7613 | AG56: =6753.47943187+0.36116788*I56+0.01252571*N56-22.85359542*V56+0.00407811*AA56-0.00067349*E56 -> 6704.8393 | AH56: =A56*'Simple Linear Regression'!$B$18+'Simple Linear Regression'!$B$17 -> 7932.2534 | AI56: =7491.3971+0.0137554*N56-0.00058829*E56-34.3283*V56+0.30565*L56+54.6031*M56 -> 7663.2316 | AJ56: =7491.3971-0.00058829*E56+0.30565*L56+54.6031*M56+0.0137554*N56-34.3283*V56 -> 7663.2316 | AL56: =2192.59+2373.87*I56+0.0316653*N56-15.7623*V56+0.00202406*AA56-0.000740146*E56-0.00963493*(I56*N56) -> 6731.3022 | AM56: =5205.907083+122.0638992*I56+13.609808*(N56/1000)-1.245906883*AD56+0.7746840854*AE56-134.2474226*AC56-1547.125689*IF(AND(B56>=DATE(2020,3,20),B56<=DATE(2020,6,26)),1,0) -> 7525.6474 | AN56: =7707.2178-144.397321*AC56+139.5614087*AF56-0.0008594506251*E56-265.7105668*I56-0.02506176117*J56+0.004708026652*N56 -> 9213.5935 | AO56: =IF(N56="","",2190.39 + 2739.06*I56 + 0.034693*N56 - 16.722*V56 - 0.000802*E56 - 1.3691*AD56 + 1.8691*AE56 - 121.7*AC56 + 209.88*IF(AND(B56>=DATE(2020,3,20),B56<=DATE(2020,6,26)),1,0) - 0.011049*(I56*N56)) -> 7096.685 | AP56: =IF(B56<DATE(2008,1,1),"",3929.06 + 1212.53*I56 - 0.0003097*N56 + 59.426*V56 - 0.0006734*E56 - 1.036*AD56 + 1.2076*AE56 + 94.923*AF56 - 131.43*AC56 - 759.61*IF(AND(B56>=DATE(2020,3,20),B56<=DATE(2020,6,26)),1,0) - 17.324*(I56*V56)) | AQ56: =IF(N56="","",I56*N56) -> 174682.6 | AR56: =I56*E56 -> 450906 | AS56: =AC56*AF56 -> 0 | AT56: =IF(N56="","",2413.3773+89.103503*I56+0.018847679*N56-5.0917058*V56-0.00064564578*E56+1.4315076*AD56-3.1976817*AE56-66.972905*AC56-217.08397*IF(AND(B56>=DATE(2020,3,20),B56<=DATE(2020,6,26)),1,0)+190.76803*AF56) -> 7275.4789 | AU56: =IF(N56="","",-480.76297+2186.3009*I56+0.033368804*N56-5.3903106*V56-0.00073731439*E56+0.93396876*AD56-1.6242981*AE56-61.304389*AC56-95.472727*IF(AND(B56>=DATE(2020,3,20),B56<=DATE(2020,6,26)),1,0)+156.04851*AF56-0.0087322858*AQ56) -> 6984.6202 | AV56: =IF(N56="","",2518.0489-204.66184*I56+0.019354281*N56-2.3328708*V56-0.0022533804*E56+1.5259709*AD56-3.5842757*AE56-65.580099*AC56-62.828483*IF(AND(B56>=DATE(2020,3,20),B56<=DATE(2020,6,26)),1,0)+200.94286*AF56+0.00080379976*AR56) -> 7168.0201 | AW56: =IF(N56="","",2361.7153+89.223162*I56+0.018847054*N56-5.0210815*V56-0.0006437347*E56+1.4213619*AD56-3.2156123*AE56+167.41121*AC56-224.35191*IF(AND(B56>=DATE(2020,3,20),B56<=DATE(2020,6,26)),1,0)+194.56435*AF56-19.897843*AS56) -> 7270.1661 | AX56: =IF(N56="","",-654.03928+2464.5589*I56+0.035956453*N56-8.0754527*V56-0.00069441316*E56+0.69511606*AD56-1.1669613*AE56-90.724569*AC56-211.24919*IF(AND(B56>=DATE(2020,3,20),B56<=DATE(2020,6,26)),1,0)+147.22132*AF56-0.010108087*AQ56) -> 6969.2925
A57: 56 | B57: 33662 | C57: 6770 | E57: 436000 | G57: 18.514 | H57: 17.422 | I57: 1.014 | J57: 6264.54 | L57: 796 | M57: 12.591 | N57: 172782 | O57: 4020.5 | P57: 818093 | U57: 28 | V57: 83.7 | AC57: 0 | AD57: 113.2 | AE57: 0 | AF57: 11.0293 | AG57: =6753.47943187+0.36116788*I57+0.01252571*N57-22.85359542*V57+0.00407811*AA57-0.00067349*E57 -> 6711.5753 | AH57: =A57*'Simple Linear Regression'!$B$18+'Simple Linear Regression'!$B$17 -> 7933.1064 | AI57: =7491.3971+0.0137554*N57-0.00058829*E57-34.3283*V57+0.30565*L57+54.6031*M57 -> 7669.1145 | AJ57: =7491.3971-0.00058829*E57+0.30565*L57+54.6031*M57+0.0137554*N57-34.3283*V57 -> 7669.1145 | AL57: =2192.59+2373.87*I57+0.0316653*N57-15.7623*V57+0.00202406*AA57-0.000740146*E57-0.00963493*(I57*N57) -> 6740.831 | AM57: =5205.907083+122.0638992*I57+13.609808*(N57/1000)-1.245906883*AD57+0.7746840854*AE57-134.2474226*AC57-1547.125689*IF(AND(B57>=DATE(2020,3,20),B57<=DATE(2020,6,26)),1,0) -> 7540.1731 | AN57: =7707.2178-144.397321*AC57+139.5614087*AF57-0.0008594506251*E57-265.7105668*I57-0.02506176117*J57+0.004708026652*N57 -> 9258.7933 | AO57: =IF(N57="","",2190.39 + 2739.06*I57 + 0.034693*N57 - 16.722*V57 - 0.000802*E57 - 1.3691*AD57 + 1.8691*AE57 - 121.7*AC57 + 209.88*IF(AND(B57>=DATE(2020,3,20),B57<=DATE(2020,6,26)),1,0) - 0.011049*(I57*N57)) -> 7122.042 | AP57: =IF(B57<DATE(2008,1,1),"",3929.06 + 1212.53*I57 - 0.0003097*N57 + 59.426*V57 - 0.0006734*E57 - 1.036*AD57 + 1.2076*AE57 + 94.923*AF57 - 131.43*AC57 - 759.61*IF(AND(B57>=DATE(2020,3,20),B57<=DATE(2020,6,26)),1,0) - 17.324*(I57*V57)) | AQ57: =IF(N57="","",I57*N57) -> 175200.95 | AR57: =I57*E57 -> 442104 | AS57: =AC57*AF57 -> 0 | AT57: =IF(N57="","",2413.3773+89.103503*I57+0.018847679*N57-5.0917058*V57-0.00064564578*E57+1.4315076*AD57-3.1976817*AE57-66.972905*AC57-217.08397*IF(AND(B57>=DATE(2020,3,20),B57<=DATE(2020,6,26)),1,0)+190.76803*AF57) -> 7318.6751 | AU57: =IF(N57="","",-480.76297+2186.3009*I57+0.033368804*N57-5.3903106*V57-0.00073731439*E57+0.93396876*AD57-1.6242981*AE57-61.304389*AC57-95.472727*IF(AND(B57>=DATE(2020,3,20),B57<=DATE(2020,6,26)),1,0)+156.04851*AF57-0.0087322858*AQ57) -> 7025.9631 | AV57: =IF(N57="","",2518.0489-204.66184*I57+0.019354281*N57-2.3328708*V57-0.0022533804*E57+1.5259709*AD57-3.5842757*AE57-65.580099*AC57-62.828483*IF(AND(B57>=DATE(2020,3,20),B57<=DATE(2020,6,26)),1,0)+200.94286*AF57+0.00080379976*AR57) -> 7221.2201 | AW57: =IF(N57="","",2361.7153+89.223162*I57+0.018847054*N57-5.0210815*V57-0.0006437347*E57+1.4213619*AD57-3.2156123*AE57+167.41121*AC57-224.35191*IF(AND(B57>=DATE(2020,3,20),B57<=DATE(2020,6,26)),1,0)+194.56435*AF57-19.897843*AS57) -> 7314.4932 | AX57: =IF(N57="","",-654.03928+2464.5589*I57+0.035956453*N57-8.0754527*V57-0.00069441316*E57+0.69511606*AD57-1.1669613*AE57-90.724569*AC57-211.24919*IF(AND(B57>=DATE(2020,3,20),B57<=DATE(2020,6,26)),1,0)+147.22132*AF57-0.010108087*AQ57) -> 7010.4606
A58: 57 | B58: 33669 | C58: 7002 | E58: 444000 | G58: 18.552 | H58: 17.282 | I58: 1.012 | J58: 6264.54 | L58: 796 | M58: 12.591 | N58: 172782 | O58: 4020.5 | P58: 818093 | U58: 28 | V58: 86.6 | AA58: 253530 | AC58: 0 | AD58: 104.3 | AE58: 1.5 | AF58: 11.3065 | AG58: =6753.47943187+0.36116788*I58+0.01252571*N58-22.85359542*V58+0.00407811*AA58-0.00067349*E58 -> 7673.8345 | AH58: =A58*'Simple Linear Regression'!$B$18+'Simple Linear Regression'!$B$17 -> 7933.9595 | AI58: =7491.3971+0.0137554*N58-0.00058829*E58-34.3283*V58+0.30565*L58+54.6031*M58 -> 7564.8561 | AJ58: =7491.3971-0.00058829*E58+0.30565*L58+54.6031*M58+0.0137554*N58-34.3283*V58 -> 7564.8561 | AL58: =2192.59+2373.87*I58+0.0316653*N58-15.7623*V58+0.00202406*AA58-0.000740146*E58-0.00963493*(I58*N58) -> 7200.9408 | AM58: =5205.907083+122.0638992*I58+13.609808*(N58/1000)-1.245906883*AD58+0.7746840854*AE58-134.2474226*AC58-1547.125689*IF(AND(B58>=DATE(2020,3,20),B58<=DATE(2020,6,26)),1,0) -> 7552.1795 | AN58: =7707.2178-144.397321*AC58+139.5614087*AF58-0.0008594506251*E58-265.7105668*I58-0.02506176117*J58+0.004708026652*N58 -> 9291.1356 | AO58: =IF(N58="","",2190.39 + 2739.06*I58 + 0.034693*N58 - 16.722*V58 - 0.000802*E58 - 1.3691*AD58 + 1.8691*AE58 - 121.7*AC58 + 209.88*IF(AND(B58>=DATE(2020,3,20),B58<=DATE(2020,6,26)),1,0) - 0.011049*(I58*N58)) -> 7080.4608 | AP58: =IF(B58<DATE(2008,1,1),"",3929.06 + 1212.53*I58 - 0.0003097*N58 + 59.426*V58 - 0.0006734*E58 - 1.036*AD58 + 1.2076*AE58 + 94.923*AF58 - 131.43*AC58 - 759.61*IF(AND(B58>=DATE(2020,3,20),B58<=DATE(2020,6,26)),1,0) - 17.324*(I58*V58)) | AQ58: =IF(N58="","",I58*N58) -> 174855.38 | AR58: =I58*E58 -> 449328 | AS58: =AC58*AF58 -> 0 | AT58: =IF(N58="","",2413.3773+89.103503*I58+0.018847679*N58-5.0917058*V58-0.00064564578*E58+1.4315076*AD58-3.1976817*AE58-66.972905*AC58-217.08397*IF(AND(B58>=DATE(2020,3,20),B58<=DATE(2020,6,26)),1,0)+190.76803*AF58) -> 7333.9097 | AU58: =IF(N58="","",-480.76297+2186.3009*I58+0.033368804*N58-5.3903106*V58-0.00073731439*E58+0.93396876*AD58-1.6242981*AE58-61.304389*AC58-95.472727*IF(AND(B58>=DATE(2020,3,20),B58<=DATE(2020,6,26)),1,0)+156.04851*AF58-0.0087322858*AQ58) -> 7035.5855 | AV58: =IF(N58="","",2518.0489-204.66184*I58+0.019354281*N58-2.3328708*V58-0.0022533804*E58+1.5259709*AD58-3.5842757*AE58-65.580099*AC58-62.828483*IF(AND(B58>=DATE(2020,3,20),B58<=DATE(2020,6,26)),1,0)+200.94286*AF58+0.00080379976*AR58) -> 7239.3875 | AW58: =IF(N58="","",2361.7153+89.223162*I58+0.018847054*N58-5.0210815*V58-0.0006437347*E58+1.4213619*AD58-3.2156123*AE58+167.41121*AC58-224.35191*IF(AND(B58>=DATE(2020,3,20),B58<=DATE(2020,6,26)),1,0)+194.56435*AF58-19.897843*AS58) -> 7331.0634 | AX58: =IF(N58="","",-654.03928+2464.5589*I58+0.035956453*N58-8.0754527*V58-0.00069441316*E58+0.69511606*AD58-1.1669613*AE58-90.724569*AC58-211.24919*IF(AND(B58>=DATE(2020,3,20),B58<=DATE(2020,6,26)),1,0)+147.22132*AF58-0.010108087*AQ58) -> 7012.9231
A59: 58 | B59: 33676 | C59: 6806 | E59: 421000 | G59: 18.758 | H59: 17.396 | I59: 1.013 | J59: 6264.54 | L59: 710 | M59: 12.591 | N59: 172782 | O59: 4084.7 | P59: 818093 | U59: 28 | V59: 86.6 | AA59: 253530 | AC59: 0 | AD59: 123.5 | AE59: 2 | AF59: 11.5898 | AG59: =6753.47943187+0.36116788*I59+0.01252571*N59-22.85359542*V59+0.00407811*AA59-0.00067349*E59 -> 7689.3251 | AH59: =A59*'Simple Linear Regression'!$B$18+'Simple Linear Regression'!$B$17 -> 7934.8125 | AI59: =7491.3971+0.0137554*N59-0.00058829*E59-34.3283*V59+0.30565*L59+54.6031*M59 -> 7552.1009 | AJ59: =7491.3971-0.00058829*E59+0.30565*L59+54.6031*M59+0.0137554*N59-34.3283*V59 -> 7552.1009 | AL59: =2192.59+2373.87*I59+0.0316653*N59-15.7623*V59+0.00202406*AA59-0.000740146*E59-0.00963493*(I59*N59) -> 7218.6733 | AM59: =5205.907083+122.0638992*I59+13.609808*(N59/1000)-1.245906883*AD59+0.7746840854*AE59-134.2474226*AC59-1547.125689*IF(AND(B59>=DATE(2020,3,20),B59<=DATE(2020,6,26)),1,0) -> 7528.7675 | AN59: =7707.2178-144.397321*AC59+139.5614087*AF59-0.0008594506251*E59-265.7105668*I59-0.02506176117*J59+0.004708026652*N59 -> 9350.175 | AO59: =IF(N59="","",2190.39 + 2739.06*I59 + 0.034693*N59 - 16.722*V59 - 0.000802*E59 - 1.3691*AD59 + 1.8691*AE59 - 121.7*AC59 + 209.88*IF(AND(B59>=DATE(2020,3,20),B59<=DATE(2020,6,26)),1,0) - 0.011049*(I59*N59)) -> 7074.3846 | AP59: =IF(B59<DATE(2008,1,1),"",3929.06 + 1212.53*I59 - 0.0003097*N59 + 59.426*V59 - 0.0006734*E59 - 1.036*AD59 + 1.2076*AE59 + 94.923*AF59 - 131.43*AC59 - 759.61*IF(AND(B59>=DATE(2020,3,20),B59<=DATE(2020,6,26)),1,0) - 17.324*(I59*V59)) | AQ59: =IF(N59="","",I59*N59) -> 175028.17 | AR59: =I59*E59 -> 426473 | AS59: =AC59*AF59 -> 0 | AT59: =IF(N59="","",2413.3773+89.103503*I59+0.018847679*N59-5.0917058*V59-0.00064564578*E59+1.4315076*AD59-3.1976817*AE59-66.972905*AC59-217.08397*IF(AND(B59>=DATE(2020,3,20),B59<=DATE(2020,6,26)),1,0)+190.76803*AF59) -> 7428.7794 | AU59: =IF(N59="","",-480.76297+2186.3009*I59+0.033368804*N59-5.3903106*V59-0.00073731439*E59+0.93396876*AD59-1.6242981*AE59-61.304389*AC59-95.472727*IF(AND(B59>=DATE(2020,3,20),B59<=DATE(2020,6,26)),1,0)+156.04851*AF59-0.0087322858*AQ59) -> 7114.5499 | AV59: =IF(N59="","",2518.0489-204.66184*I59+0.019354281*N59-2.3328708*V59-0.0022533804*E59+1.5259709*AD59-3.5842757*AE59-65.580099*AC59-62.828483*IF(AND(B59>=DATE(2020,3,20),B59<=DATE(2020,6,26)),1,0)+200.94286*AF59+0.00080379976*AR59) -> 7357.0734 | AW59: =IF(N59="","",2361.7153+89.223162*I59+0.018847054*N59-5.0210815*V59-0.0006437347*E59+1.4213619*AD59-3.2156123*AE59+167.41121*AC59-224.35191*IF(AND(B59>=DATE(2020,3,20),B59<=DATE(2020,6,26)),1,0)+194.56435*AF59-19.897843*AS59) -> 7426.761 | AX59: =IF(N59="","",-654.03928+2464.5589*I59+0.035956453*N59-8.0754527*V59-0.00069441316*E59+0.69511606*AD59-1.1669613*AE59-90.724569*AC59-211.24919*IF(AND(B59>=DATE(2020,3,20),B59<=DATE(2020,6,26)),1,0)+147.22132*AF59-0.010108087*AQ59) -> 7084.0832
A60: 59 | B60: 33683 | C60: 7221 | E60: 437000 | G60: 19.104 | H60: 17.732 | I60: 1.01 | J60: 6264.54 | L60: 710 | M60: 12.927 | N60: 167652 | O60: 4084.7 | P60: 815581 | U60: 28 | V60: 86.6 | AA60: 253530 | AC60: 0 | AD60: 138.5 | AE60: 1.6 | AF60: 11.8766 | AG60: =6753.47943187+0.36116788*I60+0.01252571*N60-22.85359542*V60+0.00407811*AA60-0.00067349*E60 -> 7614.2913 | AH60: =A60*'Simple Linear Regression'!$B$18+'Simple Linear Regression'!$B$17 -> 7935.6655 | AI60: =7491.3971+0.0137554*N60-0.00058829*E60-34.3283*V60+0.30565*L60+54.6031*M60 -> 7490.4697 | AJ60: =7491.3971-0.00058829*E60+0.30565*L60+54.6031*M60+0.0137554*N60-34.3283*V60 -> 7490.4697 | AL60: =2192.59+2373.87*I60+0.0316653*N60-15.7623*V60+0.00202406*AA60-0.000740146*E60-0.00963493*(I60*N60) -> 7092.1821 | AM60: =5205.907083+122.0638992*I60+13.609808*(N60/1000)-1.245906883*AD60+0.7746840854*AE60-134.2474226*AC60-1547.125689*IF(AND(B60>=DATE(2020,3,20),B60<=DATE(2020,6,26)),1,0) -> 7439.5845 | AN60: =7707.2178-144.397321*AC60+139.5614087*AF60-0.0008594506251*E60-265.7105668*I60-0.02506176117*J60+0.004708026652*N60 -> 9353.0949 | AO60: =IF(N60="","",2190.39 + 2739.06*I60 + 0.034693*N60 - 16.722*V60 - 0.000802*E60 - 1.3691*AD60 + 1.8691*AE60 - 121.7*AC60 + 209.88*IF(AND(B60>=DATE(2020,3,20),B60<=DATE(2020,6,26)),1,0) - 0.011049*(I60*N60)) -> 6917.0516 | AP60: =IF(B60<DATE(2008,1,1),"",3929.06 + 1212.53*I60 - 0.0003097*N60 + 59.426*V60 - 0.0006734*E60 - 1.036*AD60 + 1.2076*AE60 + 94.923*AF60 - 131.43*AC60 - 759.61*IF(AND(B60>=DATE(2020,3,20),B60<=DATE(2020,6,26)),1,0) - 17.324*(I60*V60)) | AQ60: =IF(N60="","",I60*N60) -> 169328.52 | AR60: =I60*E60 -> 441370 | AS60: =AC60*AF60 -> 0 | AT60: =IF(N60="","",2413.3773+89.103503*I60+0.018847679*N60-5.0917058*V60-0.00064564578*E60+1.4315076*AD60-3.1976817*AE60-66.972905*AC60-217.08397*IF(AND(B60>=DATE(2020,3,20),B60<=DATE(2020,6,26)),1,0)+190.76803*AF60) -> 7398.9571 | AU60: =IF(N60="","",-480.76297+2186.3009*I60+0.033368804*N60-5.3903106*V60-0.00073731439*E60+0.93396876*AD60-1.6242981*AE60-61.304389*AC60-95.472727*IF(AND(B60>=DATE(2020,3,20),B60<=DATE(2020,6,26)),1,0)+156.04851*AF60-0.0087322858*AQ60) -> 7034.1969 | AV60: =IF(N60="","",2518.0489-204.66184*I60+0.019354281*N60-2.3328708*V60-0.0022533804*E60+1.5259709*AD60-3.5842757*AE60-65.580099*AC60-62.828483*IF(AND(B60>=DATE(2020,3,20),B60<=DATE(2020,6,26)),1,0)+200.94286*AF60+0.00080379976*AR60) -> 7316.2737 | AW60: =IF(N60="","",2361.7153+89.223162*I60+0.018847054*N60-5.0210815*V60-0.0006437347*E60+1.4213619*AD60-3.2156123*AE60+167.41121*AC60-224.35191*IF(AND(B60>=DATE(2020,3,20),B60<=DATE(2020,6,26)),1,0)+194.56435*AF60-19.897843*AS60) -> 7397.9159 | AX60: =IF(N60="","",-654.03928+2464.5589*I60+0.035956453*N60-8.0754527*V60-0.00069441316*E60+0.69511606*AD60-1.1669613*AE60-90.724569*AC60-211.24919*IF(AND(B60>=DATE(2020,3,20),B60<=DATE(2020,6,26)),1,0)+147.22132*AF60-0.010108087*AQ60) -> 6991.8515
A61: 60 | B61: 33690 | C61: 7379 | E61: 440000 | G61: 19.094 | H61: 17.752 | I61: 1.015 | J61: 6264.54 | L61: 710 | M61: 12.927 | N61: 167652 | O61: 4084.7 | P61: 815581 | U61: 28 | V61: 86.6 | AA61: 253530 | AC61: 0 | AD61: 133.6 | AE61: 0.6 | AF61: 12.1645 | AG61: =6753.47943187+0.36116788*I61+0.01252571*N61-22.85359542*V61+0.00407811*AA61-0.00067349*E61 -> 7612.2726 | AH61: =A61*'Simple Linear Regression'!$B$18+'Simple Linear Regression'!$B$17 -> 7936.5186 | AI61: =7491.3971+0.0137554*N61-0.00058829*E61-34.3283*V61+0.30565*L61+54.6031*M61 -> 7488.7048 | AJ61: =7491.3971-0.00058829*E61+0.30565*L61+54.6031*M61+0.0137554*N61-34.3283*V61 -> 7488.7048 | AL61: =2192.59+2373.87*I61+0.0316653*N61-15.7623*V61+0.00202406*AA61-0.000740146*E61-0.00963493*(I61*N61) -> 7093.7544 | AM61: =5205.907083+122.0638992*I61+13.609808*(N61/1000)-1.245906883*AD61+0.7746840854*AE61-134.2474226*AC61-1547.125689*IF(AND(B61>=DATE(2020,3,20),B61<=DATE(2020,6,26)),1,0) -> 7445.5251 | AN61: =7707.2178-144.397321*AC61+139.5614087*AF61-0.0008594506251*E61-265.7105668*I61-0.02506176117*J61+0.004708026652*N61 -> 9389.3677 | AO61: =IF(N61="","",2190.39 + 2739.06*I61 + 0.034693*N61 - 16.722*V61 - 0.000802*E61 - 1.3691*AD61 + 1.8691*AE61 - 121.7*AC61 + 209.88*IF(AND(B61>=DATE(2020,3,20),B61<=DATE(2020,6,26)),1,0) - 0.011049*(I61*N61)) -> 6923.9185 | AP61: =IF(B61<DATE(2008,1,1),"",3929.06 + 1212.53*I61 - 0.0003097*N61 + 59.426*V61 - 0.0006734*E61 - 1.036*AD61 + 1.2076*AE61 + 94.923*AF61 - 131.43*AC61 - 759.61*IF(AND(B61>=DATE(2020,3,20),B61<=DATE(2020,6,26)),1,0) - 17.324*(I61*V61)) | AQ61: =IF(N61="","",I61*N61) -> 170166.78 | AR61: =I61*E61 -> 446600 | AS61: =AC61*AF61 -> 0 | AT61: =IF(N61="","",2413.3773+89.103503*I61+0.018847679*N61-5.0917058*V61-0.00064564578*E61+1.4315076*AD61-3.1976817*AE61-66.972905*AC61-217.08397*IF(AND(B61>=DATE(2020,3,20),B61<=DATE(2020,6,26)),1,0)+190.76803*AF61) -> 7448.5711 | AU61: =IF(N61="","",-480.76297+2186.3009*I61+0.033368804*N61-5.3903106*V61-0.00073731439*E61+0.93396876*AD61-1.6242981*AE61-61.304389*AC61-95.472727*IF(AND(B61>=DATE(2020,3,20),B61<=DATE(2020,6,26)),1,0)+156.04851*AF61-0.0087322858*AQ61) -> 7077.5707 | AV61: =IF(N61="","",2518.0489-204.66184*I61+0.019354281*N61-2.3328708*V61-0.0022533804*E61+1.5259709*AD61-3.5842757*AE61-65.580099*AC61-62.828483*IF(AND(B61>=DATE(2020,3,20),B61<=DATE(2020,6,26)),1,0)+200.94286*AF61+0.00080379976*AR61) -> 7366.6526 | AW61: =IF(N61="","",2361.7153+89.223162*I61+0.018847054*N61-5.0210815*V61-0.0006437347*E61+1.4213619*AD61-3.2156123*AE61+167.41121*AC61-224.35191*IF(AND(B61>=DATE(2020,3,20),B61<=DATE(2020,6,26)),1,0)+194.56435*AF61-19.897843*AS61) -> 7448.6968 | AX61: =IF(N61="","",-654.03928+2464.5589*I61+0.035956453*N61-8.0754527*V61-0.00069441316*E61+0.69511606*AD61-1.1669613*AE61-90.724569*AC61-211.24919*IF(AND(B61>=DATE(2020,3,20),B61<=DATE(2020,6,26)),1,0)+147.22132*AF61-0.010108087*AQ61) -> 7033.7637
A62: 61 | B62: 33697 | C62: 7027 | E62: 420000 | G62: 19.726 | H62: 18.522 | I62: 1.013 | J62: 6264.54 | L62: 710 | M62: 12.927 | N62: 167652 | O62: 4084.7 | P62: 815581 | U62: 28 | V62: 86.6 | AA62: 253530 | AC62: 0 | AD62: 117 | AE62: 0.7 | AF62: 12.4509 | AG62: =6753.47943187+0.36116788*I62+0.01252571*N62-22.85359542*V62+0.00407811*AA62-0.00067349*E62 -> 7625.7417 | AH62: =A62*'Simple Linear Regression'!$B$18+'Simple Linear Regression'!$B$17 -> 7937.3716 | AI62: =7491.3971+0.0137554*N62-0.00058829*E62-34.3283*V62+0.30565*L62+54.6031*M62 -> 7500.4706 | AJ62: =7491.3971-0.00058829*E62+0.30565*L62+54.6031*M62+0.0137554*N62-34.3283*V62 -> 7500.4706 | AL62: =2192.59+2373.87*I62+0.0316653*N62-15.7623*V62+0.00202406*AA62-0.000740146*E62-0.00963493*(I62*N62) -> 7107.0402 | AM62: =5205.907083+122.0638992*I62+13.609808*(N62/1000)-1.245906883*AD62+0.7746840854*AE62-134.2474226*AC62-1547.125689*IF(AND(B62>=DATE(2020,3,20),B62<=DATE(2020,6,26)),1,0) -> 7466.0405 | AN62: =7707.2178-144.397321*AC62+139.5614087*AF62-0.0008594506251*E62-265.7105668*I62-0.02506176117*J62+0.004708026652*N62 -> 9447.0586 | AO62: =IF(N62="","",2190.39 + 2739.06*I62 + 0.034693*N62 - 16.722*V62 - 0.000802*E62 - 1.3691*AD62 + 1.8691*AE62 - 121.7*AC62 + 209.88*IF(AND(B62>=DATE(2020,3,20),B62<=DATE(2020,6,26)),1,0) - 0.011049*(I62*N62)) -> 6961.0991 | AP62: =IF(B62<DATE(2008,1,1),"",3929.06 + 1212.53*I62 - 0.0003097*N62 + 59.426*V62 - 0.0006734*E62 - 1.036*AD62 + 1.2076*AE62 + 94.923*AF62 - 131.43*AC62 - 759.61*IF(AND(B62>=DATE(2020,3,20),B62<=DATE(2020,6,26)),1,0) - 17.324*(I62*V62)) | AQ62: =IF(N62="","",I62*N62) -> 169831.48 | AR62: =I62*E62 -> 425460 | AS62: =AC62*AF62 -> 0 | AT62: =IF(N62="","",2413.3773+89.103503*I62+0.018847679*N62-5.0917058*V62-0.00064564578*E62+1.4315076*AD62-3.1976817*AE62-66.972905*AC62-217.08397*IF(AND(B62>=DATE(2020,3,20),B62<=DATE(2020,6,26)),1,0)+190.76803*AF62) -> 7491.859 | AU62: =IF(N62="","",-480.76297+2186.3009*I62+0.033368804*N62-5.3903106*V62-0.00073731439*E62+0.93396876*AD62-1.6242981*AE62-61.304389*AC62-95.472727*IF(AND(B62>=DATE(2020,3,20),B62<=DATE(2020,6,26)),1,0)+156.04851*AF62-0.0087322858*AQ62) -> 7119.8984 | AV62: =IF(N62="","",2518.0489-204.66184*I62+0.019354281*N62-2.3328708*V62-0.0022533804*E62+1.5259709*AD62-3.5842757*AE62-65.580099*AC62-62.828483*IF(AND(B62>=DATE(2020,3,20),B62<=DATE(2020,6,26)),1,0)+200.94286*AF62+0.00080379976*AR62) -> 7426.9977 | AW62: =IF(N62="","",2361.7153+89.223162*I62+0.018847054*N62-5.0210815*V62-0.0006437347*E62+1.4213619*AD62-3.2156123*AE62+167.41121*AC62-224.35191*IF(AND(B62>=DATE(2020,3,20),B62<=DATE(2020,6,26)),1,0)+194.56435*AF62-19.897843*AS62) -> 7493.2001 | AX62: =IF(N62="","",-654.03928+2464.5589*I62+0.035956453*N62-8.0754527*V62-0.00069441316*E62+0.69511606*AD62-1.1669613*AE62-90.724569*AC62-211.24919*IF(AND(B62>=DATE(2020,3,20),B62<=DATE(2020,6,26)),1,0)+147.22132*AF62-0.010108087*AQ62) -> 7076.6207
A63: 62 | B63: 33704 | C63: 7744 | E63: 412000 | G63: 20.43 | H63: 19.008 | I63: 1.026 | J63: 6264.54 | L63: 669 | M63: 12.927 | N63: 167652 | O63: 4099.5 | P63: 815581 | U63: 28 | V63: 83.4 | AA63: 253530 | AC63: 0 | AD63: 84.7 | AE63: 1.9 | AF63: 12.7335 | AG63: =6753.47943187+0.36116788*I63+0.01252571*N63-22.85359542*V63+0.00407811*AA63-0.00067349*E63 -> 7704.2658 | AH63: =A63*'Simple Linear Regression'!$B$18+'Simple Linear Regression'!$B$17 -> 7938.2246 | AI63: =7491.3971+0.0137554*N63-0.00058829*E63-34.3283*V63+0.30565*L63+54.6031*M63 -> 7602.4958 | AJ63: =7491.3971-0.00058829*E63+0.30565*L63+54.6031*M63+0.0137554*N63-34.3283*V63 -> 7602.4958 | AL63: =2192.59+2373.87*I63+0.0316653*N63-15.7623*V63+0.00202406*AA63-0.000740146*E63-0.00963493*(I63*N63) -> 7173.262 | AM63: =5205.907083+122.0638992*I63+13.609808*(N63/1000)-1.245906883*AD63+0.7746840854*AE63-134.2474226*AC63-1547.125689*IF(AND(B63>=DATE(2020,3,20),B63<=DATE(2020,6,26)),1,0) -> 7508.7998 | AN63: =7707.2178-144.397321*AC63+139.5614087*AF63-0.0008594506251*E63-265.7105668*I63-0.02506176117*J63+0.004708026652*N63 -> 9489.92 | AO63: =IF(N63="","",2190.39 + 2739.06*I63 + 0.034693*N63 - 16.722*V63 - 0.000802*E63 - 1.3691*AD63 + 1.8691*AE63 - 121.7*AC63 + 209.88*IF(AND(B63>=DATE(2020,3,20),B63<=DATE(2020,6,26)),1,0) - 0.011049*(I63*N63)) -> 7079.0171 | AP63: =IF(B63<DATE(2008,1,1),"",3929.06 + 1212.53*I63 - 0.0003097*N63 + 59.426*V63 - 0.0006734*E63 - 1.036*AD63 + 1.2076*AE63 + 94.923*AF63 - 131.43*AC63 - 759.61*IF(AND(B63>=DATE(2020,3,20),B63<=DATE(2020,6,26)),1,0) - 17.324*(I63*V63)) | AQ63: =IF(N63="","",I63*N63) -> 172010.95 | AR63: =I63*E63 -> 422712 | AS63: =AC63*AF63 -> 0 | AT63: =IF(N63="","",2413.3773+89.103503*I63+0.018847679*N63-5.0917058*V63-0.00064564578*E63+1.4315076*AD63-3.1976817*AE63-66.972905*AC63-217.08397*IF(AND(B63>=DATE(2020,3,20),B63<=DATE(2020,6,26)),1,0)+190.76803*AF63) -> 7518.3121 | AU63: =IF(N63="","",-480.76297+2186.3009*I63+0.033368804*N63-5.3903106*V63-0.00073731439*E63+0.93396876*AD63-1.6242981*AE63-61.304389*AC63-95.472727*IF(AND(B63>=DATE(2020,3,20),B63<=DATE(2020,6,26)),1,0)+156.04851*AF63-0.0087322858*AQ63) -> 7164.4189 | AV63: =IF(N63="","",2518.0489-204.66184*I63+0.019354281*N63-2.3328708*V63-0.0022533804*E63+1.5259709*AD63-3.5842757*AE63-65.580099*AC63-62.828483*IF(AND(B63>=DATE(2020,3,20),B63<=DATE(2020,6,26)),1,0)+200.94286*AF63+0.00080379976*AR63) -> 7450.8169 | AW63: =IF(N63="","",2361.7153+89.223162*I63+0.018847054*N63-5.0210815*V63-0.0006437347*E63+1.4213619*AD63-3.2156123*AE63+167.41121*AC63-224.35191*IF(AND(B63>=DATE(2020,3,20),B63<=DATE(2020,6,26)),1,0)+194.56435*AF63-19.897843*AS63) -> 7520.7925 | AX63: =IF(N63="","",-654.03928+2464.5589*I63+0.035956453*N63-8.0754527*V63-0.00069441316*E63+0.69511606*AD63-1.1669613*AE63-90.724569*AC63-211.24919*IF(AND(B63>=DATE(2020,3,20),B63<=DATE(2020,6,26)),1,0)+147.22132*AF63-0.010108087*AQ63) -> 7135.7785
A64: 63 | B64: 33711 | C64: 6464 | E64: 413000 | G64: 20.0575 | H64: 18.8575 | I64: 1.051 | J64: 6264.54 | L64: 669 | M64: 12.824 | N64: 160204 | O64: 4099.5 | P64: 815581 | U64: 28 | V64: 83.4 | AA64: 253530 | AC64: 0 | AD64: 70.2 | AE64: 10.5 | AF64: 13.0096 | AG64: =6753.47943187+0.36116788*I64+0.01252571*N64-22.85359542*V64+0.00407811*AA64-0.00067349*E64 -> 7610.3099 | AH64: =A64*'Simple Linear Regression'!$B$18+'Simple Linear Regression'!$B$17 -> 7939.0777 | AI64: =7491.3971+0.0137554*N64-0.00058829*E64-34.3283*V64+0.30565*L64+54.6031*M64 -> 7493.8332 | AJ64: =7491.3971-0.00058829*E64+0.30565*L64+54.6031*M64+0.0137554*N64-34.3283*V64 -> 7493.8332 | AL64: =2192.59+2373.87*I64+0.0316653*N64-15.7623*V64+0.00202406*AA64-0.000740146*E64-0.00963493*(I64*N64) -> 7031.0633 | AM64: =5205.907083+122.0638992*I64+13.609808*(N64/1000)-1.245906883*AD64+0.7746840854*AE64-134.2474226*AC64-1547.125689*IF(AND(B64>=DATE(2020,3,20),B64<=DATE(2020,6,26)),1,0) -> 7435.2134 | AN64: =7707.2178-144.397321*AC64+139.5614087*AF64-0.0008594506251*E64-265.7105668*I64-0.02506176117*J64+0.004708026652*N64 -> 9485.8853 | AO64: =IF(N64="","",2190.39 + 2739.06*I64 + 0.034693*N64 - 16.722*V64 - 0.000802*E64 - 1.3691*AD64 + 1.8691*AE64 - 121.7*AC64 + 209.88*IF(AND(B64>=DATE(2020,3,20),B64<=DATE(2020,6,26)),1,0) - 0.011049*(I64*N64)) -> 6964.4046 | AP64: =IF(B64<DATE(2008,1,1),"",3929.06 + 1212.53*I64 - 0.0003097*N64 + 59.426*V64 - 0.0006734*E64 - 1.036*AD64 + 1.2076*AE64 + 94.923*AF64 - 131.43*AC64 - 759.61*IF(AND(B64>=DATE(2020,3,20),B64<=DATE(2020,6,26)),1,0) - 17.324*(I64*V64)) | AQ64: =IF(N64="","",I64*N64) -> 168374.4 | AR64: =I64*E64 -> 434063 | AS64: =AC64*AF64 -> 0 | AT64: =IF(N64="","",2413.3773+89.103503*I64+0.018847679*N64-5.0917058*V64-0.00064564578*E64+1.4315076*AD64-3.1976817*AE64-66.972905*AC64-217.08397*IF(AND(B64>=DATE(2020,3,20),B64<=DATE(2020,6,26)),1,0)+190.76803*AF64) -> 7383.9306 | AU64: =IF(N64="","",-480.76297+2186.3009*I64+0.033368804*N64-5.3903106*V64-0.00073731439*E64+0.93396876*AD64-1.6242981*AE64-61.304389*AC64-95.472727*IF(AND(B64>=DATE(2020,3,20),B64<=DATE(2020,6,26)),1,0)+156.04851*AF64-0.0087322858*AQ64) -> 7017.1372 | AV64: =IF(N64="","",2518.0489-204.66184*I64+0.019354281*N64-2.3328708*V64-0.0022533804*E64+1.5259709*AD64-3.5842757*AE64-65.580099*AC64-62.828483*IF(AND(B64>=DATE(2020,3,20),B64<=DATE(2020,6,26)),1,0)+200.94286*AF64+0.00080379976*AR64) -> 7310.9492 | AW64: =IF(N64="","",2361.7153+89.223162*I64+0.018847054*N64-5.0210815*V64-0.0006437347*E64+1.4213619*AD64-3.2156123*AE64+167.41121*AC64-224.35191*IF(AND(B64>=DATE(2020,3,20),B64<=DATE(2020,6,26)),1,0)+194.56435*AF64-19.897843*AS64) -> 7387.4617 | AX64: =IF(N64="","",-654.03928+2464.5589*I64+0.035956453*N64-8.0754527*V64-0.00069441316*E64+0.69511606*AD64-1.1669613*AE64-90.724569*AC64-211.24919*IF(AND(B64>=DATE(2020,3,20),B64<=DATE(2020,6,26)),1,0)+147.22132*AF64-0.010108087*AQ64) -> 6986.1857
A65: 64 | B65: 33718 | C65: 7376 | E65: 424000 | G65: 20.062 | H65: 18.856 | I65: 1.058 | J65: 6264.54 | L65: 669 | M65: 12.824 | N65: 160204 | O65: 4099.5 | P65: 815581 | U65: 28 | V65: 83.4 | AA65: 253530 | AC65: 0 | AD65: 39.7 | AE65: 14.2 | AF65: 13.2761 | AG65: =6753.47943187+0.36116788*I65+0.01252571*N65-22.85359542*V65+0.00407811*AA65-0.00067349*E65 -> 7602.904 | AH65: =A65*'Simple Linear Regression'!$B$18+'Simple Linear Regression'!$B$17 -> 7939.9307 | AI65: =7491.3971+0.0137554*N65-0.00058829*E65-34.3283*V65+0.30565*L65+54.6031*M65 -> 7487.362 | AJ65: =7491.3971-0.00058829*E65+0.30565*L65+54.6031*M65+0.0137554*N65-34.3283*V65 -> 7487.362 | AL65: =2192.59+2373.87*I65+0.0316653*N65-15.7623*V65+0.00202406*AA65-0.000740146*E65-0.00963493*(I65*N65) -> 7028.7339 | AM65: =5205.907083+122.0638992*I65+13.609808*(N65/1000)-1.245906883*AD65+0.7746840854*AE65-134.2474226*AC65-1547.125689*IF(AND(B65>=DATE(2020,3,20),B65<=DATE(2020,6,26)),1,0) -> 7476.9344 | AN65: =7707.2178-144.397321*AC65+139.5614087*AF65-0.0008594506251*E65-265.7105668*I65-0.02506176117*J65+0.004708026652*N65 -> 9511.7645 | AO65: =IF(N65="","",2190.39 + 2739.06*I65 + 0.034693*N65 - 16.722*V65 - 0.000802*E65 - 1.3691*AD65 + 1.8691*AE65 - 121.7*AC65 + 209.88*IF(AND(B65>=DATE(2020,3,20),B65<=DATE(2020,6,26)),1,0) - 0.011049*(I65*N65)) -> 7011.0386 | AP65: =IF(B65<DATE(2008,1,1),"",3929.06 + 1212.53*I65 - 0.0003097*N65 + 59.426*V65 - 0.0006734*E65 - 1.036*AD65 + 1.2076*AE65 + 94.923*AF65 - 131.43*AC65 - 759.61*IF(AND(B65>=DATE(2020,3,20),B65<=DATE(2020,6,26)),1,0) - 17.324*(I65*V65)) | AQ65: =IF(N65="","",I65*N65) -> 169495.83 | AR65: =I65*E65 -> 448592 | AS65: =AC65*AF65 -> 0 | AT65: =IF(N65="","",2413.3773+89.103503*I65+0.018847679*N65-5.0917058*V65-0.00064564578*E65+1.4315076*AD65-3.1976817*AE65-66.972905*AC65-217.08397*IF(AND(B65>=DATE(2020,3,20),B65<=DATE(2020,6,26)),1,0)+190.76803*AF65) -> 7372.7995 | AU65: =IF(N65="","",-480.76297+2186.3009*I65+0.033368804*N65-5.3903106*V65-0.00073731439*E65+0.93396876*AD65-1.6242981*AE65-61.304389*AC65-95.472727*IF(AND(B65>=DATE(2020,3,20),B65<=DATE(2020,6,26)),1,0)+156.04851*AF65-0.0087322858*AQ65) -> 7021.6292 | AV65: =IF(N65="","",2518.0489-204.66184*I65+0.019354281*N65-2.3328708*V65-0.0022533804*E65+1.5259709*AD65-3.5842757*AE65-65.580099*AC65-62.828483*IF(AND(B65>=DATE(2020,3,20),B65<=DATE(2020,6,26)),1,0)+200.94286*AF65+0.00080379976*AR65) -> 7290.1552 | AW65: =IF(N65="","",2361.7153+89.223162*I65+0.018847054*N65-5.0210815*V65-0.0006437347*E65+1.4213619*AD65-3.2156123*AE65+167.41121*AC65-224.35191*IF(AND(B65>=DATE(2020,3,20),B65<=DATE(2020,6,26)),1,0)+194.56435*AF65-19.897843*AS65) -> 7377.6073 | AX65: =IF(N65="","",-654.03928+2464.5589*I65+0.035956453*N65-8.0754527*V65-0.00069441316*E65+0.69511606*AD65-1.1669613*AE65-90.724569*AC65-211.24919*IF(AND(B65>=DATE(2020,3,20),B65<=DATE(2020,6,26)),1,0)+147.22132*AF65-0.010108087*AQ65) -> 6998.1793
A66: 65 | B66: 33725 | C66: 7899 | E66: 424000 | G66: 20.626 | H66: 19.368 | I66: 1.072 | J66: 6264.54 | L66: 669 | M66: 12.824 | N66: 160204 | O66: 4099.5 | P66: 815581 | U66: 28 | V66: 83.4 | AA66: 253530 | AC66: 0 | AD66: 63.2 | AE66: 15.2 | AF66: 13.5295 | AG66: =6753.47943187+0.36116788*I66+0.01252571*N66-22.85359542*V66+0.00407811*AA66-0.00067349*E66 -> 7602.9091 | AH66: =A66*'Simple Linear Regression'!$B$18+'Simple Linear Regression'!$B$17 -> 7940.7838 | AI66: =7491.3971+0.0137554*N66-0.00058829*E66-34.3283*V66+0.30565*L66+54.6031*M66 -> 7487.362 | AJ66: =7491.3971-0.00058829*E66+0.30565*L66+54.6031*M66+0.0137554*N66-34.3283*V66 -> 7487.362 | AL66: =2192.59+2373.87*I66+0.0316653*N66-15.7623*V66+0.00202406*AA66-0.000740146*E66-0.00963493*(I66*N66) -> 7040.3583 | AM66: =5205.907083+122.0638992*I66+13.609808*(N66/1000)-1.245906883*AD66+0.7746840854*AE66-134.2474226*AC66-1547.125689*IF(AND(B66>=DATE(2020,3,20),B66<=DATE(2020,6,26)),1,0) -> 7450.1391 | AN66: =7707.2178-144.397321*AC66+139.5614087*AF66-0.0008594506251*E66-265.7105668*I66-0.02506176117*J66+0.004708026652*N66 -> 9543.4094 | AO66: =IF(N66="","",2190.39 + 2739.06*I66 + 0.034693*N66 - 16.722*V66 - 0.000802*E66 - 1.3691*AD66 + 1.8691*AE66 - 121.7*AC66 + 209.88*IF(AND(B66>=DATE(2020,3,20),B66<=DATE(2020,6,26)),1,0) - 0.011049*(I66*N66)) -> 6994.2993 | AP66: =IF(B66<DATE(2008,1,1),"",3929.06 + 1212.53*I66 - 0.0003097*N66 + 59.426*V66 - 0.0006734*E66 - 1.036*AD66 + 1.2076*AE66 + 94.923*AF66 - 131.43*AC66 - 759.61*IF(AND(B66>=DATE(2020,3,20),B66<=DATE(2020,6,26)),1,0) - 17.324*(I66*V66)) | AQ66: =IF(N66="","",I66*N66) -> 171738.69 | AR66: =I66*E66 -> 454528 | AS66: =AC66*AF66 -> 0 | AT66: =IF(N66="","",2413.3773+89.103503*I66+0.018847679*N66-5.0917058*V66-0.00064564578*E66+1.4315076*AD66-3.1976817*AE66-66.972905*AC66-217.08397*IF(AND(B66>=DATE(2020,3,20),B66<=DATE(2020,6,26)),1,0)+190.76803*AF66) -> 7452.8303 | AU66: =IF(N66="","",-480.76297+2186.3009*I66+0.033368804*N66-5.3903106*V66-0.00073731439*E66+0.93396876*AD66-1.6242981*AE66-61.304389*AC66-95.472727*IF(AND(B66>=DATE(2020,3,20),B66<=DATE(2020,6,26)),1,0)+156.04851*AF66-0.0087322858*AQ66) -> 7092.5188 | AV66: =IF(N66="","",2518.0489-204.66184*I66+0.019354281*N66-2.3328708*V66-0.0022533804*E66+1.5259709*AD66-3.5842757*AE66-65.580099*AC66-62.828483*IF(AND(B66>=DATE(2020,3,20),B66<=DATE(2020,6,26)),1,0)+200.94286*AF66+0.00080379976*AR66) -> 7375.2562 | AW66: =IF(N66="","",2361.7153+89.223162*I66+0.018847054*N66-5.0210815*V66-0.0006437347*E66+1.4213619*AD66-3.2156123*AE66+167.41121*AC66-224.35191*IF(AND(B66>=DATE(2020,3,20),B66<=DATE(2020,6,26)),1,0)+194.56435*AF66-19.897843*AS66) -> 7458.3454 | AX66: =IF(N66="","",-654.03928+2464.5589*I66+0.035956453*N66-8.0754527*V66-0.00069441316*E66+0.69511606*AD66-1.1669613*AE66-90.724569*AC66-211.24919*IF(AND(B66>=DATE(2020,3,20),B66<=DATE(2020,6,26)),1,0)+147.22132*AF66-0.010108087*AQ66) -> 7062.4863
A67: 66 | B67: 33732 | C67: 7318 | E67: 431000 | G67: 20.856 | H67: 19.764 | I67: 1.089 | J67: 6363.102 | L67: 648 | M67: 12.824 | N67: 160204 | O67: 4117 | P67: 815581 | U67: 28 | V67: 81.3 | AA67: 253530 | AC67: 0 | AD67: 48.6 | AE67: 12.5 | AF67: 13.7659 | AG67: =6753.47943187+0.36116788*I67+0.01252571*N67-22.85359542*V67+0.00407811*AA67-0.00067349*E67 -> 7646.1933 | AH67: =A67*'Simple Linear Regression'!$B$18+'Simple Linear Regression'!$B$17 -> 7941.6368 | AI67: =7491.3971+0.0137554*N67-0.00058829*E67-34.3283*V67+0.30565*L67+54.6031*M67 -> 7548.9148 | AJ67: =7491.3971-0.00058829*E67+0.30565*L67+54.6031*M67+0.0137554*N67-34.3283*V67 -> 7548.9148 | AL67: =2192.59+2373.87*I67+0.0316653*N67-15.7623*V67+0.00202406*AA67-0.000740146*E67-0.00963493*(I67*N67) -> 7082.3935 | AM67: =5205.907083+122.0638992*I67+13.609808*(N67/1000)-1.245906883*AD67+0.7746840854*AE67-134.2474226*AC67-1547.125689*IF(AND(B67>=DATE(2020,3,20),B67<=DATE(2020,6,26)),1,0) -> 7468.3128 | AN67: =7707.2178-144.397321*AC67+139.5614087*AF67-0.0008594506251*E67-265.7105668*I67-0.02506176117*J67+0.004708026652*N67 -> 9563.3983 | AO67: =IF(N67="","",2190.39 + 2739.06*I67 + 0.034693*N67 - 16.722*V67 - 0.000802*E67 - 1.3691*AD67 + 1.8691*AE67 - 121.7*AC67 + 209.88*IF(AND(B67>=DATE(2020,3,20),B67<=DATE(2020,6,26)),1,0) - 0.011049*(I67*N67)) -> 7055.2162 | AP67: =IF(B67<DATE(2008,1,1),"",3929.06 + 1212.53*I67 - 0.0003097*N67 + 59.426*V67 - 0.0006734*E67 - 1.036*AD67 + 1.2076*AE67 + 94.923*AF67 - 131.43*AC67 - 759.61*IF(AND(B67>=DATE(2020,3,20),B67<=DATE(2020,6,26)),1,0) - 17.324*(I67*V67)) | AQ67: =IF(N67="","",I67*N67) -> 174462.16 | AR67: =I67*E67 -> 469359 | AS67: =AC67*AF67 -> 0 | AT67: =IF(N67="","",2413.3773+89.103503*I67+0.018847679*N67-5.0917058*V67-0.00064564578*E67+1.4315076*AD67-3.1976817*AE67-66.972905*AC67-217.08397*IF(AND(B67>=DATE(2020,3,20),B67<=DATE(2020,6,26)),1,0)+190.76803*AF67) -> 7493.3494 | AU67: =IF(N67="","",-480.76297+2186.3009*I67+0.033368804*N67-5.3903106*V67-0.00073731439*E67+0.93396876*AD67-1.6242981*AE67-61.304389*AC67-95.472727*IF(AND(B67>=DATE(2020,3,20),B67<=DATE(2020,6,26)),1,0)+156.04851*AF67-0.0087322858*AQ67) -> 7139.7018 | AV67: =IF(N67="","",2518.0489-204.66184*I67+0.019354281*N67-2.3328708*V67-0.0022533804*E67+1.5259709*AD67-3.5842757*AE67-65.580099*AC67-62.828483*IF(AND(B67>=DATE(2020,3,20),B67<=DATE(2020,6,26)),1,0)+200.94286*AF67+0.00080379976*AR67) -> 7407.7247 | AW67: =IF(N67="","",2361.7153+89.223162*I67+0.018847054*N67-5.0210815*V67-0.0006437347*E67+1.4213619*AD67-3.2156123*AE67+167.41121*AC67-224.35191*IF(AND(B67>=DATE(2020,3,20),B67<=DATE(2020,6,26)),1,0)+194.56435*AF67-19.897843*AS67) -> 7499.8256 | AX67: =IF(N67="","",-654.03928+2464.5589*I67+0.035956453*N67-8.0754527*V67-0.00069441316*E67+0.69511606*AD67-1.1669613*AE67-90.724569*AC67-211.24919*IF(AND(B67>=DATE(2020,3,20),B67<=DATE(2020,6,26)),1,0)+147.22132*AF67-0.010108087*AQ67) -> 7116.7575
A68: 67 | B68: 33739 | C68: 7174 | E68: 417000 | G68: 20.802 | H68: 19.786 | I68: 1.102 | J68: 6363.102 | L68: 648 | M68: 12.824 | N68: 160204 | O68: 4117 | P68: 815581 | U68: 28 | V68: 81.3 | AA68: 253530 | AC68: 0 | AD68: 19.8 | AE68: 20.3 | AF68: 13.9809 | AG68: =6753.47943187+0.36116788*I68+0.01252571*N68-22.85359542*V68+0.00407811*AA68-0.00067349*E68 -> 7655.6269 | AH68: =A68*'Simple Linear Regression'!$B$18+'Simple Linear Regression'!$B$17 -> 7942.4898 | AI68: =7491.3971+0.0137554*N68-0.00058829*E68-34.3283*V68+0.30565*L68+54.6031*M68 -> 7557.1508 | AJ68: =7491.3971-0.00058829*E68+0.30565*L68+54.6031*M68+0.0137554*N68-34.3283*V68 -> 7557.1508 | AL68: =2192.59+2373.87*I68+0.0316653*N68-15.7623*V68+0.00202406*AA68-0.000740146*E68-0.00963493*(I68*N68) -> 7103.5497 | AM68: =5205.907083+122.0638992*I68+13.609808*(N68/1000)-1.245906883*AD68+0.7746840854*AE68-134.2474226*AC68-1547.125689*IF(AND(B68>=DATE(2020,3,20),B68<=DATE(2020,6,26)),1,0) -> 7511.8243 | AN68: =7707.2178-144.397321*AC68+139.5614087*AF68-0.0008594506251*E68-265.7105668*I68-0.02506176117*J68+0.004708026652*N68 -> 9601.9821 | AO68: =IF(N68="","",2190.39 + 2739.06*I68 + 0.034693*N68 - 16.722*V68 - 0.000802*E68 - 1.3691*AD68 + 1.8691*AE68 - 121.7*AC68 + 209.88*IF(AND(B68>=DATE(2020,3,20),B68<=DATE(2020,6,26)),1,0) - 0.011049*(I68*N68)) -> 7133.0499 | AP68: =IF(B68<DATE(2008,1,1),"",3929.06 + 1212.53*I68 - 0.0003097*N68 + 59.426*V68 - 0.0006734*E68 - 1.036*AD68 + 1.2076*AE68 + 94.923*AF68 - 131.43*AC68 - 759.61*IF(AND(B68>=DATE(2020,3,20),B68<=DATE(2020,6,26)),1,0) - 17.324*(I68*V68)) | AQ68: =IF(N68="","",I68*N68) -> 176544.81 | AR68: =I68*E68 -> 459534 | AS68: =AC68*AF68 -> 0 | AT68: =IF(N68="","",2413.3773+89.103503*I68+0.018847679*N68-5.0917058*V68-0.00064564578*E68+1.4315076*AD68-3.1976817*AE68-66.972905*AC68-217.08397*IF(AND(B68>=DATE(2020,3,20),B68<=DATE(2020,6,26)),1,0)+190.76803*AF68) -> 7478.3926 | AU68: =IF(N68="","",-480.76297+2186.3009*I68+0.033368804*N68-5.3903106*V68-0.00073731439*E68+0.93396876*AD68-1.6242981*AE68-61.304389*AC68-95.472727*IF(AND(B68>=DATE(2020,3,20),B68<=DATE(2020,6,26)),1,0)+156.04851*AF68-0.0087322858*AQ68) -> 7154.2424 | AV68: =IF(N68="","",2518.0489-204.66184*I68+0.019354281*N68-2.3328708*V68-0.0022533804*E68+1.5259709*AD68-3.5842757*AE68-65.580099*AC68-62.828483*IF(AND(B68>=DATE(2020,3,20),B68<=DATE(2020,6,26)),1,0)+200.94286*AF68+0.00080379976*AR68) -> 7400.0115 | AW68: =IF(N68="","",2361.7153+89.223162*I68+0.018847054*N68-5.0210815*V68-0.0006437347*E68+1.4213619*AD68-3.2156123*AE68+167.41121*AC68-224.35191*IF(AND(B68>=DATE(2020,3,20),B68<=DATE(2020,6,26)),1,0)+194.56435*AF68-19.897843*AS68) -> 7485.8121 | AX68: =IF(N68="","",-654.03928+2464.5589*I68+0.035956453*N68-8.0754527*V68-0.00069441316*E68+0.69511606*AD68-1.1669613*AE68-90.724569*AC68-211.24919*IF(AND(B68>=DATE(2020,3,20),B68<=DATE(2020,6,26)),1,0)+147.22132*AF68-0.010108087*AQ68) -> 7139.9979
A69: 68 | B69: 33746 | C69: 7086 | E69: 414000 | G69: 20.488 | H69: 19.492 | I69: 1.118 | J69: 6363.102 | L69: 648 | M69: 12.55 | N69: 183778 | O69: 4117 | P69: 815581 | U69: 28 | V69: 81.3 | AA69: 253530 | AC69: 0 | AD69: 12.3 | AE69: 29.5 | AF69: 14.1699 | AG69: =6753.47943187+0.36116788*I69+0.01252571*N69-22.85359542*V69+0.00407811*AA69-0.00067349*E69 -> 7952.9342 | AH69: =A69*'Simple Linear Regression'!$B$18+'Simple Linear Regression'!$B$17 -> 7943.3429 | AI69: =7491.3971+0.0137554*N69-0.00058829*E69-34.3283*V69+0.30565*L69+54.6031*M69 -> 7868.2243 | AJ69: =7491.3971-0.00058829*E69+0.30565*L69+54.6031*M69+0.0137554*N69-34.3283*V69 -> 7868.2243 | AL69: =2192.59+2373.87*I69+0.0316653*N69-15.7623*V69+0.00202406*AA69-0.000740146*E69-0.00963493*(I69*N69) -> 7611.5973 | AM69: =5205.907083+122.0638992*I69+13.609808*(N69/1000)-1.245906883*AD69+0.7746840854*AE69-134.2474226*AC69-1547.125689*IF(AND(B69>=DATE(2020,3,20),B69<=DATE(2020,6,26)),1,0) -> 7851.0863 | AN69: =7707.2178-144.397321*AC69+139.5614087*AF69-0.0008594506251*E69-265.7105668*I69-0.02506176117*J69+0.004708026652*N69 -> 9737.6732 | AO69: =IF(N69="","",2190.39 + 2739.06*I69 + 0.034693*N69 - 16.722*V69 - 0.000802*E69 - 1.3691*AD69 + 1.8691*AE69 - 121.7*AC69 + 209.88*IF(AND(B69>=DATE(2020,3,20),B69<=DATE(2020,6,26)),1,0) - 0.011049*(I69*N69)) -> 7705.0716 | AP69: =IF(B69<DATE(2008,1,1),"",3929.06 + 1212.53*I69 - 0.0003097*N69 + 59.426*V69 - 0.0006734*E69 - 1.036*AD69 + 1.2076*AE69 + 94.923*AF69 - 131.43*AC69 - 759.61*IF(AND(B69>=DATE(2020,3,20),B69<=DATE(2020,6,26)),1,0) - 17.324*(I69*V69)) | AQ69: =IF(N69="","",I69*N69) -> 205463.8 | AR69: =I69*E69 -> 462852 | AS69: =AC69*AF69 -> 0 | AT69: =IF(N69="","",2413.3773+89.103503*I69+0.018847679*N69-5.0917058*V69-0.00064564578*E69+1.4315076*AD69-3.1976817*AE69-66.972905*AC69-217.08397*IF(AND(B69>=DATE(2020,3,20),B69<=DATE(2020,6,26)),1,0)+190.76803*AF69) -> 7921.9706 | AU69: =IF(N69="","",-480.76297+2186.3009*I69+0.033368804*N69-5.3903106*V69-0.00073731439*E69+0.93396876*AD69-1.6242981*AE69-61.304389*AC69-95.472727*IF(AND(B69>=DATE(2020,3,20),B69<=DATE(2020,6,26)),1,0)+156.04851*AF69-0.0087322858*AQ69) -> 7733.0872 | AV69: =IF(N69="","",2518.0489-204.66184*I69+0.019354281*N69-2.3328708*V69-0.0022533804*E69+1.5259709*AD69-3.5842757*AE69-65.580099*AC69-62.828483*IF(AND(B69>=DATE(2020,3,20),B69<=DATE(2020,6,26)),1,0)+200.94286*AF69+0.00080379976*AR69) -> 7855.98 | AW69: =IF(N69="","",2361.7153+89.223162*I69+0.018847054*N69-5.0210815*V69-0.0006437347*E69+1.4213619*AD69-3.2156123*AE69+167.41121*AC69-224.35191*IF(AND(B69>=DATE(2020,3,20),B69<=DATE(2020,6,26)),1,0)+194.56435*AF69-19.897843*AS69) -> 7930.0002 | AX69: =IF(N69="","",-654.03928+2464.5589*I69+0.035956453*N69-8.0754527*V69-0.00069441316*E69+0.69511606*AD69-1.1669613*AE69-90.724569*AC69-211.24919*IF(AND(B69>=DATE(2020,3,20),B69<=DATE(2020,6,26)),1,0)+147.22132*AF69-0.010108087*AQ69) -> 7748.7112
... A213: 212 | B213: 34754 | C213: 7670 | E213: 343000 | G213: 18.7475 | H213: 17.178 | I213: 1.067 | J213: 7455.288 | L213: 816 | M213: 14.801 | N213: 193087 | O213: 4841.6 | P213: 980405 | U213: 27 | V213: 92.7 | AA213: 260282 | AC213: 0 | AD213: 128.6 | AE213: 0.2 | AF213: 10.8748 | AG213: =6753.47943187+0.36116788*I213+0.01252571*N213-22.85359542*V213+0.00407811*AA213-0.00067349*E213 -> 7884.3398 | AH213: =A213*'Simple Linear Regression'!$B$18+'Simple Linear Regression'!$B$17 -> 8066.1802 | AI213: =7491.3971+0.0137554*N213-0.00058829*E213-34.3283*V213+0.30565*L213+54.6031*M213 -> 7820.96 | AJ213: =7491.3971-0.00058829*E213+0.30565*L213+54.6031*M213+0.0137554*N213-34.3283*V213 -> 7820.96 | AL213: =2192.59+2373.87*I213+0.0316653*N213-15.7623*V213+0.00202406*AA213-0.000740146*E213-0.00963493*(I213*N213) -> 7666.433 | AM213: =5205.907083+122.0638992*I213+13.609808*(N213/1000)-1.245906883*AD213+0.7746840854*AE213-134.2474226*AC213-1547.125689*IF(AND(B213>=DATE(2020,3,20),B213<=DATE(2020,6,26)),1,0) -> 7803.9576 | AN213: =7707.2178-144.397321*AC213+139.5614087*AF213-0.0008594506251*E213-265.7105668*I213-0.02506176117*J213+0.004708026652*N213 -> 9368.8316 | AO213: =IF(N213="","",2190.39 + 2739.06*I213 + 0.034693*N213 - 16.722*V213 - 0.000802*E213 - 1.3691*AD213 + 1.8691*AE213 - 121.7*AC213 + 209.88*IF(AND(B213>=DATE(2020,3,20),B213<=DATE(2020,6,26)),1,0) - 0.011049*(I213*N213)) -> 7534.4692 | AP213: =IF(B213<DATE(2008,1,1),"",3929.06 + 1212.53*I213 - 0.0003097*N213 + 59.426*V213 - 0.0006734*E213 - 1.036*AD213 + 1.2076*AE213 + 94.923*AF213 - 131.43*AC213 - 759.61*IF(AND(B213>=DATE(2020,3,20),B213<=DATE(2020,6,26)),1,0) - 17.324*(I213*V213)) | AQ213: =IF(N213="","",I213*N213) -> 206023.83 | AR213: =I213*E213 -> 365981 | AS213: =AC213*AF213 -> 0 | AT213: =IF(N213="","",2413.3773+89.103503*I213+0.018847679*N213-5.0917058*V213-0.00064564578*E213+1.4315076*AD213-3.1976817*AE213-66.972905*AC213-217.08397*IF(AND(B213>=DATE(2020,3,20),B213<=DATE(2020,6,26)),1,0)+190.76803*AF213) -> 7712.2514 | AU213: =IF(N213="","",-480.76297+2186.3009*I213+0.033368804*N213-5.3903106*V213-0.00073731439*E213+0.93396876*AD213-1.6242981*AE213-61.304389*AC213-95.472727*IF(AND(B213>=DATE(2020,3,20),B213<=DATE(2020,6,26)),1,0)+156.04851*AF213-0.0087322858*AQ213) -> 7560.2426 | AV213: =IF(N213="","",2518.0489-204.66184*I213+0.019354281*N213-2.3328708*V213-0.0022533804*E213+1.5259709*AD213-3.5842757*AE213-65.580099*AC213-62.828483*IF(AND(B213>=DATE(2020,3,20),B213<=DATE(2020,6,26)),1,0)+200.94286*AF213+0.00080379976*AR213) -> 7722.48 | AW213: =IF(N213="","",2361.7153+89.223162*I213+0.018847054*N213-5.0210815*V213-0.0006437347*E213+1.4213619*AD213-3.2156123*AE213+167.41121*AC213-224.35191*IF(AND(B213>=DATE(2020,3,20),B213<=DATE(2020,6,26)),1,0)+194.56435*AF213-19.897843*AS213) -> 7707.7747 | AX213: =IF(N213="","",-654.03928+2464.5589*I213+0.035956453*N213-8.0754527*V213-0.00069441316*E213+0.69511606*AD213-1.1669613*AE213-90.724569*AC213-211.24919*IF(AND(B213>=DATE(2020,3,20),B213<=DATE(2020,6,26)),1,0)+147.22132*AF213-0.010108087*AQ213) -> 7539.2447
A214: 213 | B214: 34761 | C214: 7194 | E214: 336000 | G214: 18.5 | H214: 16.932 | I214: 1.073 | J214: 7455.288 | L214: 816 | M214: 14.801 | N214: 193087 | O214: 4841.6 | P214: 980405 | R214: 2483 | U214: 27 | V214: 92.7 | AA214: 263455 | AC214: 0 | AD214: 149.6 | AE214: 0.7 | AF214: 11.1472 | AG214: =6753.47943187+0.36116788*I214+0.01252571*N214-22.85359542*V214+0.00407811*AA214-0.00067349*E214 -> 7901.9963 | AH214: =A214*'Simple Linear Regression'!$B$18+'Simple Linear Regression'!$B$17 -> 8067.0332 | AI214: =7491.3971+0.0137554*N214-0.00058829*E214-34.3283*V214+0.30565*L214+54.6031*M214 -> 7825.0781 | AJ214: =7491.3971-0.00058829*E214+0.30565*L214+54.6031*M214+0.0137554*N214-34.3283*V214 -> 7825.0781 | AL214: =2192.59+2373.87*I214+0.0316653*N214-15.7623*V214+0.00202406*AA214-0.000740146*E214-0.00963493*(I214*N214) -> 7681.1173 | AM214: =5205.907083+122.0638992*I214+13.609808*(N214/1000)-1.245906883*AD214+0.7746840854*AE214-134.2474226*AC214-1547.125689*IF(AND(B214>=DATE(2020,3,20),B214<=DATE(2020,6,26)),1,0) -> 7778.9133 | AN214: =7707.2178-144.397321*AC214+139.5614087*AF214-0.0008594506251*E214-265.7105668*I214-0.02506176117*J214+0.004708026652*N214 -> 9411.27 | AO214: =IF(N214="","",2190.39 + 2739.06*I214 + 0.034693*N214 - 16.722*V214 - 0.000802*E214 - 1.3691*AD214 + 1.8691*AE214 - 121.7*AC214 + 209.88*IF(AND(B214>=DATE(2020,3,20),B214<=DATE(2020,6,26)),1,0) - 0.011049*(I214*N214)) -> 7515.9005 | AP214: =IF(B214<DATE(2008,1,1),"",3929.06 + 1212.53*I214 - 0.0003097*N214 + 59.426*V214 - 0.0006734*E214 - 1.036*AD214 + 1.2076*AE214 + 94.923*AF214 - 131.43*AC214 - 759.61*IF(AND(B214>=DATE(2020,3,20),B214<=DATE(2020,6,26)),1,0) - 17.324*(I214*V214)) | AQ214: =IF(N214="","",I214*N214) -> 207182.35 | AR214: =I214*E214 -> 360528 | AS214: =AC214*AF214 -> 0 | AT214: =IF(N214="","",2413.3773+89.103503*I214+0.018847679*N214-5.0917058*V214-0.00064564578*E214+1.4315076*AD214-3.1976817*AE214-66.972905*AC214-217.08397*IF(AND(B214>=DATE(2020,3,20),B214<=DATE(2020,6,26)),1,0)+190.76803*AF214) -> 7797.7336 | AU214: =IF(N214="","",-480.76297+2186.3009*I214+0.033368804*N214-5.3903106*V214-0.00073731439*E214+0.93396876*AD214-1.6242981*AE214-61.304389*AC214-95.472727*IF(AND(B214>=DATE(2020,3,20),B214<=DATE(2020,6,26)),1,0)+156.04851*AF214-0.0087322858*AQ214) -> 7629.7139 | AV214: =IF(N214="","",2518.0489-204.66184*I214+0.019354281*N214-2.3328708*V214-0.0022533804*E214+1.5259709*AD214-3.5842757*AE214-65.580099*AC214-62.828483*IF(AND(B214>=DATE(2020,3,20),B214<=DATE(2020,6,26)),1,0)+200.94286*AF214+0.00080379976*AR214) -> 7817.6327 | AW214: =IF(N214="","",2361.7153+89.223162*I214+0.018847054*N214-5.0210815*V214-0.0006437347*E214+1.4213619*AD214-3.2156123*AE214+167.41121*AC214-224.35191*IF(AND(B214>=DATE(2020,3,20),B214<=DATE(2020,6,26)),1,0)+194.56435*AF214-19.897843*AS214) -> 7794.0563 | AX214: =IF(N214="","",-654.03928+2464.5589*I214+0.035956453*N214-8.0754527*V214-0.00069441316*E214+0.69511606*AD214-1.1669613*AE214-90.724569*AC214-211.24919*IF(AND(B214>=DATE(2020,3,20),B214<=DATE(2020,6,26)),1,0)+147.22132*AF214-0.010108087*AQ214) -> 7601.2995
A215: 214 | B215: 34768 | C215: 7548 | E215: 339000 | G215: 18.27 | H215: 16.696 | I215: 1.076 | J215: 7455.288 | L215: 748 | M215: 14.801 | N215: 193087 | O215: 4851.2 | P215: 980405 | R215: 2483 | U215: 27 | V215: 92.6 | AA215: 263455 | AC215: 0 | AD215: 141.1 | AE215: 0.8 | AF215: 11.4273 | AG215: =6753.47943187+0.36116788*I215+0.01252571*N215-22.85359542*V215+0.00407811*AA215-0.00067349*E215 -> 7902.2622 | AH215: =A215*'Simple Linear Regression'!$B$18+'Simple Linear Regression'!$B$17 -> 8067.8863 | AI215: =7491.3971+0.0137554*N215-0.00058829*E215-34.3283*V215+0.30565*L215+54.6031*M215 -> 7805.9618 | AJ215: =7491.3971-0.00058829*E215+0.30565*L215+54.6031*M215+0.0137554*N215-34.3283*V215 -> 7805.9618 | AL215: =2192.59+2373.87*I215+0.0316653*N215-15.7623*V215+0.00202406*AA215-0.000740146*E215-0.00963493*(I215*N215) -> 7682.0136 | AM215: =5205.907083+122.0638992*I215+13.609808*(N215/1000)-1.245906883*AD215+0.7746840854*AE215-134.2474226*AC215-1547.125689*IF(AND(B215>=DATE(2020,3,20),B215<=DATE(2020,6,26)),1,0) -> 7789.9471 | AN215: =7707.2178-144.397321*AC215+139.5614087*AF215-0.0008594506251*E215-265.7105668*I215-0.02506176117*J215+0.004708026652*N215 -> 9446.9856 | AO215: =IF(N215="","",2190.39 + 2739.06*I215 + 0.034693*N215 - 16.722*V215 - 0.000802*E215 - 1.3691*AD215 + 1.8691*AE215 - 121.7*AC215 + 209.88*IF(AND(B215>=DATE(2020,3,20),B215<=DATE(2020,6,26)),1,0) - 0.011049*(I215*N215)) -> 7528.8079 | AP215: =IF(B215<DATE(2008,1,1),"",3929.06 + 1212.53*I215 - 0.0003097*N215 + 59.426*V215 - 0.0006734*E215 - 1.036*AD215 + 1.2076*AE215 + 94.923*AF215 - 131.43*AC215 - 759.61*IF(AND(B215>=DATE(2020,3,20),B215<=DATE(2020,6,26)),1,0) - 17.324*(I215*V215)) | AQ215: =IF(N215="","",I215*N215) -> 207761.61 | AR215: =I215*E215 -> 364764 | AS215: =AC215*AF215 -> 0 | AT215: =IF(N215="","",2413.3773+89.103503*I215+0.018847679*N215-5.0917058*V215-0.00064564578*E215+1.4315076*AD215-3.1976817*AE215-66.972905*AC215-217.08397*IF(AND(B215>=DATE(2020,3,20),B215<=DATE(2020,6,26)),1,0)+190.76803*AF215) -> 7837.5197 | AU215: =IF(N215="","",-480.76297+2186.3009*I215+0.033368804*N215-5.3903106*V215-0.00073731439*E215+0.93396876*AD215-1.6242981*AE215-61.304389*AC215-95.472727*IF(AND(B215>=DATE(2020,3,20),B215<=DATE(2020,6,26)),1,0)+156.04851*AF215-0.0087322858*AQ215) -> 7665.1496 | AV215: =IF(N215="","",2518.0489-204.66184*I215+0.019354281*N215-2.3328708*V215-0.0022533804*E215+1.5259709*AD215-3.5842757*AE215-65.580099*AC215-62.828483*IF(AND(B215>=DATE(2020,3,20),B215<=DATE(2020,6,26)),1,0)+200.94286*AF215+0.00080379976*AR215) -> 7856.8517 | AW215: =IF(N215="","",2361.7153+89.223162*I215+0.018847054*N215-5.0210815*V215-0.0006437347*E215+1.4213619*AD215-3.2156123*AE215+167.41121*AC215-224.35191*IF(AND(B215>=DATE(2020,3,20),B215<=DATE(2020,6,26)),1,0)+194.56435*AF215-19.897843*AS215) -> 7834.9892 | AX215: =IF(N215="","",-654.03928+2464.5589*I215+0.035956453*N215-8.0754527*V215-0.00069441316*E215+0.69511606*AD215-1.1669613*AE215-90.724569*AC215-211.24919*IF(AND(B215>=DATE(2020,3,20),B215<=DATE(2020,6,26)),1,0)+147.22132*AF215-0.010108087*AQ215) -> 7636.7738
A216: 215 | B216: 34775 | C216: 7834 | E216: 347000 | G216: 18.132 | H216: 16.412 | I216: 1.069 | J216: 7455.288 | L216: 748 | M216: 14.861 | N216: 193087 | O216: 4851.2 | P216: 1021168 | R216: 2483 | U216: 27 | V216: 92.6 | AA216: 263455 | AC216: 0 | AD216: 91.9 | AE216: 0.3 | AF216: 11.7125 | AG216: =6753.47943187+0.36116788*I216+0.01252571*N216-22.85359542*V216+0.00407811*AA216-0.00067349*E216 -> 7896.8718 | AH216: =A216*'Simple Linear Regression'!$B$18+'Simple Linear Regression'!$B$17 -> 8068.7393 | AI216: =7491.3971+0.0137554*N216-0.00058829*E216-34.3283*V216+0.30565*L216+54.6031*M216 -> 7804.5317 | AJ216: =7491.3971-0.00058829*E216+0.30565*L216+54.6031*M216+0.0137554*N216-34.3283*V216 -> 7804.5317 | AL216: =2192.59+2373.87*I216+0.0316653*N216-15.7623*V216+0.00202406*AA216-0.000740146*E216-0.00963493*(I216*N216) -> 7672.498 | AM216: =5205.907083+122.0638992*I216+13.609808*(N216/1000)-1.245906883*AD216+0.7746840854*AE216-134.2474226*AC216-1547.125689*IF(AND(B216>=DATE(2020,3,20),B216<=DATE(2020,6,26)),1,0) -> 7850.004 | AN216: =7707.2178-144.397321*AC216+139.5614087*AF216-0.0008594506251*E216-265.7105668*I216-0.02506176117*J216+0.004708026652*N216 -> 9481.7729 | AO216: =IF(N216="","",2190.39 + 2739.06*I216 + 0.034693*N216 - 16.722*V216 - 0.000802*E216 - 1.3691*AD216 + 1.8691*AE216 - 121.7*AC216 + 209.88*IF(AND(B216>=DATE(2020,3,20),B216<=DATE(2020,6,26)),1,0) - 0.011049*(I216*N216)) -> 7584.5775 | AP216: =IF(B216<DATE(2008,1,1),"",3929.06 + 1212.53*I216 - 0.0003097*N216 + 59.426*V216 - 0.0006734*E216 - 1.036*AD216 + 1.2076*AE216 + 94.923*AF216 - 131.43*AC216 - 759.61*IF(AND(B216>=DATE(2020,3,20),B216<=DATE(2020,6,26)),1,0) - 17.324*(I216*V216)) | AQ216: =IF(N216="","",I216*N216) -> 206410 | AR216: =I216*E216 -> 370943 | AS216: =AC216*AF216 -> 0 | AT216: =IF(N216="","",2413.3773+89.103503*I216+0.018847679*N216-5.0917058*V216-0.00064564578*E216+1.4315076*AD216-3.1976817*AE216-66.972905*AC216-217.08397*IF(AND(B216>=DATE(2020,3,20),B216<=DATE(2020,6,26)),1,0)+190.76803*AF216) -> 7817.3065 | AU216: =IF(N216="","",-480.76297+2186.3009*I216+0.033368804*N216-5.3903106*V216-0.00073731439*E216+0.93396876*AD216-1.6242981*AE216-61.304389*AC216-95.472727*IF(AND(B216>=DATE(2020,3,20),B216<=DATE(2020,6,26)),1,0)+156.04851*AF216-0.0087322858*AQ216) -> 7655.1156 | AV216: =IF(N216="","",2518.0489-204.66184*I216+0.019354281*N216-2.3328708*V216-0.0022533804*E216+1.5259709*AD216-3.5842757*AE216-65.580099*AC216-62.828483*IF(AND(B216>=DATE(2020,3,20),B216<=DATE(2020,6,26)),1,0)+200.94286*AF216+0.00080379976*AR216) -> 7829.2472 | AW216: =IF(N216="","",2361.7153+89.223162*I216+0.018847054*N216-5.0210815*V216-0.0006437347*E216+1.4213619*AD216-3.2156123*AE216+167.41121*AC216-224.35191*IF(AND(B216>=DATE(2020,3,20),B216<=DATE(2020,6,26)),1,0)+194.56435*AF216-19.897843*AS216) -> 7816.3813 | AX216: =IF(N216="","",-654.03928+2464.5589*I216+0.035956453*N216-8.0754527*V216-0.00069441316*E216+0.69511606*AD216-1.1669613*AE216-90.724569*AC216-211.24919*IF(AND(B216>=DATE(2020,3,20),B216<=DATE(2020,6,26)),1,0)+147.22132*AF216-0.010108087*AQ216) -> 7636.0001
A217: 216 | B217: 34782 | C217: 7797 | E217: 343000 | G217: 18.692 | H217: 17.168 | I217: 1.068 | J217: 7455.288 | L217: 748 | M217: 14.861 | N217: 193838 | O217: 4851.2 | P217: 1021168 | R217: 2483 | U217: 27 | V217: 92.6 | AA217: 263455 | AC217: 0 | AD217: 88.9 | AE217: 6.7 | AF217: 12 | AG217: =6753.47943187+0.36116788*I217+0.01252571*N217-22.85359542*V217+0.00407811*AA217-0.00067349*E217 -> 7908.9722 | AH217: =A217*'Simple Linear Regression'!$B$18+'Simple Linear Regression'!$B$17 -> 8069.5924 | AI217: =7491.3971+0.0137554*N217-0.00058829*E217-34.3283*V217+0.30565*L217+54.6031*M217 -> 7817.2151 | AJ217: =7491.3971-0.00058829*E217+0.30565*L217+54.6031*M217+0.0137554*N217-34.3283*V217 -> 7817.2151 | AL217: =2192.59+2373.87*I217+0.0316653*N217-15.7623*V217+0.00202406*AA217-0.000740146*E217-0.00963493*(I217*N217) -> 7690.9978 | AM217: =5205.907083+122.0638992*I217+13.609808*(N217/1000)-1.245906883*AD217+0.7746840854*AE217-134.2474226*AC217-1547.125689*IF(AND(B217>=DATE(2020,3,20),B217<=DATE(2020,6,26)),1,0) -> 7868.7986 | AN217: =7707.2178-144.397321*AC217+139.5614087*AF217-0.0008594506251*E217-265.7105668*I217-0.02506176117*J217+0.004708026652*N217 -> 9529.1361 | AO217: =IF(N217="","",2190.39 + 2739.06*I217 + 0.034693*N217 - 16.722*V217 - 0.000802*E217 - 1.3691*AD217 + 1.8691*AE217 - 121.7*AC217 + 209.88*IF(AND(B217>=DATE(2020,3,20),B217<=DATE(2020,6,26)),1,0) - 0.011049*(I217*N217)) -> 7620.4418 | AP217: =IF(B217<DATE(2008,1,1),"",3929.06 + 1212.53*I217 - 0.0003097*N217 + 59.426*V217 - 0.0006734*E217 - 1.036*AD217 + 1.2076*AE217 + 94.923*AF217 - 131.43*AC217 - 759.61*IF(AND(B217>=DATE(2020,3,20),B217<=DATE(2020,6,26)),1,0) - 17.324*(I217*V217)) | AQ217: =IF(N217="","",I217*N217) -> 207018.98 | AR217: =I217*E217 -> 366324 | AS217: =AC217*AF217 -> 0 | AT217: =IF(N217="","",2413.3773+89.103503*I217+0.018847679*N217-5.0917058*V217-0.00064564578*E217+1.4315076*AD217-3.1976817*AE217-66.972905*AC217-217.08397*IF(AND(B217>=DATE(2020,3,20),B217<=DATE(2020,6,26)),1,0)+190.76803*AF217) -> 7864.0407 | AU217: =IF(N217="","",-480.76297+2186.3009*I217+0.033368804*N217-5.3903106*V217-0.00073731439*E217+0.93396876*AD217-1.6242981*AE217-61.304389*AC217-95.472727*IF(AND(B217>=DATE(2020,3,20),B217<=DATE(2020,6,26)),1,0)+156.04851*AF217-0.0087322858*AQ217) -> 7707.2872 | AV217: =IF(N217="","",2518.0489-204.66184*I217+0.019354281*N217-2.3328708*V217-0.0022533804*E217+1.5259709*AD217-3.5842757*AE217-65.580099*AC217-62.828483*IF(AND(B217>=DATE(2020,3,20),B217<=DATE(2020,6,26)),1,0)+200.94286*AF217+0.00080379976*AR217) -> 7879.5415 | AW217: =IF(N217="","",2361.7153+89.223162*I217+0.018847054*N217-5.0210815*V217-0.0006437347*E217+1.4213619*AD217-3.2156123*AE217+167.41121*AC217-224.35191*IF(AND(B217>=DATE(2020,3,20),B217<=DATE(2020,6,26)),1,0)+194.56435*AF217-19.897843*AS217) -> 7864.1144 | AX217: =IF(N217="","",-654.03928+2464.5589*I217+0.035956453*N217-8.0754527*V217-0.00069441316*E217+0.69511606*AD217-1.1669613*AE217-90.724569*AC217-211.24919*IF(AND(B217>=DATE(2020,3,20),B217<=DATE(2020,6,26)),1,0)+147.22132*AF217-0.010108087*AQ217) -> 7689.933
A218: 217 | B218: 34789 | C218: 8195 | E218: 332000 | G218: 19.118 | H218: 17.938 | I218: 1.075 | J218: 7455.288 | L218: 748 | M218: 14.861 | N218: 193838 | O218: 4851.2 | P218: 1021168 | R218: 2483 | U218: 27 | V218: 92.6 | AA218: 263455 | AC218: 0 | AD218: 101.2 | AE218: 3.9 | AF218: 12.2875 | AG218: =6753.47943187+0.36116788*I218+0.01252571*N218-22.85359542*V218+0.00407811*AA218-0.00067349*E218 -> 7916.3831 | AH218: =A218*'Simple Linear Regression'!$B$18+'Simple Linear Regression'!$B$17 -> 8070.4454 | AI218: =7491.3971+0.0137554*N218-0.00058829*E218-34.3283*V218+0.30565*L218+54.6031*M218 -> 7823.6863 | AJ218: =7491.3971-0.00058829*E218+0.30565*L218+54.6031*M218+0.0137554*N218-34.3283*V218 -> 7823.6863 | AL218: =2192.59+2373.87*I218+0.0316653*N218-15.7623*V218+0.00202406*AA218-0.000740146*E218-0.00963493*(I218*N218) -> 7702.6832 | AM218: =5205.907083+122.0638992*I218+13.609808*(N218/1000)-1.245906883*AD218+0.7746840854*AE218-134.2474226*AC218-1547.125689*IF(AND(B218>=DATE(2020,3,20),B218<=DATE(2020,6,26)),1,0) -> 7852.1592 | AN218: =7707.2178-144.397321*AC218+139.5614087*AF218-0.0008594506251*E218-265.7105668*I218-0.02506176117*J218+0.004708026652*N218 -> 9576.854 | AO218: =IF(N218="","",2190.39 + 2739.06*I218 + 0.034693*N218 - 16.722*V218 - 0.000802*E218 - 1.3691*AD218 + 1.8691*AE218 - 121.7*AC218 + 209.88*IF(AND(B218>=DATE(2020,3,20),B218<=DATE(2020,6,26)),1,0) - 0.011049*(I218*N218)) -> 7611.3718 | AP218: =IF(B218<DATE(2008,1,1),"",3929.06 + 1212.53*I218 - 0.0003097*N218 + 59.426*V218 - 0.0006734*E218 - 1.036*AD218 + 1.2076*AE218 + 94.923*AF218 - 131.43*AC218 - 759.61*IF(AND(B218>=DATE(2020,3,20),B218<=DATE(2020,6,26)),1,0) - 17.324*(I218*V218)) | AQ218: =IF(N218="","",I218*N218) -> 208375.85 | AR218: =I218*E218 -> 356900 | AS218: =AC218*AF218 -> 0 | AT218: =IF(N218="","",2413.3773+89.103503*I218+0.018847679*N218-5.0917058*V218-0.00064564578*E218+1.4315076*AD218-3.1976817*AE218-66.972905*AC218-217.08397*IF(AND(B218>=DATE(2020,3,20),B218<=DATE(2020,6,26)),1,0)+190.76803*AF218) -> 7953.1734 | AU218: =IF(N218="","",-480.76297+2186.3009*I218+0.033368804*N218-5.3903106*V218-0.00073731439*E218+0.93396876*AD218-1.6242981*AE218-61.304389*AC218-95.472727*IF(AND(B218>=DATE(2020,3,20),B218<=DATE(2020,6,26)),1,0)+156.04851*AF218-0.0087322858*AQ218) -> 7779.7531 | AV218: =IF(N218="","",2518.0489-204.66184*I218+0.019354281*N218-2.3328708*V218-0.0022533804*E218+1.5259709*AD218-3.5842757*AE218-65.580099*AC218-62.828483*IF(AND(B218>=DATE(2020,3,20),B218<=DATE(2020,6,26)),1,0)+200.94286*AF218+0.00080379976*AR218) -> 7981.8975 | AW218: =IF(N218="","",2361.7153+89.223162*I218+0.018847054*N218-5.0210815*V218-0.0006437347*E218+1.4213619*AD218-3.2156123*AE218+167.41121*AC218-224.35191*IF(AND(B218>=DATE(2020,3,20),B218<=DATE(2020,6,26)),1,0)+194.56435*AF218-19.897843*AS218) -> 7954.2438 | AX218: =IF(N218="","",-654.03928+2464.5589*I218+0.035956453*N218-8.0754527*V218-0.00069441316*E218+0.69511606*AD218-1.1669613*AE218-90.724569*AC218-211.24919*IF(AND(B218>=DATE(2020,3,20),B218<=DATE(2020,6,26)),1,0)+147.22132*AF218-0.010108087*AQ218) -> 7755.2517
A219: 218 | B219: 34796 | C219: 7588 | E219: 335000 | G219: 19.428 | H219: 18.242 | I219: 1.087 | J219: 7455.288 | L219: 713 | M219: 14.861 | N219: 193838 | O219: 4850.8 | P219: 1021168 | R219: 2483 | U219: 27 | V219: 89.6 | AA219: 263455 | AC219: 0 | AD219: 95.4 | AE219: 0.1 | AF219: 12.5727 | AG219: =6753.47943187+0.36116788*I219+0.01252571*N219-22.85359542*V219+0.00407811*AA219-0.00067349*E219 -> 7982.9278 | AH219: =A219*'Simple Linear Regression'!$B$18+'Simple Linear Regression'!$B$17 -> 8071.2984 | AI219: =7491.3971+0.0137554*N219-0.00058829*E219-34.3283*V219+0.30565*L219+54.6031*M219 -> 7914.2086 | AJ219: =7491.3971-0.00058829*E219+0.30565*L219+54.6031*M219+0.0137554*N219-34.3283*V219 -> 7914.2086 | AL219: =2192.59+2373.87*I219+0.0316653*N219-15.7623*V219+0.00202406*AA219-0.000740146*E219-0.00963493*(I219*N219) -> 7753.8247 | AM219: =5205.907083+122.0638992*I219+13.609808*(N219/1000)-1.245906883*AD219+0.7746840854*AE219-134.2474226*AC219-1547.125689*IF(AND(B219>=DATE(2020,3,20),B219<=DATE(2020,6,26)),1,0) -> 7857.9065 | AN219: =7707.2178-144.397321*AC219+139.5614087*AF219-0.0008594506251*E219-265.7105668*I219-0.02506176117*J219+0.004708026652*N219 -> 9610.89 | AO219: =IF(N219="","",2190.39 + 2739.06*I219 + 0.034693*N219 - 16.722*V219 - 0.000802*E219 - 1.3691*AD219 + 1.8691*AE219 - 121.7*AC219 + 209.88*IF(AND(B219>=DATE(2020,3,20),B219<=DATE(2020,6,26)),1,0) - 0.011049*(I219*N219)) -> 7667.1382 | AP219: =IF(B219<DATE(2008,1,1),"",3929.06 + 1212.53*I219 - 0.0003097*N219 + 59.426*V219 - 0.0006734*E219 - 1.036*AD219 + 1.2076*AE219 + 94.923*AF219 - 131.43*AC219 - 759.61*IF(AND(B219>=DATE(2020,3,20),B219<=DATE(2020,6,26)),1,0) - 17.324*(I219*V219)) | AQ219: =IF(N219="","",I219*N219) -> 210701.91 | AR219: =I219*E219 -> 364145 | AS219: =AC219*AF219 -> 0 | AT219: =IF(N219="","",2413.3773+89.103503*I219+0.018847679*N219-5.0917058*V219-0.00064564578*E219+1.4315076*AD219-3.1976817*AE219-66.972905*AC219-217.08397*IF(AND(B219>=DATE(2020,3,20),B219<=DATE(2020,6,26)),1,0)+190.76803*AF219) -> 8025.8363 | AU219: =IF(N219="","",-480.76297+2186.3009*I219+0.033368804*N219-5.3903106*V219-0.00073731439*E219+0.93396876*AD219-1.6242981*AE219-61.304389*AC219-95.472727*IF(AND(B219>=DATE(2020,3,20),B219<=DATE(2020,6,26)),1,0)+156.04851*AF219-0.0087322858*AQ219) -> 7844.8962 | AV219: =IF(N219="","",2518.0489-204.66184*I219+0.019354281*N219-2.3328708*V219-0.0022533804*E219+1.5259709*AD219-3.5842757*AE219-65.580099*AC219-62.828483*IF(AND(B219>=DATE(2020,3,20),B219<=DATE(2020,6,26)),1,0)+200.94286*AF219+0.00080379976*AR219) -> 8047.5821 | AW219: =IF(N219="","",2361.7153+89.223162*I219+0.018847054*N219-5.0210815*V219-0.0006437347*E219+1.4213619*AD219-3.2156123*AE219+167.41121*AC219-224.35191*IF(AND(B219>=DATE(2020,3,20),B219<=DATE(2020,6,26)),1,0)+194.56435*AF219-19.897843*AS219) -> 8027.9117 | AX219: =IF(N219="","",-654.03928+2464.5589*I219+0.035956453*N219-8.0754527*V219-0.00069441316*E219+0.69511606*AD219-1.1669613*AE219-90.724569*AC219-211.24919*IF(AND(B219>=DATE(2020,3,20),B219<=DATE(2020,6,26)),1,0)+147.22132*AF219-0.010108087*AQ219) -> 7825.8479
A220: 219 | B220: 34803 | C220: 7543 | E220: 347000 | G220: 19.5275 | H220: 18.3725 | I220: 1.103 | J220: 7455.288 | L220: 713 | M220: 14.861 | N220: 193838 | O220: 4850.8 | P220: 1021168 | R220: 2483 | U220: 27 | V220: 89.6 | AA220: 263455 | AC220: 0 | AD220: 74.8 | AE220: 4.8 | AF220: 12.8528 | AG220: =6753.47943187+0.36116788*I220+0.01252571*N220-22.85359542*V220+0.00407811*AA220-0.00067349*E220 -> 7974.8517 | AH220: =A220*'Simple Linear Regression'!$B$18+'Simple Linear Regression'!$B$17 -> 8072.1515 | AI220: =7491.3971+0.0137554*N220-0.00058829*E220-34.3283*V220+0.30565*L220+54.6031*M220 -> 7907.1491 | AJ220: =7491.3971-0.00058829*E220+0.30565*L220+54.6031*M220+0.0137554*N220-34.3283*V220 -> 7907.1491 | AL220: =2192.59+2373.87*I220+0.0316653*N220-15.7623*V220+0.00202406*AA220-0.000740146*E220-0.00963493*(I220*N220) -> 7753.0431 | AM220: =5205.907083+122.0638992*I220+13.609808*(N220/1000)-1.245906883*AD220+0.7746840854*AE220-134.2474226*AC220-1547.125689*IF(AND(B220>=DATE(2020,3,20),B220<=DATE(2020,6,26)),1,0) -> 7889.1662 | AN220: =7707.2178-144.397321*AC220+139.5614087*AF220-0.0008594506251*E220-265.7105668*I220-0.02506176117*J220+0.004708026652*N220 -> 9635.4164 | AO220: =IF(N220="","",2190.39 + 2739.06*I220 + 0.034693*N220 - 16.722*V220 - 0.000802*E220 - 1.3691*AD220 + 1.8691*AE220 - 121.7*AC220 + 209.88*IF(AND(B220>=DATE(2020,3,20),B220<=DATE(2020,6,26)),1,0) - 0.011049*(I220*N220)) -> 7704.0599 | AP220: =IF(B220<DATE(2008,1,1),"",3929.06 + 1212.53*I220 - 0.0003097*N220 + 59.426*V220 - 0.0006734*E220 - 1.036*AD220 + 1.2076*AE220 + 94.923*AF220 - 131.43*AC220 - 759.61*IF(AND(B220>=DATE(2020,3,20),B220<=DATE(2020,6,26)),1,0) - 17.324*(I220*V220)) | AQ220: =IF(N220="","",I220*N220) -> 213803.31 | AR220: =I220*E220 -> 382741 | AS220: =AC220*AF220 -> 0 | AT220: =IF(N220="","",2413.3773+89.103503*I220+0.018847679*N220-5.0917058*V220-0.00064564578*E220+1.4315076*AD220-3.1976817*AE220-66.972905*AC220-217.08397*IF(AND(B220>=DATE(2020,3,20),B220<=DATE(2020,6,26)),1,0)+190.76803*AF220) -> 8028.4302 | AU220: =IF(N220="","",-480.76297+2186.3009*I220+0.033368804*N220-5.3903106*V220-0.00073731439*E220+0.93396876*AD220-1.6242981*AE220-61.304389*AC220-95.472727*IF(AND(B220>=DATE(2020,3,20),B220<=DATE(2020,6,26)),1,0)+156.04851*AF220-0.0087322858*AQ220) -> 7860.7821 | AV220: =IF(N220="","",2518.0489-204.66184*I220+0.019354281*N220-2.3328708*V220-0.0022533804*E220+1.5259709*AD220-3.5842757*AE220-65.580099*AC220-62.828483*IF(AND(B220>=DATE(2020,3,20),B220<=DATE(2020,6,26)),1,0)+200.94286*AF220+0.00080379976*AR220) -> 8040.2174 | AW220: =IF(N220="","",2361.7153+89.223162*I220+0.018847054*N220-5.0210815*V220-0.0006437347*E220+1.4213619*AD220-3.2156123*AE220+167.41121*AC220-224.35191*IF(AND(B220>=DATE(2020,3,20),B220<=DATE(2020,6,26)),1,0)+194.56435*AF220-19.897843*AS220) -> 8031.7185 | AX220: =IF(N220="","",-654.03928+2464.5589*I220+0.035956453*N220-8.0754527*V220-0.00069441316*E220+0.69511606*AD220-1.1669613*AE220-90.724569*AC220-211.24919*IF(AND(B220>=DATE(2020,3,20),B220<=DATE(2020,6,26)),1,0)+147.22132*AF220-0.010108087*AQ220) -> 7847.0311
A221: 220 | B221: 34810 | C221: 8156 | E221: 355000 | G221: 20.264 | H221: 18.9025 | I221: 1.117 | J221: 7455.288 | L221: 713 | M221: 15.256 | N221: 171053 | O221: 4850.8 | P221: 1021168 | R221: 2483 | U221: 27 | V221: 89.6 | AA221: 263455 | AC221: 0 | AD221: 66.2 | AE221: 15.3 | AF221: 13.1252 | AG221: =6753.47943187+0.36116788*I221+0.01252571*N221-22.85359542*V221+0.00407811*AA221-0.00067349*E221 -> 7684.0705 | AH221: =A221*'Simple Linear Regression'!$B$18+'Simple Linear Regression'!$B$17 -> 8073.0045 | AI221: =7491.3971+0.0137554*N221-0.00058829*E221-34.3283*V221+0.30565*L221+54.6031*M221 -> 7610.5942 | AJ221: =7491.3971-0.00058829*E221+0.30565*L221+54.6031*M221+0.0137554*N221-34.3283*V221 -> 7610.5942 | AL221: =2192.59+2373.87*I221+0.0316653*N221-15.7623*V221+0.00202406*AA221-0.000740146*E221-0.00963493*(I221*N221) -> 7277.9327 | AM221: =5205.907083+122.0638992*I221+13.609808*(N221/1000)-1.245906883*AD221+0.7746840854*AE221-134.2474226*AC221-1547.125689*IF(AND(B221>=DATE(2020,3,20),B221<=DATE(2020,6,26)),1,0) -> 7599.6246 | AN221: =7707.2178-144.397321*AC221+139.5614087*AF221-0.0008594506251*E221-265.7105668*I221-0.02506176117*J221+0.004708026652*N221 -> 9555.565 | AO221: =IF(N221="","",2190.39 + 2739.06*I221 + 0.034693*N221 - 16.722*V221 - 0.000802*E221 - 1.3691*AD221 + 1.8691*AE221 - 121.7*AC221 + 209.88*IF(AND(B221>=DATE(2020,3,20),B221<=DATE(2020,6,26)),1,0) - 0.011049*(I221*N221)) -> 7228.1329 | AP221: =IF(B221<DATE(2008,1,1),"",3929.06 + 1212.53*I221 - 0.0003097*N221 + 59.426*V221 - 0.0006734*E221 - 1.036*AD221 + 1.2076*AE221 + 94.923*AF221 - 131.43*AC221 - 759.61*IF(AND(B221>=DATE(2020,3,20),B221<=DATE(2020,6,26)),1,0) - 17.324*(I221*V221)) | AQ221: =IF(N221="","",I221*N221) -> 191066.2 | AR221: =I221*E221 -> 396535 | AS221: =AC221*AF221 -> 0 | AT221: =IF(N221="","",2413.3773+89.103503*I221+0.018847679*N221-5.0917058*V221-0.00064564578*E221+1.4315076*AD221-3.1976817*AE221-66.972905*AC221-217.08397*IF(AND(B221>=DATE(2020,3,20),B221<=DATE(2020,6,26)),1,0)+190.76803*AF221) -> 7601.1467 | AU221: =IF(N221="","",-480.76297+2186.3009*I221+0.033368804*N221-5.3903106*V221-0.00073731439*E221+0.93396876*AD221-1.6242981*AE221-61.304389*AC221-95.472727*IF(AND(B221>=DATE(2020,3,20),B221<=DATE(2020,6,26)),1,0)+156.04851*AF221-0.0087322858*AQ221) -> 7341.1509 | AV221: =IF(N221="","",2518.0489-204.66184*I221+0.019354281*N221-2.3328708*V221-0.0022533804*E221+1.5259709*AD221-3.5842757*AE221-65.580099*AC221-62.828483*IF(AND(B221>=DATE(2020,3,20),B221<=DATE(2020,6,26)),1,0)+200.94286*AF221+0.00080379976*AR221) -> 7593.404 | AW221: =IF(N221="","",2361.7153+89.223162*I221+0.018847054*N221-5.0210815*V221-0.0006437347*E221+1.4213619*AD221-3.2156123*AE221+167.41121*AC221-224.35191*IF(AND(B221>=DATE(2020,3,20),B221<=DATE(2020,6,26)),1,0)+194.56435*AF221-19.897843*AS221) -> 7605.3993 | AX221: =IF(N221="","",-654.03928+2464.5589*I221+0.035956453*N221-8.0754527*V221-0.00069441316*E221+0.69511606*AD221-1.1669613*AE221-90.724569*AC221-211.24919*IF(AND(B221>=DATE(2020,3,20),B221<=DATE(2020,6,26)),1,0)+147.22132*AF221-0.010108087*AQ221) -> 7308.4126
A222: 221 | B222: 34817 | C222: 7731 | E222: 349000 | G222: 20.292 | H222: 19.072 | I222: 1.138 | J222: 7455.288 | L222: 713 | M222: 15.256 | N222: 171053 | O222: 4850.8 | P222: 1021168 | R222: 2483 | U222: 27 | V222: 89.6 | AA222: 263455 | AC222: 0 | AD222: 54.8 | AE222: 5.9 | AF222: 13.3865 | AG222: =6753.47943187+0.36116788*I222+0.01252571*N222-22.85359542*V222+0.00407811*AA222-0.00067349*E222 -> 7688.119 | AH222: =A222*'Simple Linear Regression'!$B$18+'Simple Linear Regression'!$B$17 -> 8073.8575 | AI222: =7491.3971+0.0137554*N222-0.00058829*E222-34.3283*V222+0.30565*L222+54.6031*M222 -> 7614.124 | AJ222: =7491.3971-0.00058829*E222+0.30565*L222+54.6031*M222+0.0137554*N222-34.3283*V222 -> 7614.124 | AL222: =2192.59+2373.87*I222+0.0316653*N222-15.7623*V222+0.00202406*AA222-0.000740146*E222-0.00963493*(I222*N222) -> 7297.6151 | AM222: =5205.907083+122.0638992*I222+13.609808*(N222/1000)-1.245906883*AD222+0.7746840854*AE222-134.2474226*AC222-1547.125689*IF(AND(B222>=DATE(2020,3,20),B222<=DATE(2020,6,26)),1,0) -> 7609.1092 | AN222: =7707.2178-144.397321*AC222+139.5614087*AF222-0.0008594506251*E222-265.7105668*I222-0.02506176117*J222+0.004708026652*N222 -> 9591.6091 | AO222: =IF(N222="","",2190.39 + 2739.06*I222 + 0.034693*N222 - 16.722*V222 - 0.000802*E222 - 1.3691*AD222 + 1.8691*AE222 - 121.7*AC222 + 209.88*IF(AND(B222>=DATE(2020,3,20),B222<=DATE(2020,6,26)),1,0) - 0.011049*(I222*N222)) -> 7248.8141 | AP222: =IF(B222<DATE(2008,1,1),"",3929.06 + 1212.53*I222 - 0.0003097*N222 + 59.426*V222 - 0.0006734*E222 - 1.036*AD222 + 1.2076*AE222 + 94.923*AF222 - 131.43*AC222 - 759.61*IF(AND(B222>=DATE(2020,3,20),B222<=DATE(2020,6,26)),1,0) - 17.324*(I222*V222)) | AQ222: =IF(N222="","",I222*N222) -> 194658.31 | AR222: =I222*E222 -> 397162 | AS222: =AC222*AF222 -> 0 | AT222: =IF(N222="","",2413.3773+89.103503*I222+0.018847679*N222-5.0917058*V222-0.00064564578*E222+1.4315076*AD222-3.1976817*AE222-66.972905*AC222-217.08397*IF(AND(B222>=DATE(2020,3,20),B222<=DATE(2020,6,26)),1,0)+190.76803*AF222) -> 7670.4784 | AU222: =IF(N222="","",-480.76297+2186.3009*I222+0.033368804*N222-5.3903106*V222-0.00073731439*E222+0.93396876*AD222-1.6242981*AE222-61.304389*AC222-95.472727*IF(AND(B222>=DATE(2020,3,20),B222<=DATE(2020,6,26)),1,0)+156.04851*AF222-0.0087322858*AQ222) -> 7405.5164 | AV222: =IF(N222="","",2518.0489-204.66184*I222+0.019354281*N222-2.3328708*V222-0.0022533804*E222+1.5259709*AD222-3.5842757*AE222-65.580099*AC222-62.828483*IF(AND(B222>=DATE(2020,3,20),B222<=DATE(2020,6,26)),1,0)+200.94286*AF222+0.00080379976*AR222) -> 7671.9329 | AW222: =IF(N222="","",2361.7153+89.223162*I222+0.018847054*N222-5.0210815*V222-0.0006437347*E222+1.4213619*AD222-3.2156123*AE222+167.41121*AC222-224.35191*IF(AND(B222>=DATE(2020,3,20),B222<=DATE(2020,6,26)),1,0)+194.56435*AF222-19.897843*AS222) -> 7675.9983 | AX222: =IF(N222="","",-654.03928+2464.5589*I222+0.035956453*N222-8.0754527*V222-0.00069441316*E222+0.69511606*AD222-1.1669613*AE222-90.724569*AC222-211.24919*IF(AND(B222>=DATE(2020,3,20),B222<=DATE(2020,6,26)),1,0)+147.22132*AF222-0.010108087*AQ222) -> 7369.5395
A223: 222 | B223: 34824 | C223: 7539 | E223: 365000 | G223: 20.244 | H223: 18.814 | I223: 1.148 | J223: 7455.288 | L223: 713 | M223: 15.256 | N223: 171053 | O223: 4850.8 | P223: 1021168 | R223: 2483 | U223: 27 | V223: 87.9 | AA223: 263455 | AC223: 0 | AD223: 55.4 | AE223: 13.1 | AF223: 13.6332 | AG223: =6753.47943187+0.36116788*I223+0.01252571*N223-22.85359542*V223+0.00407811*AA223-0.00067349*E223 -> 7716.1979 | AH223: =A223*'Simple Linear Regression'!$B$18+'Simple Linear Regression'!$B$17 -> 8074.7106 | AI223: =7491.3971+0.0137554*N223-0.00058829*E223-34.3283*V223+0.30565*L223+54.6031*M223 -> 7663.0695 | AJ223: =7491.3971-0.00058829*E223+0.30565*L223+54.6031*M223+0.0137554*N223-34.3283*V223 -> 7663.0695 | AL223: =2192.59+2373.87*I223+0.0316653*N223-15.7623*V223+0.00202406*AA223-0.000740146*E223-0.00963493*(I223*N223) -> 7319.8265 | AM223: =5205.907083+122.0638992*I223+13.609808*(N223/1000)-1.245906883*AD223+0.7746840854*AE223-134.2474226*AC223-1547.125689*IF(AND(B223>=DATE(2020,3,20),B223<=DATE(2020,6,26)),1,0) -> 7615.16 | AN223: =7707.2178-144.397321*AC223+139.5614087*AF223-0.0008594506251*E223-265.7105668*I223-0.02506176117*J223+0.004708026652*N223 -> 9609.6306 | AO223: =IF(N223="","",2190.39 + 2739.06*I223 + 0.034693*N223 - 16.722*V223 - 0.000802*E223 - 1.3691*AD223 + 1.8691*AE223 - 121.7*AC223 + 209.88*IF(AND(B223>=DATE(2020,3,20),B223<=DATE(2020,6,26)),1,0) - 0.011049*(I223*N223)) -> 7285.5365 | AP223: =IF(B223<DATE(2008,1,1),"",3929.06 + 1212.53*I223 - 0.0003097*N223 + 59.426*V223 - 0.0006734*E223 - 1.036*AD223 + 1.2076*AE223 + 94.923*AF223 - 131.43*AC223 - 759.61*IF(AND(B223>=DATE(2020,3,20),B223<=DATE(2020,6,26)),1,0) - 17.324*(I223*V223)) | AQ223: =IF(N223="","",I223*N223) -> 196368.84 | AR223: =I223*E223 -> 419020 | AS223: =AC223*AF223 -> 0 | AT223: =IF(N223="","",2413.3773+89.103503*I223+0.018847679*N223-5.0917058*V223-0.00064564578*E223+1.4315076*AD223-3.1976817*AE223-66.972905*AC223-217.08397*IF(AND(B223>=DATE(2020,3,20),B223<=DATE(2020,6,26)),1,0)+190.76803*AF223) -> 7694.5931 | AU223: =IF(N223="","",-480.76297+2186.3009*I223+0.033368804*N223-5.3903106*V223-0.00073731439*E223+0.93396876*AD223-1.6242981*AE223-61.304389*AC223-95.472727*IF(AND(B223>=DATE(2020,3,20),B223<=DATE(2020,6,26)),1,0)+156.04851*AF223-0.0087322858*AQ223) -> 7437.1717 | AV223: =IF(N223="","",2518.0489-204.66184*I223+0.019354281*N223-2.3328708*V223-0.0022533804*E223+1.5259709*AD223-3.5842757*AE223-65.580099*AC223-62.828483*IF(AND(B223>=DATE(2020,3,20),B223<=DATE(2020,6,26)),1,0)+200.94286*AF223+0.00080379976*AR223) -> 7680.0489 | AW223: =IF(N223="","",2361.7153+89.223162*I223+0.018847054*N223-5.0210815*V223-0.0006437347*E223+1.4213619*AD223-3.2156123*AE223+167.41121*AC223-224.35191*IF(AND(B223>=DATE(2020,3,20),B223<=DATE(2020,6,26)),1,0)+194.56435*AF223-19.897843*AS223) -> 7700.826 | AX223: =IF(N223="","",-654.03928+2464.5589*I223+0.035956453*N223-8.0754527*V223-0.00069441316*E223+0.69511606*AD223-1.1669613*AE223-90.724569*AC223-211.24919*IF(AND(B223>=DATE(2020,3,20),B223<=DATE(2020,6,26)),1,0)+147.22132*AF223-0.010108087*AQ223) -> 7407.847
