Workbook

Sheet Model Notes
A1: Sunoco Weekly Gasoline Demand – Seasonal Index Model with Covariates
A3: Starting point
A4: Baseline | B4: The class ASI demo: linear trend on week number (2022–2024) × average seasonal index of the same week over those 3 years. It is rebuilt on the Data sheet (Baseline columns) only as a benchmark.
A6: How this model differs
A7: 1. Longer, cleaner time window | B7: Fits on 2015–2024 instead of 2022–2024, excluding 2020–2021 (COVID). That is 8 usable years (≈417 weeks) instead of 3 (156 weeks), so the seasonal pattern and trend are estimated from far more data.
A8: 2. Two covariates | B8: After removing seasonality, demand is regressed on week number plus two drivers from the new dataset (highway vehicle miles traveled and weekly jobless claims). Forecast = (intercept + b·Week# + c₁·X₁ + c₂·X₂) × Seasonal Index.
A9: 3. Calendar-based week matching | B9: Seasonal indices are matched on week-of-year from the date, so the model works across 53-week years (2026) and any window.
A10: 4. Normalized index | B10: The seasonal index is rescaled to average exactly 1.0, so seasonality doesn't shift the overall level.
A11: 5. Fully live estimation | B11: All coefficients are computed with formulas on the Regression sheet, including standard errors and t-stats. Pick different covariates or years on Inputs and everything re-estimates.
A13: Results
A14: 2025 validation (live) | B14: Baseline MAPE ≈ 3.57% → Covariate model ≈ 2.75% (see Accuracy). These are the predictions in sunoco_2025_forecast_covariate_model.csv (CSV Export sheet).
A15: 2024 holdout (static check) | B15: Refit through 2023: Baseline 3.02% → Covariate model 2.79%. Beating the baseline in both years means the gain isn't a one-year coincidence.
A17: How the covariates were chosen
A18: Search | B18: Tested every single covariate and pair from 12 candidates, across start years 2012, 2015, 2017, 2019, and 2022, scoring each on both 2024 and 2025. The 2015 start was clearly the best window.
A19: Vehicle miles traveled | B19: Strongest and most defensible driver: positive, as hypothesized (more driving → more gasoline), statistically significant (t ≈ 2.8), and it improves accuracy in both holdout years.
A20: Jobless claims | B20: Chosen as the second covariate because it is statistically significant (t ≈ −3.5) with the hypothesized negative sign: more layoffs, less driving. It costs a little accuracy versus VMT alone (2.75% vs 2.65% in 2025) but is far easier to justify.
A21: Cooling degree days – rejected | B21: Slightly more accurate (2.62% in 2025), but its sign is negative (hypothesis says positive) and it is not significant (t ≈ −1.5), so the gain is likely luck.
A22: US population – rejected | B22: Looks significant, but it is annual (10 distinct values) and correlates 0.99 with week number, so it duplicates the trend term; 2025 error rose to 3.04%.
A23: Gas price – alternative | B23: Regular gas price is highly significant with the hypothesized negative sign (t ≈ −7.5), but using it made 2025 forecasts worse (≈3.07%). It explains the past well yet predicts poorly, likely because price effects are already reflected in miles driven. Select it on Inputs to compare.
A24: Also tested, not helpful | B24: Holiday week flag (no gain; the week-of-year index already captures holidays), HDD, jobless claims, work-from-home share, S&P 500, refinery utilization.
A26: Caveats
A27: Covariates must be known | B27: The 2025/2026 forecasts use observed covariate values. In real forecasting you'd need forecasts of VMT and weather, which adds error. VMT is also released with a lag.
A28: Selection effect | B28: Choosing among many variants can flatter results a little; the two-year check limits but doesn't eliminate this.
A29: Weekly noise | B29: Weekly demand swings are large (about ±300–400 units, or 3–5%, from week to week), so individual weeks will still miss. The gains are in average accuracy.
A31: Color key
A32: Blue text | B32: Hard-coded data and inputs
A33: Black text | B33: Formulas
A34: Green text | B34: Links to other sheets
A35: Yellow fill | B35: Inputs you can change

Sheet Inputs
A1: Model Inputs
A2: Change the yellow cells. Everything else recalculates.
A4: Input | B4: Value | C4: Notes | F4: Covariate list
A5: First training year | B5: 2015 | D5: 2015 tested best across 2012/2015/2017/2019/2022 on both the 2024 and 2025 holdouts. | F5: sp500_weekly_avg
A6: Last training year | B6: 2024 | D6: Last year with known demand. The following year is scored as the validation year. | F6: initial_jobless_claims
A7: Excluded year #1 | B7: 2020 | D7: COVID lockdowns – excluded from fitting. | F7: tsa_passengers_weekly_avg
A8: Excluded year #2 | B8: 2021 | D8: COVID recovery – excluded from fitting. | F8: wti_spot_usd_per_bbl
C9: Column # | F9: brent_spot_usd_per_bbl
A10: Covariate 1 | B10: vehicle_miles_mil | C10: =MATCH(B10,Data!$E$1:$AF$1,0) -> 11 | D10: Highway vehicle miles traveled (FHWA). Pick from dropdown; list in column F. | F10: regular_gas_usd_per_gal
A11: Covariate 2 | B11: initial_jobless_claims | C11: =MATCH(B11,Data!$E$1:$AF$1,0) -> 2 | D11: Weekly initial jobless claims (seasonally adjusted). Significant, with the hypothesized negative sign. See Model Notes for alternatives. | F11: gdp_saar_bil_usd
F12: transit_unlinked_trips_thous
A13: Check: covariates must differ | B13: =IF(B10=B11,"ERROR – pick two different covariates","OK") -> OK | F13: rotary_rig_count
F14: vehicle_sales_saar_mil
A15: Training weeks used | B15: =SUM(Data!$AJ$2:$AJ$1857) -> 417 | F15: vehicle_miles_mil
A16: Validation year | B16: =B6+1 -> 2025 | F16: pce_saar_bil_usd
F17: consumer_credit_mil_usd
F18: ev_sales_vehicles
F19: regulated_afv_acquisitions
F20: household_debt_tril_usd
F21: eci_total_comp_index
F22: smoking_adults_pct
F23: refinery_utilization_pct
F24: fed_broad_dollar_index
F25: home_price_expectation_pct
F26: inflation_expectation_1y_pct
F27: mean_annual_earnings_thous_usd
F28: us_population_thous
... F32: cdd_pop_weighted

Sheet Accuracy
A1: Out-of-Sample Accuracy – Validation Year
A2: ="Scored on "&Inputs!B16&", a year excluded from fitting. Lower is better." -> Scored on 2025, a year excluded from fitting. Lower is better.
A4: Metric | B4: Baseline (class ASI demo) | C4: Covariate Model | D4: Change
A5: MAPE | B5: =AVERAGEIFS(Data!$BF$2:$BF$1857,Data!$AW$2:$AW$1857,"Validation") -> 0.035698798 | C5: =AVERAGEIFS(Data!$AY$2:$AY$1857,Data!$AW$2:$AW$1857,"Validation") -> 0.027467971 | D5: =IF(B5=0,"",C5/B5-1) -> -0.23056314
A6: MAE | B6: =SUMPRODUCT(ABS(Data!$BI$2:$BI$1857))/COUNT(Data!$AY$2:$AY$1857) -> 309.04318 | C6: =SUMPRODUCT(ABS(Data!$BH$2:$BH$1857))/COUNT(Data!$AY$2:$AY$1857) -> 243.85352 | D6: =IF(B6=0,"",C6/B6-1) -> -0.21094031
A7: RMSE | B7: =SQRT(SUMPRODUCT(Data!$BI$2:$BI$1857,Data!$BI$2:$BI$1857)/COUNT(Data!$AY$2:$AY$1857)) -> 384.22135 | C7: =SQRT(SUMPRODUCT(Data!$BH$2:$BH$1857,Data!$BH$2:$BH$1857)/COUNT(Data!$AY$2:$AY$1857)) -> 307.49367 | D7: =IF(B7=0,"",C7/B7-1) -> -0.19969656
A8: Bias (forecast − actual) | B8: =SUM(Data!$BI$2:$BI$1857)/COUNT(Data!$AY$2:$AY$1857) -> 176.24566 | C8: =SUM(Data!$BH$2:$BH$1857)/COUNT(Data!$AY$2:$AY$1857) -> -101.67609
A9: Weeks scored | B9: =COUNT(Data!$AY$2:$AY$1857) -> 52 | C9: =COUNT(Data!$AY$2:$AY$1857) -> 52
A11: 2024 holdout check (static, VMT + jobless claims)
A12: MAPE, both models refit through 2023 | B12: 0.0302 | C12: 0.0279 | D12: =C12/B12-1 -> -0.07615894
A13: Hardcoded from the Python backtest used to choose settings (VMT + jobless claims, 2015 start). Does not update if inputs change.
A15: Validation-year weekly detail
A16: Date | B16: Actual | C16: Baseline | D16: Covariate Model
A17: =Data!B1771 -> 45660 | B17: =Data!AX1771 -> 8481 | C17: =Data!BE1771 -> 8075.9313 | D17: =Data!AV1771 -> 8019.2615
A18: =Data!B1772 -> 45667 | B18: =Data!AX1772 -> 8325 | C18: =Data!BE1772 -> 8334.4438 | D18: =Data!AV1772 -> 8089.1826
A19: =Data!B1773 -> 45674 | B19: =Data!AX1773 -> 8086 | C19: =Data!BE1773 -> 8329.7326 | D19: =Data!AV1773 -> 8109.0838
A20: =Data!B1774 -> 45681 | B20: =Data!AX1774 -> 8302 | C20: =Data!BE1774 -> 8441.393 | D20: =Data!AV1774 -> 8299.1479
A21: =Data!B1775 -> 45688 | B21: =Data!AX1775 -> 8328 | C21: =Data!BE1775 -> 8951.4262 | D21: =Data!AV1775 -> 8396.2612
A22: =Data!B1776 -> 45695 | B22: =Data!AX1776 -> 8576 | C22: =Data!BE1776 -> 8493.6217 | D22: =Data!AV1776 -> 8166.7731
A23: =Data!B1777 -> 45702 | B23: =Data!AX1777 -> 8239 | C23: =Data!BE1777 -> 8750.1009 | D23: =Data!AV1777 -> 8377.5943
A24: =Data!B1778 -> 45709 | B24: =Data!AX1778 -> 8454 | C24: =Data!BE1778 -> 8937.9408 | D24: =Data!AV1778 -> 8493.6331
A25: =Data!B1779 -> 45716 | B25: =Data!AX1779 -> 8877 | C25: =Data!BE1779 -> 9009.8997 | D25: =Data!AV1779 -> 8513.596
A26: =Data!B1780 -> 45723 | B26: =Data!AX1780 -> 9182 | C26: =Data!BE1780 -> 9024.9945 | D26: =Data!AV1780 -> 8634.4886
A27: =Data!B1781 -> 45730 | B27: =Data!AX1781 -> 8817 | C27: =Data!BE1781 -> 8964.9699 | D27: =Data!AV1781 -> 8697.6961
A28: =Data!B1782 -> 45737 | B28: =Data!AX1782 -> 8643 | C28: =Data!BE1782 -> 8948.839 | D28: =Data!AV1782 -> 8583.8191 | F28: 2026 forecasts (covariate model)
A29: =Data!B1783 -> 45744 | B29: =Data!AX1783 -> 8495 | C29: =Data!BE1783 -> 9196.5836 | D29: =Data!AV1783 -> 8707.4551 | F29: Date | G29: Forecast
A30: =Data!B1784 -> 45751 | B30: =Data!AX1784 -> 8425 | C30: =Data!BE1784 -> 8924.3905 | D30: =Data!AV1784 -> 8612.6139 | F30: =Data!B1823 -> 46024 | G30: =Data!AV1823 -> 7970.2535
A31: =Data!B1785 -> 45758 | B31: =Data!AX1785 -> 8462 | C31: =Data!BE1785 -> 8844.8413 | D31: =Data!AV1785 -> 8675.0767 | F31: =Data!B1824 -> 46031 | G31: =Data!AV1824 -> 8015.372
A32: =Data!B1786 -> 45765 | B32: =Data!AX1786 -> 9414 | C32: =Data!BE1786 -> 9056.9958 | D32: =Data!AV1786 -> 8656.3031 | F32: =Data!B1825 -> 46038 | G32: =Data!AV1825 -> 8079.2269
A33: =Data!B1787 -> 45772 | B33: =Data!AX1787 -> 9098 | C33: =Data!BE1787 -> 8859.4809 | D33: =Data!AV1787 -> 8494.9722 | F33: =Data!B1826 -> 46045 | G33: =Data!AV1826 -> 8255.8615
A34: =Data!B1788 -> 45779 | B34: =Data!AX1788 -> 8717 | C34: =Data!BE1788 -> 9099.4511 | D34: =Data!AV1788 -> 8732.2314 | F34: =Data!B1827 -> 46052 | G34: =Data!AV1827 -> 8321.9006
A35: =Data!B1789 -> 45786 | B35: =Data!AX1789 -> 8794 | C35: =Data!BE1789 -> 9102.9247 | D35: =Data!AV1789 -> 8719.3429 | F35: =Data!B1828 -> 46059 | G35: =Data!AV1828 -> 8066.8049
A36: =Data!B1790 -> 45793 | B36: =Data!AX1790 -> 8644 | C36: =Data!BE1790 -> 9352.0287 | D36: =Data!AV1790 -> 8989.4188 | F36: =Data!B1829 -> 46066 | G36: =Data!AV1829 -> 8264.9233
A37: =Data!B1791 -> 45800 | B37: =Data!AX1791 -> 9452 | C37: =Data!BE1791 -> 9242.0698 | D37: =Data!AV1791 -> 8988.0557 | F37: =Data!B1830 -> 46073 | G37: =Data!AV1830 -> 8456.0396
A38: =Data!B1792 -> 45807 | B38: =Data!AX1792 -> 8263 | C38: =Data!BE1792 -> 9290.9 | D38: =Data!AV1792 -> 8772.4003 | F38: =Data!B1831 -> 46080 | G38: =Data!AV1831 -> 8514.9783
A39: =Data!B1793 -> 45814 | B39: =Data!AX1793 -> 9170 | C39: =Data!BE1793 -> 9277.6807 | D39: =Data!AV1793 -> 8952.7476 | F39: =Data!B1832 -> 46087 | G39: =Data!AV1832 -> 8583.0337
A40: =Data!B1794 -> 45821 | B40: =Data!AX1794 -> 9299 | C40: =Data!BE1794 -> 9254.3446 | D40: =Data!AV1794 -> 8918.817 | F40: =Data!B1833 -> 46094 | G40: =Data!AV1833 -> 8643.2262
A41: =Data!B1795 -> 45828 | B41: =Data!AX1795 -> 9688 | C41: =Data!BE1795 -> 9233.5056 | D41: =Data!AV1795 -> 8939.0314 | F41: =Data!B1834 -> 46101 | G41: =Data!AV1834 -> 8556.5249
... A64: =Data!B1818 -> 45989 | B64: =Data!AX1818 -> 8326 | C64: =Data!BE1818 -> 8676.7311 | D64: =Data!AV1818 -> 8441.4985 | F64: =Data!B1857 -> 46262 | G64: =Data!AV1857 -> 8851.4663
A65: =Data!B1819 -> 45996 | B65: =Data!AX1819 -> 8456 | C65: =Data!BE1819 -> 8799.0423 | D65: =Data!AV1819 -> 8493.1491
A66: =Data!B1820 -> 46003 | B66: =Data!AX1820 -> 9078 | C66: =Data!BE1820 -> 8959.986 | D66: =Data!AV1820 -> 8617.1195
A67: =Data!B1821 -> 46010 | B67: =Data!AX1821 -> 8942 | C67: =Data!BE1821 -> 9337.7623 | D67: =Data!AV1821 -> 8851.6007
A68: =Data!B1822 -> 46017 | B68: =Data!AX1822 -> 8563 | C68: =Data!BE1822 -> 8021.9218 | D68: =Data!AV1822 -> 8171.8017
A70: Detail rows are fixed to calendar 2025 (the default validation year).

Sheet CSV Export
A1: date | B1: prediction | D1: Matches sunoco_2025_forecast_covariate_model.csv (same model, same settings).
A2: =Data!B1771 -> 45660 | B2: =Data!AV1771 -> 8019.2615 | D2: To export: File > Save As > CSV while this sheet is active (dates are formatted yyyy-mm-dd).
A3: =Data!B1772 -> 45667 | B3: =Data!AV1772 -> 8089.1826
A4: =Data!B1773 -> 45674 | B4: =Data!AV1773 -> 8109.0838
A5: =Data!B1774 -> 45681 | B5: =Data!AV1774 -> 8299.1479
A6: =Data!B1775 -> 45688 | B6: =Data!AV1775 -> 8396.2612
A7: =Data!B1776 -> 45695 | B7: =Data!AV1776 -> 8166.7731
A8: =Data!B1777 -> 45702 | B8: =Data!AV1777 -> 8377.5943
A9: =Data!B1778 -> 45709 | B9: =Data!AV1778 -> 8493.6331
A10: =Data!B1779 -> 45716 | B10: =Data!AV1779 -> 8513.596
A11: =Data!B1780 -> 45723 | B11: =Data!AV1780 -> 8634.4886
A12: =Data!B1781 -> 45730 | B12: =Data!AV1781 -> 8697.6961
A13: =Data!B1782 -> 45737 | B13: =Data!AV1782 -> 8583.8191
A14: =Data!B1783 -> 45744 | B14: =Data!AV1783 -> 8707.4551
... A53: =Data!B1822 -> 46017 | B53: =Data!AV1822 -> 8171.8017

Sheet Regression
A1: Two-Step Model Estimation
A2: Step 1: trend on Week # → seasonal index. Step 2: regress deseasonalized demand on Week # + 2 covariates.
B4: Step 1 – Trend (training weeks)
B5: Intercept | C5: =(C11-C6*C10)/C9 -> 10846.55
B6: Slope per week | C6: =(C9*C8-C10*C11)/(C9*C7-C10^2) -> -1.1726749
B7: Σt² (helper) | C7: =SUMPRODUCT((Data!$AJ$2:$AJ$1857=1)*Data!$A$2:$A$1857*Data!$A$2:$A$1857) -> 943749560
B8: Σty (helper) | C8: =SUMPRODUCT(Data!$AJ$2:$AJ$1857,Data!$A$2:$A$1857,Data!$BG$2:$BG$1857) -> 5656459557
B9: n | C9: =SUM(Data!$AJ$2:$AJ$1857) -> 417
B10: Σt | C10: =SUMIFS(Data!$A$2:$A$1857,Data!$AJ$2:$AJ$1857,1) -> 623532
B11: Σy | C11: =SUMIFS(Data!$C$2:$C$1857,Data!$AJ$2:$AJ$1857,1) -> 3791811
B13: Step 2 – Multiple regression on deseasonalized demand
C14: Week # | D14: =Inputs!B10 -> vehicle_miles_mil | E14: =Inputs!B11 -> initial_jobless_claims | F14: Deseas. Demand
B15: Training mean | C15: =AVERAGEIFS(Data!$A$2:$A$1857,Data!$AJ$2:$AJ$1857,1) -> 1495.2806 | D15: =AVERAGEIFS(Data!$AK$2:$AK$1857,Data!$AJ$2:$AJ$1857,1) -> 267402.98 | E15: =AVERAGEIFS(Data!$AL$2:$AL$1857,Data!$AJ$2:$AJ$1857,1) -> 235292.57 | F15: =AVERAGEIFS(Data!$AP$2:$AP$1857,Data!$AJ$2:$AJ$1857,1) -> 9094.5726
B16: Std. dev. | C16: =SQRT(SUMPRODUCT(Data!$AQ$2:$AQ$1857,Data!$AQ$2:$AQ$1857)/$C$9) -> 165.30092 | D16: =SQRT(SUMPRODUCT(Data!$AR$2:$AR$1857,Data!$AR$2:$AR$1857)/$C$9) -> 17922.091 | E16: =SQRT(SUMPRODUCT(Data!$AS$2:$AS$1857,Data!$AS$2:$AS$1857)/$C$9) -> 25481.187 | F16: =SQRT(SUMPRODUCT(Data!$AT$2:$AT$1857,Data!$AT$2:$AT$1857)/$C$9) -> 362.09315
B18: Correlation matrix (R) | G18: Corr with y
B19: Week # | C19: =SUMPRODUCT(Data!$AQ$2:$AQ$1857,Data!$AQ$2:$AQ$1857)/($C$9*C$16*C$16) -> 1 | D19: =SUMPRODUCT(Data!$AQ$2:$AQ$1857,Data!$AR$2:$AR$1857)/($C$9*C$16*D$16) -> 0.26030889 | E19: =SUMPRODUCT(Data!$AQ$2:$AQ$1857,Data!$AS$2:$AS$1857)/($C$9*C$16*E$16) -> -0.67618286 | G19: =SUMPRODUCT(Data!$AQ$2:$AQ$1857,Data!$AT$2:$AT$1857)/($C$9*C$16*$F$16) -> -0.56337162
B20: Covariate 1 | C20: =SUMPRODUCT(Data!$AR$2:$AR$1857,Data!$AQ$2:$AQ$1857)/($C$9*D$16*C$16) -> 0.26030889 | D20: =SUMPRODUCT(Data!$AR$2:$AR$1857,Data!$AR$2:$AR$1857)/($C$9*D$16*D$16) -> 1 | E20: =SUMPRODUCT(Data!$AR$2:$AR$1857,Data!$AS$2:$AS$1857)/($C$9*D$16*E$16) -> -0.22243198 | G20: =SUMPRODUCT(Data!$AR$2:$AR$1857,Data!$AT$2:$AT$1857)/($C$9*D$16*$F$16) -> -0.053784489
B21: Covariate 2 | C21: =SUMPRODUCT(Data!$AS$2:$AS$1857,Data!$AQ$2:$AQ$1857)/($C$9*E$16*C$16) -> -0.67618286 | D21: =SUMPRODUCT(Data!$AS$2:$AS$1857,Data!$AR$2:$AR$1857)/($C$9*E$16*D$16) -> -0.22243198 | E21: =SUMPRODUCT(Data!$AS$2:$AS$1857,Data!$AS$2:$AS$1857)/($C$9*E$16*E$16) -> 1 | G21: =SUMPRODUCT(Data!$AS$2:$AS$1857,Data!$AT$2:$AT$1857)/($C$9*E$16*$F$16) -> 0.27533768
B23: det(R) | C23: =MDETERM(C19:E21) -> 0.50384339
B25: Cramer matrices (column k replaced by corr-with-y)
C26: k = Week # | G26: k = Cov 1 | K26: k = Cov 2
C27: =$G$19 -> -0.56337162 | D27: =D19 -> 0.26030889 | E27: =E19 -> -0.67618286 | G27: =C19 -> 1 | H27: =$G$19 -> -0.56337162 | I27: =E19 -> -0.67618286 | K27: =C19 -> 1 | L27: =D19 -> 0.26030889 | M27: =$G$19 -> -0.56337162
C28: =$G$20 -> -0.053784489 | D28: =D20 -> 1 | E28: =E20 -> -0.22243198 | G28: =C20 -> 0.26030889 | H28: =$G$20 -> -0.053784489 | I28: =E20 -> -0.22243198 | K28: =C20 -> 0.26030889 | L28: =D20 -> 1 | M28: =$G$20 -> -0.053784489
C29: =$G$21 -> 0.27533768 | D29: =D21 -> -0.22243198 | E29: =E21 -> 1 | G29: =C21 -> -0.67618286 | H29: =$G$21 -> 0.27533768 | I29: =E21 -> 1 | K29: =C21 -> -0.67618286 | L29: =D21 -> -0.22243198 | M29: =$G$21 -> 0.27533768
B31: Standardized beta | C31: =MDETERM(C27:E29)/$C$23 -> -0.71321927 | G31: =MDETERM(G27:I29)/$C$23 -> 0.090313563 | K31: =MDETERM(K27:M29)/$C$23 -> -0.18684034
C34: Intercept | D34: Week # | E34: Covariate 1 | F34: Covariate 2
B35: Variable | C35: (constant) | D35: Week # | E35: =Inputs!B10 -> vehicle_miles_mil | F35: =Inputs!B11 -> initial_jobless_claims
B36: Std. beta | D36: =C31 -> -0.71321927 | E36: =G31 -> 0.090313563 | F36: =K31 -> -0.18684034
B38: Coefficient | C38: =F15-D38*C15-E38*D15-F38*E15 -> 11567.458 | D38: =D36*$F$16/C16 -> -1.5623132 | E38: =E36*$F$16/D16 -> 0.0018246711 | F38: =F36*$F$16/E16 -> -0.0026550414
B39: Inverse-diag (R⁻¹) | D39: =(D20*E21-E20*D21)/$C$23 -> 1.8865465 | E39: =(C19*E21-E19*C21)/$C$23 -> 1.0772727 | F39: =(C19*D20-D19*C20)/$C$23 -> 1.850256
B40: Standard error | D40: =SQRT($C$49*D39/($C$9*C16^2)) -> 0.11977237 | E40: =SQRT($C$49*E39/($C$9*D16^2)) -> 0.00083478054 | F40: =SQRT($C$49*F39/($C$9*E16^2)) -> 0.00076947484
B41: t Stat | D41: =D38/D40 -> -13.04402 | E41: =E38/E40 -> 2.1858094 | F41: =F38/F40 -> -3.450459
B42: Sign matches hypothesis? | D42: n/a | E42: =IFERROR(IF(INDEX(Hyp!$D:$D,MATCH(E35,Hyp!$A:$A,0))="Positive",IF(E38>0,"Yes","No"),IF(INDEX(Hyp!$D:$D,MATCH(E35,Hyp!$A:$A,0))="Negative",IF(E38<0,"Yes","No"),"Conditional")),"n/a") -> Yes | F42: =IFERROR(IF(INDEX(Hyp!$D:$D,MATCH(F35,Hyp!$A:$A,0))="Positive",IF(F38>0,"Yes","No"),IF(INDEX(Hyp!$D:$D,MATCH(F35,Hyp!$A:$A,0))="Negative",IF(F38<0,"Yes","No"),"Conditional")),"n/a") -> Yes
B43: |t| > 2 means the coefficient is statistically significant at roughly the 5% level.
B44: Baseline (class ASI demo) trend, 2022–2024
B45: Intercept | C45: =(SUMPRODUCT((Data!$AH$2:$AH$1857>=2022)*(Data!$AH$2:$AH$1857<=2024)*Data!$BG$2:$BG$1857)-C46*SUMPRODUCT((Data!$AH$2:$AH$1857>=2022)*(Data!$AH$2:$AH$1857<=2024)*Data!$A$2:$A$1857))/C47 -> 6144.2795
B46: Slope per week | C46: =(C47*SUMPRODUCT((Data!$AH$2:$AH$1857>=2022)*(Data!$AH$2:$AH$1857<=2024)*Data!$A$2:$A$1857*Data!$BG$2:$BG$1857)-SUMPRODUCT((Data!$AH$2:$AH$1857>=2022)*(Data!$AH$2:$AH$1857<=2024)*Data!$A$2:$A$1857)*SUMPRODUCT((Data!$AH$2:$AH$1857>=2022)*(Data!$AH$2:$AH$1857<=2024)*Data!$BG$2:$BG$1857))/(C47*SUMPRODUCT((Data!$AH$2:$AH$1857>=2022)*(Data!$AH$2:$AH$1857<=2024)*Data!$A$2:$A$1857^2)-SUMPRODUCT((Data!$AH$2:$AH$1857>=2022)*(Data!$AH$2:$AH$1857<=2024)*Data!$A$2:$A$1857)^2) -> 1.5594996
B47: n | C47: =SUMPRODUCT((Data!$AH$2:$AH$1857>=2022)*(Data!$AH$2:$AH$1857<=2024)) -> 156
B49: Residual variance (s²) | C49: =SUMPRODUCT(Data!$AZ$2:$AZ$1857,Data!$AZ$2:$AZ$1857)/(C9-4) -> 86642.781
B50: R² (deseasonalized) | C50: =1-SUMPRODUCT(Data!$AZ$2:$AZ$1857,Data!$AZ$2:$AZ$1857)/SUMPRODUCT(Data!$AT$2:$AT$1857,Data!$AT$2:$AT$1857) -> 0.34550584
B51: Std. error of regression | C51: =SQRT(C49) -> 294.35146

Sheet Seasonal Index
A1: Week of Year | B1: Avg SI (training) | C1: # Weeks | D1: Sum Check | E1: Seasonal Index (normalized) | G1: Baseline avg SI (2022–24) | H1: Baseline ASI
A2: 1 | B2: =AVERAGEIFS(Data!$AN$2:$AN$1857,Data!$AI$2:$AI$1857,A2,Data!$AJ$2:$AJ$1857,1) -> 0.91478473 | C2: =COUNTIFS(Data!$AI$2:$AI$1857,A2,Data!$AJ$2:$AJ$1857,1) -> 8 | E2: =B2/AVERAGE($B$2:$B$53) -> 0.91465819 | G2: =AVERAGEIFS(Data!$BC$2:$BC$1857,Data!$AI$2:$AI$1857,A2,Data!$AH$2:$AH$1857,">=2022",Data!$AH$2:$AH$1857,"<=2024") -> 0.90693989 | H2: =G2 -> 0.90693989
A3: 2 | B3: =AVERAGEIFS(Data!$AN$2:$AN$1857,Data!$AI$2:$AI$1857,A3,Data!$AJ$2:$AJ$1857,1) -> 0.92125116 | C3: =COUNTIFS(Data!$AI$2:$AI$1857,A3,Data!$AJ$2:$AJ$1857,1) -> 8 | E3: =B3/AVERAGE($B$2:$B$53) -> 0.92112372 | G3: =AVERAGEIFS(Data!$BC$2:$BC$1857,Data!$AI$2:$AI$1857,A3,Data!$AH$2:$AH$1857,">=2022",Data!$AH$2:$AH$1857,"<=2024") -> 0.93580736 | H3: =G3 -> 0.93580736
A4: 3 | B4: =AVERAGEIFS(Data!$AN$2:$AN$1857,Data!$AI$2:$AI$1857,A4,Data!$AJ$2:$AJ$1857,1) -> 0.93260472 | C4: =COUNTIFS(Data!$AI$2:$AI$1857,A4,Data!$AJ$2:$AJ$1857,1) -> 8 | E4: =B4/AVERAGE($B$2:$B$53) -> 0.93247571 | G4: =AVERAGEIFS(Data!$BC$2:$BC$1857,Data!$AI$2:$AI$1857,A4,Data!$AH$2:$AH$1857,">=2022",Data!$AH$2:$AH$1857,"<=2024") -> 0.93511464 | H4: =G4 -> 0.93511464
A5: 4 | B5: =AVERAGEIFS(Data!$AN$2:$AN$1857,Data!$AI$2:$AI$1857,A5,Data!$AJ$2:$AJ$1857,1) -> 0.95580246 | C5: =COUNTIFS(Data!$AI$2:$AI$1857,A5,Data!$AJ$2:$AJ$1857,1) -> 8 | E5: =B5/AVERAGE($B$2:$B$53) -> 0.95567024 | G5: =AVERAGEIFS(Data!$BC$2:$BC$1857,Data!$AI$2:$AI$1857,A5,Data!$AH$2:$AH$1857,">=2022",Data!$AH$2:$AH$1857,"<=2024") -> 0.947484 | H5: =G5 -> 0.947484
A6: 5 | B6: =AVERAGEIFS(Data!$AN$2:$AN$1857,Data!$AI$2:$AI$1857,A6,Data!$AJ$2:$AJ$1857,1) -> 0.96391855 | C6: =COUNTIFS(Data!$AI$2:$AI$1857,A6,Data!$AJ$2:$AJ$1857,1) -> 8 | E6: =B6/AVERAGE($B$2:$B$53) -> 0.96378521 | G6: =AVERAGEIFS(Data!$BC$2:$BC$1857,Data!$AI$2:$AI$1857,A6,Data!$AH$2:$AH$1857,">=2022",Data!$AH$2:$AH$1857,"<=2024") -> 1.0045556 | H6: =G6 -> 1.0045556
A7: 6 | B7: =AVERAGEIFS(Data!$AN$2:$AN$1857,Data!$AI$2:$AI$1857,A7,Data!$AJ$2:$AJ$1857,1) -> 0.94003306 | C7: =COUNTIFS(Data!$AI$2:$AI$1857,A7,Data!$AJ$2:$AJ$1857,1) -> 8 | E7: =B7/AVERAGE($B$2:$B$53) -> 0.93990302 | G7: =AVERAGEIFS(Data!$BC$2:$BC$1857,Data!$AI$2:$AI$1857,A7,Data!$AH$2:$AH$1857,">=2022",Data!$AH$2:$AH$1857,"<=2024") -> 0.95301266 | H7: =G7 -> 0.95301266
A8: 7 | B8: =AVERAGEIFS(Data!$AN$2:$AN$1857,Data!$AI$2:$AI$1857,A8,Data!$AJ$2:$AJ$1857,1) -> 0.96329535 | C8: =COUNTIFS(Data!$AI$2:$AI$1857,A8,Data!$AJ$2:$AJ$1857,1) -> 8 | E8: =B8/AVERAGE($B$2:$B$53) -> 0.96316209 | G8: =AVERAGEIFS(Data!$BC$2:$BC$1857,Data!$AI$2:$AI$1857,A8,Data!$AH$2:$AH$1857,">=2022",Data!$AH$2:$AH$1857,"<=2024") -> 0.98161871 | H8: =G8 -> 0.98161871
A9: 8 | B9: =AVERAGEIFS(Data!$AN$2:$AN$1857,Data!$AI$2:$AI$1857,A9,Data!$AJ$2:$AJ$1857,1) -> 0.97852242 | C9: =COUNTIFS(Data!$AI$2:$AI$1857,A9,Data!$AJ$2:$AJ$1857,1) -> 8 | E9: =B9/AVERAGE($B$2:$B$53) -> 0.97838706 | G9: =AVERAGEIFS(Data!$BC$2:$BC$1857,Data!$AI$2:$AI$1857,A9,Data!$AH$2:$AH$1857,">=2022",Data!$AH$2:$AH$1857,"<=2024") -> 1.0025159 | H9: =G9 -> 1.0025159
A10: 9 | B10: =AVERAGEIFS(Data!$AN$2:$AN$1857,Data!$AI$2:$AI$1857,A10,Data!$AJ$2:$AJ$1857,1) -> 0.98643013 | C10: =COUNTIFS(Data!$AI$2:$AI$1857,A10,Data!$AJ$2:$AJ$1857,1) -> 8 | E10: =B10/AVERAGE($B$2:$B$53) -> 0.98629368 | G10: =AVERAGEIFS(Data!$BC$2:$BC$1857,Data!$AI$2:$AI$1857,A10,Data!$AH$2:$AH$1857,">=2022",Data!$AH$2:$AH$1857,"<=2024") -> 1.0104104 | H10: =G10 -> 1.0104104
A11: 10 | B11: =AVERAGEIFS(Data!$AN$2:$AN$1857,Data!$AI$2:$AI$1857,A11,Data!$AJ$2:$AJ$1857,1) -> 0.99541261 | C11: =COUNTIFS(Data!$AI$2:$AI$1857,A11,Data!$AJ$2:$AJ$1857,1) -> 8 | E11: =B11/AVERAGE($B$2:$B$53) -> 0.99527491 | G11: =AVERAGEIFS(Data!$BC$2:$BC$1857,Data!$AI$2:$AI$1857,A11,Data!$AH$2:$AH$1857,">=2022",Data!$AH$2:$AH$1857,"<=2024") -> 1.0119262 | H11: =G11 -> 1.0119262
A12: 11 | B12: =AVERAGEIFS(Data!$AN$2:$AN$1857,Data!$AI$2:$AI$1857,A12,Data!$AJ$2:$AJ$1857,1) -> 1.0022664 | C12: =COUNTIFS(Data!$AI$2:$AI$1857,A12,Data!$AJ$2:$AJ$1857,1) -> 8 | E12: =B12/AVERAGE($B$2:$B$53) -> 1.0021278 | G12: =AVERAGEIFS(Data!$BC$2:$BC$1857,Data!$AI$2:$AI$1857,A12,Data!$AH$2:$AH$1857,">=2022",Data!$AH$2:$AH$1857,"<=2024") -> 1.0050202 | H12: =G12 -> 1.0050202
A13: 12 | B13: =AVERAGEIFS(Data!$AN$2:$AN$1857,Data!$AI$2:$AI$1857,A13,Data!$AJ$2:$AJ$1857,1) -> 0.99268835 | C13: =COUNTIFS(Data!$AI$2:$AI$1857,A13,Data!$AJ$2:$AJ$1857,1) -> 8 | E13: =B13/AVERAGE($B$2:$B$53) -> 0.99255102 | G13: =AVERAGEIFS(Data!$BC$2:$BC$1857,Data!$AI$2:$AI$1857,A13,Data!$AH$2:$AH$1857,">=2022",Data!$AH$2:$AH$1857,"<=2024") -> 1.0030365 | H13: =G13 -> 1.0030365
... A53: 52 | B53: =AVERAGEIFS(Data!$AN$2:$AN$1857,Data!$AI$2:$AI$1857,A53,Data!$AJ$2:$AJ$1857,1) -> 0.9411899 | C53: =COUNTIFS(Data!$AI$2:$AI$1857,A53,Data!$AJ$2:$AJ$1857,1) -> 9 | E53: =B53/AVERAGE($B$2:$B$53) -> 0.9410597 | G53: =AVERAGEIFS(Data!$BC$2:$BC$1857,Data!$AI$2:$AI$1857,A53,Data!$AH$2:$AH$1857,">=2022",Data!$AH$2:$AH$1857,"<=2024") -> 0.8928993 | H53: =G53 -> 0.8928993
A55: Average of index (should be 1.0000) | E55: =AVERAGE(E2:E53) -> 1
A57: The improved index is normalized so it averages exactly 1; the baseline ASI is left unnormalized, as in the class demo.

Sheet Data
A1: Week # | B1: Date | C1: Demand | D1: Actual 2025 | E1: sp500_weekly_avg | F1: initial_jobless_claims | G1: tsa_passengers_weekly_avg | H1: wti_spot_usd_per_bbl | I1: brent_spot_usd_per_bbl | J1: regular_gas_usd_per_gal | K1: gdp_saar_bil_usd | L1: transit_unlinked_trips_thous | M1: rotary_rig_count | N1: vehicle_sales_saar_mil | O1: vehicle_miles_mil | P1: pce_saar_bil_usd | Q1: consumer_credit_mil_usd | R1: ev_sales_vehicles | S1: regulated_afv_acquisitions | T1: household_debt_tril_usd | U1: eci_total_comp_index | V1: smoking_adults_pct | W1: refinery_utilization_pct | X1: fed_broad_dollar_index | Y1: home_price_expectation_pct | Z1: inflation_expectation_1y_pct | AA1: mean_annual_earnings_thous_usd | AB1: us_population_thous | AC1: wfh_share_paid_days_pct | AD1: major_holiday_week | AE1: hdd_pop_weighted | AF1: cdd_pop_weighted | AH1: Year | AI1: Week of Year | AJ1: In Training (1/0) | AK1: Covariate 1 | AL1: Covariate 2 | AM1: Trend | AN1: SI | AO1: Seasonal Index | AP1: Deseasonalized Demand | AQ1: dev t | AR1: dev X1 | AS1: dev X2 | AT1: dev y | AU1: Fitted Deseasonalized | AV1: Forecast | AW1: Set | AX1: Actual (scoring) | AY1: Abs % Err | AZ1: Residual (train) | BB1: Baseline Trend (2022–24) | BC1: Baseline SI | BD1: Baseline ASI | BE1: Baseline Forecast | BF1: Baseline Abs % Err | BG1: Demand (0 if blank) | BH1: Signed Err – Model | BI1: Signed Err – Baseline
A2: 1 | B2: 33277 | C2: 6621 | F2: 483000 | H2: 21.304 | I2: 20.626 | J2: 1.139 | M2: 1136 | W2: 84.2 | AD2: 0 | AE2: 18.5 | AF2: 0 | AH2: =YEAR(B2) -> 1991 | AI2: =MIN(52,INT((B2-DATE(AH2,1,1))/7)+1) -> 6 | AJ2: =IF(AND(ISNUMBER(C2),ISNUMBER(AK2),ISNUMBER(AL2),AH2>=Inputs!$B$5,AH2<=Inputs!$B$6,AH2<>Inputs!$B$7,AH2<>Inputs!$B$8),1,0) -> 0 | AK2: =IF(INDEX($E2:$AF2,Inputs!$C$10)="","",INDEX($E2:$AF2,Inputs!$C$10)) | AL2: =IF(INDEX($E2:$AF2,Inputs!$C$11)="","",INDEX($E2:$AF2,Inputs!$C$11)) -> 483000 | AM2: =Regression!$C$5+Regression!$C$6*A2 -> 10845.377 | AN2: =IF(AJ2=1,C2/AM2,"") | AO2: =INDEX('Seasonal Index'!$E$2:$E$53,AI2) -> 0.93990302 | AP2: =IF(AJ2=1,C2/AO2,"") | AQ2: =IF(AJ2=1,A2-Regression!$C$15,0) -> 0 | AR2: =IF(AJ2=1,AK2-Regression!$D$15,0) -> 0 | AS2: =IF(AJ2=1,AL2-Regression!$E$15,0) -> 0 | AT2: =IF(AJ2=1,AP2-Regression!$F$15,0) -> 0 | AU2: =IF(AND(ISNUMBER(AK2),ISNUMBER(AL2)),Regression!$C$38+Regression!$D$38*A2+Regression!$E$38*AK2+Regression!$F$38*AL2,"") | AV2: =IF(ISNUMBER(AU2),AU2*AO2,"") | AW2: =IF(AJ2=1,"Train",IF(AH2=Inputs!$B$6+1,"Validation",IF(AH2>Inputs!$B$6+1,"Forecast","Not used"))) -> Not used | AX2: =IF(ISNUMBER(C2),C2,IF(ISNUMBER(D2),D2,"")) -> 6621 | AY2: =IF(AND(AW2="Validation",ISNUMBER(AX2),ISNUMBER(AV2)),ABS(AX2-AV2)/AX2,"") | AZ2: =IF(AJ2=1,AP2-AU2,0) -> 0 | BB2: =Regression!$C$45+Regression!$C$46*A2 -> 6145.839 | BC2: =IF(AND(AH2>=2022,AH2<=2024),C2/BB2,"") | BD2: =INDEX('Seasonal Index'!$H$2:$H$53,AI2) -> 0.95301266 | BE2: =IF(AH2>=2022,BB2*BD2,"") | BF2: =IF(AND(AW2="Validation",ISNUMBER(AX2),ISNUMBER(BE2)),ABS(AX2-BE2)/AX2,"") | BG2: =IF(ISNUMBER(C2),C2,0) -> 6621 | BH2: =IF(ISNUMBER(AY2),AV2-AX2,0) -> 0 | BI2: =IF(ISNUMBER(AY2),BE2-AX2,0) -> 0
A3: 2 | B3: 33284 | C3: 6433 | F3: 480000 | H3: 22.116 | I3: 20.436 | J3: 1.106 | M3: 1136 | W3: 84.2 | AD3: 0 | AE3: 145.9 | AF3: 0.7 | AH3: =YEAR(B3) -> 1991 | AI3: =MIN(52,INT((B3-DATE(AH3,1,1))/7)+1) -> 7 | AJ3: =IF(AND(ISNUMBER(C3),ISNUMBER(AK3),ISNUMBER(AL3),AH3>=Inputs!$B$5,AH3<=Inputs!$B$6,AH3<>Inputs!$B$7,AH3<>Inputs!$B$8),1,0) -> 0 | AK3: =IF(INDEX($E3:$AF3,Inputs!$C$10)="","",INDEX($E3:$AF3,Inputs!$C$10)) | AL3: =IF(INDEX($E3:$AF3,Inputs!$C$11)="","",INDEX($E3:$AF3,Inputs!$C$11)) -> 480000 | AM3: =Regression!$C$5+Regression!$C$6*A3 -> 10844.205 | AN3: =IF(AJ3=1,C3/AM3,"") | AO3: =INDEX('Seasonal Index'!$E$2:$E$53,AI3) -> 0.96316209 | AP3: =IF(AJ3=1,C3/AO3,"") | AQ3: =IF(AJ3=1,A3-Regression!$C$15,0) -> 0 | AR3: =IF(AJ3=1,AK3-Regression!$D$15,0) -> 0 | AS3: =IF(AJ3=1,AL3-Regression!$E$15,0) -> 0 | AT3: =IF(AJ3=1,AP3-Regression!$F$15,0) -> 0 | AU3: =IF(AND(ISNUMBER(AK3),ISNUMBER(AL3)),Regression!$C$38+Regression!$D$38*A3+Regression!$E$38*AK3+Regression!$F$38*AL3,"") | AV3: =IF(ISNUMBER(AU3),AU3*AO3,"") | AW3: =IF(AJ3=1,"Train",IF(AH3=Inputs!$B$6+1,"Validation",IF(AH3>Inputs!$B$6+1,"Forecast","Not used"))) -> Not used | AX3: =IF(ISNUMBER(C3),C3,IF(ISNUMBER(D3),D3,"")) -> 6433 | AY3: =IF(AND(AW3="Validation",ISNUMBER(AX3),ISNUMBER(AV3)),ABS(AX3-AV3)/AX3,"") | AZ3: =IF(AJ3=1,AP3-AU3,0) -> 0 | BB3: =Regression!$C$45+Regression!$C$46*A3 -> 6147.3985 | BC3: =IF(AND(AH3>=2022,AH3<=2024),C3/BB3,"") | BD3: =INDEX('Seasonal Index'!$H$2:$H$53,AI3) -> 0.98161871 | BE3: =IF(AH3>=2022,BB3*BD3,"") | BF3: =IF(AND(AW3="Validation",ISNUMBER(AX3),ISNUMBER(BE3)),ABS(AX3-BE3)/AX3,"") | BG3: =IF(ISNUMBER(C3),C3,0) -> 6433 | BH3: =IF(ISNUMBER(AY3),AV3-AX3,0) -> 0 | BI3: =IF(ISNUMBER(AY3),BE3-AX3,0) -> 0
A4: 3 | B4: 33291 | C4: 6582 | F4: 474000 | H4: 19.38 | I4: 18.126 | J4: 1.078 | M4: 1136 | N4: 11.829 | W4: 84.2 | AD4: 0 | AE4: 130.1 | AF4: 1.5 | AH4: =YEAR(B4) -> 1991 | AI4: =MIN(52,INT((B4-DATE(AH4,1,1))/7)+1) -> 8 | AJ4: =IF(AND(ISNUMBER(C4),ISNUMBER(AK4),ISNUMBER(AL4),AH4>=Inputs!$B$5,AH4<=Inputs!$B$6,AH4<>Inputs!$B$7,AH4<>Inputs!$B$8),1,0) -> 0 | AK4: =IF(INDEX($E4:$AF4,Inputs!$C$10)="","",INDEX($E4:$AF4,Inputs!$C$10)) | AL4: =IF(INDEX($E4:$AF4,Inputs!$C$11)="","",INDEX($E4:$AF4,Inputs!$C$11)) -> 474000 | AM4: =Regression!$C$5+Regression!$C$6*A4 -> 10843.032 | AN4: =IF(AJ4=1,C4/AM4,"") | AO4: =INDEX('Seasonal Index'!$E$2:$E$53,AI4) -> 0.97838706 | AP4: =IF(AJ4=1,C4/AO4,"") | AQ4: =IF(AJ4=1,A4-Regression!$C$15,0) -> 0 | AR4: =IF(AJ4=1,AK4-Regression!$D$15,0) -> 0 | AS4: =IF(AJ4=1,AL4-Regression!$E$15,0) -> 0 | AT4: =IF(AJ4=1,AP4-Regression!$F$15,0) -> 0 | AU4: =IF(AND(ISNUMBER(AK4),ISNUMBER(AL4)),Regression!$C$38+Regression!$D$38*A4+Regression!$E$38*AK4+Regression!$F$38*AL4,"") | AV4: =IF(ISNUMBER(AU4),AU4*AO4,"") | AW4: =IF(AJ4=1,"Train",IF(AH4=Inputs!$B$6+1,"Validation",IF(AH4>Inputs!$B$6+1,"Forecast","Not used"))) -> Not used | AX4: =IF(ISNUMBER(C4),C4,IF(ISNUMBER(D4),D4,"")) -> 6582 | AY4: =IF(AND(AW4="Validation",ISNUMBER(AX4),ISNUMBER(AV4)),ABS(AX4-AV4)/AX4,"") | AZ4: =IF(AJ4=1,AP4-AU4,0) -> 0 | BB4: =Regression!$C$45+Regression!$C$46*A4 -> 6148.958 | BC4: =IF(AND(AH4>=2022,AH4<=2024),C4/BB4,"") | BD4: =INDEX('Seasonal Index'!$H$2:$H$53,AI4) -> 1.0025159 | BE4: =IF(AH4>=2022,BB4*BD4,"") | BF4: =IF(AND(AW4="Validation",ISNUMBER(AX4),ISNUMBER(BE4)),ABS(AX4-BE4)/AX4,"") | BG4: =IF(ISNUMBER(C4),C4,0) -> 6582 | BH4: =IF(ISNUMBER(AY4),AV4-AX4,0) -> 0 | BI4: =IF(ISNUMBER(AY4),BE4-AX4,0) -> 0
A5: 4 | B5: 33298 | C5: 7224 | F5: 499000 | H5: 18.73 | I5: 18.662 | J5: 1.054 | M5: 1136 | N5: 11.829 | W5: 84.2 | AD5: 0 | AE5: 149.8 | AF5: 0.9 | AH5: =YEAR(B5) -> 1991 | AI5: =MIN(52,INT((B5-DATE(AH5,1,1))/7)+1) -> 9 | AJ5: =IF(AND(ISNUMBER(C5),ISNUMBER(AK5),ISNUMBER(AL5),AH5>=Inputs!$B$5,AH5<=Inputs!$B$6,AH5<>Inputs!$B$7,AH5<>Inputs!$B$8),1,0) -> 0 | AK5: =IF(INDEX($E5:$AF5,Inputs!$C$10)="","",INDEX($E5:$AF5,Inputs!$C$10)) | AL5: =IF(INDEX($E5:$AF5,Inputs!$C$11)="","",INDEX($E5:$AF5,Inputs!$C$11)) -> 499000 | AM5: =Regression!$C$5+Regression!$C$6*A5 -> 10841.859 | AN5: =IF(AJ5=1,C5/AM5,"") | AO5: =INDEX('Seasonal Index'!$E$2:$E$53,AI5) -> 0.98629368 | AP5: =IF(AJ5=1,C5/AO5,"") | AQ5: =IF(AJ5=1,A5-Regression!$C$15,0) -> 0 | AR5: =IF(AJ5=1,AK5-Regression!$D$15,0) -> 0 | AS5: =IF(AJ5=1,AL5-Regression!$E$15,0) -> 0 | AT5: =IF(AJ5=1,AP5-Regression!$F$15,0) -> 0 | AU5: =IF(AND(ISNUMBER(AK5),ISNUMBER(AL5)),Regression!$C$38+Regression!$D$38*A5+Regression!$E$38*AK5+Regression!$F$38*AL5,"") | AV5: =IF(ISNUMBER(AU5),AU5*AO5,"") | AW5: =IF(AJ5=1,"Train",IF(AH5=Inputs!$B$6+1,"Validation",IF(AH5>Inputs!$B$6+1,"Forecast","Not used"))) -> Not used | AX5: =IF(ISNUMBER(C5),C5,IF(ISNUMBER(D5),D5,"")) -> 7224 | AY5: =IF(AND(AW5="Validation",ISNUMBER(AX5),ISNUMBER(AV5)),ABS(AX5-AV5)/AX5,"") | AZ5: =IF(AJ5=1,AP5-AU5,0) -> 0 | BB5: =Regression!$C$45+Regression!$C$46*A5 -> 6150.5175 | BC5: =IF(AND(AH5>=2022,AH5<=2024),C5/BB5,"") | BD5: =INDEX('Seasonal Index'!$H$2:$H$53,AI5) -> 1.0104104 | BE5: =IF(AH5>=2022,BB5*BD5,"") | BF5: =IF(AND(AW5="Validation",ISNUMBER(AX5),ISNUMBER(BE5)),ABS(AX5-BE5)/AX5,"") | BG5: =IF(ISNUMBER(C5),C5,0) -> 7224 | BH5: =IF(ISNUMBER(AY5),AV5-AX5,0) -> 0 | BI5: =IF(ISNUMBER(AY5),BE5-AX5,0) -> 0
A6: 5 | B6: 33305 | C6: 6875 | F6: 488000 | H6: 19.856 | I6: 19.77 | J6: 1.025 | M6: 1068 | N6: 11.829 | P6: 3841 | W6: 82.8 | AD6: 0 | AE6: 111.1 | AF6: 1.8 | AH6: =YEAR(B6) -> 1991 | AI6: =MIN(52,INT((B6-DATE(AH6,1,1))/7)+1) -> 10 | AJ6: =IF(AND(ISNUMBER(C6),ISNUMBER(AK6),ISNUMBER(AL6),AH6>=Inputs!$B$5,AH6<=Inputs!$B$6,AH6<>Inputs!$B$7,AH6<>Inputs!$B$8),1,0) -> 0 | AK6: =IF(INDEX($E6:$AF6,Inputs!$C$10)="","",INDEX($E6:$AF6,Inputs!$C$10)) | AL6: =IF(INDEX($E6:$AF6,Inputs!$C$11)="","",INDEX($E6:$AF6,Inputs!$C$11)) -> 488000 | AM6: =Regression!$C$5+Regression!$C$6*A6 -> 10840.687 | AN6: =IF(AJ6=1,C6/AM6,"") | AO6: =INDEX('Seasonal Index'!$E$2:$E$53,AI6) -> 0.99527491 | AP6: =IF(AJ6=1,C6/AO6,"") | AQ6: =IF(AJ6=1,A6-Regression!$C$15,0) -> 0 | AR6: =IF(AJ6=1,AK6-Regression!$D$15,0) -> 0 | AS6: =IF(AJ6=1,AL6-Regression!$E$15,0) -> 0 | AT6: =IF(AJ6=1,AP6-Regression!$F$15,0) -> 0 | AU6: =IF(AND(ISNUMBER(AK6),ISNUMBER(AL6)),Regression!$C$38+Regression!$D$38*A6+Regression!$E$38*AK6+Regression!$F$38*AL6,"") | AV6: =IF(ISNUMBER(AU6),AU6*AO6,"") | AW6: =IF(AJ6=1,"Train",IF(AH6=Inputs!$B$6+1,"Validation",IF(AH6>Inputs!$B$6+1,"Forecast","Not used"))) -> Not used | AX6: =IF(ISNUMBER(C6),C6,IF(ISNUMBER(D6),D6,"")) -> 6875 | AY6: =IF(AND(AW6="Validation",ISNUMBER(AX6),ISNUMBER(AV6)),ABS(AX6-AV6)/AX6,"") | AZ6: =IF(AJ6=1,AP6-AU6,0) -> 0 | BB6: =Regression!$C$45+Regression!$C$46*A6 -> 6152.077 | BC6: =IF(AND(AH6>=2022,AH6<=2024),C6/BB6,"") | BD6: =INDEX('Seasonal Index'!$H$2:$H$53,AI6) -> 1.0119262 | BE6: =IF(AH6>=2022,BB6*BD6,"") | BF6: =IF(AND(AW6="Validation",ISNUMBER(AX6),ISNUMBER(BE6)),ABS(AX6-BE6)/AX6,"") | BG6: =IF(ISNUMBER(C6),C6,0) -> 6875 | BH6: =IF(ISNUMBER(AY6),AV6-AX6,0) -> 0 | BI6: =IF(ISNUMBER(AY6),BE6-AX6,0) -> 0
A7: 6 | B7: 33312 | C7: 6947 | F7: 499000 | H7: 19.894 | I7: 19.278 | J7: 1.045 | M7: 1068 | N7: 11.829 | P7: 3841 | W7: 82.8 | AD7: 0 | AE7: 148 | AF7: 0.7 | AH7: =YEAR(B7) -> 1991 | AI7: =MIN(52,INT((B7-DATE(AH7,1,1))/7)+1) -> 11 | AJ7: =IF(AND(ISNUMBER(C7),ISNUMBER(AK7),ISNUMBER(AL7),AH7>=Inputs!$B$5,AH7<=Inputs!$B$6,AH7<>Inputs!$B$7,AH7<>Inputs!$B$8),1,0) -> 0 | AK7: =IF(INDEX($E7:$AF7,Inputs!$C$10)="","",INDEX($E7:$AF7,Inputs!$C$10)) | AL7: =IF(INDEX($E7:$AF7,Inputs!$C$11)="","",INDEX($E7:$AF7,Inputs!$C$11)) -> 499000 | AM7: =Regression!$C$5+Regression!$C$6*A7 -> 10839.514 | AN7: =IF(AJ7=1,C7/AM7,"") | AO7: =INDEX('Seasonal Index'!$E$2:$E$53,AI7) -> 1.0021278 | AP7: =IF(AJ7=1,C7/AO7,"") | AQ7: =IF(AJ7=1,A7-Regression!$C$15,0) -> 0 | AR7: =IF(AJ7=1,AK7-Regression!$D$15,0) -> 0 | AS7: =IF(AJ7=1,AL7-Regression!$E$15,0) -> 0 | AT7: =IF(AJ7=1,AP7-Regression!$F$15,0) -> 0 | AU7: =IF(AND(ISNUMBER(AK7),ISNUMBER(AL7)),Regression!$C$38+Regression!$D$38*A7+Regression!$E$38*AK7+Regression!$F$38*AL7,"") | AV7: =IF(ISNUMBER(AU7),AU7*AO7,"") | AW7: =IF(AJ7=1,"Train",IF(AH7=Inputs!$B$6+1,"Validation",IF(AH7>Inputs!$B$6+1,"Forecast","Not used"))) -> Not used | AX7: =IF(ISNUMBER(C7),C7,IF(ISNUMBER(D7),D7,"")) -> 6947 | AY7: =IF(AND(AW7="Validation",ISNUMBER(AX7),ISNUMBER(AV7)),ABS(AX7-AV7)/AX7,"") | AZ7: =IF(AJ7=1,AP7-AU7,0) -> 0 | BB7: =Regression!$C$45+Regression!$C$46*A7 -> 6153.6365 | BC7: =IF(AND(AH7>=2022,AH7<=2024),C7/BB7,"") | BD7: =INDEX('Seasonal Index'!$H$2:$H$53,AI7) -> 1.0050202 | BE7: =IF(AH7>=2022,BB7*BD7,"") | BF7: =IF(AND(AW7="Validation",ISNUMBER(AX7),ISNUMBER(BE7)),ABS(AX7-BE7)/AX7,"") | BG7: =IF(ISNUMBER(C7),C7,0) -> 6947 | BH7: =IF(ISNUMBER(AY7),AV7-AX7,0) -> 0 | BI7: =IF(ISNUMBER(AY7),BE7-AX7,0) -> 0
A8: 7 | B8: 33319 | C8: 7328 | F8: 498000 | H8: 20.304 | I8: 18.796 | J8: 1.043 | M8: 1068 | N8: 12.409 | O8: 157889 | P8: 3841 | W8: 82.8 | AD8: 0 | AE8: 104.9 | AF8: 3.3 | AH8: =YEAR(B8) -> 1991 | AI8: =MIN(52,INT((B8-DATE(AH8,1,1))/7)+1) -> 12 | AJ8: =IF(AND(ISNUMBER(C8),ISNUMBER(AK8),ISNUMBER(AL8),AH8>=Inputs!$B$5,AH8<=Inputs!$B$6,AH8<>Inputs!$B$7,AH8<>Inputs!$B$8),1,0) -> 0 | AK8: =IF(INDEX($E8:$AF8,Inputs!$C$10)="","",INDEX($E8:$AF8,Inputs!$C$10)) -> 157889 | AL8: =IF(INDEX($E8:$AF8,Inputs!$C$11)="","",INDEX($E8:$AF8,Inputs!$C$11)) -> 498000 | AM8: =Regression!$C$5+Regression!$C$6*A8 -> 10838.341 | AN8: =IF(AJ8=1,C8/AM8,"") | AO8: =INDEX('Seasonal Index'!$E$2:$E$53,AI8) -> 0.99255102 | AP8: =IF(AJ8=1,C8/AO8,"") | AQ8: =IF(AJ8=1,A8-Regression!$C$15,0) -> 0 | AR8: =IF(AJ8=1,AK8-Regression!$D$15,0) -> 0 | AS8: =IF(AJ8=1,AL8-Regression!$E$15,0) -> 0 | AT8: =IF(AJ8=1,AP8-Regression!$F$15,0) -> 0 | AU8: =IF(AND(ISNUMBER(AK8),ISNUMBER(AL8)),Regression!$C$38+Regression!$D$38*A8+Regression!$E$38*AK8+Regression!$F$38*AL8,"") -> 10522.407 | AV8: =IF(ISNUMBER(AU8),AU8*AO8,"") -> 10444.026 | AW8: =IF(AJ8=1,"Train",IF(AH8=Inputs!$B$6+1,"Validation",IF(AH8>Inputs!$B$6+1,"Forecast","Not used"))) -> Not used | AX8: =IF(ISNUMBER(C8),C8,IF(ISNUMBER(D8),D8,"")) -> 7328 | AY8: =IF(AND(AW8="Validation",ISNUMBER(AX8),ISNUMBER(AV8)),ABS(AX8-AV8)/AX8,"") | AZ8: =IF(AJ8=1,AP8-AU8,0) -> 0 | BB8: =Regression!$C$45+Regression!$C$46*A8 -> 6155.196 | BC8: =IF(AND(AH8>=2022,AH8<=2024),C8/BB8,"") | BD8: =INDEX('Seasonal Index'!$H$2:$H$53,AI8) -> 1.0030365 | BE8: =IF(AH8>=2022,BB8*BD8,"") | BF8: =IF(AND(AW8="Validation",ISNUMBER(AX8),ISNUMBER(BE8)),ABS(AX8-BE8)/AX8,"") | BG8: =IF(ISNUMBER(C8),C8,0) -> 7328 | BH8: =IF(ISNUMBER(AY8),AV8-AX8,0) -> 0 | BI8: =IF(ISNUMBER(AY8),BE8-AX8,0) -> 0
A9: 8 | B9: 33326 | C9: 6777 | F9: 509000 | H9: 19.5825 | I9: 18.275 | J9: 1.047 | M9: 1068 | N9: 12.409 | O9: 157889 | P9: 3841 | W9: 82.8 | AD9: 0 | AE9: 79 | AF9: 7.1 | AH9: =YEAR(B9) -> 1991 | AI9: =MIN(52,INT((B9-DATE(AH9,1,1))/7)+1) -> 13 | AJ9: =IF(AND(ISNUMBER(C9),ISNUMBER(AK9),ISNUMBER(AL9),AH9>=Inputs!$B$5,AH9<=Inputs!$B$6,AH9<>Inputs!$B$7,AH9<>Inputs!$B$8),1,0) -> 0 | AK9: =IF(INDEX($E9:$AF9,Inputs!$C$10)="","",INDEX($E9:$AF9,Inputs!$C$10)) -> 157889 | AL9: =IF(INDEX($E9:$AF9,Inputs!$C$11)="","",INDEX($E9:$AF9,Inputs!$C$11)) -> 509000 | AM9: =Regression!$C$5+Regression!$C$6*A9 -> 10837.169 | AN9: =IF(AJ9=1,C9/AM9,"") | AO9: =INDEX('Seasonal Index'!$E$2:$E$53,AI9) -> 1.0067199 | AP9: =IF(AJ9=1,C9/AO9,"") | AQ9: =IF(AJ9=1,A9-Regression!$C$15,0) -> 0 | AR9: =IF(AJ9=1,AK9-Regression!$D$15,0) -> 0 | AS9: =IF(AJ9=1,AL9-Regression!$E$15,0) -> 0 | AT9: =IF(AJ9=1,AP9-Regression!$F$15,0) -> 0 | AU9: =IF(AND(ISNUMBER(AK9),ISNUMBER(AL9)),Regression!$C$38+Regression!$D$38*A9+Regression!$E$38*AK9+Regression!$F$38*AL9,"") -> 10491.639 | AV9: =IF(ISNUMBER(AU9),AU9*AO9,"") -> 10562.142 | AW9: =IF(AJ9=1,"Train",IF(AH9=Inputs!$B$6+1,"Validation",IF(AH9>Inputs!$B$6+1,"Forecast","Not used"))) -> Not used | AX9: =IF(ISNUMBER(C9),C9,IF(ISNUMBER(D9),D9,"")) -> 6777 | AY9: =IF(AND(AW9="Validation",ISNUMBER(AX9),ISNUMBER(AV9)),ABS(AX9-AV9)/AX9,"") | AZ9: =IF(AJ9=1,AP9-AU9,0) -> 0 | BB9: =Regression!$C$45+Regression!$C$46*A9 -> 6156.7555 | BC9: =IF(AND(AH9>=2022,AH9<=2024),C9/BB9,"") | BD9: =INDEX('Seasonal Index'!$H$2:$H$53,AI9) -> 1.0306249 | BE9: =IF(AH9>=2022,BB9*BD9,"") | BF9: =IF(AND(AW9="Validation",ISNUMBER(AX9),ISNUMBER(BE9)),ABS(AX9-BE9)/AX9,"") | BG9: =IF(ISNUMBER(C9),C9,0) -> 6777 | BH9: =IF(ISNUMBER(AY9),AV9-AX9,0) -> 0 | BI9: =IF(ISNUMBER(AY9),BE9-AX9,0) -> 0
A10: 9 | B10: 33333 | C10: 7503 | F10: 499000 | H10: 19.63 | I10: 17.946 | J10: 1.052 | M10: 984 | N10: 12.409 | O10: 157889 | P10: 3866.7 | W10: 82.8 | AD10: 0 | AE10: 92.3 | AF10: 2.8 | AH10: =YEAR(B10) -> 1991 | AI10: =MIN(52,INT((B10-DATE(AH10,1,1))/7)+1) -> 14 | AJ10: =IF(AND(ISNUMBER(C10),ISNUMBER(AK10),ISNUMBER(AL10),AH10>=Inputs!$B$5,AH10<=Inputs!$B$6,AH10<>Inputs!$B$7,AH10<>Inputs!$B$8),1,0) -> 0 | AK10: =IF(INDEX($E10:$AF10,Inputs!$C$10)="","",INDEX($E10:$AF10,Inputs!$C$10)) -> 157889 | AL10: =IF(INDEX($E10:$AF10,Inputs!$C$11)="","",INDEX($E10:$AF10,Inputs!$C$11)) -> 499000 | AM10: =Regression!$C$5+Regression!$C$6*A10 -> 10835.996 | AN10: =IF(AJ10=1,C10/AM10,"") | AO10: =INDEX('Seasonal Index'!$E$2:$E$53,AI10) -> 0.99471307 | AP10: =IF(AJ10=1,C10/AO10,"") | AQ10: =IF(AJ10=1,A10-Regression!$C$15,0) -> 0 | AR10: =IF(AJ10=1,AK10-Regression!$D$15,0) -> 0 | AS10: =IF(AJ10=1,AL10-Regression!$E$15,0) -> 0 | AT10: =IF(AJ10=1,AP10-Regression!$F$15,0) -> 0 | AU10: =IF(AND(ISNUMBER(AK10),ISNUMBER(AL10)),Regression!$C$38+Regression!$D$38*A10+Regression!$E$38*AK10+Regression!$F$38*AL10,"") -> 10516.627 | AV10: =IF(ISNUMBER(AU10),AU10*AO10,"") -> 10461.027 | AW10: =IF(AJ10=1,"Train",IF(AH10=Inputs!$B$6+1,"Validation",IF(AH10>Inputs!$B$6+1,"Forecast","Not used"))) -> Not used | AX10: =IF(ISNUMBER(C10),C10,IF(ISNUMBER(D10),D10,"")) -> 7503 | AY10: =IF(AND(AW10="Validation",ISNUMBER(AX10),ISNUMBER(AV10)),ABS(AX10-AV10)/AX10,"") | AZ10: =IF(AJ10=1,AP10-AU10,0) -> 0 | BB10: =Regression!$C$45+Regression!$C$46*A10 -> 6158.315 | BC10: =IF(AND(AH10>=2022,AH10<=2024),C10/BB10,"") | BD10: =INDEX('Seasonal Index'!$H$2:$H$53,AI10) -> 0.99994657 | BE10: =IF(AH10>=2022,BB10*BD10,"") | BF10: =IF(AND(AW10="Validation",ISNUMBER(AX10),ISNUMBER(BE10)),ABS(AX10-BE10)/AX10,"") | BG10: =IF(ISNUMBER(C10),C10,0) -> 7503 | BH10: =IF(ISNUMBER(AY10),AV10-AX10,0) -> 0 | BI10: =IF(ISNUMBER(AY10),BE10-AX10,0) -> 0
A11: 10 | B11: 33340 | C11: 6916 | F11: 452000 | H11: 20.892 | I11: 19.172 | J11: 1.066 | M11: 984 | N11: 12.409 | O11: 157889 | P11: 3866.7 | W11: 82.5 | AD11: 0 | AE11: 37.2 | AF11: 14.2 | AH11: =YEAR(B11) -> 1991 | AI11: =MIN(52,INT((B11-DATE(AH11,1,1))/7)+1) -> 15 | AJ11: =IF(AND(ISNUMBER(C11),ISNUMBER(AK11),ISNUMBER(AL11),AH11>=Inputs!$B$5,AH11<=Inputs!$B$6,AH11<>Inputs!$B$7,AH11<>Inputs!$B$8),1,0) -> 0 | AK11: =IF(INDEX($E11:$AF11,Inputs!$C$10)="","",INDEX($E11:$AF11,Inputs!$C$10)) -> 157889 | AL11: =IF(INDEX($E11:$AF11,Inputs!$C$11)="","",INDEX($E11:$AF11,Inputs!$C$11)) -> 452000 | AM11: =Regression!$C$5+Regression!$C$6*A11 -> 10834.823 | AN11: =IF(AJ11=1,C11/AM11,"") | AO11: =INDEX('Seasonal Index'!$E$2:$E$53,AI11) -> 1.0030309 | AP11: =IF(AJ11=1,C11/AO11,"") | AQ11: =IF(AJ11=1,A11-Regression!$C$15,0) -> 0 | AR11: =IF(AJ11=1,AK11-Regression!$D$15,0) -> 0 | AS11: =IF(AJ11=1,AL11-Regression!$E$15,0) -> 0 | AT11: =IF(AJ11=1,AP11-Regression!$F$15,0) -> 0 | AU11: =IF(AND(ISNUMBER(AK11),ISNUMBER(AL11)),Regression!$C$38+Regression!$D$38*A11+Regression!$E$38*AK11+Regression!$F$38*AL11,"") -> 10639.852 | AV11: =IF(ISNUMBER(AU11),AU11*AO11,"") -> 10672.1 | AW11: =IF(AJ11=1,"Train",IF(AH11=Inputs!$B$6+1,"Validation",IF(AH11>Inputs!$B$6+1,"Forecast","Not used"))) -> Not used | AX11: =IF(ISNUMBER(C11),C11,IF(ISNUMBER(D11),D11,"")) -> 6916 | AY11: =IF(AND(AW11="Validation",ISNUMBER(AX11),ISNUMBER(AV11)),ABS(AX11-AV11)/AX11,"") | AZ11: =IF(AJ11=1,AP11-AU11,0) -> 0 | BB11: =Regression!$C$45+Regression!$C$46*A11 -> 6159.8745 | BC11: =IF(AND(AH11>=2022,AH11<=2024),C11/BB11,"") | BD11: =INDEX('Seasonal Index'!$H$2:$H$53,AI11) -> 0.99086023 | BE11: =IF(AH11>=2022,BB11*BD11,"") | BF11: =IF(AND(AW11="Validation",ISNUMBER(AX11),ISNUMBER(BE11)),ABS(AX11-BE11)/AX11,"") | BG11: =IF(ISNUMBER(C11),C11,0) -> 6916 | BH11: =IF(ISNUMBER(AY11),AV11-AX11,0) -> 0 | BI11: =IF(ISNUMBER(AY11),BE11-AX11,0) -> 0
A12: 11 | B12: 33347 | C12: 7045 | F12: 477000 | H12: 21.484 | I12: 19.712 | J12: 1.069 | M12: 984 | N12: 12.848 | O12: 153351 | P12: 3866.7 | W12: 82.5 | AD12: 0 | AE12: 62 | AF12: 14.6 | AH12: =YEAR(B12) -> 1991 | AI12: =MIN(52,INT((B12-DATE(AH12,1,1))/7)+1) -> 16 | AJ12: =IF(AND(ISNUMBER(C12),ISNUMBER(AK12),ISNUMBER(AL12),AH12>=Inputs!$B$5,AH12<=Inputs!$B$6,AH12<>Inputs!$B$7,AH12<>Inputs!$B$8),1,0) -> 0 | AK12: =IF(INDEX($E12:$AF12,Inputs!$C$10)="","",INDEX($E12:$AF12,Inputs!$C$10)) -> 153351 | AL12: =IF(INDEX($E12:$AF12,Inputs!$C$11)="","",INDEX($E12:$AF12,Inputs!$C$11)) -> 477000 | AM12: =Regression!$C$5+Regression!$C$6*A12 -> 10833.651 | AN12: =IF(AJ12=1,C12/AM12,"") | AO12: =INDEX('Seasonal Index'!$E$2:$E$53,AI12) -> 1.0020974 | AP12: =IF(AJ12=1,C12/AO12,"") | AQ12: =IF(AJ12=1,A12-Regression!$C$15,0) -> 0 | AR12: =IF(AJ12=1,AK12-Regression!$D$15,0) -> 0 | AS12: =IF(AJ12=1,AL12-Regression!$E$15,0) -> 0 | AT12: =IF(AJ12=1,AP12-Regression!$F$15,0) -> 0 | AU12: =IF(AND(ISNUMBER(AK12),ISNUMBER(AL12)),Regression!$C$38+Regression!$D$38*A12+Regression!$E$38*AK12+Regression!$F$38*AL12,"") -> 10563.633 | AV12: =IF(ISNUMBER(AU12),AU12*AO12,"") -> 10585.789 | AW12: =IF(AJ12=1,"Train",IF(AH12=Inputs!$B$6+1,"Validation",IF(AH12>Inputs!$B$6+1,"Forecast","Not used"))) -> Not used | AX12: =IF(ISNUMBER(C12),C12,IF(ISNUMBER(D12),D12,"")) -> 7045 | AY12: =IF(AND(AW12="Validation",ISNUMBER(AX12),ISNUMBER(AV12)),ABS(AX12-AV12)/AX12,"") | AZ12: =IF(AJ12=1,AP12-AU12,0) -> 0 | BB12: =Regression!$C$45+Regression!$C$46*A12 -> 6161.434 | BC12: =IF(AND(AH12>=2022,AH12<=2024),C12/BB12,"") | BD12: =INDEX('Seasonal Index'!$H$2:$H$53,AI12) -> 1.01445 | BE12: =IF(AH12>=2022,BB12*BD12,"") | BF12: =IF(AND(AW12="Validation",ISNUMBER(AX12),ISNUMBER(BE12)),ABS(AX12-BE12)/AX12,"") | BG12: =IF(ISNUMBER(C12),C12,0) -> 7045 | BH12: =IF(ISNUMBER(AY12),AV12-AX12,0) -> 0 | BI12: =IF(ISNUMBER(AY12),BE12-AX12,0) -> 0
A13: 12 | B13: 33354 | C13: 6956 | F13: 478000 | H13: 21.188 | I13: 19.632 | J13: 1.09 | M13: 984 | N13: 12.848 | O13: 153351 | P13: 3866.7 | W13: 82.5 | AD13: 0 | AE13: 64.9 | AF13: 9.9 | AH13: =YEAR(B13) -> 1991 | AI13: =MIN(52,INT((B13-DATE(AH13,1,1))/7)+1) -> 17 | AJ13: =IF(AND(ISNUMBER(C13),ISNUMBER(AK13),ISNUMBER(AL13),AH13>=Inputs!$B$5,AH13<=Inputs!$B$6,AH13<>Inputs!$B$7,AH13<>Inputs!$B$8),1,0) -> 0 | AK13: =IF(INDEX($E13:$AF13,Inputs!$C$10)="","",INDEX($E13:$AF13,Inputs!$C$10)) -> 153351 | AL13: =IF(INDEX($E13:$AF13,Inputs!$C$11)="","",INDEX($E13:$AF13,Inputs!$C$11)) -> 478000 | AM13: =Regression!$C$5+Regression!$C$6*A13 -> 10832.478 | AN13: =IF(AJ13=1,C13/AM13,"") | AO13: =INDEX('Seasonal Index'!$E$2:$E$53,AI13) -> 0.98572001 | AP13: =IF(AJ13=1,C13/AO13,"") | AQ13: =IF(AJ13=1,A13-Regression!$C$15,0) -> 0 | AR13: =IF(AJ13=1,AK13-Regression!$D$15,0) -> 0 | AS13: =IF(AJ13=1,AL13-Regression!$E$15,0) -> 0 | AT13: =IF(AJ13=1,AP13-Regression!$F$15,0) -> 0 | AU13: =IF(AND(ISNUMBER(AK13),ISNUMBER(AL13)),Regression!$C$38+Regression!$D$38*A13+Regression!$E$38*AK13+Regression!$F$38*AL13,"") -> 10559.416 | AV13: =IF(ISNUMBER(AU13),AU13*AO13,"") -> 10408.627 | AW13: =IF(AJ13=1,"Train",IF(AH13=Inputs!$B$6+1,"Validation",IF(AH13>Inputs!$B$6+1,"Forecast","Not used"))) -> Not used | AX13: =IF(ISNUMBER(C13),C13,IF(ISNUMBER(D13),D13,"")) -> 6956 | AY13: =IF(AND(AW13="Validation",ISNUMBER(AX13),ISNUMBER(AV13)),ABS(AX13-AV13)/AX13,"") | AZ13: =IF(AJ13=1,AP13-AU13,0) -> 0 | BB13: =Regression!$C$45+Regression!$C$46*A13 -> 6162.9935 | BC13: =IF(AND(AH13>=2022,AH13<=2024),C13/BB13,"") | BD13: =INDEX('Seasonal Index'!$H$2:$H$53,AI13) -> 0.99215359 | BE13: =IF(AH13>=2022,BB13*BD13,"") | BF13: =IF(AND(AW13="Validation",ISNUMBER(AX13),ISNUMBER(BE13)),ABS(AX13-BE13)/AX13,"") | BG13: =IF(ISNUMBER(C13),C13,0) -> 6956 | BH13: =IF(ISNUMBER(AY13),AV13-AX13,0) -> 0 | BI13: =IF(ISNUMBER(AY13),BE13-AX13,0) -> 0
A14: 13 | B14: 33361 | C14: 6976 | F14: 462000 | H14: 21.234 | I14: 19.72 | J14: 1.104 | M14: 984 | N14: 12.848 | O14: 153351 | P14: 3866.7 | W14: 82.5 | AD14: 0 | AE14: 30.2 | AF14: 21.4 | AH14: =YEAR(B14) -> 1991 | AI14: =MIN(52,INT((B14-DATE(AH14,1,1))/7)+1) -> 18 | AJ14: =IF(AND(ISNUMBER(C14),ISNUMBER(AK14),ISNUMBER(AL14),AH14>=Inputs!$B$5,AH14<=Inputs!$B$6,AH14<>Inputs!$B$7,AH14<>Inputs!$B$8),1,0) -> 0 | AK14: =IF(INDEX($E14:$AF14,Inputs!$C$10)="","",INDEX($E14:$AF14,Inputs!$C$10)) -> 153351 | AL14: =IF(INDEX($E14:$AF14,Inputs!$C$11)="","",INDEX($E14:$AF14,Inputs!$C$11)) -> 462000 | AM14: =Regression!$C$5+Regression!$C$6*A14 -> 10831.305 | AN14: =IF(AJ14=1,C14/AM14,"") | AO14: =INDEX('Seasonal Index'!$E$2:$E$53,AI14) -> 1.0181402 | AP14: =IF(AJ14=1,C14/AO14,"") | AQ14: =IF(AJ14=1,A14-Regression!$C$15,0) -> 0 | AR14: =IF(AJ14=1,AK14-Regression!$D$15,0) -> 0 | AS14: =IF(AJ14=1,AL14-Regression!$E$15,0) -> 0 | AT14: =IF(AJ14=1,AP14-Regression!$F$15,0) -> 0 | AU14: =IF(AND(ISNUMBER(AK14),ISNUMBER(AL14)),Regression!$C$38+Regression!$D$38*A14+Regression!$E$38*AK14+Regression!$F$38*AL14,"") -> 10600.334 | AV14: =IF(ISNUMBER(AU14),AU14*AO14,"") -> 10792.626 | AW14: =IF(AJ14=1,"Train",IF(AH14=Inputs!$B$6+1,"Validation",IF(AH14>Inputs!$B$6+1,"Forecast","Not used"))) -> Not used | AX14: =IF(ISNUMBER(C14),C14,IF(ISNUMBER(D14),D14,"")) -> 6976 | AY14: =IF(AND(AW14="Validation",ISNUMBER(AX14),ISNUMBER(AV14)),ABS(AX14-AV14)/AX14,"") | AZ14: =IF(AJ14=1,AP14-AU14,0) -> 0 | BB14: =Regression!$C$45+Regression!$C$46*A14 -> 6164.553 | BC14: =IF(AND(AH14>=2022,AH14<=2024),C14/BB14,"") | BD14: =INDEX('Seasonal Index'!$H$2:$H$53,AI14) -> 1.0188494 | BE14: =IF(AH14>=2022,BB14*BD14,"") | BF14: =IF(AND(AW14="Validation",ISNUMBER(AX14),ISNUMBER(BE14)),ABS(AX14-BE14)/AX14,"") | BG14: =IF(ISNUMBER(C14),C14,0) -> 6976 | BH14: =IF(ISNUMBER(AY14),AV14-AX14,0) -> 0 | BI14: =IF(ISNUMBER(AY14),BE14-AX14,0) -> 0
A15: 14 | B15: 33368 | C15: 7185 | F15: 451000 | H15: 21.69 | I15: 19.812 | J15: 1.113 | K15: 6035.178 | M15: 929 | N15: 12.848 | O15: 153351 | P15: 3913 | W15: 84.4 | AD15: 0 | AE15: 27.9 | AF15: 19.4 | AH15: =YEAR(B15) -> 1991 | AI15: =MIN(52,INT((B15-DATE(AH15,1,1))/7)+1) -> 19 | AJ15: =IF(AND(ISNUMBER(C15),ISNUMBER(AK15),ISNUMBER(AL15),AH15>=Inputs!$B$5,AH15<=Inputs!$B$6,AH15<>Inputs!$B$7,AH15<>Inputs!$B$8),1,0) -> 0 | AK15: =IF(INDEX($E15:$AF15,Inputs!$C$10)="","",INDEX($E15:$AF15,Inputs!$C$10)) -> 153351 | AL15: =IF(INDEX($E15:$AF15,Inputs!$C$11)="","",INDEX($E15:$AF15,Inputs!$C$11)) -> 451000 | AM15: =Regression!$C$5+Regression!$C$6*A15 -> 10830.133 | AN15: =IF(AJ15=1,C15/AM15,"") | AO15: =INDEX('Seasonal Index'!$E$2:$E$53,AI15) -> 1.0133712 | AP15: =IF(AJ15=1,C15/AO15,"") | AQ15: =IF(AJ15=1,A15-Regression!$C$15,0) -> 0 | AR15: =IF(AJ15=1,AK15-Regression!$D$15,0) -> 0 | AS15: =IF(AJ15=1,AL15-Regression!$E$15,0) -> 0 | AT15: =IF(AJ15=1,AP15-Regression!$F$15,0) -> 0 | AU15: =IF(AND(ISNUMBER(AK15),ISNUMBER(AL15)),Regression!$C$38+Regression!$D$38*A15+Regression!$E$38*AK15+Regression!$F$38*AL15,"") -> 10627.977 | AV15: =IF(ISNUMBER(AU15),AU15*AO15,"") -> 10770.087 | AW15: =IF(AJ15=1,"Train",IF(AH15=Inputs!$B$6+1,"Validation",IF(AH15>Inputs!$B$6+1,"Forecast","Not used"))) -> Not used | AX15: =IF(ISNUMBER(C15),C15,IF(ISNUMBER(D15),D15,"")) -> 7185 | AY15: =IF(AND(AW15="Validation",ISNUMBER(AX15),ISNUMBER(AV15)),ABS(AX15-AV15)/AX15,"") | AZ15: =IF(AJ15=1,AP15-AU15,0) -> 0 | BB15: =Regression!$C$45+Regression!$C$46*A15 -> 6166.1125 | BC15: =IF(AND(AH15>=2022,AH15<=2024),C15/BB15,"") | BD15: =INDEX('Seasonal Index'!$H$2:$H$53,AI15) -> 1.0190604 | BE15: =IF(AH15>=2022,BB15*BD15,"") | BF15: =IF(AND(AW15="Validation",ISNUMBER(AX15),ISNUMBER(BE15)),ABS(AX15-BE15)/AX15,"") | BG15: =IF(ISNUMBER(C15),C15,0) -> 7185 | BH15: =IF(ISNUMBER(AY15),AV15-AX15,0) -> 0 | BI15: =IF(ISNUMBER(AY15),BE15-AX15,0) -> 0
A16: 15 | B16: 33375 | C16: 6899 | F16: 446000 | H16: 20.952 | I16: 18.9 | J16: 1.121 | K16: 6035.178 | M16: 929 | N16: 12.038 | O16: 179076 | P16: 3913 | W16: 84.4 | AD16: 0 | AE16: 4.5 | AF16: 42.5 | AH16: =YEAR(B16) -> 1991 | AI16: =MIN(52,INT((B16-DATE(AH16,1,1))/7)+1) -> 20 | AJ16: =IF(AND(ISNUMBER(C16),ISNUMBER(AK16),ISNUMBER(AL16),AH16>=Inputs!$B$5,AH16<=Inputs!$B$6,AH16<>Inputs!$B$7,AH16<>Inputs!$B$8),1,0) -> 0 | AK16: =IF(INDEX($E16:$AF16,Inputs!$C$10)="","",INDEX($E16:$AF16,Inputs!$C$10)) -> 179076 | AL16: =IF(INDEX($E16:$AF16,Inputs!$C$11)="","",INDEX($E16:$AF16,Inputs!$C$11)) -> 446000 | AM16: =Regression!$C$5+Regression!$C$6*A16 -> 10828.96 | AN16: =IF(AJ16=1,C16/AM16,"") | AO16: =INDEX('Seasonal Index'!$E$2:$E$53,AI16) -> 1.0355119 | AP16: =IF(AJ16=1,C16/AO16,"") | AQ16: =IF(AJ16=1,A16-Regression!$C$15,0) -> 0 | AR16: =IF(AJ16=1,AK16-Regression!$D$15,0) -> 0 | AS16: =IF(AJ16=1,AL16-Regression!$E$15,0) -> 0 | AT16: =IF(AJ16=1,AP16-Regression!$F$15,0) -> 0 | AU16: =IF(AND(ISNUMBER(AK16),ISNUMBER(AL16)),Regression!$C$38+Regression!$D$38*A16+Regression!$E$38*AK16+Regression!$F$38*AL16,"") -> 10686.63 | AV16: =IF(ISNUMBER(AU16),AU16*AO16,"") -> 11066.133 | AW16: =IF(AJ16=1,"Train",IF(AH16=Inputs!$B$6+1,"Validation",IF(AH16>Inputs!$B$6+1,"Forecast","Not used"))) -> Not used | AX16: =IF(ISNUMBER(C16),C16,IF(ISNUMBER(D16),D16,"")) -> 6899 | AY16: =IF(AND(AW16="Validation",ISNUMBER(AX16),ISNUMBER(AV16)),ABS(AX16-AV16)/AX16,"") | AZ16: =IF(AJ16=1,AP16-AU16,0) -> 0 | BB16: =Regression!$C$45+Regression!$C$46*A16 -> 6167.672 | BC16: =IF(AND(AH16>=2022,AH16<=2024),C16/BB16,"") | BD16: =INDEX('Seasonal Index'!$H$2:$H$53,AI16) -> 1.0467645 | BE16: =IF(AH16>=2022,BB16*BD16,"") | BF16: =IF(AND(AW16="Validation",ISNUMBER(AX16),ISNUMBER(BE16)),ABS(AX16-BE16)/AX16,"") | BG16: =IF(ISNUMBER(C16),C16,0) -> 6899 | BH16: =IF(ISNUMBER(AY16),AV16-AX16,0) -> 0 | BI16: =IF(ISNUMBER(AY16),BE16-AX16,0) -> 0
A17: 16 | B17: 33382 | C17: 7396 | F17: 448000 | H17: 21.036 | I17: 18.824 | J17: 1.129 | K17: 6035.178 | M17: 929 | N17: 12.038 | O17: 179076 | P17: 3913 | W17: 84.4 | AD17: 0 | AE17: 15.8 | AF17: 31.9 | AH17: =YEAR(B17) -> 1991 | AI17: =MIN(52,INT((B17-DATE(AH17,1,1))/7)+1) -> 21 | AJ17: =IF(AND(ISNUMBER(C17),ISNUMBER(AK17),ISNUMBER(AL17),AH17>=Inputs!$B$5,AH17<=Inputs!$B$6,AH17<>Inputs!$B$7,AH17<>Inputs!$B$8),1,0) -> 0 | AK17: =IF(INDEX($E17:$AF17,Inputs!$C$10)="","",INDEX($E17:$AF17,Inputs!$C$10)) -> 179076 | AL17: =IF(INDEX($E17:$AF17,Inputs!$C$11)="","",INDEX($E17:$AF17,Inputs!$C$11)) -> 448000 | AM17: =Regression!$C$5+Regression!$C$6*A17 -> 10827.787 | AN17: =IF(AJ17=1,C17/AM17,"") | AO17: =INDEX('Seasonal Index'!$E$2:$E$53,AI17) -> 1.0352246 | AP17: =IF(AJ17=1,C17/AO17,"") | AQ17: =IF(AJ17=1,A17-Regression!$C$15,0) -> 0 | AR17: =IF(AJ17=1,AK17-Regression!$D$15,0) -> 0 | AS17: =IF(AJ17=1,AL17-Regression!$E$15,0) -> 0 | AT17: =IF(AJ17=1,AP17-Regression!$F$15,0) -> 0 | AU17: =IF(AND(ISNUMBER(AK17),ISNUMBER(AL17)),Regression!$C$38+Regression!$D$38*A17+Regression!$E$38*AK17+Regression!$F$38*AL17,"") -> 10679.758 | AV17: =IF(ISNUMBER(AU17),AU17*AO17,"") -> 11055.947 | AW17: =IF(AJ17=1,"Train",IF(AH17=Inputs!$B$6+1,"Validation",IF(AH17>Inputs!$B$6+1,"Forecast","Not used"))) -> Not used | AX17: =IF(ISNUMBER(C17),C17,IF(ISNUMBER(D17),D17,"")) -> 7396 | AY17: =IF(AND(AW17="Validation",ISNUMBER(AX17),ISNUMBER(AV17)),ABS(AX17-AV17)/AX17,"") | AZ17: =IF(AJ17=1,AP17-AU17,0) -> 0 | BB17: =Regression!$C$45+Regression!$C$46*A17 -> 6169.2315 | BC17: =IF(AND(AH17>=2022,AH17<=2024),C17/BB17,"") | BD17: =INDEX('Seasonal Index'!$H$2:$H$53,AI17) -> 1.0342763 | BE17: =IF(AH17>=2022,BB17*BD17,"") | BF17: =IF(AND(AW17="Validation",ISNUMBER(AX17),ISNUMBER(BE17)),ABS(AX17-BE17)/AX17,"") | BG17: =IF(ISNUMBER(C17),C17,0) -> 7396 | BH17: =IF(ISNUMBER(AY17),AV17-AX17,0) -> 0 | BI17: =IF(ISNUMBER(AY17),BE17-AX17,0) -> 0
A18: 17 | B18: 33389 | C18: 7287 | F18: 443000 | H18: 21.21 | I18: 18.87 | J18: 1.14 | K18: 6035.178 | M18: 929 | N18: 12.038 | O18: 179076 | P18: 3913 | W18: 84.4 | AD18: 1 | AE18: 3.7 | AF18: 69 | AH18: =YEAR(B18) -> 1991 | AI18: =MIN(52,INT((B18-DATE(AH18,1,1))/7)+1) -> 22 | AJ18: =IF(AND(ISNUMBER(C18),ISNUMBER(AK18),ISNUMBER(AL18),AH18>=Inputs!$B$5,AH18<=Inputs!$B$6,AH18<>Inputs!$B$7,AH18<>Inputs!$B$8),1,0) -> 0 | AK18: =IF(INDEX($E18:$AF18,Inputs!$C$10)="","",INDEX($E18:$AF18,Inputs!$C$10)) -> 179076 | AL18: =IF(INDEX($E18:$AF18,Inputs!$C$11)="","",INDEX($E18:$AF18,Inputs!$C$11)) -> 443000 | AM18: =Regression!$C$5+Regression!$C$6*A18 -> 10826.615 | AN18: =IF(AJ18=1,C18/AM18,"") | AO18: =INDEX('Seasonal Index'!$E$2:$E$53,AI18) -> 1.0139792 | AP18: =IF(AJ18=1,C18/AO18,"") | AQ18: =IF(AJ18=1,A18-Regression!$C$15,0) -> 0 | AR18: =IF(AJ18=1,AK18-Regression!$D$15,0) -> 0 | AS18: =IF(AJ18=1,AL18-Regression!$E$15,0) -> 0 | AT18: =IF(AJ18=1,AP18-Regression!$F$15,0) -> 0 | AU18: =IF(AND(ISNUMBER(AK18),ISNUMBER(AL18)),Regression!$C$38+Regression!$D$38*A18+Regression!$E$38*AK18+Regression!$F$38*AL18,"") -> 10691.47 | AV18: =IF(ISNUMBER(AU18),AU18*AO18,"") -> 10840.928 | AW18: =IF(AJ18=1,"Train",IF(AH18=Inputs!$B$6+1,"Validation",IF(AH18>Inputs!$B$6+1,"Forecast","Not used"))) -> Not used | AX18: =IF(ISNUMBER(C18),C18,IF(ISNUMBER(D18),D18,"")) -> 7287 | AY18: =IF(AND(AW18="Validation",ISNUMBER(AX18),ISNUMBER(AV18)),ABS(AX18-AV18)/AX18,"") | AZ18: =IF(AJ18=1,AP18-AU18,0) -> 0 | BB18: =Regression!$C$45+Regression!$C$46*A18 -> 6170.791 | BC18: =IF(AND(AH18>=2022,AH18<=2024),C18/BB18,"") | BD18: =INDEX('Seasonal Index'!$H$2:$H$53,AI18) -> 1.0395595 | BE18: =IF(AH18>=2022,BB18*BD18,"") | BF18: =IF(AND(AW18="Validation",ISNUMBER(AX18),ISNUMBER(BE18)),ABS(AX18-BE18)/AX18,"") | BG18: =IF(ISNUMBER(C18),C18,0) -> 7287 | BH18: =IF(ISNUMBER(AY18),AV18-AX18,0) -> 0 | BI18: =IF(ISNUMBER(AY18),BE18-AX18,0) -> 0
A19: 18 | B19: 33396 | C19: 7220 | F19: 432000 | H19: 20.634 | I19: 18.554 | J19: 1.138 | K19: 6035.178 | M19: 865 | N19: 12.038 | O19: 179076 | P19: 3907.1 | W19: 83.2 | AD19: 0 | AE19: 3.7 | AF19: 46.7 | AH19: =YEAR(B19) -> 1991 | AI19: =MIN(52,INT((B19-DATE(AH19,1,1))/7)+1) -> 23 | AJ19: =IF(AND(ISNUMBER(C19),ISNUMBER(AK19),ISNUMBER(AL19),AH19>=Inputs!$B$5,AH19<=Inputs!$B$6,AH19<>Inputs!$B$7,AH19<>Inputs!$B$8),1,0) -> 0 | AK19: =IF(INDEX($E19:$AF19,Inputs!$C$10)="","",INDEX($E19:$AF19,Inputs!$C$10)) -> 179076 | AL19: =IF(INDEX($E19:$AF19,Inputs!$C$11)="","",INDEX($E19:$AF19,Inputs!$C$11)) -> 432000 | AM19: =Regression!$C$5+Regression!$C$6*A19 -> 10825.442 | AN19: =IF(AJ19=1,C19/AM19,"") | AO19: =INDEX('Seasonal Index'!$E$2:$E$53,AI19) -> 1.0375597 | AP19: =IF(AJ19=1,C19/AO19,"") | AQ19: =IF(AJ19=1,A19-Regression!$C$15,0) -> 0 | AR19: =IF(AJ19=1,AK19-Regression!$D$15,0) -> 0 | AS19: =IF(AJ19=1,AL19-Regression!$E$15,0) -> 0 | AT19: =IF(AJ19=1,AP19-Regression!$F$15,0) -> 0 | AU19: =IF(AND(ISNUMBER(AK19),ISNUMBER(AL19)),Regression!$C$38+Regression!$D$38*A19+Regression!$E$38*AK19+Regression!$F$38*AL19,"") -> 10719.114 | AV19: =IF(ISNUMBER(AU19),AU19*AO19,"") -> 11121.721 | AW19: =IF(AJ19=1,"Train",IF(AH19=Inputs!$B$6+1,"Validation",IF(AH19>Inputs!$B$6+1,"Forecast","Not used"))) -> Not used | AX19: =IF(ISNUMBER(C19),C19,IF(ISNUMBER(D19),D19,"")) -> 7220 | AY19: =IF(AND(AW19="Validation",ISNUMBER(AX19),ISNUMBER(AV19)),ABS(AX19-AV19)/AX19,"") | AZ19: =IF(AJ19=1,AP19-AU19,0) -> 0 | BB19: =Regression!$C$45+Regression!$C$46*A19 -> 6172.3505 | BC19: =IF(AND(AH19>=2022,AH19<=2024),C19/BB19,"") | BD19: =INDEX('Seasonal Index'!$H$2:$H$53,AI19) -> 1.0378993 | BE19: =IF(AH19>=2022,BB19*BD19,"") | BF19: =IF(AND(AW19="Validation",ISNUMBER(AX19),ISNUMBER(BE19)),ABS(AX19-BE19)/AX19,"") | BG19: =IF(ISNUMBER(C19),C19,0) -> 7220 | BH19: =IF(ISNUMBER(AY19),AV19-AX19,0) -> 0 | BI19: =IF(ISNUMBER(AY19),BE19-AX19,0) -> 0
A20: 19 | B20: 33403 | C20: 7651 | F20: 441000 | H20: 19.836 | I20: 17.856 | J20: 1.135 | K20: 6035.178 | M20: 865 | N20: 12.038 | O20: 179076 | P20: 3907.1 | W20: 83.2 | AD20: 0 | AE20: 0.2 | AF20: 56.4 | AH20: =YEAR(B20) -> 1991 | AI20: =MIN(52,INT((B20-DATE(AH20,1,1))/7)+1) -> 24 | AJ20: =IF(AND(ISNUMBER(C20),ISNUMBER(AK20),ISNUMBER(AL20),AH20>=Inputs!$B$5,AH20<=Inputs!$B$6,AH20<>Inputs!$B$7,AH20<>Inputs!$B$8),1,0) -> 0 | AK20: =IF(INDEX($E20:$AF20,Inputs!$C$10)="","",INDEX($E20:$AF20,Inputs!$C$10)) -> 179076 | AL20: =IF(INDEX($E20:$AF20,Inputs!$C$11)="","",INDEX($E20:$AF20,Inputs!$C$11)) -> 441000 | AM20: =Regression!$C$5+Regression!$C$6*A20 -> 10824.269 | AN20: =IF(AJ20=1,C20/AM20,"") | AO20: =INDEX('Seasonal Index'!$E$2:$E$53,AI20) -> 1.0344513 | AP20: =IF(AJ20=1,C20/AO20,"") | AQ20: =IF(AJ20=1,A20-Regression!$C$15,0) -> 0 | AR20: =IF(AJ20=1,AK20-Regression!$D$15,0) -> 0 | AS20: =IF(AJ20=1,AL20-Regression!$E$15,0) -> 0 | AT20: =IF(AJ20=1,AP20-Regression!$F$15,0) -> 0 | AU20: =IF(AND(ISNUMBER(AK20),ISNUMBER(AL20)),Regression!$C$38+Regression!$D$38*A20+Regression!$E$38*AK20+Regression!$F$38*AL20,"") -> 10693.656 | AV20: =IF(ISNUMBER(AU20),AU20*AO20,"") -> 11062.066 | AW20: =IF(AJ20=1,"Train",IF(AH20=Inputs!$B$6+1,"Validation",IF(AH20>Inputs!$B$6+1,"Forecast","Not used"))) -> Not used | AX20: =IF(ISNUMBER(C20),C20,IF(ISNUMBER(D20),D20,"")) -> 7651 | AY20: =IF(AND(AW20="Validation",ISNUMBER(AX20),ISNUMBER(AV20)),ABS(AX20-AV20)/AX20,"") | AZ20: =IF(AJ20=1,AP20-AU20,0) -> 0 | BB20: =Regression!$C$45+Regression!$C$46*A20 -> 6173.91 | BC20: =IF(AND(AH20>=2022,AH20<=2024),C20/BB20,"") | BD20: =INDEX('Seasonal Index'!$H$2:$H$53,AI20) -> 1.0351081 | BE20: =IF(AH20>=2022,BB20*BD20,"") | BF20: =IF(AND(AW20="Validation",ISNUMBER(AX20),ISNUMBER(BE20)),ABS(AX20-BE20)/AX20,"") | BG20: =IF(ISNUMBER(C20),C20,0) -> 7651 | BH20: =IF(ISNUMBER(AY20),AV20-AX20,0) -> 0 | BI20: =IF(ISNUMBER(AY20),BE20-AX20,0) -> 0
A21: 20 | B21: 33410 | C21: 7720 | F21: 429000 | H21: 20.078 | I21: 18.062 | J21: 1.126 | K21: 6035.178 | M21: 865 | N21: 12.487 | O21: 179538 | P21: 3907.1 | Q21: 824860 | W21: 83.2 | AD21: 0 | AE21: 0.2 | AF21: 69.4 | AH21: =YEAR(B21) -> 1991 | AI21: =MIN(52,INT((B21-DATE(AH21,1,1))/7)+1) -> 25 | AJ21: =IF(AND(ISNUMBER(C21),ISNUMBER(AK21),ISNUMBER(AL21),AH21>=Inputs!$B$5,AH21<=Inputs!$B$6,AH21<>Inputs!$B$7,AH21<>Inputs!$B$8),1,0) -> 0 | AK21: =IF(INDEX($E21:$AF21,Inputs!$C$10)="","",INDEX($E21:$AF21,Inputs!$C$10)) -> 179538 | AL21: =IF(INDEX($E21:$AF21,Inputs!$C$11)="","",INDEX($E21:$AF21,Inputs!$C$11)) -> 429000 | AM21: =Regression!$C$5+Regression!$C$6*A21 -> 10823.097 | AN21: =IF(AJ21=1,C21/AM21,"") | AO21: =INDEX('Seasonal Index'!$E$2:$E$53,AI21) -> 1.0360607 | AP21: =IF(AJ21=1,C21/AO21,"") | AQ21: =IF(AJ21=1,A21-Regression!$C$15,0) -> 0 | AR21: =IF(AJ21=1,AK21-Regression!$D$15,0) -> 0 | AS21: =IF(AJ21=1,AL21-Regression!$E$15,0) -> 0 | AT21: =IF(AJ21=1,AP21-Regression!$F$15,0) -> 0 | AU21: =IF(AND(ISNUMBER(AK21),ISNUMBER(AL21)),Regression!$C$38+Regression!$D$38*A21+Regression!$E$38*AK21+Regression!$F$38*AL21,"") -> 10724.797 | AV21: =IF(ISNUMBER(AU21),AU21*AO21,"") -> 11111.541 | AW21: =IF(AJ21=1,"Train",IF(AH21=Inputs!$B$6+1,"Validation",IF(AH21>Inputs!$B$6+1,"Forecast","Not used"))) -> Not used | AX21: =IF(ISNUMBER(C21),C21,IF(ISNUMBER(D21),D21,"")) -> 7720 | AY21: =IF(AND(AW21="Validation",ISNUMBER(AX21),ISNUMBER(AV21)),ABS(AX21-AV21)/AX21,"") | AZ21: =IF(AJ21=1,AP21-AU21,0) -> 0 | BB21: =Regression!$C$45+Regression!$C$46*A21 -> 6175.4695 | BC21: =IF(AND(AH21>=2022,AH21<=2024),C21/BB21,"") | BD21: =INDEX('Seasonal Index'!$H$2:$H$53,AI21) -> 1.0325971 | BE21: =IF(AH21>=2022,BB21*BD21,"") | BF21: =IF(AND(AW21="Validation",ISNUMBER(AX21),ISNUMBER(BE21)),ABS(AX21-BE21)/AX21,"") | BG21: =IF(ISNUMBER(C21),C21,0) -> 7720 | BH21: =IF(ISNUMBER(AY21),AV21-AX21,0) -> 0 | BI21: =IF(ISNUMBER(AY21),BE21-AX21,0) -> 0
A22: 21 | B22: 33417 | C22: 7543 | F22: 423000 | H22: 20.208 | I22: 18.198 | J22: 1.114 | K22: 6035.178 | M22: 865 | N22: 12.487 | O22: 179538 | P22: 3907.1 | Q22: 824860 | W22: 83.2 | AD22: 0 | AE22: 0.8 | AF22: 57.1 | AH22: =YEAR(B22) -> 1991 | AI22: =MIN(52,INT((B22-DATE(AH22,1,1))/7)+1) -> 26 | AJ22: =IF(AND(ISNUMBER(C22),ISNUMBER(AK22),ISNUMBER(AL22),AH22>=Inputs!$B$5,AH22<=Inputs!$B$6,AH22<>Inputs!$B$7,AH22<>Inputs!$B$8),1,0) -> 0 | AK22: =IF(INDEX($E22:$AF22,Inputs!$C$10)="","",INDEX($E22:$AF22,Inputs!$C$10)) -> 179538 | AL22: =IF(INDEX($E22:$AF22,Inputs!$C$11)="","",INDEX($E22:$AF22,Inputs!$C$11)) -> 423000 | AM22: =Regression!$C$5+Regression!$C$6*A22 -> 10821.924 | AN22: =IF(AJ22=1,C22/AM22,"") | AO22: =INDEX('Seasonal Index'!$E$2:$E$53,AI22) -> 1.057751 | AP22: =IF(AJ22=1,C22/AO22,"") | AQ22: =IF(AJ22=1,A22-Regression!$C$15,0) -> 0 | AR22: =IF(AJ22=1,AK22-Regression!$D$15,0) -> 0 | AS22: =IF(AJ22=1,AL22-Regression!$E$15,0) -> 0 | AT22: =IF(AJ22=1,AP22-Regression!$F$15,0) -> 0 | AU22: =IF(AND(ISNUMBER(AK22),ISNUMBER(AL22)),Regression!$C$38+Regression!$D$38*A22+Regression!$E$38*AK22+Regression!$F$38*AL22,"") -> 10739.165 | AV22: =IF(ISNUMBER(AU22),AU22*AO22,"") -> 11359.363 | AW22: =IF(AJ22=1,"Train",IF(AH22=Inputs!$B$6+1,"Validation",IF(AH22>Inputs!$B$6+1,"Forecast","Not used"))) -> Not used | AX22: =IF(ISNUMBER(C22),C22,IF(ISNUMBER(D22),D22,"")) -> 7543 | AY22: =IF(AND(AW22="Validation",ISNUMBER(AX22),ISNUMBER(AV22)),ABS(AX22-AV22)/AX22,"") | AZ22: =IF(AJ22=1,AP22-AU22,0) -> 0 | BB22: =Regression!$C$45+Regression!$C$46*A22 -> 6177.029 | BC22: =IF(AND(AH22>=2022,AH22<=2024),C22/BB22,"") | BD22: =INDEX('Seasonal Index'!$H$2:$H$53,AI22) -> 1.0794606 | BE22: =IF(AH22>=2022,BB22*BD22,"") | BF22: =IF(AND(AW22="Validation",ISNUMBER(AX22),ISNUMBER(BE22)),ABS(AX22-BE22)/AX22,"") | BG22: =IF(ISNUMBER(C22),C22,0) -> 7543 | BH22: =IF(ISNUMBER(AY22),AV22-AX22,0) -> 0 | BI22: =IF(ISNUMBER(AY22),BE22-AX22,0) -> 0
A23: 22 | B23: 33424 | C23: 7961 | F23: 418000 | H23: 20.798 | I23: 18.552 | J23: 1.104 | K23: 6035.178 | M23: 865 | N23: 12.487 | O23: 179538 | P23: 3907.1 | Q23: 824860 | W23: 84.6 | AD23: 1 | AE23: 0 | AF23: 88.7 | AH23: =YEAR(B23) -> 1991 | AI23: =MIN(52,INT((B23-DATE(AH23,1,1))/7)+1) -> 27 | AJ23: =IF(AND(ISNUMBER(C23),ISNUMBER(AK23),ISNUMBER(AL23),AH23>=Inputs!$B$5,AH23<=Inputs!$B$6,AH23<>Inputs!$B$7,AH23<>Inputs!$B$8),1,0) -> 0 | AK23: =IF(INDEX($E23:$AF23,Inputs!$C$10)="","",INDEX($E23:$AF23,Inputs!$C$10)) -> 179538 | AL23: =IF(INDEX($E23:$AF23,Inputs!$C$11)="","",INDEX($E23:$AF23,Inputs!$C$11)) -> 418000 | AM23: =Regression!$C$5+Regression!$C$6*A23 -> 10820.751 | AN23: =IF(AJ23=1,C23/AM23,"") | AO23: =INDEX('Seasonal Index'!$E$2:$E$53,AI23) -> 1.0212619 | AP23: =IF(AJ23=1,C23/AO23,"") | AQ23: =IF(AJ23=1,A23-Regression!$C$15,0) -> 0 | AR23: =IF(AJ23=1,AK23-Regression!$D$15,0) -> 0 | AS23: =IF(AJ23=1,AL23-Regression!$E$15,0) -> 0 | AT23: =IF(AJ23=1,AP23-Regression!$F$15,0) -> 0 | AU23: =IF(AND(ISNUMBER(AK23),ISNUMBER(AL23)),Regression!$C$38+Regression!$D$38*A23+Regression!$E$38*AK23+Regression!$F$38*AL23,"") -> 10750.878 | AV23: =IF(ISNUMBER(AU23),AU23*AO23,"") -> 10979.462 | AW23: =IF(AJ23=1,"Train",IF(AH23=Inputs!$B$6+1,"Validation",IF(AH23>Inputs!$B$6+1,"Forecast","Not used"))) -> Not used | AX23: =IF(ISNUMBER(C23),C23,IF(ISNUMBER(D23),D23,"")) -> 7961 | AY23: =IF(AND(AW23="Validation",ISNUMBER(AX23),ISNUMBER(AV23)),ABS(AX23-AV23)/AX23,"") | AZ23: =IF(AJ23=1,AP23-AU23,0) -> 0 | BB23: =Regression!$C$45+Regression!$C$46*A23 -> 6178.5885 | BC23: =IF(AND(AH23>=2022,AH23<=2024),C23/BB23,"") | BD23: =INDEX('Seasonal Index'!$H$2:$H$53,AI23) -> 0.99454601 | BE23: =IF(AH23>=2022,BB23*BD23,"") | BF23: =IF(AND(AW23="Validation",ISNUMBER(AX23),ISNUMBER(BE23)),ABS(AX23-BE23)/AX23,"") | BG23: =IF(ISNUMBER(C23),C23,0) -> 7961 | BH23: =IF(ISNUMBER(AY23),AV23-AX23,0) -> 0 | BI23: =IF(ISNUMBER(AY23),BE23-AX23,0) -> 0
A24: 23 | B24: 33431 | C24: 7327 | F24: 422000 | H24: 21.426 | I24: 19.244 | J24: 1.098 | K24: 6035.178 | M24: 819 | N24: 12.487 | O24: 179538 | P24: 3933.2 | Q24: 824860 | W24: 84.6 | AD24: 0 | AE24: 0 | AF24: 83.2 | AH24: =YEAR(B24) -> 1991 | AI24: =MIN(52,INT((B24-DATE(AH24,1,1))/7)+1) -> 28 | AJ24: =IF(AND(ISNUMBER(C24),ISNUMBER(AK24),ISNUMBER(AL24),AH24>=Inputs!$B$5,AH24<=Inputs!$B$6,AH24<>Inputs!$B$7,AH24<>Inputs!$B$8),1,0) -> 0 | AK24: =IF(INDEX($E24:$AF24,Inputs!$C$10)="","",INDEX($E24:$AF24,Inputs!$C$10)) -> 179538 | AL24: =IF(INDEX($E24:$AF24,Inputs!$C$11)="","",INDEX($E24:$AF24,Inputs!$C$11)) -> 422000 | AM24: =Regression!$C$5+Regression!$C$6*A24 -> 10819.578 | AN24: =IF(AJ24=1,C24/AM24,"") | AO24: =INDEX('Seasonal Index'!$E$2:$E$53,AI24) -> 1.013509 | AP24: =IF(AJ24=1,C24/AO24,"") | AQ24: =IF(AJ24=1,A24-Regression!$C$15,0) -> 0 | AR24: =IF(AJ24=1,AK24-Regression!$D$15,0) -> 0 | AS24: =IF(AJ24=1,AL24-Regression!$E$15,0) -> 0 | AT24: =IF(AJ24=1,AP24-Regression!$F$15,0) -> 0 | AU24: =IF(AND(ISNUMBER(AK24),ISNUMBER(AL24)),Regression!$C$38+Regression!$D$38*A24+Regression!$E$38*AK24+Regression!$F$38*AL24,"") -> 10738.695 | AV24: =IF(ISNUMBER(AU24),AU24*AO24,"") -> 10883.765 | AW24: =IF(AJ24=1,"Train",IF(AH24=Inputs!$B$6+1,"Validation",IF(AH24>Inputs!$B$6+1,"Forecast","Not used"))) -> Not used | AX24: =IF(ISNUMBER(C24),C24,IF(ISNUMBER(D24),D24,"")) -> 7327 | AY24: =IF(AND(AW24="Validation",ISNUMBER(AX24),ISNUMBER(AV24)),ABS(AX24-AV24)/AX24,"") | AZ24: =IF(AJ24=1,AP24-AU24,0) -> 0 | BB24: =Regression!$C$45+Regression!$C$46*A24 -> 6180.148 | BC24: =IF(AND(AH24>=2022,AH24<=2024),C24/BB24,"") | BD24: =INDEX('Seasonal Index'!$H$2:$H$53,AI24) -> 0.99258236 | BE24: =IF(AH24>=2022,BB24*BD24,"") | BF24: =IF(AND(AW24="Validation",ISNUMBER(AX24),ISNUMBER(BE24)),ABS(AX24-BE24)/AX24,"") | BG24: =IF(ISNUMBER(C24),C24,0) -> 7327 | BH24: =IF(ISNUMBER(AY24),AV24-AX24,0) -> 0 | BI24: =IF(ISNUMBER(AY24),BE24-AX24,0) -> 0
A25: 24 | B25: 33438 | C25: 7380 | F25: 420000 | H25: 21.906 | I25: 20.024 | J25: 1.094 | K25: 6035.178 | M25: 819 | N25: 12.719 | O25: 191929 | P25: 3933.2 | Q25: 824860 | W25: 84.6 | AD25: 0 | AE25: 0 | AF25: 83.8 | AH25: =YEAR(B25) -> 1991 | AI25: =MIN(52,INT((B25-DATE(AH25,1,1))/7)+1) -> 29 | AJ25: =IF(AND(ISNUMBER(C25),ISNUMBER(AK25),ISNUMBER(AL25),AH25>=Inputs!$B$5,AH25<=Inputs!$B$6,AH25<>Inputs!$B$7,AH25<>Inputs!$B$8),1,0) -> 0 | AK25: =IF(INDEX($E25:$AF25,Inputs!$C$10)="","",INDEX($E25:$AF25,Inputs!$C$10)) -> 191929 | AL25: =IF(INDEX($E25:$AF25,Inputs!$C$11)="","",INDEX($E25:$AF25,Inputs!$C$11)) -> 420000 | AM25: =Regression!$C$5+Regression!$C$6*A25 -> 10818.406 | AN25: =IF(AJ25=1,C25/AM25,"") | AO25: =INDEX('Seasonal Index'!$E$2:$E$53,AI25) -> 1.0519567 | AP25: =IF(AJ25=1,C25/AO25,"") | AQ25: =IF(AJ25=1,A25-Regression!$C$15,0) -> 0 | AR25: =IF(AJ25=1,AK25-Regression!$D$15,0) -> 0 | AS25: =IF(AJ25=1,AL25-Regression!$E$15,0) -> 0 | AT25: =IF(AJ25=1,AP25-Regression!$F$15,0) -> 0 | AU25: =IF(AND(ISNUMBER(AK25),ISNUMBER(AL25)),Regression!$C$38+Regression!$D$38*A25+Regression!$E$38*AK25+Regression!$F$38*AL25,"") -> 10765.053 | AV25: =IF(ISNUMBER(AU25),AU25*AO25,"") -> 11324.369 | AW25: =IF(AJ25=1,"Train",IF(AH25=Inputs!$B$6+1,"Validation",IF(AH25>Inputs!$B$6+1,"Forecast","Not used"))) -> Not used | AX25: =IF(ISNUMBER(C25),C25,IF(ISNUMBER(D25),D25,"")) -> 7380 | AY25: =IF(AND(AW25="Validation",ISNUMBER(AX25),ISNUMBER(AV25)),ABS(AX25-AV25)/AX25,"") | AZ25: =IF(AJ25=1,AP25-AU25,0) -> 0 | BB25: =Regression!$C$45+Regression!$C$46*A25 -> 6181.7075 | BC25: =IF(AND(AH25>=2022,AH25<=2024),C25/BB25,"") | BD25: =INDEX('Seasonal Index'!$H$2:$H$53,AI25) -> 1.048616 | BE25: =IF(AH25>=2022,BB25*BD25,"") | BF25: =IF(AND(AW25="Validation",ISNUMBER(AX25),ISNUMBER(BE25)),ABS(AX25-BE25)/AX25,"") | BG25: =IF(ISNUMBER(C25),C25,0) -> 7380 | BH25: =IF(ISNUMBER(AY25),AV25-AX25,0) -> 0 | BI25: =IF(ISNUMBER(AY25),BE25-AX25,0) -> 0
A26: 25 | B26: 33445 | C26: 7501 | F26: 408000 | H26: 21.398 | I26: 19.664 | J26: 1.091 | K26: 6035.178 | M26: 819 | N26: 12.719 | O26: 191929 | P26: 3933.2 | Q26: 824860 | W26: 84.6 | AD26: 0 | AE26: 0 | AF26: 90.6 | AH26: =YEAR(B26) -> 1991 | AI26: =MIN(52,INT((B26-DATE(AH26,1,1))/7)+1) -> 30 | AJ26: =IF(AND(ISNUMBER(C26),ISNUMBER(AK26),ISNUMBER(AL26),AH26>=Inputs!$B$5,AH26<=Inputs!$B$6,AH26<>Inputs!$B$7,AH26<>Inputs!$B$8),1,0) -> 0 | AK26: =IF(INDEX($E26:$AF26,Inputs!$C$10)="","",INDEX($E26:$AF26,Inputs!$C$10)) -> 191929 | AL26: =IF(INDEX($E26:$AF26,Inputs!$C$11)="","",INDEX($E26:$AF26,Inputs!$C$11)) -> 408000 | AM26: =Regression!$C$5+Regression!$C$6*A26 -> 10817.233 | AN26: =IF(AJ26=1,C26/AM26,"") | AO26: =INDEX('Seasonal Index'!$E$2:$E$53,AI26) -> 1.031713 | AP26: =IF(AJ26=1,C26/AO26,"") | AQ26: =IF(AJ26=1,A26-Regression!$C$15,0) -> 0 | AR26: =IF(AJ26=1,AK26-Regression!$D$15,0) -> 0 | AS26: =IF(AJ26=1,AL26-Regression!$E$15,0) -> 0 | AT26: =IF(AJ26=1,AP26-Regression!$F$15,0) -> 0 | AU26: =IF(AND(ISNUMBER(AK26),ISNUMBER(AL26)),Regression!$C$38+Regression!$D$38*A26+Regression!$E$38*AK26+Regression!$F$38*AL26,"") -> 10795.351 | AV26: =IF(ISNUMBER(AU26),AU26*AO26,"") -> 11137.704 | AW26: =IF(AJ26=1,"Train",IF(AH26=Inputs!$B$6+1,"Validation",IF(AH26>Inputs!$B$6+1,"Forecast","Not used"))) -> Not used | AX26: =IF(ISNUMBER(C26),C26,IF(ISNUMBER(D26),D26,"")) -> 7501 | AY26: =IF(AND(AW26="Validation",ISNUMBER(AX26),ISNUMBER(AV26)),ABS(AX26-AV26)/AX26,"") | AZ26: =IF(AJ26=1,AP26-AU26,0) -> 0 | BB26: =Regression!$C$45+Regression!$C$46*A26 -> 6183.267 | BC26: =IF(AND(AH26>=2022,AH26<=2024),C26/BB26,"") | BD26: =INDEX('Seasonal Index'!$H$2:$H$53,AI26) -> 1.0099032 | BE26: =IF(AH26>=2022,BB26*BD26,"") | BF26: =IF(AND(AW26="Validation",ISNUMBER(AX26),ISNUMBER(BE26)),ABS(AX26-BE26)/AX26,"") | BG26: =IF(ISNUMBER(C26),C26,0) -> 7501 | BH26: =IF(ISNUMBER(AY26),AV26-AX26,0) -> 0 | BI26: =IF(ISNUMBER(AY26),BE26-AX26,0) -> 0
A27: 26 | B27: 33452 | C27: 7605 | F27: 423000 | H27: 21.462 | I27: 19.568 | J27: 1.091 | K27: 6035.178 | M27: 819 | N27: 12.719 | O27: 191929 | P27: 3933.2 | Q27: 824860 | W27: 84.6 | AD27: 0 | AE27: 0 | AF27: 80.7 | AH27: =YEAR(B27) -> 1991 | AI27: =MIN(52,INT((B27-DATE(AH27,1,1))/7)+1) -> 31 | AJ27: =IF(AND(ISNUMBER(C27),ISNUMBER(AK27),ISNUMBER(AL27),AH27>=Inputs!$B$5,AH27<=Inputs!$B$6,AH27<>Inputs!$B$7,AH27<>Inputs!$B$8),1,0) -> 0 | AK27: =IF(INDEX($E27:$AF27,Inputs!$C$10)="","",INDEX($E27:$AF27,Inputs!$C$10)) -> 191929 | AL27: =IF(INDEX($E27:$AF27,Inputs!$C$11)="","",INDEX($E27:$AF27,Inputs!$C$11)) -> 423000 | AM27: =Regression!$C$5+Regression!$C$6*A27 -> 10816.06 | AN27: =IF(AJ27=1,C27/AM27,"") | AO27: =INDEX('Seasonal Index'!$E$2:$E$53,AI27) -> 1.0399732 | AP27: =IF(AJ27=1,C27/AO27,"") | AQ27: =IF(AJ27=1,A27-Regression!$C$15,0) -> 0 | AR27: =IF(AJ27=1,AK27-Regression!$D$15,0) -> 0 | AS27: =IF(AJ27=1,AL27-Regression!$E$15,0) -> 0 | AT27: =IF(AJ27=1,AP27-Regression!$F$15,0) -> 0 | AU27: =IF(AND(ISNUMBER(AK27),ISNUMBER(AL27)),Regression!$C$38+Regression!$D$38*A27+Regression!$E$38*AK27+Regression!$F$38*AL27,"") -> 10753.963 | AV27: =IF(ISNUMBER(AU27),AU27*AO27,"") -> 11183.833 | AW27: =IF(AJ27=1,"Train",IF(AH27=Inputs!$B$6+1,"Validation",IF(AH27>Inputs!$B$6+1,"Forecast","Not used"))) -> Not used | AX27: =IF(ISNUMBER(C27),C27,IF(ISNUMBER(D27),D27,"")) -> 7605 | AY27: =IF(AND(AW27="Validation",ISNUMBER(AX27),ISNUMBER(AV27)),ABS(AX27-AV27)/AX27,"") | AZ27: =IF(AJ27=1,AP27-AU27,0) -> 0 | BB27: =Regression!$C$45+Regression!$C$46*A27 -> 6184.8265 | BC27: =IF(AND(AH27>=2022,AH27<=2024),C27/BB27,"") | BD27: =INDEX('Seasonal Index'!$H$2:$H$53,AI27) -> 1.0389648 | BE27: =IF(AH27>=2022,BB27*BD27,"") | BF27: =IF(AND(AW27="Validation",ISNUMBER(AX27),ISNUMBER(BE27)),ABS(AX27-BE27)/AX27,"") | BG27: =IF(ISNUMBER(C27),C27,0) -> 7605 | BH27: =IF(ISNUMBER(AY27),AV27-AX27,0) -> 0 | BI27: =IF(ISNUMBER(AY27),BE27-AX27,0) -> 0
A28: 27 | B28: 33459 | C28: 7584 | F28: 438000 | H28: 21.502 | I28: 19.516 | J28: 1.099 | K28: 6126.862 | M28: 867 | N28: 12.719 | O28: 191929 | P28: 3940.5 | Q28: 824860 | W28: 87.5 | AD28: 0 | AE28: 0 | AF28: 74.8 | AH28: =YEAR(B28) -> 1991 | AI28: =MIN(52,INT((B28-DATE(AH28,1,1))/7)+1) -> 32 | AJ28: =IF(AND(ISNUMBER(C28),ISNUMBER(AK28),ISNUMBER(AL28),AH28>=Inputs!$B$5,AH28<=Inputs!$B$6,AH28<>Inputs!$B$7,AH28<>Inputs!$B$8),1,0) -> 0 | AK28: =IF(INDEX($E28:$AF28,Inputs!$C$10)="","",INDEX($E28:$AF28,Inputs!$C$10)) -> 191929 | AL28: =IF(INDEX($E28:$AF28,Inputs!$C$11)="","",INDEX($E28:$AF28,Inputs!$C$11)) -> 438000 | AM28: =Regression!$C$5+Regression!$C$6*A28 -> 10814.888 | AN28: =IF(AJ28=1,C28/AM28,"") | AO28: =INDEX('Seasonal Index'!$E$2:$E$53,AI28) -> 1.0406169 | AP28: =IF(AJ28=1,C28/AO28,"") | AQ28: =IF(AJ28=1,A28-Regression!$C$15,0) -> 0 | AR28: =IF(AJ28=1,AK28-Regression!$D$15,0) -> 0 | AS28: =IF(AJ28=1,AL28-Regression!$E$15,0) -> 0 | AT28: =IF(AJ28=1,AP28-Regression!$F$15,0) -> 0 | AU28: =IF(AND(ISNUMBER(AK28),ISNUMBER(AL28)),Regression!$C$38+Regression!$D$38*A28+Regression!$E$38*AK28+Regression!$F$38*AL28,"") -> 10712.575 | AV28: =IF(ISNUMBER(AU28),AU28*AO28,"") -> 11147.687 | AW28: =IF(AJ28=1,"Train",IF(AH28=Inputs!$B$6+1,"Validation",IF(AH28>Inputs!$B$6+1,"Forecast","Not used"))) -> Not used | AX28: =IF(ISNUMBER(C28),C28,IF(ISNUMBER(D28),D28,"")) -> 7584 | AY28: =IF(AND(AW28="Validation",ISNUMBER(AX28),ISNUMBER(AV28)),ABS(AX28-AV28)/AX28,"") | AZ28: =IF(AJ28=1,AP28-AU28,0) -> 0 | BB28: =Regression!$C$45+Regression!$C$46*A28 -> 6186.386 | BC28: =IF(AND(AH28>=2022,AH28<=2024),C28/BB28,"") | BD28: =INDEX('Seasonal Index'!$H$2:$H$53,AI28) -> 1.0332209 | BE28: =IF(AH28>=2022,BB28*BD28,"") | BF28: =IF(AND(AW28="Validation",ISNUMBER(AX28),ISNUMBER(BE28)),ABS(AX28-BE28)/AX28,"") | BG28: =IF(ISNUMBER(C28),C28,0) -> 7584 | BH28: =IF(ISNUMBER(AY28),AV28-AX28,0) -> 0 | BI28: =IF(ISNUMBER(AY28),BE28-AX28,0) -> 0
A29: 28 | B29: 33466 | C29: 7401 | F29: 437000 | H29: 21.442 | I29: 19.392 | J29: 1.112 | K29: 6126.862 | M29: 867 | N29: 12.972 | O29: 193467 | P29: 3940.5 | Q29: 824860 | W29: 87.5 | AD29: 0 | AE29: 0 | AF29: 75.2 | AH29: =YEAR(B29) -> 1991 | AI29: =MIN(52,INT((B29-DATE(AH29,1,1))/7)+1) -> 33 | AJ29: =IF(AND(ISNUMBER(C29),ISNUMBER(AK29),ISNUMBER(AL29),AH29>=Inputs!$B$5,AH29<=Inputs!$B$6,AH29<>Inputs!$B$7,AH29<>Inputs!$B$8),1,0) -> 0 | AK29: =IF(INDEX($E29:$AF29,Inputs!$C$10)="","",INDEX($E29:$AF29,Inputs!$C$10)) -> 193467 | AL29: =IF(INDEX($E29:$AF29,Inputs!$C$11)="","",INDEX($E29:$AF29,Inputs!$C$11)) -> 437000 | AM29: =Regression!$C$5+Regression!$C$6*A29 -> 10813.715 | AN29: =IF(AJ29=1,C29/AM29,"") | AO29: =INDEX('Seasonal Index'!$E$2:$E$53,AI29) -> 1.0274781 | AP29: =IF(AJ29=1,C29/AO29,"") | AQ29: =IF(AJ29=1,A29-Regression!$C$15,0) -> 0 | AR29: =IF(AJ29=1,AK29-Regression!$D$15,0) -> 0 | AS29: =IF(AJ29=1,AL29-Regression!$E$15,0) -> 0 | AT29: =IF(AJ29=1,AP29-Regression!$F$15,0) -> 0 | AU29: =IF(AND(ISNUMBER(AK29),ISNUMBER(AL29)),Regression!$C$38+Regression!$D$38*A29+Regression!$E$38*AK29+Regression!$F$38*AL29,"") -> 10716.474 | AV29: =IF(ISNUMBER(AU29),AU29*AO29,"") -> 11010.942 | AW29: =IF(AJ29=1,"Train",IF(AH29=Inputs!$B$6+1,"Validation",IF(AH29>Inputs!$B$6+1,"Forecast","Not used"))) -> Not used | AX29: =IF(ISNUMBER(C29),C29,IF(ISNUMBER(D29),D29,"")) -> 7401 | AY29: =IF(AND(AW29="Validation",ISNUMBER(AX29),ISNUMBER(AV29)),ABS(AX29-AV29)/AX29,"") | AZ29: =IF(AJ29=1,AP29-AU29,0) -> 0 | BB29: =Regression!$C$45+Regression!$C$46*A29 -> 6187.9455 | BC29: =IF(AND(AH29>=2022,AH29<=2024),C29/BB29,"") | BD29: =INDEX('Seasonal Index'!$H$2:$H$53,AI29) -> 1.00586 | BE29: =IF(AH29>=2022,BB29*BD29,"") | BF29: =IF(AND(AW29="Validation",ISNUMBER(AX29),ISNUMBER(BE29)),ABS(AX29-BE29)/AX29,"") | BG29: =IF(ISNUMBER(C29),C29,0) -> 7401 | BH29: =IF(ISNUMBER(AY29),AV29-AX29,0) -> 0 | BI29: =IF(ISNUMBER(AY29),BE29-AX29,0) -> 0
A30: 29 | B30: 33473 | C30: 7505 | F30: 433000 | H30: 21.99 | I30: 20.092 | J30: 1.124 | K30: 6126.862 | M30: 867 | N30: 12.972 | O30: 193467 | P30: 3940.5 | Q30: 824860 | W30: 87.5 | AD30: 0 | AE30: 0 | AF30: 73.4 | AH30: =YEAR(B30) -> 1991 | AI30: =MIN(52,INT((B30-DATE(AH30,1,1))/7)+1) -> 34 | AJ30: =IF(AND(ISNUMBER(C30),ISNUMBER(AK30),ISNUMBER(AL30),AH30>=Inputs!$B$5,AH30<=Inputs!$B$6,AH30<>Inputs!$B$7,AH30<>Inputs!$B$8),1,0) -> 0 | AK30: =IF(INDEX($E30:$AF30,Inputs!$C$10)="","",INDEX($E30:$AF30,Inputs!$C$10)) -> 193467 | AL30: =IF(INDEX($E30:$AF30,Inputs!$C$11)="","",INDEX($E30:$AF30,Inputs!$C$11)) -> 433000 | AM30: =Regression!$C$5+Regression!$C$6*A30 -> 10812.542 | AN30: =IF(AJ30=1,C30/AM30,"") | AO30: =INDEX('Seasonal Index'!$E$2:$E$53,AI30) -> 1.038164 | AP30: =IF(AJ30=1,C30/AO30,"") | AQ30: =IF(AJ30=1,A30-Regression!$C$15,0) -> 0 | AR30: =IF(AJ30=1,AK30-Regression!$D$15,0) -> 0 | AS30: =IF(AJ30=1,AL30-Regression!$E$15,0) -> 0 | AT30: =IF(AJ30=1,AP30-Regression!$F$15,0) -> 0 | AU30: =IF(AND(ISNUMBER(AK30),ISNUMBER(AL30)),Regression!$C$38+Regression!$D$38*A30+Regression!$E$38*AK30+Regression!$F$38*AL30,"") -> 10725.532 | AV30: =IF(ISNUMBER(AU30),AU30*AO30,"") -> 11134.861 | AW30: =IF(AJ30=1,"Train",IF(AH30=Inputs!$B$6+1,"Validation",IF(AH30>Inputs!$B$6+1,"Forecast","Not used"))) -> Not used | AX30: =IF(ISNUMBER(C30),C30,IF(ISNUMBER(D30),D30,"")) -> 7505 | AY30: =IF(AND(AW30="Validation",ISNUMBER(AX30),ISNUMBER(AV30)),ABS(AX30-AV30)/AX30,"") | AZ30: =IF(AJ30=1,AP30-AU30,0) -> 0 | BB30: =Regression!$C$45+Regression!$C$46*A30 -> 6189.505 | BC30: =IF(AND(AH30>=2022,AH30<=2024),C30/BB30,"") | BD30: =INDEX('Seasonal Index'!$H$2:$H$53,AI30) -> 1.0219589 | BE30: =IF(AH30>=2022,BB30*BD30,"") | BF30: =IF(AND(AW30="Validation",ISNUMBER(AX30),ISNUMBER(BE30)),ABS(AX30-BE30)/AX30,"") | BG30: =IF(ISNUMBER(C30),C30,0) -> 7505 | BH30: =IF(ISNUMBER(AY30),AV30-AX30,0) -> 0 | BI30: =IF(ISNUMBER(AY30),BE30-AX30,0) -> 0
A31: 30 | B31: 33480 | C31: 7427 | F31: 425000 | H31: 21.982 | I31: 20.174 | J31: 1.124 | K31: 6126.862 | M31: 867 | N31: 12.972 | O31: 193467 | P31: 3940.5 | Q31: 824860 | W31: 87.5 | AD31: 0 | AE31: 0 | AF31: 82.8 | AH31: =YEAR(B31) -> 1991 | AI31: =MIN(52,INT((B31-DATE(AH31,1,1))/7)+1) -> 35 | AJ31: =IF(AND(ISNUMBER(C31),ISNUMBER(AK31),ISNUMBER(AL31),AH31>=Inputs!$B$5,AH31<=Inputs!$B$6,AH31<>Inputs!$B$7,AH31<>Inputs!$B$8),1,0) -> 0 | AK31: =IF(INDEX($E31:$AF31,Inputs!$C$10)="","",INDEX($E31:$AF31,Inputs!$C$10)) -> 193467 | AL31: =IF(INDEX($E31:$AF31,Inputs!$C$11)="","",INDEX($E31:$AF31,Inputs!$C$11)) -> 425000 | AM31: =Regression!$C$5+Regression!$C$6*A31 -> 10811.37 | AN31: =IF(AJ31=1,C31/AM31,"") | AO31: =INDEX('Seasonal Index'!$E$2:$E$53,AI31) -> 1.022466 | AP31: =IF(AJ31=1,C31/AO31,"") | AQ31: =IF(AJ31=1,A31-Regression!$C$15,0) -> 0 | AR31: =IF(AJ31=1,AK31-Regression!$D$15,0) -> 0 | AS31: =IF(AJ31=1,AL31-Regression!$E$15,0) -> 0 | AT31: =IF(AJ31=1,AP31-Regression!$F$15,0) -> 0 | AU31: =IF(AND(ISNUMBER(AK31),ISNUMBER(AL31)),Regression!$C$38+Regression!$D$38*A31+Regression!$E$38*AK31+Regression!$F$38*AL31,"") -> 10745.21 | AV31: =IF(ISNUMBER(AU31),AU31*AO31,"") -> 10986.611 | AW31: =IF(AJ31=1,"Train",IF(AH31=Inputs!$B$6+1,"Validation",IF(AH31>Inputs!$B$6+1,"Forecast","Not used"))) -> Not used | AX31: =IF(ISNUMBER(C31),C31,IF(ISNUMBER(D31),D31,"")) -> 7427 | AY31: =IF(AND(AW31="Validation",ISNUMBER(AX31),ISNUMBER(AV31)),ABS(AX31-AV31)/AX31,"") | AZ31: =IF(AJ31=1,AP31-AU31,0) -> 0 | BB31: =Regression!$C$45+Regression!$C$46*A31 -> 6191.0645 | BC31: =IF(AND(AH31>=2022,AH31<=2024),C31/BB31,"") | BD31: =INDEX('Seasonal Index'!$H$2:$H$53,AI31) -> 1.0227114 | BE31: =IF(AH31>=2022,BB31*BD31,"") | BF31: =IF(AND(AW31="Validation",ISNUMBER(AX31),ISNUMBER(BE31)),ABS(AX31-BE31)/AX31,"") | BG31: =IF(ISNUMBER(C31),C31,0) -> 7427 | BH31: =IF(ISNUMBER(AY31),AV31-AX31,0) -> 0 | BI31: =IF(ISNUMBER(AY31),BE31-AX31,0) -> 0
A32: 31 | B32: 33487 | C32: 6993 | F32: 425000 | H32: 21.8375 | I32: 20.336 | J32: 1.127 | K32: 6126.862 | M32: 844 | N32: 12.972 | O32: 193467 | P32: 3966 | Q32: 824860 | W32: 89.8 | AD32: 1 | AE32: 0.4 | AF32: 63.4 | AH32: =YEAR(B32) -> 1991 | AI32: =MIN(52,INT((B32-DATE(AH32,1,1))/7)+1) -> 36 | AJ32: =IF(AND(ISNUMBER(C32),ISNUMBER(AK32),ISNUMBER(AL32),AH32>=Inputs!$B$5,AH32<=Inputs!$B$6,AH32<>Inputs!$B$7,AH32<>Inputs!$B$8),1,0) -> 0 | AK32: =IF(INDEX($E32:$AF32,Inputs!$C$10)="","",INDEX($E32:$AF32,Inputs!$C$10)) -> 193467 | AL32: =IF(INDEX($E32:$AF32,Inputs!$C$11)="","",INDEX($E32:$AF32,Inputs!$C$11)) -> 425000 | AM32: =Regression!$C$5+Regression!$C$6*A32 -> 10810.197 | AN32: =IF(AJ32=1,C32/AM32,"") | AO32: =INDEX('Seasonal Index'!$E$2:$E$53,AI32) -> 1.0036108 | AP32: =IF(AJ32=1,C32/AO32,"") | AQ32: =IF(AJ32=1,A32-Regression!$C$15,0) -> 0 | AR32: =IF(AJ32=1,AK32-Regression!$D$15,0) -> 0 | AS32: =IF(AJ32=1,AL32-Regression!$E$15,0) -> 0 | AT32: =IF(AJ32=1,AP32-Regression!$F$15,0) -> 0 | AU32: =IF(AND(ISNUMBER(AK32),ISNUMBER(AL32)),Regression!$C$38+Regression!$D$38*A32+Regression!$E$38*AK32+Regression!$F$38*AL32,"") -> 10743.648 | AV32: =IF(ISNUMBER(AU32),AU32*AO32,"") -> 10782.441 | AW32: =IF(AJ32=1,"Train",IF(AH32=Inputs!$B$6+1,"Validation",IF(AH32>Inputs!$B$6+1,"Forecast","Not used"))) -> Not used | AX32: =IF(ISNUMBER(C32),C32,IF(ISNUMBER(D32),D32,"")) -> 6993 | AY32: =IF(AND(AW32="Validation",ISNUMBER(AX32),ISNUMBER(AV32)),ABS(AX32-AV32)/AX32,"") | AZ32: =IF(AJ32=1,AP32-AU32,0) -> 0 | BB32: =Regression!$C$45+Regression!$C$46*A32 -> 6192.624 | BC32: =IF(AND(AH32>=2022,AH32<=2024),C32/BB32,"") | BD32: =INDEX('Seasonal Index'!$H$2:$H$53,AI32) -> 0.95792594 | BE32: =IF(AH32>=2022,BB32*BD32,"") | BF32: =IF(AND(AW32="Validation",ISNUMBER(AX32),ISNUMBER(BE32)),ABS(AX32-BE32)/AX32,"") | BG32: =IF(ISNUMBER(C32),C32,0) -> 6993 | BH32: =IF(ISNUMBER(AY32),AV32-AX32,0) -> 0 | BI32: =IF(ISNUMBER(AY32),BE32-AX32,0) -> 0
... A47: 46 | B47: 33592 | C47: 7447 | F47: 475000 | H47: 19.204 | I47: 18.306 | J47: 1.075 | K47: 6205.937 | M47: 795 | N47: 12.576 | O47: 188445 | P47: 3976 | Q47: 818093 | W47: 88.3 | AD47: 0 | AE47: 161.3 | AF47: 0.6 | AH47: =YEAR(B47) -> 1991 | AI47: =MIN(52,INT((B47-DATE(AH47,1,1))/7)+1) -> 51 | AJ47: =IF(AND(ISNUMBER(C47),ISNUMBER(AK47),ISNUMBER(AL47),AH47>=Inputs!$B$5,AH47<=Inputs!$B$6,AH47<>Inputs!$B$7,AH47<>Inputs!$B$8),1,0) -> 0 | AK47: =IF(INDEX($E47:$AF47,Inputs!$C$10)="","",INDEX($E47:$AF47,Inputs!$C$10)) -> 188445 | AL47: =IF(INDEX($E47:$AF47,Inputs!$C$11)="","",INDEX($E47:$AF47,Inputs!$C$11)) -> 475000 | AM47: =Regression!$C$5+Regression!$C$6*A47 -> 10792.607 | AN47: =IF(AJ47=1,C47/AM47,"") | AO47: =INDEX('Seasonal Index'!$E$2:$E$53,AI47) -> 1.0219733 | AP47: =IF(AJ47=1,C47/AO47,"") | AQ47: =IF(AJ47=1,A47-Regression!$C$15,0) -> 0 | AR47: =IF(AJ47=1,AK47-Regression!$D$15,0) -> 0 | AS47: =IF(AJ47=1,AL47-Regression!$E$15,0) -> 0 | AT47: =IF(AJ47=1,AP47-Regression!$F$15,0) -> 0 | AU47: =IF(AND(ISNUMBER(AK47),ISNUMBER(AL47)),Regression!$C$38+Regression!$D$38*A47+Regression!$E$38*AK47+Regression!$F$38*AL47,"") -> 10578.297 | AV47: =IF(ISNUMBER(AU47),AU47*AO47,"") -> 10810.738 | AW47: =IF(AJ47=1,"Train",IF(AH47=Inputs!$B$6+1,"Validation",IF(AH47>Inputs!$B$6+1,"Forecast","Not used"))) -> Not used | AX47: =IF(ISNUMBER(C47),C47,IF(ISNUMBER(D47),D47,"")) -> 7447 | AY47: =IF(AND(AW47="Validation",ISNUMBER(AX47),ISNUMBER(AV47)),ABS(AX47-AV47)/AX47,"") | AZ47: =IF(AJ47=1,AP47-AU47,0) -> 0 | BB47: =Regression!$C$45+Regression!$C$46*A47 -> 6216.0165 | BC47: =IF(AND(AH47>=2022,AH47<=2024),C47/BB47,"") | BD47: =INDEX('Seasonal Index'!$H$2:$H$53,AI47) -> 1.0395425 | BE47: =IF(AH47>=2022,BB47*BD47,"") | BF47: =IF(AND(AW47="Validation",ISNUMBER(AX47),ISNUMBER(BE47)),ABS(AX47-BE47)/AX47,"") | BG47: =IF(ISNUMBER(C47),C47,0) -> 7447 | BH47: =IF(ISNUMBER(AY47),AV47-AX47,0) -> 0 | BI47: =IF(ISNUMBER(AY47),BE47-AX47,0) -> 0
A48: 47 | B48: 33599 | C48: 7186 | F48: 436000 | H48: 18.6775 | I48: 17.7275 | J48: 1.063 | K48: 6205.937 | M48: 795 | N48: 12.576 | O48: 188445 | P48: 3976 | Q48: 818093 | V48: 28 | W48: 88.3 | AD48: 1 | AE48: 145.4 | AF48: 1.4 | AH48: =YEAR(B48) -> 1991 | AI48: =MIN(52,INT((B48-DATE(AH48,1,1))/7)+1) -> 52 | AJ48: =IF(AND(ISNUMBER(C48),ISNUMBER(AK48),ISNUMBER(AL48),AH48>=Inputs!$B$5,AH48<=Inputs!$B$6,AH48<>Inputs!$B$7,AH48<>Inputs!$B$8),1,0) -> 0 | AK48: =IF(INDEX($E48:$AF48,Inputs!$C$10)="","",INDEX($E48:$AF48,Inputs!$C$10)) -> 188445 | AL48: =IF(INDEX($E48:$AF48,Inputs!$C$11)="","",INDEX($E48:$AF48,Inputs!$C$11)) -> 436000 | AM48: =Regression!$C$5+Regression!$C$6*A48 -> 10791.434 | AN48: =IF(AJ48=1,C48/AM48,"") | AO48: =INDEX('Seasonal Index'!$E$2:$E$53,AI48) -> 0.9410597 | AP48: =IF(AJ48=1,C48/AO48,"") | AQ48: =IF(AJ48=1,A48-Regression!$C$15,0) -> 0 | AR48: =IF(AJ48=1,AK48-Regression!$D$15,0) -> 0 | AS48: =IF(AJ48=1,AL48-Regression!$E$15,0) -> 0 | AT48: =IF(AJ48=1,AP48-Regression!$F$15,0) -> 0 | AU48: =IF(AND(ISNUMBER(AK48),ISNUMBER(AL48)),Regression!$C$38+Regression!$D$38*A48+Regression!$E$38*AK48+Regression!$F$38*AL48,"") -> 10680.282 | AV48: =IF(ISNUMBER(AU48),AU48*AO48,"") -> 10050.783 | AW48: =IF(AJ48=1,"Train",IF(AH48=Inputs!$B$6+1,"Validation",IF(AH48>Inputs!$B$6+1,"Forecast","Not used"))) -> Not used | AX48: =IF(ISNUMBER(C48),C48,IF(ISNUMBER(D48),D48,"")) -> 7186 | AY48: =IF(AND(AW48="Validation",ISNUMBER(AX48),ISNUMBER(AV48)),ABS(AX48-AV48)/AX48,"") | AZ48: =IF(AJ48=1,AP48-AU48,0) -> 0 | BB48: =Regression!$C$45+Regression!$C$46*A48 -> 6217.576 | BC48: =IF(AND(AH48>=2022,AH48<=2024),C48/BB48,"") | BD48: =INDEX('Seasonal Index'!$H$2:$H$53,AI48) -> 0.8928993 | BE48: =IF(AH48>=2022,BB48*BD48,"") | BF48: =IF(AND(AW48="Validation",ISNUMBER(AX48),ISNUMBER(BE48)),ABS(AX48-BE48)/AX48,"") | BG48: =IF(ISNUMBER(C48),C48,0) -> 7186 | BH48: =IF(ISNUMBER(AY48),AV48-AX48,0) -> 0 | BI48: =IF(ISNUMBER(AY48),BE48-AX48,0) -> 0
A49: 48 | B49: 33606 | C49: 6642 | F49: 441000 | H49: 19.1075 | I49: 18.175 | J49: 1.053 | K49: 6205.937 | M49: 795 | N49: 12.576 | O49: 188445 | P49: 3976 | Q49: 818093 | V49: 28 | W49: 88.3 | AD49: 1 | AE49: 155.2 | AF49: 0 | AH49: =YEAR(B49) -> 1992 | AI49: =MIN(52,INT((B49-DATE(AH49,1,1))/7)+1) -> 1 | AJ49: =IF(AND(ISNUMBER(C49),ISNUMBER(AK49),ISNUMBER(AL49),AH49>=Inputs!$B$5,AH49<=Inputs!$B$6,AH49<>Inputs!$B$7,AH49<>Inputs!$B$8),1,0) -> 0 | AK49: =IF(INDEX($E49:$AF49,Inputs!$C$10)="","",INDEX($E49:$AF49,Inputs!$C$10)) -> 188445 | AL49: =IF(INDEX($E49:$AF49,Inputs!$C$11)="","",INDEX($E49:$AF49,Inputs!$C$11)) -> 441000 | AM49: =Regression!$C$5+Regression!$C$6*A49 -> 10790.262 | AN49: =IF(AJ49=1,C49/AM49,"") | AO49: =INDEX('Seasonal Index'!$E$2:$E$53,AI49) -> 0.91465819 | AP49: =IF(AJ49=1,C49/AO49,"") | AQ49: =IF(AJ49=1,A49-Regression!$C$15,0) -> 0 | AR49: =IF(AJ49=1,AK49-Regression!$D$15,0) -> 0 | AS49: =IF(AJ49=1,AL49-Regression!$E$15,0) -> 0 | AT49: =IF(AJ49=1,AP49-Regression!$F$15,0) -> 0 | AU49: =IF(AND(ISNUMBER(AK49),ISNUMBER(AL49)),Regression!$C$38+Regression!$D$38*A49+Regression!$E$38*AK49+Regression!$F$38*AL49,"") -> 10665.444 | AV49: =IF(ISNUMBER(AU49),AU49*AO49,"") -> 9755.2358 | AW49: =IF(AJ49=1,"Train",IF(AH49=Inputs!$B$6+1,"Validation",IF(AH49>Inputs!$B$6+1,"Forecast","Not used"))) -> Not used | AX49: =IF(ISNUMBER(C49),C49,IF(ISNUMBER(D49),D49,"")) -> 6642 | AY49: =IF(AND(AW49="Validation",ISNUMBER(AX49),ISNUMBER(AV49)),ABS(AX49-AV49)/AX49,"") | AZ49: =IF(AJ49=1,AP49-AU49,0) -> 0 | BB49: =Regression!$C$45+Regression!$C$46*A49 -> 6219.1355 | BC49: =IF(AND(AH49>=2022,AH49<=2024),C49/BB49,"") | BD49: =INDEX('Seasonal Index'!$H$2:$H$53,AI49) -> 0.90693989 | BE49: =IF(AH49>=2022,BB49*BD49,"") | BF49: =IF(AND(AW49="Validation",ISNUMBER(AX49),ISNUMBER(BE49)),ABS(AX49-BE49)/AX49,"") | BG49: =IF(ISNUMBER(C49),C49,0) -> 6642 | BH49: =IF(ISNUMBER(AY49),AV49-AX49,0) -> 0 | BI49: =IF(ISNUMBER(AY49),BE49-AX49,0) -> 0
A50: 49 | B50: 33613 | C50: 6788 | F50: 432000 | H50: 18.412 | I50: 17.772 | J50: 1.042 | K50: 6205.937 | M50: 808 | N50: 12.576 | O50: 188445 | P50: 4003.6 | Q50: 818093 | V50: 28 | W50: 83.4 | AD50: 0 | AE50: 140.8 | AF50: 0 | AH50: =YEAR(B50) -> 1992 | AI50: =MIN(52,INT((B50-DATE(AH50,1,1))/7)+1) -> 2 | AJ50: =IF(AND(ISNUMBER(C50),ISNUMBER(AK50),ISNUMBER(AL50),AH50>=Inputs!$B$5,AH50<=Inputs!$B$6,AH50<>Inputs!$B$7,AH50<>Inputs!$B$8),1,0) -> 0 | AK50: =IF(INDEX($E50:$AF50,Inputs!$C$10)="","",INDEX($E50:$AF50,Inputs!$C$10)) -> 188445 | AL50: =IF(INDEX($E50:$AF50,Inputs!$C$11)="","",INDEX($E50:$AF50,Inputs!$C$11)) -> 432000 | AM50: =Regression!$C$5+Regression!$C$6*A50 -> 10789.089 | AN50: =IF(AJ50=1,C50/AM50,"") | AO50: =INDEX('Seasonal Index'!$E$2:$E$53,AI50) -> 0.92112372 | AP50: =IF(AJ50=1,C50/AO50,"") | AQ50: =IF(AJ50=1,A50-Regression!$C$15,0) -> 0 | AR50: =IF(AJ50=1,AK50-Regression!$D$15,0) -> 0 | AS50: =IF(AJ50=1,AL50-Regression!$E$15,0) -> 0 | AT50: =IF(AJ50=1,AP50-Regression!$F$15,0) -> 0 | AU50: =IF(AND(ISNUMBER(AK50),ISNUMBER(AL50)),Regression!$C$38+Regression!$D$38*A50+Regression!$E$38*AK50+Regression!$F$38*AL50,"") -> 10687.777 | AV50: =IF(ISNUMBER(AU50),AU50*AO50,"") -> 9844.7651 | AW50: =IF(AJ50=1,"Train",IF(AH50=Inputs!$B$6+1,"Validation",IF(AH50>Inputs!$B$6+1,"Forecast","Not used"))) -> Not used | AX50: =IF(ISNUMBER(C50),C50,IF(ISNUMBER(D50),D50,"")) -> 6788 | AY50: =IF(AND(AW50="Validation",ISNUMBER(AX50),ISNUMBER(AV50)),ABS(AX50-AV50)/AX50,"") | AZ50: =IF(AJ50=1,AP50-AU50,0) -> 0 | BB50: =Regression!$C$45+Regression!$C$46*A50 -> 6220.695 | BC50: =IF(AND(AH50>=2022,AH50<=2024),C50/BB50,"") | BD50: =INDEX('Seasonal Index'!$H$2:$H$53,AI50) -> 0.93580736 | BE50: =IF(AH50>=2022,BB50*BD50,"") | BF50: =IF(AND(AW50="Validation",ISNUMBER(AX50),ISNUMBER(BE50)),ABS(AX50-BE50)/AX50,"") | BG50: =IF(ISNUMBER(C50),C50,0) -> 6788 | BH50: =IF(ISNUMBER(AY50),AV50-AX50,0) -> 0 | BI50: =IF(ISNUMBER(AY50),BE50-AX50,0) -> 0
A51: 50 | B51: 33620 | C51: 6783 | F51: 440000 | H51: 18.81 | I51: 18.37 | J51: 1.026 | K51: 6205.937 | M51: 808 | N51: 12.658 | O51: 169693 | P51: 4003.6 | Q51: 818093 | V51: 28 | W51: 83.4 | AD51: 0 | AE51: 185.6 | AF51: 0 | AH51: =YEAR(B51) -> 1992 | AI51: =MIN(52,INT((B51-DATE(AH51,1,1))/7)+1) -> 3 | AJ51: =IF(AND(ISNUMBER(C51),ISNUMBER(AK51),ISNUMBER(AL51),AH51>=Inputs!$B$5,AH51<=Inputs!$B$6,AH51<>Inputs!$B$7,AH51<>Inputs!$B$8),1,0) -> 0 | AK51: =IF(INDEX($E51:$AF51,Inputs!$C$10)="","",INDEX($E51:$AF51,Inputs!$C$10)) -> 169693 | AL51: =IF(INDEX($E51:$AF51,Inputs!$C$11)="","",INDEX($E51:$AF51,Inputs!$C$11)) -> 440000 | AM51: =Regression!$C$5+Regression!$C$6*A51 -> 10787.916 | AN51: =IF(AJ51=1,C51/AM51,"") | AO51: =INDEX('Seasonal Index'!$E$2:$E$53,AI51) -> 0.93247571 | AP51: =IF(AJ51=1,C51/AO51,"") | AQ51: =IF(AJ51=1,A51-Regression!$C$15,0) -> 0 | AR51: =IF(AJ51=1,AK51-Regression!$D$15,0) -> 0 | AS51: =IF(AJ51=1,AL51-Regression!$E$15,0) -> 0 | AT51: =IF(AJ51=1,AP51-Regression!$F$15,0) -> 0 | AU51: =IF(AND(ISNUMBER(AK51),ISNUMBER(AL51)),Regression!$C$38+Regression!$D$38*A51+Regression!$E$38*AK51+Regression!$F$38*AL51,"") -> 10630.758 | AV51: =IF(ISNUMBER(AU51),AU51*AO51,"") -> 9912.9239 | AW51: =IF(AJ51=1,"Train",IF(AH51=Inputs!$B$6+1,"Validation",IF(AH51>Inputs!$B$6+1,"Forecast","Not used"))) -> Not used | AX51: =IF(ISNUMBER(C51),C51,IF(ISNUMBER(D51),D51,"")) -> 6783 | AY51: =IF(AND(AW51="Validation",ISNUMBER(AX51),ISNUMBER(AV51)),ABS(AX51-AV51)/AX51,"") | AZ51: =IF(AJ51=1,AP51-AU51,0) -> 0 | BB51: =Regression!$C$45+Regression!$C$46*A51 -> 6222.2545 | BC51: =IF(AND(AH51>=2022,AH51<=2024),C51/BB51,"") | BD51: =INDEX('Seasonal Index'!$H$2:$H$53,AI51) -> 0.93511464 | BE51: =IF(AH51>=2022,BB51*BD51,"") | BF51: =IF(AND(AW51="Validation",ISNUMBER(AX51),ISNUMBER(BE51)),ABS(AX51-BE51)/AX51,"") | BG51: =IF(ISNUMBER(C51),C51,0) -> 6783 | BH51: =IF(ISNUMBER(AY51),AV51-AX51,0) -> 0 | BI51: =IF(ISNUMBER(AY51),BE51-AX51,0) -> 0
A52: 51 | B52: 33627 | C52: 7037 | F52: 443000 | H52: 18.656 | I52: 18.112 | J52: 1.014 | K52: 6205.937 | M52: 808 | N52: 12.658 | O52: 169693 | P52: 4003.6 | Q52: 818093 | V52: 28 | W52: 83.4 | AD52: 0 | AE52: 191.3 | AF52: 0 | AH52: =YEAR(B52) -> 1992 | AI52: =MIN(52,INT((B52-DATE(AH52,1,1))/7)+1) -> 4 | AJ52: =IF(AND(ISNUMBER(C52),ISNUMBER(AK52),ISNUMBER(AL52),AH52>=Inputs!$B$5,AH52<=Inputs!$B$6,AH52<>Inputs!$B$7,AH52<>Inputs!$B$8),1,0) -> 0 | AK52: =IF(INDEX($E52:$AF52,Inputs!$C$10)="","",INDEX($E52:$AF52,Inputs!$C$10)) -> 169693 | AL52: =IF(INDEX($E52:$AF52,Inputs!$C$11)="","",INDEX($E52:$AF52,Inputs!$C$11)) -> 443000 | AM52: =Regression!$C$5+Regression!$C$6*A52 -> 10786.744 | AN52: =IF(AJ52=1,C52/AM52,"") | AO52: =INDEX('Seasonal Index'!$E$2:$E$53,AI52) -> 0.95567024 | AP52: =IF(AJ52=1,C52/AO52,"") | AQ52: =IF(AJ52=1,A52-Regression!$C$15,0) -> 0 | AR52: =IF(AJ52=1,AK52-Regression!$D$15,0) -> 0 | AS52: =IF(AJ52=1,AL52-Regression!$E$15,0) -> 0 | AT52: =IF(AJ52=1,AP52-Regression!$F$15,0) -> 0 | AU52: =IF(AND(ISNUMBER(AK52),ISNUMBER(AL52)),Regression!$C$38+Regression!$D$38*A52+Regression!$E$38*AK52+Regression!$F$38*AL52,"") -> 10621.231 | AV52: =IF(ISNUMBER(AU52),AU52*AO52,"") -> 10150.394 | AW52: =IF(AJ52=1,"Train",IF(AH52=Inputs!$B$6+1,"Validation",IF(AH52>Inputs!$B$6+1,"Forecast","Not used"))) -> Not used | AX52: =IF(ISNUMBER(C52),C52,IF(ISNUMBER(D52),D52,"")) -> 7037 | AY52: =IF(AND(AW52="Validation",ISNUMBER(AX52),ISNUMBER(AV52)),ABS(AX52-AV52)/AX52,"") | AZ52: =IF(AJ52=1,AP52-AU52,0) -> 0 | BB52: =Regression!$C$45+Regression!$C$46*A52 -> 6223.814 | BC52: =IF(AND(AH52>=2022,AH52<=2024),C52/BB52,"") | BD52: =INDEX('Seasonal Index'!$H$2:$H$53,AI52) -> 0.947484 | BE52: =IF(AH52>=2022,BB52*BD52,"") | BF52: =IF(AND(AW52="Validation",ISNUMBER(AX52),ISNUMBER(BE52)),ABS(AX52-BE52)/AX52,"") | BG52: =IF(ISNUMBER(C52),C52,0) -> 7037 | BH52: =IF(ISNUMBER(AY52),AV52-AX52,0) -> 0 | BI52: =IF(ISNUMBER(AY52),BE52-AX52,0) -> 0
A53: 52 | B53: 33634 | C53: 7112 | F53: 441000 | H53: 19.048 | I53: 18.276 | J53: 1.006 | K53: 6205.937 | M53: 808 | N53: 12.658 | O53: 169693 | P53: 4003.6 | Q53: 818093 | V53: 28 | W53: 83.4 | AD53: 0 | AE53: 156.1 | AF53: 0 | AH53: =YEAR(B53) -> 1992 | AI53: =MIN(52,INT((B53-DATE(AH53,1,1))/7)+1) -> 5 | AJ53: =IF(AND(ISNUMBER(C53),ISNUMBER(AK53),ISNUMBER(AL53),AH53>=Inputs!$B$5,AH53<=Inputs!$B$6,AH53<>Inputs!$B$7,AH53<>Inputs!$B$8),1,0) -> 0 | AK53: =IF(INDEX($E53:$AF53,Inputs!$C$10)="","",INDEX($E53:$AF53,Inputs!$C$10)) -> 169693 | AL53: =IF(INDEX($E53:$AF53,Inputs!$C$11)="","",INDEX($E53:$AF53,Inputs!$C$11)) -> 441000 | AM53: =Regression!$C$5+Regression!$C$6*A53 -> 10785.571 | AN53: =IF(AJ53=1,C53/AM53,"") | AO53: =INDEX('Seasonal Index'!$E$2:$E$53,AI53) -> 0.96378521 | AP53: =IF(AJ53=1,C53/AO53,"") | AQ53: =IF(AJ53=1,A53-Regression!$C$15,0) -> 0 | AR53: =IF(AJ53=1,AK53-Regression!$D$15,0) -> 0 | AS53: =IF(AJ53=1,AL53-Regression!$E$15,0) -> 0 | AT53: =IF(AJ53=1,AP53-Regression!$F$15,0) -> 0 | AU53: =IF(AND(ISNUMBER(AK53),ISNUMBER(AL53)),Regression!$C$38+Regression!$D$38*A53+Regression!$E$38*AK53+Regression!$F$38*AL53,"") -> 10624.979 | AV53: =IF(ISNUMBER(AU53),AU53*AO53,"") -> 10240.197 | AW53: =IF(AJ53=1,"Train",IF(AH53=Inputs!$B$6+1,"Validation",IF(AH53>Inputs!$B$6+1,"Forecast","Not used"))) -> Not used | AX53: =IF(ISNUMBER(C53),C53,IF(ISNUMBER(D53),D53,"")) -> 7112 | AY53: =IF(AND(AW53="Validation",ISNUMBER(AX53),ISNUMBER(AV53)),ABS(AX53-AV53)/AX53,"") | AZ53: =IF(AJ53=1,AP53-AU53,0) -> 0 | BB53: =Regression!$C$45+Regression!$C$46*A53 -> 6225.3735 | BC53: =IF(AND(AH53>=2022,AH53<=2024),C53/BB53,"") | BD53: =INDEX('Seasonal Index'!$H$2:$H$53,AI53) -> 1.0045556 | BE53: =IF(AH53>=2022,BB53*BD53,"") | BF53: =IF(AND(AW53="Validation",ISNUMBER(AX53),ISNUMBER(BE53)),ABS(AX53-BE53)/AX53,"") | BG53: =IF(ISNUMBER(C53),C53,0) -> 7112 | BH53: =IF(ISNUMBER(AY53),AV53-AX53,0) -> 0 | BI53: =IF(ISNUMBER(AY53),BE53-AX53,0) -> 0
A54: 53 | B54: 33641 | C54: 7039 | F54: 440000 | H54: 19.424 | I54: 18.468 | J54: 0.995 | K54: 6264.54 | M54: 796 | N54: 12.658 | O54: 169693 | P54: 4020.5 | Q54: 818093 | V54: 28 | W54: 83.7 | AD54: 0 | AE54: 155.8 | AF54: 0 | AH54: =YEAR(B54) -> 1992 | AI54: =MIN(52,INT((B54-DATE(AH54,1,1))/7)+1) -> 6 | AJ54: =IF(AND(ISNUMBER(C54),ISNUMBER(AK54),ISNUMBER(AL54),AH54>=Inputs!$B$5,AH54<=Inputs!$B$6,AH54<>Inputs!$B$7,AH54<>Inputs!$B$8),1,0) -> 0 | AK54: =IF(INDEX($E54:$AF54,Inputs!$C$10)="","",INDEX($E54:$AF54,Inputs!$C$10)) -> 169693 | AL54: =IF(INDEX($E54:$AF54,Inputs!$C$11)="","",INDEX($E54:$AF54,Inputs!$C$11)) -> 440000 | AM54: =Regression!$C$5+Regression!$C$6*A54 -> 10784.398 | AN54: =IF(AJ54=1,C54/AM54,"") | AO54: =INDEX('Seasonal Index'!$E$2:$E$53,AI54) -> 0.93990302 | AP54: =IF(AJ54=1,C54/AO54,"") | AQ54: =IF(AJ54=1,A54-Regression!$C$15,0) -> 0 | AR54: =IF(AJ54=1,AK54-Regression!$D$15,0) -> 0 | AS54: =IF(AJ54=1,AL54-Regression!$E$15,0) -> 0 | AT54: =IF(AJ54=1,AP54-Regression!$F$15,0) -> 0 | AU54: =IF(AND(ISNUMBER(AK54),ISNUMBER(AL54)),Regression!$C$38+Regression!$D$38*A54+Regression!$E$38*AK54+Regression!$F$38*AL54,"") -> 10626.071 | AV54: =IF(ISNUMBER(AU54),AU54*AO54,"") -> 9987.4766 | AW54: =IF(AJ54=1,"Train",IF(AH54=Inputs!$B$6+1,"Validation",IF(AH54>Inputs!$B$6+1,"Forecast","Not used"))) -> Not used | AX54: =IF(ISNUMBER(C54),C54,IF(ISNUMBER(D54),D54,"")) -> 7039 | AY54: =IF(AND(AW54="Validation",ISNUMBER(AX54),ISNUMBER(AV54)),ABS(AX54-AV54)/AX54,"") | AZ54: =IF(AJ54=1,AP54-AU54,0) -> 0 | BB54: =Regression!$C$45+Regression!$C$46*A54 -> 6226.933 | BC54: =IF(AND(AH54>=2022,AH54<=2024),C54/BB54,"") | BD54: =INDEX('Seasonal Index'!$H$2:$H$53,AI54) -> 0.95301266 | BE54: =IF(AH54>=2022,BB54*BD54,"") | BF54: =IF(AND(AW54="Validation",ISNUMBER(AX54),ISNUMBER(BE54)),ABS(AX54-BE54)/AX54,"") | BG54: =IF(ISNUMBER(C54),C54,0) -> 7039 | BH54: =IF(ISNUMBER(AY54),AV54-AX54,0) -> 0 | BI54: =IF(ISNUMBER(AY54),BE54-AX54,0) -> 0
A55: 54 | B55: 33648 | C55: 6576 | F55: 445000 | H55: 19.492 | I55: 18.584 | J55: 1.004 | K55: 6264.54 | M55: 796 | N55: 12.658 | O55: 169693 | P55: 4020.5 | Q55: 818093 | V55: 28 | W55: 83.7 | AD55: 0 | AE55: 170.1 | AF55: 0.5 | AH55: =YEAR(B55) -> 1992 | AI55: =MIN(52,INT((B55-DATE(AH55,1,1))/7)+1) -> 7 | AJ55: =IF(AND(ISNUMBER(C55),ISNUMBER(AK55),ISNUMBER(AL55),AH55>=Inputs!$B$5,AH55<=Inputs!$B$6,AH55<>Inputs!$B$7,AH55<>Inputs!$B$8),1,0) -> 0 | AK55: =IF(INDEX($E55:$AF55,Inputs!$C$10)="","",INDEX($E55:$AF55,Inputs!$C$10)) -> 169693 | AL55: =IF(INDEX($E55:$AF55,Inputs!$C$11)="","",INDEX($E55:$AF55,Inputs!$C$11)) -> 445000 | AM55: =Regression!$C$5+Regression!$C$6*A55 -> 10783.226 | AN55: =IF(AJ55=1,C55/AM55,"") | AO55: =INDEX('Seasonal Index'!$E$2:$E$53,AI55) -> 0.96316209 | AP55: =IF(AJ55=1,C55/AO55,"") | AQ55: =IF(AJ55=1,A55-Regression!$C$15,0) -> 0 | AR55: =IF(AJ55=1,AK55-Regression!$D$15,0) -> 0 | AS55: =IF(AJ55=1,AL55-Regression!$E$15,0) -> 0 | AT55: =IF(AJ55=1,AP55-Regression!$F$15,0) -> 0 | AU55: =IF(AND(ISNUMBER(AK55),ISNUMBER(AL55)),Regression!$C$38+Regression!$D$38*A55+Regression!$E$38*AK55+Regression!$F$38*AL55,"") -> 10611.234 | AV55: =IF(ISNUMBER(AU55),AU55*AO55,"") -> 10220.338 | AW55: =IF(AJ55=1,"Train",IF(AH55=Inputs!$B$6+1,"Validation",IF(AH55>Inputs!$B$6+1,"Forecast","Not used"))) -> Not used | AX55: =IF(ISNUMBER(C55),C55,IF(ISNUMBER(D55),D55,"")) -> 6576 | AY55: =IF(AND(AW55="Validation",ISNUMBER(AX55),ISNUMBER(AV55)),ABS(AX55-AV55)/AX55,"") | AZ55: =IF(AJ55=1,AP55-AU55,0) -> 0 | BB55: =Regression!$C$45+Regression!$C$46*A55 -> 6228.4925 | BC55: =IF(AND(AH55>=2022,AH55<=2024),C55/BB55,"") | BD55: =INDEX('Seasonal Index'!$H$2:$H$53,AI55) -> 0.98161871 | BE55: =IF(AH55>=2022,BB55*BD55,"") | BF55: =IF(AND(AW55="Validation",ISNUMBER(AX55),ISNUMBER(BE55)),ABS(AX55-BE55)/AX55,"") | BG55: =IF(ISNUMBER(C55),C55,0) -> 6576 | BH55: =IF(ISNUMBER(AY55),AV55-AX55,0) -> 0 | BI55: =IF(ISNUMBER(AY55),BE55-AX55,0) -> 0
A56: 55 | B56: 33655 | C56: 7002 | F56: 446000 | H56: 18.62 | I56: 17.74 | J56: 1.011 | K56: 6264.54 | M56: 796 | N56: 12.591 | O56: 172782 | P56: 4020.5 | Q56: 818093 | V56: 28 | W56: 83.7 | AD56: 0 | AE56: 125 | AF56: 0.7 | AH56: =YEAR(B56) -> 1992 | AI56: =MIN(52,INT((B56-DATE(AH56,1,1))/7)+1) -> 8 | AJ56: =IF(AND(ISNUMBER(C56),ISNUMBER(AK56),ISNUMBER(AL56),AH56>=Inputs!$B$5,AH56<=Inputs!$B$6,AH56<>Inputs!$B$7,AH56<>Inputs!$B$8),1,0) -> 0 | AK56: =IF(INDEX($E56:$AF56,Inputs!$C$10)="","",INDEX($E56:$AF56,Inputs!$C$10)) -> 172782 | AL56: =IF(INDEX($E56:$AF56,Inputs!$C$11)="","",INDEX($E56:$AF56,Inputs!$C$11)) -> 446000 | AM56: =Regression!$C$5+Regression!$C$6*A56 -> 10782.053 | AN56: =IF(AJ56=1,C56/AM56,"") | AO56: =INDEX('Seasonal Index'!$E$2:$E$53,AI56) -> 0.97838706 | AP56: =IF(AJ56=1,C56/AO56,"") | AQ56: =IF(AJ56=1,A56-Regression!$C$15,0) -> 0 | AR56: =IF(AJ56=1,AK56-Regression!$D$15,0) -> 0 | AS56: =IF(AJ56=1,AL56-Regression!$E$15,0) -> 0 | AT56: =IF(AJ56=1,AP56-Regression!$F$15,0) -> 0 | AU56: =IF(AND(ISNUMBER(AK56),ISNUMBER(AL56)),Regression!$C$38+Regression!$D$38*A56+Regression!$E$38*AK56+Regression!$F$38*AL56,"") -> 10612.653 | AV56: =IF(ISNUMBER(AU56),AU56*AO56,"") -> 10383.282 | AW56: =IF(AJ56=1,"Train",IF(AH56=Inputs!$B$6+1,"Validation",IF(AH56>Inputs!$B$6+1,"Forecast","Not used"))) -> Not used | AX56: =IF(ISNUMBER(C56),C56,IF(ISNUMBER(D56),D56,"")) -> 7002 | AY56: =IF(AND(AW56="Validation",ISNUMBER(AX56),ISNUMBER(AV56)),ABS(AX56-AV56)/AX56,"") | AZ56: =IF(AJ56=1,AP56-AU56,0) -> 0 | BB56: =Regression!$C$45+Regression!$C$46*A56 -> 6230.052 | BC56: =IF(AND(AH56>=2022,AH56<=2024),C56/BB56,"") | BD56: =INDEX('Seasonal Index'!$H$2:$H$53,AI56) -> 1.0025159 | BE56: =IF(AH56>=2022,BB56*BD56,"") | BF56: =IF(AND(AW56="Validation",ISNUMBER(AX56),ISNUMBER(BE56)),ABS(AX56-BE56)/AX56,"") | BG56: =IF(ISNUMBER(C56),C56,0) -> 7002 | BH56: =IF(ISNUMBER(AY56),AV56-AX56,0) -> 0 | BI56: =IF(ISNUMBER(AY56),BE56-AX56,0) -> 0
A57: 56 | B57: 33662 | C57: 6770 | F57: 436000 | H57: 18.514 | I57: 17.422 | J57: 1.014 | K57: 6264.54 | M57: 796 | N57: 12.591 | O57: 172782 | P57: 4020.5 | Q57: 818093 | V57: 28 | W57: 83.7 | AD57: 0 | AE57: 113.2 | AF57: 0 | AH57: =YEAR(B57) -> 1992 | AI57: =MIN(52,INT((B57-DATE(AH57,1,1))/7)+1) -> 9 | AJ57: =IF(AND(ISNUMBER(C57),ISNUMBER(AK57),ISNUMBER(AL57),AH57>=Inputs!$B$5,AH57<=Inputs!$B$6,AH57<>Inputs!$B$7,AH57<>Inputs!$B$8),1,0) -> 0 | AK57: =IF(INDEX($E57:$AF57,Inputs!$C$10)="","",INDEX($E57:$AF57,Inputs!$C$10)) -> 172782 | AL57: =IF(INDEX($E57:$AF57,Inputs!$C$11)="","",INDEX($E57:$AF57,Inputs!$C$11)) -> 436000 | AM57: =Regression!$C$5+Regression!$C$6*A57 -> 10780.88 | AN57: =IF(AJ57=1,C57/AM57,"") | AO57: =INDEX('Seasonal Index'!$E$2:$E$53,AI57) -> 0.98629368 | AP57: =IF(AJ57=1,C57/AO57,"") | AQ57: =IF(AJ57=1,A57-Regression!$C$15,0) -> 0 | AR57: =IF(AJ57=1,AK57-Regression!$D$15,0) -> 0 | AS57: =IF(AJ57=1,AL57-Regression!$E$15,0) -> 0 | AT57: =IF(AJ57=1,AP57-Regression!$F$15,0) -> 0 | AU57: =IF(AND(ISNUMBER(AK57),ISNUMBER(AL57)),Regression!$C$38+Regression!$D$38*A57+Regression!$E$38*AK57+Regression!$F$38*AL57,"") -> 10637.641 | AV57: =IF(ISNUMBER(AU57),AU57*AO57,"") -> 10491.838 | AW57: =IF(AJ57=1,"Train",IF(AH57=Inputs!$B$6+1,"Validation",IF(AH57>Inputs!$B$6+1,"Forecast","Not used"))) -> Not used | AX57: =IF(ISNUMBER(C57),C57,IF(ISNUMBER(D57),D57,"")) -> 6770 | AY57: =IF(AND(AW57="Validation",ISNUMBER(AX57),ISNUMBER(AV57)),ABS(AX57-AV57)/AX57,"") | AZ57: =IF(AJ57=1,AP57-AU57,0) -> 0 | BB57: =Regression!$C$45+Regression!$C$46*A57 -> 6231.6115 | BC57: =IF(AND(AH57>=2022,AH57<=2024),C57/BB57,"") | BD57: =INDEX('Seasonal Index'!$H$2:$H$53,AI57) -> 1.0104104 | BE57: =IF(AH57>=2022,BB57*BD57,"") | BF57: =IF(AND(AW57="Validation",ISNUMBER(AX57),ISNUMBER(BE57)),ABS(AX57-BE57)/AX57,"") | BG57: =IF(ISNUMBER(C57),C57,0) -> 6770 | BH57: =IF(ISNUMBER(AY57),AV57-AX57,0) -> 0 | BI57: =IF(ISNUMBER(AY57),BE57-AX57,0) -> 0
A58: 57 | B58: 33669 | C58: 7002 | F58: 444000 | H58: 18.552 | I58: 17.282 | J58: 1.012 | K58: 6264.54 | M58: 796 | N58: 12.591 | O58: 172782 | P58: 4020.5 | Q58: 818093 | V58: 28 | W58: 86.6 | AB58: 253530 | AD58: 0 | AE58: 104.3 | AF58: 1.5 | AH58: =YEAR(B58) -> 1992 | AI58: =MIN(52,INT((B58-DATE(AH58,1,1))/7)+1) -> 10 | AJ58: =IF(AND(ISNUMBER(C58),ISNUMBER(AK58),ISNUMBER(AL58),AH58>=Inputs!$B$5,AH58<=Inputs!$B$6,AH58<>Inputs!$B$7,AH58<>Inputs!$B$8),1,0) -> 0 | AK58: =IF(INDEX($E58:$AF58,Inputs!$C$10)="","",INDEX($E58:$AF58,Inputs!$C$10)) -> 172782 | AL58: =IF(INDEX($E58:$AF58,Inputs!$C$11)="","",INDEX($E58:$AF58,Inputs!$C$11)) -> 444000 | AM58: =Regression!$C$5+Regression!$C$6*A58 -> 10779.708 | AN58: =IF(AJ58=1,C58/AM58,"") | AO58: =INDEX('Seasonal Index'!$E$2:$E$53,AI58) -> 0.99527491 | AP58: =IF(AJ58=1,C58/AO58,"") | AQ58: =IF(AJ58=1,A58-Regression!$C$15,0) -> 0 | AR58: =IF(AJ58=1,AK58-Regression!$D$15,0) -> 0 | AS58: =IF(AJ58=1,AL58-Regression!$E$15,0) -> 0 | AT58: =IF(AJ58=1,AP58-Regression!$F$15,0) -> 0 | AU58: =IF(AND(ISNUMBER(AK58),ISNUMBER(AL58)),Regression!$C$38+Regression!$D$38*A58+Regression!$E$38*AK58+Regression!$F$38*AL58,"") -> 10614.838 | AV58: =IF(ISNUMBER(AU58),AU58*AO58,"") -> 10564.682 | AW58: =IF(AJ58=1,"Train",IF(AH58=Inputs!$B$6+1,"Validation",IF(AH58>Inputs!$B$6+1,"Forecast","Not used"))) -> Not used | AX58: =IF(ISNUMBER(C58),C58,IF(ISNUMBER(D58),D58,"")) -> 7002 | AY58: =IF(AND(AW58="Validation",ISNUMBER(AX58),ISNUMBER(AV58)),ABS(AX58-AV58)/AX58,"") | AZ58: =IF(AJ58=1,AP58-AU58,0) -> 0 | BB58: =Regression!$C$45+Regression!$C$46*A58 -> 6233.171 | BC58: =IF(AND(AH58>=2022,AH58<=2024),C58/BB58,"") | BD58: =INDEX('Seasonal Index'!$H$2:$H$53,AI58) -> 1.0119262 | BE58: =IF(AH58>=2022,BB58*BD58,"") | BF58: =IF(AND(AW58="Validation",ISNUMBER(AX58),ISNUMBER(BE58)),ABS(AX58-BE58)/AX58,"") | BG58: =IF(ISNUMBER(C58),C58,0) -> 7002 | BH58: =IF(ISNUMBER(AY58),AV58-AX58,0) -> 0 | BI58: =IF(ISNUMBER(AY58),BE58-AX58,0) -> 0
A59: 58 | B59: 33676 | C59: 6806 | F59: 421000 | H59: 18.758 | I59: 17.396 | J59: 1.013 | K59: 6264.54 | M59: 710 | N59: 12.591 | O59: 172782 | P59: 4084.7 | Q59: 818093 | V59: 28 | W59: 86.6 | AB59: 253530 | AD59: 0 | AE59: 123.5 | AF59: 2 | AH59: =YEAR(B59) -> 1992 | AI59: =MIN(52,INT((B59-DATE(AH59,1,1))/7)+1) -> 11 | AJ59: =IF(AND(ISNUMBER(C59),ISNUMBER(AK59),ISNUMBER(AL59),AH59>=Inputs!$B$5,AH59<=Inputs!$B$6,AH59<>Inputs!$B$7,AH59<>Inputs!$B$8),1,0) -> 0 | AK59: =IF(INDEX($E59:$AF59,Inputs!$C$10)="","",INDEX($E59:$AF59,Inputs!$C$10)) -> 172782 | AL59: =IF(INDEX($E59:$AF59,Inputs!$C$11)="","",INDEX($E59:$AF59,Inputs!$C$11)) -> 421000 | AM59: =Regression!$C$5+Regression!$C$6*A59 -> 10778.535 | AN59: =IF(AJ59=1,C59/AM59,"") | AO59: =INDEX('Seasonal Index'!$E$2:$E$53,AI59) -> 1.0021278 | AP59: =IF(AJ59=1,C59/AO59,"") | AQ59: =IF(AJ59=1,A59-Regression!$C$15,0) -> 0 | AR59: =IF(AJ59=1,AK59-Regression!$D$15,0) -> 0 | AS59: =IF(AJ59=1,AL59-Regression!$E$15,0) -> 0 | AT59: =IF(AJ59=1,AP59-Regression!$F$15,0) -> 0 | AU59: =IF(AND(ISNUMBER(AK59),ISNUMBER(AL59)),Regression!$C$38+Regression!$D$38*A59+Regression!$E$38*AK59+Regression!$F$38*AL59,"") -> 10674.342 | AV59: =IF(ISNUMBER(AU59),AU59*AO59,"") -> 10697.054 | AW59: =IF(AJ59=1,"Train",IF(AH59=Inputs!$B$6+1,"Validation",IF(AH59>Inputs!$B$6+1,"Forecast","Not used"))) -> Not used | AX59: =IF(ISNUMBER(C59),C59,IF(ISNUMBER(D59),D59,"")) -> 6806 | AY59: =IF(AND(AW59="Validation",ISNUMBER(AX59),ISNUMBER(AV59)),ABS(AX59-AV59)/AX59,"") | AZ59: =IF(AJ59=1,AP59-AU59,0) -> 0 | BB59: =Regression!$C$45+Regression!$C$46*A59 -> 6234.7305 | BC59: =IF(AND(AH59>=2022,AH59<=2024),C59/BB59,"") | BD59: =INDEX('Seasonal Index'!$H$2:$H$53,AI59) -> 1.0050202 | BE59: =IF(AH59>=2022,BB59*BD59,"") | BF59: =IF(AND(AW59="Validation",ISNUMBER(AX59),ISNUMBER(BE59)),ABS(AX59-BE59)/AX59,"") | BG59: =IF(ISNUMBER(C59),C59,0) -> 6806 | BH59: =IF(ISNUMBER(AY59),AV59-AX59,0) -> 0 | BI59: =IF(ISNUMBER(AY59),BE59-AX59,0) -> 0
A60: 59 | B60: 33683 | C60: 7221 | F60: 437000 | H60: 19.104 | I60: 17.732 | J60: 1.01 | K60: 6264.54 | M60: 710 | N60: 12.927 | O60: 167652 | P60: 4084.7 | Q60: 815581 | V60: 28 | W60: 86.6 | AB60: 253530 | AD60: 0 | AE60: 138.5 | AF60: 1.6 | AH60: =YEAR(B60) -> 1992 | AI60: =MIN(52,INT((B60-DATE(AH60,1,1))/7)+1) -> 12 | AJ60: =IF(AND(ISNUMBER(C60),ISNUMBER(AK60),ISNUMBER(AL60),AH60>=Inputs!$B$5,AH60<=Inputs!$B$6,AH60<>Inputs!$B$7,AH60<>Inputs!$B$8),1,0) -> 0 | AK60: =IF(INDEX($E60:$AF60,Inputs!$C$10)="","",INDEX($E60:$AF60,Inputs!$C$10)) -> 167652 | AL60: =IF(INDEX($E60:$AF60,Inputs!$C$11)="","",INDEX($E60:$AF60,Inputs!$C$11)) -> 437000 | AM60: =Regression!$C$5+Regression!$C$6*A60 -> 10777.362 | AN60: =IF(AJ60=1,C60/AM60,"") | AO60: =INDEX('Seasonal Index'!$E$2:$E$53,AI60) -> 0.99255102 | AP60: =IF(AJ60=1,C60/AO60,"") | AQ60: =IF(AJ60=1,A60-Regression!$C$15,0) -> 0 | AR60: =IF(AJ60=1,AK60-Regression!$D$15,0) -> 0 | AS60: =IF(AJ60=1,AL60-Regression!$E$15,0) -> 0 | AT60: =IF(AJ60=1,AP60-Regression!$F$15,0) -> 0 | AU60: =IF(AND(ISNUMBER(AK60),ISNUMBER(AL60)),Regression!$C$38+Regression!$D$38*A60+Regression!$E$38*AK60+Regression!$F$38*AL60,"") -> 10620.938 | AV60: =IF(ISNUMBER(AU60),AU60*AO60,"") -> 10541.823 | AW60: =IF(AJ60=1,"Train",IF(AH60=Inputs!$B$6+1,"Validation",IF(AH60>Inputs!$B$6+1,"Forecast","Not used"))) -> Not used | AX60: =IF(ISNUMBER(C60),C60,IF(ISNUMBER(D60),D60,"")) -> 7221 | AY60: =IF(AND(AW60="Validation",ISNUMBER(AX60),ISNUMBER(AV60)),ABS(AX60-AV60)/AX60,"") | AZ60: =IF(AJ60=1,AP60-AU60,0) -> 0 | BB60: =Regression!$C$45+Regression!$C$46*A60 -> 6236.29 | BC60: =IF(AND(AH60>=2022,AH60<=2024),C60/BB60,"") | BD60: =INDEX('Seasonal Index'!$H$2:$H$53,AI60) -> 1.0030365 | BE60: =IF(AH60>=2022,BB60*BD60,"") | BF60: =IF(AND(AW60="Validation",ISNUMBER(AX60),ISNUMBER(BE60)),ABS(AX60-BE60)/AX60,"") | BG60: =IF(ISNUMBER(C60),C60,0) -> 7221 | BH60: =IF(ISNUMBER(AY60),AV60-AX60,0) -> 0 | BI60: =IF(ISNUMBER(AY60),BE60-AX60,0) -> 0
A61: 60 | B61: 33690 | C61: 7379 | F61: 440000 | H61: 19.094 | I61: 17.752 | J61: 1.015 | K61: 6264.54 | M61: 710 | N61: 12.927 | O61: 167652 | P61: 4084.7 | Q61: 815581 | V61: 28 | W61: 86.6 | AB61: 253530 | AD61: 0 | AE61: 133.6 | AF61: 0.6 | AH61: =YEAR(B61) -> 1992 | AI61: =MIN(52,INT((B61-DATE(AH61,1,1))/7)+1) -> 13 | AJ61: =IF(AND(ISNUMBER(C61),ISNUMBER(AK61),ISNUMBER(AL61),AH61>=Inputs!$B$5,AH61<=Inputs!$B$6,AH61<>Inputs!$B$7,AH61<>Inputs!$B$8),1,0) -> 0 | AK61: =IF(INDEX($E61:$AF61,Inputs!$C$10)="","",INDEX($E61:$AF61,Inputs!$C$10)) -> 167652 | AL61: =IF(INDEX($E61:$AF61,Inputs!$C$11)="","",INDEX($E61:$AF61,Inputs!$C$11)) -> 440000 | AM61: =Regression!$C$5+Regression!$C$6*A61 -> 10776.19 | AN61: =IF(AJ61=1,C61/AM61,"") | AO61: =INDEX('Seasonal Index'!$E$2:$E$53,AI61) -> 1.0067199 | AP61: =IF(AJ61=1,C61/AO61,"") | AQ61: =IF(AJ61=1,A61-Regression!$C$15,0) -> 0 | AR61: =IF(AJ61=1,AK61-Regression!$D$15,0) -> 0 | AS61: =IF(AJ61=1,AL61-Regression!$E$15,0) -> 0 | AT61: =IF(AJ61=1,AP61-Regression!$F$15,0) -> 0 | AU61: =IF(AND(ISNUMBER(AK61),ISNUMBER(AL61)),Regression!$C$38+Regression!$D$38*A61+Regression!$E$38*AK61+Regression!$F$38*AL61,"") -> 10611.411 | AV61: =IF(ISNUMBER(AU61),AU61*AO61,"") -> 10682.719 | AW61: =IF(AJ61=1,"Train",IF(AH61=Inputs!$B$6+1,"Validation",IF(AH61>Inputs!$B$6+1,"Forecast","Not used"))) -> Not used | AX61: =IF(ISNUMBER(C61),C61,IF(ISNUMBER(D61),D61,"")) -> 7379 | AY61: =IF(AND(AW61="Validation",ISNUMBER(AX61),ISNUMBER(AV61)),ABS(AX61-AV61)/AX61,"") | AZ61: =IF(AJ61=1,AP61-AU61,0) -> 0 | BB61: =Regression!$C$45+Regression!$C$46*A61 -> 6237.8495 | BC61: =IF(AND(AH61>=2022,AH61<=2024),C61/BB61,"") | BD61: =INDEX('Seasonal Index'!$H$2:$H$53,AI61) -> 1.0306249 | BE61: =IF(AH61>=2022,BB61*BD61,"") | BF61: =IF(AND(AW61="Validation",ISNUMBER(AX61),ISNUMBER(BE61)),ABS(AX61-BE61)/AX61,"") | BG61: =IF(ISNUMBER(C61),C61,0) -> 7379 | BH61: =IF(ISNUMBER(AY61),AV61-AX61,0) -> 0 | BI61: =IF(ISNUMBER(AY61),BE61-AX61,0) -> 0
A62: 61 | B62: 33697 | C62: 7027 | F62: 420000 | H62: 19.726 | I62: 18.522 | J62: 1.013 | K62: 6264.54 | M62: 710 | N62: 12.927 | O62: 167652 | P62: 4084.7 | Q62: 815581 | V62: 28 | W62: 86.6 | AB62: 253530 | AD62: 0 | AE62: 117 | AF62: 0.7 | AH62: =YEAR(B62) -> 1992 | AI62: =MIN(52,INT((B62-DATE(AH62,1,1))/7)+1) -> 14 | AJ62: =IF(AND(ISNUMBER(C62),ISNUMBER(AK62),ISNUMBER(AL62),AH62>=Inputs!$B$5,AH62<=Inputs!$B$6,AH62<>Inputs!$B$7,AH62<>Inputs!$B$8),1,0) -> 0 | AK62: =IF(INDEX($E62:$AF62,Inputs!$C$10)="","",INDEX($E62:$AF62,Inputs!$C$10)) -> 167652 | AL62: =IF(INDEX($E62:$AF62,Inputs!$C$11)="","",INDEX($E62:$AF62,Inputs!$C$11)) -> 420000 | AM62: =Regression!$C$5+Regression!$C$6*A62 -> 10775.017 | AN62: =IF(AJ62=1,C62/AM62,"") | AO62: =INDEX('Seasonal Index'!$E$2:$E$53,AI62) -> 0.99471307 | AP62: =IF(AJ62=1,C62/AO62,"") | AQ62: =IF(AJ62=1,A62-Regression!$C$15,0) -> 0 | AR62: =IF(AJ62=1,AK62-Regression!$D$15,0) -> 0 | AS62: =IF(AJ62=1,AL62-Regression!$E$15,0) -> 0 | AT62: =IF(AJ62=1,AP62-Regression!$F$15,0) -> 0 | AU62: =IF(AND(ISNUMBER(AK62),ISNUMBER(AL62)),Regression!$C$38+Regression!$D$38*A62+Regression!$E$38*AK62+Regression!$F$38*AL62,"") -> 10662.95 | AV62: =IF(ISNUMBER(AU62),AU62*AO62,"") -> 10606.575 | AW62: =IF(AJ62=1,"Train",IF(AH62=Inputs!$B$6+1,"Validation",IF(AH62>Inputs!$B$6+1,"Forecast","Not used"))) -> Not used | AX62: =IF(ISNUMBER(C62),C62,IF(ISNUMBER(D62),D62,"")) -> 7027 | AY62: =IF(AND(AW62="Validation",ISNUMBER(AX62),ISNUMBER(AV62)),ABS(AX62-AV62)/AX62,"") | AZ62: =IF(AJ62=1,AP62-AU62,0) -> 0 | BB62: =Regression!$C$45+Regression!$C$46*A62 -> 6239.409 | BC62: =IF(AND(AH62>=2022,AH62<=2024),C62/BB62,"") | BD62: =INDEX('Seasonal Index'!$H$2:$H$53,AI62) -> 0.99994657 | BE62: =IF(AH62>=2022,BB62*BD62,"") | BF62: =IF(AND(AW62="Validation",ISNUMBER(AX62),ISNUMBER(BE62)),ABS(AX62-BE62)/AX62,"") | BG62: =IF(ISNUMBER(C62),C62,0) -> 7027 | BH62: =IF(ISNUMBER(AY62),AV62-AX62,0) -> 0 | BI62: =IF(ISNUMBER(AY62),BE62-AX62,0) -> 0
A63: 62 | B63: 33704 | C63: 7744 | F63: 412000 | H63: 20.43 | I63: 19.008 | J63: 1.026 | K63: 6264.54 | M63: 669 | N63: 12.927 | O63: 167652 | P63: 4099.5 | Q63: 815581 | V63: 28 | W63: 83.4 | AB63: 253530 | AD63: 0 | AE63: 84.7 | AF63: 1.9 | AH63: =YEAR(B63) -> 1992 | AI63: =MIN(52,INT((B63-DATE(AH63,1,1))/7)+1) -> 15 | AJ63: =IF(AND(ISNUMBER(C63),ISNUMBER(AK63),ISNUMBER(AL63),AH63>=Inputs!$B$5,AH63<=Inputs!$B$6,AH63<>Inputs!$B$7,AH63<>Inputs!$B$8),1,0) -> 0 | AK63: =IF(INDEX($E63:$AF63,Inputs!$C$10)="","",INDEX($E63:$AF63,Inputs!$C$10)) -> 167652 | AL63: =IF(INDEX($E63:$AF63,Inputs!$C$11)="","",INDEX($E63:$AF63,Inputs!$C$11)) -> 412000 | AM63: =Regression!$C$5+Regression!$C$6*A63 -> 10773.844 | AN63: =IF(AJ63=1,C63/AM63,"") | AO63: =INDEX('Seasonal Index'!$E$2:$E$53,AI63) -> 1.0030309 | AP63: =IF(AJ63=1,C63/AO63,"") | AQ63: =IF(AJ63=1,A63-Regression!$C$15,0) -> 0 | AR63: =IF(AJ63=1,AK63-Regression!$D$15,0) -> 0 | AS63: =IF(AJ63=1,AL63-Regression!$E$15,0) -> 0 | AT63: =IF(AJ63=1,AP63-Regression!$F$15,0) -> 0 | AU63: =IF(AND(ISNUMBER(AK63),ISNUMBER(AL63)),Regression!$C$38+Regression!$D$38*A63+Regression!$E$38*AK63+Regression!$F$38*AL63,"") -> 10682.628 | AV63: =IF(ISNUMBER(AU63),AU63*AO63,"") -> 10715.006 | AW63: =IF(AJ63=1,"Train",IF(AH63=Inputs!$B$6+1,"Validation",IF(AH63>Inputs!$B$6+1,"Forecast","Not used"))) -> Not used | AX63: =IF(ISNUMBER(C63),C63,IF(ISNUMBER(D63),D63,"")) -> 7744 | AY63: =IF(AND(AW63="Validation",ISNUMBER(AX63),ISNUMBER(AV63)),ABS(AX63-AV63)/AX63,"") | AZ63: =IF(AJ63=1,AP63-AU63,0) -> 0 | BB63: =Regression!$C$45+Regression!$C$46*A63 -> 6240.9685 | BC63: =IF(AND(AH63>=2022,AH63<=2024),C63/BB63,"") | BD63: =INDEX('Seasonal Index'!$H$2:$H$53,AI63) -> 0.99086023 | BE63: =IF(AH63>=2022,BB63*BD63,"") | BF63: =IF(AND(AW63="Validation",ISNUMBER(AX63),ISNUMBER(BE63)),ABS(AX63-BE63)/AX63,"") | BG63: =IF(ISNUMBER(C63),C63,0) -> 7744 | BH63: =IF(ISNUMBER(AY63),AV63-AX63,0) -> 0 | BI63: =IF(ISNUMBER(AY63),BE63-AX63,0) -> 0
A64: 63 | B64: 33711 | C64: 6464 | F64: 413000 | H64: 20.0575 | I64: 18.8575 | J64: 1.051 | K64: 6264.54 | M64: 669 | N64: 12.824 | O64: 160204 | P64: 4099.5 | Q64: 815581 | V64: 28 | W64: 83.4 | AB64: 253530 | AD64: 0 | AE64: 70.2 | AF64: 10.5 | AH64: =YEAR(B64) -> 1992 | AI64: =MIN(52,INT((B64-DATE(AH64,1,1))/7)+1) -> 16 | AJ64: =IF(AND(ISNUMBER(C64),ISNUMBER(AK64),ISNUMBER(AL64),AH64>=Inputs!$B$5,AH64<=Inputs!$B$6,AH64<>Inputs!$B$7,AH64<>Inputs!$B$8),1,0) -> 0 | AK64: =IF(INDEX($E64:$AF64,Inputs!$C$10)="","",INDEX($E64:$AF64,Inputs!$C$10)) -> 160204 | AL64: =IF(INDEX($E64:$AF64,Inputs!$C$11)="","",INDEX($E64:$AF64,Inputs!$C$11)) -> 413000 | AM64: =Regression!$C$5+Regression!$C$6*A64 -> 10772.671 | AN64: =IF(AJ64=1,C64/AM64,"") | AO64: =INDEX('Seasonal Index'!$E$2:$E$53,AI64) -> 1.0020974 | AP64: =IF(AJ64=1,C64/AO64,"") | AQ64: =IF(AJ64=1,A64-Regression!$C$15,0) -> 0 | AR64: =IF(AJ64=1,AK64-Regression!$D$15,0) -> 0 | AS64: =IF(AJ64=1,AL64-Regression!$E$15,0) -> 0 | AT64: =IF(AJ64=1,AP64-Regression!$F$15,0) -> 0 | AU64: =IF(AND(ISNUMBER(AK64),ISNUMBER(AL64)),Regression!$C$38+Regression!$D$38*A64+Regression!$E$38*AK64+Regression!$F$38*AL64,"") -> 10664.82 | AV64: =IF(ISNUMBER(AU64),AU64*AO64,"") -> 10687.189 | AW64: =IF(AJ64=1,"Train",IF(AH64=Inputs!$B$6+1,"Validation",IF(AH64>Inputs!$B$6+1,"Forecast","Not used"))) -> Not used | AX64: =IF(ISNUMBER(C64),C64,IF(ISNUMBER(D64),D64,"")) -> 6464 | AY64: =IF(AND(AW64="Validation",ISNUMBER(AX64),ISNUMBER(AV64)),ABS(AX64-AV64)/AX64,"") | AZ64: =IF(AJ64=1,AP64-AU64,0) -> 0 | BB64: =Regression!$C$45+Regression!$C$46*A64 -> 6242.528 | BC64: =IF(AND(AH64>=2022,AH64<=2024),C64/BB64,"") | BD64: =INDEX('Seasonal Index'!$H$2:$H$53,AI64) -> 1.01445 | BE64: =IF(AH64>=2022,BB64*BD64,"") | BF64: =IF(AND(AW64="Validation",ISNUMBER(AX64),ISNUMBER(BE64)),ABS(AX64-BE64)/AX64,"") | BG64: =IF(ISNUMBER(C64),C64,0) -> 6464 | BH64: =IF(ISNUMBER(AY64),AV64-AX64,0) -> 0 | BI64: =IF(ISNUMBER(AY64),BE64-AX64,0) -> 0
A65: 64 | B65: 33718 | C65: 7376 | F65: 424000 | H65: 20.062 | I65: 18.856 | J65: 1.058 | K65: 6264.54 | M65: 669 | N65: 12.824 | O65: 160204 | P65: 4099.5 | Q65: 815581 | V65: 28 | W65: 83.4 | AB65: 253530 | AD65: 0 | AE65: 39.7 | AF65: 14.2 | AH65: =YEAR(B65) -> 1992 | AI65: =MIN(52,INT((B65-DATE(AH65,1,1))/7)+1) -> 17 | AJ65: =IF(AND(ISNUMBER(C65),ISNUMBER(AK65),ISNUMBER(AL65),AH65>=Inputs!$B$5,AH65<=Inputs!$B$6,AH65<>Inputs!$B$7,AH65<>Inputs!$B$8),1,0) -> 0 | AK65: =IF(INDEX($E65:$AF65,Inputs!$C$10)="","",INDEX($E65:$AF65,Inputs!$C$10)) -> 160204 | AL65: =IF(INDEX($E65:$AF65,Inputs!$C$11)="","",INDEX($E65:$AF65,Inputs!$C$11)) -> 424000 | AM65: =Regression!$C$5+Regression!$C$6*A65 -> 10771.499 | AN65: =IF(AJ65=1,C65/AM65,"") | AO65: =INDEX('Seasonal Index'!$E$2:$E$53,AI65) -> 0.98572001 | AP65: =IF(AJ65=1,C65/AO65,"") | AQ65: =IF(AJ65=1,A65-Regression!$C$15,0) -> 0 | AR65: =IF(AJ65=1,AK65-Regression!$D$15,0) -> 0 | AS65: =IF(AJ65=1,AL65-Regression!$E$15,0) -> 0 | AT65: =IF(AJ65=1,AP65-Regression!$F$15,0) -> 0 | AU65: =IF(AND(ISNUMBER(AK65),ISNUMBER(AL65)),Regression!$C$38+Regression!$D$38*A65+Regression!$E$38*AK65+Regression!$F$38*AL65,"") -> 10634.052 | AV65: =IF(ISNUMBER(AU65),AU65*AO65,"") -> 10482.198 | AW65: =IF(AJ65=1,"Train",IF(AH65=Inputs!$B$6+1,"Validation",IF(AH65>Inputs!$B$6+1,"Forecast","Not used"))) -> Not used | AX65: =IF(ISNUMBER(C65),C65,IF(ISNUMBER(D65),D65,"")) -> 7376 | AY65: =IF(AND(AW65="Validation",ISNUMBER(AX65),ISNUMBER(AV65)),ABS(AX65-AV65)/AX65,"") | AZ65: =IF(AJ65=1,AP65-AU65,0) -> 0 | BB65: =Regression!$C$45+Regression!$C$46*A65 -> 6244.0875 | BC65: =IF(AND(AH65>=2022,AH65<=2024),C65/BB65,"") | BD65: =INDEX('Seasonal Index'!$H$2:$H$53,AI65) -> 0.99215359 | BE65: =IF(AH65>=2022,BB65*BD65,"") | BF65: =IF(AND(AW65="Validation",ISNUMBER(AX65),ISNUMBER(BE65)),ABS(AX65-BE65)/AX65,"") | BG65: =IF(ISNUMBER(C65),C65,0) -> 7376 | BH65: =IF(ISNUMBER(AY65),AV65-AX65,0) -> 0 | BI65: =IF(ISNUMBER(AY65),BE65-AX65,0) -> 0
A66: 65 | B66: 33725 | C66: 7899 | F66: 424000 | H66: 20.626 | I66: 19.368 | J66: 1.072 | K66: 6264.54 | M66: 669 | N66: 12.824 | O66: 160204 | P66: 4099.5 | Q66: 815581 | V66: 28 | W66: 83.4 | AB66: 253530 | AD66: 0 | AE66: 63.2 | AF66: 15.2 | AH66: =YEAR(B66) -> 1992 | AI66: =MIN(52,INT((B66-DATE(AH66,1,1))/7)+1) -> 18 | AJ66: =IF(AND(ISNUMBER(C66),ISNUMBER(AK66),ISNUMBER(AL66),AH66>=Inputs!$B$5,AH66<=Inputs!$B$6,AH66<>Inputs!$B$7,AH66<>Inputs!$B$8),1,0) -> 0 | AK66: =IF(INDEX($E66:$AF66,Inputs!$C$10)="","",INDEX($E66:$AF66,Inputs!$C$10)) -> 160204 | AL66: =IF(INDEX($E66:$AF66,Inputs!$C$11)="","",INDEX($E66:$AF66,Inputs!$C$11)) -> 424000 | AM66: =Regression!$C$5+Regression!$C$6*A66 -> 10770.326 | AN66: =IF(AJ66=1,C66/AM66,"") | AO66: =INDEX('Seasonal Index'!$E$2:$E$53,AI66) -> 1.0181402 | AP66: =IF(AJ66=1,C66/AO66,"") | AQ66: =IF(AJ66=1,A66-Regression!$C$15,0) -> 0 | AR66: =IF(AJ66=1,AK66-Regression!$D$15,0) -> 0 | AS66: =IF(AJ66=1,AL66-Regression!$E$15,0) -> 0 | AT66: =IF(AJ66=1,AP66-Regression!$F$15,0) -> 0 | AU66: =IF(AND(ISNUMBER(AK66),ISNUMBER(AL66)),Regression!$C$38+Regression!$D$38*A66+Regression!$E$38*AK66+Regression!$F$38*AL66,"") -> 10632.49 | AV66: =IF(ISNUMBER(AU66),AU66*AO66,"") -> 10825.365 | AW66: =IF(AJ66=1,"Train",IF(AH66=Inputs!$B$6+1,"Validation",IF(AH66>Inputs!$B$6+1,"Forecast","Not used"))) -> Not used | AX66: =IF(ISNUMBER(C66),C66,IF(ISNUMBER(D66),D66,"")) -> 7899 | AY66: =IF(AND(AW66="Validation",ISNUMBER(AX66),ISNUMBER(AV66)),ABS(AX66-AV66)/AX66,"") | AZ66: =IF(AJ66=1,AP66-AU66,0) -> 0 | BB66: =Regression!$C$45+Regression!$C$46*A66 -> 6245.647 | BC66: =IF(AND(AH66>=2022,AH66<=2024),C66/BB66,"") | BD66: =INDEX('Seasonal Index'!$H$2:$H$53,AI66) -> 1.0188494 | BE66: =IF(AH66>=2022,BB66*BD66,"") | BF66: =IF(AND(AW66="Validation",ISNUMBER(AX66),ISNUMBER(BE66)),ABS(AX66-BE66)/AX66,"") | BG66: =IF(ISNUMBER(C66),C66,0) -> 7899 | BH66: =IF(ISNUMBER(AY66),AV66-AX66,0) -> 0 | BI66: =IF(ISNUMBER(AY66),BE66-AX66,0) -> 0
A67: 66 | B67: 33732 | C67: 7318 | F67: 431000 | H67: 20.856 | I67: 19.764 | J67: 1.089 | K67: 6363.102 | M67: 648 | N67: 12.824 | O67: 160204 | P67: 4117 | Q67: 815581 | V67: 28 | W67: 81.3 | AB67: 253530 | AD67: 0 | AE67: 48.6 | AF67: 12.5 | AH67: =YEAR(B67) -> 1992 | AI67: =MIN(52,INT((B67-DATE(AH67,1,1))/7)+1) -> 19 | AJ67: =IF(AND(ISNUMBER(C67),ISNUMBER(AK67),ISNUMBER(AL67),AH67>=Inputs!$B$5,AH67<=Inputs!$B$6,AH67<>Inputs!$B$7,AH67<>Inputs!$B$8),1,0) -> 0 | AK67: =IF(INDEX($E67:$AF67,Inputs!$C$10)="","",INDEX($E67:$AF67,Inputs!$C$10)) -> 160204 | AL67: =IF(INDEX($E67:$AF67,Inputs!$C$11)="","",INDEX($E67:$AF67,Inputs!$C$11)) -> 431000 | AM67: =Regression!$C$5+Regression!$C$6*A67 -> 10769.153 | AN67: =IF(AJ67=1,C67/AM67,"") | AO67: =INDEX('Seasonal Index'!$E$2:$E$53,AI67) -> 1.0133712 | AP67: =IF(AJ67=1,C67/AO67,"") | AQ67: =IF(AJ67=1,A67-Regression!$C$15,0) -> 0 | AR67: =IF(AJ67=1,AK67-Regression!$D$15,0) -> 0 | AS67: =IF(AJ67=1,AL67-Regression!$E$15,0) -> 0 | AT67: =IF(AJ67=1,AP67-Regression!$F$15,0) -> 0 | AU67: =IF(AND(ISNUMBER(AK67),ISNUMBER(AL67)),Regression!$C$38+Regression!$D$38*A67+Regression!$E$38*AK67+Regression!$F$38*AL67,"") -> 10612.342 | AV67: =IF(ISNUMBER(AU67),AU67*AO67,"") -> 10754.243 | AW67: =IF(AJ67=1,"Train",IF(AH67=Inputs!$B$6+1,"Validation",IF(AH67>Inputs!$B$6+1,"Forecast","Not used"))) -> Not used | AX67: =IF(ISNUMBER(C67),C67,IF(ISNUMBER(D67),D67,"")) -> 7318 | AY67: =IF(AND(AW67="Validation",ISNUMBER(AX67),ISNUMBER(AV67)),ABS(AX67-AV67)/AX67,"") | AZ67: =IF(AJ67=1,AP67-AU67,0) -> 0 | BB67: =Regression!$C$45+Regression!$C$46*A67 -> 6247.2065 | BC67: =IF(AND(AH67>=2022,AH67<=2024),C67/BB67,"") | BD67: =INDEX('Seasonal Index'!$H$2:$H$53,AI67) -> 1.0190604 | BE67: =IF(AH67>=2022,BB67*BD67,"") | BF67: =IF(AND(AW67="Validation",ISNUMBER(AX67),ISNUMBER(BE67)),ABS(AX67-BE67)/AX67,"") | BG67: =IF(ISNUMBER(C67),C67,0) -> 7318 | BH67: =IF(ISNUMBER(AY67),AV67-AX67,0) -> 0 | BI67: =IF(ISNUMBER(AY67),BE67-AX67,0) -> 0
A68: 67 | B68: 33739 | C68: 7174 | F68: 417000 | H68: 20.802 | I68: 19.786 | J68: 1.102 | K68: 6363.102 | M68: 648 | N68: 12.824 | O68: 160204 | P68: 4117 | Q68: 815581 | V68: 28 | W68: 81.3 | AB68: 253530 | AD68: 0 | AE68: 19.8 | AF68: 20.3 | AH68: =YEAR(B68) -> 1992 | AI68: =MIN(52,INT((B68-DATE(AH68,1,1))/7)+1) -> 20 | AJ68: =IF(AND(ISNUMBER(C68),ISNUMBER(AK68),ISNUMBER(AL68),AH68>=Inputs!$B$5,AH68<=Inputs!$B$6,AH68<>Inputs!$B$7,AH68<>Inputs!$B$8),1,0) -> 0 | AK68: =IF(INDEX($E68:$AF68,Inputs!$C$10)="","",INDEX($E68:$AF68,Inputs!$C$10)) -> 160204 | AL68: =IF(INDEX($E68:$AF68,Inputs!$C$11)="","",INDEX($E68:$AF68,Inputs!$C$11)) -> 417000 | AM68: =Regression!$C$5+Regression!$C$6*A68 -> 10767.981 | AN68: =IF(AJ68=1,C68/AM68,"") | AO68: =INDEX('Seasonal Index'!$E$2:$E$53,AI68) -> 1.0355119 | AP68: =IF(AJ68=1,C68/AO68,"") | AQ68: =IF(AJ68=1,A68-Regression!$C$15,0) -> 0 | AR68: =IF(AJ68=1,AK68-Regression!$D$15,0) -> 0 | AS68: =IF(AJ68=1,AL68-Regression!$E$15,0) -> 0 | AT68: =IF(AJ68=1,AP68-Regression!$F$15,0) -> 0 | AU68: =IF(AND(ISNUMBER(AK68),ISNUMBER(AL68)),Regression!$C$38+Regression!$D$38*A68+Regression!$E$38*AK68+Regression!$F$38*AL68,"") -> 10647.951 | AV68: =IF(ISNUMBER(AU68),AU68*AO68,"") -> 11026.08 | AW68: =IF(AJ68=1,"Train",IF(AH68=Inputs!$B$6+1,"Validation",IF(AH68>Inputs!$B$6+1,"Forecast","Not used"))) -> Not used | AX68: =IF(ISNUMBER(C68),C68,IF(ISNUMBER(D68),D68,"")) -> 7174 | AY68: =IF(AND(AW68="Validation",ISNUMBER(AX68),ISNUMBER(AV68)),ABS(AX68-AV68)/AX68,"") | AZ68: =IF(AJ68=1,AP68-AU68,0) -> 0 | BB68: =Regression!$C$45+Regression!$C$46*A68 -> 6248.766 | BC68: =IF(AND(AH68>=2022,AH68<=2024),C68/BB68,"") | BD68: =INDEX('Seasonal Index'!$H$2:$H$53,AI68) -> 1.0467645 | BE68: =IF(AH68>=2022,BB68*BD68,"") | BF68: =IF(AND(AW68="Validation",ISNUMBER(AX68),ISNUMBER(BE68)),ABS(AX68-BE68)/AX68,"") | BG68: =IF(ISNUMBER(C68),C68,0) -> 7174 | BH68: =IF(ISNUMBER(AY68),AV68-AX68,0) -> 0 | BI68: =IF(ISNUMBER(AY68),BE68-AX68,0) -> 0
A69: 68 | B69: 33746 | C69: 7086 | F69: 414000 | H69: 20.488 | I69: 19.492 | J69: 1.118 | K69: 6363.102 | M69: 648 | N69: 12.55 | O69: 183778 | P69: 4117 | Q69: 815581 | V69: 28 | W69: 81.3 | AB69: 253530 | AD69: 0 | AE69: 12.3 | AF69: 29.5 | AH69: =YEAR(B69) -> 1992 | AI69: =MIN(52,INT((B69-DATE(AH69,1,1))/7)+1) -> 21 | AJ69: =IF(AND(ISNUMBER(C69),ISNUMBER(AK69),ISNUMBER(AL69),AH69>=Inputs!$B$5,AH69<=Inputs!$B$6,AH69<>Inputs!$B$7,AH69<>Inputs!$B$8),1,0) -> 0 | AK69: =IF(INDEX($E69:$AF69,Inputs!$C$10)="","",INDEX($E69:$AF69,Inputs!$C$10)) -> 183778 | AL69: =IF(INDEX($E69:$AF69,Inputs!$C$11)="","",INDEX($E69:$AF69,Inputs!$C$11)) -> 414000 | AM69: =Regression!$C$5+Regression!$C$6*A69 -> 10766.808 | AN69: =IF(AJ69=1,C69/AM69,"") | AO69: =INDEX('Seasonal Index'!$E$2:$E$53,AI69) -> 1.0352246 | AP69: =IF(AJ69=1,C69/AO69,"") | AQ69: =IF(AJ69=1,A69-Regression!$C$15,0) -> 0 | AR69: =IF(AJ69=1,AK69-Regression!$D$15,0) -> 0 | AS69: =IF(AJ69=1,AL69-Regression!$E$15,0) -> 0 | AT69: =IF(AJ69=1,AP69-Regression!$F$15,0) -> 0 | AU69: =IF(AND(ISNUMBER(AK69),ISNUMBER(AL69)),Regression!$C$38+Regression!$D$38*A69+Regression!$E$38*AK69+Regression!$F$38*AL69,"") -> 10697.368 | AV69: =IF(ISNUMBER(AU69),AU69*AO69,"") -> 11074.179 | AW69: =IF(AJ69=1,"Train",IF(AH69=Inputs!$B$6+1,"Validation",IF(AH69>Inputs!$B$6+1,"Forecast","Not used"))) -> Not used | AX69: =IF(ISNUMBER(C69),C69,IF(ISNUMBER(D69),D69,"")) -> 7086 | AY69: =IF(AND(AW69="Validation",ISNUMBER(AX69),ISNUMBER(AV69)),ABS(AX69-AV69)/AX69,"") | AZ69: =IF(AJ69=1,AP69-AU69,0) -> 0 | BB69: =Regression!$C$45+Regression!$C$46*A69 -> 6250.3255 | BC69: =IF(AND(AH69>=2022,AH69<=2024),C69/BB69,"") | BD69: =INDEX('Seasonal Index'!$H$2:$H$53,AI69) -> 1.0342763 | BE69: =IF(AH69>=2022,BB69*BD69,"") | BF69: =IF(AND(AW69="Validation",ISNUMBER(AX69),ISNUMBER(BE69)),ABS(AX69-BE69)/AX69,"") | BG69: =IF(ISNUMBER(C69),C69,0) -> 7086 | BH69: =IF(ISNUMBER(AY69),AV69-AX69,0) -> 0 | BI69: =IF(ISNUMBER(AY69),BE69-AX69,0) -> 0
... A213: 212 | B213: 34754 | C213: 7670 | F213: 343000 | H213: 18.7475 | I213: 17.178 | J213: 1.067 | K213: 7455.288 | M213: 816 | N213: 14.801 | O213: 193087 | P213: 4841.6 | Q213: 980405 | V213: 27 | W213: 92.7 | AB213: 260282 | AD213: 0 | AE213: 128.6 | AF213: 0.2 | AH213: =YEAR(B213) -> 1995 | AI213: =MIN(52,INT((B213-DATE(AH213,1,1))/7)+1) -> 8 | AJ213: =IF(AND(ISNUMBER(C213),ISNUMBER(AK213),ISNUMBER(AL213),AH213>=Inputs!$B$5,AH213<=Inputs!$B$6,AH213<>Inputs!$B$7,AH213<>Inputs!$B$8),1,0) -> 0 | AK213: =IF(INDEX($E213:$AF213,Inputs!$C$10)="","",INDEX($E213:$AF213,Inputs!$C$10)) -> 193087 | AL213: =IF(INDEX($E213:$AF213,Inputs!$C$11)="","",INDEX($E213:$AF213,Inputs!$C$11)) -> 343000 | AM213: =Regression!$C$5+Regression!$C$6*A213 -> 10597.943 | AN213: =IF(AJ213=1,C213/AM213,"") | AO213: =INDEX('Seasonal Index'!$E$2:$E$53,AI213) -> 0.97838706 | AP213: =IF(AJ213=1,C213/AO213,"") | AQ213: =IF(AJ213=1,A213-Regression!$C$15,0) -> 0 | AR213: =IF(AJ213=1,AK213-Regression!$D$15,0) -> 0 | AS213: =IF(AJ213=1,AL213-Regression!$E$15,0) -> 0 | AT213: =IF(AJ213=1,AP213-Regression!$F$15,0) -> 0 | AU213: =IF(AND(ISNUMBER(AK213),ISNUMBER(AL213)),Regression!$C$38+Regression!$D$38*A213+Regression!$E$38*AK213+Regression!$F$38*AL213,"") -> 10677.889 | AV213: =IF(ISNUMBER(AU213),AU213*AO213,"") -> 10447.108 | AW213: =IF(AJ213=1,"Train",IF(AH213=Inputs!$B$6+1,"Validation",IF(AH213>Inputs!$B$6+1,"Forecast","Not used"))) -> Not used | AX213: =IF(ISNUMBER(C213),C213,IF(ISNUMBER(D213),D213,"")) -> 7670 | AY213: =IF(AND(AW213="Validation",ISNUMBER(AX213),ISNUMBER(AV213)),ABS(AX213-AV213)/AX213,"") | AZ213: =IF(AJ213=1,AP213-AU213,0) -> 0 | BB213: =Regression!$C$45+Regression!$C$46*A213 -> 6474.8934 | BC213: =IF(AND(AH213>=2022,AH213<=2024),C213/BB213,"") | BD213: =INDEX('Seasonal Index'!$H$2:$H$53,AI213) -> 1.0025159 | BE213: =IF(AH213>=2022,BB213*BD213,"") | BF213: =IF(AND(AW213="Validation",ISNUMBER(AX213),ISNUMBER(BE213)),ABS(AX213-BE213)/AX213,"") | BG213: =IF(ISNUMBER(C213),C213,0) -> 7670 | BH213: =IF(ISNUMBER(AY213),AV213-AX213,0) -> 0 | BI213: =IF(ISNUMBER(AY213),BE213-AX213,0) -> 0
A214: 213 | B214: 34761 | C214: 7194 | F214: 336000 | H214: 18.5 | I214: 16.932 | J214: 1.073 | K214: 7455.288 | M214: 816 | N214: 14.801 | O214: 193087 | P214: 4841.6 | Q214: 980405 | S214: 2483 | V214: 27 | W214: 92.7 | AB214: 263455 | AD214: 0 | AE214: 149.6 | AF214: 0.7 | AH214: =YEAR(B214) -> 1995 | AI214: =MIN(52,INT((B214-DATE(AH214,1,1))/7)+1) -> 9 | AJ214: =IF(AND(ISNUMBER(C214),ISNUMBER(AK214),ISNUMBER(AL214),AH214>=Inputs!$B$5,AH214<=Inputs!$B$6,AH214<>Inputs!$B$7,AH214<>Inputs!$B$8),1,0) -> 0 | AK214: =IF(INDEX($E214:$AF214,Inputs!$C$10)="","",INDEX($E214:$AF214,Inputs!$C$10)) -> 193087 | AL214: =IF(INDEX($E214:$AF214,Inputs!$C$11)="","",INDEX($E214:$AF214,Inputs!$C$11)) -> 336000 | AM214: =Regression!$C$5+Regression!$C$6*A214 -> 10596.77 | AN214: =IF(AJ214=1,C214/AM214,"") | AO214: =INDEX('Seasonal Index'!$E$2:$E$53,AI214) -> 0.98629368 | AP214: =IF(AJ214=1,C214/AO214,"") | AQ214: =IF(AJ214=1,A214-Regression!$C$15,0) -> 0 | AR214: =IF(AJ214=1,AK214-Regression!$D$15,0) -> 0 | AS214: =IF(AJ214=1,AL214-Regression!$E$15,0) -> 0 | AT214: =IF(AJ214=1,AP214-Regression!$F$15,0) -> 0 | AU214: =IF(AND(ISNUMBER(AK214),ISNUMBER(AL214)),Regression!$C$38+Regression!$D$38*A214+Regression!$E$38*AK214+Regression!$F$38*AL214,"") -> 10694.912 | AV214: =IF(ISNUMBER(AU214),AU214*AO214,"") -> 10548.324 | AW214: =IF(AJ214=1,"Train",IF(AH214=Inputs!$B$6+1,"Validation",IF(AH214>Inputs!$B$6+1,"Forecast","Not used"))) -> Not used | AX214: =IF(ISNUMBER(C214),C214,IF(ISNUMBER(D214),D214,"")) -> 7194 | AY214: =IF(AND(AW214="Validation",ISNUMBER(AX214),ISNUMBER(AV214)),ABS(AX214-AV214)/AX214,"") | AZ214: =IF(AJ214=1,AP214-AU214,0) -> 0 | BB214: =Regression!$C$45+Regression!$C$46*A214 -> 6476.4529 | BC214: =IF(AND(AH214>=2022,AH214<=2024),C214/BB214,"") | BD214: =INDEX('Seasonal Index'!$H$2:$H$53,AI214) -> 1.0104104 | BE214: =IF(AH214>=2022,BB214*BD214,"") | BF214: =IF(AND(AW214="Validation",ISNUMBER(AX214),ISNUMBER(BE214)),ABS(AX214-BE214)/AX214,"") | BG214: =IF(ISNUMBER(C214),C214,0) -> 7194 | BH214: =IF(ISNUMBER(AY214),AV214-AX214,0) -> 0 | BI214: =IF(ISNUMBER(AY214),BE214-AX214,0) -> 0
A215: 214 | B215: 34768 | C215: 7548 | F215: 339000 | H215: 18.27 | I215: 16.696 | J215: 1.076 | K215: 7455.288 | M215: 748 | N215: 14.801 | O215: 193087 | P215: 4851.2 | Q215: 980405 | S215: 2483 | V215: 27 | W215: 92.6 | AB215: 263455 | AD215: 0 | AE215: 141.1 | AF215: 0.8 | AH215: =YEAR(B215) -> 1995 | AI215: =MIN(52,INT((B215-DATE(AH215,1,1))/7)+1) -> 10 | AJ215: =IF(AND(ISNUMBER(C215),ISNUMBER(AK215),ISNUMBER(AL215),AH215>=Inputs!$B$5,AH215<=Inputs!$B$6,AH215<>Inputs!$B$7,AH215<>Inputs!$B$8),1,0) -> 0 | AK215: =IF(INDEX($E215:$AF215,Inputs!$C$10)="","",INDEX($E215:$AF215,Inputs!$C$10)) -> 193087 | AL215: =IF(INDEX($E215:$AF215,Inputs!$C$11)="","",INDEX($E215:$AF215,Inputs!$C$11)) -> 339000 | AM215: =Regression!$C$5+Regression!$C$6*A215 -> 10595.598 | AN215: =IF(AJ215=1,C215/AM215,"") | AO215: =INDEX('Seasonal Index'!$E$2:$E$53,AI215) -> 0.99527491 | AP215: =IF(AJ215=1,C215/AO215,"") | AQ215: =IF(AJ215=1,A215-Regression!$C$15,0) -> 0 | AR215: =IF(AJ215=1,AK215-Regression!$D$15,0) -> 0 | AS215: =IF(AJ215=1,AL215-Regression!$E$15,0) -> 0 | AT215: =IF(AJ215=1,AP215-Regression!$F$15,0) -> 0 | AU215: =IF(AND(ISNUMBER(AK215),ISNUMBER(AL215)),Regression!$C$38+Regression!$D$38*A215+Regression!$E$38*AK215+Regression!$F$38*AL215,"") -> 10685.384 | AV215: =IF(ISNUMBER(AU215),AU215*AO215,"") -> 10634.895 | AW215: =IF(AJ215=1,"Train",IF(AH215=Inputs!$B$6+1,"Validation",IF(AH215>Inputs!$B$6+1,"Forecast","Not used"))) -> Not used | AX215: =IF(ISNUMBER(C215),C215,IF(ISNUMBER(D215),D215,"")) -> 7548 | AY215: =IF(AND(AW215="Validation",ISNUMBER(AX215),ISNUMBER(AV215)),ABS(AX215-AV215)/AX215,"") | AZ215: =IF(AJ215=1,AP215-AU215,0) -> 0 | BB215: =Regression!$C$45+Regression!$C$46*A215 -> 6478.0124 | BC215: =IF(AND(AH215>=2022,AH215<=2024),C215/BB215,"") | BD215: =INDEX('Seasonal Index'!$H$2:$H$53,AI215) -> 1.0119262 | BE215: =IF(AH215>=2022,BB215*BD215,"") | BF215: =IF(AND(AW215="Validation",ISNUMBER(AX215),ISNUMBER(BE215)),ABS(AX215-BE215)/AX215,"") | BG215: =IF(ISNUMBER(C215),C215,0) -> 7548 | BH215: =IF(ISNUMBER(AY215),AV215-AX215,0) -> 0 | BI215: =IF(ISNUMBER(AY215),BE215-AX215,0) -> 0
A216: 215 | B216: 34775 | C216: 7834 | F216: 347000 | H216: 18.132 | I216: 16.412 | J216: 1.069 | K216: 7455.288 | M216: 748 | N216: 14.861 | O216: 193087 | P216: 4851.2 | Q216: 1021168 | S216: 2483 | V216: 27 | W216: 92.6 | AB216: 263455 | AD216: 0 | AE216: 91.9 | AF216: 0.3 | AH216: =YEAR(B216) -> 1995 | AI216: =MIN(52,INT((B216-DATE(AH216,1,1))/7)+1) -> 11 | AJ216: =IF(AND(ISNUMBER(C216),ISNUMBER(AK216),ISNUMBER(AL216),AH216>=Inputs!$B$5,AH216<=Inputs!$B$6,AH216<>Inputs!$B$7,AH216<>Inputs!$B$8),1,0) -> 0 | AK216: =IF(INDEX($E216:$AF216,Inputs!$C$10)="","",INDEX($E216:$AF216,Inputs!$C$10)) -> 193087 | AL216: =IF(INDEX($E216:$AF216,Inputs!$C$11)="","",INDEX($E216:$AF216,Inputs!$C$11)) -> 347000 | AM216: =Regression!$C$5+Regression!$C$6*A216 -> 10594.425 | AN216: =IF(AJ216=1,C216/AM216,"") | AO216: =INDEX('Seasonal Index'!$E$2:$E$53,AI216) -> 1.0021278 | AP216: =IF(AJ216=1,C216/AO216,"") | AQ216: =IF(AJ216=1,A216-Regression!$C$15,0) -> 0 | AR216: =IF(AJ216=1,AK216-Regression!$D$15,0) -> 0 | AS216: =IF(AJ216=1,AL216-Regression!$E$15,0) -> 0 | AT216: =IF(AJ216=1,AP216-Regression!$F$15,0) -> 0 | AU216: =IF(AND(ISNUMBER(AK216),ISNUMBER(AL216)),Regression!$C$38+Regression!$D$38*A216+Regression!$E$38*AK216+Regression!$F$38*AL216,"") -> 10662.582 | AV216: =IF(ISNUMBER(AU216),AU216*AO216,"") -> 10685.269 | AW216: =IF(AJ216=1,"Train",IF(AH216=Inputs!$B$6+1,"Validation",IF(AH216>Inputs!$B$6+1,"Forecast","Not used"))) -> Not used | AX216: =IF(ISNUMBER(C216),C216,IF(ISNUMBER(D216),D216,"")) -> 7834 | AY216: =IF(AND(AW216="Validation",ISNUMBER(AX216),ISNUMBER(AV216)),ABS(AX216-AV216)/AX216,"") | AZ216: =IF(AJ216=1,AP216-AU216,0) -> 0 | BB216: =Regression!$C$45+Regression!$C$46*A216 -> 6479.5719 | BC216: =IF(AND(AH216>=2022,AH216<=2024),C216/BB216,"") | BD216: =INDEX('Seasonal Index'!$H$2:$H$53,AI216) -> 1.0050202 | BE216: =IF(AH216>=2022,BB216*BD216,"") | BF216: =IF(AND(AW216="Validation",ISNUMBER(AX216),ISNUMBER(BE216)),ABS(AX216-BE216)/AX216,"") | BG216: =IF(ISNUMBER(C216),C216,0) -> 7834 | BH216: =IF(ISNUMBER(AY216),AV216-AX216,0) -> 0 | BI216: =IF(ISNUMBER(AY216),BE216-AX216,0) -> 0
A217: 216 | B217: 34782 | C217: 7797 | F217: 343000 | H217: 18.692 | I217: 17.168 | J217: 1.068 | K217: 7455.288 | M217: 748 | N217: 14.861 | O217: 193838 | P217: 4851.2 | Q217: 1021168 | S217: 2483 | V217: 27 | W217: 92.6 | AB217: 263455 | AD217: 0 | AE217: 88.9 | AF217: 6.7 | AH217: =YEAR(B217) -> 1995 | AI217: =MIN(52,INT((B217-DATE(AH217,1,1))/7)+1) -> 12 | AJ217: =IF(AND(ISNUMBER(C217),ISNUMBER(AK217),ISNUMBER(AL217),AH217>=Inputs!$B$5,AH217<=Inputs!$B$6,AH217<>Inputs!$B$7,AH217<>Inputs!$B$8),1,0) -> 0 | AK217: =IF(INDEX($E217:$AF217,Inputs!$C$10)="","",INDEX($E217:$AF217,Inputs!$C$10)) -> 193838 | AL217: =IF(INDEX($E217:$AF217,Inputs!$C$11)="","",INDEX($E217:$AF217,Inputs!$C$11)) -> 343000 | AM217: =Regression!$C$5+Regression!$C$6*A217 -> 10593.252 | AN217: =IF(AJ217=1,C217/AM217,"") | AO217: =INDEX('Seasonal Index'!$E$2:$E$53,AI217) -> 0.99255102 | AP217: =IF(AJ217=1,C217/AO217,"") | AQ217: =IF(AJ217=1,A217-Regression!$C$15,0) -> 0 | AR217: =IF(AJ217=1,AK217-Regression!$D$15,0) -> 0 | AS217: =IF(AJ217=1,AL217-Regression!$E$15,0) -> 0 | AT217: =IF(AJ217=1,AP217-Regression!$F$15,0) -> 0 | AU217: =IF(AND(ISNUMBER(AK217),ISNUMBER(AL217)),Regression!$C$38+Regression!$D$38*A217+Regression!$E$38*AK217+Regression!$F$38*AL217,"") -> 10673.01 | AV217: =IF(ISNUMBER(AU217),AU217*AO217,"") -> 10593.507 | AW217: =IF(AJ217=1,"Train",IF(AH217=Inputs!$B$6+1,"Validation",IF(AH217>Inputs!$B$6+1,"Forecast","Not used"))) -> Not used | AX217: =IF(ISNUMBER(C217),C217,IF(ISNUMBER(D217),D217,"")) -> 7797 | AY217: =IF(AND(AW217="Validation",ISNUMBER(AX217),ISNUMBER(AV217)),ABS(AX217-AV217)/AX217,"") | AZ217: =IF(AJ217=1,AP217-AU217,0) -> 0 | BB217: =Regression!$C$45+Regression!$C$46*A217 -> 6481.1314 | BC217: =IF(AND(AH217>=2022,AH217<=2024),C217/BB217,"") | BD217: =INDEX('Seasonal Index'!$H$2:$H$53,AI217) -> 1.0030365 | BE217: =IF(AH217>=2022,BB217*BD217,"") | BF217: =IF(AND(AW217="Validation",ISNUMBER(AX217),ISNUMBER(BE217)),ABS(AX217-BE217)/AX217,"") | BG217: =IF(ISNUMBER(C217),C217,0) -> 7797 | BH217: =IF(ISNUMBER(AY217),AV217-AX217,0) -> 0 | BI217: =IF(ISNUMBER(AY217),BE217-AX217,0) -> 0
A218: 217 | B218: 34789 | C218: 8195 | F218: 332000 | H218: 19.118 | I218: 17.938 | J218: 1.075 | K218: 7455.288 | M218: 748 | N218: 14.861 | O218: 193838 | P218: 4851.2 | Q218: 1021168 | S218: 2483 | V218: 27 | W218: 92.6 | AB218: 263455 | AD218: 0 | AE218: 101.2 | AF218: 3.9 | AH218: =YEAR(B218) -> 1995 | AI218: =MIN(52,INT((B218-DATE(AH218,1,1))/7)+1) -> 13 | AJ218: =IF(AND(ISNUMBER(C218),ISNUMBER(AK218),ISNUMBER(AL218),AH218>=Inputs!$B$5,AH218<=Inputs!$B$6,AH218<>Inputs!$B$7,AH218<>Inputs!$B$8),1,0) -> 0 | AK218: =IF(INDEX($E218:$AF218,Inputs!$C$10)="","",INDEX($E218:$AF218,Inputs!$C$10)) -> 193838 | AL218: =IF(INDEX($E218:$AF218,Inputs!$C$11)="","",INDEX($E218:$AF218,Inputs!$C$11)) -> 332000 | AM218: =Regression!$C$5+Regression!$C$6*A218 -> 10592.08 | AN218: =IF(AJ218=1,C218/AM218,"") | AO218: =INDEX('Seasonal Index'!$E$2:$E$53,AI218) -> 1.0067199 | AP218: =IF(AJ218=1,C218/AO218,"") | AQ218: =IF(AJ218=1,A218-Regression!$C$15,0) -> 0 | AR218: =IF(AJ218=1,AK218-Regression!$D$15,0) -> 0 | AS218: =IF(AJ218=1,AL218-Regression!$E$15,0) -> 0 | AT218: =IF(AJ218=1,AP218-Regression!$F$15,0) -> 0 | AU218: =IF(AND(ISNUMBER(AK218),ISNUMBER(AL218)),Regression!$C$38+Regression!$D$38*A218+Regression!$E$38*AK218+Regression!$F$38*AL218,"") -> 10700.653 | AV218: =IF(ISNUMBER(AU218),AU218*AO218,"") -> 10772.561 | AW218: =IF(AJ218=1,"Train",IF(AH218=Inputs!$B$6+1,"Validation",IF(AH218>Inputs!$B$6+1,"Forecast","Not used"))) -> Not used | AX218: =IF(ISNUMBER(C218),C218,IF(ISNUMBER(D218),D218,"")) -> 8195 | AY218: =IF(AND(AW218="Validation",ISNUMBER(AX218),ISNUMBER(AV218)),ABS(AX218-AV218)/AX218,"") | AZ218: =IF(AJ218=1,AP218-AU218,0) -> 0 | BB218: =Regression!$C$45+Regression!$C$46*A218 -> 6482.6909 | BC218: =IF(AND(AH218>=2022,AH218<=2024),C218/BB218,"") | BD218: =INDEX('Seasonal Index'!$H$2:$H$53,AI218) -> 1.0306249 | BE218: =IF(AH218>=2022,BB218*BD218,"") | BF218: =IF(AND(AW218="Validation",ISNUMBER(AX218),ISNUMBER(BE218)),ABS(AX218-BE218)/AX218,"") | BG218: =IF(ISNUMBER(C218),C218,0) -> 8195 | BH218: =IF(ISNUMBER(AY218),AV218-AX218,0) -> 0 | BI218: =IF(ISNUMBER(AY218),BE218-AX218,0) -> 0
A219: 218 | B219: 34796 | C219: 7588 | F219: 335000 | H219: 19.428 | I219: 18.242 | J219: 1.087 | K219: 7455.288 | M219: 713 | N219: 14.861 | O219: 193838 | P219: 4850.8 | Q219: 1021168 | S219: 2483 | V219: 27 | W219: 89.6 | AB219: 263455 | AD219: 0 | AE219: 95.4 | AF219: 0.1 | AH219: =YEAR(B219) -> 1995 | AI219: =MIN(52,INT((B219-DATE(AH219,1,1))/7)+1) -> 14 | AJ219: =IF(AND(ISNUMBER(C219),ISNUMBER(AK219),ISNUMBER(AL219),AH219>=Inputs!$B$5,AH219<=Inputs!$B$6,AH219<>Inputs!$B$7,AH219<>Inputs!$B$8),1,0) -> 0 | AK219: =IF(INDEX($E219:$AF219,Inputs!$C$10)="","",INDEX($E219:$AF219,Inputs!$C$10)) -> 193838 | AL219: =IF(INDEX($E219:$AF219,Inputs!$C$11)="","",INDEX($E219:$AF219,Inputs!$C$11)) -> 335000 | AM219: =Regression!$C$5+Regression!$C$6*A219 -> 10590.907 | AN219: =IF(AJ219=1,C219/AM219,"") | AO219: =INDEX('Seasonal Index'!$E$2:$E$53,AI219) -> 0.99471307 | AP219: =IF(AJ219=1,C219/AO219,"") | AQ219: =IF(AJ219=1,A219-Regression!$C$15,0) -> 0 | AR219: =IF(AJ219=1,AK219-Regression!$D$15,0) -> 0 | AS219: =IF(AJ219=1,AL219-Regression!$E$15,0) -> 0 | AT219: =IF(AJ219=1,AP219-Regression!$F$15,0) -> 0 | AU219: =IF(AND(ISNUMBER(AK219),ISNUMBER(AL219)),Regression!$C$38+Regression!$D$38*A219+Regression!$E$38*AK219+Regression!$F$38*AL219,"") -> 10691.126 | AV219: =IF(ISNUMBER(AU219),AU219*AO219,"") -> 10634.602 | AW219: =IF(AJ219=1,"Train",IF(AH219=Inputs!$B$6+1,"Validation",IF(AH219>Inputs!$B$6+1,"Forecast","Not used"))) -> Not used | AX219: =IF(ISNUMBER(C219),C219,IF(ISNUMBER(D219),D219,"")) -> 7588 | AY219: =IF(AND(AW219="Validation",ISNUMBER(AX219),ISNUMBER(AV219)),ABS(AX219-AV219)/AX219,"") | AZ219: =IF(AJ219=1,AP219-AU219,0) -> 0 | BB219: =Regression!$C$45+Regression!$C$46*A219 -> 6484.2504 | BC219: =IF(AND(AH219>=2022,AH219<=2024),C219/BB219,"") | BD219: =INDEX('Seasonal Index'!$H$2:$H$53,AI219) -> 0.99994657 | BE219: =IF(AH219>=2022,BB219*BD219,"") | BF219: =IF(AND(AW219="Validation",ISNUMBER(AX219),ISNUMBER(BE219)),ABS(AX219-BE219)/AX219,"") | BG219: =IF(ISNUMBER(C219),C219,0) -> 7588 | BH219: =IF(ISNUMBER(AY219),AV219-AX219,0) -> 0 | BI219: =IF(ISNUMBER(AY219),BE219-AX219,0) -> 0
A220: 219 | B220: 34803 | C220: 7543 | F220: 347000 | H220: 19.5275 | I220: 18.3725 | J220: 1.103 | K220: 7455.288 | M220: 713 | N220: 14.861 | O220: 193838 | P220: 4850.8 | Q220: 1021168 | S220: 2483 | V220: 27 | W220: 89.6 | AB220: 263455 | AD220: 0 | AE220: 74.8 | AF220: 4.8 | AH220: =YEAR(B220) -> 1995 | AI220: =MIN(52,INT((B220-DATE(AH220,1,1))/7)+1) -> 15 | AJ220: =IF(AND(ISNUMBER(C220),ISNUMBER(AK220),ISNUMBER(AL220),AH220>=Inputs!$B$5,AH220<=Inputs!$B$6,AH220<>Inputs!$B$7,AH220<>Inputs!$B$8),1,0) -> 0 | AK220: =IF(INDEX($E220:$AF220,Inputs!$C$10)="","",INDEX($E220:$AF220,Inputs!$C$10)) -> 193838 | AL220: =IF(INDEX($E220:$AF220,Inputs!$C$11)="","",INDEX($E220:$AF220,Inputs!$C$11)) -> 347000 | AM220: =Regression!$C$5+Regression!$C$6*A220 -> 10589.734 | AN220: =IF(AJ220=1,C220/AM220,"") | AO220: =INDEX('Seasonal Index'!$E$2:$E$53,AI220) -> 1.0030309 | AP220: =IF(AJ220=1,C220/AO220,"") | AQ220: =IF(AJ220=1,A220-Regression!$C$15,0) -> 0 | AR220: =IF(AJ220=1,AK220-Regression!$D$15,0) -> 0 | AS220: =IF(AJ220=1,AL220-Regression!$E$15,0) -> 0 | AT220: =IF(AJ220=1,AP220-Regression!$F$15,0) -> 0 | AU220: =IF(AND(ISNUMBER(AK220),ISNUMBER(AL220)),Regression!$C$38+Regression!$D$38*A220+Regression!$E$38*AK220+Regression!$F$38*AL220,"") -> 10657.703 | AV220: =IF(ISNUMBER(AU220),AU220*AO220,"") -> 10690.006 | AW220: =IF(AJ220=1,"Train",IF(AH220=Inputs!$B$6+1,"Validation",IF(AH220>Inputs!$B$6+1,"Forecast","Not used"))) -> Not used | AX220: =IF(ISNUMBER(C220),C220,IF(ISNUMBER(D220),D220,"")) -> 7543 | AY220: =IF(AND(AW220="Validation",ISNUMBER(AX220),ISNUMBER(AV220)),ABS(AX220-AV220)/AX220,"") | AZ220: =IF(AJ220=1,AP220-AU220,0) -> 0 | BB220: =Regression!$C$45+Regression!$C$46*A220 -> 6485.8099 | BC220: =IF(AND(AH220>=2022,AH220<=2024),C220/BB220,"") | BD220: =INDEX('Seasonal Index'!$H$2:$H$53,AI220) -> 0.99086023 | BE220: =IF(AH220>=2022,BB220*BD220,"") | BF220: =IF(AND(AW220="Validation",ISNUMBER(AX220),ISNUMBER(BE220)),ABS(AX220-BE220)/AX220,"") | BG220: =IF(ISNUMBER(C220),C220,0) -> 7543 | BH220: =IF(ISNUMBER(AY220),AV220-AX220,0) -> 0 | BI220: =IF(ISNUMBER(AY220),BE220-AX220,0) -> 0
A221: 220 | B221: 34810 | C221: 8156 | F221: 355000 | H221: 20.264 | I221: 18.9025 | J221: 1.117 | K221: 7455.288 | M221: 713 | N221: 15.256 | O221: 171053 | P221: 4850.8 | Q221: 1021168 | S221: 2483 | V221: 27 | W221: 89.6 | AB221: 263455 | AD221: 0 | AE221: 66.2 | AF221: 15.3 | AH221: =YEAR(B221) -> 1995 | AI221: =MIN(52,INT((B221-DATE(AH221,1,1))/7)+1) -> 16 | AJ221: =IF(AND(ISNUMBER(C221),ISNUMBER(AK221),ISNUMBER(AL221),AH221>=Inputs!$B$5,AH221<=Inputs!$B$6,AH221<>Inputs!$B$7,AH221<>Inputs!$B$8),1,0) -> 0 | AK221: =IF(INDEX($E221:$AF221,Inputs!$C$10)="","",INDEX($E221:$AF221,Inputs!$C$10)) -> 171053 | AL221: =IF(INDEX($E221:$AF221,Inputs!$C$11)="","",INDEX($E221:$AF221,Inputs!$C$11)) -> 355000 | AM221: =Regression!$C$5+Regression!$C$6*A221 -> 10588.562 | AN221: =IF(AJ221=1,C221/AM221,"") | AO221: =INDEX('Seasonal Index'!$E$2:$E$53,AI221) -> 1.0020974 | AP221: =IF(AJ221=1,C221/AO221,"") | AQ221: =IF(AJ221=1,A221-Regression!$C$15,0) -> 0 | AR221: =IF(AJ221=1,AK221-Regression!$D$15,0) -> 0 | AS221: =IF(AJ221=1,AL221-Regression!$E$15,0) -> 0 | AT221: =IF(AJ221=1,AP221-Regression!$F$15,0) -> 0 | AU221: =IF(AND(ISNUMBER(AK221),ISNUMBER(AL221)),Regression!$C$38+Regression!$D$38*A221+Regression!$E$38*AK221+Regression!$F$38*AL221,"") -> 10593.325 | AV221: =IF(ISNUMBER(AU221),AU221*AO221,"") -> 10615.544 | AW221: =IF(AJ221=1,"Train",IF(AH221=Inputs!$B$6+1,"Validation",IF(AH221>Inputs!$B$6+1,"Forecast","Not used"))) -> Not used | AX221: =IF(ISNUMBER(C221),C221,IF(ISNUMBER(D221),D221,"")) -> 8156 | AY221: =IF(AND(AW221="Validation",ISNUMBER(AX221),ISNUMBER(AV221)),ABS(AX221-AV221)/AX221,"") | AZ221: =IF(AJ221=1,AP221-AU221,0) -> 0 | BB221: =Regression!$C$45+Regression!$C$46*A221 -> 6487.3694 | BC221: =IF(AND(AH221>=2022,AH221<=2024),C221/BB221,"") | BD221: =INDEX('Seasonal Index'!$H$2:$H$53,AI221) -> 1.01445 | BE221: =IF(AH221>=2022,BB221*BD221,"") | BF221: =IF(AND(AW221="Validation",ISNUMBER(AX221),ISNUMBER(BE221)),ABS(AX221-BE221)/AX221,"") | BG221: =IF(ISNUMBER(C221),C221,0) -> 8156 | BH221: =IF(ISNUMBER(AY221),AV221-AX221,0) -> 0 | BI221: =IF(ISNUMBER(AY221),BE221-AX221,0) -> 0
A222: 221 | B222: 34817 | C222: 7731 | F222: 349000 | H222: 20.292 | I222: 19.072 | J222: 1.138 | K222: 7455.288 | M222: 713 | N222: 15.256 | O222: 171053 | P222: 4850.8 | Q222: 1021168 | S222: 2483 | V222: 27 | W222: 89.6 | AB222: 263455 | AD222: 0 | AE222: 54.8 | AF222: 5.9 | AH222: =YEAR(B222) -> 1995 | AI222: =MIN(52,INT((B222-DATE(AH222,1,1))/7)+1) -> 17 | AJ222: =IF(AND(ISNUMBER(C222),ISNUMBER(AK222),ISNUMBER(AL222),AH222>=Inputs!$B$5,AH222<=Inputs!$B$6,AH222<>Inputs!$B$7,AH222<>Inputs!$B$8),1,0) -> 0 | AK222: =IF(INDEX($E222:$AF222,Inputs!$C$10)="","",INDEX($E222:$AF222,Inputs!$C$10)) -> 171053 | AL222: =IF(INDEX($E222:$AF222,Inputs!$C$11)="","",INDEX($E222:$AF222,Inputs!$C$11)) -> 349000 | AM222: =Regression!$C$5+Regression!$C$6*A222 -> 10587.389 | AN222: =IF(AJ222=1,C222/AM222,"") | AO222: =INDEX('Seasonal Index'!$E$2:$E$53,AI222) -> 0.98572001 | AP222: =IF(AJ222=1,C222/AO222,"") | AQ222: =IF(AJ222=1,A222-Regression!$C$15,0) -> 0 | AR222: =IF(AJ222=1,AK222-Regression!$D$15,0) -> 0 | AS222: =IF(AJ222=1,AL222-Regression!$E$15,0) -> 0 | AT222: =IF(AJ222=1,AP222-Regression!$F$15,0) -> 0 | AU222: =IF(AND(ISNUMBER(AK222),ISNUMBER(AL222)),Regression!$C$38+Regression!$D$38*A222+Regression!$E$38*AK222+Regression!$F$38*AL222,"") -> 10607.693 | AV222: =IF(ISNUMBER(AU222),AU222*AO222,"") -> 10456.215 | AW222: =IF(AJ222=1,"Train",IF(AH222=Inputs!$B$6+1,"Validation",IF(AH222>Inputs!$B$6+1,"Forecast","Not used"))) -> Not used | AX222: =IF(ISNUMBER(C222),C222,IF(ISNUMBER(D222),D222,"")) -> 7731 | AY222: =IF(AND(AW222="Validation",ISNUMBER(AX222),ISNUMBER(AV222)),ABS(AX222-AV222)/AX222,"") | AZ222: =IF(AJ222=1,AP222-AU222,0) -> 0 | BB222: =Regression!$C$45+Regression!$C$46*A222 -> 6488.9289 | BC222: =IF(AND(AH222>=2022,AH222<=2024),C222/BB222,"") | BD222: =INDEX('Seasonal Index'!$H$2:$H$53,AI222) -> 0.99215359 | BE222: =IF(AH222>=2022,BB222*BD222,"") | BF222: =IF(AND(AW222="Validation",ISNUMBER(AX222),ISNUMBER(BE222)),ABS(AX222-BE222)/AX222,"") | BG222: =IF(ISNUMBER(C222),C222,0) -> 7731 | BH222: =IF(ISNUMBER(AY222),AV222-AX222,0) -> 0 | BI222: =IF(ISNUMBER(AY222),BE222-AX222,0) -> 0
A223: 222 | B223: 34824 | C223: 7539 | F223: 365000 | H223: 20.244 | I223: 18.814 | J223: 1.148 | K223: 7455.288 | M223: 713 | N223: 15.256 | O223: 171053 | P223: 4850.8 | Q223: 1021168 | S223: 2483 | V223: 27 | W223: 87.9 | AB223: 263455 | AD223: 0 | AE223: 55.4 | AF223: 13.1 | AH223: =YEAR(B223) -> 1995 | AI223: =MIN(52,INT((B223-DATE(AH223,1,1))/7)+1) -> 18 | AJ223: =IF(AND(ISNUMBER(C223),ISNUMBER(AK223),ISNUMBER(AL223),AH223>=Inputs!$B$5,AH223<=Inputs!$B$6,AH223<>Inputs!$B$7,AH223<>Inputs!$B$8),1,0) -> 0 | AK223: =IF(INDEX($E223:$AF223,Inputs!$C$10)="","",INDEX($E223:$AF223,Inputs!$C$10)) -> 171053 | AL223: =IF(INDEX($E223:$AF223,Inputs!$C$11)="","",INDEX($E223:$AF223,Inputs!$C$11)) -> 365000 | AM223: =Regression!$C$5+Regression!$C$6*A223 -> 10586.216 | AN223: =IF(AJ223=1,C223/AM223,"") | AO223: =INDEX('Seasonal Index'!$E$2:$E$53,AI223) -> 1.0181402 | AP223: =IF(AJ223=1,C223/AO223,"") | AQ223: =IF(AJ223=1,A223-Regression!$C$15,0) -> 0 | AR223: =IF(AJ223=1,AK223-Regression!$D$15,0) -> 0 | AS223: =IF(AJ223=1,AL223-Regression!$E$15,0) -> 0 | AT223: =IF(AJ223=1,AP223-Regression!$F$15,0) -> 0 | AU223: =IF(AND(ISNUMBER(AK223),ISNUMBER(AL223)),Regression!$C$38+Regression!$D$38*A223+Regression!$E$38*AK223+Regression!$F$38*AL223,"") -> 10563.65 | AV223: =IF(ISNUMBER(AU223),AU223*AO223,"") -> 10755.276 | AW223: =IF(AJ223=1,"Train",IF(AH223=Inputs!$B$6+1,"Validation",IF(AH223>Inputs!$B$6+1,"Forecast","Not used"))) -> Not used | AX223: =IF(ISNUMBER(C223),C223,IF(ISNUMBER(D223),D223,"")) -> 7539 | AY223: =IF(AND(AW223="Validation",ISNUMBER(AX223),ISNUMBER(AV223)),ABS(AX223-AV223)/AX223,"") | AZ223: =IF(AJ223=1,AP223-AU223,0) -> 0 | BB223: =Regression!$C$45+Regression!$C$46*A223 -> 6490.4884 | BC223: =IF(AND(AH223>=2022,AH223<=2024),C223/BB223,"") | BD223: =INDEX('Seasonal Index'!$H$2:$H$53,AI223) -> 1.0188494 | BE223: =IF(AH223>=2022,BB223*BD223,"") | BF223: =IF(AND(AW223="Validation",ISNUMBER(AX223),ISNUMBER(BE223)),ABS(AX223-BE223)/AX223,"") | BG223: =IF(ISNUMBER(C223),C223,0) -> 7539 | BH223: =IF(ISNUMBER(AY223),AV223-AX223,0) -> 0 | BI223: =IF(ISNUMBER(AY223),BE223-AX223,0) -> 0
A224: 223 | B224: 34831 | C224: 8052 | F224: 364000 | H224: 19.74 | I224: 18.262 | J224: 1.169 | K224: 7522.289 | M224: 665 | N224: 15.256 | O224: 171053 | P224: 4885.4 | Q224: 1021168 | S224: 2483 | V224: 27 | W224: 87.9 | AB224: 263455 | AD224: 0 | AE224: 38.9 | AF224: 23.3 | AH224: =YEAR(B224) -> 1995 | AI224: =MIN(52,INT((B224-DATE(AH224,1,1))/7)+1) -> 19 | AJ224: =IF(AND(ISNUMBER(C224),ISNUMBER(AK224),ISNUMBER(AL224),AH224>=Inputs!$B$5,AH224<=Inputs!$B$6,AH224<>Inputs!$B$7,AH224<>Inputs!$B$8),1,0) -> 0 | AK224: =IF(INDEX($E224:$AF224,Inputs!$C$10)="","",INDEX($E224:$AF224,Inputs!$C$10)) -> 171053 | AL224: =IF(INDEX($E224:$AF224,Inputs!$C$11)="","",INDEX($E224:$AF224,Inputs!$C$11)) -> 364000 | AM224: =Regression!$C$5+Regression!$C$6*A224 -> 10585.043 | AN224: =IF(AJ224=1,C224/AM224,"") | AO224: =INDEX('Seasonal Index'!$E$2:$E$53,AI224) -> 1.0133712 | AP224: =IF(AJ224=1,C224/AO224,"") | AQ224: =IF(AJ224=1,A224-Regression!$C$15,0) -> 0 | AR224: =IF(AJ224=1,AK224-Regression!$D$15,0) -> 0 | AS224: =IF(AJ224=1,AL224-Regression!$E$15,0) -> 0 | AT224: =IF(AJ224=1,AP224-Regression!$F$15,0) -> 0 | AU224: =IF(AND(ISNUMBER(AK224),ISNUMBER(AL224)),Regression!$C$38+Regression!$D$38*A224+Regression!$E$38*AK224+Regression!$F$38*AL224,"") -> 10564.743 | AV224: =IF(ISNUMBER(AU224),AU224*AO224,"") -> 10706.007 | AW224: =IF(AJ224=1,"Train",IF(AH224=Inputs!$B$6+1,"Validation",IF(AH224>Inputs!$B$6+1,"Forecast","Not used"))) -> Not used | AX224: =IF(ISNUMBER(C224),C224,IF(ISNUMBER(D224),D224,"")) -> 8052 | AY224: =IF(AND(AW224="Validation",ISNUMBER(AX224),ISNUMBER(AV224)),ABS(AX224-AV224)/AX224,"") | AZ224: =IF(AJ224=1,AP224-AU224,0) -> 0 | BB224: =Regression!$C$45+Regression!$C$46*A224 -> 6492.0479 | BC224: =IF(AND(AH224>=2022,AH224<=2024),C224/BB224,"") | BD224: =INDEX('Seasonal Index'!$H$2:$H$53,AI224) -> 1.0190604 | BE224: =IF(AH224>=2022,BB224*BD224,"") | BF224: =IF(AND(AW224="Validation",ISNUMBER(AX224),ISNUMBER(BE224)),ABS(AX224-BE224)/AX224,"") | BG224: =IF(ISNUMBER(C224),C224,0) -> 8052 | BH224: =IF(ISNUMBER(AY224),AV224-AX224,0) -> 0 | BI224: =IF(ISNUMBER(AY224),BE224-AX224,0) -> 0
A225: 224 | B225: 34838 | C225: 8183 | F225: 366000 | H225: 19.982 | I225: 18.424 | J225: 1.179 | K225: 7522.289 | M225: 665 | N225: 14.378 | O225: 201227 | P225: 4885.4 | Q225: 1021168 | S225: 2483 | V225: 27 | W225: 87.9 | AB225: 263455 | AD225: 0 | AE225: 25.8 | AF225: 32.5 | AH225: =YEAR(B225) -> 1995 | AI225: =MIN(52,INT((B225-DATE(AH225,1,1))/7)+1) -> 20 | AJ225: =IF(AND(ISNUMBER(C225),ISNUMBER(AK225),ISNUMBER(AL225),AH225>=Inputs!$B$5,AH225<=Inputs!$B$6,AH225<>Inputs!$B$7,AH225<>Inputs!$B$8),1,0) -> 0 | AK225: =IF(INDEX($E225:$AF225,Inputs!$C$10)="","",INDEX($E225:$AF225,Inputs!$C$10)) -> 201227 | AL225: =IF(INDEX($E225:$AF225,Inputs!$C$11)="","",INDEX($E225:$AF225,Inputs!$C$11)) -> 366000 | AM225: =Regression!$C$5+Regression!$C$6*A225 -> 10583.871 | AN225: =IF(AJ225=1,C225/AM225,"") | AO225: =INDEX('Seasonal Index'!$E$2:$E$53,AI225) -> 1.0355119 | AP225: =IF(AJ225=1,C225/AO225,"") | AQ225: =IF(AJ225=1,A225-Regression!$C$15,0) -> 0 | AR225: =IF(AJ225=1,AK225-Regression!$D$15,0) -> 0 | AS225: =IF(AJ225=1,AL225-Regression!$E$15,0) -> 0 | AT225: =IF(AJ225=1,AP225-Regression!$F$15,0) -> 0 | AU225: =IF(AND(ISNUMBER(AK225),ISNUMBER(AL225)),Regression!$C$38+Regression!$D$38*A225+Regression!$E$38*AK225+Regression!$F$38*AL225,"") -> 10612.928 | AV225: =IF(ISNUMBER(AU225),AU225*AO225,"") -> 10989.813 | AW225: =IF(AJ225=1,"Train",IF(AH225=Inputs!$B$6+1,"Validation",IF(AH225>Inputs!$B$6+1,"Forecast","Not used"))) -> Not used | AX225: =IF(ISNUMBER(C225),C225,IF(ISNUMBER(D225),D225,"")) -> 8183 | AY225: =IF(AND(AW225="Validation",ISNUMBER(AX225),ISNUMBER(AV225)),ABS(AX225-AV225)/AX225,"") | AZ225: =IF(AJ225=1,AP225-AU225,0) -> 0 | BB225: =Regression!$C$45+Regression!$C$46*A225 -> 6493.6074 | BC225: =IF(AND(AH225>=2022,AH225<=2024),C225/BB225,"") | BD225: =INDEX('Seasonal Index'!$H$2:$H$53,AI225) -> 1.0467645 | BE225: =IF(AH225>=2022,BB225*BD225,"") | BF225: =IF(AND(AW225="Validation",ISNUMBER(AX225),ISNUMBER(BE225)),ABS(AX225-BE225)/AX225,"") | BG225: =IF(ISNUMBER(C225),C225,0) -> 8183 | BH225: =IF(ISNUMBER(AY225),AV225-AX225,0) -> 0 | BI225: =IF(ISNUMBER(AY225),BE225-AX225,0) -> 0
... A484: 483 | B484: 36651 | C484: 8679 | F484: 291000 | H484: 26.75 | I484: 24.9625 | J484: 1.42 | K484: 9900.169 | M484: 763 | N484: 18.343 | O484: 199261 | P484: 6625.3 | Q484: 1553622 | S484: 6119 | V484: 23 | W484: 86.4 | AB484: 279328 | AD484: 0 | AE484: 27.8 | AF484: 22.2 | AH484: =YEAR(B484) -> 2000 | AI484: =MIN(52,INT((B484-DATE(AH484,1,1))/7)+1) -> 18 | AJ484: =IF(AND(ISNUMBER(C484),ISNUMBER(AK484),ISNUMBER(AL484),AH484>=Inputs!$B$5,AH484<=Inputs!$B$6,AH484<>Inputs!$B$7,AH484<>Inputs!$B$8),1,0) -> 0 | AK484: =IF(INDEX($E484:$AF484,Inputs!$C$10)="","",INDEX($E484:$AF484,Inputs!$C$10)) -> 199261 | AL484: =IF(INDEX($E484:$AF484,Inputs!$C$11)="","",INDEX($E484:$AF484,Inputs!$C$11)) -> 291000 | AM484: =Regression!$C$5+Regression!$C$6*A484 -> 10280.148 | AN484: =IF(AJ484=1,C484/AM484,"") | AO484: =INDEX('Seasonal Index'!$E$2:$E$53,AI484) -> 1.0181402 | AP484: =IF(AJ484=1,C484/AO484,"") | AQ484: =IF(AJ484=1,A484-Regression!$C$15,0) -> 0 | AR484: =IF(AJ484=1,AK484-Regression!$D$15,0) -> 0 | AS484: =IF(AJ484=1,AL484-Regression!$E$15,0) -> 0 | AT484: =IF(AJ484=1,AP484-Regression!$F$15,0) -> 0 | AU484: =IF(AND(ISNUMBER(AK484),ISNUMBER(AL484)),Regression!$C$38+Regression!$D$38*A484+Regression!$E$38*AK484+Regression!$F$38*AL484,"") -> 10403.83 | AV484: =IF(ISNUMBER(AU484),AU484*AO484,"") -> 10592.557 | AW484: =IF(AJ484=1,"Train",IF(AH484=Inputs!$B$6+1,"Validation",IF(AH484>Inputs!$B$6+1,"Forecast","Not used"))) -> Not used | AX484: =IF(ISNUMBER(C484),C484,IF(ISNUMBER(D484),D484,"")) -> 8679 | AY484: =IF(AND(AW484="Validation",ISNUMBER(AX484),ISNUMBER(AV484)),ABS(AX484-AV484)/AX484,"") | AZ484: =IF(AJ484=1,AP484-AU484,0) -> 0 | BB484: =Regression!$C$45+Regression!$C$46*A484 -> 6897.5178 | BC484: =IF(AND(AH484>=2022,AH484<=2024),C484/BB484,"") | BD484: =INDEX('Seasonal Index'!$H$2:$H$53,AI484) -> 1.0188494 | BE484: =IF(AH484>=2022,BB484*BD484,"") | BF484: =IF(AND(AW484="Validation",ISNUMBER(AX484),ISNUMBER(BE484)),ABS(AX484-BE484)/AX484,"") | BG484: =IF(ISNUMBER(C484),C484,0) -> 8679 | BH484: =IF(ISNUMBER(AY484),AV484-AX484,0) -> 0 | BI484: =IF(ISNUMBER(AY484),BE484-AX484,0) -> 0
A485: 484 | B485: 36658 | C485: 8242 | F485: 293000 | H485: 28.7 | I485: 26.902 | J485: 1.455 | K485: 10002.179 | L485: 724934 | M485: 773 | N485: 18.343 | O485: 199261 | P485: 6686.5 | Q485: 1553622 | S485: 6119 | V485: 23 | W485: 86.4 | AB485: 279328 | AD485: 0 | AE485: 6.7 | AF485: 44.2 | AH485: =YEAR(B485) -> 2000 | AI485: =MIN(52,INT((B485-DATE(AH485,1,1))/7)+1) -> 19 | AJ485: =IF(AND(ISNUMBER(C485),ISNUMBER(AK485),ISNUMBER(AL485),AH485>=Inputs!$B$5,AH485<=Inputs!$B$6,AH485<>Inputs!$B$7,AH485<>Inputs!$B$8),1,0) -> 0 | AK485: =IF(INDEX($E485:$AF485,Inputs!$C$10)="","",INDEX($E485:$AF485,Inputs!$C$10)) -> 199261 | AL485: =IF(INDEX($E485:$AF485,Inputs!$C$11)="","",INDEX($E485:$AF485,Inputs!$C$11)) -> 293000 | AM485: =Regression!$C$5+Regression!$C$6*A485 -> 10278.975 | AN485: =IF(AJ485=1,C485/AM485,"") | AO485: =INDEX('Seasonal Index'!$E$2:$E$53,AI485) -> 1.0133712 | AP485: =IF(AJ485=1,C485/AO485,"") | AQ485: =IF(AJ485=1,A485-Regression!$C$15,0) -> 0 | AR485: =IF(AJ485=1,AK485-Regression!$D$15,0) -> 0 | AS485: =IF(AJ485=1,AL485-Regression!$E$15,0) -> 0 | AT485: =IF(AJ485=1,AP485-Regression!$F$15,0) -> 0 | AU485: =IF(AND(ISNUMBER(AK485),ISNUMBER(AL485)),Regression!$C$38+Regression!$D$38*A485+Regression!$E$38*AK485+Regression!$F$38*AL485,"") -> 10396.957 | AV485: =IF(ISNUMBER(AU485),AU485*AO485,"") -> 10535.978 | AW485: =IF(AJ485=1,"Train",IF(AH485=Inputs!$B$6+1,"Validation",IF(AH485>Inputs!$B$6+1,"Forecast","Not used"))) -> Not used | AX485: =IF(ISNUMBER(C485),C485,IF(ISNUMBER(D485),D485,"")) -> 8242 | AY485: =IF(AND(AW485="Validation",ISNUMBER(AX485),ISNUMBER(AV485)),ABS(AX485-AV485)/AX485,"") | AZ485: =IF(AJ485=1,AP485-AU485,0) -> 0 | BB485: =Regression!$C$45+Regression!$C$46*A485 -> 6899.0773 | BC485: =IF(AND(AH485>=2022,AH485<=2024),C485/BB485,"") | BD485: =INDEX('Seasonal Index'!$H$2:$H$53,AI485) -> 1.0190604 | BE485: =IF(AH485>=2022,BB485*BD485,"") | BF485: =IF(AND(AW485="Validation",ISNUMBER(AX485),ISNUMBER(BE485)),ABS(AX485-BE485)/AX485,"") | BG485: =IF(ISNUMBER(C485),C485,0) -> 8242 | BH485: =IF(ISNUMBER(AY485),AV485-AX485,0) -> 0 | BI485: =IF(ISNUMBER(AY485),BE485-AX485,0) -> 0
A486: 485 | B486: 36665 | C486: 8408 | F486: 276000 | H486: 29.878 | I486: 28.67 | J486: 1.492 | K486: 10002.179 | L486: 724934 | M486: 773 | N486: 17.939 | O486: 232490 | P486: 6686.5 | Q486: 1553622 | S486: 6119 | V486: 23 | W486: 86.4 | AB486: 279328 | AD486: 0 | AE486: 21.2 | AF486: 29.8 | AH486: =YEAR(B486) -> 2000 | AI486: =MIN(52,INT((B486-DATE(AH486,1,1))/7)+1) -> 20 | AJ486: =IF(AND(ISNUMBER(C486),ISNUMBER(AK486),ISNUMBER(AL486),AH486>=Inputs!$B$5,AH486<=Inputs!$B$6,AH486<>Inputs!$B$7,AH486<>Inputs!$B$8),1,0) -> 0 | AK486: =IF(INDEX($E486:$AF486,Inputs!$C$10)="","",INDEX($E486:$AF486,Inputs!$C$10)) -> 232490 | AL486: =IF(INDEX($E486:$AF486,Inputs!$C$11)="","",INDEX($E486:$AF486,Inputs!$C$11)) -> 276000 | AM486: =Regression!$C$5+Regression!$C$6*A486 -> 10277.803 | AN486: =IF(AJ486=1,C486/AM486,"") | AO486: =INDEX('Seasonal Index'!$E$2:$E$53,AI486) -> 1.0355119 | AP486: =IF(AJ486=1,C486/AO486,"") | AQ486: =IF(AJ486=1,A486-Regression!$C$15,0) -> 0 | AR486: =IF(AJ486=1,AK486-Regression!$D$15,0) -> 0 | AS486: =IF(AJ486=1,AL486-Regression!$E$15,0) -> 0 | AT486: =IF(AJ486=1,AP486-Regression!$F$15,0) -> 0 | AU486: =IF(AND(ISNUMBER(AK486),ISNUMBER(AL486)),Regression!$C$38+Regression!$D$38*A486+Regression!$E$38*AK486+Regression!$F$38*AL486,"") -> 10501.163 | AV486: =IF(ISNUMBER(AU486),AU486*AO486,"") -> 10874.079 | AW486: =IF(AJ486=1,"Train",IF(AH486=Inputs!$B$6+1,"Validation",IF(AH486>Inputs!$B$6+1,"Forecast","Not used"))) -> Not used | AX486: =IF(ISNUMBER(C486),C486,IF(ISNUMBER(D486),D486,"")) -> 8408 | AY486: =IF(AND(AW486="Validation",ISNUMBER(AX486),ISNUMBER(AV486)),ABS(AX486-AV486)/AX486,"") | AZ486: =IF(AJ486=1,AP486-AU486,0) -> 0 | BB486: =Regression!$C$45+Regression!$C$46*A486 -> 6900.6368 | BC486: =IF(AND(AH486>=2022,AH486<=2024),C486/BB486,"") | BD486: =INDEX('Seasonal Index'!$H$2:$H$53,AI486) -> 1.0467645 | BE486: =IF(AH486>=2022,BB486*BD486,"") | BF486: =IF(AND(AW486="Validation",ISNUMBER(AX486),ISNUMBER(BE486)),ABS(AX486-BE486)/AX486,"") | BG486: =IF(ISNUMBER(C486),C486,0) -> 8408 | BH486: =IF(ISNUMBER(AY486),AV486-AX486,0) -> 0 | BI486: =IF(ISNUMBER(AY486),BE486-AX486,0) -> 0
A487: 486 | B487: 36672 | C487: 9075 | F487: 280000 | H487: 29.462 | I487: 29.05 | J487: 1.527 | K487: 10002.179 | L487: 724934 | M487: 773 | N487: 17.939 | O487: 232490 | P487: 6686.5 | Q487: 1553622 | S487: 6119 | V487: 23 | W487: 86.4 | AB487: 279328 | AD487: 0 | AE487: 15 | AF487: 43.4 | AH487: =YEAR(B487) -> 2000 | AI487: =MIN(52,INT((B487-DATE(AH487,1,1))/7)+1) -> 21 | AJ487: =IF(AND(ISNUMBER(C487),ISNUMBER(AK487),ISNUMBER(AL487),AH487>=Inputs!$B$5,AH487<=Inputs!$B$6,AH487<>Inputs!$B$7,AH487<>Inputs!$B$8),1,0) -> 0 | AK487: =IF(INDEX($E487:$AF487,Inputs!$C$10)="","",INDEX($E487:$AF487,Inputs!$C$10)) -> 232490 | AL487: =IF(INDEX($E487:$AF487,Inputs!$C$11)="","",INDEX($E487:$AF487,Inputs!$C$11)) -> 280000 | AM487: =Regression!$C$5+Regression!$C$6*A487 -> 10276.63 | AN487: =IF(AJ487=1,C487/AM487,"") | AO487: =INDEX('Seasonal Index'!$E$2:$E$53,AI487) -> 1.0352246 | AP487: =IF(AJ487=1,C487/AO487,"") | AQ487: =IF(AJ487=1,A487-Regression!$C$15,0) -> 0 | AR487: =IF(AJ487=1,AK487-Regression!$D$15,0) -> 0 | AS487: =IF(AJ487=1,AL487-Regression!$E$15,0) -> 0 | AT487: =IF(AJ487=1,AP487-Regression!$F$15,0) -> 0 | AU487: =IF(AND(ISNUMBER(AK487),ISNUMBER(AL487)),Regression!$C$38+Regression!$D$38*A487+Regression!$E$38*AK487+Regression!$F$38*AL487,"") -> 10488.98 | AV487: =IF(ISNUMBER(AU487),AU487*AO487,"") -> 10858.45 | AW487: =IF(AJ487=1,"Train",IF(AH487=Inputs!$B$6+1,"Validation",IF(AH487>Inputs!$B$6+1,"Forecast","Not used"))) -> Not used | AX487: =IF(ISNUMBER(C487),C487,IF(ISNUMBER(D487),D487,"")) -> 9075 | AY487: =IF(AND(AW487="Validation",ISNUMBER(AX487),ISNUMBER(AV487)),ABS(AX487-AV487)/AX487,"") | AZ487: =IF(AJ487=1,AP487-AU487,0) -> 0 | BB487: =Regression!$C$45+Regression!$C$46*A487 -> 6902.1963 | BC487: =IF(AND(AH487>=2022,AH487<=2024),C487/BB487,"") | BD487: =INDEX('Seasonal Index'!$H$2:$H$53,AI487) -> 1.0342763 | BE487: =IF(AH487>=2022,BB487*BD487,"") | BF487: =IF(AND(AW487="Validation",ISNUMBER(AX487),ISNUMBER(BE487)),ABS(AX487-BE487)/AX487,"") | BG487: =IF(ISNUMBER(C487),C487,0) -> 9075 | BH487: =IF(ISNUMBER(AY487),AV487-AX487,0) -> 0 | BI487: =IF(ISNUMBER(AY487),BE487-AX487,0) -> 0
A488: 487 | B488: 36679 | C488: 8863 | F488: 280000 | H488: 29.98 | I488: 29.6425 | J488: 1.54 | K488: 10002.179 | L488: 724934 | M488: 773 | N488: 17.939 | O488: 232490 | P488: 6686.5 | Q488: 1553622 | S488: 6119 | V488: 23 | W488: 86.4 | AB488: 279328 | AD488: 1 | AE488: 10.5 | AF488: 50.7 | AH488: =YEAR(B488) -> 2000 | AI488: =MIN(52,INT((B488-DATE(AH488,1,1))/7)+1) -> 22 | AJ488: =IF(AND(ISNUMBER(C488),ISNUMBER(AK488),ISNUMBER(AL488),AH488>=Inputs!$B$5,AH488<=Inputs!$B$6,AH488<>Inputs!$B$7,AH488<>Inputs!$B$8),1,0) -> 0 | AK488: =IF(INDEX($E488:$AF488,Inputs!$C$10)="","",INDEX($E488:$AF488,Inputs!$C$10)) -> 232490 | AL488: =IF(INDEX($E488:$AF488,Inputs!$C$11)="","",INDEX($E488:$AF488,Inputs!$C$11)) -> 280000 | AM488: =Regression!$C$5+Regression!$C$6*A488 -> 10275.457 | AN488: =IF(AJ488=1,C488/AM488,"") | AO488: =INDEX('Seasonal Index'!$E$2:$E$53,AI488) -> 1.0139792 | AP488: =IF(AJ488=1,C488/AO488,"") | AQ488: =IF(AJ488=1,A488-Regression!$C$15,0) -> 0 | AR488: =IF(AJ488=1,AK488-Regression!$D$15,0) -> 0 | AS488: =IF(AJ488=1,AL488-Regression!$E$15,0) -> 0 | AT488: =IF(AJ488=1,AP488-Regression!$F$15,0) -> 0 | AU488: =IF(AND(ISNUMBER(AK488),ISNUMBER(AL488)),Regression!$C$38+Regression!$D$38*A488+Regression!$E$38*AK488+Regression!$F$38*AL488,"") -> 10487.418 | AV488: =IF(ISNUMBER(AU488),AU488*AO488,"") -> 10634.023 | AW488: =IF(AJ488=1,"Train",IF(AH488=Inputs!$B$6+1,"Validation",IF(AH488>Inputs!$B$6+1,"Forecast","Not used"))) -> Not used | AX488: =IF(ISNUMBER(C488),C488,IF(ISNUMBER(D488),D488,"")) -> 8863 | AY488: =IF(AND(AW488="Validation",ISNUMBER(AX488),ISNUMBER(AV488)),ABS(AX488-AV488)/AX488,"") | AZ488: =IF(AJ488=1,AP488-AU488,0) -> 0 | BB488: =Regression!$C$45+Regression!$C$46*A488 -> 6903.7558 | BC488: =IF(AND(AH488>=2022,AH488<=2024),C488/BB488,"") | BD488: =INDEX('Seasonal Index'!$H$2:$H$53,AI488) -> 1.0395595 | BE488: =IF(AH488>=2022,BB488*BD488,"") | BF488: =IF(AND(AW488="Validation",ISNUMBER(AX488),ISNUMBER(BE488)),ABS(AX488-BE488)/AX488,"") | BG488: =IF(ISNUMBER(C488),C488,0) -> 8863 | BH488: =IF(ISNUMBER(AY488),AV488-AX488,0) -> 0 | BI488: =IF(ISNUMBER(AY488),BE488-AX488,0) -> 0
A489: 488 | B489: 36686 | C489: 8403 | F489: 290000 | H489: 29.788 | I489: 28.67 | J489: 1.563 | K489: 10002.179 | L489: 756536 | M489: 805 | N489: 17.939 | O489: 232490 | P489: 6679.1 | Q489: 1553622 | S489: 6119 | V489: 23 | W489: 89.7 | AB489: 279328 | AD489: 0 | AE489: 9.8 | AF489: 42.7 | AH489: =YEAR(B489) -> 2000 | AI489: =MIN(52,INT((B489-DATE(AH489,1,1))/7)+1) -> 23 | AJ489: =IF(AND(ISNUMBER(C489),ISNUMBER(AK489),ISNUMBER(AL489),AH489>=Inputs!$B$5,AH489<=Inputs!$B$6,AH489<>Inputs!$B$7,AH489<>Inputs!$B$8),1,0) -> 0 | AK489: =IF(INDEX($E489:$AF489,Inputs!$C$10)="","",INDEX($E489:$AF489,Inputs!$C$10)) -> 232490 | AL489: =IF(INDEX($E489:$AF489,Inputs!$C$11)="","",INDEX($E489:$AF489,Inputs!$C$11)) -> 290000 | AM489: =Regression!$C$5+Regression!$C$6*A489 -> 10274.285 | AN489: =IF(AJ489=1,C489/AM489,"") | AO489: =INDEX('Seasonal Index'!$E$2:$E$53,AI489) -> 1.0375597 | AP489: =IF(AJ489=1,C489/AO489,"") | AQ489: =IF(AJ489=1,A489-Regression!$C$15,0) -> 0 | AR489: =IF(AJ489=1,AK489-Regression!$D$15,0) -> 0 | AS489: =IF(AJ489=1,AL489-Regression!$E$15,0) -> 0 | AT489: =IF(AJ489=1,AP489-Regression!$F$15,0) -> 0 | AU489: =IF(AND(ISNUMBER(AK489),ISNUMBER(AL489)),Regression!$C$38+Regression!$D$38*A489+Regression!$E$38*AK489+Regression!$F$38*AL489,"") -> 10459.305 | AV489: =IF(ISNUMBER(AU489),AU489*AO489,"") -> 10852.154 | AW489: =IF(AJ489=1,"Train",IF(AH489=Inputs!$B$6+1,"Validation",IF(AH489>Inputs!$B$6+1,"Forecast","Not used"))) -> Not used | AX489: =IF(ISNUMBER(C489),C489,IF(ISNUMBER(D489),D489,"")) -> 8403 | AY489: =IF(AND(AW489="Validation",ISNUMBER(AX489),ISNUMBER(AV489)),ABS(AX489-AV489)/AX489,"") | AZ489: =IF(AJ489=1,AP489-AU489,0) -> 0 | BB489: =Regression!$C$45+Regression!$C$46*A489 -> 6905.3153 | BC489: =IF(AND(AH489>=2022,AH489<=2024),C489/BB489,"") | BD489: =INDEX('Seasonal Index'!$H$2:$H$53,AI489) -> 1.0378993 | BE489: =IF(AH489>=2022,BB489*BD489,"") | BF489: =IF(AND(AW489="Validation",ISNUMBER(AX489),ISNUMBER(BE489)),ABS(AX489-BE489)/AX489,"") | BG489: =IF(ISNUMBER(C489),C489,0) -> 8403 | BH489: =IF(ISNUMBER(AY489),AV489-AX489,0) -> 0 | BI489: =IF(ISNUMBER(AY489),BE489-AX489,0) -> 0
A490: 489 | B490: 36693 | C490: 8895 | F490: 284000 | H490: 32.452 | I490: 29.814 | J490: 1.631 | K490: 10002.179 | L490: 756536 | M490: 805 | N490: 17.943 | O490: 227698 | P490: 6679.1 | Q490: 1584412 | S490: 6119 | V490: 23 | W490: 89.7 | AB490: 279328 | AD490: 0 | AE490: 2.6 | AF490: 73.2 | AH490: =YEAR(B490) -> 2000 | AI490: =MIN(52,INT((B490-DATE(AH490,1,1))/7)+1) -> 24 | AJ490: =IF(AND(ISNUMBER(C490),ISNUMBER(AK490),ISNUMBER(AL490),AH490>=Inputs!$B$5,AH490<=Inputs!$B$6,AH490<>Inputs!$B$7,AH490<>Inputs!$B$8),1,0) -> 0 | AK490: =IF(INDEX($E490:$AF490,Inputs!$C$10)="","",INDEX($E490:$AF490,Inputs!$C$10)) -> 227698 | AL490: =IF(INDEX($E490:$AF490,Inputs!$C$11)="","",INDEX($E490:$AF490,Inputs!$C$11)) -> 284000 | AM490: =Regression!$C$5+Regression!$C$6*A490 -> 10273.112 | AN490: =IF(AJ490=1,C490/AM490,"") | AO490: =INDEX('Seasonal Index'!$E$2:$E$53,AI490) -> 1.0344513 | AP490: =IF(AJ490=1,C490/AO490,"") | AQ490: =IF(AJ490=1,A490-Regression!$C$15,0) -> 0 | AR490: =IF(AJ490=1,AK490-Regression!$D$15,0) -> 0 | AS490: =IF(AJ490=1,AL490-Regression!$E$15,0) -> 0 | AT490: =IF(AJ490=1,AP490-Regression!$F$15,0) -> 0 | AU490: =IF(AND(ISNUMBER(AK490),ISNUMBER(AL490)),Regression!$C$38+Regression!$D$38*A490+Regression!$E$38*AK490+Regression!$F$38*AL490,"") -> 10464.929 | AV490: =IF(ISNUMBER(AU490),AU490*AO490,"") -> 10825.46 | AW490: =IF(AJ490=1,"Train",IF(AH490=Inputs!$B$6+1,"Validation",IF(AH490>Inputs!$B$6+1,"Forecast","Not used"))) -> Not used | AX490: =IF(ISNUMBER(C490),C490,IF(ISNUMBER(D490),D490,"")) -> 8895 | AY490: =IF(AND(AW490="Validation",ISNUMBER(AX490),ISNUMBER(AV490)),ABS(AX490-AV490)/AX490,"") | AZ490: =IF(AJ490=1,AP490-AU490,0) -> 0 | BB490: =Regression!$C$45+Regression!$C$46*A490 -> 6906.8748 | BC490: =IF(AND(AH490>=2022,AH490<=2024),C490/BB490,"") | BD490: =INDEX('Seasonal Index'!$H$2:$H$53,AI490) -> 1.0351081 | BE490: =IF(AH490>=2022,BB490*BD490,"") | BF490: =IF(AND(AW490="Validation",ISNUMBER(AX490),ISNUMBER(BE490)),ABS(AX490-BE490)/AX490,"") | BG490: =IF(ISNUMBER(C490),C490,0) -> 8895 | BH490: =IF(ISNUMBER(AY490),AV490-AX490,0) -> 0 | BI490: =IF(ISNUMBER(AY490),BE490-AX490,0) -> 0
A491: 490 | B491: 36700 | C491: 8475 | F491: 294000 | H491: 33.552 | I491: 29.778 | J491: 1.681 | K491: 10002.179 | L491: 756536 | M491: 805 | N491: 17.943 | O491: 227698 | P491: 6679.1 | Q491: 1584412 | S491: 6119 | V491: 23 | W491: 89.7 | AB491: 279328 | AD491: 0 | AE491: 0.5 | AF491: 66.9 | AH491: =YEAR(B491) -> 2000 | AI491: =MIN(52,INT((B491-DATE(AH491,1,1))/7)+1) -> 25 | AJ491: =IF(AND(ISNUMBER(C491),ISNUMBER(AK491),ISNUMBER(AL491),AH491>=Inputs!$B$5,AH491<=Inputs!$B$6,AH491<>Inputs!$B$7,AH491<>Inputs!$B$8),1,0) -> 0 | AK491: =IF(INDEX($E491:$AF491,Inputs!$C$10)="","",INDEX($E491:$AF491,Inputs!$C$10)) -> 227698 | AL491: =IF(INDEX($E491:$AF491,Inputs!$C$11)="","",INDEX($E491:$AF491,Inputs!$C$11)) -> 294000 | AM491: =Regression!$C$5+Regression!$C$6*A491 -> 10271.939 | AN491: =IF(AJ491=1,C491/AM491,"") | AO491: =INDEX('Seasonal Index'!$E$2:$E$53,AI491) -> 1.0360607 | AP491: =IF(AJ491=1,C491/AO491,"") | AQ491: =IF(AJ491=1,A491-Regression!$C$15,0) -> 0 | AR491: =IF(AJ491=1,AK491-Regression!$D$15,0) -> 0 | AS491: =IF(AJ491=1,AL491-Regression!$E$15,0) -> 0 | AT491: =IF(AJ491=1,AP491-Regression!$F$15,0) -> 0 | AU491: =IF(AND(ISNUMBER(AK491),ISNUMBER(AL491)),Regression!$C$38+Regression!$D$38*A491+Regression!$E$38*AK491+Regression!$F$38*AL491,"") -> 10436.817 | AV491: =IF(ISNUMBER(AU491),AU491*AO491,"") -> 10813.175 | AW491: =IF(AJ491=1,"Train",IF(AH491=Inputs!$B$6+1,"Validation",IF(AH491>Inputs!$B$6+1,"Forecast","Not used"))) -> Not used | AX491: =IF(ISNUMBER(C491),C491,IF(ISNUMBER(D491),D491,"")) -> 8475 | AY491: =IF(AND(AW491="Validation",ISNUMBER(AX491),ISNUMBER(AV491)),ABS(AX491-AV491)/AX491,"") | AZ491: =IF(AJ491=1,AP491-AU491,0) -> 0 | BB491: =Regression!$C$45+Regression!$C$46*A491 -> 6908.4343 | BC491: =IF(AND(AH491>=2022,AH491<=2024),C491/BB491,"") | BD491: =INDEX('Seasonal Index'!$H$2:$H$53,AI491) -> 1.0325971 | BE491: =IF(AH491>=2022,BB491*BD491,"") | BF491: =IF(AND(AW491="Validation",ISNUMBER(AX491),ISNUMBER(BE491)),ABS(AX491-BE491)/AX491,"") | BG491: =IF(ISNUMBER(C491),C491,0) -> 8475 | BH491: =IF(ISNUMBER(AY491),AV491-AX491,0) -> 0 | BI491: =IF(ISNUMBER(AY491),BE491-AX491,0) -> 0
A492: 491 | B492: 36707 | C492: 8620 | F492: 296000 | H492: 32.12 | I492: 31.03 | J492: 1.658 | K492: 10002.179 | L492: 756536 | M492: 805 | N492: 17.943 | O492: 227698 | P492: 6679.1 | Q492: 1584412 | S492: 6119 | V492: 23 | W492: 89.7 | AB492: 279328 | AD492: 0 | AE492: 0 | AF492: 77.9 | AH492: =YEAR(B492) -> 2000 | AI492: =MIN(52,INT((B492-DATE(AH492,1,1))/7)+1) -> 26 | AJ492: =IF(AND(ISNUMBER(C492),ISNUMBER(AK492),ISNUMBER(AL492),AH492>=Inputs!$B$5,AH492<=Inputs!$B$6,AH492<>Inputs!$B$7,AH492<>Inputs!$B$8),1,0) -> 0 | AK492: =IF(INDEX($E492:$AF492,Inputs!$C$10)="","",INDEX($E492:$AF492,Inputs!$C$10)) -> 227698 | AL492: =IF(INDEX($E492:$AF492,Inputs!$C$11)="","",INDEX($E492:$AF492,Inputs!$C$11)) -> 296000 | AM492: =Regression!$C$5+Regression!$C$6*A492 -> 10270.767 | AN492: =IF(AJ492=1,C492/AM492,"") | AO492: =INDEX('Seasonal Index'!$E$2:$E$53,AI492) -> 1.057751 | AP492: =IF(AJ492=1,C492/AO492,"") | AQ492: =IF(AJ492=1,A492-Regression!$C$15,0) -> 0 | AR492: =IF(AJ492=1,AK492-Regression!$D$15,0) -> 0 | AS492: =IF(AJ492=1,AL492-Regression!$E$15,0) -> 0 | AT492: =IF(AJ492=1,AP492-Regression!$F$15,0) -> 0 | AU492: =IF(AND(ISNUMBER(AK492),ISNUMBER(AL492)),Regression!$C$38+Regression!$D$38*A492+Regression!$E$38*AK492+Regression!$F$38*AL492,"") -> 10429.944 | AV492: =IF(ISNUMBER(AU492),AU492*AO492,"") -> 11032.284 | AW492: =IF(AJ492=1,"Train",IF(AH492=Inputs!$B$6+1,"Validation",IF(AH492>Inputs!$B$6+1,"Forecast","Not used"))) -> Not used | AX492: =IF(ISNUMBER(C492),C492,IF(ISNUMBER(D492),D492,"")) -> 8620 | AY492: =IF(AND(AW492="Validation",ISNUMBER(AX492),ISNUMBER(AV492)),ABS(AX492-AV492)/AX492,"") | AZ492: =IF(AJ492=1,AP492-AU492,0) -> 0 | BB492: =Regression!$C$45+Regression!$C$46*A492 -> 6909.9938 | BC492: =IF(AND(AH492>=2022,AH492<=2024),C492/BB492,"") | BD492: =INDEX('Seasonal Index'!$H$2:$H$53,AI492) -> 1.0794606 | BE492: =IF(AH492>=2022,BB492*BD492,"") | BF492: =IF(AND(AW492="Validation",ISNUMBER(AX492),ISNUMBER(BE492)),ABS(AX492-BE492)/AX492,"") | BG492: =IF(ISNUMBER(C492),C492,0) -> 8620 | BH492: =IF(ISNUMBER(AY492),AV492-AX492,0) -> 0 | BI492: =IF(ISNUMBER(AY492),BE492-AX492,0) -> 0
A493: 492 | B493: 36714 | C493: 8519 | F493: 281000 | H493: 30.403333 | I493: 30.904 | J493: 1.625 | K493: 10002.179 | L493: 756536 | M493: 844 | N493: 17.943 | O493: 227698 | P493: 6709.7 | Q493: 1584412 | S493: 6119 | V493: 23 | W493: 92.6 | AB493: 279328 | AD493: 1 | AE493: 0 | AF493: 78.3 | AH493: =YEAR(B493) -> 2000 | AI493: =MIN(52,INT((B493-DATE(AH493,1,1))/7)+1) -> 27 | AJ493: =IF(AND(ISNUMBER(C493),ISNUMBER(AK493),ISNUMBER(AL493),AH493>=Inputs!$B$5,AH493<=Inputs!$B$6,AH493<>Inputs!$B$7,AH493<>Inputs!$B$8),1,0) -> 0 | AK493: =IF(INDEX($E493:$AF493,Inputs!$C$10)="","",INDEX($E493:$AF493,Inputs!$C$10)) -> 227698 | AL493: =IF(INDEX($E493:$AF493,Inputs!$C$11)="","",INDEX($E493:$AF493,Inputs!$C$11)) -> 281000 | AM493: =Regression!$C$5+Regression!$C$6*A493 -> 10269.594 | AN493: =IF(AJ493=1,C493/AM493,"") | AO493: =INDEX('Seasonal Index'!$E$2:$E$53,AI493) -> 1.0212619 | AP493: =IF(AJ493=1,C493/AO493,"") | AQ493: =IF(AJ493=1,A493-Regression!$C$15,0) -> 0 | AR493: =IF(AJ493=1,AK493-Regression!$D$15,0) -> 0 | AS493: =IF(AJ493=1,AL493-Regression!$E$15,0) -> 0 | AT493: =IF(AJ493=1,AP493-Regression!$F$15,0) -> 0 | AU493: =IF(AND(ISNUMBER(AK493),ISNUMBER(AL493)),Regression!$C$38+Regression!$D$38*A493+Regression!$E$38*AK493+Regression!$F$38*AL493,"") -> 10468.207 | AV493: =IF(ISNUMBER(AU493),AU493*AO493,"") -> 10690.781 | AW493: =IF(AJ493=1,"Train",IF(AH493=Inputs!$B$6+1,"Validation",IF(AH493>Inputs!$B$6+1,"Forecast","Not used"))) -> Not used | AX493: =IF(ISNUMBER(C493),C493,IF(ISNUMBER(D493),D493,"")) -> 8519 | AY493: =IF(AND(AW493="Validation",ISNUMBER(AX493),ISNUMBER(AV493)),ABS(AX493-AV493)/AX493,"") | AZ493: =IF(AJ493=1,AP493-AU493,0) -> 0 | BB493: =Regression!$C$45+Regression!$C$46*A493 -> 6911.5533 | BC493: =IF(AND(AH493>=2022,AH493<=2024),C493/BB493,"") | BD493: =INDEX('Seasonal Index'!$H$2:$H$53,AI493) -> 0.99454601 | BE493: =IF(AH493>=2022,BB493*BD493,"") | BF493: =IF(AND(AW493="Validation",ISNUMBER(AX493),ISNUMBER(BE493)),ABS(AX493-BE493)/AX493,"") | BG493: =IF(ISNUMBER(C493),C493,0) -> 8519 | BH493: =IF(ISNUMBER(AY493),AV493-AX493,0) -> 0 | BI493: =IF(ISNUMBER(AY493),BE493-AX493,0) -> 0
A494: 493 | B494: 36721 | C494: 8844 | F494: 293000 | H494: 30.436 | I494: 30.53 | J494: 1.593 | K494: 10002.179 | L494: 843730 | M494: 844 | N494: 17.943 | O494: 227698 | P494: 6709.7 | Q494: 1584412 | S494: 6119 | V494: 23 | W494: 92.6 | AB494: 279328 | AD494: 0 | AE494: 0 | AF494: 88.6 | AH494: =YEAR(B494) -> 2000 | AI494: =MIN(52,INT((B494-DATE(AH494,1,1))/7)+1) -> 28 | AJ494: =IF(AND(ISNUMBER(C494),ISNUMBER(AK494),ISNUMBER(AL494),AH494>=Inputs!$B$5,AH494<=Inputs!$B$6,AH494<>Inputs!$B$7,AH494<>Inputs!$B$8),1,0) -> 0 | AK494: =IF(INDEX($E494:$AF494,Inputs!$C$10)="","",INDEX($E494:$AF494,Inputs!$C$10)) -> 227698 | AL494: =IF(INDEX($E494:$AF494,Inputs!$C$11)="","",INDEX($E494:$AF494,Inputs!$C$11)) -> 293000 | AM494: =Regression!$C$5+Regression!$C$6*A494 -> 10268.421 | AN494: =IF(AJ494=1,C494/AM494,"") | AO494: =INDEX('Seasonal Index'!$E$2:$E$53,AI494) -> 1.013509 | AP494: =IF(AJ494=1,C494/AO494,"") | AQ494: =IF(AJ494=1,A494-Regression!$C$15,0) -> 0 | AR494: =IF(AJ494=1,AK494-Regression!$D$15,0) -> 0 | AS494: =IF(AJ494=1,AL494-Regression!$E$15,0) -> 0 | AT494: =IF(AJ494=1,AP494-Regression!$F$15,0) -> 0 | AU494: =IF(AND(ISNUMBER(AK494),ISNUMBER(AL494)),Regression!$C$38+Regression!$D$38*A494+Regression!$E$38*AK494+Regression!$F$38*AL494,"") -> 10434.785 | AV494: =IF(ISNUMBER(AU494),AU494*AO494,"") -> 10575.748 | AW494: =IF(AJ494=1,"Train",IF(AH494=Inputs!$B$6+1,"Validation",IF(AH494>Inputs!$B$6+1,"Forecast","Not used"))) -> Not used | AX494: =IF(ISNUMBER(C494),C494,IF(ISNUMBER(D494),D494,"")) -> 8844 | AY494: =IF(AND(AW494="Validation",ISNUMBER(AX494),ISNUMBER(AV494)),ABS(AX494-AV494)/AX494,"") | AZ494: =IF(AJ494=1,AP494-AU494,0) -> 0 | BB494: =Regression!$C$45+Regression!$C$46*A494 -> 6913.1128 | BC494: =IF(AND(AH494>=2022,AH494<=2024),C494/BB494,"") | BD494: =INDEX('Seasonal Index'!$H$2:$H$53,AI494) -> 0.99258236 | BE494: =IF(AH494>=2022,BB494*BD494,"") | BF494: =IF(AND(AW494="Validation",ISNUMBER(AX494),ISNUMBER(BE494)),ABS(AX494-BE494)/AX494,"") | BG494: =IF(ISNUMBER(C494),C494,0) -> 8844 | BH494: =IF(ISNUMBER(AY494),AV494-AX494,0) -> 0 | BI494: =IF(ISNUMBER(AY494),BE494-AX494,0) -> 0
A495: 494 | B495: 36728 | C495: 8361 | F495: 303000 | H495: 30.65 | I495: 27.952 | J495: 1.546 | K495: 10002.179 | L495: 843730 | M495: 844 | N495: 17.596 | O495: 242501 | P495: 6709.7 | Q495: 1584412 | S495: 6119 | V495: 23 | W495: 92.6 | AB495: 279328 | AD495: 0 | AE495: 0 | AF495: 89.7 | AH495: =YEAR(B495) -> 2000 | AI495: =MIN(52,INT((B495-DATE(AH495,1,1))/7)+1) -> 29 | AJ495: =IF(AND(ISNUMBER(C495),ISNUMBER(AK495),ISNUMBER(AL495),AH495>=Inputs!$B$5,AH495<=Inputs!$B$6,AH495<>Inputs!$B$7,AH495<>Inputs!$B$8),1,0) -> 0 | AK495: =IF(INDEX($E495:$AF495,Inputs!$C$10)="","",INDEX($E495:$AF495,Inputs!$C$10)) -> 242501 | AL495: =IF(INDEX($E495:$AF495,Inputs!$C$11)="","",INDEX($E495:$AF495,Inputs!$C$11)) -> 303000 | AM495: =Regression!$C$5+Regression!$C$6*A495 -> 10267.249 | AN495: =IF(AJ495=1,C495/AM495,"") | AO495: =INDEX('Seasonal Index'!$E$2:$E$53,AI495) -> 1.0519567 | AP495: =IF(AJ495=1,C495/AO495,"") | AQ495: =IF(AJ495=1,A495-Regression!$C$15,0) -> 0 | AR495: =IF(AJ495=1,AK495-Regression!$D$15,0) -> 0 | AS495: =IF(AJ495=1,AL495-Regression!$E$15,0) -> 0 | AT495: =IF(AJ495=1,AP495-Regression!$F$15,0) -> 0 | AU495: =IF(AND(ISNUMBER(AK495),ISNUMBER(AL495)),Regression!$C$38+Regression!$D$38*A495+Regression!$E$38*AK495+Regression!$F$38*AL495,"") -> 10433.683 | AV495: =IF(ISNUMBER(AU495),AU495*AO495,"") -> 10975.782 | AW495: =IF(AJ495=1,"Train",IF(AH495=Inputs!$B$6+1,"Validation",IF(AH495>Inputs!$B$6+1,"Forecast","Not used"))) -> Not used | AX495: =IF(ISNUMBER(C495),C495,IF(ISNUMBER(D495),D495,"")) -> 8361 | AY495: =IF(AND(AW495="Validation",ISNUMBER(AX495),ISNUMBER(AV495)),ABS(AX495-AV495)/AX495,"") | AZ495: =IF(AJ495=1,AP495-AU495,0) -> 0 | BB495: =Regression!$C$45+Regression!$C$46*A495 -> 6914.6723 | BC495: =IF(AND(AH495>=2022,AH495<=2024),C495/BB495,"") | BD495: =INDEX('Seasonal Index'!$H$2:$H$53,AI495) -> 1.048616 | BE495: =IF(AH495>=2022,BB495*BD495,"") | BF495: =IF(AND(AW495="Validation",ISNUMBER(AX495),ISNUMBER(BE495)),ABS(AX495-BE495)/AX495,"") | BG495: =IF(ISNUMBER(C495),C495,0) -> 8361 | BH495: =IF(ISNUMBER(AY495),AV495-AX495,0) -> 0 | BI495: =IF(ISNUMBER(AY495),BE495-AX495,0) -> 0
A496: 495 | B496: 36735 | C496: 8614 | F496: 300000 | H496: 28.02 | I496: 26.02 | J496: 1.52 | K496: 10002.179 | L496: 843730 | M496: 844 | N496: 17.596 | O496: 242501 | P496: 6709.7 | Q496: 1584412 | S496: 6119 | V496: 23 | W496: 92.6 | AB496: 279328 | AD496: 0 | AE496: 0 | AF496: 76.2 | AH496: =YEAR(B496) -> 2000 | AI496: =MIN(52,INT((B496-DATE(AH496,1,1))/7)+1) -> 30 | AJ496: =IF(AND(ISNUMBER(C496),ISNUMBER(AK496),ISNUMBER(AL496),AH496>=Inputs!$B$5,AH496<=Inputs!$B$6,AH496<>Inputs!$B$7,AH496<>Inputs!$B$8),1,0) -> 0 | AK496: =IF(INDEX($E496:$AF496,Inputs!$C$10)="","",INDEX($E496:$AF496,Inputs!$C$10)) -> 242501 | AL496: =IF(INDEX($E496:$AF496,Inputs!$C$11)="","",INDEX($E496:$AF496,Inputs!$C$11)) -> 300000 | AM496: =Regression!$C$5+Regression!$C$6*A496 -> 10266.076 | AN496: =IF(AJ496=1,C496/AM496,"") | AO496: =INDEX('Seasonal Index'!$E$2:$E$53,AI496) -> 1.031713 | AP496: =IF(AJ496=1,C496/AO496,"") | AQ496: =IF(AJ496=1,A496-Regression!$C$15,0) -> 0 | AR496: =IF(AJ496=1,AK496-Regression!$D$15,0) -> 0 | AS496: =IF(AJ496=1,AL496-Regression!$E$15,0) -> 0 | AT496: =IF(AJ496=1,AP496-Regression!$F$15,0) -> 0 | AU496: =IF(AND(ISNUMBER(AK496),ISNUMBER(AL496)),Regression!$C$38+Regression!$D$38*A496+Regression!$E$38*AK496+Regression!$F$38*AL496,"") -> 10440.085 | AV496: =IF(ISNUMBER(AU496),AU496*AO496,"") -> 10771.172 | AW496: =IF(AJ496=1,"Train",IF(AH496=Inputs!$B$6+1,"Validation",IF(AH496>Inputs!$B$6+1,"Forecast","Not used"))) -> Not used | AX496: =IF(ISNUMBER(C496),C496,IF(ISNUMBER(D496),D496,"")) -> 8614 | AY496: =IF(AND(AW496="Validation",ISNUMBER(AX496),ISNUMBER(AV496)),ABS(AX496-AV496)/AX496,"") | AZ496: =IF(AJ496=1,AP496-AU496,0) -> 0 | BB496: =Regression!$C$45+Regression!$C$46*A496 -> 6916.2318 | BC496: =IF(AND(AH496>=2022,AH496<=2024),C496/BB496,"") | BD496: =INDEX('Seasonal Index'!$H$2:$H$53,AI496) -> 1.0099032 | BE496: =IF(AH496>=2022,BB496*BD496,"") | BF496: =IF(AND(AW496="Validation",ISNUMBER(AX496),ISNUMBER(BE496)),ABS(AX496-BE496)/AX496,"") | BG496: =IF(ISNUMBER(C496),C496,0) -> 8614 | BH496: =IF(ISNUMBER(AY496),AV496-AX496,0) -> 0 | BI496: =IF(ISNUMBER(AY496),BE496-AX496,0) -> 0
... A536: 535 | B536: 37015 | C536: 8665 | F536: 406000 | H536: 28.362 | I536: 27.278 | J536: 1.626 | K536: 10435.744 | L536: 755040 | M536: 1136 | N536: 17.248 | O536: 200876 | P536: 7001.8 | Q536: 1741267 | S536: 8007 | V536: 25 | W536: 90.2 | AB536: 282398 | AD536: 0 | AE536: 18.3 | AF536: 17.4 | AH536: =YEAR(B536) -> 2001 | AI536: =MIN(52,INT((B536-DATE(AH536,1,1))/7)+1) -> 18 | AJ536: =IF(AND(ISNUMBER(C536),ISNUMBER(AK536),ISNUMBER(AL536),AH536>=Inputs!$B$5,AH536<=Inputs!$B$6,AH536<>Inputs!$B$7,AH536<>Inputs!$B$8),1,0) -> 0 | AK536: =IF(INDEX($E536:$AF536,Inputs!$C$10)="","",INDEX($E536:$AF536,Inputs!$C$10)) -> 200876 | AL536: =IF(INDEX($E536:$AF536,Inputs!$C$11)="","",INDEX($E536:$AF536,Inputs!$C$11)) -> 406000 | AM536: =Regression!$C$5+Regression!$C$6*A536 -> 10219.169 | AN536: =IF(AJ536=1,C536/AM536,"") | AO536: =INDEX('Seasonal Index'!$E$2:$E$53,AI536) -> 1.0181402 | AP536: =IF(AJ536=1,C536/AO536,"") | AQ536: =IF(AJ536=1,A536-Regression!$C$15,0) -> 0 | AR536: =IF(AJ536=1,AK536-Regression!$D$15,0) -> 0 | AS536: =IF(AJ536=1,AL536-Regression!$E$15,0) -> 0 | AT536: =IF(AJ536=1,AP536-Regression!$F$15,0) -> 0 | AU536: =IF(AND(ISNUMBER(AK536),ISNUMBER(AL536)),Regression!$C$38+Regression!$D$38*A536+Regression!$E$38*AK536+Regression!$F$38*AL536,"") -> 10020.207 | AV536: =IF(ISNUMBER(AU536),AU536*AO536,"") -> 10201.975 | AW536: =IF(AJ536=1,"Train",IF(AH536=Inputs!$B$6+1,"Validation",IF(AH536>Inputs!$B$6+1,"Forecast","Not used"))) -> Not used | AX536: =IF(ISNUMBER(C536),C536,IF(ISNUMBER(D536),D536,"")) -> 8665 | AY536: =IF(AND(AW536="Validation",ISNUMBER(AX536),ISNUMBER(AV536)),ABS(AX536-AV536)/AX536,"") | AZ536: =IF(AJ536=1,AP536-AU536,0) -> 0 | BB536: =Regression!$C$45+Regression!$C$46*A536 -> 6978.6118 | BC536: =IF(AND(AH536>=2022,AH536<=2024),C536/BB536,"") | BD536: =INDEX('Seasonal Index'!$H$2:$H$53,AI536) -> 1.0188494 | BE536: =IF(AH536>=2022,BB536*BD536,"") | BF536: =IF(AND(AW536="Validation",ISNUMBER(AX536),ISNUMBER(BE536)),ABS(AX536-BE536)/AX536,"") | BG536: =IF(ISNUMBER(C536),C536,0) -> 8665 | BH536: =IF(ISNUMBER(AY536),AV536-AX536,0) -> 0 | BI536: =IF(ISNUMBER(AY536),BE536-AX536,0) -> 0
A537: 536 | B537: 37022 | C537: 8275 | F537: 381000 | H537: 28.124 | I537: 27.772 | J537: 1.703 | K537: 10470.231 | L537: 755040 | M537: 1163 | N537: 17.248 | O537: 200876 | P537: 6996.7 | Q537: 1741267 | S537: 8007 | U537: 84.7 | V537: 25 | W537: 90.5 | AB537: 282398 | AD537: 0 | AE537: 15.2 | AF537: 26.6 | AH537: =YEAR(B537) -> 2001 | AI537: =MIN(52,INT((B537-DATE(AH537,1,1))/7)+1) -> 19 | AJ537: =IF(AND(ISNUMBER(C537),ISNUMBER(AK537),ISNUMBER(AL537),AH537>=Inputs!$B$5,AH537<=Inputs!$B$6,AH537<>Inputs!$B$7,AH537<>Inputs!$B$8),1,0) -> 0 | AK537: =IF(INDEX($E537:$AF537,Inputs!$C$10)="","",INDEX($E537:$AF537,Inputs!$C$10)) -> 200876 | AL537: =IF(INDEX($E537:$AF537,Inputs!$C$11)="","",INDEX($E537:$AF537,Inputs!$C$11)) -> 381000 | AM537: =Regression!$C$5+Regression!$C$6*A537 -> 10217.996 | AN537: =IF(AJ537=1,C537/AM537,"") | AO537: =INDEX('Seasonal Index'!$E$2:$E$53,AI537) -> 1.0133712 | AP537: =IF(AJ537=1,C537/AO537,"") | AQ537: =IF(AJ537=1,A537-Regression!$C$15,0) -> 0 | AR537: =IF(AJ537=1,AK537-Regression!$D$15,0) -> 0 | AS537: =IF(AJ537=1,AL537-Regression!$E$15,0) -> 0 | AT537: =IF(AJ537=1,AP537-Regression!$F$15,0) -> 0 | AU537: =IF(AND(ISNUMBER(AK537),ISNUMBER(AL537)),Regression!$C$38+Regression!$D$38*A537+Regression!$E$38*AK537+Regression!$F$38*AL537,"") -> 10085.02 | AV537: =IF(ISNUMBER(AU537),AU537*AO537,"") -> 10219.869 | AW537: =IF(AJ537=1,"Train",IF(AH537=Inputs!$B$6+1,"Validation",IF(AH537>Inputs!$B$6+1,"Forecast","Not used"))) -> Not used | AX537: =IF(ISNUMBER(C537),C537,IF(ISNUMBER(D537),D537,"")) -> 8275 | AY537: =IF(AND(AW537="Validation",ISNUMBER(AX537),ISNUMBER(AV537)),ABS(AX537-AV537)/AX537,"") | AZ537: =IF(AJ537=1,AP537-AU537,0) -> 0 | BB537: =Regression!$C$45+Regression!$C$46*A537 -> 6980.1713 | BC537: =IF(AND(AH537>=2022,AH537<=2024),C537/BB537,"") | BD537: =INDEX('Seasonal Index'!$H$2:$H$53,AI537) -> 1.0190604 | BE537: =IF(AH537>=2022,BB537*BD537,"") | BF537: =IF(AND(AW537="Validation",ISNUMBER(AX537),ISNUMBER(BE537)),ABS(AX537-BE537)/AX537,"") | BG537: =IF(ISNUMBER(C537),C537,0) -> 8275 | BH537: =IF(ISNUMBER(AY537),AV537-AX537,0) -> 0 | BI537: =IF(ISNUMBER(AY537),BE537-AX537,0) -> 0
A538: 537 | B538: 37029 | C538: 8917 | F538: 390000 | H538: 29.084 | I538: 28.342 | J538: 1.713 | K538: 10470.231 | L538: 800293 | M538: 1163 | N538: 16.872 | O538: 232587 | P538: 6996.7 | Q538: 1741267 | S538: 8007 | U538: 84.7 | V538: 25 | W538: 90.5 | AB538: 282398 | AD538: 0 | AE538: 18.7 | AF538: 27.5 | AH538: =YEAR(B538) -> 2001 | AI538: =MIN(52,INT((B538-DATE(AH538,1,1))/7)+1) -> 20 | AJ538: =IF(AND(ISNUMBER(C538),ISNUMBER(AK538),ISNUMBER(AL538),AH538>=Inputs!$B$5,AH538<=Inputs!$B$6,AH538<>Inputs!$B$7,AH538<>Inputs!$B$8),1,0) -> 0 | AK538: =IF(INDEX($E538:$AF538,Inputs!$C$10)="","",INDEX($E538:$AF538,Inputs!$C$10)) -> 232587 | AL538: =IF(INDEX($E538:$AF538,Inputs!$C$11)="","",INDEX($E538:$AF538,Inputs!$C$11)) -> 390000 | AM538: =Regression!$C$5+Regression!$C$6*A538 -> 10216.824 | AN538: =IF(AJ538=1,C538/AM538,"") | AO538: =INDEX('Seasonal Index'!$E$2:$E$53,AI538) -> 1.0355119 | AP538: =IF(AJ538=1,C538/AO538,"") | AQ538: =IF(AJ538=1,A538-Regression!$C$15,0) -> 0 | AR538: =IF(AJ538=1,AK538-Regression!$D$15,0) -> 0 | AS538: =IF(AJ538=1,AL538-Regression!$E$15,0) -> 0 | AT538: =IF(AJ538=1,AP538-Regression!$F$15,0) -> 0 | AU538: =IF(AND(ISNUMBER(AK538),ISNUMBER(AL538)),Regression!$C$38+Regression!$D$38*A538+Regression!$E$38*AK538+Regression!$F$38*AL538,"") -> 10117.425 | AV538: =IF(ISNUMBER(AU538),AU538*AO538,"") -> 10476.714 | AW538: =IF(AJ538=1,"Train",IF(AH538=Inputs!$B$6+1,"Validation",IF(AH538>Inputs!$B$6+1,"Forecast","Not used"))) -> Not used | AX538: =IF(ISNUMBER(C538),C538,IF(ISNUMBER(D538),D538,"")) -> 8917 | AY538: =IF(AND(AW538="Validation",ISNUMBER(AX538),ISNUMBER(AV538)),ABS(AX538-AV538)/AX538,"") | AZ538: =IF(AJ538=1,AP538-AU538,0) -> 0 | BB538: =Regression!$C$45+Regression!$C$46*A538 -> 6981.7308 | BC538: =IF(AND(AH538>=2022,AH538<=2024),C538/BB538,"") | BD538: =INDEX('Seasonal Index'!$H$2:$H$53,AI538) -> 1.0467645 | BE538: =IF(AH538>=2022,BB538*BD538,"") | BF538: =IF(AND(AW538="Validation",ISNUMBER(AX538),ISNUMBER(BE538)),ABS(AX538-BE538)/AX538,"") | BG538: =IF(ISNUMBER(C538),C538,0) -> 8917 | BH538: =IF(ISNUMBER(AY538),AV538-AX538,0) -> 0 | BI538: =IF(ISNUMBER(AY538),BE538-AX538,0) -> 0
A539: 538 | B539: 37036 | C539: 8270 | F539: 402000 | H539: 28.922 | I539: 29.314 | J539: 1.687 | K539: 10470.231 | L539: 800293 | M539: 1163 | N539: 16.872 | O539: 232587 | P539: 6996.7 | Q539: 1741267 | S539: 8007 | U539: 84.7 | V539: 25 | W539: 90.5 | AB539: 282398 | AD539: 0 | AE539: 20.2 | AF539: 27.9 | AH539: =YEAR(B539) -> 2001 | AI539: =MIN(52,INT((B539-DATE(AH539,1,1))/7)+1) -> 21 | AJ539: =IF(AND(ISNUMBER(C539),ISNUMBER(AK539),ISNUMBER(AL539),AH539>=Inputs!$B$5,AH539<=Inputs!$B$6,AH539<>Inputs!$B$7,AH539<>Inputs!$B$8),1,0) -> 0 | AK539: =IF(INDEX($E539:$AF539,Inputs!$C$10)="","",INDEX($E539:$AF539,Inputs!$C$10)) -> 232587 | AL539: =IF(INDEX($E539:$AF539,Inputs!$C$11)="","",INDEX($E539:$AF539,Inputs!$C$11)) -> 402000 | AM539: =Regression!$C$5+Regression!$C$6*A539 -> 10215.651 | AN539: =IF(AJ539=1,C539/AM539,"") | AO539: =INDEX('Seasonal Index'!$E$2:$E$53,AI539) -> 1.0352246 | AP539: =IF(AJ539=1,C539/AO539,"") | AQ539: =IF(AJ539=1,A539-Regression!$C$15,0) -> 0 | AR539: =IF(AJ539=1,AK539-Regression!$D$15,0) -> 0 | AS539: =IF(AJ539=1,AL539-Regression!$E$15,0) -> 0 | AT539: =IF(AJ539=1,AP539-Regression!$F$15,0) -> 0 | AU539: =IF(AND(ISNUMBER(AK539),ISNUMBER(AL539)),Regression!$C$38+Regression!$D$38*A539+Regression!$E$38*AK539+Regression!$F$38*AL539,"") -> 10084.002 | AV539: =IF(ISNUMBER(AU539),AU539*AO539,"") -> 10439.207 | AW539: =IF(AJ539=1,"Train",IF(AH539=Inputs!$B$6+1,"Validation",IF(AH539>Inputs!$B$6+1,"Forecast","Not used"))) -> Not used | AX539: =IF(ISNUMBER(C539),C539,IF(ISNUMBER(D539),D539,"")) -> 8270 | AY539: =IF(AND(AW539="Validation",ISNUMBER(AX539),ISNUMBER(AV539)),ABS(AX539-AV539)/AX539,"") | AZ539: =IF(AJ539=1,AP539-AU539,0) -> 0 | BB539: =Regression!$C$45+Regression!$C$46*A539 -> 6983.2903 | BC539: =IF(AND(AH539>=2022,AH539<=2024),C539/BB539,"") | BD539: =INDEX('Seasonal Index'!$H$2:$H$53,AI539) -> 1.0342763 | BE539: =IF(AH539>=2022,BB539*BD539,"") | BF539: =IF(AND(AW539="Validation",ISNUMBER(AX539),ISNUMBER(BE539)),ABS(AX539-BE539)/AX539,"") | BG539: =IF(ISNUMBER(C539),C539,0) -> 8270 | BH539: =IF(ISNUMBER(AY539),AV539-AX539,0) -> 0 | BI539: =IF(ISNUMBER(AY539),BE539-AX539,0) -> 0
A540: 539 | B540: 37043 | C540: 8809 | F540: 405000 | H540: 28.435 | I540: 28.86 | J540: 1.704 | K540: 10470.231 | L540: 800293 | M540: 1163 | N540: 16.872 | O540: 232587 | P540: 6996.7 | Q540: 1741267 | S540: 8007 | U540: 84.7 | V540: 25 | W540: 90.5 | AB540: 282398 | AD540: 1 | AE540: 22.8 | AF540: 29.3 | AH540: =YEAR(B540) -> 2001 | AI540: =MIN(52,INT((B540-DATE(AH540,1,1))/7)+1) -> 22 | AJ540: =IF(AND(ISNUMBER(C540),ISNUMBER(AK540),ISNUMBER(AL540),AH540>=Inputs!$B$5,AH540<=Inputs!$B$6,AH540<>Inputs!$B$7,AH540<>Inputs!$B$8),1,0) -> 0 | AK540: =IF(INDEX($E540:$AF540,Inputs!$C$10)="","",INDEX($E540:$AF540,Inputs!$C$10)) -> 232587 | AL540: =IF(INDEX($E540:$AF540,Inputs!$C$11)="","",INDEX($E540:$AF540,Inputs!$C$11)) -> 405000 | AM540: =Regression!$C$5+Regression!$C$6*A540 -> 10214.478 | AN540: =IF(AJ540=1,C540/AM540,"") | AO540: =INDEX('Seasonal Index'!$E$2:$E$53,AI540) -> 1.0139792 | AP540: =IF(AJ540=1,C540/AO540,"") | AQ540: =IF(AJ540=1,A540-Regression!$C$15,0) -> 0 | AR540: =IF(AJ540=1,AK540-Regression!$D$15,0) -> 0 | AS540: =IF(AJ540=1,AL540-Regression!$E$15,0) -> 0 | AT540: =IF(AJ540=1,AP540-Regression!$F$15,0) -> 0 | AU540: =IF(AND(ISNUMBER(AK540),ISNUMBER(AL540)),Regression!$C$38+Regression!$D$38*A540+Regression!$E$38*AK540+Regression!$F$38*AL540,"") -> 10074.474 | AV540: =IF(ISNUMBER(AU540),AU540*AO540,"") -> 10215.307 | AW540: =IF(AJ540=1,"Train",IF(AH540=Inputs!$B$6+1,"Validation",IF(AH540>Inputs!$B$6+1,"Forecast","Not used"))) -> Not used | AX540: =IF(ISNUMBER(C540),C540,IF(ISNUMBER(D540),D540,"")) -> 8809 | AY540: =IF(AND(AW540="Validation",ISNUMBER(AX540),ISNUMBER(AV540)),ABS(AX540-AV540)/AX540,"") | AZ540: =IF(AJ540=1,AP540-AU540,0) -> 0 | BB540: =Regression!$C$45+Regression!$C$46*A540 -> 6984.8498 | BC540: =IF(AND(AH540>=2022,AH540<=2024),C540/BB540,"") | BD540: =INDEX('Seasonal Index'!$H$2:$H$53,AI540) -> 1.0395595 | BE540: =IF(AH540>=2022,BB540*BD540,"") | BF540: =IF(AND(AW540="Validation",ISNUMBER(AX540),ISNUMBER(BE540)),ABS(AX540-BE540)/AX540,"") | BG540: =IF(ISNUMBER(C540),C540,0) -> 8809 | BH540: =IF(ISNUMBER(AY540),AV540-AX540,0) -> 0 | BI540: =IF(ISNUMBER(AY540),BE540-AX540,0) -> 0
A541: 540 | B541: 37050 | C541: 8428 | F541: 406000 | H541: 27.976 | I541: 28.872 | J541: 1.679 | K541: 10470.231 | L541: 800293 | M541: 1206 | N541: 16.872 | O541: 232587 | P541: 7004.2 | Q541: 1741267 | S541: 8007 | U541: 84.7 | V541: 25 | W541: 89.4 | AB541: 282398 | AD541: 0 | AE541: 13.7 | AF541: 32.4 | AH541: =YEAR(B541) -> 2001 | AI541: =MIN(52,INT((B541-DATE(AH541,1,1))/7)+1) -> 23 | AJ541: =IF(AND(ISNUMBER(C541),ISNUMBER(AK541),ISNUMBER(AL541),AH541>=Inputs!$B$5,AH541<=Inputs!$B$6,AH541<>Inputs!$B$7,AH541<>Inputs!$B$8),1,0) -> 0 | AK541: =IF(INDEX($E541:$AF541,Inputs!$C$10)="","",INDEX($E541:$AF541,Inputs!$C$10)) -> 232587 | AL541: =IF(INDEX($E541:$AF541,Inputs!$C$11)="","",INDEX($E541:$AF541,Inputs!$C$11)) -> 406000 | AM541: =Regression!$C$5+Regression!$C$6*A541 -> 10213.306 | AN541: =IF(AJ541=1,C541/AM541,"") | AO541: =INDEX('Seasonal Index'!$E$2:$E$53,AI541) -> 1.0375597 | AP541: =IF(AJ541=1,C541/AO541,"") | AQ541: =IF(AJ541=1,A541-Regression!$C$15,0) -> 0 | AR541: =IF(AJ541=1,AK541-Regression!$D$15,0) -> 0 | AS541: =IF(AJ541=1,AL541-Regression!$E$15,0) -> 0 | AT541: =IF(AJ541=1,AP541-Regression!$F$15,0) -> 0 | AU541: =IF(AND(ISNUMBER(AK541),ISNUMBER(AL541)),Regression!$C$38+Regression!$D$38*A541+Regression!$E$38*AK541+Regression!$F$38*AL541,"") -> 10070.257 | AV541: =IF(ISNUMBER(AU541),AU541*AO541,"") -> 10448.493 | AW541: =IF(AJ541=1,"Train",IF(AH541=Inputs!$B$6+1,"Validation",IF(AH541>Inputs!$B$6+1,"Forecast","Not used"))) -> Not used | AX541: =IF(ISNUMBER(C541),C541,IF(ISNUMBER(D541),D541,"")) -> 8428 | AY541: =IF(AND(AW541="Validation",ISNUMBER(AX541),ISNUMBER(AV541)),ABS(AX541-AV541)/AX541,"") | AZ541: =IF(AJ541=1,AP541-AU541,0) -> 0 | BB541: =Regression!$C$45+Regression!$C$46*A541 -> 6986.4093 | BC541: =IF(AND(AH541>=2022,AH541<=2024),C541/BB541,"") | BD541: =INDEX('Seasonal Index'!$H$2:$H$53,AI541) -> 1.0378993 | BE541: =IF(AH541>=2022,BB541*BD541,"") | BF541: =IF(AND(AW541="Validation",ISNUMBER(AX541),ISNUMBER(BE541)),ABS(AX541-BE541)/AX541,"") | BG541: =IF(ISNUMBER(C541),C541,0) -> 8428 | BH541: =IF(ISNUMBER(AY541),AV541-AX541,0) -> 0 | BI541: =IF(ISNUMBER(AY541),BE541-AX541,0) -> 0
A542: 541 | B542: 37057 | C542: 8393 | F542: 411000 | H542: 28.904 | I542: 28.872 | J542: 1.647 | K542: 10470.231 | L542: 761213 | M542: 1206 | N542: 16.872 | O542: 232513 | P542: 7004.2 | Q542: 1784759 | S542: 8007 | U542: 84.7 | V542: 25 | W542: 89.4 | AB542: 282398 | AD542: 0 | AE542: 0 | AF542: 61.9 | AH542: =YEAR(B542) -> 2001 | AI542: =MIN(52,INT((B542-DATE(AH542,1,1))/7)+1) -> 24 | AJ542: =IF(AND(ISNUMBER(C542),ISNUMBER(AK542),ISNUMBER(AL542),AH542>=Inputs!$B$5,AH542<=Inputs!$B$6,AH542<>Inputs!$B$7,AH542<>Inputs!$B$8),1,0) -> 0 | AK542: =IF(INDEX($E542:$AF542,Inputs!$C$10)="","",INDEX($E542:$AF542,Inputs!$C$10)) -> 232513 | AL542: =IF(INDEX($E542:$AF542,Inputs!$C$11)="","",INDEX($E542:$AF542,Inputs!$C$11)) -> 411000 | AM542: =Regression!$C$5+Regression!$C$6*A542 -> 10212.133 | AN542: =IF(AJ542=1,C542/AM542,"") | AO542: =INDEX('Seasonal Index'!$E$2:$E$53,AI542) -> 1.0344513 | AP542: =IF(AJ542=1,C542/AO542,"") | AQ542: =IF(AJ542=1,A542-Regression!$C$15,0) -> 0 | AR542: =IF(AJ542=1,AK542-Regression!$D$15,0) -> 0 | AS542: =IF(AJ542=1,AL542-Regression!$E$15,0) -> 0 | AT542: =IF(AJ542=1,AP542-Regression!$F$15,0) -> 0 | AU542: =IF(AND(ISNUMBER(AK542),ISNUMBER(AL542)),Regression!$C$38+Regression!$D$38*A542+Regression!$E$38*AK542+Regression!$F$38*AL542,"") -> 10055.285 | AV542: =IF(ISNUMBER(AU542),AU542*AO542,"") -> 10401.702 | AW542: =IF(AJ542=1,"Train",IF(AH542=Inputs!$B$6+1,"Validation",IF(AH542>Inputs!$B$6+1,"Forecast","Not used"))) -> Not used | AX542: =IF(ISNUMBER(C542),C542,IF(ISNUMBER(D542),D542,"")) -> 8393 | AY542: =IF(AND(AW542="Validation",ISNUMBER(AX542),ISNUMBER(AV542)),ABS(AX542-AV542)/AX542,"") | AZ542: =IF(AJ542=1,AP542-AU542,0) -> 0 | BB542: =Regression!$C$45+Regression!$C$46*A542 -> 6987.9688 | BC542: =IF(AND(AH542>=2022,AH542<=2024),C542/BB542,"") | BD542: =INDEX('Seasonal Index'!$H$2:$H$53,AI542) -> 1.0351081 | BE542: =IF(AH542>=2022,BB542*BD542,"") | BF542: =IF(AND(AW542="Validation",ISNUMBER(AX542),ISNUMBER(BE542)),ABS(AX542-BE542)/AX542,"") | BG542: =IF(ISNUMBER(C542),C542,0) -> 8393 | BH542: =IF(ISNUMBER(AY542),AV542-AX542,0) -> 0 | BI542: =IF(ISNUMBER(AY542),BE542-AX542,0) -> 0
